Workbook
Name CalendarQ: [11]RTG!$B$36

Sheet SAM TO DO
B4: Clean up Tabcorp Model | G4: FY COMPS
G5: QUARTERLY COMPS
B6: Fill out VC margins
B7: Get bet365/entain data
B8: Look Through Sacha old Notes
B9: Look at industry reports
B10: Look at Rival Investor Days
B11: Compare all state retail licences
B12: Read demerger Docs
B13: Look at Total Wagering Revenue
B16: Look at state lottery revenue budgets
B20: Look Into
B21: Racing NSW Country | C21: http://racingnswcountry.com.au/wp-content/uploads/2016/09/RacingNSWCountry_Annual-Report_2020_final-PDF-2.pdf
B22: Racing Clubs | C22: https://cdn.australianturfclub.com.au/app/uploads/2019/10/2019_WEB_Download_ATC-Annual-Report_2018.pdf
B23: Racing vs World | C23: https://www.ifhaonline.org/resources/Annual_Report_2019.pdf
B24: RacinigCorp ATO | C24: https://connectonline.asic.gov.au/RegistrySearch/faces/landing/panelSearch.jspx?searchText=080959495&searchType=OrgAndBusNm&_adf.ctrl-state=javmibtd9_30
B25: Tabcorp vs Entain Racing Case | C25: https://www.austlii.edu.au/cgi-bin/viewdoc/au/cases/nsw/NSWSC/2023/220.html?context=1;query=entain;mask_path=#fn9
B26: Racing NSW race field fees Case | C26: https://www.troa.com.au/news/racing-nsw-wins-both-race-fields-legislation-cases
B27: Tax comparison | C27: https://www.treasury.nsw.gov.au/sites/default/files/2023-06/trp23-15_interstate-comparison-of-taxes_2022-23.pdf
B28: 1997 NSW Tote Act Notes | C28: https://www.austlii.edu.au/cgi-bin/viewdoc/au/legis/nsw/consol_act/ta1997167/notes.html
B29: NSW Wagering | C29: https://www.liquorandgaming.nsw.gov.au/operating-a-business/gaming-licences/gaming-licences-permits/sports-wagering-in-nsw
B30: POCT example | C30: https://www.treasury.tas.gov.au/liquor-and-gaming/fees/wagering-point-of-consumption-tax
B33: US Sports Betting Revenue
B34: https://sportsbetting.legal/revenue-tracking/
B37: https://h2gc.com/site/assets/News%20Stories/IBIA-Report-2024_FINAL-TEXT_SINGLE_AW.pdf
B44: https://treasury.nt.gov.au/publications/annual-reports
B45: https://industry.nt.gov.au/publications/corporate/annual-reports

Sheet COMPS

Sheet QTR
D3: =IF(MONTH(D11)>6,RIGHT(YEAR(D11),2)+1,RIGHT(YEAR(D11),2)) -> 17 | E3: =IF(MONTH(E11)>6,RIGHT(YEAR(E11),2)+1,RIGHT(YEAR(E11),2)) -> 18 | F3: =IF(MONTH(F11)>6,RIGHT(YEAR(F11),2)+1,RIGHT(YEAR(F11),2)) -> 18 | G3: =IF(MONTH(G11)>6,RIGHT(YEAR(G11),2)+1,RIGHT(YEAR(G11),2)) -> 18 | H3: =IF(MONTH(H11)>6,RIGHT(YEAR(H11),2)+1,RIGHT(YEAR(H11),2)) -> 18 | I3: =IF(MONTH(I11)>6,RIGHT(YEAR(I11),2)+1,RIGHT(YEAR(I11),2)) -> 19 | J3: =IF(MONTH(J11)>6,RIGHT(YEAR(J11),2)+1,RIGHT(YEAR(J11),2)) -> 19 | K3: =IF(MONTH(K11)>6,RIGHT(YEAR(K11),2)+1,RIGHT(YEAR(K11),2)) -> 19 | ... AN3: =IF(MONTH(AN11)>6,RIGHT(YEAR(AN11),2)+1,RIGHT(YEAR(AN11),2)) -> 26
D4: =RIGHT(YEAR(D$11),2) -> 17 | E4: =RIGHT(YEAR(E$11),2) -> 17 | F4: =RIGHT(YEAR(F$11),2) -> 17 | G4: =RIGHT(YEAR(G$11),2) -> 18 | H4: =RIGHT(YEAR(H$11),2) -> 18 | I4: =RIGHT(YEAR(I$11),2) -> 18 | J4: =RIGHT(YEAR(J$11),2) -> 18 | K4: =RIGHT(YEAR(K$11),2) -> 19 | ... AN4: =RIGHT(YEAR(AN$11),2) -> 26
D5: ="FY"&TEXT(D$3,"00") -> FY17 | E5: ="FY"&TEXT(E$3,"00") -> FY18 | F5: ="FY"&TEXT(F$3,"00") -> FY18 | G5: ="FY"&TEXT(G$3,"00") -> FY18 | H5: ="FY"&TEXT(H$3,"00") -> FY18 | I5: ="FY"&TEXT(I$3,"00") -> FY19 | J5: ="FY"&TEXT(J$3,"00") -> FY19 | K5: ="FY"&TEXT(K$3,"00") -> FY19 | ... AN5: ="FY"&TEXT(AN$3,"00") -> FY26
D6: ="CY"&TEXT(D$4,"00") -> CY17 | E6: ="CY"&TEXT(E$4,"00") -> CY17 | F6: ="CY"&TEXT(F$4,"00") -> CY17 | G6: ="CY"&TEXT(G$4,"00") -> CY18 | H6: ="CY"&TEXT(H$4,"00") -> CY18 | I6: ="CY"&TEXT(I$4,"00") -> CY18 | J6: ="CY"&TEXT(J$4,"00") -> CY18 | K6: ="CY"&TEXT(K$4,"00") -> CY19 | ... AN6: ="CY"&TEXT(AN$4,"00") -> CY26
D7: =D11-EOMONTH(D11,-3) -> 91 | E7: =E11-EOMONTH(E11,-3) -> 92 | F7: =F11-EOMONTH(F11,-3) -> 92 | G7: =G11-EOMONTH(G11,-3) -> 90 | H7: =H11-EOMONTH(H11,-3) -> 91 | I7: =I11-EOMONTH(I11,-3) -> 92 | J7: =J11-EOMONTH(J11,-3) -> 92 | K7: =K11-EOMONTH(K11,-3) -> 90 | ... AN7: =AN11-EOMONTH(AN11,-3) -> 91
E9: 1H18 | F9: 1H18 | G9: 2H18 | H9: 2H18 | I9: 1H19 | J9: 1H19 | K9: 2H19 | L9: 2H19 | M9: 1H20 | N9: 1H20 | O9: 2H20 | P9: 2H20 | Q9: 1H21 | R9: 1H21 | S9: 2H21 | T9: 2H21 | U9: 1H22 | V9: 1H22 | W9: 2H22 | X9: 2H22 | Y9: 1H23 | Z9: 1H23 | AA9: 2H23 | AB9: 2H23 | AC9: 1H24 | AD9: 1H24 | AE9: 2H24 | AF9: 2H24 | AG9: 1H25 | AH9: 1H25 | AI9: 2H25 | AJ9: 2H25 | AK9: 1H26 | AL9: 1H26 | AM9: 2H26 | AN9: 2H26 | AP9: YoY | AQ9: QoQ
D10: 4Q17 | E10: 1Q18 | F10: 2Q18 | G10: 3Q18 | H10: 4Q18 | I10: 1Q19 | J10: 2Q19 | K10: 3Q19 | L10: 4Q19 | M10: 1Q20 | N10: 2Q20 | O10: 3Q20 | P10: 4Q20 | Q10: 1Q21 | R10: 2Q21 | S10: 3Q21 | T10: 4Q21 | U10: 1Q22 | V10: 2Q22 | W10: 3Q22 | X10: 4Q22 | Y10: 1Q23 | Z10: 2Q23 | AA10: 3Q23 | AB10: 4Q23 | AC10: 1Q24 | AD10: 2Q24 | AE10: 3Q24 | AF10: 4Q24 | AG10: 1Q25 | AH10: 2Q25 | AI10: 3Q25 | AJ10: 4Q25 | AK10: 1Q26 | AL10: 2Q26 | AM10: 3Q26 | AN10: 4Q26 | AP10: 3Q24 | AQ10: 3Q24
D11: 42916 | E11: =EOMONTH( D11, 3) -> 43008 | F11: =EOMONTH( E11, 3) -> 43100 | G11: =EOMONTH( F11, 3) -> 43190 | H11: =EOMONTH( G11, 3) -> 43281 | I11: =EOMONTH( H11, 3) -> 43373 | J11: =EOMONTH( I11, 3) -> 43465 | K11: =EOMONTH( J11, 3) -> 43555 | L11: =EOMONTH( K11, 3) -> 43646 | ... AN11: =EOMONTH( AM11, 3) -> 46203
B14: Turnover
B15: SportsBet | C15: A$m | O15: ='SBET QTR'!O56 -> 3005.7916 | P15: ='SBET QTR'!P56 -> 4110.3288 | Q15: ='SBET QTR'!Q56 -> 5423.9746 | R15: ='SBET QTR'!R56 -> 5396.7741 | S15: ='SBET QTR'!S56 -> 4373.3237 | T15: ='SBET QTR'!T56 -> 4625.8092 | U15: ='SBET QTR'!U56 -> 6235.0564 | V15: ='SBET QTR'!V56 -> 6261.5594 | ... AH15: ='SBET QTR'!AH56 -> 4379.4949 | AP15: =$AE15/AA15-1 -> -0.15797019 | AQ15: =$AE15/AD15-1 -> -0.16534921
B16: PointsBet | C16: A$m | O16: =PBH!N12 -> 178.4 | P16: =PBH!O12 -> 302.9 | Q16: =PBH!P12 -> 527.7 | R16: =PBH!Q12 -> 543.3 | S16: =PBH!R12 -> 423.2 | T16: =PBH!S12 -> 494.8 | U16: =PBH!T12 -> 631.4 | V16: =PBH!U12 -> 727 | ... AH16: =PBH!AG12 -> 591.5 | AP16: =$AE16/AA16-1 -> 0.04432563 | AQ16: =$AE16/AD16-1 -> -0.32841615
B17: BlueBet | C17: A$m | Q17: ='BBET + BetR'!P12 -> 75.2 | R17: ='BBET + BetR'!Q12 -> 89.5 | S17: ='BBET + BetR'!R12 -> 83.5 | T17: ='BBET + BetR'!S12 -> 96.5 | U17: ='BBET + BetR'!T12 -> 125.9 | V17: ='BBET + BetR'!U12 -> 138.6 | W17: ='BBET + BetR'!V12 -> 120.7 | X17: ='BBET + BetR'!W12 -> 126.7 | ... AH17: ='BBET + BetR'!AG12 -> 0 | AP17: =$AE17/AA17-1 -> 0.17212427 | AQ17: =$AE17/AD17-1 -> -0.098191214
B18: BetR | C18: A$m | AA18: =BETR!Z12 -> 354.2 | AE18: =BETR!AD12 -> 273.1 | AF18: =BETR!AE12 -> 0 | AG18: =BETR!AF12 -> 0 | AH18: =BETR!AG12 -> 0 | AP18: =$AE18/AA18-1 -> -0.22896669
B19: Gross Win
B20: SportsBet | C20: A$m
B21: PointsBet | C21: A$m | O21: =PBH!N14 -> 21.2 | P21: =PBH!O14 -> 41.6 | Q21: =PBH!P14 -> 60.5 | R21: =PBH!Q14 -> 75.5 | S21: =PBH!R14 -> 54.8 | T21: =PBH!S14 -> 66.4 | U21: =PBH!T14 -> 87.9 | V21: =PBH!U14 -> 92.2 | ... AH21: =PBH!AG14 -> 80.5 | AP21: =$AE21/AA21-1 -> 0.093883357 | AQ21: =$AE21/AD21-1 -> -0.12712826
B22: BlueBet | C22: A$m | Q22: ='BBET + BetR'!P14 -> 9.6 | R22: ='BBET + BetR'!Q14 -> 11.5 | S22: ='BBET + BetR'!R14 -> 10.4 | T22: ='BBET + BetR'!S14 -> 12.7 | U22: ='BBET + BetR'!T14 -> 18.1 | V22: ='BBET + BetR'!U14 -> 18.4 | W22: ='BBET + BetR'!V14 -> 17 | X22: ='BBET + BetR'!W14 -> 17 | ... AH22: ='BBET + BetR'!AG14 -> 0 | AP22: =$AE22/AA22-1 -> 0.1835443 | AQ22: =$AE22/AD22-1 -> 0.78095238
B23: BetR | C23: A$m | AA23: =BETR!Z14 -> 37.6 | AE23: =BETR!AD14 -> 37.1 | AF23: =BETR!AE14 -> 0 | AG23: =BETR!AF14 -> 0 | AH23: =BETR!AG14 -> 0 | AP23: =$AE23/AA23-1 -> -0.013297872
B24: Net Win
B25: SportsBet | C25: A$m | O25: ='SBET QTR'!O59 -> 313.22488 | P25: ='SBET QTR'!P59 -> 517.09371 | Q25: ='SBET QTR'!Q59 -> 577.97932 | R25: ='SBET QTR'!R59 -> 578.16127 | S25: ='SBET QTR'!S59 -> 497.98966 | T25: ='SBET QTR'!T59 -> 557.18708 | U25: ='SBET QTR'!U59 -> 698.74904 | V25: ='SBET QTR'!V59 -> 623.82185 | ... AH25: ='SBET QTR'!AH59 -> 530.38335 | AP25: =$AE25/AA25-1 -> -0.024942934 | AQ25: =$AE25/AD25-1 -> -0.13164329
B26: PointsBet | C26: A$m | O26: =PBH!N19 -> 15.5 | P26: =PBH!O19 -> 32.4 | Q26: =PBH!P19 -> 35.1 | R26: =PBH!Q19 -> 49.8 | S26: =PBH!R19 -> 38.2 | T26: =PBH!S19 -> 43.1 | U26: =PBH!T19 -> 54.8 | V26: =PBH!U19 -> 53.1 | ... AH26: =PBH!AG19 -> 60.5 | AP26: =$AE26/AA26-1 -> 0.19921105 | AQ26: =$AE26/AD26-1 -> 0.021848739
B27: BlueBet | C27: A$m | Q27: ='BBET + BetR'!P17 -> 7.9 | R27: ='BBET + BetR'!Q17 -> 9.1 | S27: ='BBET + BetR'!R17 -> 8.5 | T27: ='BBET + BetR'!S17 -> 10.1 | U27: ='BBET + BetR'!T17 -> 14.8 | V27: ='BBET + BetR'!U17 -> 13.8 | W27: ='BBET + BetR'!V17 -> 13.2 | X27: ='BBET + BetR'!W17 -> 12.8 | ... AH27: ='BBET + BetR'!AG17 -> 0 | AP27: =$AE27/AA27-1 -> 0.325 | AQ27: =$AE27/AD27-1 -> -0.018518519
B28: BetR | C28: A$m | AA28: =BETR!Z17 -> 15 | AE28: =BETR!AD17 -> 23.3 | AF28: =BETR!AE17 -> 0 | AG28: =BETR!AF17 -> 0 | AH28: =BETR!AG17 -> 0 | AP28: =$AE28/AA28-1 -> 0.55333333
B29: Active Customers (LTM)
B30: SportsBet | C30: #
B31: PointsBet | C31: # | O31: =PBH!N22 -> 83330 | P31: =PBH!O22 -> 90422 | Q31: =PBH!P22 -> 124715 | R31: =PBH!Q22 -> 142992 | S31: =PBH!R22 -> 158041 | T31: =PBH!S22 -> 196585 | U31: =PBH!T22 -> 222662 | V31: =PBH!U22 -> 232875 | ... AH31: =PBH!AG22 -> 235100 | AP31: =$AE31/AA31-1 -> -0.071639208 | AQ31: =$AE31/AD31-1 -> 0.012423954
B32: BlueBet | C32: # | O32: ='BBET + BetR'!N20 -> 20217 | P32: ='BBET + BetR'!O20 -> 22289 | Q32: ='BBET + BetR'!P20 -> 23927 | R32: ='BBET + BetR'!Q20 -> 25540 | S32: ='BBET + BetR'!R20 -> 26824 | T32: ='BBET + BetR'!S20 -> 32472 | U32: ='BBET + BetR'!T20 -> 39195 | V32: ='BBET + BetR'!U20 -> 45087 | ... AH32: ='BBET + BetR'!AG20 -> 0 | AP32: =$AE32/AA32-1 -> 0.073101176 | AQ32: =$AE32/AD32-1 -> 0.0050600229
B33: BetR | C33: #
B34: Gross Win Margin
B35: SportsBet | C35: %
B36: PointsBet | C36: % | O36: =O21/O16 -> 0.11883408 | P36: =P21/P16 -> 0.13733906 | Q36: =Q21/Q16 -> 0.11464847 | R36: =R21/R16 -> 0.13896558 | S36: =S21/S16 -> 0.1294896 | T36: =T21/T16 -> 0.13419563 | U36: =U21/U16 -> 0.13921444 | V36: =V21/V16 -> 0.12682256 | ... AH36: =AH21/AH16 -> 0.13609467 | AP36: =($AE36-AA36)*100 -> 0.57537708 | AQ36: =($AE36-AD36)*100 -> 2.9287304
B37: BlueBet | C37: % | Q37: =Q22/Q17 -> 0.12765957 | R37: =R22/R17 -> 0.12849162 | S37: =S22/S17 -> 0.1245509 | T37: =T22/T17 -> 0.13160622 | U37: =U22/U17 -> 0.14376489 | V37: =V22/V17 -> 0.13275613 | W37: =W22/W17 -> 0.14084507 | X37: =X22/X17 -> 0.13417522 | ... AH37: =AH22/AH17 -> #DIV/0! | AP37: =($AE37-AA37)*100 -> 0.12925258 | AQ37: =($AE37-AD37)*100 -> 6.6124697
B38: BetR | C38: % | AA38: =AA23/AA18 -> 0.10615471 | AE38: =AE23/AE18 -> 0.13584767 | AF38: =AF23/AF18 -> #DIV/0! | AG38: =AG23/AG18 -> #DIV/0! | AH38: =AH23/AH18 -> #DIV/0! | AP38: =($AE38-AA38)*100 -> 2.969296
B39: Net Win Margin
B40: SportsBet | C40: % | O40: =O25/O15 -> 0.10420712 | P40: =P25/P15 -> 0.12580349 | Q40: =Q25/Q15 -> 0.10656011 | R40: =R25/R15 -> 0.1071309 | S40: =S25/S15 -> 0.11386984 | T40: =T25/T15 -> 0.12045181 | U40: =U25/U15 -> 0.1120678 | V40: =V25/V15 -> 0.099627235 | ... AH40: =AH25/AH15 -> 0.12110606 | AP40: =($AE40-AA40)*100 -> 1.7619132 | AQ40: =($AE40-AD40)*100 -> 0.50128189
B41: PointsBet | C41: % | O41: =O26/O16 -> 0.086883408 | P41: =P26/P16 -> 0.106966 | Q41: =Q26/Q16 -> 0.066515065 | R41: =R26/R16 -> 0.091662065 | S41: =S26/S16 -> 0.09026465 | T41: =T26/T16 -> 0.087105901 | U41: =U26/U16 -> 0.086791258 | V41: =V26/V16 -> 0.07303989 | ... AH41: =AH26/AH16 -> 0.10228233 | AP41: =($AE41-AA41)*100 -> 1.2968936 | AQ41: =($AE41-AD41)*100 -> 3.4419093
B42: BlueBet | C42: % | Q42: =Q27/Q17 -> 0.10505319 | R42: =R27/R17 -> 0.10167598 | S42: =S27/S17 -> 0.10179641 | T42: =T27/T17 -> 0.10466321 | U42: =U27/U17 -> 0.11755361 | V42: =V27/V17 -> 0.0995671 | W42: =W27/W17 -> 0.10936205 | X42: =X27/X17 -> 0.10102605 | ... AH42: =AH27/AH17 -> #DIV/0! | AP42: =($AE42-AA42)*100 -> 1.3141181 | AQ42: =($AE42-AD42)*100 -> 0.92456853
B43: BetR | C43: % | AA43: =AA28/AA18 -> 0.042348955 | AE43: =AE28/AE18 -> 0.085316734 | AF43: =AF28/AF18 -> #DIV/0! | AG43: =AG28/AG18 -> #DIV/0! | AH43: =AH28/AH18 -> #DIV/0! | AP43: =($AE43-AA43)*100 -> 4.2967778
B44: Marketing as a % of Net Win
B45: SportsBet | S45: ='SBET QTR'!S41 -> 0.10731699 | T45: ='SBET QTR'!T41 -> 0.15982187 | U45: ='SBET QTR'!U41 -> 0.1274918 | V45: ='SBET QTR'!V41 -> 0.1243399 | W45: ='SBET QTR'!W41 -> 0.11873294 | X45: ='SBET QTR'!X41 -> 0.13270822 | Y45: ='SBET QTR'!Y41 -> 0.16729703 | Z45: ='SBET QTR'!Z41 -> 0.17042412 | ... AH45: ='SBET QTR'!AH41 -> 0.1734104
O48: =O15/$O15 -> 1 | P48: =P15/$O15 -> 1.3674697 | Q48: =Q15/$O15 -> 1.8045079 | R48: =R15/$O15 -> 1.7954585 | S48: =S15/$O15 -> 1.4549657 | T48: =T15/$O15 -> 1.5389654 | U48: =U15/$O15 -> 2.0743476 | V48: =V15/$O15 -> 2.0831648 | ... AH48: =AH15/$O15 -> 1.4570188
O49: =O25/$O25 -> 1 | P49: =P25/$O25 -> 1.6508705 | Q49: =Q25/$O25 -> 1.8452535 | R49: =R25/$O25 -> 1.8458344 | S49: =S25/$O25 -> 1.589879 | T49: =T25/$O25 -> 1.7788723 | U49: =U25/$O25 -> 2.2308222 | V49: =V25/$O25 -> 1.9916101 | ... AH49: =AH25/$O25 -> 1.6932989
O51: =O16/$O16 -> 1 | P51: =P16/$O16 -> 1.69787 | Q51: =Q16/$O16 -> 2.9579596 | R51: =R16/$O16 -> 3.0454036 | S51: =S16/$O16 -> 2.3721973 | T51: =T16/$O16 -> 2.7735426 | U51: =U16/$O16 -> 3.5392377 | V51: =V16/$O16 -> 4.0751121 | ... AH51: =AH16/$O16 -> 3.315583
O52: =O26/$O26 -> 1 | P52: =P26/$O26 -> 2.0903226 | Q52: =Q26/$O26 -> 2.2645161 | R52: =R26/$O26 -> 3.2129032 | S52: =S26/$O26 -> 2.4645161 | T52: =T26/$O26 -> 2.7806452 | U52: =U26/$O26 -> 3.5354839 | V52: =V26/$O26 -> 3.4258065 | ... AH52: =AH26/$O26 -> 3.9032258
O57: 43921 | P57: =EOMONTH(O57,12) -> 44286 | Q57: =EOMONTH(P57,12) -> 44651 | R57: =EOMONTH(Q57,12) -> 45016 | S57: =EOMONTH(R57,12) -> 45382
C58: SportsBet | D58: PointsBet | E58: BlueBet | F58: BetR | O58: =EOMONTH(O57,3) -> 44012 | P58: =EOMONTH(O58,12) -> 44377 | Q58: =EOMONTH(P58,12) -> 44742 | R58: =EOMONTH(Q58,12) -> 45107 | S58: =EOMONTH(R58,12) -> 45473
B59: Turnover | C59: -0.15480858 | D59: 0.04432563 | E59: 0.17212427 | F59: -0.22896669 | O59: =EOMONTH(O58,3) -> 44104 | P59: =EOMONTH(O59,12) -> 44469 | Q59: =EOMONTH(P59,12) -> 44834 | R59: =EOMONTH(Q59,12) -> 45199 | S59: =EOMONTH(R59,12) -> 45565
B60: Gross Win | D60: 0.093883357 | E60: 0.1835443 | F60: -0.013297872 | O60: =EOMONTH(O59,3) -> 44196 | P60: =EOMONTH(O60,12) -> 44561 | Q60: =EOMONTH(P60,12) -> 44926 | R60: =EOMONTH(Q60,12) -> 45291 | S60: =EOMONTH(R60,12) -> 45657
B61: Net Win | C61: -0.026520596 | D61: 0.19921105 | E61: 0.325 | F61: 0.55333333
B62: Active Customers (LTM) | D62: -0.071639208 | E62: 0.073101176 | O62: 2020 | P62: 2021 | Q62: 2022 | R62: 2023 | S62: 2024
N63: Q1 | O63: =_xlfn.XLOOKUP(O57,$O$11:$AN$11,$O$15:$AN$15) -> 3005.7916 | P63: =_xlfn.XLOOKUP(P57,$O$11:$AN$11,$O$15:$AN$15) -> 4373.3237 | Q63: =_xlfn.XLOOKUP(Q57,$O$11:$AN$11,$O$15:$AN$15) -> 4675.1818 | R63: =_xlfn.XLOOKUP(R57,$O$11:$AN$11,$O$15:$AN$15) -> 4597.6408 | S63: =_xlfn.XLOOKUP(S57,$O$11:$AN$11,$O$15:$AN$15) -> 3871.3506
C64: SportsBet | D64: PointsBet | N64: Q2 | O64: =_xlfn.XLOOKUP(O58,$O$11:$AN$11,$O$15:$AN$15) -> 4110.3288 | P64: =_xlfn.XLOOKUP(P58,$O$11:$AN$11,$O$15:$AN$15) -> 4625.8092 | Q64: =_xlfn.XLOOKUP(Q58,$O$11:$AN$11,$O$15:$AN$15) -> 4727.8058 | R64: =_xlfn.XLOOKUP(R58,$O$11:$AN$11,$O$15:$AN$15) -> 4430.1206 | S64: =_xlfn.XLOOKUP(S58,$O$11:$AN$11,$O$15:$AN$15) -> 4136.1216
B65: Turnover | C65: -0.083231977 | D65: -0.016581408 | N65: Q3 | O65: =_xlfn.XLOOKUP(O59,$O$11:$AN$11,$O$15:$AN$15) -> 5423.9746 | P65: =_xlfn.XLOOKUP(P59,$O$11:$AN$11,$O$15:$AN$15) -> 6235.0564 | Q65: =_xlfn.XLOOKUP(Q59,$O$11:$AN$11,$O$15:$AN$15) -> 4942.4107 | R65: =_xlfn.XLOOKUP(R59,$O$11:$AN$11,$O$15:$AN$15) -> 4472.3478 | S65: =_xlfn.XLOOKUP(S59,$O$11:$AN$11,$O$15:$AN$15) -> 4007.0947
B66: Net Win | C66: 0.11801715 | D66: 0.071969697 | N66: Q4 | O66: =_xlfn.XLOOKUP(O60,$O$11:$AN$11,$O$15:$AN$15) -> 5396.7741 | P66: =_xlfn.XLOOKUP(P60,$O$11:$AN$11,$O$15:$AN$15) -> 6261.5594 | Q66: =_xlfn.XLOOKUP(Q60,$O$11:$AN$11,$O$15:$AN$15) -> 5729.4138 | R66: =_xlfn.XLOOKUP(R60,$O$11:$AN$11,$O$15:$AN$15) -> 4638.2878
B67: EBITDA | C67: 0.14281058
B68: Active Customers | C68: 0.064951041 | D68: 0.013980511 | O68: 2020 | P68: 2021 | Q68: 2022 | R68: 2023 | S68: 2024
N69: Q1 | O69: =_xlfn.XLOOKUP(O57,$O$11:$AN$11,$O$25:$AN$25) -> 313.22488 | P69: =_xlfn.XLOOKUP(P57,$O$11:$AN$11,$O$25:$AN$25) -> 497.98966 | Q69: =_xlfn.XLOOKUP(Q57,$O$11:$AN$11,$O$25:$AN$25) -> 538.41917 | R69: =_xlfn.XLOOKUP(R57,$O$11:$AN$11,$O$25:$AN$25) -> 512.75083 | S69: =_xlfn.XLOOKUP(S57,$O$11:$AN$11,$O$25:$AN$25) -> 499.96132
N70: Q2 | O70: =_xlfn.XLOOKUP(O58,$O$11:$AN$11,$O$25:$AN$25) -> 517.09371 | P70: =_xlfn.XLOOKUP(P58,$O$11:$AN$11,$O$25:$AN$25) -> 557.18708 | Q70: =_xlfn.XLOOKUP(Q58,$O$11:$AN$11,$O$25:$AN$25) -> 566.19782 | R70: =_xlfn.XLOOKUP(R58,$O$11:$AN$11,$O$25:$AN$25) -> 583.02977 | S70: =_xlfn.XLOOKUP(S58,$O$11:$AN$11,$O$25:$AN$25) -> 529.5328
N71: Q3 | O71: =_xlfn.XLOOKUP(O59,$O$11:$AN$11,$O$25:$AN$25) -> 577.97932 | P71: =_xlfn.XLOOKUP(P59,$O$11:$AN$11,$O$25:$AN$25) -> 698.74904 | Q71: =_xlfn.XLOOKUP(Q59,$O$11:$AN$11,$O$25:$AN$25) -> 547.26343 | R71: =_xlfn.XLOOKUP(R59,$O$11:$AN$11,$O$25:$AN$25) -> 506.91829 | S71: =_xlfn.XLOOKUP(S59,$O$11:$AN$11,$O$25:$AN$25) -> 553.88679
N72: Q4 | O72: =_xlfn.XLOOKUP(O60,$O$11:$AN$11,$O$25:$AN$25) -> 578.16127 | P72: =_xlfn.XLOOKUP(P60,$O$11:$AN$11,$O$25:$AN$25) -> 623.82185 | Q72: =_xlfn.XLOOKUP(Q60,$O$11:$AN$11,$O$25:$AN$25) -> 592.0424 | R72: =_xlfn.XLOOKUP(R60,$O$11:$AN$11,$O$25:$AN$25) -> 575.75569
O74: 2020 | P74: 2021 | Q74: 2022 | R74: 2023 | S74: 2024
N75: Q1 | O75: =_xlfn.XLOOKUP(O57,$O$11:$AN$11,$O$40:$AN$40) -> 0.10420712 | P75: =_xlfn.XLOOKUP(P57,$O$11:$AN$11,$O$40:$AN$40) -> 0.11386984 | Q75: =_xlfn.XLOOKUP(Q57,$O$11:$AN$11,$O$40:$AN$40) -> 0.1151654 | R75: =_xlfn.XLOOKUP(R57,$O$11:$AN$11,$O$40:$AN$40) -> 0.11152477 | S75: =_xlfn.XLOOKUP(S57,$O$11:$AN$11,$O$40:$AN$40) -> 0.1291439
N76: Q2 | O76: =_xlfn.XLOOKUP(O58,$O$11:$AN$11,$O$40:$AN$40) -> 0.12580349 | P76: =_xlfn.XLOOKUP(P58,$O$11:$AN$11,$O$40:$AN$40) -> 0.12045181 | Q76: =_xlfn.XLOOKUP(Q58,$O$11:$AN$11,$O$40:$AN$40) -> 0.11975911 | R76: =_xlfn.XLOOKUP(R58,$O$11:$AN$11,$O$40:$AN$40) -> 0.13160585 | S76: =_xlfn.XLOOKUP(S58,$O$11:$AN$11,$O$40:$AN$40) -> 0.12802641
N77: Q3 | O77: =_xlfn.XLOOKUP(O59,$O$11:$AN$11,$O$40:$AN$40) -> 0.10656011 | P77: =_xlfn.XLOOKUP(P59,$O$11:$AN$11,$O$40:$AN$40) -> 0.1120678 | Q77: =_xlfn.XLOOKUP(Q59,$O$11:$AN$11,$O$40:$AN$40) -> 0.11072804 | R77: =_xlfn.XLOOKUP(R59,$O$11:$AN$11,$O$40:$AN$40) -> 0.11334501 | S77: =_xlfn.XLOOKUP(S59,$O$11:$AN$11,$O$40:$AN$40) -> 0.13822653
N78: Q4 | O78: =_xlfn.XLOOKUP(O60,$O$11:$AN$11,$O$40:$AN$40) -> 0.1071309 | P78: =_xlfn.XLOOKUP(P60,$O$11:$AN$11,$O$40:$AN$40) -> 0.099627235 | Q78: =_xlfn.XLOOKUP(Q60,$O$11:$AN$11,$O$40:$AN$40) -> 0.10333385 | R78: =_xlfn.XLOOKUP(R60,$O$11:$AN$11,$O$40:$AN$40) -> 0.12413108
O80: 2020 | P80: 2021 | Q80: 2022 | R80: 2023 | S80: 2024
N81: Q1 | P81: =_xlfn.XLOOKUP(P57,$O$11:$AN$11,$O$45:$AN$45) -> 0.10731699 | Q81: =_xlfn.XLOOKUP(Q57,$O$11:$AN$11,$O$45:$AN$45) -> 0.11873294 | R81: =_xlfn.XLOOKUP(R57,$O$11:$AN$11,$O$45:$AN$45) -> 0.14977179 | S81: =_xlfn.XLOOKUP(S57,$O$11:$AN$11,$O$45:$AN$45) -> 0.14264808
N82: Q2 | P82: =_xlfn.XLOOKUP(P58,$O$11:$AN$11,$O$45:$AN$45) -> 0.15982187 | Q82: =_xlfn.XLOOKUP(Q58,$O$11:$AN$11,$O$45:$AN$45) -> 0.13270822 | R82: =_xlfn.XLOOKUP(R58,$O$11:$AN$11,$O$45:$AN$45) -> 0.14536131 | S82: =_xlfn.XLOOKUP(S58,$O$11:$AN$11,$O$45:$AN$45) -> 0.16045845
N83: Q3 | P83: =_xlfn.XLOOKUP(P59,$O$11:$AN$11,$O$45:$AN$45) -> 0.1274918 | Q83: =_xlfn.XLOOKUP(Q59,$O$11:$AN$11,$O$45:$AN$45) -> 0.16729703 | R83: =_xlfn.XLOOKUP(R59,$O$11:$AN$11,$O$45:$AN$45) -> 0.17578651 | S83: =_xlfn.XLOOKUP(S59,$O$11:$AN$11,$O$45:$AN$45) -> 0.16172507
N84: Q4 | P84: =_xlfn.XLOOKUP(P60,$O$11:$AN$11,$O$45:$AN$45) -> 0.1243399 | Q84: =_xlfn.XLOOKUP(Q60,$O$11:$AN$11,$O$45:$AN$45) -> 0.17042412 | R84: =_xlfn.XLOOKUP(R60,$O$11:$AN$11,$O$45:$AN$45) -> 0.15466667
O92: 2020 | P92: 2021 | Q92: 2022 | R92: 2023 | S92: 2024
N93: Q1 | O93: =_xlfn.XLOOKUP(O57,$O$11:$AN$11,$O$16:$AN$16) -> 178.4 | P93: =_xlfn.XLOOKUP(P57,$O$11:$AN$11,$O$16:$AN$16) -> 423.2 | Q93: =_xlfn.XLOOKUP(Q57,$O$11:$AN$11,$O$16:$AN$16) -> 579.4 | R93: =_xlfn.XLOOKUP(R57,$O$11:$AN$11,$O$16:$AN$16) -> 579.8 | S93: =_xlfn.XLOOKUP(S57,$O$11:$AN$11,$O$16:$AN$16) -> 605.5
N94: Q2 | O94: =_xlfn.XLOOKUP(O58,$O$11:$AN$11,$O$16:$AN$16) -> 302.9 | P94: =_xlfn.XLOOKUP(P58,$O$11:$AN$11,$O$16:$AN$16) -> 494.8 | Q94: =_xlfn.XLOOKUP(Q58,$O$11:$AN$11,$O$16:$AN$16) -> 598.6 | R94: =_xlfn.XLOOKUP(R58,$O$11:$AN$11,$O$16:$AN$16) -> 502.3 | S94: =_xlfn.XLOOKUP(S58,$O$11:$AN$11,$O$16:$AN$16) -> 602.7
N95: Q3 | O95: =_xlfn.XLOOKUP(O59,$O$11:$AN$11,$O$16:$AN$16) -> 527.7 | P95: =_xlfn.XLOOKUP(P59,$O$11:$AN$11,$O$16:$AN$16) -> 631.4 | Q95: =_xlfn.XLOOKUP(Q59,$O$11:$AN$11,$O$16:$AN$16) -> 611.9 | R95: =_xlfn.XLOOKUP(R59,$O$11:$AN$11,$O$16:$AN$16) -> 566.9 | S95: =_xlfn.XLOOKUP(S59,$O$11:$AN$11,$O$16:$AN$16) -> 557.5
N96: Q4 | O96: =_xlfn.XLOOKUP(O60,$O$11:$AN$11,$O$16:$AN$16) -> 543.3 | P96: =_xlfn.XLOOKUP(P60,$O$11:$AN$11,$O$16:$AN$16) -> 727 | Q96: =_xlfn.XLOOKUP(Q60,$O$11:$AN$11,$O$16:$AN$16) -> 938.5 | R96: =_xlfn.XLOOKUP(R60,$O$11:$AN$11,$O$16:$AN$16) -> 901.6
O98: 2020 | P98: 2021 | Q98: 2022 | R98: 2023 | S98: 2024
N99: Q1 | O99: =_xlfn.XLOOKUP(O57,$O$11:$AN$11,$O$26:$AN$26) -> 15.5 | P99: =_xlfn.XLOOKUP(P57,$O$11:$AN$11,$O$26:$AN$26) -> 38.2 | Q99: =_xlfn.XLOOKUP(Q57,$O$11:$AN$11,$O$26:$AN$26) -> 52.3 | R99: =_xlfn.XLOOKUP(R57,$O$11:$AN$11,$O$26:$AN$26) -> 50.7 | S99: =_xlfn.XLOOKUP(S57,$O$11:$AN$11,$O$26:$AN$26) -> 60.8
N100: Q2 | O100: =_xlfn.XLOOKUP(O58,$O$11:$AN$11,$O$26:$AN$26) -> 32.4 | P100: =_xlfn.XLOOKUP(P58,$O$11:$AN$11,$O$26:$AN$26) -> 43.1 | Q100: =_xlfn.XLOOKUP(Q58,$O$11:$AN$11,$O$26:$AN$26) -> 55.2 | R100: =_xlfn.XLOOKUP(R58,$O$11:$AN$11,$O$26:$AN$26) -> 55.6 | S100: =_xlfn.XLOOKUP(S58,$O$11:$AN$11,$O$26:$AN$26) -> 60.1
N101: Q3 | O101: =_xlfn.XLOOKUP(O59,$O$11:$AN$11,$O$26:$AN$26) -> 35.1 | P101: =_xlfn.XLOOKUP(P59,$O$11:$AN$11,$O$26:$AN$26) -> 54.8 | Q101: =_xlfn.XLOOKUP(Q59,$O$11:$AN$11,$O$26:$AN$26) -> 47.5 | R101: =_xlfn.XLOOKUP(R59,$O$11:$AN$11,$O$26:$AN$26) -> 52.8 | S101: =_xlfn.XLOOKUP(S59,$O$11:$AN$11,$O$26:$AN$26) -> 56.6
N102: Q4 | O102: =_xlfn.XLOOKUP(O60,$O$11:$AN$11,$O$26:$AN$26) -> 49.8 | P102: =_xlfn.XLOOKUP(P60,$O$11:$AN$11,$O$26:$AN$26) -> 53.1 | Q102: =_xlfn.XLOOKUP(Q60,$O$11:$AN$11,$O$26:$AN$26) -> 57.7 | R102: =_xlfn.XLOOKUP(R60,$O$11:$AN$11,$O$26:$AN$26) -> 59.5
O104: 2020 | P104: 2021 | Q104: 2022 | R104: 2023 | S104: 2024
N105: Q1 | O105: =_xlfn.XLOOKUP(O57,$O$11:$AN$11,$O$41:$AN$41) -> 0.086883408 | P105: =_xlfn.XLOOKUP(P57,$O$11:$AN$11,$O$41:$AN$41) -> 0.09026465 | Q105: =_xlfn.XLOOKUP(Q57,$O$11:$AN$11,$O$41:$AN$41) -> 0.090265792 | R105: =_xlfn.XLOOKUP(R57,$O$11:$AN$11,$O$41:$AN$41) -> 0.087443946 | S105: =_xlfn.XLOOKUP(S57,$O$11:$AN$11,$O$41:$AN$41) -> 0.10041288
N106: Q2 | O106: =_xlfn.XLOOKUP(O58,$O$11:$AN$11,$O$41:$AN$41) -> 0.106966 | P106: =_xlfn.XLOOKUP(P58,$O$11:$AN$11,$O$41:$AN$41) -> 0.087105901 | Q106: =_xlfn.XLOOKUP(Q58,$O$11:$AN$11,$O$41:$AN$41) -> 0.092215169 | R106: =_xlfn.XLOOKUP(R58,$O$11:$AN$11,$O$41:$AN$41) -> 0.11069082 | S106: =_xlfn.XLOOKUP(S58,$O$11:$AN$11,$O$41:$AN$41) -> 0.099717936
N107: Q3 | O107: =_xlfn.XLOOKUP(O59,$O$11:$AN$11,$O$41:$AN$41) -> 0.066515065 | P107: =_xlfn.XLOOKUP(P59,$O$11:$AN$11,$O$41:$AN$41) -> 0.086791258 | Q107: =_xlfn.XLOOKUP(Q59,$O$11:$AN$11,$O$41:$AN$41) -> 0.077627063 | R107: =_xlfn.XLOOKUP(R59,$O$11:$AN$11,$O$41:$AN$41) -> 0.09313812 | S107: =_xlfn.XLOOKUP(S59,$O$11:$AN$11,$O$41:$AN$41) -> 0.10152466
N108: Q4 | O108: =_xlfn.XLOOKUP(O60,$O$11:$AN$11,$O$41:$AN$41) -> 0.091662065 | P108: =_xlfn.XLOOKUP(P60,$O$11:$AN$11,$O$41:$AN$41) -> 0.07303989 | Q108: =_xlfn.XLOOKUP(Q60,$O$11:$AN$11,$O$41:$AN$41) -> 0.061481087 | R108: =_xlfn.XLOOKUP(R60,$O$11:$AN$11,$O$41:$AN$41) -> 0.065993789

Sheet HY
A2: X | D2: =D7&D9 -> 1H18A | E2: =E7&E9 -> 2H18A | F2: =F7&F9 -> 1H19A | G2: =G7&G9 -> 2H19A | H2: =H7&H9 -> 1H20A | I2: =I7&I9 -> 2H20A | J2: =J7&J9 -> 1H21A | K2: =K7&K9 -> 2H21A | ... AK2: =AK7&AK9 -> 2H34E
B3: Period End | D3: 43100 | E3: =EOMONTH(D3,6) -> 43281 | F3: =EOMONTH(E3,6) -> 43465 | G3: =EOMONTH(F3,6) -> 43646 | H3: =EOMONTH(G3,6) -> 43830 | I3: =EOMONTH(H3,6) -> 44012 | J3: =EOMONTH(I3,6) -> 44196 | K3: =EOMONTH(J3,6) -> 44377 | L3: =EOMONTH(K3,6) -> 44561 | ... AK3: =EOMONTH(AJ3,6) -> 49125
B5: Half | D5: {=_xlfn.IFS(AND(MONTH(D$3)>=7,MONTH(D$3)<=12),"1H",AND(MONTH(D$3)>=1,MONTH(D$3)<=6),"2H")} -> 1H | E5: {=_xlfn.IFS(AND(MONTH(E$3)>=7,MONTH(E$3)<=12),"1H",AND(MONTH(E$3)>=1,MONTH(E$3)<=6),"2H")} -> 2H | F5: {=_xlfn.IFS(AND(MONTH(F$3)>=7,MONTH(F$3)<=12),"1H",AND(MONTH(F$3)>=1,MONTH(F$3)<=6),"2H")} -> 1H | G5: {=_xlfn.IFS(AND(MONTH(G$3)>=7,MONTH(G$3)<=12),"1H",AND(MONTH(G$3)>=1,MONTH(G$3)<=6),"2H")} -> 2H | H5: {=_xlfn.IFS(AND(MONTH(H$3)>=7,MONTH(H$3)<=12),"1H",AND(MONTH(H$3)>=1,MONTH(H$3)<=6),"2H")} -> 1H | I5: {=_xlfn.IFS(AND(MONTH(I$3)>=7,MONTH(I$3)<=12),"1H",AND(MONTH(I$3)>=1,MONTH(I$3)<=6),"2H")} -> 2H | J5: {=_xlfn.IFS(AND(MONTH(J$3)>=7,MONTH(J$3)<=12),"1H",AND(MONTH(J$3)>=1,MONTH(J$3)<=6),"2H")} -> 1H | K5: {=_xlfn.IFS(AND(MONTH(K$3)>=7,MONTH(K$3)<=12),"1H",AND(MONTH(K$3)>=1,MONTH(K$3)<=6),"2H")} -> 2H | ... AK5: {=_xlfn.IFS(AND(MONTH(AK$3)>=7,MONTH(AK$3)<=12),"1H",AND(MONTH(AK$3)>=1,MONTH(AK$3)<=6),"2H")} -> 2H
B6: FY | D6: =IF(MONTH(D3)>6,RIGHT(YEAR(D3),2)+1,RIGHT(YEAR(D3),2)) -> 18 | E6: =IF(MONTH(E3)>6,RIGHT(YEAR(E3),2)+1,RIGHT(YEAR(E3),2)) -> 18 | F6: =IF(MONTH(F3)>6,RIGHT(YEAR(F3),2)+1,RIGHT(YEAR(F3),2)) -> 19 | G6: =IF(MONTH(G3)>6,RIGHT(YEAR(G3),2)+1,RIGHT(YEAR(G3),2)) -> 19 | H6: =IF(MONTH(H3)>6,RIGHT(YEAR(H3),2)+1,RIGHT(YEAR(H3),2)) -> 20 | I6: =IF(MONTH(I3)>6,RIGHT(YEAR(I3),2)+1,RIGHT(YEAR(I3),2)) -> 20 | J6: =IF(MONTH(J3)>6,RIGHT(YEAR(J3),2)+1,RIGHT(YEAR(J3),2)) -> 21 | K6: =IF(MONTH(K3)>6,RIGHT(YEAR(K3),2)+1,RIGHT(YEAR(K3),2)) -> 21 | ... AK6: =IF(MONTH(AK3)>6,RIGHT(YEAR(AK3),2)+1,RIGHT(YEAR(AK3),2)) -> 34
B7: FY Year | D7: =D$5&TEXT(D$6,"00") -> 1H18 | E7: =E$5&TEXT(E$6,"00") -> 2H18 | F7: =F$5&TEXT(F$6,"00") -> 1H19 | G7: =G$5&TEXT(G$6,"00") -> 2H19 | H7: =H$5&TEXT(H$6,"00") -> 1H20 | I7: =I$5&TEXT(I$6,"00") -> 2H20 | J7: =J$5&TEXT(J$6,"00") -> 1H21 | K7: =K$5&TEXT(K$6,"00") -> 2H21 | ... AK7: =AK$5&TEXT(AK$6,"00") -> 2H34
B8: Financial Year | D8: {=_xlfn.IFS(MONTH(D$3)=12,YEAR(D$3)+1,MONTH(D$3)=6,YEAR(D$3))} -> 2018 | E8: {=_xlfn.IFS(MONTH(E$3)=12,YEAR(E$3)+1,MONTH(E$3)=6,YEAR(E$3))} -> 2018 | F8: {=_xlfn.IFS(MONTH(F$3)=12,YEAR(F$3)+1,MONTH(F$3)=6,YEAR(F$3))} -> 2019 | G8: {=_xlfn.IFS(MONTH(G$3)=12,YEAR(G$3)+1,MONTH(G$3)=6,YEAR(G$3))} -> 2019 | H8: {=_xlfn.IFS(MONTH(H$3)=12,YEAR(H$3)+1,MONTH(H$3)=6,YEAR(H$3))} -> 2020 | I8: {=_xlfn.IFS(MONTH(I$3)=12,YEAR(I$3)+1,MONTH(I$3)=6,YEAR(I$3))} -> 2020 | J8: {=_xlfn.IFS(MONTH(J$3)=12,YEAR(J$3)+1,MONTH(J$3)=6,YEAR(J$3))} -> 2021 | K8: {=_xlfn.IFS(MONTH(K$3)=12,YEAR(K$3)+1,MONTH(K$3)=6,YEAR(K$3))} -> 2021 | ... AK8: {=_xlfn.IFS(MONTH(AK$3)=12,YEAR(AK$3)+1,MONTH(AK$3)=6,YEAR(AK$3))} -> 2034
B9: Actual/Estimate | D9: =IF(ISNUMBER(D$14),"A","E") -> A | E9: =IF(ISNUMBER(E$14),"A","E") -> A | F9: =IF(ISNUMBER(F$14),"A","E") -> A | G9: =IF(ISNUMBER(G$14),"A","E") -> A | H9: =IF(ISNUMBER(H$14),"A","E") -> A | I9: =IF(ISNUMBER(I$14),"A","E") -> A | J9: =IF(ISNUMBER(J$14),"A","E") -> A | K9: =IF(ISNUMBER(K$14),"A","E") -> A | ... AK9: =IF(ISNUMBER(AK$14),"A","E") -> E
B10: Days in period | D10: =D3-EOMONTH(D3,-6) -> 184 | E10: =E3-D3 -> 181 | F10: =F3-E3 -> 184 | G10: =G3-F3 -> 181 | H10: =H3-G3 -> 184 | I10: =I3-H3 -> 182 | J10: =J3-I3 -> 184 | K10: =K3-J3 -> 181 | L10: =L3-K3 -> 184 | ... AK10: =AK3-AJ3 -> 181
B12: SEGMENTS
B13: Turnover
B14: Tabcorp - Retail | D14: 4254 | E14: 3765.4 | F14: 3969.7 | G14: 3458.8 | H14: 3612 | I14: 1742 | J14: 2595 | K14: 2710 | L14: 1720.5 | M14: 2476.2 | N14: 2839 | O14: 2445.1 | P14: 2732.4
B15: Tabcorp - Digital | D15: 3491.4 | E15: 3360.2 | F15: 3821.9 | G15: 3446.8 | H15: 3616 | I15: 3842 | J15: 5167 | K15: 4314 | L15: 5259 | M15: 4438 | N15: 4920.5 | O15: 4346.2 | P15: 4731.2
B16: SportsBet | D16: =_xlfn.XLOOKUP(D$7,SBET!$18:$18,SBET!$94:$94) -> 2998.4194 | E16: =_xlfn.XLOOKUP(E$7,SBET!$18:$18,SBET!$94:$94) -> 3770.1165 | F16: =_xlfn.XLOOKUP(F$7,SBET!$18:$18,SBET!$94:$94) -> 3921.6312 | G16: =_xlfn.XLOOKUP(G$7,SBET!$18:$18,SBET!$94:$94) -> 6066.1924 | H16: =_xlfn.XLOOKUP(H$7,SBET!$18:$18,SBET!$94:$94) -> 6326.0608 | I16: =_xlfn.XLOOKUP(I$7,SBET!$18:$18,SBET!$94:$94) -> 7132.9197 | J16: =_xlfn.XLOOKUP(J$7,SBET!$18:$18,SBET!$94:$94) -> 10820.753 | K16: =_xlfn.XLOOKUP(K$7,SBET!$18:$18,SBET!$94:$94) -> 9001.6287 | ... P16: =_xlfn.XLOOKUP(P$7,SBET!$18:$18,SBET!$94:$94) -> 8171.3795
B17: LadBrokes
B18: Bet365
B19: PointsBet | F19: =SUMIF(PBH!$9:$9,HY!F$7,PBH!$12:$12) -> 209.6 | G19: =SUMIF(PBH!$9:$9,HY!G$7,PBH!$12:$12) -> 280.5 | H19: =SUMIF(PBH!$9:$9,HY!H$7,PBH!$12:$12) -> 349.2 | I19: =SUMIF(PBH!$9:$9,HY!I$7,PBH!$12:$12) -> 481.3 | J19: =SUMIF(PBH!$9:$9,HY!J$7,PBH!$12:$12) -> 1071 | K19: =SUMIF(PBH!$9:$9,HY!K$7,PBH!$12:$12) -> 918 | L19: =SUMIF(PBH!$9:$9,HY!L$7,PBH!$12:$12) -> 1358.4 | M19: =SUMIF(PBH!$9:$9,HY!M$7,PBH!$12:$12) -> 1178 | ... P19: =SUMIF(PBH!$9:$9,HY!P$7,PBH!$12:$12) -> 1468.5
B20: BlueBet | J20: =SUMIF('BBET + BetR'!$9:$9,HY!J$7,'BBET + BetR'!$12:$12) -> 164.7 | K20: =SUMIF('BBET + BetR'!$9:$9,HY!K$7,'BBET + BetR'!$12:$12) -> 180 | L20: =SUMIF('BBET + BetR'!$9:$9,HY!L$7,'BBET + BetR'!$12:$12) -> 264.5 | M20: =SUMIF('BBET + BetR'!$9:$9,HY!M$7,'BBET + BetR'!$12:$12) -> 247.4 | N20: =SUMIF('BBET + BetR'!$9:$9,HY!N$7,'BBET + BetR'!$12:$12) -> 279.1 | O20: =SUMIF('BBET + BetR'!$9:$9,HY!O$7,'BBET + BetR'!$12:$12) -> 250.7 | P20: =SUMIF('BBET + BetR'!$9:$9,HY!P$7,'BBET + BetR'!$12:$12) -> 298.7
B21: BetR | P21: =SUMIF(BETR!$10:$10,HY!P$7,BETR!$12:$12) -> 673.2
B23: Gross Revenue
B24: Tabcorp - Retail | L24: 288.1 | M24: 410.7 | N24: 471.9 | O24: 410.1 | P24: 458.1
B25: Tabcorp - Digital | L25: 894.03 | M25: 744.763 | N25: 806.962 | O25: 712.7768 | P25: 780.648
B26: SportsBet
B27: LadBrokes
B28: Bet365
B29: PointsBet | F29: =SUMIF(PBH!$9:$9,HY!F$7,PBH!$14:$14) -> 21.8 | G29: =SUMIF(PBH!$9:$9,HY!G$7,PBH!$14:$14) -> 28.7 | H29: =SUMIF(PBH!$9:$9,HY!H$7,PBH!$14:$14) -> 38 | I29: =SUMIF(PBH!$9:$9,HY!I$7,PBH!$14:$14) -> 62.8 | J29: =SUMIF(PBH!$9:$9,HY!J$7,PBH!$14:$14) -> 136 | K29: =SUMIF(PBH!$9:$9,HY!K$7,PBH!$14:$14) -> 121.2 | L29: =SUMIF(PBH!$9:$9,HY!L$7,PBH!$14:$14) -> 180.1 | M29: =SUMIF(PBH!$9:$9,HY!M$7,PBH!$14:$14) -> 158.3 | ... P29: =SUMIF(PBH!$9:$9,HY!P$7,PBH!$14:$14) -> 159.7
B30: BlueBet | J30: =SUMIF('BBET + BetR'!$9:$9,HY!J$7,'BBET + BetR'!$14:$14) -> 21.1 | K30: =SUMIF('BBET + BetR'!$9:$9,HY!K$7,'BBET + BetR'!$14:$14) -> 23.1 | L30: =SUMIF('BBET + BetR'!$9:$9,HY!L$7,'BBET + BetR'!$14:$14) -> 36.5 | M30: =SUMIF('BBET + BetR'!$9:$9,HY!M$7,'BBET + BetR'!$14:$14) -> 34 | N30: =SUMIF('BBET + BetR'!$9:$9,HY!N$7,'BBET + BetR'!$14:$14) -> 36 | O30: =SUMIF('BBET + BetR'!$9:$9,HY!O$7,'BBET + BetR'!$14:$14) -> 34.9 | P30: =SUMIF('BBET + BetR'!$9:$9,HY!P$7,'BBET + BetR'!$14:$14) -> 29.3
B31: BetR | P31: =SUMIF(BETR!$10:$10,HY!P$7,BETR!$14:$14) -> 79.8
B33: Net Revenue
B34: Tabcorp - Retail | L34: 288.1 | M34: 410.7 | N34: 471.9 | O34: 410.1 | P34: 458.1 | T34: =SUM(N34:O35)/SUM(L34:M35)-1 -> 0.011594782
B35: Tabcorp - Digital | L35: 702.3 | M35: 599.8 | N35: 599.2 | O35: 542.9 | P35: 572.9
B36: SportsBet | D36: =_xlfn.XLOOKUP(D$7,SBET!$18:$18,SBET!$96:$96) -> 375.43661 | E36: =_xlfn.XLOOKUP(E$7,SBET!$18:$18,SBET!$96:$96) -> 369.16467 | F36: =_xlfn.XLOOKUP(F$7,SBET!$18:$18,SBET!$96:$96) -> 350.33716 | G36: =_xlfn.XLOOKUP(G$7,SBET!$18:$18,SBET!$96:$96) -> 575.11607 | H36: =_xlfn.XLOOKUP(H$7,SBET!$18:$18,SBET!$96:$96) -> 675.09866 | I36: =_xlfn.XLOOKUP(I$7,SBET!$18:$18,SBET!$96:$96) -> 833.4193 | J36: =_xlfn.XLOOKUP(J$7,SBET!$18:$18,SBET!$96:$96) -> 1156.1406 | K36: =_xlfn.XLOOKUP(K$7,SBET!$18:$18,SBET!$96:$96) -> 1053.1906 | ... P36: =_xlfn.XLOOKUP(P$7,SBET!$18:$18,SBET!$96:$96) -> 969.78114 | R36: =SUM(L36:M36)/SUM(J36:K36)-1 -> 0.097209867 | T36: =SUM(N36:O36)/SUM(L36:M36)-1 -> -0.076750483
B37: LadBrokes | E37: =_xlfn.XLOOKUP(E$7,ENT!$17:$17,ENT!$28:$28) -> 157.12085 | F37: =_xlfn.XLOOKUP(F$7,ENT!$17:$17,ENT!$28:$28) -> 204.83165 | G37: =_xlfn.XLOOKUP(G$7,ENT!$17:$17,ENT!$28:$28) -> 206.54747 | H37: =_xlfn.XLOOKUP(H$7,ENT!$17:$17,ENT!$28:$28) -> 247.45072 | I37: =_xlfn.XLOOKUP(I$7,ENT!$17:$17,ENT!$28:$28) -> 308.96149 | J37: =_xlfn.XLOOKUP(J$7,ENT!$17:$17,ENT!$28:$28) -> 401.10624 | K37: =_xlfn.XLOOKUP(K$7,ENT!$17:$17,ENT!$28:$28) -> 322.25831 | L37: =_xlfn.XLOOKUP(L$7,ENT!$17:$17,ENT!$28:$28) -> 442.75863 | ... P37: =_xlfn.XLOOKUP(P$7,ENT!$17:$17,ENT!$28:$28) -> 587.66523 | R37: =SUM(L37:M37)/SUM(J37:K37)-1 -> 0.14474571 | T37: =SUM(N37:O37)/SUM(L37:M37)-1 -> -0.011385251
B38: Bet365
B39: PointsBet | F39: =SUMIF(PBH!$9:$9,HY!F$7,PBH!$19:$19) -> 13.3 | G39: =SUMIF(PBH!$9:$9,HY!G$7,PBH!$19:$19) -> 15.7 | H39: =SUMIF(PBH!$9:$9,HY!H$7,PBH!$19:$19) -> 27.2 | I39: =SUMIF(PBH!$9:$9,HY!I$7,PBH!$19:$19) -> 47.9 | J39: =SUMIF(PBH!$9:$9,HY!J$7,PBH!$19:$19) -> 84.9 | K39: =SUMIF(PBH!$9:$9,HY!K$7,PBH!$19:$19) -> 81.3 | L39: =SUMIF(PBH!$9:$9,HY!L$7,PBH!$19:$19) -> 107.9 | M39: =SUMIF(PBH!$9:$9,HY!M$7,PBH!$19:$19) -> 107.5 | ... P39: =SUMIF(PBH!$9:$9,HY!P$7,PBH!$19:$19) -> 112.3 | R39: =SUM(L39:M39)/SUM(J39:K39)-1 -> 0.29602888 | T39: =SUM(N39:O39)/SUM(L39:M39)-1 -> -0.01810585
B40: BlueBet | J40: =SUMIF('BBET + BetR'!$9:$9,HY!J$7,'BBET + BetR'!$17:$17) -> 17 | K40: =SUMIF('BBET + BetR'!$9:$9,HY!K$7,'BBET + BetR'!$17:$17) -> 18.6 | L40: =SUMIF('BBET + BetR'!$9:$9,HY!L$7,'BBET + BetR'!$17:$17) -> 28.6 | M40: =SUMIF('BBET + BetR'!$9:$9,HY!M$7,'BBET + BetR'!$17:$17) -> 26 | N40: =SUMIF('BBET + BetR'!$9:$9,HY!N$7,'BBET + BetR'!$17:$17) -> 27.2 | O40: =SUMIF('BBET + BetR'!$9:$9,HY!O$7,'BBET + BetR'!$17:$17) -> 26.9 | P40: =SUMIF('BBET + BetR'!$9:$9,HY!P$7,'BBET + BetR'!$17:$17) -> 30.7 | R40: =SUM(L40:M40)/SUM(J40:K40)-1 -> 0.53370787 | T40: =SUM(N40:O40)/SUM(L40:M40)-1 -> -0.0091575092
B41: BetR | P41: =SUMIF(BETR!$10:$10,HY!P$7,BETR!$17:$17) -> 49.8
B43: Gross Profit
B44: Tabcorp - Retail
B45: Tabcorp - Digital
B46: SportsBet | D46: =_xlfn.XLOOKUP(D$7,SBET!$18:$18,SBET!$99:$99) -> 272.2761 | E46: =_xlfn.XLOOKUP(E$7,SBET!$18:$18,SBET!$99:$99) -> 221.14212 | F46: =_xlfn.XLOOKUP(F$7,SBET!$18:$18,SBET!$99:$99) -> 282.41465 | G46: =_xlfn.XLOOKUP(G$7,SBET!$18:$18,SBET!$99:$99) -> 318.69489 | H46: =_xlfn.XLOOKUP(H$7,SBET!$18:$18,SBET!$99:$99) -> 382.61723 | I46: =_xlfn.XLOOKUP(I$7,SBET!$18:$18,SBET!$99:$99) -> 450.23801 | J46: =_xlfn.XLOOKUP(J$7,SBET!$18:$18,SBET!$99:$99) -> 578.07028 | K46: =_xlfn.XLOOKUP(K$7,SBET!$18:$18,SBET!$99:$99) -> 558.10098 | ... O46: =_xlfn.XLOOKUP(O$7,SBET!$18:$18,SBET!$99:$99) -> 518.27
B47: LadBrokes
B48: Bet365
B49: PointsBet
B50: BlueBet
B51: BetR | P51: =SUMIF(BETR!$10:$10,HY!P$7,BETR!$14:$14) -> 79.8
B53: YIELDS/MARGINS
B54: Gross Yield
B55: Tabcorp - Retail | L55: =L24/L14 -> 0.16745132 | M55: =M24/M14 -> 0.16585898 | N55: =N24/N14 -> 0.1662205 | O55: =O24/O14 -> 0.1677232 | P55: =P24/P14 -> 0.16765481
B56: Tabcorp - Digital | L56: =L25/L15 -> 0.17 | M56: =M25/M15 -> 0.16781501 | N56: =N25/N15 -> 0.164 | O56: =O25/O15 -> 0.164 | P56: =P25/P15 -> 0.165
B57: SportsBet
B58: LadBrokes
B59: Bet365
B60: PointsBet | F60: =F29/F19 -> 0.10400763 | G60: =G29/G19 -> 0.10231729 | H60: =H29/H19 -> 0.10882016 | I60: =I29/I19 -> 0.13047995 | J60: =J29/J19 -> 0.12698413 | K60: =K29/K19 -> 0.13202614 | L60: =L29/L19 -> 0.13258245 | M60: =M29/M19 -> 0.13438031 | ... P60: =P29/P19 -> 0.10875043
B61: BlueBet | J61: =J30/J20 -> 0.12811172 | K61: =K30/K20 -> 0.12833333 | L61: =L30/L20 -> 0.13799622 | M61: =M30/M20 -> 0.13742926 | N61: =N30/N20 -> 0.12898603 | O61: =O30/O20 -> 0.13921021 | P61: =P30/P20 -> 0.098091731
B63: Net Yield
B64: Tabcorp - Retail | L64: =L34/L14 -> 0.16745132 | M64: =M34/M14 -> 0.16585898 | N64: =N34/N14 -> 0.1662205 | O64: =O34/O14 -> 0.1677232 | P64: =P34/P14 -> 0.16765481
B65: Tabcorp - Digital | L65: =L35/L15 -> 0.1335425 | M65: =M35/M15 -> 0.13515097 | N65: =N35/N15 -> 0.12177624 | O65: =O35/O15 -> 0.12491372 | P65: =P35/P15 -> 0.12108979
B66: SportsBet | D66: =D36/D16 -> 0.12521151 | E66: =E36/E16 -> 0.097918638 | F66: =F36/F16 -> 0.089334549 | G66: =G36/G16 -> 0.094806763 | H66: =H36/H16 -> 0.10671707 | I66: =I36/I16 -> 0.11684126 | J66: =J36/J16 -> 0.10684474 | K66: =K36/K16 -> 0.117 | ... P66: =P36/P16 -> 0.11868022
B67: LadBrokes
B68: Bet365
B69: PointsBet | F69: =F39/F19 -> 0.063454198 | G69: =G39/G19 -> 0.05597148 | H69: =H39/H19 -> 0.077892325 | I69: =I39/I19 -> 0.099522128 | J69: =J39/J19 -> 0.079271709 | K69: =K39/K19 -> 0.088562092 | L69: =L39/L19 -> 0.079431684 | M69: =M39/M19 -> 0.091256367 | ... P69: =P39/P19 -> 0.076472591
B70: BlueBet | J70: =J40/J20 -> 0.10321797 | K70: =K40/K20 -> 0.10333333 | L70: =L40/L20 -> 0.10812854 | M70: =M40/M20 -> 0.10509297 | N70: =N40/N20 -> 0.097456109 | O70: =O40/O20 -> 0.10729956 | P70: =P40/P20 -> 0.10277871
B72: Promo's
B73: Tabcorp - Retail | L73: =L55-L64 -> 0 | M73: =M55-M64 -> 0 | N73: =N55-N64 -> 0 | O73: =O55-O64 -> 0 | P73: =P55-P64 -> 0
B74: Tabcorp - Digital | L74: =L56-L65 -> 0.036457501 | M74: =M56-M65 -> 0.032664038 | N74: =N56-N65 -> 0.042223758 | O74: =O56-O65 -> 0.039086282 | P74: =P56-P65 -> 0.043910213
B75: SportsBet
B76: LadBrokes
B77: Bet365
B78: PointsBet | F78: =F60-F69 -> 0.040553435 | G78: =G60-G69 -> 0.046345811 | H78: =H60-H69 -> 0.030927835 | I78: =I60-I69 -> 0.030957823 | J78: =J60-J69 -> 0.047712418 | K78: =K60-K69 -> 0.043464052 | L78: =L60-L69 -> 0.053150766 | M78: =M60-M69 -> 0.043123939 | ... P78: =P60-P69 -> 0.032277835
B79: BlueBet | J79: =J61-J70 -> 0.024893746 | K79: =K61-K70 -> 0.025 | L79: =L61-L70 -> 0.029867675 | M79: =M61-M70 -> 0.032336297 | N79: =N61-N70 -> 0.031529918 | O79: =O61-O70 -> 0.03191065 | P79: =P61-P70 -> -0.0046869769
B81: Cost of Sales % of Net Revenue
B82: Tabcorp - Retail
B83: Tabcorp - Digital
B84: SportsBet | D84: =(D36-D46)/D36 -> 0.27477477 | E84: =(E36-E46)/E36 -> 0.40096618 | F84: =(F36-F46)/F36 -> 0.19387755 | G84: =(G36-G46)/G36 -> 0.44585987 | H84: =(H36-H46)/H36 -> 0.43324251 | I84: =(I36-I46)/I36 -> 0.45977011 | J84: =(J36-J46)/J36 -> 0.5 | K84: =(K36-K46)/K36 -> 0.47008547 | ... O84: =(O36-O46)/O36 -> 0.52745424
B85: LadBrokes
B86: Bet365
B87: PointsBet
B88: BlueBet
B90: KPI's
B91: Sales & Marketing
B92: Tabcorp - Retail
B93: Tabcorp - Digital
B94: SportsBet | D94: =-_xlfn.XLOOKUP(D$7,SBET!$18:$18,SBET!$100:$100) -> 71.028548 | E94: =-_xlfn.XLOOKUP(E$7,SBET!$18:$18,SBET!$100:$100) -> 60.635742 | F94: =-_xlfn.XLOOKUP(F$7,SBET!$18:$18,SBET!$100:$100) -> 85.796855 | G94: =-_xlfn.XLOOKUP(G$7,SBET!$18:$18,SBET!$100:$100) -> 102.56847 | H94: =-_xlfn.XLOOKUP(H$7,SBET!$18:$18,SBET!$100:$100) -> 125.0864 | I94: =-_xlfn.XLOOKUP(I$7,SBET!$18:$18,SBET!$100:$100) -> 113.03848 | J94: =-_xlfn.XLOOKUP(J$7,SBET!$18:$18,SBET!$100:$100) -> 126.45287 | K94: =-_xlfn.XLOOKUP(K$7,SBET!$18:$18,SBET!$100:$100) -> 106.21922 | ... O94: =-_xlfn.XLOOKUP(O$7,SBET!$18:$18,SBET!$100:$100) -> 116.79324
B95: LadBrokes
B96: Bet365
B97: PointsBet | J97: =SUMIF(PBH!$9:$9,HY!J$7,PBH!$34:$34) -> 21 | K97: =SUMIF(PBH!$9:$9,HY!K$7,PBH!$34:$34) -> 30.4 | L97: =SUMIF(PBH!$9:$9,HY!L$7,PBH!$34:$34) -> 44.7 | M97: =SUMIF(PBH!$9:$9,HY!M$7,PBH!$34:$34) -> 16.7 | N97: =SUMIF(PBH!$9:$9,HY!N$7,PBH!$34:$34) -> 45.4 | O97: =SUMIF(PBH!$9:$9,HY!O$7,PBH!$34:$34) -> 15.7 | P97: =SUMIF(PBH!$9:$9,HY!P$7,PBH!$34:$34) -> 28.4
B98: BlueBet
B100: Active Players (LTM)
B101: Tabcorp - Retail
B102: Tabcorp - Digital
B103: SportsBet
B104: LadBrokes
B105: Bet365
B106: PointsBet | F106: =_xlfn.XLOOKUP(F$3,PBH!$11:$11,PBH!$22:$22) -> 45828 | G106: =_xlfn.XLOOKUP(G$3,PBH!$11:$11,PBH!$22:$22) -> 68464 | H106: =_xlfn.XLOOKUP(H$3,PBH!$11:$11,PBH!$22:$22) -> 81014 | I106: =_xlfn.XLOOKUP(I$3,PBH!$11:$11,PBH!$22:$22) -> 90422 | J106: =_xlfn.XLOOKUP(J$3,PBH!$11:$11,PBH!$22:$22) -> 142992 | K106: =_xlfn.XLOOKUP(K$3,PBH!$11:$11,PBH!$22:$22) -> 196585 | L106: =_xlfn.XLOOKUP(L$3,PBH!$11:$11,PBH!$22:$22) -> 232875 | M106: =_xlfn.XLOOKUP(M$3,PBH!$11:$11,PBH!$22:$22) -> 239121 | ... P106: =_xlfn.XLOOKUP(P$3,PBH!$11:$11,PBH!$22:$22) -> 218288
B107: BlueBet | J107: =_xlfn.XLOOKUP(J$3,'BBET + BetR'!$11:$11,'BBET + BetR'!$20:$20) -> 25540 | K107: =_xlfn.XLOOKUP(K$3,'BBET + BetR'!$11:$11,'BBET + BetR'!$20:$20) -> 32472 | L107: =_xlfn.XLOOKUP(L$3,'BBET + BetR'!$11:$11,'BBET + BetR'!$20:$20) -> 45087 | M107: =_xlfn.XLOOKUP(M$3,'BBET + BetR'!$11:$11,'BBET + BetR'!$20:$20) -> 53328 | N107: =_xlfn.XLOOKUP(N$3,'BBET + BetR'!$11:$11,'BBET + BetR'!$20:$20) -> 59632 | O107: =_xlfn.XLOOKUP(O$3,'BBET + BetR'!$11:$11,'BBET + BetR'!$20:$20) -> 65415 | P107: =_xlfn.XLOOKUP(P$3,'BBET + BetR'!$11:$11,'BBET + BetR'!$20:$20) -> 67391
B112: Splits
B113: Sports
B114: Racing
B115: Retail
B116: Digital
...

Sheet Market Size Summary
B2: Revenue
C4: FY18 | D4: FY19 | E4: FY20 | F4: FY21 | G4: FY22 | H4: FY23 | I4: FY24 | J4: FY25 | K4: FY26 | L4: FY27 | M4: FY28 | N4: FY29 | O4: FY30
B6: Digitlal Market
B7: Digital Revenue Market Share - Tabcorp per VRI | G7: 5229.3173 | H7: 4661.6327
B9: Total Market (incl Retail)
B10: Total Revenue Market Share - Tabcorp per VRI | G10: 5955.0595 | H10: 5850
B11: Australian Gambling Stats - Total Gambling | C11: 4946.739 | D11: 5030.124 | E11: 4567.098 | F11: 5815.092
C13: CY18 | D13: CY19 | E13: CY20 | F13: CY21 | G13: CY22 | H13: CY23 | I13: CY24 | J13: CY25 | K13: CY26 | L13: CY27 | M13: CY28 | N13: CY29 | O13: CY30
B15: Digitlal Market
B16: Digital Revenue Market Share - SB Investor Day | C16: 2588.1361 | D16: 4126.1212 | E16: 4936.8731
B17: Digital Revenue Market Share - SB Annual Reports | D17: 2907.4761 | E17: 4325.1301 | F17: 4747.6589 | G17: 4676.5595 | H17: 4839.9147
B18: Digital Market - SB Annual Reports | C18: 3417 | D18: 3834 | E18: 5934 | F18: 6873 | G18: 6972
B19: Responsible Wagering Australia - Apr 2023 | C19: 3348 | D19: 3608 | E19: 4584 | F19: 6033 | G19: 6585
B20: Responsible Wagering Australia - Nov 2025 | D20: 3818 | E20: 5161 | F20: 6970 | G20: 7430 | H20: 7066 | I20: 7037 | J20: 6982 | K20: 7204 | L20: 7375 | M20: 7544 | N20: 7714
B22: OffShore Betting | D22: 1465 | E22: 2082 | F22: 2413 | G22: 2682 | H22: 4052 | I22: 3893 | J22: 3929 | K22: 4209 | L22: 4467 | M22: 4729 | N22: 4997
B23: OffShore Betting & Casino | D23: 693 | E23: 911 | F23: 1090 | G23: 1086 | H23: 1359 | I23: 1237 | J23: 1228 | K23: 1294 | L23: 1351 | M23: 1407 | N23: 1463
B25: Total Market (incl Retail)
B26: Total Market - SB Annual Reports | C26: 5100 | D26: 5400 | E26: 6900 | F26: 7900 | G26: 8400
B27: Responsible Wagering Australia | C27: 5682 | D27: 5635 | E27: 6234 | F27: 7487 | G27: 7792
B29: TURNOVER
C31: FY18 | D31: FY19 | E31: FY20 | F31: FY21 | G31: FY22 | H31: FY23 | I31: FY24 | J31: FY25 | K31: FY26 | L31: FY27 | M31: FY28 | N31: FY29 | O31: FY30
B33: Digitlal Market
B34: Digital Revenue Market Share - Tabcorp | G34: 49223.35 | H34: 46102.985
B35: NT Licenced Turnover | C35: 24800 | D35: 27900 | E35: 29100 | F35: 42400 | G35: 50000
B37: Total Market (incl Retail)
B38: Racing Australia Annual Report | C38: 39318.91 | D38: 42282.33 | E38: 41693.57 | F38: 59905.07

Sheet FY - Market Shares
C2: FY18 | D2: FY19 | E2: FY20 | F2: FY21 | G2: FY22 | H2: FY23 | I2: FY24 | J2: FY25 | M2: CY18 | N2: CY19 | O2: CY20 | P2: CY21 | Q2: CY22 | R2: CY23 | S2: CY24 | T2: CY25
C3: 43281 | D3: =EOMONTH(C3,12) -> 43646 | E3: =EOMONTH(D3,12) -> 44012 | F3: =EOMONTH(E3,12) -> 44377 | G3: =EOMONTH(F3,12) -> 44742 | H3: =EOMONTH(G3,12) -> 45107 | I3: =EOMONTH(H3,12) -> 45473 | J3: =EOMONTH(I3,12) -> 45838 | M3: 43465 | N3: =EOMONTH(M3,12) -> 43830 | O3: =EOMONTH(N3,12) -> 44196 | P3: =EOMONTH(O3,12) -> 44561 | Q3: =EOMONTH(P3,12) -> 44926 | R3: =EOMONTH(Q3,12) -> 45291 | S3: =EOMONTH(R3,12) -> 45657 | T3: =EOMONTH(S3,12) -> 46022
B5: MARKET SHARE ESTIMATES - NET REVENUE
B7: Net Revenue - Tabcorp | L7: Net Revenue - Tabcorp
B8: Tabcorp - Retail - per VRI Share | G8: 698.8 | H8: 882 | L8: Tabcorp - Retail - per VRI Share | Q8: 882.6 | R8: 868.2 | S8: 918.8 | T8: 916.2
B9: Tabcorp - Digital - per VRI Share | G9: 1302.1 | H9: 1142.1 | L9: Tabcorp - Digital - per VRI Share | Q9: 1199 | R9: 1115.8 | S9: 1101.4 | T9: 1056.2
B10: Tabcorp - Retail | G10: 654 | H10: 818.4 | L10: Tabcorp - Retail | Q10: 814.8 | R10: 801.6
B11: Tabcorp - Digital | G11: 1073.5 | H11: 942.7 | L11: Tabcorp - Digital | Q11: 986.6 | R11: 923.1
B13: Market Share - reported | L13: Market Share - reported
B14: Digital Revenue Market Share - Tabcorp | G14: 0.249 | H14: 0.245 | L14: SportsBet Share - Investor Day | M14: 0.278 | N14: 0.303 | O14: 0.403
B15: Total Revenue Market Share - Tabcorp | G15: 0.336 | H15: 0.346 | L15: SportsBet Share - Annual Reports | N15: 0.43 | O15: 0.46 | P15: 0.5 | Q15: 0.48 | R15: 0.45
B17: Grossed Up Market Size | L17: Grossed Up Market Size
B18: Digital Revenue Market Share - Tabcorp per VRI | G18: =G9/G14 -> 5229.3173 | H18: =H9/H14 -> 4661.6327 | L18: Digital Revenue Market Share - SB Investor Day | M18: =M25/M14 -> 2579.4065 | N18: =N25/N14 -> 2707.9472 | O18: =O25/O14 -> 4101.8263
B19: Total Revenue Market Share - Tabcorp per VRI | G19: =SUM(G8:G9)/G15 -> 5955.0595 | H19: =SUM(H8:H9)/H15 -> 5850 | L19: Digital Revenue Market Share - SB Annual Reports | N19: =N25/N15 -> 1908.1581 | O19: =O25/O15 -> 3593.5565 | P19: =P25/P15 -> 4764.476 | Q19: =Q25/Q15 -> 4677.7354 | R19: =R25/R15 -> 4864.1311
B20: Digital Revenue Market Share - Tabcorp | G20: =G11/G14 -> 4311.245 | H20: =H11/H14 -> 3847.7551
B21: Total Revenue Market Share - Tabcorp | G21: =SUM(G10:G11)/G15 -> 5141.369 | H21: =SUM(H10:H11)/H15 -> 5089.8844 | L21: WA RETAIL? | T21: 300
B23: Digital Net Revenue | L23: Digital Net Revenue - Pre GST
B24: Tabcorp - Digital | G24: =G9 -> 1302.1 | H24: =H9 -> 1142.1 | L24: Tabcorp - Digital | Q24: =Q9 -> 1199 | R24: =R9 -> 1115.8 | S24: =S9 -> 1101.4 | T24: =T9 -> 1056.2 | V24: =S24/R24-1 -> -0.012905539 | W24: =T24/S24-1 -> -0.041038678
B25: SportsBet | C25: =SUMIF(SBET!$5:$5,C$2,SBET!$96:$96) -> 744.60128 | D25: =SUMIF(SBET!$5:$5,D$2,SBET!$96:$96) -> 925.45323 | E25: =SUMIF(SBET!$5:$5,E$2,SBET!$96:$96) -> 1508.518 | F25: =SUMIF(SBET!$5:$5,F$2,SBET!$96:$96) -> 2209.3311 | G25: =SUMIF(SBET!$5:$5,G$2,SBET!$96:$96) -> 2424.0999 | H25: =SUMIF(SBET!$5:$5,H$2,SBET!$96:$96) -> 2238.0491 | I25: =SUMIF(SBET!$5:$5,I$2,SBET!$96:$96) -> 969.78114 | L25: SportsBet | M25: ='SportsBet ASIC'!D5/1000 -> 717.075 | N25: ='SportsBet ASIC'!E5/1000 -> 820.508 | O25: ='SportsBet ASIC'!F5/1000 -> 1653.036 | P25: ='SportsBet ASIC'!G5/1000 -> 2382.238 | Q25: ='SportsBet ASIC'!H5/1000 -> 2245.313 | R25: ='SportsBet ASIC'!I5/1000 -> 2188.859 | S25: ='SportsBet ASIC'!J5/1000 -> 2114.311 | T25: ='SportsBet ASIC'!K5/1000 -> 2038.378 | V25: =S25/R25-1 -> -0.034057927 | W25: =T25/S25-1 -> -0.035913827
B26: LadBrokes | C26: =SUMIF(ENT!$5:$5,C$2,ENT!$28:$28) -> 157.12085 | D26: =SUMIF(ENT!$5:$5,D$2,ENT!$28:$28) -> 411.37912 | E26: =SUMIF(ENT!$5:$5,E$2,ENT!$28:$28) -> 556.41221 | F26: =SUMIF(ENT!$5:$5,F$2,ENT!$28:$28) -> 723.36454 | G26: =SUMIF(ENT!$5:$5,G$2,ENT!$28:$28) -> 828.06846 | H26: =SUMIF(ENT!$5:$5,H$2,ENT!$28:$28) -> 818.64069 | L26: LadBrokes | M26: ='Entain ASIC'!D15/1000 -> 323.279 | N26: ='Entain ASIC'!E15/1000 -> 461.9714 | O26: ='Entain ASIC'!F15/1000 -> 715.1353 | P26: ='Entain ASIC'!G15/1000 -> 841.8366 | Q26: ='Entain ASIC'!H15/1000 -> 915.1868 | R26: ='Entain ASIC'!I15/1000 -> 839.6883 | S26: ='Entain ASIC'!J15/1000 -> 848.9437 | T26: ='Entain ASIC'!K15/1000 -> 797.4901 | V26: =S26/R26-1 -> 0.011022423 | W26: =T26/S26-1 -> -0.060608966
B27: Bet365 | C27: =SUMIF('B365'!$5:$5,C$2,'B365'!$15:$15) -> 114.999 | D27: =SUMIF('B365'!$5:$5,D$2,'B365'!$15:$15) -> 120.914 | E27: =SUMIF('B365'!$5:$5,E$2,'B365'!$15:$15) -> 147.173 | F27: =SUMIF('B365'!$5:$5,F$2,'B365'!$15:$15) -> 190.321 | G27: =SUMIF('B365'!$5:$5,G$2,'B365'!$15:$15) -> 200.429 | H27: =SUMIF('B365'!$5:$5,H$2,'B365'!$15:$15) -> 201.286 | L27: Bet365 | M27: ='Bet365 ASIC'!E8/1000 -> 120.914 | N27: ='Bet365 ASIC'!F8/1000 -> 147.173 | O27: ='Bet365 ASIC'!G8/1000 -> 190.321 | P27: ='Bet365 ASIC'!H8/1000 -> 200.429 | Q27: ='Bet365 ASIC'!I8/1000 -> 201.286 | R27: ='Bet365 ASIC'!J8/1000 -> 261.002 | S27: ='Bet365 ASIC'!K8/1000 -> 292.645 | T27: 285
B28: PointsBet | E28: =SUMIF(PBH!$5:$5,E$2,PBH!$19:$19) -> 75.1 | F28: =SUMIF(PBH!$5:$5,F$2,PBH!$19:$19) -> 166.2 | G28: =SUMIF(PBH!$5:$5,G$2,PBH!$19:$19) -> 215.4 | H28: =SUMIF(PBH!$5:$5,H$2,PBH!$19:$19) -> 211.5 | L28: PointsBet | N28: =PBH!BG19 -> 42.9 | O28: =PBH!BH19 -> 132.8 | P28: =PBH!BI19 -> 189.2 | Q28: =PBH!BJ19 -> 212.7 | R28: =PBH!BK19 -> 218.6 | S28: =PBH!BL19 -> 238 | T28: =PBH!BM19 -> 238.6
B29: BlueBet | F29: =SUMIF('BBET + BetR'!$5:$5,F$2,'BBET + BetR'!$17:$17) -> 35.6 | G29: =SUMIF('BBET + BetR'!$5:$5,G$2,'BBET + BetR'!$17:$17) -> 54.6 | H29: =SUMIF('BBET + BetR'!$5:$5,H$2,'BBET + BetR'!$17:$17) -> 54.1 | L29: BlueBet | P29: =SUMIF('BBET + BetR'!$6:$6,P$2,'BBET + BetR'!$17:$17) -> 47.2 | Q29: =SUMIF('BBET + BetR'!$6:$6,Q$2,'BBET + BetR'!$17:$17) -> 53.2 | R29: =SUMIF('BBET + BetR'!$6:$6,R$2,'BBET + BetR'!$17:$17) -> 57.6 | S29: =SUMIF('BBET + BetR'!$6:$6,S$2,'BBET + BetR'!$17:$17) -> 33.2 | T29: 0
L30: BetR | Q30: 85 | R30: 85 | S30: 118 | T30: =SUMIF('BBET + BetR'!$6:$6,T$2,'BBET + BetR'!$30:$30) -> 153.9
L31: Dabble | Q31: 0 | R31: ='Dabble ASIC'!I14/1000000 -> 0 | S31: ='Dabble ASIC'!J14/1000000 -> 81.884418 | T31: ='Dabble ASIC'!K14/1000000 -> 146.93183
B32: Other - Balancing | G32: =G33-SUM(G24:G29) -> 204.61991 | H32: =H33-SUM(H24:H29) -> -4.0430973 | L32: Other - Balancing | Q32: 150 | R32: 150 | S32: 150 | T32: 150
B33: Digital Market | G33: =G18 -> 5229.3173 | H33: =H18 -> 4661.6327 | L33: Digital Market | O33: =O19 -> 3593.5565 | P33: =P19 -> 4764.476 | Q33: =SUM(Q24:Q32) -> 5061.6858 | R33: =SUM(R24:R32) -> 4916.5493 | S33: =SUM(S24:S32) -> 4978.3841 | T33: =SUM(T24:T32) -> 4866.4999
B35: Share | L35: Share
B36: Tabcorp - Digital | G36: =G24/G$33 -> 0.249 | H36: =H24/H$33 -> 0.245 | L36: Tabcorp | Q36: =Q24/Q$33 -> 0.2368776 | R36: =R24/R$33 -> 0.22694779 | S36: =S24/S$33 -> 0.22123644 | T36: =T24/T$33 -> 0.21703483
B37: SportsBet | G37: =G25/G$33 -> 0.46355954 | H37: =H25/H$33 -> 0.48009983 | L37: SportsBet | O37: =O25/O$33 -> 0.46 | P37: =P25/P$33 -> 0.5 | Q37: =Q25/Q$33 -> 0.44358996 | R37: =R25/R$33 -> 0.44520229 | S37: =S25/S$33 -> 0.42469825 | T37: =T25/T$33 -> 0.41885915
B38: LadBrokes | G38: =G26/G$33 -> 0.15835116 | H38: =H26/H$33 -> 0.17561244 | L38: LadBrokes | O38: =O26/O$33 -> 0.19900488 | P38: =P26/P$33 -> 0.17669028 | Q38: =Q26/Q$33 -> 0.18080672 | R38: =R26/R$33 -> 0.17078814 | S38: =S26/S$33 -> 0.17052595 | T38: =T26/T$33 -> 0.16387344
B39: Bet365 | G39: =G27/G$33 -> 0.038327948 | H39: =H27/H$33 -> 0.043179293 | L39: Bet365 | O39: =O27/O$33 -> 0.052961738 | P39: =P27/P$33 -> 0.042067375 | Q39: =Q27/Q$33 -> 0.039766593 | R39: =R27/R$33 -> 0.05308642 | S39: =S27/S$33 -> 0.05878313 | T39: =T27/T$33 -> 0.05856365
B40: PointsBet | G40: =G28/G$33 -> 0.041190846 | H40: =H28/H$33 -> 0.04537037 | L40: PointsBet | O40: =O28/O$33 -> 0.036955033 | P40: =P28/P$33 -> 0.039710558 | Q40: =Q28/Q$33 -> 0.042021573 | R40: =R28/R$33 -> 0.044462078 | S40: =S28/S$33 -> 0.047806677 | T40: =T28/T$33 -> 0.049029077
B41: BlueBet | G41: =G29/G$33 -> 0.010441134 | H41: =H29/H$33 -> 0.011605376 | L41: BlueBet | P41: =P29/P$33 -> 0.0099066508 | Q41: =Q29/Q$33 -> 0.010510332 | R41: =R29/R$33 -> 0.011715534 | S41: =S29/S$33 -> 0.0066688305 | T41: =T29/T$33 -> 0
B42: Other - Balancing | G42: =G32/G$33 -> 0.039129375 | H42: =H32/H$33 -> -0.00086731357 | L42: BetR | P42: =P30/P$33 -> 0 | Q42: =Q30/Q$33 -> 0.016792824 | R42: =R30/R$33 -> 0.017288548 | S42: =S30/S$33 -> 0.02370247 | T42: =T30/T$33 -> 0.031624371
L43: Dabble | P43: =P31/P$33 -> 0 | Q43: =Q31/Q$33 -> 0 | R43: =R31/R$33 -> 0 | S43: =S31/S$33 -> 0.016447991 | T43: =T31/T$33 -> 0.030192505
B44: Total Net Revenue (ex WA retail) | L44: Other | T44: =T32/T$33 -> 0.030822974
B45: Tabcorp - Total | G45: =G8+G9 -> 2000.9 | H45: =H8+H9 -> 2024.1
B46: SportsBet | C46: =SUMIF(SBET!$5:$5,C$2,SBET!$96:$96) -> 744.60128 | D46: =SUMIF(SBET!$5:$5,D$2,SBET!$96:$96) -> 925.45323 | E46: =SUMIF(SBET!$5:$5,E$2,SBET!$96:$96) -> 1508.518 | F46: =SUMIF(SBET!$5:$5,F$2,SBET!$96:$96) -> 2209.3311 | G46: =SUMIF(SBET!$5:$5,G$2,SBET!$96:$96) -> 2424.0999 | H46: =SUMIF(SBET!$5:$5,H$2,SBET!$96:$96) -> 2238.0491
B47: LadBrokes | C47: =SUMIF(ENT!$5:$5,C$2,ENT!$28:$28) -> 157.12085 | D47: =SUMIF(ENT!$5:$5,D$2,ENT!$28:$28) -> 411.37912 | E47: =SUMIF(ENT!$5:$5,E$2,ENT!$28:$28) -> 556.41221 | F47: =SUMIF(ENT!$5:$5,F$2,ENT!$28:$28) -> 723.36454 | G47: =SUMIF(ENT!$5:$5,G$2,ENT!$28:$28) -> 828.06846 | H47: =SUMIF(ENT!$5:$5,H$2,ENT!$28:$28) -> 818.64069
B48: Bet365 | C48: =SUMIF('B365'!$5:$5,C$2,'B365'!$15:$15) -> 114.999 | D48: =SUMIF('B365'!$5:$5,D$2,'B365'!$15:$15) -> 120.914 | E48: =SUMIF('B365'!$5:$5,E$2,'B365'!$15:$15) -> 147.173 | F48: =SUMIF('B365'!$5:$5,F$2,'B365'!$15:$15) -> 190.321 | G48: =SUMIF('B365'!$5:$5,G$2,'B365'!$15:$15) -> 200.429 | H48: =SUMIF('B365'!$5:$5,H$2,'B365'!$15:$15) -> 201.286
B49: PointsBet | E49: =SUMIF(PBH!$5:$5,E$2,PBH!$19:$19) -> 75.1 | F49: =SUMIF(PBH!$5:$5,F$2,PBH!$19:$19) -> 166.2 | G49: =SUMIF(PBH!$5:$5,G$2,PBH!$19:$19) -> 215.4 | H49: =SUMIF(PBH!$5:$5,H$2,PBH!$19:$19) -> 211.5
B50: BlueBet | F50: =SUMIF('BBET + BetR'!$5:$5,F$2,'BBET + BetR'!$17:$17) -> 35.6 | G50: =SUMIF('BBET + BetR'!$5:$5,G$2,'BBET + BetR'!$17:$17) -> 54.6 | H50: =SUMIF('BBET + BetR'!$5:$5,H$2,'BBET + BetR'!$17:$17) -> 54.1
B51: Other - Balancing | G51: =G52-SUM(G45:G50) -> 231.56217 | H51: =H52-SUM(H45:H50) -> 302.32425
B52: Total Market | G52: =G19 -> 5955.0595 | H52: =H19 -> 5850
B54: Share
B55: Tabcorp - Total | G55: =G45/G$52 -> 0.336 | H55: =H45/H$52 -> 0.346
B56: SportsBet | G56: =G46/G$52 -> 0.4070656 | H56: =H46/H$52 -> 0.38257249
B57: LadBrokes | G57: =G47/G$52 -> 0.13905293 | H57: =H47/H$52 -> 0.13993858
B58: Bet365 | G58: =G48/G$52 -> 0.033656926 | H58: =H48/H$52 -> 0.034407863
B59: PointsBet | G59: =G49/G$52 -> 0.036170923 | H59: =H49/H$52 -> 0.036153846
B60: BlueBet | G60: =G50/G$52 -> 0.0091686741 | H60: =H50/H$52 -> 0.0092478632
B61: Other - Balancing | G61: =G51/G$52 -> 0.038884946 | H61: =H51/H$52 -> 0.051679359
B63: AUSTRALIAN GAMBLING STATS | L63: SPORTSBET
B64: Total Wagering | C64: 4946.739 | D64: 5030.124 | E64: 4567.098 | F64: 5815.092 | L64: Retail % | M64: 0.33 | N64: 0.29 | O64: 0.14 | P64: 0.13 | Q64: 0.17
L65: Digital % | M65: 0.67 | N65: 0.71 | O65: 0.86 | P65: 0.87 | Q65: 0.83
L66: Market Size | M66: 5100 | N66: 5400 | O66: 6900 | P66: 7900 | Q66: 8400
L68: Retail Market | M68: =M64*M66 -> 1683 | N68: =N64*N66 -> 1566 | O68: =O64*O66 -> 966 | P68: =P64*P66 -> 1027 | Q68: =Q64*Q66 -> 1428
L69: Digital market | M69: =M65*M66 -> 3417 | N69: =N65*N66 -> 3834 | O69: =O65*O66 -> 5934 | P69: =P65*P66 -> 6873 | Q69: =Q65*Q66 -> 6972
L71: RESPONSIBLE WAGERING AUSTRALIA
L72: Land Racing | M72: 1848 | N72: 1696 | O72: 1321 | P72: 1050 | Q72: 870
L73: Land Sports | M73: 486 | N73: 331 | O73: 329 | P73: 404 | Q73: 337
L74: Total Land | M74: =SUM(M72:M73) -> 2334 | N74: =SUM(N72:N73) -> 2027 | O74: =SUM(O72:O73) -> 1650 | P74: =SUM(P72:P73) -> 1454 | Q74: =SUM(Q72:Q73) -> 1207
L76: Online Racing | M76: 2389 | N76: 2544 | O76: 3793 | P76: 4915 | Q76: 5322
L77: Online Sports | M77: 959 | N77: 1064 | O77: 791 | P77: 1118 | Q77: 1263
L78: Total Online | M78: =SUM(M76:M77) -> 3348 | N78: =SUM(N76:N77) -> 3608 | O78: =SUM(O76:O77) -> 4584 | P78: =SUM(P76:P77) -> 6033 | Q78: =SUM(Q76:Q77) -> 6585
L80: Total Racing | M80: =SUM(M72,M76) -> 4237 | N80: =SUM(N72,N76) -> 4240 | O80: =SUM(O72,O76) -> 5114 | P80: =SUM(P72,P76) -> 5965 | Q80: =SUM(Q72,Q76) -> 6192
L81: Total Sports | M81: =SUM(M73,M77) -> 1445 | N81: =SUM(N73,N77) -> 1395 | O81: =SUM(O73,O77) -> 1120 | P81: =SUM(P73,P77) -> 1522 | Q81: =SUM(Q73,Q77) -> 1600
L82: Total Market | M82: =SUM(M80:M81) -> 5682 | N82: =SUM(N80:N81) -> 5635 | O82: =SUM(O80:O81) -> 6234 | P82: =SUM(P80:P81) -> 7487 | Q82: =SUM(Q80:Q81) -> 7792
L84: Grey Market Racing | M84: 193 | N84: 186 | O84: 170 | P84: 209 | Q84: 207
L85: Grey Market Sports | M85: 327 | N85: 316 | O85: 288 | P85: 355 | Q85: 352
L86: Offshore Market | M86: =SUM(M84:M85) -> 520 | N86: =SUM(N84:N85) -> 502 | O86: =SUM(O84:O85) -> 458 | P86: =SUM(P84:P85) -> 564 | Q86: =SUM(Q84:Q85) -> 559
B95: MARKET SHARE ESTIMATES - TURNOVER
B97: Turnover - Tabcorp | L97: Turnover - Tabcorp
B98: Tabcorp - Retail | G98: 4196.7 | H98: 5284.1 | L98: Tabcorp - Retail | Q98: 5315.2 | R98: 5177.5
B99: Tabcorp - Digital | G99: 9697 | H99: 9266.7 | L99: Tabcorp - Digital | Q99: 9358.5 | R99: 9077.4
B101: Market Share - reported | L101: Market Share - reported
B102: Digital Turnover Market Share - Tabcorp | G102: 0.197 | H102: 0.201 | L102: Digital Turnover Market Share - SportsBet
B104: Grossed Up Market Size | L104: Grossed Up Market Size
B105: Digital Turnover Market Share - Tabcorp | G105: =G99/G102 -> 49223.35 | H105: =H99/H102 -> 46102.985 | L105: Digital Turnover Market Share - Tabcorp
B107: Digital Turnover | L107: Digital Turnover
B108: Tabcorp - Digital | G108: =G99 -> 9697 | H108: =H99 -> 9266.7 | L108: Tabcorp - Digital | Q108: 9358.5 | R108: 9077.4
B109: SportsBet | C109: =SUMIF(SBET!$5:$5,C$2,SBET!$94:$94) -> 6768.5359 | D109: =SUMIF(SBET!$5:$5,D$2,SBET!$94:$94) -> 9987.8237 | E109: =SUMIF(SBET!$5:$5,E$2,SBET!$94:$94) -> 13458.98 | F109: =SUMIF(SBET!$5:$5,F$2,SBET!$94:$94) -> 19822.382 | G109: =SUMIF(SBET!$5:$5,G$2,SBET!$94:$94) -> 21875.71 | H109: =SUMIF(SBET!$5:$5,H$2,SBET!$94:$94) -> 19710.003 | L109: SportsBet | M109: =SUMIF(SBET!$6:$6,M$2,SBET!$94:$94) -> 7691.7477 | N109: =SUMIF(SBET!$6:$6,N$2,SBET!$94:$94) -> 12392.253 | O109: =SUMIF(SBET!$6:$6,O$2,SBET!$94:$94) -> 17953.673 | P109: =SUMIF(SBET!$6:$6,P$2,SBET!$94:$94) -> 21485.298 | Q109: =SUMIF(SBET!$6:$6,Q$2,SBET!$94:$94) -> 20063.341 | R109: =SUMIF(SBET!$6:$6,R$2,SBET!$94:$94) -> 17210.081
B110: LadBrokes | L110: LadBrokes
B111: Bet365 | L111: Bet365
B112: PointsBet | E112: =SUMIF(PBH!$5:$5,E$2,PBH!$12:$12) -> 830.5 | F112: =SUMIF(PBH!$5:$5,F$2,PBH!$12:$12) -> 1989 | G112: =SUMIF(PBH!$5:$5,G$2,PBH!$12:$12) -> 2536.4 | H112: =SUMIF(PBH!$5:$5,H$2,PBH!$12:$12) -> 2632.5 | L112: PointsBet | O112: =SUMIF(PBH!$6:$6,O$2,PBH!$12:$12) -> 1552.3 | P112: =SUMIF(PBH!$6:$6,P$2,PBH!$12:$12) -> 2276.4 | Q112: =SUMIF(PBH!$6:$6,Q$2,PBH!$12:$12) -> 2728.4 | R112: =SUMIF(PBH!$6:$6,R$2,PBH!$12:$12) -> 2550.6
B113: BlueBet | F113: =SUMIF('BBET + BetR'!$5:$5,F$2,'BBET + BetR'!$12:$12) -> 344.7 | G113: =SUMIF('BBET + BetR'!$5:$5,G$2,'BBET + BetR'!$12:$12) -> 511.9 | H113: =SUMIF('BBET + BetR'!$5:$5,H$2,'BBET + BetR'!$12:$12) -> 529.8 | L113: BlueBet | P113: =SUMIF('BBET + BetR'!$6:$6,P$2,'BBET + BetR'!$12:$12) -> 444.5 | Q113: =SUMIF('BBET + BetR'!$6:$6,Q$2,'BBET + BetR'!$12:$12) -> 526.5 | R113: =SUMIF('BBET + BetR'!$6:$6,R$2,'BBET + BetR'!$12:$12) -> 549.4
B114: Other - Balancing | G114: =G115-SUM(G108:G113) -> 14602.341 | H114: =H115-SUM(H108:H113) -> 13963.982 | L114: Other - Balancing
B115: Digital Market | G115: =G105 -> 49223.35 | H115: =H105 -> 46102.985 | L115: Digital Market
B117: Share
B118: Tabcorp - Digital | G118: =G108/G$115 -> 0.197 | H118: =H108/H$115 -> 0.201
B119: SportsBet | G119: =G109/G$115 -> 0.44441732 | H119: =H109/H$115 -> 0.4275212
B120: LadBrokes
B121: Bet365
B122: PointsBet | G122: =G112/G$115 -> 0.05152839 | H122: =H112/H$115 -> 0.057100424
B123: BlueBet | G123: =G113/G$115 -> 0.010399536 | H123: =H113/H$115 -> 0.011491664
B124: Other - Balancing | G124: =G114/G$115 -> 0.29665475 | H124: =H114/H$115 -> 0.30288672
B126: RACING AUSTRALIA ANNAUL REPORT
B127: Total Racing | C127: 28088.42 | D127: 29923.3 | E127: 31533.18 | F127: 43302.08
B128: Sports Betting | C128: 11230.49 | D128: 12359.03 | E128: 10160.39 | F128: 16602.99
...

Sheet MS
D3: CY18 | E3: CY19 | F3: CY20 | G3: CY21 | H3: CY22 | I3: CY23 | J3: CY24 | K3: CY25
C4: Tabcorp | H4: 0.25632061 | I4: 0.23408968 | J4: 0.22810944 | K4: 0.21703483
C5: SportsBet | F5: 0.46 | G5: 0.5 | H5: 0.48 | I5: 0.4592125 | J5: 0.43789205 | K5: 0.41885915
C6: LadBrokes | F6: 0.19900488 | G6: 0.17669028 | H6: 0.19564741 | I6: 0.17616272 | J6: 0.17582356 | K6: 0.16387344
C7: Bet365 | F7: 0.052961738 | G7: 0.042067375 | H7: 0.043030651 | I7: 0.054757013 | J7: 0.060609304 | K7: 0.05856365
C8: PointsBet | F8: 0.036955033 | G8: 0.039710558 | H8: 0.045470721 | I8: 0.045861269 | J8: 0.049291853 | K8: 0.049029077
C9: BlueBet | G9: 0.0099066508 | H9: 0.011373025 | I9: 0.012084214 | J9: 0.0068760064 | K9: 0
C10: BetR | G10: 0 | H10: 0 | I10: 0.017832607 | J10: 0.024438818 | K10: 0.031624371
C11: Dabble | G11: 0 | H11: 0 | I11: 0 | J11: 0.016958969 | K11: 0.030192505
C12: Other | K12: 0.030822974
C17: Other | D17: 0.030192505
C18: Dabble | D18: 0.030192505
C19: betr | D19: 0.031624371
C20: PointsBet | D20: 0.049029077
C21: bet365 | D21: 0.05856365
C22: Entain | D22: 0.16387344
C23: Tabcorp | D23: 0.21703483
C24: Sportsbet | D24: 0.41885915
H38: ~

Sheet SBET QTR
AN2: X
D3: =IF(MONTH(D13)>6,RIGHT(YEAR(D13),2)+1,RIGHT(YEAR(D13),2)) -> 17 | E3: =IF(MONTH(E13)>6,RIGHT(YEAR(E13),2)+1,RIGHT(YEAR(E13),2)) -> 18 | F3: =IF(MONTH(F13)>6,RIGHT(YEAR(F13),2)+1,RIGHT(YEAR(F13),2)) -> 18 | G3: =IF(MONTH(G13)>6,RIGHT(YEAR(G13),2)+1,RIGHT(YEAR(G13),2)) -> 18 | H3: =IF(MONTH(H13)>6,RIGHT(YEAR(H13),2)+1,RIGHT(YEAR(H13),2)) -> 18 | I3: =IF(MONTH(I13)>6,RIGHT(YEAR(I13),2)+1,RIGHT(YEAR(I13),2)) -> 19 | J3: =IF(MONTH(J13)>6,RIGHT(YEAR(J13),2)+1,RIGHT(YEAR(J13),2)) -> 19 | K3: =IF(MONTH(K13)>6,RIGHT(YEAR(K13),2)+1,RIGHT(YEAR(K13),2)) -> 19 | ... AN3: =IF(MONTH(AN13)>6,RIGHT(YEAR(AN13),2)+1,RIGHT(YEAR(AN13),2)) -> 26
D4: =RIGHT(YEAR(D$13),2) -> 17 | E4: =RIGHT(YEAR(E$13),2) -> 17 | F4: =RIGHT(YEAR(F$13),2) -> 17 | G4: =RIGHT(YEAR(G$13),2) -> 18 | H4: =RIGHT(YEAR(H$13),2) -> 18 | I4: =RIGHT(YEAR(I$13),2) -> 18 | J4: =RIGHT(YEAR(J$13),2) -> 18 | K4: =RIGHT(YEAR(K$13),2) -> 19 | ... AN4: =RIGHT(YEAR(AN$13),2) -> 26
D5: ="FY"&TEXT(D$3,"00") -> FY17 | E5: ="FY"&TEXT(E$3,"00") -> FY18 | F5: ="FY"&TEXT(F$3,"00") -> FY18 | G5: ="FY"&TEXT(G$3,"00") -> FY18 | H5: ="FY"&TEXT(H$3,"00") -> FY18 | I5: ="FY"&TEXT(I$3,"00") -> FY19 | J5: ="FY"&TEXT(J$3,"00") -> FY19 | K5: ="FY"&TEXT(K$3,"00") -> FY19 | ... AN5: ="FY"&TEXT(AN$3,"00") -> FY26
D6: ="CY"&TEXT(D$4,"00") -> CY17 | E6: ="CY"&TEXT(E$4,"00") -> CY17 | F6: ="CY"&TEXT(F$4,"00") -> CY17 | G6: ="CY"&TEXT(G$4,"00") -> CY18 | H6: ="CY"&TEXT(H$4,"00") -> CY18 | I6: ="CY"&TEXT(I$4,"00") -> CY18 | J6: ="CY"&TEXT(J$4,"00") -> CY18 | K6: ="CY"&TEXT(K$4,"00") -> CY19 | ... AN6: ="CY"&TEXT(AN$4,"00") -> CY26
D7: =D13-EOMONTH(D13,-3) -> 91 | E7: =E13-EOMONTH(E13,-3) -> 92 | F7: =F13-EOMONTH(F13,-3) -> 92 | G7: =G13-EOMONTH(G13,-3) -> 90 | H7: =H13-EOMONTH(H13,-3) -> 91 | I7: =I13-EOMONTH(I13,-3) -> 92 | J7: =J13-EOMONTH(J13,-3) -> 92 | K7: =K13-EOMONTH(K13,-3) -> 90 | ... AN7: =AN13-EOMONTH(AN13,-3) -> 91
B9: SPORTSBET FY | D9: ="FY"&D4 -> FY17 | E9: ="FY"&E4 -> FY17 | F9: ="FY"&F4 -> FY17 | G9: ="FY"&G4 -> FY18 | H9: ="FY"&H4 -> FY18 | I9: ="FY"&I4 -> FY18 | J9: ="FY"&J4 -> FY18 | K9: ="FY"&K4 -> FY19 | ... AN9: ="FY"&AN4 -> FY26
E11: 1H18 | F11: 1H18 | G11: 2H18 | H11: 2H18 | I11: 1H19 | J11: 1H19 | K11: 2H19 | L11: 2H19 | M11: 1H20 | N11: 1H20 | O11: 2H20 | P11: 2H20 | Q11: 1H21 | R11: 1H21 | S11: 2H21 | T11: 2H21 | U11: 1H22 | V11: 1H22 | W11: 2H22 | X11: 2H22 | Y11: 1H23 | Z11: 1H23 | AA11: 2H23 | AB11: 2H23 | AC11: 1H24 | AD11: 1H24 | AE11: 2H24 | AF11: 2H24 | AG11: 1H25 | AH11: 1H25 | AI11: 2H25 | AJ11: 2H25 | AK11: 1H26 | AL11: 1H26 | AM11: 2H26 | AN11: 2H26
C12: Units | D12: 4Q17 | E12: 1Q18 | F12: 2Q18 | G12: 3Q18 | H12: 4Q18 | I12: 1Q19 | J12: 2Q19 | K12: 3Q19 | L12: 4Q19 | M12: 1Q20 | N12: 2Q20 | O12: 3Q20 | P12: 4Q20 | Q12: 1Q21 | R12: 2Q21 | S12: 3Q21 | T12: 4Q21 | U12: 1Q22 | V12: 2Q22 | W12: 3Q22 | X12: 4Q22 | Y12: 1Q23 | Z12: 2Q23 | AA12: 3Q23 | AB12: 4Q23 | AC12: 1Q24 | AD12: 2Q24 | AE12: 3Q24 | AF12: 4Q24 | AG12: 1Q25 | AH12: 2Q25 | AI12: 3Q25 | AJ12: 4Q25 | AK12: 1Q26 | AL12: 2Q26 | AM12: 3Q26 | AN12: 4Q26
D13: 42916 | E13: =EOMONTH( D13, 3) -> 43008 | F13: =EOMONTH( E13, 3) -> 43100 | G13: =EOMONTH( F13, 3) -> 43190 | H13: =EOMONTH( G13, 3) -> 43281 | I13: =EOMONTH( H13, 3) -> 43373 | J13: =EOMONTH( I13, 3) -> 43465 | K13: =EOMONTH( J13, 3) -> 43555 | L13: =EOMONTH( K13, 3) -> 43646 | ... AN13: =EOMONTH( AM13, 3) -> 46203
B15: US | AM15: FY24 (june)
B16: Turnover | C16: US$m | S16: 3379.2051 | T16: 3561.3984 | U16: 4581.0703 | V16: 4562.7286 | W16: 3386.8935 | X16: 3377.2182 | Y16: 3376.7265 | Z16: 3766.7405 | AA16: 3142.8397 | AB16: 2959.4014 | AC16: 2927.6763 | AD16: 3021 | AE16: 2546.2987 | AF16: 2726 | AG16: 2684 | AH16: 2857 | AK16: =AG16*(1+AK17) -> 2549.8 | AM16: =SUM(AC16:AF16) -> 11220.975
B17: Growth | C17: % | AK17: -0.05
B19: Net Revenue | C19: US$m | S19: 384.78953 | T19: 428.97687 | U19: 513.39045 | V19: 454.57203 | W19: 390.05293 | X19: 404.45265 | Y19: 373.8983 | Z19: 389.23181 | AA19: 350.50448 | AB19: 389.47452 | AC19: 331.83749 | AD19: 375 | AE19: 328.83894 | AF19: 349 | AG19: 371 | AH19: 346 | AI19: =AE19*(1+AI21) -> 269.64793 | AM19: =SUM(AC19:AF19) -> 1384.6764
B20: Net Margin | C20: % | S20: 0.11386984 | T20: 0.12045181 | U20: 0.1120678 | V20: 0.099627235 | W20: 0.1151654 | X20: 0.11975911 | Y20: 0.11072804 | Z20: 0.10333385 | AA20: 0.11152477 | AB20: 0.13160585 | AC20: 0.11334501 | AD20: 0.12431417 | AE20: 0.1291439 | AF20: 0.128 | AG20: 0.138 | AH20: 0.121
B21: Growth | C21: % | AI21: -0.18
B24: Adjusted EBITDA | C24: US$m | S24: 148.73192 | T24: 131.08437 | U24: 185.05653 | V24: 140.2235 | W24: 141.00243 | X24: 143.76083 | Y24: 98.6097 | Z24: 101.70612 | AA24: 84.976508 | AB24: 107.59599 | AC24: 63.002567 | AD24: 100 | AE24: 82.602199 | AF24: 74 | AG24: 72 | AH24: 66
B25: Margin | C25: US$m | S25: =S24/S19 -> 0.38652798 | T25: =T24/T19 -> 0.30557446 | U25: =U24/U19 -> 0.36045962 | V25: =V24/V19 -> 0.30847366 | W25: =W24/W19 -> 0.36149562 | X25: =X24/X19 -> 0.35544538 | Y25: =Y24/Y19 -> 0.26373402 | Z25: =Z24/Z19 -> 0.26129961 | ... AH25: =AH24/AH19 -> 0.19075145
W26: =W24/S24-1 -> -0.0519693 | X26: =X24/T24-1 -> 0.096704534 | Y26: =Y24/U24-1 -> -0.46713741 | Z26: =Z24/V24-1 -> -0.27468562 | AA26: =AA24/W24-1 -> -0.3973401 | AB26: =AB24/X24-1 -> -0.25156252 | AC26: =AC24/Y24-1 -> -0.36109158 | AD26: =AD24/Z24-1 -> -0.016775004 | ... AH26: =AH24/AD24-1 -> -0.34
B27: Other
B28: Cost of sales | S28: 177.11938 | T28: 202.11462 | U28: 235.27885 | V28: 240.03077 | W28: 184.24373 | X28: 185.26411 | Y28: 189.06075 | Z28: 195.34253 | AA28: 186.73942 | AB28: 198.03909 | AC28: 181.96593 | AD28: 197 | AE28: 173.72262 | AF28: 192 | AG28: 207 | AH28: 190
B29: Technology, research and development expenses | S29: 7.3864106 | T29: 8.4393985 | U29: 6.5744555 | V29: 8.6009782 | W29: 6.3170277 | X29: 8.2596997 | Y29: 6.7157571 | Z29: 6.9343037 | AA29: 9.7940145 | AB29: 6.2655882 | AC29: 9.9015001 | AD29: 6 | AE29: 8.7680674 | AF29: 9 | AG29: 8 | AH29: 8
B30: Sales & marketing expenses | S30: 41.294453 | T30: 68.559888 | U30: 65.453073 | V30: 56.521443 | W30: 46.312131 | X30: 53.674191 | Y30: 62.552075 | Z30: 66.334489 | AA30: 52.495681 | AB30: 56.614528 | AC30: 58.332554 | AD30: 58 | AE30: 46.908244 | AF30: 56 | AG30: 60 | AH30: 60
B31: General and administrative expenses | S31: 10.257372 | T31: 18.778597 | U31: 21.027545 | V31: 9.1953434 | W31: 12.177611 | X31: 13.493821 | Y31: 16.960017 | Z31: 18.914364 | AA31: 16.498849 | AB31: 20.959324 | AC31: 18.634935 | AD31: 14 | AE31: 16.837813 | AF31: 18 | AG31: 24 | AH31: 21
B33: Check | S33: =S19-SUM(S28:S31)-S24 -> 0 | T33: =T19-SUM(T28:T31)-T24 -> 0 | U33: =U19-SUM(U28:U31)-U24 -> 0 | V33: =V19-SUM(V28:V31)-V24 -> 0 | W33: =W19-SUM(W28:W31)-W24 -> 0 | X33: =X19-SUM(X28:X31)-X24 -> 0 | Y33: =Y19-SUM(Y28:Y31)-Y24 -> 0 | Z33: =Z19-SUM(Z28:Z31)-Z24 -> 0 | ... AH33: =AH19-SUM(AH28:AH31)-AH24 -> 1
B35: Average Monthly Players | S35: 830.616 | T35: 982.084 | U35: 1086 | V35: 1133 | W35: 914.57833 | X35: 1072.2427 | Y35: 1100.187 | Z35: 1274.6497 | AA35: 992.86633 | AB35: 1139.0143 | AC35: 1123.9953 | AD35: 1189.3203 | AE35: 990.56833 | AF35: 1199 | AG35: 1197 | AH35: 1275
S37: =S28/S16 -> 0.05241451 | T37: =T28/T16 -> 0.056751476 | U37: =U28/U16 -> 0.051358927 | V37: =V28/V16 -> 0.052606848 | W37: =W28/W16 -> 0.054399034 | X37: =X28/X16 -> 0.054857016 | Y37: =Y28/Y16 -> 0.055989357 | Z37: =Z28/Z16 -> 0.051859832 | ... AH37: =AH28/AH16 -> 0.066503325
S38: =S28/S19 -> 0.46030196 | T38: =T28/T19 -> 0.47115504 | U38: =U28/U19 -> 0.45828444 | V38: =V28/V19 -> 0.52803682 | W38: =W28/W19 -> 0.47235572 | X38: =X28/X19 -> 0.45806131 | Y38: =Y28/Y19 -> 0.50564752 | Z38: =Z28/Z19 -> 0.50186682 | ... AH38: =AH28/AH19 -> 0.54913295
S40: =S30/S16 -> 0.012220168 | T40: =T30/T16 -> 0.019250834 | U40: =U30/U16 -> 0.014287725 | V40: =V30/V16 -> 0.012387641 | W40: =W30/W16 -> 0.013673926 | X40: =X30/X16 -> 0.015893018 | Y40: =Y30/Y16 -> 0.018524472 | Z40: =Z30/Z16 -> 0.017610581 | ... AH40: =AH30/AH16 -> 0.02100105
S41: =S30/S19 -> 0.10731699 | T41: =T30/T19 -> 0.15982187 | U41: =U30/U19 -> 0.1274918 | V41: =V30/V19 -> 0.1243399 | W41: =W30/W19 -> 0.11873294 | X41: =X30/X19 -> 0.13270822 | Y41: =Y30/Y19 -> 0.16729703 | Z41: =Z30/Z19 -> 0.17042412 | ... AH41: =AH30/AH19 -> 0.1734104
S42: =S30/S24 -> 0.27764351 | T42: =T30/T24 -> 0.52302105 | U42: =U30/U24 -> 0.35369232 | V42: =V30/V24 -> 0.4030811 | W42: =W30/W24 -> 0.32844918 | X42: =X30/X24 -> 0.37335755 | Y42: =Y30/Y24 -> 0.63433998 | Z42: =Z30/Z24 -> 0.65221728 | ... AH42: =AH30/AH24 -> 0.90909091
B45: UK | AG45: =AG37/S37-1 -> 0.47141882 | AH45: =AH37/T37-1 -> 0.17183428
B46: Turnover | C46: £m | O46: 1545 | P46: =3723-O46 -> 2178 | Q46: 3003 | R46: =9713-SUM(O46:Q46) -> 2987 | S46: 2451 | T46: =5000-S46 -> 2549 | U46: 3323 | V46: =11702-SUM(S46:U46) -> 3379 | W46: =W48/W49 -> 2530.4348 | X46: =5209-W46 -> 2678.5652 | Y46: =Y48/Y49 -> 2873.8739 | Z46: =11296-SUM(W46:Y46) -> 3213.1261 | AA46: =AA48/AA49 -> 2580.3571 | AB46: =4953-AA46 -> 2372.6429 | AC46: =AC48/AC49 -> 2318.5841 | AD46: =12051/(1447/1167)-SUM(AA46:AC46) -> 2447.5016
B48: Net Revenue | C48: £m | O48: 161 | P48: =435-O48 -> 274 | Q48: 320 | R48: =1075-SUM(O48:Q48) -> 320 | S48: 279 | T48: =585-S48 -> 306 | U48: 370 | V48: =1294-SUM(S48:U48) -> 339 | W48: 291 | X48: =612-W48 -> 321 | Y48: 319 | Z48: 332 | AA48: 289 | AB48: =601-AA48 -> 312 | AC48: 262 | AD48: 304
B49: Net Margin | C49: % | O49: 0.104 | P49: =P48/P46 -> 0.12580349 | Q49: 0.107 | R49: =R48/R46 -> 0.1071309 | S49: 0.114 | T49: =T48/T46 -> 0.12004708 | U49: 0.111 | V49: =V48/V46 -> 0.10032554 | W49: 0.115 | X49: =X48/X46 -> 0.11984028 | Y49: 0.111 | Z49: =Z48/Z46 -> 0.10332616 | AA49: 0.112 | AB49: =AB48/AB46 -> 0.13149893 | AC49: 0.113 | AD49: =AD48/AD46 -> 0.12420829
B51: FX
B52: AUD/GBP | C52: X
B53: AUD/USD | C53: X | O53: 0.51400769 | P53: 0.52988462 | Q53: 0.55365303 | R53: 0.55347879 | S53: 0.56027656 | T53: 0.55070769 | U53: 0.53319394 | V53: 0.54052879 | W53: 0.5405125 | X53: 0.56850769 | Y53: 0.58086212 | Z53: 0.55979385 | AA53: 0.56243692 | AB53: 0.53351692 | AC53: 0.51697231 | AD53: 0.52443692 | AE53: 0.51863385 | AF53: 0.52217121 | AG53: 0.5151303 | AH53: 0.50898485
G54: 0.78601577 | H54: 0.75657031 | I54: 0.73147023 | J54: 0.71691333 | K54: 0.71251328 | L54: 0.70020331 | M54: 0.68542265 | N54: 0.68374765 | O54: 0.65818446 | P54: 0.65791254 | Q54: 0.71519015 | R54: 0.73181273 | S54: 0.77268578 | T54: 0.76989738 | U54: 0.73472795 | V54: 0.72868886 | W54: 0.72444102 | X54: 0.714331 | Y54: 0.68321447 | Z54: 0.65743908 | AA54: 0.68357662 | AB54: 0.66801823 | AC54: 0.65461731 | AD54: 0.65131792 | AE54: 0.65772877 | AF54: 0.65907154 | AG54: 0.66981197 | AH54: 0.65235833 | AI54: 0.62766781 | AJ54: 0.64098477 | AK54: 0.65418364 | AL54: 0.65667879 | AM54: 0.69517305
B55: AUS
B56: Turnover | C56: A$m | O56: =O46/O$53 -> 3005.7916 | P56: =P46/P$53 -> 4110.3288 | Q56: =Q46/Q$53 -> 5423.9746 | R56: =R46/R$53 -> 5396.7741 | S56: =S16/S$54 -> 4373.3237 | T56: =T16/T$54 -> 4625.8092 | U56: =U16/U$54 -> 6235.0564 | V56: =V16/V$54 -> 6261.5594 | W56: =W16/W$54 -> 4675.1818 | X56: =X16/X$54 -> 4727.8058 | Y56: =Y16/Y$54 -> 4942.4107 | Z56: =Z16/Z$54 -> 5729.4138 | ... AH56: =AH16/AH$54 -> 4379.4949 | AJ56: =AF56*(1+AJ57) -> 4012.0379 | AM56: =SUM(AC56:AF56) -> 17118.108
B57: Growth | C57: % | AJ57: -0.03
B59: Net Revenue | C59: A$m | O59: =O48/O$53 -> 313.22488 | P59: =P48/P$53 -> 517.09371 | Q59: =Q48/Q$53 -> 577.97932 | R59: =R48/R$53 -> 578.16127 | S59: =S19/S$54 -> 497.98966 | T59: =T19/T$54 -> 557.18708 | U59: =U19/U$54 -> 698.74904 | V59: =V19/V$54 -> 623.82185 | W59: =W19/W$54 -> 538.41917 | X59: =X19/X$54 -> 566.19782 | Y59: =Y19/Y$54 -> 547.26343 | Z59: =Z19/Z$54 -> 592.0424 | ... AH59: =AH19/AH$54 -> 530.38335 | AJ59: =AF59*(1+AJ61) -> 561.30477 | AM59: =SUM(AC59:AF59) -> 2112.1681
B60: Net Margin | C60: % | O60: =O59/O56 -> 0.10420712 | P60: =P59/P56 -> 0.12580349 | Q60: =Q59/Q56 -> 0.10656011 | R60: =R59/R56 -> 0.1071309 | S60: =S59/S56 -> 0.11386984 | T60: =T59/T56 -> 0.12045181 | U60: =U59/U56 -> 0.1120678 | V60: =V59/V56 -> 0.099627235 | ... AH60: =AH59/AH56 -> 0.12110606
B61: Growth | C61: % | AJ61: 0.06
B64: Adjusted EBITDA | S64: =S24/S$54 -> 192.48694 | T64: =T24/T$54 -> 170.26214 | U64: =U24/U$54 -> 251.87081 | V64: =V24/V$54 -> 192.43261 | W64: =W24/W$54 -> 194.63617 | X64: =X24/X$54 -> 201.2524 | Y64: =Y24/Y$54 -> 144.33198 | Z64: =Z24/Z$54 -> 154.70045 | ... AH64: =AH24/AH$54 -> 101.17139 | AM64: =SUM(AC64:AF64) -> 487.64439
B68: Cost of sales | S68: =S28/S$54 -> 229.22562 | T68: =T28/T$54 -> 262.5215 | U68: =U28/U$54 -> 320.22581 | V68: =V28/V$54 -> 329.4009 | W68: =W28/W$54 -> 254.32538 | X68: =X28/X$54 -> 259.35332 | Y68: =Y28/Y$54 -> 276.7224 | Z68: =Z28/Z$54 -> 297.12644 | ... AH68: =AH28/AH$54 -> 291.25097 | AM68: =SUM(AC68:AF68) -> 1135.8806
B69: Technology, research and development expenses | S69: =S29/S$54 -> 9.5593976 | T69: =T29/T$54 -> 10.961719 | U69: =U29/U$54 -> 8.9481495 | V69: =V29/V$54 -> 11.803362 | W69: =W29/W$54 -> 8.7198648 | X69: =X29/X$54 -> 11.562846 | Y69: =Y29/Y$54 -> 9.8296471 | Z69: =Z29/Z$54 -> 10.547447 | ... AH69: =AH29/AH$54 -> 12.263199 | AM69: =SUM(AC69:AF69) -> 51.324122
B70: Sales & marketing expenses | S70: =S30/S$54 -> 53.44275 | T70: =T30/T$54 -> 89.050683 | U70: =U30/U$54 -> 89.084773 | V70: =V30/V$54 -> 77.565948 | W70: =W30/W$54 -> 63.928091 | X70: =X30/X$54 -> 75.139103 | Y70: =Y30/Y$54 -> 91.555548 | Z70: =Z30/Z$54 -> 100.89831 | ... AH70: =AH30/AH$54 -> 91.973992 | AM70: =SUM(AC70:AF70) -> 334.44615
B71: General and administrative expenses | S71: =S31/S$54 -> 13.274958 | T71: =T31/T$54 -> 24.391038 | U71: =U31/U$54 -> 28.619497 | V71: =V31/V$54 -> 12.619026 | W71: =W31/W$54 -> 16.809665 | X71: =X31/X$54 -> 18.890152 | Y71: =Y31/Y$54 -> 24.823855 | Z71: =Z31/Z$54 -> 28.769759 | ... AH71: =AH31/AH$54 -> 32.190897 | AM71: =SUM(AC71:AF71) -> 102.87287
B73: Cost of sales | S73: =S68/S$59 -> 0.46030196 | T73: =T68/T$59 -> 0.47115504 | U73: =U68/U$59 -> 0.45828444 | V73: =V68/V$59 -> 0.52803682 | W73: =W68/W$59 -> 0.47235572 | X73: =X68/X$59 -> 0.45806131 | Y73: =Y68/Y$59 -> 0.50564752 | Z73: =Z68/Z$59 -> 0.50186682 | ... AH73: =AH68/AH$59 -> 0.54913295
B74: Technology, research and development expenses | S74: =S69/S$59 -> 0.019195976 | T74: =T69/T$59 -> 0.019673318 | U74: =U69/U$59 -> 0.012805956 | V74: =V69/V$59 -> 0.018921046 | W74: =W69/W$59 -> 0.016195309 | X74: =X69/X$59 -> 0.02042192 | Y74: =Y69/Y$59 -> 0.017961454 | Z74: =Z69/Z$59 -> 0.017815357 | ... AH74: =AH69/AH$59 -> 0.023121387
B75: Sales & marketing expenses | S75: =S70/S$59 -> 0.10731699 | T75: =T70/T$59 -> 0.15982187 | U75: =U70/U$59 -> 0.1274918 | V75: =V70/V$59 -> 0.1243399 | W75: =W70/W$59 -> 0.11873294 | X75: =X70/X$59 -> 0.13270822 | Y75: =Y70/Y$59 -> 0.16729703 | Z75: =Z70/Z$59 -> 0.17042412 | ... AH75: =AH70/AH$59 -> 0.1734104
B76: General and administrative expenses | S76: =S71/S$59 -> 0.026657096 | T76: =T71/T$59 -> 0.043775313 | U76: =U71/U$59 -> 0.040958192 | V76: =V71/V$59 -> 0.020228573 | W76: =W71/W$59 -> 0.031220406 | X76: =X71/X$59 -> 0.033363167 | Y76: =Y71/Y$59 -> 0.045359974 | Z76: =Z71/Z$59 -> 0.048594086 | ... AH76: =AH71/AH$59 -> 0.060693642
B78: Cost of sales | S78: =S68/S$56 -> 0.05241451 | T78: =T68/T$56 -> 0.056751476 | U78: =U68/U$56 -> 0.051358927 | V78: =V68/V$56 -> 0.052606848 | W78: =W68/W$56 -> 0.054399034 | X78: =X68/X$56 -> 0.054857016 | Y78: =Y68/Y$56 -> 0.055989357 | Z78: =Z68/Z$56 -> 0.051859832 | ... AH78: =AH68/AH$56 -> 0.066503325
B79: Technology, research and development expenses | S79: =S69/S$56 -> 0.0021858427 | T79: =T69/T$56 -> 0.0023696867 | U79: =U69/U$56 -> 0.0014351353 | V79: =V69/V$56 -> 0.0018850515 | W79: =W69/W$56 -> 0.0018651392 | X79: =X69/X$56 -> 0.002445711 | Y79: =Y69/Y$56 -> 0.0019888366 | Z79: =Z69/Z$56 -> 0.0018409295 | ... AH79: =AH69/AH$56 -> 0.00280014
B80: Sales & marketing expenses | S80: =S70/S$56 -> 0.012220168 | T80: =T70/T$56 -> 0.019250834 | U80: =U70/U$56 -> 0.014287725 | V80: =V70/V$56 -> 0.012387641 | W80: =W70/W$56 -> 0.013673926 | X80: =X70/X$56 -> 0.015893018 | Y80: =Y70/Y$56 -> 0.018524472 | Z80: =Z70/Z$56 -> 0.017610581 | ... AH80: =AH70/AH$56 -> 0.02100105
B81: General and administrative expenses | S81: =S71/S$56 -> 0.0030354392 | T81: =T71/T$56 -> 0.0052728155 | U81: =U71/U$56 -> 0.0045900944 | V81: =V71/V$56 -> 0.0020153168 | W81: =W71/W$56 -> 0.0035955104 | X81: =X71/X$56 -> 0.0039955432 | Y81: =Y71/Y$56 -> 0.0050226209 | Z81: =Z71/Z$56 -> 0.0050214141 | ... AH81: =AH71/AH$56 -> 0.0073503675
S83: =S69+S71 -> 22.834356 | T83: =T69+T71 -> 35.352757 | U83: =U69+U71 -> 37.567647 | V83: =V69+V71 -> 24.422387 | W83: =W69+W71 -> 25.52953 | X83: =X69+X71 -> 30.452999 | Y83: =Y69+Y71 -> 34.653502 | Z83: =Z69+Z71 -> 39.317206 | ... AH83: =AH69+AH71 -> 44.454096

Sheet SBET
D3: =IF(MONTH(D11)>6,RIGHT(YEAR(D11),2)+1,RIGHT(YEAR(D11),2)) -> 17 | E3: =IF(MONTH(E11)>6,RIGHT(YEAR(E11),2)+1,RIGHT(YEAR(E11),2)) -> 18 | F3: =IF(MONTH(F11)>6,RIGHT(YEAR(F11),2)+1,RIGHT(YEAR(F11),2)) -> 18 | G3: =IF(MONTH(G11)>6,RIGHT(YEAR(G11),2)+1,RIGHT(YEAR(G11),2)) -> 19 | H3: =IF(MONTH(H11)>6,RIGHT(YEAR(H11),2)+1,RIGHT(YEAR(H11),2)) -> 19 | I3: =IF(MONTH(I11)>6,RIGHT(YEAR(I11),2)+1,RIGHT(YEAR(I11),2)) -> 20 | J3: =IF(MONTH(J11)>6,RIGHT(YEAR(J11),2)+1,RIGHT(YEAR(J11),2)) -> 20 | K3: =IF(MONTH(K11)>6,RIGHT(YEAR(K11),2)+1,RIGHT(YEAR(K11),2)) -> 21 | ... U3: =IF(MONTH(U11)>6,RIGHT(YEAR(U11),2)+1,RIGHT(YEAR(U11),2)) -> 26
D4: =RIGHT(YEAR(D$11),2) -> 17 | E4: =RIGHT(YEAR(E$11),2) -> 17 | F4: =RIGHT(YEAR(F$11),2) -> 18 | G4: =RIGHT(YEAR(G$11),2) -> 18 | H4: =RIGHT(YEAR(H$11),2) -> 19 | I4: =RIGHT(YEAR(I$11),2) -> 19 | J4: =RIGHT(YEAR(J$11),2) -> 20 | K4: =RIGHT(YEAR(K$11),2) -> 20 | ... U4: =RIGHT(YEAR(U$11),2) -> 25
D5: ="FY"&TEXT(D$3,"00") -> FY17 | E5: ="FY"&TEXT(E$3,"00") -> FY18 | F5: ="FY"&TEXT(F$3,"00") -> FY18 | G5: ="FY"&TEXT(G$3,"00") -> FY19 | H5: ="FY"&TEXT(H$3,"00") -> FY19 | I5: ="FY"&TEXT(I$3,"00") -> FY20 | J5: ="FY"&TEXT(J$3,"00") -> FY20 | K5: ="FY"&TEXT(K$3,"00") -> FY21 | ... U5: ="FY"&TEXT(U$3,"00") -> FY26
D6: ="CY"&TEXT(D$4,"00") -> CY17 | E6: ="CY"&TEXT(E$4,"00") -> CY17 | F6: ="CY"&TEXT(F$4,"00") -> CY18 | G6: ="CY"&TEXT(G$4,"00") -> CY18 | H6: ="CY"&TEXT(H$4,"00") -> CY19 | I6: ="CY"&TEXT(I$4,"00") -> CY19 | J6: ="CY"&TEXT(J$4,"00") -> CY20 | K6: ="CY"&TEXT(K$4,"00") -> CY20 | ... U6: ="CY"&TEXT(U$4,"00") -> CY25
D7: =D11-EOMONTH(D11,-6) -> 181 | E7: =E11-EOMONTH(E11,-6) -> 184 | F7: =F11-EOMONTH(F11,-6) -> 181 | G7: =G11-EOMONTH(G11,-6) -> 184 | H7: =H11-EOMONTH(H11,-6) -> 181 | I7: =I11-EOMONTH(I11,-6) -> 184 | J7: =J11-EOMONTH(J11,-6) -> 182 | K7: =K11-EOMONTH(K11,-6) -> 184 | ... U7: =U11-EOMONTH(U11,-6) -> 184
W8: https://www.flutter.com/media/entjjnsy/ppb-r-n-a-2017-180327.pdf | X8: https://www.flutter.com/media/ebldbz5p/annual-report-and-accounts-2018.pdf | Y8: https://www.flutter.com/media/jtzac4uu/2019-annual-report-28-02-20.pdf | Z8: https://www.flutter.com/media/3akfm0gk/annual-report-and-accounts-2020-1.pdf | AA8: https://www.flutter.com/media/dvvn0ith/flutter-entertainment-plc-annual-report-2021.pdf | AB8: https://www.flutter.com/media/pzuc0n0y/flutter-entertainment-plc-annual-report-accounts-2022.pdf | AC8: https://www.flutter.com/media/a0rj0ng5/flutter-entertainment-plc-annual-report-and-accounts-2023-10-k_updated.pdf
Z9: ID | AA9: https://www.flutter.com/media/otjhgrgn/sb-investor-day-presentation.pdf
G10: Pre BetEasy/BetFair | H10: Pro Forma | X10: Pre BetEasy/BetFair | Y10: Pro Forma
B11: Add SB Quarterly | D11: 42916 | E11: =EOMONTH(D11,6) -> 43100 | F11: =EOMONTH(E11,6) -> 43281 | G11: =EOMONTH(F11,6) -> 43465 | H11: =EOMONTH(G11,6) -> 43646 | I11: =EOMONTH(H11,6) -> 43830 | J11: =EOMONTH(I11,6) -> 44012 | K11: =EOMONTH(J11,6) -> 44196 | L11: =EOMONTH(K11,6) -> 44377 | ... U11: =EOMONTH(T11,6) -> 46022 | W11: 43100 | X11: =EOMONTH(W11,12) -> 43465 | Y11: =EOMONTH(X11,12) -> 43830 | Z11: =EOMONTH(Y11,12) -> 44196 | AA11: =EOMONTH(Z11,12) -> 44561 | AB11: =EOMONTH(AA11,12) -> 44926 | AC11: =EOMONTH(AB11,12) -> 45291 | AD11: =EOMONTH(AC11,12) -> 45657 | AE11: =EOMONTH(AD11,12) -> 46022
W12: CY17 | X12: CY18 | Y12: CY19 | Z12: CY20 | AA12: CY21 | AB12: CY22 | AC12: CY23 | AD12: CY24 | AE12: CY25
B14: FLUTTER HALFS | D14: 1H | E14: 2H | F14: 1H | G14: 2H | H14: 1H | I14: 2H | J14: 1H | K14: 2H | L14: 1H | M14: 2H | N14: 1H | O14: 2H | P14: 1H | Q14: 2H | R14: 1H | S14: 2H | T14: 1H | U14: 2H | W14: FY | X14: FY | Y14: FY | Z14: FY | AA14: FY | AB14: FY | AC14: FY | AD14: FY | AE14: FY
D15: 2017 | E15: 2017 | F15: 2018 | G15: 2018 | H15: 2019 | I15: 2019 | J15: 2020 | K15: 2020 | L15: 2021 | M15: 2021 | N15: 2022 | O15: 2022 | P15: 2023 | Q15: 2023 | R15: 2024 | S15: 2024 | T15: 2025 | U15: 2025 | W15: 2017 | X15: 2018 | Y15: 2019 | Z15: 2020 | AA15: 2021 | AB15: 2022 | AC15: 2023 | AD15: 2024 | AE15: 2025
B17: TABCORP HALFS
D18: =E14&RIGHT(E$15,2) -> 2H17 | E18: =F14&RIGHT(F$15,2) -> 1H18 | F18: =G14&RIGHT(G$15,2) -> 2H18 | G18: =H14&RIGHT(H$15,2) -> 1H19 | H18: =I14&RIGHT(I$15,2) -> 2H19 | I18: =J14&RIGHT(J$15,2) -> 1H20 | J18: =K14&RIGHT(K$15,2) -> 2H20 | K18: =L14&RIGHT(L$15,2) -> 1H21 | ... Q18: =R14&RIGHT(R$15,2) -> 1H24
B20: Headcount | AC20: 1129 | AD20: 1323 | AE20: 1164
B22: Market Share - SB Investor Day | K22: 0.426 | W22: 0.224 | X22: 0.278 | Y22: 0.303 | Z22: 0.403
B23: Market Share - Annual Reports | Y23: 0.43 | Z23: 0.46 | AA23: 0.5 | AB23: 0.48 | AC23: 0.45
B24: Market Share - Annual Reports pre Bet Easy | W24: 0.25 | X24: 0.26 | Y24: 0.27
B26: Sportsbook stakes | C26: US$m | AA26: 16084 | AB26: 13908 | AC26: 12050.556 | AD26: 10813 | AG26: -52m rev, -62m EBITDA
B27: Sportsbook net revenue margin | C27: % | AA27: 0.111 | AB27: 0.112 | AC27: 0.12010439 | AD27: 0.129
B28: Total revenue | C28: US$m | AA28: 1782 | AB28: 1558 | AC28: 1447 | AD28: 1397 | AE28: 1315
B29: Adjusted EBITDA | C29: US$m | AA29: 599 | AB29: 477 | AC29: 348 | AD29: 295 | AE29: =AD29-62 -> 233
B30: Adjusted EBITDA margin | C30: % | AA30: 0.33961189 | AB30: 0.31142011 | AC30: 0.247 | AD30: 0.211 | AE30: 0.211
B32: Sportsbook stakes | C32: £m | D32: 1935 | E32: =W32-D32 -> 1773 | F32: 2114 | G32: =X32-F32 -> 2194 | H32: 3312 | I32: =Y32-H32 -> 3439 | J32: 3723 | K32: =Z32-J32 -> 5990 | L32: 5000 | M32: =AA32-L32 -> 6702 | N32: 5209 | O32: =AB32-N32 -> 6087 | P32: 4953 | W32: 3708 | X32: 4308 | Y32: 6751 | Z32: 9713 | AA32: 11702 | AB32: 11296
B33: Sportsbook net revenue margin | C33: % | D33: 0.094 | E33: =E34/E32 -> 0.12521151 | F33: 0.098 | G33: =G34/G32 -> 0.089334549 | H33: 0.095 | I33: =I34/I32 -> 0.10671707 | J33: 0.117 | K33: =K34/K32 -> 0.10684474 | L33: 0.117 | M33: =M34/M32 -> 0.10578932 | N33: 0.118 | O33: =O34/O32 -> 0.10694924 | P33: 0.121 | W33: 0.109 | X33: 0.094 | Y33: 0.101 | Z33: 0.111 | AA33: 0.111 | AB33: 0.112
B34: Total revenue | C34: £m | D34: 182 | E34: =W34-D34 -> 222 | F34: 207 | G34: =X34-F34 -> 196 | H34: 314 | I34: =Y34-H34 -> 367 | J34: 435 | K34: =Z34-J34 -> 640 | L34: 585 | M34: =AA34-L34 -> 709 | N34: 612 | O34: =AB34-N34 -> 651 | P34: 601 | W34: 404 | X34: 403 | Y34: 681 | Z34: 1075 | AA34: 1294 | AB34: 1263
B35: Cost of sales | C35: £m | D35: -51 | E35: =W35-D35 -> -60 | F35: -83 | G35: =X35-F35 -> -38 | H35: -140 | I35: =Y35-H35 -> -159 | J35: -200 | K35: =Z35-J35 -> -320 | L35: -275 | M35: =AA35-L35 -> -361 | N35: -290 | O35: =AB35-N35 -> -345 | P35: -317 | W35: -111 | X35: -121 | Y35: -299 | Z35: -520 | AA35: -636 | AB35: -635
B36: Cost of sales as a % of net revenue | C36: % | D36: =-D35/D34 -> 0.28021978 | E36: =-E35/E34 -> 0.27027027 | F36: =-F35/F34 -> 0.40096618 | G36: =-G35/G34 -> 0.19387755 | H36: 0.445 | I36: =-I35/I34 -> 0.43324251 | J36: 0.459 | K36: =-K35/K34 -> 0.5 | L36: 0.47 | M36: =-M35/M34 -> 0.50916784 | N36: 0.473 | O36: =-O35/O34 -> 0.52995392 | P36: 0.528 | W36: =-W35/W34 -> 0.27475248 | X36: 0.301 | Y36: 0.439 | Z36: 0.484 | AA36: 0.492 | AB36: 0.503
B37: Gross profit | C37: £m | D37: 131 | E37: =W37-D37 -> 161 | F37: 124 | G37: =X37-F37 -> 158 | H37: 174 | I37: =Y37-H37 -> 208 | J37: 235 | K37: =Z37-J37 -> 320 | L37: 310 | M37: =AA37-L37 -> 348 | N37: 322 | O37: =AB37-N37 -> 306 | P37: 284 | W37: 292 | X37: 282 | Y37: 382 | Z37: 555 | AA37: 658 | AB37: 628
B38: Sales and marketing | C38: £m | D38: -40 | E38: =W38-D38 -> -42 | F38: -34 | G38: =X38-F38 -> -48 | H38: -56 | I38: =Y38-H38 -> -68 | J38: -59 | K38: =Z38-J38 -> -70 | L38: -59 | M38: =AA38-L38 -> -60 | N38: -54 | O38: =AB38-N38 -> -80 | P38: -64 | W38: -82 | X38: -82 | Y38: -124 | Z38: -129 | AA38: -119 | AB38: -134
B39: Contribution | C39: £m | D39: =D37+D38 -> 91 | E39: =W39-D39 -> 119 | F39: =F37+F38 -> 90 | G39: =X39-F39 -> 109 | H39: 118 | I39: =Y39-H39 -> 140 | J39: 176 | K39: =Z39-J39 -> 250 | L39: 252 | M39: =AA39-L39 -> 287 | N39: 269 | O39: =AB39-N39 -> 225 | P39: 219 | W39: =W37+W38 -> 210 | X39: 199 | Y39: 258 | Z39: 426 | AA39: 539 | AB39: 494
B40: Other operating costs | C40: £m | D40: =D41-D39 -> -22 | E40: =W40-D40 -> -49 | F40: =F41-F39 -> -21 | G40: =X40-F40 -> -41 | H40: -49 | I40: =Y40-H40 -> -47 | J40: -55 | K40: =Z40-J40 -> -53 | L40: -51 | M40: =AA40-L40 -> -51 | N40: -50 | O40: =AB40-N40 -> -54 | P40: -61 | W40: =W41-W39 -> -71 | X40: -62 | Y40: -96 | Z40: -108 | AA40: -102 | AB40: -104
B41: Adjusted EBITDA | C41: £m | D41: 69 | E41: =W41-D41 -> 70 | F41: 69 | G41: =X41-F41 -> 68 | H41: 69 | I41: =Y41-H41 -> 92 | J41: 121 | K41: =Z41-J41 -> 197 | L41: 201 | M41: =AA41-L41 -> 236 | N41: 219 | O41: =AB41-N41 -> 171 | P41: 158 | W41: 139 | X41: 137 | Y41: 161 | Z41: 318 | AA41: 437 | AB41: 390
B42: Adjusted EBITDA margin | C42: % | D42: =D41/D34 -> 0.37912088 | E42: =E41/E34 -> 0.31531532 | F42: =F41/F34 -> 0.33333333 | G42: =G41/G34 -> 0.34693878 | H42: 0.219 | I42: =I41/I34 -> 0.2506812 | J42: 0.279 | K42: =K41/K34 -> 0.3078125 | L42: 0.343 | M42: =M41/M34 -> 0.33286319 | N42: 0.358 | O42: =O41/O34 -> 0.26267281 | P42: 0.264 | W42: =W41/W34 -> 0.34405941 | X42: 0.34 | Y42: 0.237 | Z42: 0.296 | AA42: 0.337 | AB42: 0.309
B43: Depreciation and amortisation | C43: £m | D43: -8 | E43: =W43-D43 -> -7 | F43: -10 | G43: =X43-F43 -> -8 | H43: -15 | I43: =Y43-H43 -> -15 | J43: -14 | K43: =Z43-J43 -> -16 | L43: -13 | M43: =AA43-L43 -> -13 | N43: -14 | O43: =AB43-N43 -> -15 | P43: -16 | W43: -15 | X43: -18 | Y43: -30 | Z43: -30 | AA43: -26 | AB43: -29
B44: Adjusted operating profit | C44: £m | D44: 51 | E44: =W44-D44 -> 74 | F44: 47 | G44: =X44-F44 -> 72 | H44: 54 | I44: =Y44-H44 -> 77 | J44: 107 | K44: =Z44-J44 -> 181 | L44: 188 | M44: =AA44-L44 -> 223 | N44: 206 | O44: =AB44-N44 -> 155 | P44: 142 | W44: 125 | X44: 119 | Y44: 131 | Z44: 288 | AA44: 411 | AB44: 361
B46: Exchange Rate (Average) | C46: x | F46: 0.77129154 | G46: 0.72413664 | H46: 0.70631085 | I46: 0.68458409 | J46: 0.65804692 | K46: 0.72349848 | L46: 0.7712845 | M46: 0.7317053 | N46: 0.71934729 | O46: 0.67042595 | P46: 0.67579846 | Q46: 0.65296692 | X46: 0.78601577 | Y46: 0.75657031 | Z46: 0.73147023 | AA46: 0.71691333 | AB46: 0.71251328 | AC46: 0.70020331 | AD46: 0.68542265 | AE46: 0.68374765
B47: Exchange Rate (Average) | C47: x | D47: 0.59926385 | E47: 0.59131154 | F47: 0.56072538 | G47: 0.55946107 | H47: 0.54597674 | I47: 0.54362424 | J47: 0.52194615 | K47: 0.55356591 | L47: 0.55545504 | M47: 0.53686136 | N47: 0.5546186 | O47: 0.5704084 | P47: 0.54797692 | Q47: 0.52070462 | W47: 0.59528769 | X47: 0.5600908 | Y47: 0.54478697 | Z47: 0.53787672 | AA47: 0.54605134 | AB47: 0.56257423 | AC47: 0.53434077
B49: US
B50: Average monthly players | C50: (‘000s) | J50: 596 | L50: 906 | N50: 993 | P50: 1066 | Z50: 794 | AA50: 1008 | AB50: 1090 | AC50: 1111 | AD50: 1165
B51: Sportsbook stakes | C51: A$m | AA51: =AA26/AA$46 -> 22435.069 | AB51: =AB26/AB$46 -> 19519.636 | AC51: =AC26/AC$46 -> 17210.081 | AD51: =AD26/AD$46 -> 15775.668
B52: Sportsbook net revenue margin | C52: % | AA52: =AA53/AA51 -> 0.11079333 | AB52: =AB53/AB51 -> 0.11202186 | AC52: =AC53/AC51 -> 0.12007745 | AD52: =AD53/AD51 -> 0.12919634
B53: Total revenue | C53: A$m | AA53: =AA28/AA$46 -> 2485.6561 | AB53: =AB28/AB$46 -> 2186.6259 | AC53: =AC28/AC$46 -> 2066.5427 | AD53: =AD28/AD$46 -> 2038.1585 | AE53: =AE28/AE$46 -> 1923.2242
B54: Adjusted EBITDA | C54: A$m | AA54: =AA29/AA$46 -> 835.52638 | AB54: =AB29/AB$46 -> 669.46121 | AC54: =AC29/AC$46 -> 496.99851 | AD54: =AD29/AD$46 -> 430.39138 | AE54: =AE29/AE$46 -> 340.76899
B55: Adjusted EBITDA margin | C55: % | AA55: =AA54/AA53 -> 0.33613917 | AB55: =AB54/AB53 -> 0.30616175 | AC55: =AC54/AC53 -> 0.24049758 | AD55: =AD54/AD53 -> 0.21116679 | AE55: =AE54/AE53 -> 0.17718631
B57: US - QTR
B58: Sportsbook stakes | C58: A$m | Z58: =SUMIF('SBET QTR'!$9:$9,SBET!Z$12,'SBET QTR'!$56:$56) -> 0 | AA58: =SUMIF('SBET QTR'!$9:$9,SBET!AA$12,'SBET QTR'!$56:$56) -> 0 | AB58: =SUMIF('SBET QTR'!$9:$9,SBET!AB$12,'SBET QTR'!$56:$56) -> 0 | AC58: =SUMIF('SBET QTR'!$9:$9,SBET!AC$12,'SBET QTR'!$56:$56) -> 0 | AD58: =SUMIF('SBET QTR'!$9:$9,SBET!AD$12,'SBET QTR'!$56:$56) -> 0
B59: Sportsbook net revenue margin | C59: %
B60: Total revenue | C60: A$m | AA60: =SUMIF('SBET QTR'!$9:$9,SBET!AA$12,'SBET QTR'!$59:$59) -> 0 | AB60: =SUMIF('SBET QTR'!$9:$9,SBET!AB$12,'SBET QTR'!$59:$59) -> 0 | AC60: =SUMIF('SBET QTR'!$9:$9,SBET!AC$12,'SBET QTR'!$59:$59) -> 0 | AD60: =SUMIF('SBET QTR'!$9:$9,SBET!AD$12,'SBET QTR'!$59:$59) -> 0
B61: Cost of sales | C61: A$m | AA61: =SUMIF('SBET QTR'!$9:$9,SBET!AA$12,'SBET QTR'!$68:$68) -> 0 | AB61: =SUMIF('SBET QTR'!$9:$9,SBET!AB$12,'SBET QTR'!$68:$68) -> 0 | AC61: =SUMIF('SBET QTR'!$9:$9,SBET!AC$12,'SBET QTR'!$68:$68) -> 0 | AD61: =SUMIF('SBET QTR'!$9:$9,SBET!AD$12,'SBET QTR'!$68:$68) -> 0
B62: Cost of sales as a % of net revenue | C62: % | AA62: =-AA61/AA60 -> #DIV/0! | AB62: =-AB61/AB60 -> #DIV/0! | AC62: =-AC61/AC60 -> #DIV/0! | AD62: =-AD61/AD60 -> #DIV/0!
B63: Gross profit | C63: A$m | AA63: =AA60-AA61 -> 0 | AB63: =AB60-AB61 -> 0 | AC63: =AC60-AC61 -> 0 | AD63: =AD60-AD61 -> 0
B64: Sales and marketing | C64: A$m | AA64: =SUMIF('SBET QTR'!$9:$9,SBET!AA$12,'SBET QTR'!$70:$70) -> 0 | AB64: =SUMIF('SBET QTR'!$9:$9,SBET!AB$12,'SBET QTR'!$70:$70) -> 0 | AC64: =SUMIF('SBET QTR'!$9:$9,SBET!AC$12,'SBET QTR'!$70:$70) -> 0 | AD64: =SUMIF('SBET QTR'!$9:$9,SBET!AD$12,'SBET QTR'!$70:$70) -> 0
B65: Contribution | C65: A$m | AA65: =AA63-AA64 -> 0 | AB65: =AB63-AB64 -> 0 | AC65: =AC63-AC64 -> 0 | AD65: =AD63-AD64 -> 0
B66: Other operating costs | C66: A$m | AA66: =AA65-AA67 -> 0 | AB66: =AB65-AB67 -> 0 | AC66: =AC65-AC67 -> 0 | AD66: =AD65-AD67 -> 0
B67: Adjusted EBITDA | C67: A$m | AA67: =SUMIF('SBET QTR'!$9:$9,SBET!AA$12,'SBET QTR'!$64:$64) -> 0 | AB67: =SUMIF('SBET QTR'!$9:$9,SBET!AB$12,'SBET QTR'!$64:$64) -> 0 | AC67: =SUMIF('SBET QTR'!$9:$9,SBET!AC$12,'SBET QTR'!$64:$64) -> 0 | AD67: =SUMIF('SBET QTR'!$9:$9,SBET!AD$12,'SBET QTR'!$64:$64) -> 0
B68: Adjusted EBITDA margin | C68: % | AA68: =AA67/AA60 -> #DIV/0! | AB68: =AB67/AB60 -> #DIV/0! | AC68: =AC67/AC60 -> #DIV/0! | AD68: =AD67/AD60 -> #DIV/0!
B69: Depreciation and amortisation | C69: A$m
B70: Adjusted operating profit | C70: A$m
B77: UK
B78: Sportsbook stakes | C78: A$m | D78: =D32/D$47 -> 3228.9617 | E78: =E32/E$47 -> 2998.4194 | F78: =F32/F$47 -> 3770.1165 | G78: =G32/G$47 -> 3921.6312 | H78: =H32/H$47 -> 6066.1924 | I78: =I32/I$47 -> 6326.0608 | J78: =J32/J$47 -> 7132.9197 | K78: =K32/K$47 -> 10820.753 | ... P78: =P32/P$47 -> 9038.7018 | W78: =W32/W$47 -> 6228.921 | X78: =X32/X$47 -> 7691.6099 | Y78: =Y32/Y$47 -> 12392 | Z78: =Z32/Z$47 -> 18058.041 | AA78: =AA32/AA$47 -> 21430.219 | AB78: =AB32/AB$47 -> 20079.128
B79: Sportsbook net revenue margin | C79: % | D79: =D80/D78 -> 0.094056848 | E79: =E80/E78 -> 0.12521151 | F79: =F80/F78 -> 0.097918638 | G79: =G80/G78 -> 0.089334549 | H79: =H80/H78 -> 0.094806763 | I79: =I80/I78 -> 0.10671707 | J79: =J80/J78 -> 0.11684126 | K79: =K80/K78 -> 0.10684474 | ... P79: =P80/P78 -> 0.1213406 | W79: =W80/W78 -> 0.10895361 | X79: =X80/X78 -> 0.09354689 | Y79: =Y80/Y78 -> 0.10087394 | Z79: =Z80/Z78 -> 0.11067641 | AA79: =AA80/AA78 -> 0.11057939 | AB79: =AB80/AB78 -> 0.11180949
B80: Total revenue | C80: A$m | D80: =D34/D$47 -> 303.70596 | E80: =E34/E$47 -> 375.43661 | F80: =F34/F$47 -> 369.16467 | G80: =G34/G$47 -> 350.33716 | H80: =H34/H$47 -> 575.11607 | I80: =I34/I$47 -> 675.09866 | J80: =J34/J$47 -> 833.4193 | K80: =K34/K$47 -> 1156.1406 | ... P80: =P34/P$47 -> 1096.7615 | W80: =W34/W$47 -> 678.66345 | X80: =X34/X$47 -> 719.52619 | Y80: =Y34/Y$47 -> 1250.0299 | Z80: =Z34/Z$47 -> 1998.5992 | AA80: =AA34/AA$47 -> 2369.7405 | AB80: =AB34/AB$47 -> 2245.0371
B81: Cost of sales | C81: A$m | D81: =D35/D$47 -> -85.104417 | E81: =E35/E$47 -> -101.46935 | F81: =F35/F$47 -> -148.02255 | G81: =G35/G$47 -> -67.92251 | H81: =H35/H$47 -> -256.42118 | I81: =I35/I$47 -> -292.48144 | J81: =J35/J$47 -> -383.18129 | K81: =K35/K$47 -> -578.07028 | ... P81: =P35/P$47 -> -578.49151 | W81: =W35/W$47 -> -186.46446 | X81: =X35/X$47 -> -216.0364 | Y81: =Y35/Y$47 -> -548.83838 | Z81: =Z35/Z$47 -> -966.76428 | AA81: =AA35/AA$47 -> -1164.7256 | AB81: =AB35/AB$47 -> -1128.7399
B82: Cost of sales as a % of net revenue | C82: % | D82: =-D81/D80 -> 0.28021978 | E82: =-E81/E80 -> 0.27027027 | F82: =-F81/F80 -> 0.40096618 | G82: =-G81/G80 -> 0.19387755 | H82: =-H81/H80 -> 0.44585987 | I82: =-I81/I80 -> 0.43324251 | J82: =-J81/J80 -> 0.45977011 | K82: =-K81/K80 -> 0.5 | ... P82: =-P81/P80 -> 0.52745424 | W82: =-W81/W80 -> 0.27475248 | X82: =-X81/X80 -> 0.30024814 | Y82: =-Y81/Y80 -> 0.43906021 | Z82: =-Z81/Z80 -> 0.48372093 | AA82: =-AA81/AA80 -> 0.49149923 | AB82: =-AB81/AB80 -> 0.50277118
B83: Gross profit | C83: A$m | D83: =D37/D$47 -> 218.60154 | E83: =E37/E$47 -> 272.2761 | F83: =F37/F$47 -> 221.14212 | G83: =G37/G$47 -> 282.41465 | H83: =H37/H$47 -> 318.69489 | I83: =I37/I$47 -> 382.61723 | J83: =J37/J$47 -> 450.23801 | K83: =K37/K$47 -> 578.07028 | ... P83: =P37/P$47 -> 518.27 | W83: =W37/W$47 -> 490.51913 | X83: =X37/X$47 -> 503.48979 | Y83: =Y37/Y$47 -> 701.19151 | Z83: =Z37/Z$47 -> 1031.835 | AA83: =AA37/AA$47 -> 1205.0149 | AB83: =AB37/AB$47 -> 1116.2971
B84: Sales and marketing | C84: A$m | D84: =D38/D$47 -> -66.748562 | E84: =E38/E$47 -> -71.028548 | F84: =F38/F$47 -> -60.635742 | G84: =G38/G$47 -> -85.796855 | H84: =H38/H$47 -> -102.56847 | I84: =I38/I$47 -> -125.0864 | J84: =J38/J$47 -> -113.03848 | K84: =K38/K$47 -> -126.45287 | ... P84: =P38/P$47 -> -116.79324 | W84: =W38/W$47 -> -137.74852 | X84: =X38/X$47 -> -146.40483 | Y84: =Y38/Y$47 -> -227.6119 | Z84: =Z38/Z$47 -> -239.83191 | AA84: =AA38/AA$47 -> -217.92823 | AB84: =AB38/AB$47 -> -238.19079
B85: Contribution | C85: A$m | D85: =D39/D$47 -> 151.85298 | E85: =E39/E$47 -> 201.24755 | F85: =F39/F$47 -> 160.50638 | G85: =G39/G$47 -> 194.83036 | H85: =H39/H$47 -> 216.12642 | I85: =I39/I$47 -> 257.53083 | J85: =J39/J$47 -> 337.19953 | K85: =K39/K$47 -> 451.61741 | ... P85: =P39/P$47 -> 399.65187 | W85: =W39/W$47 -> 352.77061 | X85: =X39/X$47 -> 355.29953 | Y85: =Y39/Y$47 -> 473.57961 | Z85: =Z39/Z$47 -> 792.00305 | AA85: =AA39/AA$47 -> 987.08667 | AB85: =AB39/AB$47 -> 878.10634
B86: Other operating costs | C86: A$m | D86: =D40/D$47 -> -36.711709 | E86: =E40/E$47 -> -82.866639 | F86: =F40/F$47 -> -37.451488 | G86: =G40/G$47 -> -73.284813 | H86: =H40/H$47 -> -89.747412 | I86: =I40/I$47 -> -86.456777 | J86: =J40/J$47 -> -105.37485 | K86: =K40/K$47 -> -95.74289 | ... P86: =P40/P$47 -> -111.31856 | W86: =W40/W$47 -> -119.27006 | X86: =X40/X$47 -> -110.69634 | Y86: =Y40/Y$47 -> -176.21567 | Z86: =Z40/Z$47 -> -200.78951 | AA86: =AA40/AA$47 -> -186.79562 | AB86: =AB40/AB$47 -> -184.86449
B87: Adjusted EBITDA | C87: A$m | D87: =D41/D$47 -> 115.14127 | E87: =E41/E$47 -> 118.38091 | F87: =F41/F$47 -> 123.05489 | G87: =G41/G$47 -> 121.54554 | H87: =H41/H$47 -> 126.37901 | I87: =I41/I$47 -> 169.23454 | J87: =J41/J$47 -> 231.82468 | K87: =K41/K$47 -> 355.87452 | ... P87: =P41/P$47 -> 288.33331 | W87: =W41/W$47 -> 233.50054 | X87: =X41/X$47 -> 244.60319 | Y87: =Y41/Y$47 -> 295.52836 | Z87: =Z41/Z$47 -> 591.21354 | AA87: =AA41/AA$47 -> 800.29105 | AB87: =AB41/AB$47 -> 693.24185
B88: Adjusted EBITDA margin | C88: % | D88: =D103/D96 -> 0.37912088 | E88: =E103/E96 -> 0.31531532 | F88: =F87/F80 -> 0.33333333 | G88: =G87/G80 -> 0.34693878 | H88: =H87/H80 -> 0.21974522 | I88: =I87/I80 -> 0.2506812 | J88: =J87/J80 -> 0.27816092 | K88: =K87/K80 -> 0.3078125 | L88: =L87/L80 -> 0.34358974 | M88: =M87/M80 -> 0.33286319 | ... P88: =P87/P80 -> 0.26289517 | W88: =W87/W80 -> 0.34405941 | X88: =X87/X80 -> 0.33995037 | Y88: =Y87/Y80 -> 0.23641703 | Z88: =Z87/Z80 -> 0.29581395 | AA88: =AA87/AA80 -> 0.33771252 | AB88: =AB87/AB80 -> 0.3087886
B89: Depreciation and amortisation | C89: A$m | D89: =D43/D$47 -> -13.349712 | E89: =E43/E$47 -> -11.838091 | F89: =F43/F$47 -> -17.834042 | G89: =G43/G$47 -> -14.299476 | H89: =H43/H$47 -> -27.473698 | I89: =I43/I$47 -> -27.592588 | J89: =J43/J$47 -> -26.82269 | K89: =K43/K$47 -> -28.903514 | ... P89: =P43/P$47 -> -29.19831 | W89: =W43/W$47 -> -25.1979 | X89: =X43/X$47 -> -32.137646 | Y89: =Y43/Y$47 -> -55.067396 | Z89: =Z43/Z$47 -> -55.774863 | AA89: =AA43/AA$47 -> -47.61457 | AB89: =AB43/AB$47 -> -51.548753
B90: Adjusted operating profit | C90: A$m | D90: =D44/D$47 -> 85.104417 | E90: =E44/E$47 -> 125.14554 | F90: =F44/F$47 -> 83.819997 | G90: =G44/G$47 -> 128.69528 | H90: =H44/H$47 -> 98.905312 | I90: =I44/I$47 -> 141.64195 | J90: =J44/J$47 -> 205.00199 | K90: =K44/K$47 -> 326.971 | ... P90: =P44/P$47 -> 259.135 | W90: =W44/W$47 -> 209.9825 | X90: =X44/X$47 -> 212.46555 | Y90: =Y44/Y$47 -> 240.46096 | Z90: =Z44/Z$47 -> 535.43868 | AA90: =AA44/AA$47 -> 752.67648 | AB90: =AB44/AB$47 -> 641.6931
B92: Combined | D92: UK | E92: UK | F92: UK | G92: UK | H92: UK | I92: UK | J92: UK | K92: UK | L92: UK | M92: UK | N92: UK | O92: UK | P92: UK | Q92: UK/US | W92: UK | X92: UK | Y92: UK | Z92: UK | AA92: UK | AB92: UK | AC92: US | AD92: US | AE92: US
B93: Average monthly players | C93: (‘000s) | J93: =J50 -> 596 | L93: =L50 -> 906 | N93: =N50 -> 993 | P93: =P50 -> 1066 | Z93: =Z50 -> 794 | AA93: =AA50 -> 1008 | AB93: =AB50 -> 1090 | AC93: =AC50 -> 1111 | AD93: =AD50 -> 1165
B94: Sportsbook stakes | C94: A$m | D94: =D78 -> 3228.9617 | E94: =E78 -> 2998.4194 | F94: =F78 -> 3770.1165 | G94: =G78 -> 3921.6312 | H94: =H78 -> 6066.1924 | I94: =I78 -> 6326.0608 | J94: =J78 -> 7132.9197 | K94: =K78 -> 10820.753 | ... P94: =P78 -> 9038.7018 | Q94: =AC94-P94 -> 8171.3795 | W94: =W78 -> 6228.921 | X94: =X78 -> 7691.6099 | Y94: =Y78 -> 12392 | Z94: =Z78 -> 18058.041 | AA94: =AA78 -> 21430.219 | AB94: =AB78 -> 20079.128 | AC94: =AC51 -> 17210.081 | AD94: =AD51 -> 15775.668
B95: Sportsbook net revenue margin | C95: % | D95: =D79 -> 0.094056848 | E95: =E79 -> 0.12521151 | F95: =F79 -> 0.097918638 | G95: =G79 -> 0.089334549 | H95: =H79 -> 0.094806763 | I95: =I79 -> 0.10671707 | J95: =J79 -> 0.11684126 | K95: =K79 -> 0.10684474 | ... P95: =P79 -> 0.1213406 | Q95: =Q96/Q94 -> 0.11868022 | W95: =W79 -> 0.10895361 | X95: =X79 -> 0.09354689 | Y95: =Y79 -> 0.10087394 | Z95: =Z79 -> 0.11067641 | AA95: =AA79 -> 0.11057939 | AB95: =AB79 -> 0.11180949 | AC95: =AC52 -> 0.12007745 | AD95: =AD52 -> 0.12919634
B96: Total revenue | C96: A$m | D96: =D80 -> 303.70596 | E96: =E80 -> 375.43661 | F96: =F80 -> 369.16467 | G96: =G80 -> 350.33716 | H96: =H80 -> 575.11607 | I96: =I80 -> 675.09866 | J96: =J80 -> 833.4193 | K96: =K80 -> 1156.1406 | ... P96: =P80 -> 1096.7615 | Q96: =AC96-P96 -> 969.78114 | W96: =W80 -> 678.66345 | X96: =X80 -> 719.52619 | Y96: =Y80 -> 1250.0299 | Z96: =Z80 -> 1998.5992 | AA96: =AA80 -> 2369.7405 | AB96: =AB80 -> 2245.0371 | AC96: =AC53 -> 2066.5427 | AD96: =AD53 -> 2038.1585 | AE96: =AE53 -> 1923.2242
B97: Cost of sales | C97: A$m | D97: =D81 -> -85.104417 | E97: =E81 -> -101.46935 | F97: =F81 -> -148.02255 | G97: =G81 -> -67.92251 | H97: =H81 -> -256.42118 | I97: =I81 -> -292.48144 | J97: =J81 -> -383.18129 | K97: =K81 -> -578.07028 | ... P97: =P81 -> -578.49151 | W97: =W81 -> -186.46446 | X97: =X81 -> -216.0364 | Y97: =Y81 -> -548.83838 | Z97: =Z81 -> -966.76428 | AA97: =AA81 -> -1164.7256 | AB97: =AB81 -> -1128.7399
B98: Cost of sales as a % of net revenue | C98: % | D98: =D82 -> 0.28021978 | E98: =E82 -> 0.27027027 | F98: =F82 -> 0.40096618 | G98: =G82 -> 0.19387755 | H98: =H82 -> 0.44585987 | I98: =I82 -> 0.43324251 | J98: =J82 -> 0.45977011 | K98: =K82 -> 0.5 | ... P98: =P82 -> 0.52745424 | W98: =W82 -> 0.27475248 | X98: =X82 -> 0.30024814 | Y98: =Y82 -> 0.43906021 | Z98: =Z82 -> 0.48372093 | AA98: =AA82 -> 0.49149923 | AB98: =AB82 -> 0.50277118
B99: Gross profit | C99: A$m | D99: =D83 -> 218.60154 | E99: =E83 -> 272.2761 | F99: =F83 -> 221.14212 | G99: =G83 -> 282.41465 | H99: =H83 -> 318.69489 | I99: =I83 -> 382.61723 | J99: =J83 -> 450.23801 | K99: =K83 -> 578.07028 | ... P99: =P83 -> 518.27 | W99: =W83 -> 490.51913 | X99: =X83 -> 503.48979 | Y99: =Y83 -> 701.19151 | Z99: =Z83 -> 1031.835 | AA99: =AA83 -> 1205.0149 | AB99: =AB83 -> 1116.2971
B100: Sales and marketing | C100: A$m | D100: =D84 -> -66.748562 | E100: =E84 -> -71.028548 | F100: =F84 -> -60.635742 | G100: =G84 -> -85.796855 | H100: =H84 -> -102.56847 | I100: =I84 -> -125.0864 | J100: =J84 -> -113.03848 | K100: =K84 -> -126.45287 | ... P100: =P84 -> -116.79324 | W100: =W84 -> -137.74852 | X100: =X84 -> -146.40483 | Y100: =Y84 -> -227.6119 | Z100: =Z84 -> -239.83191 | AA100: =AA84 -> -217.92823 | AB100: =AB84 -> -238.19079
B101: Contribution | C101: A$m | D101: =D85 -> 151.85298 | E101: =E85 -> 201.24755 | F101: =F85 -> 160.50638 | G101: =G85 -> 194.83036 | H101: =H85 -> 216.12642 | I101: =I85 -> 257.53083 | J101: =J85 -> 337.19953 | K101: =K85 -> 451.61741 | ... P101: =P85 -> 399.65187 | W101: =W85 -> 352.77061 | X101: =X85 -> 355.29953 | Y101: =Y85 -> 473.57961 | Z101: =Z85 -> 792.00305 | AA101: =AA85 -> 987.08667 | AB101: =AB85 -> 878.10634
B102: Other operating costs | C102: A$m | D102: =D86 -> -36.711709 | E102: =E86 -> -82.866639 | F102: =F86 -> -37.451488 | G102: =G86 -> -73.284813 | H102: =H86 -> -89.747412 | I102: =I86 -> -86.456777 | J102: =J86 -> -105.37485 | K102: =K86 -> -95.74289 | ... P102: =P86 -> -111.31856 | W102: =W86 -> -119.27006 | X102: =X86 -> -110.69634 | Y102: =Y86 -> -176.21567 | Z102: =Z86 -> -200.78951 | AA102: =AA86 -> -186.79562 | AB102: =AB86 -> -184.86449
B103: Adjusted EBITDA | C103: A$m | D103: =D87 -> 115.14127 | E103: =E87 -> 118.38091 | F103: =F87 -> 123.05489 | G103: =G87 -> 121.54554 | H103: =H87 -> 126.37901 | I103: =I87 -> 169.23454 | J103: =J87 -> 231.82468 | K103: =K87 -> 355.87452 | ... P103: =P87 -> 288.33331 | Q103: =AC103-P103 -> 208.6652 | W103: =W87 -> 233.50054 | X103: =X87 -> 244.60319 | Y103: =Y87 -> 295.52836 | Z103: =Z87 -> 591.21354 | AA103: =AA87 -> 800.29105 | AB103: =AB87 -> 693.24185 | AC103: =AC54 -> 496.99851 | AD103: =AD54 -> 430.39138 | AE103: =AE54 -> 340.76899
B104: Adjusted EBITDA margin | C104: % | D104: =D88 -> 0.37912088 | E104: =E88 -> 0.31531532 | F104: =F88 -> 0.33333333 | G104: =G88 -> 0.34693878 | H104: =H88 -> 0.21974522 | I104: =I88 -> 0.2506812 | J104: =J88 -> 0.27816092 | K104: =K88 -> 0.3078125 | ... P104: =P88 -> 0.26289517 | Q104: =Q103/Q96 -> 0.21516731 | W104: =W88 -> 0.34405941 | X104: =X88 -> 0.33995037 | Y104: =Y88 -> 0.23641703 | Z104: =Z88 -> 0.29581395 | AA104: =AA88 -> 0.33771252 | AB104: =AB88 -> 0.3087886 | AC104: =AC55 -> 0.24049758 | AD104: =AD55 -> 0.21116679 | AE104: =AE55 -> 0.17718631
B105: Depreciation and amortisation | C105: A$m | D105: =D89 -> -13.349712 | E105: =E89 -> -11.838091 | F105: =F89 -> -17.834042 | G105: =G89 -> -14.299476 | H105: =H89 -> -27.473698 | I105: =I89 -> -27.592588 | J105: =J89 -> -26.82269 | K105: =K89 -> -28.903514 | ... P105: =P89 -> -29.19831 | W105: =W89 -> -25.1979 | X105: =X89 -> -32.137646 | Y105: =Y89 -> -55.067396 | Z105: =Z89 -> -55.774863 | AA105: =AA89 -> -47.61457 | AB105: =AB89 -> -51.548753
B106: Adjusted operating profit | C106: A$m | D106: =D90 -> 85.104417 | E106: =E90 -> 125.14554 | F106: =F90 -> 83.819997 | G106: =G90 -> 128.69528 | H106: =H90 -> 98.905312 | I106: =I90 -> 141.64195 | J106: =J90 -> 205.00199 | K106: =K90 -> 326.971 | ... P106: =P90 -> 259.135 | W106: =W90 -> 209.9825 | X106: =X90 -> 212.46555 | Y106: =Y90 -> 240.46096 | Z106: =Z90 -> 535.43868 | AA106: =AA90 -> 752.67648 | AB106: =AB90 -> 641.6931
B108: ASIC
B109: Revenue
B110: Cost of Sales
B111: Gross Profit
B112: Advertising & Marketing Expenses | X112: ='SportsBet ASIC'!D8/1000 -> -122.256 | Y112: ='SportsBet ASIC'!E8/1000 -> -113.544 | Z112: ='SportsBet ASIC'!F8/1000 -> -156.744 | AA112: ='SportsBet ASIC'!G8/1000 -> -187.505 | AB112: ='SportsBet ASIC'!H8/1000 -> -217.928 | AC112: ='SportsBet ASIC'!I8/1000 -> -222.334 | AD112: ='SportsBet ASIC'!J8/1000 -> -232.23 | AE112: ='SportsBet ASIC'!K8/1000 -> -201.911
B113: Depreciation & Ammortisation Expense
B114: Other Opex
B115: Results from Operating Activities
B117: QTR
B120: Marketing
B121: FY | X121: =X100 -> -146.40483 | Y121: =Y100 -> -227.6119 | Z121: =Z100 -> -239.83191 | AA121: =AA100 -> -217.92823 | AB121: =AB100 -> -238.19079 | AC121: =AC100 -> 0 | AD121: =AD100 -> 0 | AE121: =AE100 -> 0
B122: QtR | X122: =SUMIF('SBET QTR'!$6:$6,SBET!X$12,'SBET QTR'!$70:$70) -> 0 | Y122: =SUMIF('SBET QTR'!$6:$6,SBET!Y$12,'SBET QTR'!$70:$70) -> 0 | Z122: =SUMIF('SBET QTR'!$6:$6,SBET!Z$12,'SBET QTR'!$70:$70) -> 0 | AA122: =SUMIF('SBET QTR'!$6:$6,SBET!AA$12,'SBET QTR'!$70:$70) -> 309.14415 | AB122: =SUMIF('SBET QTR'!$6:$6,SBET!AB$12,'SBET QTR'!$70:$70) -> 331.52105 | AC122: =SUMIF('SBET QTR'!$6:$6,SBET!AC$12,'SBET QTR'!$70:$70) -> 339.70519 | AD122: =SUMIF('SBET QTR'!$6:$6,SBET!AD$12,'SBET QTR'!$70:$70) -> 337.83791 | AE122: =SUMIF('SBET QTR'!$6:$6,SBET!AE$12,'SBET QTR'!$70:$70) -> 0
...

Sheet ENT
D3: =IF(MONTH(D11)>6,RIGHT(YEAR(D11),2)+1,RIGHT(YEAR(D11),2)) -> 17 | E3: =IF(MONTH(E11)>6,RIGHT(YEAR(E11),2)+1,RIGHT(YEAR(E11),2)) -> 18 | F3: =IF(MONTH(F11)>6,RIGHT(YEAR(F11),2)+1,RIGHT(YEAR(F11),2)) -> 18 | G3: =IF(MONTH(G11)>6,RIGHT(YEAR(G11),2)+1,RIGHT(YEAR(G11),2)) -> 19 | H3: =IF(MONTH(H11)>6,RIGHT(YEAR(H11),2)+1,RIGHT(YEAR(H11),2)) -> 19 | I3: =IF(MONTH(I11)>6,RIGHT(YEAR(I11),2)+1,RIGHT(YEAR(I11),2)) -> 20 | J3: =IF(MONTH(J11)>6,RIGHT(YEAR(J11),2)+1,RIGHT(YEAR(J11),2)) -> 20 | K3: =IF(MONTH(K11)>6,RIGHT(YEAR(K11),2)+1,RIGHT(YEAR(K11),2)) -> 21 | ... U3: =IF(MONTH(U11)>6,RIGHT(YEAR(U11),2)+1,RIGHT(YEAR(U11),2)) -> 26
D4: =RIGHT(YEAR(D$11),2) -> 17 | E4: =RIGHT(YEAR(E$11),2) -> 17 | F4: =RIGHT(YEAR(F$11),2) -> 18 | G4: =RIGHT(YEAR(G$11),2) -> 18 | H4: =RIGHT(YEAR(H$11),2) -> 19 | I4: =RIGHT(YEAR(I$11),2) -> 19 | J4: =RIGHT(YEAR(J$11),2) -> 20 | K4: =RIGHT(YEAR(K$11),2) -> 20 | ... U4: =RIGHT(YEAR(U$11),2) -> 25
D5: ="FY"&TEXT(D$3,"00") -> FY17 | E5: ="FY"&TEXT(E$3,"00") -> FY18 | F5: ="FY"&TEXT(F$3,"00") -> FY18 | G5: ="FY"&TEXT(G$3,"00") -> FY19 | H5: ="FY"&TEXT(H$3,"00") -> FY19 | I5: ="FY"&TEXT(I$3,"00") -> FY20 | J5: ="FY"&TEXT(J$3,"00") -> FY20 | K5: ="FY"&TEXT(K$3,"00") -> FY21 | ... U5: ="FY"&TEXT(U$3,"00") -> FY26
D6: ="CY"&TEXT(D$4,"00") -> CY17 | E6: ="CY"&TEXT(E$4,"00") -> CY17 | F6: ="CY"&TEXT(F$4,"00") -> CY18 | G6: ="CY"&TEXT(G$4,"00") -> CY18 | H6: ="CY"&TEXT(H$4,"00") -> CY19 | I6: ="CY"&TEXT(I$4,"00") -> CY19 | J6: ="CY"&TEXT(J$4,"00") -> CY20 | K6: ="CY"&TEXT(K$4,"00") -> CY20 | ... U6: ="CY"&TEXT(U$4,"00") -> CY25
D7: =D11-EOMONTH(D11,-6) -> 181 | E7: =E11-EOMONTH(E11,-6) -> 184 | F7: =F11-EOMONTH(F11,-6) -> 181 | G7: =G11-EOMONTH(G11,-6) -> 184 | H7: =H11-EOMONTH(H11,-6) -> 181 | I7: =I11-EOMONTH(I11,-6) -> 184 | J7: =J11-EOMONTH(J11,-6) -> 182 | K7: =K11-EOMONTH(K11,-6) -> 184 | ... U7: =U11-EOMONTH(U11,-6) -> 184
D11: 42916 | E11: =EOMONTH(D11,6) -> 43100 | F11: =EOMONTH(E11,6) -> 43281 | G11: =EOMONTH(F11,6) -> 43465 | H11: =EOMONTH(G11,6) -> 43646 | I11: =EOMONTH(H11,6) -> 43830 | J11: =EOMONTH(I11,6) -> 44012 | K11: =EOMONTH(J11,6) -> 44196 | L11: =EOMONTH(K11,6) -> 44377 | ... U11: =EOMONTH(T11,6) -> 46022 | W11: 43100 | X11: =EOMONTH(W11,12) -> 43465 | Y11: =EOMONTH(X11,12) -> 43830 | Z11: =EOMONTH(Y11,12) -> 44196 | AA11: =EOMONTH(Z11,12) -> 44561 | AB11: =EOMONTH(AA11,12) -> 44926 | AC11: =EOMONTH(AB11,12) -> 45291
B13: ENTAIN HALFS | D13: 1H | E13: 2H | F13: 1H | G13: 2H | H13: 1H | I13: 2H | J13: 1H | K13: 2H | L13: 1H | M13: 2H | N13: 1H | O13: 2H | P13: 1H | Q13: 2H | R13: 1H | S13: 2H | T13: 1H | U13: 2H | W13: FY | X13: FY | Y13: FY | Z13: FY | AA13: FY | AB13: FY | AC13: FY
D14: 2017 | E14: 2017 | F14: 2018 | G14: 2018 | H14: 2019 | I14: 2019 | J14: 2020 | K14: 2020 | L14: 2021 | M14: 2021 | N14: 2022 | O14: 2022 | P14: 2023 | Q14: 2023 | R14: 2024 | S14: 2024 | T14: 2025 | U14: 2025 | W14: 2017 | X14: 2018 | Y14: 2019 | Z14: 2020 | AA14: 2021 | AB14: 2022 | AC14: 2023
B17: TABCORP HALFS | D17: =E13&RIGHT(E$14,2) -> 2H17 | E17: =F13&RIGHT(F$14,2) -> 1H18 | F17: =G13&RIGHT(G$14,2) -> 2H18 | G17: =H13&RIGHT(H$14,2) -> 1H19 | H17: =I13&RIGHT(I$14,2) -> 2H19 | I17: =J13&RIGHT(J$14,2) -> 1H20 | J17: =K13&RIGHT(K$14,2) -> 2H20 | K17: =L13&RIGHT(L$14,2) -> 1H21 | ... P17: =Q13&RIGHT(Q$14,2) -> 2H23 | Q17: 1H24
B19: Revenue | C19: £m | F19: =H19/(1+H20) -> 88.101651 | G19: =X19-F19 -> 114.59534 | H19: =J19/(1+J20) -> 112.77011 | I19: =Y19-H19 -> 134.52021 | J19: =L19/(1+L20) -> 161.26126 | K19: =Z19-J19 -> 222.03874 | L19: 179 | M19: =AA19-L19 -> 237.7 | N19: 213.7 | O19: =AB19-N19 -> 249.3 | P19: 209.1 | Q19: =AC19-P19 -> 306 | X19: =Y19/(1+Y20) -> 202.69699 | Y19: =Z19/(1+Z20) -> 247.29032 | Z19: 383.3 | AA19: 416.7 | AB19: 463 | AC19: 515.1
B20: proforma incl Neds | H20: 0.28 | J20: 0.43 | L20: 0.11 | Y20: 0.22 | Z20: 0.55
B23: ex Neds | C23: £m | D23: =F23/(1+F24) -> 61.448405 | E23: =W23-D23 -> 86.355266 | F23: =H23/(1+H24) -> 76.196022 | G23: =X23-F23 -> 96.734273 | H23: =J19/(1+J20) -> 112.77011 | I23: =Y23-H23 -> 134.52021 | W23: =X23/(1+X24) -> 147.80367 | X23: =Y23/(1+Y24) -> 172.9303 | Y23: =Z19/(1+Z20) -> 247.29032
F24: 0.24 | H24: 0.48 | X24: 0.17 | Y24: 0.43
B26: Exchange Rate (Average) | C26: x | D26: 0.59926385 | E26: 0.59131154 | F26: 0.56072538 | G26: 0.55946107 | H26: 0.54597674 | I26: 0.54362424 | J26: 0.52194615 | K26: 0.55356591 | L26: 0.55545504 | M26: 0.53686136 | N26: 0.5546186 | O26: 0.5704084 | P26: 0.54797692 | Q26: 0.52070462 | W26: 0.59528769 | X26: =1/1.781 -> 0.56148231 | Y26: =1/1.831 -> 0.54614965 | Z26: =1/1.876 -> 0.53304904 | AA26: =1/1.832 -> 0.54585153 | AB26: =1/1.788 -> 0.55928412 | AC26: =1/1.873 -> 0.53390283
B28: Revenue | C28: A$m | F28: =F19/F$26 -> 157.12085 | G28: =G19/G$26 -> 204.83165 | H28: =H19/H$26 -> 206.54747 | I28: =I19/I$26 -> 247.45072 | J28: =J19/J$26 -> 308.96149 | K28: =K19/K$26 -> 401.10624 | L28: =L19/L$26 -> 322.25831 | M28: =M19/M$26 -> 442.75863 | ... Q28: =Q19/Q$26 -> 587.66523

Sheet B365
B3: =IF(MONTH(B11)>6,RIGHT(YEAR(B11),2)+1,RIGHT(YEAR(B11),2)) -> 18 | C3: =IF(MONTH(C11)>6,RIGHT(YEAR(C11),2)+1,RIGHT(YEAR(C11),2)) -> 19 | D3: =IF(MONTH(D11)>6,RIGHT(YEAR(D11),2)+1,RIGHT(YEAR(D11),2)) -> 20 | E3: =IF(MONTH(E11)>6,RIGHT(YEAR(E11),2)+1,RIGHT(YEAR(E11),2)) -> 21 | F3: =IF(MONTH(F11)>6,RIGHT(YEAR(F11),2)+1,RIGHT(YEAR(F11),2)) -> 22 | G3: =IF(MONTH(G11)>6,RIGHT(YEAR(G11),2)+1,RIGHT(YEAR(G11),2)) -> 23
B4: =RIGHT(YEAR(B$11),2) -> 18 | C4: =RIGHT(YEAR(C$11),2) -> 19 | D4: =RIGHT(YEAR(D$11),2) -> 20 | E4: =RIGHT(YEAR(E$11),2) -> 21 | F4: =RIGHT(YEAR(F$11),2) -> 22 | G4: =RIGHT(YEAR(G$11),2) -> 23
B5: ="FY"&TEXT(B$3,"00") -> FY18 | C5: ="FY"&TEXT(C$3,"00") -> FY19 | D5: ="FY"&TEXT(D$3,"00") -> FY20 | E5: ="FY"&TEXT(E$3,"00") -> FY21 | F5: ="FY"&TEXT(F$3,"00") -> FY22 | G5: ="FY"&TEXT(G$3,"00") -> FY23
B6: ="CY"&TEXT(B$4,"00") -> CY18 | C6: ="CY"&TEXT(C$4,"00") -> CY19 | D6: ="CY"&TEXT(D$4,"00") -> CY20 | E6: ="CY"&TEXT(E$4,"00") -> CY21 | F6: ="CY"&TEXT(F$4,"00") -> CY22 | G6: ="CY"&TEXT(G$4,"00") -> CY23
B7: =B11-EOMONTH(B11,-12) -> 365 | C7: =C11-EOMONTH(C11,-12) -> 365 | D7: =D11-EOMONTH(D11,-12) -> 366 | E7: =E11-EOMONTH(E11,-12) -> 365 | F7: =F11-EOMONTH(F11,-12) -> 365 | G7: =G11-EOMONTH(G11,-12) -> 365
B11: 43281 | C11: =EOMONTH(B11,12) -> 43646 | D11: =EOMONTH(C11,12) -> 44012 | E11: =EOMONTH(D11,12) -> 44377 | F11: =EOMONTH(E11,12) -> 44742 | G11: =EOMONTH(F11,12) -> 45107
A13: Bet365 Australia data
B14: 2018 | C14: 2019 | D14: 2020 | E14: 2021 | F14: 2022 | G14: 2023
A15: Revenue | B15: 114.999 | C15: 120.914 | D15: 147.173 | E15: 190.321 | F15: 200.429 | G15: 201.286
A16: Other Income | B16: =0.178+0.03 -> 0.208 | C16: =0.422+0.035 -> 0.457 | D16: =0.151-0.019 -> 0.132 | E16: =0.02+0.045 -> 0.065 | F16: =0.001+0.022 -> 0.023 | G16: =0.217+0.009 -> 0.226
A17: ----- | B17: ----- | C17: ----- | D17: ----- | E17: ----- | F17: ----- | G17: -----
A18: Employee Expenses | B18: -34.214 | C18: -40.664 | D18: -43.577 | E18: -48.696 | F18: -49.796 | G18: -54.732
A19: Advertising Expenses | B19: -30.324 | C19: -36.799 | D19: -32.768 | E19: -37.038 | F19: -41.518 | G19: -44.618
A20: Levy Expense | B20: -29.906 | C20: -41.267 | D20: -56.073 | E20: -70.855 | F20: -74.595 | G20: -80.187
A21: Other Opex | B21: =-0.908-0.163-2.234-0.549-11.763-2.876 -> -18.493 | C21: =-1.55-0.195-2.415-0.937-5.715-2.669 -> -13.481 | D21: =-0.198-24.711-6.634 -> -31.543 | E21: =-0.363-22.645-5.246 -> -28.254 | F21: =-0.346-10.53-5.878 -> -16.754 | G21: =-0.527+1.098-9.875 -> -9.304
A22: ----- | B22: ----- | C22: ----- | D22: ----- | E22: ----- | F22: ----- | G22: -----
A23: EBITDA | B23: =SUM(B15:B22) -> 2.27 | C23: =SUM(C15:C22) -> -10.84 | D23: =SUM(D15:D22) -> -16.656 | E23: =SUM(E15:E22) -> 5.543 | F23: =SUM(F15:F22) -> 17.789 | G23: =SUM(G15:G22) -> 12.671
A24: D&A | B24: -0.951 | C24: -1.472 | D24: -3.252 | E24: -4.066 | F24: -3.495 | G24: -3.608
A25: ----- | B25: ----- | C25: ----- | D25: ----- | E25: ----- | F25: ----- | G25: -----
A26: EBIT | B26: =SUM(B23:B25) -> 1.319 | C26: =SUM(C23:C25) -> -12.312 | D26: =SUM(D23:D25) -> -19.908 | E26: =SUM(E23:E25) -> 1.477 | F26: =SUM(F23:F25) -> 14.294 | G26: =SUM(G23:G25) -> 9.063
A27: Tax | B27: -0.397 | C27: 3.688 | D27: 5.969 | E27: -0.473 | F27: -4.294 | G27: -2.746
A28: ----- | B28: ----- | C28: ----- | D28: ----- | E28: ----- | F28: ----- | G28: -----
A29: NPAT | B29: =SUM(B26:B28) -> 0.922 | C29: =SUM(C26:C28) -> -8.624 | D29: =SUM(D26:D28) -> -13.939 | E29: =SUM(E26:E28) -> 1.004 | F29: =SUM(F26:F28) -> 10 | G29: =SUM(G26:G28) -> 6.317

Sheet PBH
C3: =IF(MONTH(C11)>6,RIGHT(YEAR(C11),2)+1,RIGHT(YEAR(C11),2)) -> 17 | D3: =IF(MONTH(D11)>6,RIGHT(YEAR(D11),2)+1,RIGHT(YEAR(D11),2)) -> 18 | E3: =IF(MONTH(E11)>6,RIGHT(YEAR(E11),2)+1,RIGHT(YEAR(E11),2)) -> 18 | F3: =IF(MONTH(F11)>6,RIGHT(YEAR(F11),2)+1,RIGHT(YEAR(F11),2)) -> 18 | G3: =IF(MONTH(G11)>6,RIGHT(YEAR(G11),2)+1,RIGHT(YEAR(G11),2)) -> 18 | H3: =IF(MONTH(H11)>6,RIGHT(YEAR(H11),2)+1,RIGHT(YEAR(H11),2)) -> 19 | I3: =IF(MONTH(I11)>6,RIGHT(YEAR(I11),2)+1,RIGHT(YEAR(I11),2)) -> 19 | J3: =IF(MONTH(J11)>6,RIGHT(YEAR(J11),2)+1,RIGHT(YEAR(J11),2)) -> 19 | ... AM3: =IF(MONTH(AM11)>6,RIGHT(YEAR(AM11),2)+1,RIGHT(YEAR(AM11),2)) -> 26
C4: =RIGHT(YEAR(C$11),2) -> 17 | D4: =RIGHT(YEAR(D$11),2) -> 17 | E4: =RIGHT(YEAR(E$11),2) -> 17 | F4: =RIGHT(YEAR(F$11),2) -> 18 | G4: =RIGHT(YEAR(G$11),2) -> 18 | H4: =RIGHT(YEAR(H$11),2) -> 18 | I4: =RIGHT(YEAR(I$11),2) -> 18 | J4: =RIGHT(YEAR(J$11),2) -> 19 | ... AM4: =RIGHT(YEAR(AM$11),2) -> 26
C5: ="FY"&TEXT(C$3,"00") -> FY17 | D5: ="FY"&TEXT(D$3,"00") -> FY18 | E5: ="FY"&TEXT(E$3,"00") -> FY18 | F5: ="FY"&TEXT(F$3,"00") -> FY18 | G5: ="FY"&TEXT(G$3,"00") -> FY18 | H5: ="FY"&TEXT(H$3,"00") -> FY19 | I5: ="FY"&TEXT(I$3,"00") -> FY19 | J5: ="FY"&TEXT(J$3,"00") -> FY19 | ... AM5: ="FY"&TEXT(AM$3,"00") -> FY26
C6: ="CY"&TEXT(C$4,"00") -> CY17 | D6: ="CY"&TEXT(D$4,"00") -> CY17 | E6: ="CY"&TEXT(E$4,"00") -> CY17 | F6: ="CY"&TEXT(F$4,"00") -> CY18 | G6: ="CY"&TEXT(G$4,"00") -> CY18 | H6: ="CY"&TEXT(H$4,"00") -> CY18 | I6: ="CY"&TEXT(I$4,"00") -> CY18 | J6: ="CY"&TEXT(J$4,"00") -> CY19 | ... AM6: ="CY"&TEXT(AM$4,"00") -> CY26 | AP6: CY24 | AQ6: CY24 | AR6: CY25 | AS6: CY25 | AT6: CY26
C7: =C11-EOMONTH(C11,-3) -> 91 | D7: =D11-EOMONTH(D11,-3) -> 92 | E7: =E11-EOMONTH(E11,-3) -> 92 | F7: =F11-EOMONTH(F11,-3) -> 90 | G7: =G11-EOMONTH(G11,-3) -> 91 | H7: =H11-EOMONTH(H11,-3) -> 92 | I7: =I11-EOMONTH(I11,-3) -> 92 | J7: =J11-EOMONTH(J11,-3) -> 90 | ... AM7: =AM11-EOMONTH(AM11,-3) -> 91
D9: 1H18 | E9: 1H18 | F9: 2H18 | G9: 2H18 | H9: 1H19 | I9: 1H19 | J9: 2H19 | K9: 2H19 | L9: 1H20 | M9: 1H20 | N9: 2H20 | O9: 2H20 | P9: 1H21 | Q9: 1H21 | R9: 2H21 | S9: 2H21 | T9: 1H22 | U9: 1H22 | V9: 2H22 | W9: 2H22 | X9: 1H23 | Y9: 1H23 | Z9: 2H23 | AA9: 2H23 | AB9: 1H24 | AC9: 1H24 | AD9: 2H24 | AE9: 2H24 | AF9: 1H25 | AG9: 1H25 | AH9: 2H25 | AI9: 2H25 | AJ9: 1H26 | AK9: 1H26 | AL9: 2H26 | AM9: 2H26
C10: 4Q17 | D10: 1Q18 | E10: 2Q18 | F10: 3Q18 | G10: 4Q18 | H10: 1Q19 | I10: 2Q19 | J10: 3Q19 | K10: 4Q19 | L10: 1Q20 | M10: 2Q20 | N10: 3Q20 | O10: 4Q20 | P10: 1Q21 | Q10: 2Q21 | R10: 3Q21 | S10: 4Q21 | T10: 1Q22 | U10: 2Q22 | V10: 3Q22 | W10: 4Q22 | X10: 1Q23 | Y10: 2Q23 | Z10: 3Q23 | AA10: 4Q23 | AB10: 1Q24 | AC10: 2Q24 | AD10: 3Q24 | AE10: 4Q24 | AF10: 1Q25 | AG10: 2Q25 | AH10: 3Q25 | AI10: 4Q25 | AJ10: 1Q26 | AK10: 2Q26 | AL10: 3Q26 | AM10: 4Q26 | AO10: 1H24 | AP10: 2H24 | AQ10: 1H25 | AR10: 2H25 | AS10: 1H26 | AV10: FY18 | AW10: FY19 | AX10: FY20 | AY10: FY21 | AZ10: FY22 | BA10: FY23 | BB10: FY24 | BC10: FY25 | BG10: CY19 | BH10: CY20 | BI10: CY21 | BJ10: CY22 | BK10: CY23 | BL10: CY24 | BM10: CY25 | BN10: CY26
C11: 42916 | D11: =EOMONTH( C11, 3) -> 43008 | E11: =EOMONTH( D11, 3) -> 43100 | F11: =EOMONTH( E11, 3) -> 43190 | G11: =EOMONTH( F11, 3) -> 43281 | H11: =EOMONTH( G11, 3) -> 43373 | I11: =EOMONTH( H11, 3) -> 43465 | J11: =EOMONTH( I11, 3) -> 43555 | K11: =EOMONTH( J11, 3) -> 43646 | ... AM11: =EOMONTH( AL11, 3) -> 46203 | AO11: 45291 | AP11: =EOMONTH(AO11,6) -> 45473 | AQ11: =EOMONTH(AP11,6) -> 45657 | AR11: =EOMONTH(AQ11,6) -> 45838 | AS11: =EOMONTH(AR11,6) -> 46022 | AV11: 43281 | AW11: =EOMONTH(AV11,12) -> 43646 | AX11: =EOMONTH(AW11,12) -> 44012 | AY11: =EOMONTH(AX11,12) -> 44377 | AZ11: =EOMONTH(AY11,12) -> 44742 | BA11: =EOMONTH(AZ11,12) -> 45107 | BB11: =EOMONTH(BA11,12) -> 45473 | BC11: =EOMONTH(BB11,12) -> 45838 | BG11: 43830 | BH11: =EOMONTH(BG11,12) -> 44196 | BI11: =EOMONTH(BH11,12) -> 44561 | BJ11: =EOMONTH(BI11,12) -> 44926 | BK11: =EOMONTH(BJ11,12) -> 45291 | BL11: =EOMONTH(BK11,12) -> 45657 | BM11: =EOMONTH(BL11,12) -> 46022 | BN11: =EOMONTH(BM11,12) -> 46387
B12: Turnover | H12: 99.1 | I12: 110.5 | J12: 112.7 | K12: 167.8 | L12: 164.4 | M12: 184.8 | N12: 178.4 | O12: 302.9 | P12: 527.7 | Q12: 543.3 | R12: 423.2 | S12: 494.8 | T12: 631.4 | U12: 727 | V12: 579.4 | W12: 598.6 | X12: 611.9 | Y12: 938.5 | Z12: 579.8 | AA12: 502.3 | AB12: 566.9 | AC12: 901.6 | AD12: 605.5 | AE12: 602.7 | AF12: 557.5 | AG12: 591.5 | AH12: =1715.1-SUM(AQ12) -> 566.1 | AL12: =1690.7-SUM(AS12) -> 497.8 | AO12: 1468.5 | AP12: =BB12-AO12 -> 1208.3 | AQ12: 1149 | AR12: =BC12-AQ12 -> 1165.2 | AS12: 1192.9 | AW12: 490.1 | AX12: 830.5 | AY12: 1989 | AZ12: 2536.4 | BA12: 2632.6 | BB12: 2676.8 | BC12: 2314.2 | BG12: =SUMIF($H$6:$AM$6,BG$10,$H12:$AM12) -> 629.7 | BH12: =SUMIF($H$6:$AM$6,BH$10,$H12:$AM12) -> 1552.3 | BI12: =SUMIF($H$6:$AM$6,BI$10,$H12:$AM12) -> 2276.4 | BJ12: =SUMIF($H$6:$AM$6,BJ$10,$H12:$AM12) -> 2728.4 | BK12: =SUMIF($H$6:$AM$6,BK$10,$H12:$AM12) -> 2550.6 | BL12: =SUMIF($AO$6:$AT$6,BL$10,$AO12:$AT12) -> 2357.3 | BM12: =SUMIF($AO$6:$AT$6,BM$10,$AO12:$AT12) -> 2358.1 | BN12: =SUMIF($H$6:$AM$6,BN$10,$H12:$AM12) -> 497.8
B14: Gross Win | H14: 9.5 | I14: 12.3 | J14: 12.9 | K14: 15.8 | L14: 17.3 | M14: 20.7 | N14: 21.2 | O14: 41.6 | P14: 60.5 | Q14: 75.5 | R14: 54.8 | S14: 66.4 | T14: 87.9 | U14: 92.2 | V14: 78.8 | W14: 79.5 | X14: 73 | Y14: 93.5 | Z14: 70.3 | AA14: 72.3 | AB14: 71.6 | AC14: 88.1 | AD14: 76.9 | AE14: 78.6 | AF14: 73.5 | AG14: 80.5 | AH14: =228.3-SUM(AQ14) -> 74.3 | AL14: =224.3-SUM(AS14) -> 68.2 | AO14: 159.7 | AP14: =BB14-AO14 -> 155.5 | AQ14: 154 | AR14: =BC14-AQ14 -> 161.2 | AS14: 156.1 | AW14: 50.5 | AX14: 100.8 | AY14: 257.3 | AZ14: 338.4 | BA14: 309.1 | BB14: 315.2 | BC14: 315.2 | BG14: =SUMIF($H$6:$AM$6,BG$10,$H14:$AM14) -> 66.7 | BH14: =SUMIF($H$6:$AM$6,BH$10,$H14:$AM14) -> 198.8 | BI14: =SUMIF($H$6:$AM$6,BI$10,$H14:$AM14) -> 301.3 | BJ14: =SUMIF($H$6:$AM$6,BJ$10,$H14:$AM14) -> 324.8 | BK14: =SUMIF($H$6:$AM$6,BK$10,$H14:$AM14) -> 302.3 | BL14: =SUMIF($AO$6:$AT$6,BL$10,$AO14:$AT14) -> 309.5 | BM14: =SUMIF($AO$6:$AT$6,BM$10,$AO14:$AT14) -> 317.3 | BN14: =SUMIF($H$6:$AM$6,BN$10,$H14:$AM14) -> 68.2
B15: Gross Win Margin | H15: =H14/H12 -> 0.095862765 | I15: =I14/I12 -> 0.11131222 | J15: =J14/J12 -> 0.11446318 | K15: =K14/K12 -> 0.094159714 | L15: =L14/L12 -> 0.10523114 | M15: =M14/M12 -> 0.11201299 | N15: =N14/N12 -> 0.11883408 | O15: =O14/O12 -> 0.13733906 | ... AH15: =AH14/AH12 -> 0.1312489 | AL15: =AL14/AL12 -> 0.13700281 | AO15: =AO14/AO12 -> 0.10875043 | AP15: =AP14/AP12 -> 0.12869321 | AQ15: =AQ14/AQ12 -> 0.13402959 | AR15: =AR14/AR12 -> 0.13834535 | AS15: =AS14/AS12 -> 0.13085757 | AX15: =AX14/AX12 -> 0.12137267 | AY15: =AY14/AY12 -> 0.12936149 | AZ15: =AZ14/AZ12 -> 0.13341744 | BA15: =BA14/BA12 -> 0.11741244 | BB15: =BB14/BB12 -> 0.11775254 | BC15: =BC14/BC12 -> 0.13620258 | BG15: =BG14/BG12 -> 0.10592346 | BH15: =BH14/BH12 -> 0.12806803 | BI15: =BI14/BI12 -> 0.13235811 | BJ15: =BJ14/BJ12 -> 0.11904413 | BK15: =BK14/BK12 -> 0.11852113 | BL15: =BL14/BL12 -> 0.13129428 | BM15: =BM14/BM12 -> 0.13455748 | BN15: =BN14/BN12 -> 0.13700281
V17: =V20-V15 -> -0.045736969 | W17: =W20-W15 -> -0.040594721 | X17: =X20-X15 -> -0.041673476 | Y17: =Y20-Y15 -> -0.038145978 | Z17: =Z20-Z15 -> -0.03380476 | AA17: =AA20-AA15 -> -0.033247064 | AB17: =AB20-AB15 -> -0.033162815 | AC17: =AC20-AC15 -> -0.031721384 | ... AH17: =AH20-AH15 -> -0.031089913 | AL17: =AL20-AL15 -> -0.032141422
B19: Net Win | H19: 5 | I19: 8.3 | J19: 8.2 | K19: 7.5 | L19: 12.6 | M19: 14.6 | N19: 15.5 | O19: 32.4 | P19: 35.1 | Q19: 49.8 | R19: 38.2 | S19: 43.1 | T19: 54.8 | U19: 53.1 | V19: 52.3 | W19: 55.2 | X19: 47.5 | Y19: 57.7 | Z19: 50.7 | AA19: 55.6 | AB19: 52.8 | AC19: 59.5 | AD19: 60.8 | AE19: 60.1 | AF19: 56.6 | AG19: 60.5 | AH19: =173.8-SUM(AQ19) -> 56.7 | AL19: =167.3-SUM(AS19) -> 52.2 | AO19: 112.2 | AP19: =BB19-AO19 -> 120.9 | AQ19: 117.1 | AR19: =BC19-AQ19 -> 123.5 | AS19: 115.1 | AW19: 28.9 | AX19: 75.1 | AY19: 166.1 | AZ19: 215.4 | BA19: 211.7 | BB19: 233.1 | BC19: 240.6 | BG19: =SUMIF($H$6:$AM$6,BG$10,$H19:$AM19) -> 42.9 | BH19: =SUMIF($H$6:$AM$6,BH$10,$H19:$AM19) -> 132.8 | BI19: =SUMIF($H$6:$AM$6,BI$10,$H19:$AM19) -> 189.2 | BJ19: =SUMIF($H$6:$AM$6,BJ$10,$H19:$AM19) -> 212.7 | BK19: =SUMIF($H$6:$AM$6,BK$10,$H19:$AM19) -> 218.6 | BL19: =SUMIF($AO$6:$AT$6,BL$10,$AO19:$AT19) -> 238 | BM19: =SUMIF($AO$6:$AT$6,BM$10,$AO19:$AT19) -> 238.6 | BN19: =SUMIF($H$6:$AM$6,BN$10,$H19:$AM19) -> 52.2
B20: Net Win Margin | H20: =H19/H12 -> 0.050454087 | I20: =I19/I12 -> 0.075113122 | J20: =J19/J12 -> 0.072759539 | K20: =K19/K12 -> 0.044696067 | L20: =L19/L12 -> 0.076642336 | M20: =M19/M12 -> 0.079004329 | N20: =N19/N12 -> 0.086883408 | O20: =O19/O12 -> 0.106966 | ... AH20: =AH19/AH12 -> 0.10015898 | AL20: =AL19/AL12 -> 0.10486139 | AO20: =AO19/AO12 -> 0.076404494 | AP20: =AP19/AP12 -> 0.10005793 | AQ20: =AQ19/AQ12 -> 0.10191471 | AR20: =AR19/AR12 -> 0.10599039 | AS20: =AS19/AS12 -> 0.096487551 | AW20: =AW19/AW12 -> 0.058967558 | AX20: =AX19/AX12 -> 0.090427453 | AY20: =AY19/AY12 -> 0.083509301 | AZ20: =AZ19/AZ12 -> 0.084923514 | BA20: =BA19/BA12 -> 0.080414799 | BB20: =BB19/BB12 -> 0.08708159 | BC20: =BC19/BC12 -> 0.10396681 | BG20: =BG19/BG12 -> 0.06812768 | BH20: =BH19/BH12 -> 0.085550473 | BI20: =BI19/BI12 -> 0.083113688 | BJ20: =BJ19/BJ12 -> 0.077957777 | BK20: =BK19/BK12 -> 0.085705324 | BL20: =BL19/BL12 -> 0.10096297 | BM20: =BM19/BM12 -> 0.10118316 | BN20: =BN19/BN12 -> 0.10486139
B22: Active Customers (LTM) | H22: 32913 | I22: 45828 | J22: 56788 | K22: 68464 | L22: 72011 | M22: 81014 | N22: 83330 | O22: 90422 | P22: 124715 | Q22: 142992 | R22: 158041 | S22: 196585 | T22: 222662 | U22: 232875 | V22: 232763 | W22: 239121 | X22: 231627 | Y22: 234989 | Z22: 238054 | AA22: 238624 | AB22: 235113 | AC22: 218288 | AD22: 221000 | AE22: 227900 | AF22: 238400 | AG22: 235100 | AO22: 218288 | AP22: =BB22 -> 227900 | AQ22: 235100 | AR22: =BC22 -> 237400 | AS22: =AQ22*(1-3%) -> 228047 | AW22: 68464 | AX22: 90422 | AY22: 96585 | AZ22: 239121 | BA22: 238624 | BB22: 227900 | BC22: =295800-58400 -> 237400
B25: GST, Point of Consumption Tax, and Product Fee payments to Australian Governments and Racing and Sports Bodies, representing | AD25: 26.4 | AE25: 27.3 | AF25: 26.9
B27: Revenue ex GST | BA27: =BA19*10/11 -> 192.45455 | BB27: =BB19*10/11 -> 211.90909 | BC27: =BC19*10/11 -> 218.72727 | BG27: =BG19*10/11 -> 39 | BH27: =BH19*10/11 -> 120.72727 | BI27: =BI19*10/11 -> 172 | BJ27: =BJ19*10/11 -> 193.36364 | BK27: =BK19*10/11 -> 198.72727 | BL27: =BL19*10/11 -> 216.36364 | BM27: =BM19*10/11 -> 216.90909 | BN27: =BN19*10/11 -> 47.454545
B31: Revenue | AH31: =157.8-SUM(AQ31) -> 51.6 | AL31: =152-SUM(AS31) -> 47.1 | AO31: 101.7 | AP31: =BB31-AO31 -> 109.8 | AQ31: 106.2 | AR31: =BC31-AQ31 -> 112.3 | AS31: 104.9 | BA31: 192.1 | BB31: 211.5 | BC31: 218.5 | BG31: =SUMIF($H$6:$AM$6,BG$10,$H31:$AM31) -> 0 | BH31: =SUMIF($H$6:$AM$6,BH$10,$H31:$AM31) -> 0 | BI31: =SUMIF($H$6:$AM$6,BI$10,$H31:$AM31) -> 0 | BJ31: =SUMIF($H$6:$AM$6,BJ$10,$H31:$AM31) -> 0 | BK31: =SUMIF($H$6:$AM$6,BK$10,$H31:$AM31) -> 0 | BL31: =SUMIF($H$6:$AM$6,BL$10,$H31:$AM31) -> 0 | BM31: =SUMIF($H$6:$AM$6,BM$10,$H31:$AM31) -> 51.6 | BN31: =SUMIF($H$6:$AM$6,BN$10,$H31:$AM31) -> 47.1
B32: Gross Profit | AH32: =84-SUM(AQ32) -> 28.2 | AL32: =77-SUM(AS32) -> 24.7 | AO32: 50.1 | AP32: =BB32-AO32 -> 61.7 | AQ32: 55.8 | AR32: =BC32-AQ32 -> 58.7 | AS32: 52.3 | BA32: 98.4 | BB32: 111.8 | BC32: 114.5 | BG32: =SUMIF($H$6:$AM$6,BG$10,$H32:$AM32) -> 0 | BH32: =SUMIF($H$6:$AM$6,BH$10,$H32:$AM32) -> 0 | BI32: =SUMIF($H$6:$AM$6,BI$10,$H32:$AM32) -> 0 | BJ32: =SUMIF($H$6:$AM$6,BJ$10,$H32:$AM32) -> 0 | BK32: =SUMIF($H$6:$AM$6,BK$10,$H32:$AM32) -> 0 | BL32: =SUMIF($H$6:$AM$6,BL$10,$H32:$AM32) -> 0 | BM32: =SUMIF($H$6:$AM$6,BM$10,$H32:$AM32) -> 28.2 | BN32: =SUMIF($H$6:$AM$6,BN$10,$H32:$AM32) -> 24.7
O33: 20.1 FY20
B34: Marketing Expense | N34: =7-2 -> 5 | O34: 6.5 | P34: 11.3 | Q34: 9.7 | R34: 13.5 | S34: 16.9 | T34: 22.1 | U34: 22.6 | V34: 7.1 | W34: 9.6 | X34: 25.2 | Y34: 20.2 | Z34: 8.3 | AA34: 7.4 | AB34: 14.8 | AC34: 13.6 | AH34: =32.5-SUM(AQ34) -> 7.2 | AL34: =32.8-SUM(AS34) -> 9.3 | AO34: =AQ34/(1-11%) -> 28.426966 | AP34: =BB34-AO34 -> 16.773034 | AQ34: 25.3 | AR34: =BC34-AQ34 -> 16.8 | AS34: 23.5 | AX34: 20.1 | AY34: 51.4 | AZ34: 61.5 | BA34: 61 | BB34: 45.2 | BC34: 42.1 | BG34: =SUMIF($H$6:$AM$6,BG$10,$H34:$AM34) -> 0 | BH34: =SUMIF($H$6:$AM$6,BH$10,$H34:$AM34) -> 32.5 | BI34: =SUMIF($H$6:$AM$6,BI$10,$H34:$AM34) -> 75.1 | BJ34: =SUMIF($H$6:$AM$6,BJ$10,$H34:$AM34) -> 62.1 | BK34: =SUMIF($H$6:$AM$6,BK$10,$H34:$AM34) -> 44.1 | BL34: =SUMIF($AO$6:$AT$6,BL$10,$AO34:$AT34) -> 42.073034 | BM34: =SUMIF($AO$6:$AT$6,BM$10,$AO34:$AT34) -> 40.3 | BN34: =SUMIF($H$6:$AM$6,BN$10,$H34:$AM34) -> 9.3
B35: Other Opex | AH35: =AH37-AH32+AH34 -> -11.3 | AL35: =AL37-AL32+AL34 -> -8.3 | AO35: =AO37-AO32+AO34 -> -19.373034 | AP35: =AP37-AP32+AP34 -> -20.426966 | AQ35: =AQ37-AQ32+AQ34 -> -19.8 | AR35: =AR37-AR32+AR34 -> -22.5 | AS35: =AS37-AS32+AS34 -> -21.7 | BA35: =BA37-BA32+BA34 -> -37.3 | BB35: =BB37-BB32+BB34 -> -39.8 | BC35: =BC37-BC32+BC34 -> -42.3
B37: Statutory EBITDA | AH37: =20.4-SUM(AQ37) -> 9.7 | AL37: =14.2-SUM(AS37) -> 7.1 | AO37: 2.3 | AP37: =BB37-AO37 -> 24.5 | AQ37: 10.7 | AR37: =BC37-AQ37 -> 19.4 | AS37: 7.1 | BA37: 0.1 | BB37: 26.8 | BC37: 30.1 | BG37: =SUMIF($H$6:$AM$6,BG$10,$H37:$AM37) -> 0 | BH37: =SUMIF($H$6:$AM$6,BH$10,$H37:$AM37) -> 0 | BI37: =SUMIF($H$6:$AM$6,BI$10,$H37:$AM37) -> 0 | BJ37: =SUMIF($H$6:$AM$6,BJ$10,$H37:$AM37) -> 0 | BK37: =SUMIF($H$6:$AM$6,BK$10,$H37:$AM37) -> 0 | BL37: =SUMIF($H$6:$AM$6,BL$10,$H37:$AM37) -> 0 | BM37: =SUMIF($H$6:$AM$6,BM$10,$H37:$AM37) -> 9.7 | BN37: =SUMIF($H$6:$AM$6,BN$10,$H37:$AM37) -> 7.1
AO39: point | AP39: =AP32/AP31 -> 0.56193078 | AQ39: =AQ32/AQ31 -> 0.52542373 | AR39: =AR32/AR31 -> 0.52270703 | AS39: =AS32/AS31 -> 0.49857007 | BA39: =BA32/BA31 -> 0.51223321 | BB39: =BB32/BB31 -> 0.5286052 | BC39: =BC32/BC31 -> 0.52402746 | BG39: =BG32/BG31 -> #DIV/0! | BH39: =BH32/BH31 -> #DIV/0! | BI39: =BI32/BI31 -> #DIV/0! | BJ39: =BJ32/BJ31 -> #DIV/0! | BK39: =BK32/BK31 -> #DIV/0!

Sheet BBET + BetR
AM2: X
C3: =IF(MONTH(C11)>6,RIGHT(YEAR(C11),2)+1,RIGHT(YEAR(C11),2)) -> 17 | D3: =IF(MONTH(D11)>6,RIGHT(YEAR(D11),2)+1,RIGHT(YEAR(D11),2)) -> 18 | E3: =IF(MONTH(E11)>6,RIGHT(YEAR(E11),2)+1,RIGHT(YEAR(E11),2)) -> 18 | F3: =IF(MONTH(F11)>6,RIGHT(YEAR(F11),2)+1,RIGHT(YEAR(F11),2)) -> 18 | G3: =IF(MONTH(G11)>6,RIGHT(YEAR(G11),2)+1,RIGHT(YEAR(G11),2)) -> 18 | H3: =IF(MONTH(H11)>6,RIGHT(YEAR(H11),2)+1,RIGHT(YEAR(H11),2)) -> 19 | I3: =IF(MONTH(I11)>6,RIGHT(YEAR(I11),2)+1,RIGHT(YEAR(I11),2)) -> 19 | J3: =IF(MONTH(J11)>6,RIGHT(YEAR(J11),2)+1,RIGHT(YEAR(J11),2)) -> 19 | ... AM3: =IF(MONTH(AM11)>6,RIGHT(YEAR(AM11),2)+1,RIGHT(YEAR(AM11),2)) -> 26
C4: =RIGHT(YEAR(C$11),2) -> 17 | D4: =RIGHT(YEAR(D$11),2) -> 17 | E4: =RIGHT(YEAR(E$11),2) -> 17 | F4: =RIGHT(YEAR(F$11),2) -> 18 | G4: =RIGHT(YEAR(G$11),2) -> 18 | H4: =RIGHT(YEAR(H$11),2) -> 18 | I4: =RIGHT(YEAR(I$11),2) -> 18 | J4: =RIGHT(YEAR(J$11),2) -> 19 | ... AM4: =RIGHT(YEAR(AM$11),2) -> 26
C5: ="FY"&TEXT(C$3,"00") -> FY17 | D5: ="FY"&TEXT(D$3,"00") -> FY18 | E5: ="FY"&TEXT(E$3,"00") -> FY18 | F5: ="FY"&TEXT(F$3,"00") -> FY18 | G5: ="FY"&TEXT(G$3,"00") -> FY18 | H5: ="FY"&TEXT(H$3,"00") -> FY19 | I5: ="FY"&TEXT(I$3,"00") -> FY19 | J5: ="FY"&TEXT(J$3,"00") -> FY19 | ... AM5: ="FY"&TEXT(AM$3,"00") -> FY26
C6: ="CY"&TEXT(C$4,"00") -> CY17 | D6: ="CY"&TEXT(D$4,"00") -> CY17 | E6: ="CY"&TEXT(E$4,"00") -> CY17 | F6: ="CY"&TEXT(F$4,"00") -> CY18 | G6: ="CY"&TEXT(G$4,"00") -> CY18 | H6: ="CY"&TEXT(H$4,"00") -> CY18 | I6: ="CY"&TEXT(I$4,"00") -> CY18 | J6: ="CY"&TEXT(J$4,"00") -> CY19 | ... AM6: ="CY"&TEXT(AM$4,"00") -> CY26
C7: =C11-EOMONTH(C11,-3) -> 91 | D7: =D11-EOMONTH(D11,-3) -> 92 | E7: =E11-EOMONTH(E11,-3) -> 92 | F7: =F11-EOMONTH(F11,-3) -> 90 | G7: =G11-EOMONTH(G11,-3) -> 91 | H7: =H11-EOMONTH(H11,-3) -> 92 | I7: =I11-EOMONTH(I11,-3) -> 92 | J7: =J11-EOMONTH(J11,-3) -> 90 | ... AM7: =AM11-EOMONTH(AM11,-3) -> 91
D9: 1H18 | E9: 1H18 | F9: 2H18 | G9: 2H18 | H9: 1H19 | I9: 1H19 | J9: 2H19 | K9: 2H19 | L9: 1H20 | M9: 1H20 | N9: 2H20 | O9: 2H20 | P9: 1H21 | Q9: 1H21 | R9: 2H21 | S9: 2H21 | T9: 1H22 | U9: 1H22 | V9: 2H22 | W9: 2H22 | X9: 1H23 | Y9: 1H23 | Z9: 2H23 | AA9: 2H23 | AB9: 1H24 | AC9: 1H24 | AD9: 2H24 | AE9: 2H24 | AF9: 1H25 | AG9: 1H25 | AH9: 2H25 | AI9: 2H25 | AJ9: 1H26 | AK9: 1H26 | AL9: 2H26 | AM9: 2H26
C10: 4Q17 | D10: 1Q18 | E10: 2Q18 | F10: 3Q18 | G10: 4Q18 | H10: 1Q19 | I10: 2Q19 | J10: 3Q19 | K10: 4Q19 | L10: 1Q20 | M10: 2Q20 | N10: 3Q20 | O10: 4Q20 | P10: 1Q21 | Q10: 2Q21 | R10: 3Q21 | S10: 4Q21 | T10: 1Q22 | U10: 2Q22 | V10: 3Q22 | W10: 4Q22 | X10: 1Q23 | Y10: 2Q23 | Z10: 3Q23 | AA10: 4Q23 | AB10: 1Q24 | AC10: 2Q24 | AD10: 3Q24 | AE10: 4Q24 | AF10: 1Q25 | AG10: 2Q25 | AH10: 3Q25 | AI10: 4Q25 | AJ10: 1Q26 | AK10: 2Q26 | AL10: 3Q26 | AM10: 4Q26
C11: 42916 | D11: =EOMONTH( C11, 3) -> 43008 | E11: =EOMONTH( D11, 3) -> 43100 | F11: =EOMONTH( E11, 3) -> 43190 | G11: =EOMONTH( F11, 3) -> 43281 | H11: =EOMONTH( G11, 3) -> 43373 | I11: =EOMONTH( H11, 3) -> 43465 | J11: =EOMONTH( I11, 3) -> 43555 | K11: =EOMONTH( J11, 3) -> 43646 | ... AM11: =EOMONTH( AL11, 3) -> 46203
B12: Turnover | P12: 75.2 | Q12: 89.5 | R12: 83.5 | S12: 96.5 | T12: 125.9 | U12: 138.6 | V12: 120.7 | W12: 126.7 | X12: 132.8 | Y12: 146.3 | Z12: 119.1 | AA12: 131.6 | AB12: 143.9 | AC12: 154.8 | AD12: 139.6 | AE12: 153.6
B14: Gross Win | P14: 9.6 | Q14: 11.5 | R14: 10.4 | S14: 12.7 | T14: 18.1 | U14: 18.4 | V14: 17 | W14: 17 | X14: 17.8 | Y14: 18.2 | Z14: 15.8 | AA14: 19.1 | AB14: 18.8 | AC14: 10.5 | AD14: 18.7 | AE14: 20.8
B15: Gross Win Margin | H15: =H14/H12 -> #DIV/0! | I15: =I14/I12 -> #DIV/0! | J15: =J14/J12 -> #DIV/0! | K15: =K14/K12 -> #DIV/0! | L15: =L14/L12 -> #DIV/0! | M15: =M14/M12 -> #DIV/0! | N15: =N14/N12 -> #DIV/0! | O15: =O14/O12 -> #DIV/0! | ... AE15: =AE14/AE12 -> 0.13541667
B17: Net Win | P17: 7.9 | Q17: 9.1 | R17: 8.5 | S17: 10.1 | T17: 14.8 | U17: 13.8 | V17: 13.2 | W17: 12.8 | X17: 13.5 | Y17: 13.7 | Z17: 12 | AA17: 14.9 | AB17: 14.5 | AC17: 16.2 | AD17: 15.9 | AE17: 17.3
B18: Net Win Margin | H18: =H17/H12 -> #DIV/0! | I18: =I17/I12 -> #DIV/0! | J18: =J17/J12 -> #DIV/0! | K18: =K17/K12 -> #DIV/0! | L18: =L17/L12 -> #DIV/0! | M18: =M17/M12 -> #DIV/0! | N18: =N17/N12 -> #DIV/0! | O18: =O17/O12 -> #DIV/0! | ... AE18: =AE17/AE12 -> 0.11263021
B20: Active Customers (LTM) | L20: 20045 | M20: 19479 | N20: 20217 | O20: 22289 | P20: 23927 | Q20: 25540 | R20: 26824 | S20: 32472 | T20: 39195 | U20: 45087 | V20: 49556 | W20: 53328 | X20: 54920 | Y20: 59632 | Z20: 63118 | AA20: 65415 | AB20: 66526 | AC20: 67391 | AD20: 67732 | AE20: 70456
P21: =P12/P20*1000000 -> 3142.893 | Q21: =Q12/Q20*1000000 -> 3504.307 | R21: =R12/R20*1000000 -> 3112.884 | S21: =S12/S20*1000000 -> 2971.7911 | T21: =T12/T20*1000000 -> 3212.1444 | U21: =U12/U20*1000000 -> 3074.0568 | V21: =V12/V20*1000000 -> 2435.6284 | W21: =W12/W20*1000000 -> 2375.8626 | ... AE21: =AE12/AE20*1000000 -> 2180.084
P22: =P17/P20*1000000 -> 330.17094 | Q22: =Q17/Q20*1000000 -> 356.30384 | R22: =R17/R20*1000000 -> 316.88041 | S22: =S17/S20*1000000 -> 311.0372 | T22: =T17/T20*1000000 -> 377.59918 | U22: =U17/U20*1000000 -> 306.07492 | V22: =V17/V20*1000000 -> 266.36532 | W22: =W17/W20*1000000 -> 240.024 | ... AE22: =AE17/AE20*1000000 -> 245.54332
B25: Turnover | Z25: 354.2 | AD25: 273.1 | AF25: 286.6 | AG25: 357 | AH25: 376 | AI25: 399.5 | AJ25: 363 | AK25: 444.4 | AL25: 383
B27: Gross Win | Z27: 37.6 | AD27: 37.1 | AF27: 38.8 | AG27: 52.2 | AH27: 51.7 | AI27: 53.1 | AJ27: 51.8 | AK27: 55.9 | AL27: 50.3
B28: Gross Win Margin | Z28: 0.10615471 | AD28: 0.13584767 | AF28: =AF27/AF25 -> 0.13538032 | AG28: =AG27/AG25 -> 0.14621849 | AH28: =AH27/AH25 -> 0.1375 | AI28: =AI27/AI25 -> 0.13291615 | AJ28: =AJ27/AJ25 -> 0.14269972 | AK28: =AK27/AK25 -> 0.12578758 | AL28: =AL27/AL25 -> 0.13133159
B30: Net Win | Z30: 15 | AD30: 23.3 | AF30: 27.9 | AG30: 39.2 | AH30: 37.8 | AI30: 40.2 | AJ30: 38 | AK30: 37.9 | AL30: 38.2
B31: Net Win Margin | Z31: 0.042348955 | AD31: 0.085316734 | AF31: =AF30/AF25 -> 0.097348221 | AG31: =AG30/AG25 -> 0.10980392 | AH31: =AH30/AH25 -> 0.10053191 | AI31: =AI30/AI25 -> 0.10062578 | AJ31: =AJ30/AJ25 -> 0.1046832 | AK31: =AK30/AK25 -> 0.085283528 | AL31: =AL30/AL25 -> 0.099738903
B33: Active Customers (LTM) | AD33: 112083 | AF33: 120200 | AG33: 144700 | AH33: 153000 | AI33: 155400 | AJ33: 154700 | AK33: 163500 | AL33: 157264
AD34: =AD25/AD33*1000000 -> 2436.5872 | AF34: =AF25/AF33*1000000 -> 2384.3594 | AG34: =AG25/AG33*1000000 -> 2467.1735 | AH34: =AH25/AH33*1000000 -> 2457.5163 | AI34: =AI25/AI33*1000000 -> 2570.7851 | AJ34: =AJ25/AJ33*1000000 -> 2346.4771 | AK34: =AK25/AK33*1000000 -> 2718.0428 | AL34: =AL25/AL33*1000000 -> 2435.3953
AD35: =AD30/AD33*1000000 -> 207.88166 | AF35: =AF30/AF33*1000000 -> 232.11314 | AG35: =AG30/AG33*1000000 -> 270.90532 | AH35: =AH30/AH33*1000000 -> 247.05882 | AI35: =AI30/AI33*1000000 -> 258.68726 | AJ35: =AJ30/AJ33*1000000 -> 245.63672 | AK35: =AK30/AK33*1000000 -> 231.80428 | AL35: =AL30/AL33*1000000 -> 242.90365
B38: Marketing | AD38: 1.6 | AE38: 2.2
AD42: =SUM(AD43:AD45)/SUM(Z43:Z45)-1 -> 0.10051282
B43: Thouroughbred | P43: 37.4 | Q43: 48.6 | R43: 42.3 | S43: 45.5 | T43: 59.3 | U43: 77.7 | V43: 62.5 | W43: 59.4 | X43: 63.2 | Y43: 80.4 | Z43: 61.3 | AA43: 59.7 | AB43: 66.5 | AC43: =147.2-AB43 -> 80.7 | AD43: 65.2 | AE43: 64.2
B44: Greyhound | P44: 20.1 | Q44: 24.8 | R44: 20.9 | S44: 25.1 | T44: 37.3 | U44: 35.4 | V44: 32.6 | W44: 32.7 | X44: 36.5 | Y44: 33.6 | Z44: 27 | AA44: 32.4 | AB44: 35.6 | AC44: =71-AB44 -> 35.4 | AD44: 33 | AE44: 40.3
B45: Harness | P45: 7.1 | Q45: 8 | R45: 7.9 | S45: 9.1 | T45: 12 | U45: 12.4 | V45: 10.8 | W45: 11.1 | X45: 13 | Y45: 11.5 | Z45: 9.2 | AA45: 10.1 | AB45: 10.9 | AC45: =22.4-AB45 -> 11.5 | AD45: 9.1 | AE45: 11.5
B46: Sport | P46: 10.6 | Q46: 8.1 | R46: 12.4 | S46: 16.8 | T46: 17.3 | U46: 13.1 | V46: 14.8 | W46: 23.5 | X46: 20.1 | Y46: 20.8 | Z46: 21.6 | AA46: 29.5 | AB46: 30.9 | AC46: =58.1-AB46 -> 27.2 | AD46: 32.3 | AE46: 37.5
B48: iPhone | P48: 38.3 | Q48: 46.4 | R48: 45.4 | S48: 52.2 | T48: 70.6 | U48: 77.5 | V48: 65.4 | W48: 68.1 | X48: 73.7 | Y48: 84 | Z48: 66.2 | AA48: 73.2 | AB48: 83.6 | AC48: =170.3-AB48 -> 86.7 | AD48: 77 | AE48: 91.5
B49: Website | P49: 26.3 | Q49: 33 | R49: 27.3 | S49: 31.7 | T49: 39.5 | U49: 44.1 | V49: 41.2 | W49: 41.3 | X49: 40.9 | Y49: 44.3 | Z49: 36.5 | AA49: 38.9 | AB49: 41.1 | AC49: =88.4-AB49 -> 47.3 | AD49: 46.7 | AE49: 41.7
B50: Android | P50: 8.1 | Q50: 7.2 | R50: 6.5 | S50: 8.8 | T50: 12.9 | U50: 14.4 | V50: 11.8 | W50: 14.8 | X50: 16.4 | Y50: 15.8 | Z50: 14.5 | AA50: 17.3 | AB50: 16.8 | AC50: =34.7-AB50 -> 17.9 | AD50: 13.6 | AE50: 17.4
B51: Call Centre | P51: 2.5 | Q51: 2.9 | R51: 4.3 | S51: 3.8 | T51: 2.9 | U51: 2.7 | V51: 2.3 | W51: 2.4 | X51: 1.8 | Y51: 2.2 | Z51: 2 | AA51: 2.3 | AB51: 2.4 | AC51: =5.3-AB51 -> 2.9 | AD51: 2.3 | AE51: 3
B53: Bet Count
B54: Cost per First Time Depositor | P54: 136 | Q54: 170 | R54: 182 | S54: 214 | T54: 142 | U54: 195 | V54: 312 | W54: 366 | X54: 405 | Y54: 447 | Z54: 310 | AA54: 362 | AB54: 413 | AD54: 250 | AE54: 205
B55: Average Annual Customer Value | P55: 963 | Q55: 1119 | R55: 1261 | S55: 1095 | T55: 1083 | U55: 1044 | V55: 1044 | W55: 1025 | X55: 995 | Y55: 884 | AA55: 826 | AB55: 828 | AD55: 908 | AE55: 898
AD56: =AD54/Z54-1 -> -0.19354839
AD57: =AD55/Z55-1 -> #DIV/0!
B58: Check | C58: =C12-SUM(C43:C46) -> 0 | D58: =D12-SUM(D43:D46) -> 0 | E58: =E12-SUM(E43:E46) -> 0 | F58: =F12-SUM(F43:F46) -> 0 | G58: =G12-SUM(G43:G46) -> 0 | H58: =H12-SUM(H43:H46) -> 0 | I58: =I12-SUM(I43:I46) -> 0 | J58: =J12-SUM(J43:J46) -> 0 | ... AB58: =AB12-SUM(AB43:AB46) -> 0 | AD58: =AD12-SUM(AD43:AD46) -> 0
B59: Check | C59: =C12-SUM(C48:C51) -> 0 | D59: =D12-SUM(D48:D51) -> 0 | E59: =E12-SUM(E48:E51) -> 0 | F59: =F12-SUM(F48:F51) -> 0 | G59: =G12-SUM(G48:G51) -> 0 | H59: =H12-SUM(H48:H51) -> 0 | I59: =I12-SUM(I48:I51) -> 0 | J59: =J12-SUM(J48:J51) -> 0 | ... T59: =T12-SUM(T48:T51) -> 0 | U59: =U12-SUM(U43:U46) -> 0 | V59: =V12-SUM(V48:V51) -> 0 | W59: =W12-SUM(W48:W51) -> 0.1 | X59: =X12-SUM(X48:X51) -> 0 | Y59: =Y12-SUM(Y48:Y51) -> 0 | Z59: =Z12-SUM(Z48:Z51) -> -0.1 | AA59: =AA12-SUM(AA48:AA51) -> -0.1 | AB59: =AB12-SUM(AB48:AB51) -> 0 | AD59: =AD12-SUM(AD48:AD51) -> 0
B61: NWM
B62: iPhone | P62: 0.116 | Q62: 0.112 | R62: 0.12 | S62: 0.116 | T62: 0.128 | U62: 0.106 | V62: 0.124 | W62: 0.125 | X62: 0.113 | Y62: 0.101 | Z62: 0.111 | AA62: 0.108 | AB62: 0.105 | AD62: 0.127
B63: Website | P63: 0.084 | Q63: 0.087 | R63: 0.079 | S63: 0.081 | T63: 0.098 | U63: 0.086 | V63: 0.087 | W63: 0.076 | X63: 0.082 | Y63: 0.07 | Z63: 0.084 | AA63: 0.075 | AB63: 0.08 | AD63: 0.078
B64: Android | P64: 0.116 | Q64: 0.112 | R64: 0.102 | S64: 0.128 | T64: 0.123 | U64: 0.115 | V64: 0.119 | W64: 0.131 | X64: 0.106 | Y64: 0.117 | Z64: 0.121 | AA64: 0.104 | AB64: 0.119 | AD64: 0.129
B65: Call Centre | P65: 0.036 | Q65: 0.077 | R65: 0.062 | S65: 0.082 | T65: 0.097 | U65: -0.003 | V65: 0.053 | W65: 0.154 | X65: 0.057 | Y65: -0.005 | Z65: 0.112 | AA65: 0.151 | AB65: 0.092 | AD65: 0.057
B67: Thouroughbred | AA67: =AA43/W43-1 -> 0.0050505051 | AB67: =AB43/X43-1 -> 0.05221519 | AC67: =AC43/Y43-1 -> 0.0037313433 | AD67: =AD43/Z43-1 -> 0.063621533
B68: Greyhound | AA68: =AA44/W44-1 -> -0.0091743119 | AB68: =AB44/X44-1 -> -0.024657534 | AC68: =AC44/Y44-1 -> 0.053571429 | AD68: =AD44/Z44-1 -> 0.22222222
B69: Harness | AA69: =AA45/W45-1 -> -0.09009009 | AB69: =AB45/X45-1 -> -0.16153846 | AC69: =AC45/Y45-1 -> 0 | AD69: =AD45/Z45-1 -> -0.010869565
B70: Sport | AA70: =AA46/W46-1 -> 0.25531915 | AB70: =AB46/X46-1 -> 0.53731343 | AC70: =AC46/Y46-1 -> 0.30769231 | AD70: =AD46/Z46-1 -> 0.49537037
B72: Thouroughbred | P72: =P43/P$12 -> 0.49734043 | Q72: =Q43/Q$12 -> 0.54301676 | R72: =R43/R$12 -> 0.50658683 | S72: =S43/S$12 -> 0.47150259 | T72: =T43/T$12 -> 0.47100874 | U72: =U43/U$12 -> 0.56060606 | V72: =V43/V$12 -> 0.51781276 | W72: =W43/W$12 -> 0.46882399 | ... AE72: =AE43/AE$12 -> 0.41796875
B73: Greyhound | P73: =P44/P$12 -> 0.26728723 | Q73: =Q44/Q$12 -> 0.27709497 | R73: =R44/R$12 -> 0.2502994 | S73: =S44/S$12 -> 0.26010363 | T73: =T44/T$12 -> 0.29626688 | U73: =U44/U$12 -> 0.25541126 | V73: =V44/V$12 -> 0.27009114 | W73: =W44/W$12 -> 0.25808998 | ... AE73: =AE44/AE$12 -> 0.26236979
B74: Harness | P74: =P45/P$12 -> 0.094414894 | Q74: =Q45/Q$12 -> 0.089385475 | R74: =R45/R$12 -> 0.094610778 | S74: =S45/S$12 -> 0.094300518 | T74: =T45/T$12 -> 0.095313741 | U74: =U45/U$12 -> 0.089466089 | V74: =V45/V$12 -> 0.089478045 | W74: =W45/W$12 -> 0.087608524 | ... AE74: =AE45/AE$12 -> 0.074869792
B75: Sport | P75: =P46/P$12 -> 0.14095745 | Q75: =Q46/Q$12 -> 0.090502793 | R75: =R46/R$12 -> 0.14850299 | S75: =S46/S$12 -> 0.17409326 | T75: =T46/T$12 -> 0.13741064 | U75: =U46/U$12 -> 0.094516595 | V75: =V46/V$12 -> 0.12261806 | W75: =W46/W$12 -> 0.18547751 | ... AE75: =AE46/AE$12 -> 0.24414062

Sheet BETR
B2: https://www.bluebetplc.com/_files/ugd/b0ca0f_63bddb44985044d2b2f70a4eeed24e0e.pdf
C3: =IF(MONTH(C11)>6,RIGHT(YEAR(C11),2)+1,RIGHT(YEAR(C11),2)) -> 17 | D3: =IF(MONTH(D11)>6,RIGHT(YEAR(D11),2)+1,RIGHT(YEAR(D11),2)) -> 18 | E3: =IF(MONTH(E11)>6,RIGHT(YEAR(E11),2)+1,RIGHT(YEAR(E11),2)) -> 18 | F3: =IF(MONTH(F11)>6,RIGHT(YEAR(F11),2)+1,RIGHT(YEAR(F11),2)) -> 18 | G3: =IF(MONTH(G11)>6,RIGHT(YEAR(G11),2)+1,RIGHT(YEAR(G11),2)) -> 18 | H3: =IF(MONTH(H11)>6,RIGHT(YEAR(H11),2)+1,RIGHT(YEAR(H11),2)) -> 19 | I3: =IF(MONTH(I11)>6,RIGHT(YEAR(I11),2)+1,RIGHT(YEAR(I11),2)) -> 19 | J3: =IF(MONTH(J11)>6,RIGHT(YEAR(J11),2)+1,RIGHT(YEAR(J11),2)) -> 19 | ... AM3: =IF(MONTH(AM11)>6,RIGHT(YEAR(AM11),2)+1,RIGHT(YEAR(AM11),2)) -> 26 | AO3: =IF(MONTH(AO11)>6,RIGHT(YEAR(AO11),2)+1,RIGHT(YEAR(AO11),2)) -> 17 | AP3: =IF(MONTH(AP11)>6,RIGHT(YEAR(AP11),2)+1,RIGHT(YEAR(AP11),2)) -> 18 | AQ3: =IF(MONTH(AQ11)>6,RIGHT(YEAR(AQ11),2)+1,RIGHT(YEAR(AQ11),2)) -> 18 | AR3: =IF(MONTH(AR11)>6,RIGHT(YEAR(AR11),2)+1,RIGHT(YEAR(AR11),2)) -> 19 | AS3: =IF(MONTH(AS11)>6,RIGHT(YEAR(AS11),2)+1,RIGHT(YEAR(AS11),2)) -> 19 | AT3: =IF(MONTH(AT11)>6,RIGHT(YEAR(AT11),2)+1,RIGHT(YEAR(AT11),2)) -> 20 | AU3: =IF(MONTH(AU11)>6,RIGHT(YEAR(AU11),2)+1,RIGHT(YEAR(AU11),2)) -> 20 | AV3: =IF(MONTH(AV11)>6,RIGHT(YEAR(AV11),2)+1,RIGHT(YEAR(AV11),2)) -> 21 | ... BG3: =IF(MONTH(BG11)>6,RIGHT(YEAR(BG11),2)+1,RIGHT(YEAR(BG11),2)) -> 26
C4: =RIGHT(YEAR(C$11),2) -> 17 | D4: =RIGHT(YEAR(D$11),2) -> 17 | E4: =RIGHT(YEAR(E$11),2) -> 17 | F4: =RIGHT(YEAR(F$11),2) -> 18 | G4: =RIGHT(YEAR(G$11),2) -> 18 | H4: =RIGHT(YEAR(H$11),2) -> 18 | I4: =RIGHT(YEAR(I$11),2) -> 18 | J4: =RIGHT(YEAR(J$11),2) -> 19 | ... AM4: =RIGHT(YEAR(AM$11),2) -> 26 | AO4: =RIGHT(YEAR(AO$11),2) -> 17 | AP4: =RIGHT(YEAR(AP$11),2) -> 17 | AQ4: =RIGHT(YEAR(AQ$11),2) -> 18 | AR4: =RIGHT(YEAR(AR$11),2) -> 18 | AS4: =RIGHT(YEAR(AS$11),2) -> 19 | AT4: =RIGHT(YEAR(AT$11),2) -> 19 | AU4: =RIGHT(YEAR(AU$11),2) -> 20 | AV4: =RIGHT(YEAR(AV$11),2) -> 20 | ... BG4: =RIGHT(YEAR(BG$11),2) -> 26
C5: ="FY"&TEXT(C$3,"00") -> FY17 | D5: ="FY"&TEXT(D$3,"00") -> FY18 | E5: ="FY"&TEXT(E$3,"00") -> FY18 | F5: ="FY"&TEXT(F$3,"00") -> FY18 | G5: ="FY"&TEXT(G$3,"00") -> FY18 | H5: ="FY"&TEXT(H$3,"00") -> FY19 | I5: ="FY"&TEXT(I$3,"00") -> FY19 | J5: ="FY"&TEXT(J$3,"00") -> FY19 | ... AM5: ="FY"&TEXT(AM$3,"00") -> FY26 | AO5: ="FY"&TEXT(AO$3,"00") -> FY17 | AP5: ="FY"&TEXT(AP$3,"00") -> FY18 | AQ5: ="FY"&TEXT(AQ$3,"00") -> FY18 | AR5: ="FY"&TEXT(AR$3,"00") -> FY19 | AS5: ="FY"&TEXT(AS$3,"00") -> FY19 | AT5: ="FY"&TEXT(AT$3,"00") -> FY20 | AU5: ="FY"&TEXT(AU$3,"00") -> FY20 | AV5: ="FY"&TEXT(AV$3,"00") -> FY21 | ... BG5: ="FY"&TEXT(BG$3,"00") -> FY26
C6: ="CY"&TEXT(C$4,"00") -> CY17 | D6: ="CY"&TEXT(D$4,"00") -> CY17 | E6: ="CY"&TEXT(E$4,"00") -> CY17 | F6: ="CY"&TEXT(F$4,"00") -> CY18 | G6: ="CY"&TEXT(G$4,"00") -> CY18 | H6: ="CY"&TEXT(H$4,"00") -> CY18 | I6: ="CY"&TEXT(I$4,"00") -> CY18 | J6: ="CY"&TEXT(J$4,"00") -> CY19 | ... AM6: ="CY"&TEXT(AM$4,"00") -> CY26 | AO6: ="CY"&TEXT(AO$4,"00") -> CY17 | AP6: ="CY"&TEXT(AP$4,"00") -> CY17 | AQ6: ="CY"&TEXT(AQ$4,"00") -> CY18 | AR6: ="CY"&TEXT(AR$4,"00") -> CY18 | AS6: ="CY"&TEXT(AS$4,"00") -> CY19 | AT6: ="CY"&TEXT(AT$4,"00") -> CY19 | AU6: ="CY"&TEXT(AU$4,"00") -> CY20 | AV6: ="CY"&TEXT(AV$4,"00") -> CY20 | ... BG6: ="CY"&TEXT(BG$4,"00") -> CY26
C7: =C11-EOMONTH(C11,-3) -> 91 | D7: =D11-EOMONTH(D11,-3) -> 92 | E7: =E11-EOMONTH(E11,-3) -> 92 | F7: =F11-EOMONTH(F11,-3) -> 90 | G7: =G11-EOMONTH(G11,-3) -> 91 | H7: =H11-EOMONTH(H11,-3) -> 92 | I7: =I11-EOMONTH(I11,-3) -> 92 | J7: =J11-EOMONTH(J11,-3) -> 90 | ... AM7: =AM11-EOMONTH(AM11,-3) -> 91 | AO7: =AO11-EOMONTH(AO11,-3) -> 91 | AP7: =AP11-EOMONTH(AP11,-3) -> 92 | AQ7: =AQ11-EOMONTH(AQ11,-3) -> 91 | AR7: =AR11-EOMONTH(AR11,-3) -> 92 | AS7: =AS11-EOMONTH(AS11,-3) -> 91 | AT7: =AT11-EOMONTH(AT11,-3) -> 92 | AU7: =AU11-EOMONTH(AU11,-3) -> 91 | AV7: =AV11-EOMONTH(AV11,-3) -> 92 | ... BG7: =BG11-EOMONTH(BG11,-3) -> 91
D9: 1H18 | E9: 1H18 | F9: 2H18 | G9: 2H18 | H9: 1H19 | I9: 1H19 | J9: 2H19 | K9: 2H19 | L9: 1H20 | M9: 1H20 | N9: 2H20 | O9: 2H20 | P9: 1H21 | Q9: 1H21 | R9: 2H21 | S9: 2H21 | T9: 1H22 | U9: 1H22 | V9: 2H22 | W9: 2H22 | X9: 1H23 | Y9: 1H23 | Z9: 2H23 | AA9: 2H23 | AB9: 1H24 | AC9: 1H24 | AD9: 2H24 | AE9: 2H24 | AF9: 1H25 | AG9: 1H25 | AH9: 2H25 | AI9: 2H25 | AJ9: 1H26 | AK9: 1H26 | AL9: 2H26 | AM9: 2H26
B10: 4Q17 | C10: 4Q17 | D10: 1Q18 | E10: 2Q18 | F10: 3Q18 | G10: 4Q18 | H10: 1Q19 | I10: 2Q19 | J10: 3Q19 | K10: 4Q19 | L10: 1Q20 | M10: 2Q20 | N10: 3Q20 | O10: 4Q20 | P10: 1Q21 | Q10: 2Q21 | R10: 3Q21 | S10: 4Q21 | T10: 1Q22 | U10: 2Q22 | V10: 3Q22 | W10: 4Q22 | X10: 1Q23 | Y10: 2Q23 | Z10: 3Q23 | AA10: 4Q23 | AB10: 1Q24 | AC10: 2Q24 | AD10: 3Q24 | AE10: 4Q24 | AF10: 1Q25 | AG10: 2Q25 | AH10: 3Q25 | AI10: 4Q25 | AJ10: 1Q26 | AK10: 2Q26 | AL10: 3Q26 | AM10: 4Q26 | AO10: 2H17 | AP10: 1H18 | AQ10: 2H18 | AR10: 1H19 | AS10: 2H19 | AT10: 1H20 | AU10: 2H20 | AV10: 1H21 | AW10: 2H21 | AX10: 1H22 | AY10: 2H22 | AZ10: 1H23 | BA10: 2H23 | BB10: 1H24 | BC10: 2H24 | BD10: 1H25 | BE10: 2H25 | BF10: 1H26 | BG10: 2H26
C11: 42916 | D11: =EOMONTH( C11, 3) -> 43008 | E11: =EOMONTH( D11, 3) -> 43100 | F11: =EOMONTH( E11, 3) -> 43190 | G11: =EOMONTH( F11, 3) -> 43281 | H11: =EOMONTH( G11, 3) -> 43373 | I11: =EOMONTH( H11, 3) -> 43465 | J11: =EOMONTH( I11, 3) -> 43555 | K11: =EOMONTH( J11, 3) -> 43646 | ... AM11: =EOMONTH( AL11, 3) -> 46203 | AO11: 42916 | AP11: =EOMONTH( AO11, 6) -> 43100 | AQ11: =EOMONTH( AP11, 6) -> 43281 | AR11: =EOMONTH( AQ11, 6) -> 43465 | AS11: =EOMONTH( AR11, 6) -> 43646 | AT11: =EOMONTH( AS11, 6) -> 43830 | AU11: =EOMONTH( AT11, 6) -> 44012 | AV11: =EOMONTH( AU11, 6) -> 44196 | AW11: =EOMONTH( AV11, 6) -> 44377 | ... BG11: =EOMONTH( BF11, 6) -> 46203
B12: Turnover | Z12: 354.2 | AD12: 273.1 | BB12: 673.2
B14: Gross Win | Z14: 37.6 | AD14: 37.1 | BB14: 79.8
B15: Gross Win Margin | Z15: =Z14/Z12 -> 0.10615471 | AD15: =AD14/AD12 -> 0.13584767 | BB15: =BB14/BB12 -> 0.11853832
B17: Pro Forma Net Win | Z17: 15 | AD17: 23.3 | BB17: 49.8
B18: Net Win Margin | Z18: =Z17/Z12 -> 0.042348955 | AD18: =AD17/AD12 -> 0.085316734 | BB18: =BB17/BB12 -> 0.073975045
B20: Active Customers (L6M) | BB20: 112083
B22: Cost per First Time Depositor | BB22: 332
B24: Pro Forma EBITDA | BB24: -2.8
B26: Reported Net Win | BB26: 11.9
B27: Reported EBITDA | BB27: -28.6
BA33: active | BB33: 112
BA34: inactive | BB34: =341-112 -> 229
BA35: open accounts | BB35: 341

Sheet Profitability
E2: Sportsbet | F2: PointsBet | G2: BlueBet | I2: FY24
C4: Turnover | E4: 17118.108 | F4: 2676.8 | G4: 591.5
C5: Gross Win | F5: 315.2 | G5: 79.5
C6: Net Win | F6: 233.1 | G6: 63.3
C12: Revenue | E12: 2112.1681 | F12: 211.5 | G12: 57.589
C13: COGS | E13: -1135.8806 | F13: =F14-F12 -> -99.7 | G13: -26.804 | K13: PointsBet paid $115.3m in GST, POCT and Product Fees to Australian Governments, Racing bodies and Sports bodies.
C14: Gross Profit | E14: =SUM(E12:E13) -> 976.28754 | F14: 111.8 | G14: 30.785 | K14: GST will be diff
K15: =F12-F6 -> -21.6
C16: Marketing | E16: -334.44615 | F16: -45.2
C17: Other Opex | E17: -154.197 | F17: =F20-F16-F14 -> -39.8
C18: Normalised EBITDA | E18: 487.64439 | G18: 3.3
C20: Statutory EBITDA | F20: 26.8 | G20: -3.316
C23: Revenue | E23: =E12 -> 2112.1681 | F23: =F12 -> 211.5 | H23: =E23/F23 -> 9.9866104
C24: COGS | E24: =E13 -> -1135.8806 | F24: =F13 -> -99.7 | H24: =E24/F24 -> 11.392985
C25: Gross Profit | E25: =E14 -> 976.28754 | F25: =F14 -> 111.8 | H25: =E25/F25 -> 8.7324467
C26: Marketing | E26: =E16 -> -334.44615 | F26: =F16 -> -45.2 | H26: =E26/F26 -> 7.3992511
C27: Other Opex | E27: =E17 -> -154.197 | F27: =F17 -> -39.8 | H27: =E27/F27 -> 3.8742964
C28: EBITDA | E28: =E18 -> 487.64439 | F28: =F20 -> 26.8 | H28: =E28/F28 -> 18.195686
B30: COGS/Revenue | C30: COGS | E30: =-E24/E23 -> 0.53777943 | F30: =-F24/F23 -> 0.4713948
B31: Marketing/Revenue | C31: Marketing | E31: =-E26/E23 -> 0.15834258 | F31: =-F26/F23 -> 0.21371158
B32: Other Opex/Revenue | C32: Other Opex | E32: =-E27/E23 -> 0.073004131 | F32: =-F27/F23 -> 0.18817967
B33: EBITDA Margin | C33: EBITDA | E33: =E28/E23 -> 0.23087386 | F33: =F28/F23 -> 0.12671395
C37: Revenue | E37: =E23 -> 2112.1681 | F37: =F23 -> 211.5 | H37: =H23 -> 9.9866104
C38: COGS | E38: =-E24 -> 1135.8806 | F38: =-F24 -> 99.7 | H38: =H24 -> 11.392985
C39: Gross Profit | E39: =E25 -> 976.28754 | F39: =F25 -> 111.8 | H39: =H25 -> 8.7324467
C40: Marketing | E40: =-E26 -> 334.44615 | F40: =-F26 -> 45.2 | H40: =H26 -> 7.3992511
C41: Other Opex | E41: =-E27 -> 154.197 | F41: =-F27 -> 39.8 | H41: =H27 -> 3.8742964
C42: EBITDA | E42: =E28 -> 487.64439 | F42: =F28 -> 26.8 | H42: =H28 -> 18.195686
C45: 2885
C46: 46713841
C47: =C46/C45 -> 16191.973
C48: =C47/181 -> 89.458412

Sheet MERGER
C3: TURNOVER | D3: 1H24A
C5: Tabcorp - Retail | D5: 2732.4 | K5: =D5/$E$12 -> 2.8114003
C6: Tabcorp - Digital | D6: 4731.2 | E6: =SUM(D5:D6) -> 7463.6 | K6: =D6/$E$12 -> 4.8679905
C7: SportsBet | D7: 9099.9405 | K7: =D7/$E$12 -> 9.363042
C8: LadBrokes | D8: =D19/12% -> 4897.2103 | K8: =D8/$E$12 -> 5.0388006
C9: Bet365 | K9: =D9/$E$12 -> 0
C10: PointsBet | D10: 1468.5 | F10: =SUM(D11:D12)/SUM(D6:D12) -> 0.045912015 | K10: =D10/$E$12 -> 1.5109579
C11: BlueBet | D11: 298.7 | F11: =SUM(D11:D12)/SUM(D5:D12) -> 0.040663314 | K11: =D11/$E$12 -> 0.30733615
C12: BetR | D12: 673.2 | E12: =SUM(D11:D12) -> 971.9 | K12: =D12/$E$12 -> 0.69266385
D15: 1H24A
C16: Tabcorp - Retail | D16: 458.1 | E16: =D16/D5 -> 0.16765481 | K16: =D16/$J$32 -> 14.921824
C17: Tabcorp - Digital | D17: 572.9 | E17: =D17/D6 -> 0.12108979 | K17: =D17/$J$32 -> 18.661238
C18: SportsBet | D18: 1081.2001 | E18: =D18/D7 -> 0.11881397 | K18: =D18/$J$32 -> 35.218244
C19: LadBrokes | D19: 587.66523 | E19: =D19/D8 -> 0.12 | K19: =D19/$J$32 -> 19.14219
C20: Bet365 | E20: =D20/D9 -> #DIV/0! | K20: =D20/$J$32 -> 0
C21: PointsBet | D21: 112.3 | E21: =D21/D10 -> 0.076472591 | G21: =SUM(D22:D24)/SUM(D17:D24) -> 0.017774697 | H21: =81/SUM(D17:D24) -> 0.033796959 | K21: =D21/$J$32 -> 3.6579805
C22: BlueBet | D22: 30.7 | E22: =D22/D11 -> 0.10277871 | G22: =SUM(D22:D24)/SUM(D16:D24) -> 0.014922417 | H22: =81/SUM(D16:D24) -> 0.028373611 | K22: =D22/$J$32 -> 1
C23: BetR - ProForma | E23: =49.8/D12 -> 0.073975045 | K23: =D24/$J$32 -> 0.38762215
C24: BetR - Reported | D24: 11.9 | E24: =D24/D12 -> 0.017676768
C27: Tabcorp | D27: 2732.4 | E27: 4731.2 | G27: 458.1 | H27: 572.9 | J27: =SUM(G27:H27) -> 1031 | M27: =J27/$J$32 -> 33.583062 | N27: =G27/$J$32 -> 14.921824
C28: SportsBet | E28: 9099.9405 | H28: 1081.2001 | J28: =SUM(G28:H28) -> 1081.2001 | M28: =J28/$J$32 -> 35.218244
C29: LadBrokes | H29: 587.66523 | J29: =SUM(G29:H29) -> 587.66523 | M29: =J29/$J$32 -> 19.14219
C30: Bet365 | J30: =SUM(G30:H30) -> 0 | M30: =J30/$J$32 -> 0
C31: PointsBet | E31: 1468.5 | H31: 112.3 | J31: =SUM(G31:H31) -> 112.3 | M31: =J31/$J$32 -> 3.6579805
C32: BlueBet | E32: 298.7 | F32: 673.2 | H32: 30.7 | I32: 11.9 | J32: =SUM(G32:H32) -> 30.7 | M32: =J32/$J$32 -> 1
C33: BlueBet Proforma | H33: 30.7 | I33: 49.8 | J33: =SUM(G33:H33) -> 30.7
D35: 1H24
I36: 37900000
C37: BlueBet/BetR | D37: 971.9 | E37: 42.6 | F37: 80.5 | I37: =I36/1000 -> 37900
C38: BlueBet/BetR ProForma
C39: Tabcorp Total | D39: 7463.6 | E39: 1031 | F39: 1031 | G39: =D39/D$37 -> 7.6793909 | H39: =E39/E$37 -> 24.201878 | I39: =F39/F$37 -> 12.807453
C40: Tabcorp - Digital | D40: 4731.2 | E40: 572.9 | F40: 572.9 | G40: =D40/D$37 -> 4.8679905 | H40: =E40/E$37 -> 13.448357 | I40: =F40/F$37 -> 7.1167702
C41: SportsBet | D41: 9099.9405 | E41: 1081.2001 | F41: 1081.2001 | G41: =D41/D$37 -> 9.363042 | H41: =E41/E$37 -> 25.380284 | I41: =F41/F$37 -> 13.431057
C42: PointsBet | D42: 1468.5 | E42: 112.3 | F42: 112.3 | G42: =D42/D$37 -> 1.5109579 | H42: =E42/E$37 -> 2.6361502 | I42: =F42/F$37 -> 1.3950311
E45: 971.9 | F45: 7463.6 | G45: 4731.2 | H45: 9099.9405 | I45: 1468.5
E46: 42.6 | F46: 1031 | G46: 572.9 | H46: 1081.2001 | I46: 112.3
E47: 80.5 | F47: 1031 | G47: 572.9 | H47: 1081.2001 | I47: 112.3
F53: Tabcorp Total | G53: Tabcorp - Digital | H53: SportsBet | I53: PointsBet
E54: Turnover | F54: =F45/$E45 -> 7.6793909 | G54: =G45/$E45 -> 4.8679905 | H54: =H45/$E45 -> 9.363042 | I54: =I45/$E45 -> 1.5109579
E55: Reported Net Win | F55: =F46/$E46 -> 24.201878 | G55: =G46/$E46 -> 13.448357 | H55: =H46/$E46 -> 25.380284 | I55: =I46/$E46 -> 2.6361502
E56: Pro Forma Net Win | F56: =F47/$E47 -> 12.807453 | G56: =G47/$E47 -> 7.1167702 | H56: =H47/$E47 -> 13.431057 | I56: =I47/$E47 -> 1.3950311

Sheet SportsBet ASIC
D2: FY18A | E2: FY19A | F2: FY20A | G2: FY21A | H2: FY22A | I2: FY23A | J2: FY24A | K2: FY25A
B3: Period End | C3: Units | D3: 43465 | E3: =EOMONTH(D3,12) -> 43830 | F3: =EOMONTH(E3,12) -> 44196 | G3: =EOMONTH(F3,12) -> 44561 | H3: =EOMONTH(G3,12) -> 44926 | I3: =EOMONTH(H3,12) -> 45291 | J3: =EOMONTH(I3,12) -> 45657 | K3: =EOMONTH(J3,12) -> 46022
B5: Revenue | C5: A$m | D5: 717075 | E5: 820508 | F5: 1653036 | G5: 2382238 | H5: 2245313 | I5: 2188859 | J5: 2114311 | K5: 2038378
B6: Cost of Sales | C6: A$m | D6: -225058 | E6: -342073 | F6: -791608 | G6: -1182658 | H6: -1100899 | I6: -1187752 | J6: -1156895 | K6: -1114650
B7: Gross Profit | C7: A$m | D7: =D5+D6 -> 492017 | E7: =E5+E6 -> 478435 | F7: =F5+F6 -> 861428 | G7: =G5+G6 -> 1199580 | H7: =H5+H6 -> 1144414 | I7: =I5+I6 -> 1001107 | J7: =J5+J6 -> 957416 | K7: =K5+K6 -> 923728
B8: Advertising & Marketing Expenses | C8: A$m | D8: -122256 | E8: -113544 | F8: -156744 | G8: -187505 | H8: -217928 | I8: -222334 | J8: -232230 | K8: -201911
B9: Other Opex | C9: A$m | D9: =D23-D7-D8-D10 -> -224427 | E9: =E23-E7-E8-E10 -> -230864 | F9: =F23-F7-F8-F10 -> -413454 | G9: =G23-G7-G8-G10 -> -382731 | H9: =H23-H7-H8-H10 -> -370612 | I9: =I23-I7-I8-I10 -> -396363 | J9: =J23-J7-J8-J10 -> -440202 | K9: =K23-K7-K8-K10 -> -440402
B10: Depreciation & Ammortisation Expense | C10: A$m | D10: -31421 | E10: -43758 | F10: -70016 | G10: -81564 | H10: -88447 | I10: -94302 | J10: -104289 | K10: -110351
B12: EBITDA (statutory) | C12: A$m | D12: =D23-D10 -> 145334 | E12: =E23-E10 -> 134027 | F12: =F23-F10 -> 291230 | G12: =G23-G10 -> 629344 | H12: =H23-H10 -> 555874 | I12: =I23-I10 -> 382410 | J12: =J23-J10 -> 284984 | K12: =K23-K10 -> 281415
B14: Ratios
B23: Results from Operating Activities | C23: A$m | D23: 113913 | E23: 90269 | F23: 221214 | G23: 547780 | H23: 467427 | I23: 288108 | J23: 180695 | K23: 171064
B24: EBITDA margin (%) | D24: =D12/D5 -> 0.20267615 | E24: =E12/E5 -> 0.16334637 | F24: =F12/F5 -> 0.17617886 | G24: =G12/G5 -> 0.26418183 | H24: =H12/H5 -> 0.24757083 | I24: =I12/I5 -> 0.17470746 | J24: =J12/J5 -> 0.13478812 | K24: =K12/K5 -> 0.1380583
B25: Revenue growth (% YoY) | E25: =E5/D5-1 -> 0.14424293 | F25: =F5/E5-1 -> 1.0146495 | G25: =G5/F5-1 -> 0.44112893 | H25: =H5/G5-1 -> -0.057477464 | I25: =I5/H5-1 -> -0.025143042 | J25: =J5/I5-1 -> -0.034057927 | K25: =K5/J5-1 -> -0.035913827
B27: All figures A$'000 unless labelled (%). Negatives in brackets. Blue = hardcoded inputs from the filings; black = formulas.
B28: Source: Paddy Power Australia Pty Limited (Sportsbet) - ASIC Form 388 financial statements, FY19-FY25. LATEST reported basis: where a later filing restated a comparative, the restated value is used (FY23 revenue/results; FY22 A&M/D&A). FY18 from the FY19 report comparative; FY25 from its own report.
B29: Gross Profit = Revenue + Cost of Sales. Other Opex = Results from Operating Activities - Gross Profit - A&M - D&A (residual, net of Other Income). EBITDA (statutory) = Results from Operating Activities + D&A.
B30: FY19-FY21 and FY24 are unchanged between their own filing and the following year's comparative. FY25 income-statement values read from the source PDF (text layer corrupted); all figures tie to the Form 388 cover and the face of the statement.
D32: FY18A | E32: FY19A | F32: FY20A | G32: FY21A | H32: FY22A | I32: FY23A | J32: FY24A | K32: FY25A
B33: Period End | C33: Units | D33: 43465 | E33: =EOMONTH(D33,12) -> 43830 | F33: =EOMONTH(E33,12) -> 44196 | G33: =EOMONTH(F33,12) -> 44561 | H33: =EOMONTH(G33,12) -> 44926 | I33: =EOMONTH(H33,12) -> 45291 | J33: =EOMONTH(I33,12) -> 45657 | K33: =EOMONTH(J33,12) -> 46022
B35: Revenue | C35: A$m | D35: 717075 | E35: 820508 | F35: 1653036 | G35: 2382238 | H35: 2245313 | I35: 2188859 | J35: 2114311 | K35: 2038378 | M35: 0.001
B36: Cost of Sales | C36: A$m | D36: -225058 | E36: -342073 | F36: -791608 | G36: -1182658 | H36: -1100899 | I36: -1187752 | J36: -1156895 | K36: -1114650
B37: Gross Profit | C37: A$m | D37: =D35+D36 -> 492017 | E37: =E35+E36 -> 478435 | F37: =F35+F36 -> 861428 | G37: =G35+G36 -> 1199580 | H37: =H35+H36 -> 1144414 | I37: =I35+I36 -> 1001107 | J37: =J35+J36 -> 957416 | K37: =K35+K36 -> 923728
B38: Advertising & Marketing Expenses | C38: A$m | D38: -122256 | E38: -113544 | F38: -156744 | G38: -187505 | H38: -217928 | I38: -222334 | J38: -232230 | K38: -201911
B39: Other Opex | C39: A$m | D39: -224427 | E39: -230864 | F39: -413454 | G39: -382731 | H39: -370612 | I39: -396363 | J39: -440202 | K39: -440402
B40: EBITDA (statutory) | C40: A$m | D40: 145334 | E40: 134027 | F40: 291230 | G40: 629344 | H40: 555874 | I40: 382410 | J40: 284984 | K40: 281415
B41: NPAT (statutory) | C41: A$m | D41: 64111 | E41: 57120 | F41: 146551 | G41: 369312 | H41: 316348 | I41: 186310 | J41: 115841 | K41: 79722
B43: Ratios
B44: Cost of Sales as a % of Revenue | C44: % | D44: =D6/D5 -> -0.31385559 | E44: =E6/E5 -> -0.41690392 | F44: =F6/F5 -> -0.47888128 | G44: =G6/G5 -> -0.4964483 | H44: =H6/H5 -> -0.49030981 | I44: =I6/I5 -> -0.54263523 | J44: =J6/J5 -> -0.54717352 | K44: =K6/K5 -> -0.54683184
B45: Advertising & Marketing Expenses as a % of Revenue | C45: % | D45: =D8/D5 -> -0.17049263 | E45: =E8/E5 -> -0.13838256 | F45: =F8/F5 -> -0.094821891 | G45: =G8/G5 -> -0.0787096 | H45: =H8/H5 -> -0.097059074 | I45: =I8/I5 -> -0.1015753 | J45: =J8/J5 -> -0.1098372 | K45: =K8/K5 -> -0.099054739
B46: EBITDA margin (statutory) | C46: % | D46: =D12/D5 -> 0.20267615 | E46: =E12/E5 -> 0.16334637 | F46: =F12/F5 -> 0.17617886 | G46: =G12/G5 -> 0.26418183 | H46: =H12/H5 -> 0.24757083 | I46: =I12/I5 -> 0.17470746 | J46: =J12/J5 -> 0.13478812 | K46: =K12/K5 -> 0.1380583
B47: NPAT margin (statutory) | C47: % | D47: =D41/D35 -> 0.089406269 | E47: =E41/E35 -> 0.069615409 | F47: =F41/F35 -> 0.088655661 | G47: =G41/G35 -> 0.15502733 | H47: =H41/H35 -> 0.14089261 | I47: =I41/I35 -> 0.085117406 | J47: =J41/J35 -> 0.054789007 | K47: =K41/K35 -> 0.039110508
D50: FY18A | E50: FY19A | F50: FY20A | G50: FY21A | H50: FY22A | I50: FY23A | J50: FY24A | K50: FY25A
B51: Period End | C51: Units | D51: 43465 | E51: =EOMONTH(D51,12) -> 43830 | F51: =EOMONTH(E51,12) -> 44196 | G51: =EOMONTH(F51,12) -> 44561 | H51: =EOMONTH(G51,12) -> 44926 | I51: =EOMONTH(H51,12) -> 45291 | J51: =EOMONTH(I51,12) -> 45657 | K51: =EOMONTH(J51,12) -> 46022
B52: P&L
B53: Revenue | C53: A$m | D53: =D35/1000 -> 717.075 | E53: =E35/1000 -> 820.508 | F53: =F35/1000 -> 1653.036 | G53: =G35/1000 -> 2382.238 | H53: =H35/1000 -> 2245.313 | I53: =I35/1000 -> 2188.859 | J53: =J35/1000 -> 2114.311 | K53: =K35/1000 -> 2038.378 | M53: 0.001
B54: Cost of Sales | C54: A$m | D54: =D36/1000 -> -225.058 | E54: =E36/1000 -> -342.073 | F54: =F36/1000 -> -791.608 | G54: =G36/1000 -> -1182.658 | H54: =H36/1000 -> -1100.899 | I54: =I36/1000 -> -1187.752 | J54: =J36/1000 -> -1156.895 | K54: =K36/1000 -> -1114.65
B55: Gross Profit | C55: A$m | D55: =D37/1000 -> 492.017 | E55: =E37/1000 -> 478.435 | F55: =F37/1000 -> 861.428 | G55: =G37/1000 -> 1199.58 | H55: =H37/1000 -> 1144.414 | I55: =I37/1000 -> 1001.107 | J55: =J37/1000 -> 957.416 | K55: =K37/1000 -> 923.728
B56: Advertising & Marketing Expenses | C56: A$m | D56: =D38/1000 -> -122.256 | E56: =E38/1000 -> -113.544 | F56: =F38/1000 -> -156.744 | G56: =G38/1000 -> -187.505 | H56: =H38/1000 -> -217.928 | I56: =I38/1000 -> -222.334 | J56: =J38/1000 -> -232.23 | K56: =K38/1000 -> -201.911
B57: Other Opex | C57: A$m | D57: =D39/1000 -> -224.427 | E57: =E39/1000 -> -230.864 | F57: =F39/1000 -> -413.454 | G57: =G39/1000 -> -382.731 | H57: =H39/1000 -> -370.612 | I57: =I39/1000 -> -396.363 | J57: =J39/1000 -> -440.202 | K57: =K39/1000 -> -440.402
B58: EBITDA (Statutory) | C58: A$m | D58: =D40/1000 -> 145.334 | E58: =E40/1000 -> 134.027 | F58: =F40/1000 -> 291.23 | G58: =G40/1000 -> 629.344 | H58: =H40/1000 -> 555.874 | I58: =I40/1000 -> 382.41 | J58: =J40/1000 -> 284.984 | K58: =K40/1000 -> 281.415
B59: NPAT (Statutory) | C59: A$m | D59: =D41/1000 -> 64.111 | E59: =E41/1000 -> 57.12 | F59: =F41/1000 -> 146.551 | G59: =G41/1000 -> 369.312 | H59: =H41/1000 -> 316.348 | I59: =I41/1000 -> 186.31 | J59: =J41/1000 -> 115.841 | K59: =K41/1000 -> 79.722
B61: Ratios
B62: Cost of Sales as a % of Revenue | C62: % | D62: =D44 -> -0.31385559 | E62: =E44 -> -0.41690392 | F62: =F44 -> -0.47888128 | G62: =G44 -> -0.4964483 | H62: =H44 -> -0.49030981 | I62: =I44 -> -0.54263523 | J62: =J44 -> -0.54717352 | K62: =K44 -> -0.54683184
B63: Advertising & Marketing as a % of Revenue | C63: % | D63: =D45 -> -0.17049263 | E63: =E45 -> -0.13838256 | F63: =F45 -> -0.094821891 | G63: =G45 -> -0.0787096 | H63: =H45 -> -0.097059074 | I63: =I45 -> -0.1015753 | J63: =J45 -> -0.1098372 | K63: =K45 -> -0.099054739
B64: EBITDA Margin (Statutory) | C64: % | D64: =D46 -> 0.20267615 | E64: =E46 -> 0.16334637 | F64: =F46 -> 0.17617886 | G64: =G46 -> 0.26418183 | H64: =H46 -> 0.24757083 | I64: =I46 -> 0.17470746 | J64: =J46 -> 0.13478812 | K64: =K46 -> 0.1380583
B65: NPAT Margin (Statutory) | C65: % | D65: =D47 -> 0.089406269 | E65: =E47 -> 0.069615409 | F65: =F47 -> 0.088655661 | G65: =G47 -> 0.15502733 | H65: =H47 -> 0.14089261 | I65: =I47 -> 0.085117406 | J65: =J47 -> 0.054789007 | K65: =K47 -> 0.039110508

Sheet TAH AR 
A1: Tabcorp Holdings Limited (ASX: TAH) — Divisional & Wagering KPIs, FY18–FY25
A2: A$ million. Continuing Tabcorp (Wagering & Media + Gaming Services); FY18–FY19 pro-forma (incl. Tatts full year); Lotteries demerged 1 Jun 2022. Figures as reported in each year's own full-year results. Blue = as reported; grey = memo/alt-basis; blank = not reported on this basis. See Notes.
A4: A. WAGERING & MEDIA (A$m)
A5: A$m | B5: FY18 | C5: FY19 | D5: FY20 | E5: FY21 | F5: FY22 | G5: FY23 | H5: FY24 | I5: FY25
A6: Year ended | B6: 30 Jun 2018 | C6: 30 Jun 2019 | D6: 30 Jun 2020 | E6: 30 Jun 2021 | F6: 30 Jun 2022 | G6: 30 Jun 2023 | H6: 30 Jun 2024 | I6: 30 Jun 2025
A7: Digital domestic wagering revenue | F7: 1073.5 | G7: 942.7 | H7: 922 | I7: 1069.7
A8: Cash domestic wagering revenue | F8: 654 | G8: 818.4 | H8: 821.8 | I8: 965.7
A9: Domestic wagering revenue | F9: 1727.5 | G9: 1761.1 | H9: 1743.8 | I9: 2035.4
A10: International wagering revenue | G10: 249.3 | H10: 212.3 | I10: 232.2
A11: Total wagering revenue | G11: 2010.4 | H11: 1956.1 | I11: 2267.6
A12: Media revenue | G12: 220.4 | H12: 360.9 | I12: 370.6
A13: (memo) Internal eliminations (SKY/TAB, FY24–25 basis) | H13: -154.2 | I13: -199.4
A14: (memo) Media & International revenue (bundled, FY22–23 basis) | F14: 454.4 | G14: 469.7
A15: Wagering & Media revenue | B15: 2461.8 | C15: 2312.2 | D15: 2084 | E15: 2298 | F15: 2181.9 | G15: 2230.8 | H15: 2162.8 | I15: 2438.8
A16: Wagering & Media VC | B16: 993.8 | C16: 944.3 | D16: 825 | E16: 883.6 | F16: 799.3 | G16: 815.1 | H16: 758.2 | I16: 915.9
A17: Wagering & Media EBITDA | B17: 451.8 | C17: 416 | D17: 371 | E17: 414.1 | F17: 306 | G17: 308 | H17: 251.2 | I17: 329.1
A18: Media basis change: FY23 media (220.4) is NET of internal SKY/TAB charges (FY23/FY24 decks); FY24–FY25 (360.9/370.6) are GROSS with eliminations shown separately — on the net basis FY24 media was 206.7, so the FY23→FY24 media step is largely presentation, not growth. FY22 international & media were bundled as 'Media & International' (454.4). VC/EBITDA are own-year reported: FY22 was restated in the FY23 deck (W&M EBITDA 306.0→287.0) and FY23 W&M VC was 815.1 as-reported vs 775.0 restated in the FY24 deck (VC definition changed). FY25 revenue grossed up post the Victorian JV ending 15 Aug 2024 — not like-for-like vs FY24.
A23: B. GAMING SERVICES / INTEGRITY SERVICES (A$m)
A24: A$m | B24: FY18 | C24: FY19 | D24: FY20 | E24: FY21 | F24: FY22 | G24: FY23 | H24: FY24 | I24: FY25
A25: Year ended | B25: 30 Jun 2018 | C25: 30 Jun 2019 | D25: 30 Jun 2020 | E25: 30 Jun 2021 | F25: 30 Jun 2022 | G25: 30 Jun 2023 | H25: 30 Jun 2024 | I25: 30 Jun 2025
A26: Gaming Services / Integrity Services revenue | B26: 315 | C26: 304 | D26: 221 | E26: 183.2 | F26: 192.9 | G26: 203.6 | H26: 176.1 | I26: 175.8
A27: Gaming Services / Integrity Services EBITDA | B27: 152 | C27: 139.7 | D27: 84 | E27: 70.7 | F27: 75.2 | G27: 83.1 | H27: 66.5 | I27: 62.4
A28: Renamed 'Integrity Services' from FY24. MPS business sold 1H24 (reduced FY24 vs FY23). Own-year reported; FY22 restated in FY23 deck (Rev 192.9→196.9, EBITDA 75.2→73.2). FY18–19 pro-forma.
A31: C. NET REVENUE PRE VRI SHARE (A$m) — Victorian 50/50 JV, ended 15 Aug 2024
A32: A$m | B32: FY18 | C32: FY19 | D32: FY20 | E32: FY21 | F32: FY22 | G32: FY23 | H32: FY24 | I32: FY25
A33: Year ended | B33: 30 Jun 2018 | C33: 30 Jun 2019 | D33: 30 Jun 2020 | E33: 30 Jun 2021 | F33: 30 Jun 2022 | G33: 30 Jun 2023 | H33: 30 Jun 2024 | I33: 30 Jun 2025
A34: Net digital revenue pre VRI share | F34: 1302.1 | G34: 1142.1 | H34: 1116.4 | I34: 1081.2
A35: Net cash revenue pre VRI share | F35: 698.8 | G35: 882 | H35: 895.8 | I35: 917.4
A36: 'Pre VRI share' = before deducting the Victorian Racing Industry JV's revenue share. Reported FY22–FY25 (JV ended 15 Aug 2024, so FY25 largely equals post-share revenue).
A39: D. DOMESTIC WAGERING TURNOVER (A$m) — FY23–FY25 basis (incl. VRI to 15 Aug 2024)
A40: A$m | B40: FY18 | C40: FY19 | D40: FY20 | E40: FY21 | F40: FY22 | G40: FY23 | H40: FY24 | I40: FY25
A41: Year ended | B41: 30 Jun 2018 | C41: 30 Jun 2019 | D41: 30 Jun 2020 | E41: 30 Jun 2021 | F41: 30 Jun 2022 | G41: 30 Jun 2023 | H41: 30 Jun 2024 | I41: 30 Jun 2025
A42: Racing turnover | G42: 11946.5 | H42: 11361.2 | I42: 10903
A43: Sport turnover | G43: 2604.3 | H43: 2696.5 | I43: 2840
A44: Total turnover | G44: 14550.8 | H44: 14057.7 | I44: 13742.9
A45: Digital turnover | G45: 9266.7 | H45: 8809.1 | I45: 8381.9
A46: Cash turnover | G46: 5284.1 | H46: 5248.6 | I46: 5361
A47: Domestic wagering turnover (Racing+Sport = Digital+Cash = Total). Disclosed on this basis only from FY23; FY18–FY22 turnover was reported differently (see Block F). Includes 100% of VRI turnover until the JV ended 15 Aug 2024.
A50: E. WAGERING PRODUCT REVENUE (A$m) — FY18–FY22 (combined wagering incl 100% VRI, EXCL media)
A51: A$m | B51: FY18 | C51: FY19 | D51: FY20 | E51: FY21 | F51: FY22 | G51: FY23 | H51: FY24 | I51: FY25
A52: Year ended | B52: 30 Jun 2018 | C52: 30 Jun 2019 | D52: 30 Jun 2020 | E52: 30 Jun 2021 | F52: 30 Jun 2022 | G52: 30 Jun 2023 | H52: 30 Jun 2024 | I52: 30 Jun 2025
A53: Totalisator revenue | B53: 1300.3 | C53: 1183 | D53: 1026 | E53: 1071.8 | F53: 1119.7
A54: Fixed Odds Racing revenue | B54: 913.7 | C54: 911.9 | D54: 911 | E54: 977.3 | F54: 844.2
A55: Sport revenue | B55: 277.9 | C55: 252.1 | D55: 193 | E55: 242.2 | F55: 228.5
A56: Trackside revenue | B56: 76.6 | C56: 72.4 | D56: 55 | E56: 52.7 | F56: 43.1
A57: (memo) Total product revenue | B57: 2568.5 | C57: 2419.4 | D57: 2185 | E57: 2344 | F57: 2235.5
A58: Product split on a 'combined wagering incl 100% VRI, excludes Media' basis — different from the statutory W&M divisional revenue in Block A. NOT disclosed from FY23. FY18–19 pro-forma.
A61: F. COMBINED WAGERING CHANNEL TURNOVER (A$m) — FY18–FY22 memo (incl 100% VRI, all channels)
A62: A$m | B62: FY18 | C62: FY19 | D62: FY20 | E62: FY21 | F62: FY22 | G62: FY23 | H62: FY24 | I62: FY25
A63: Year ended | B63: 30 Jun 2018 | C63: 30 Jun 2019 | D63: 30 Jun 2020 | E63: 30 Jun 2021 | F63: 30 Jun 2022 | G63: 30 Jun 2023 | H63: 30 Jun 2024 | I63: 30 Jun 2025
A64: Retail (cash) turnover | B64: 8019.4 | C64: 7428.5 | D64: 5354 | E64: 5305.2 | F64: 4089.7
A65: Digital turnover | B65: 6323.3 | C65: 6808.2 | D65: 7067 | E65: 9097.1 | F65: 9321.4
A66: Total turnover (all channels) | B66: 16269.1 | C66: 16074.9 | D66: 14079 | E66: 16445.3 | F66: 16304.9
A67: Different basis to Block D: total includes call-centre/other/export channels and 100% VRI, so it is NOT comparable to the FY23–FY25 domestic wagering turnover total. Shown for the pre-FY23 years only. FY18–19 pro-forma.
A70: A$m | B70: FY18 | C70: FY19 | D70: FY20 | E70: FY21 | F70: FY22 | G70: FY23 | H70: FY24 | I70: FY25
A71: Year ended | B71: 30 Jun 2018 | C71: 30 Jun 2019 | D71: 30 Jun 2020 | E71: 30 Jun 2021 | F71: 30 Jun 2022 | G71: 30 Jun 2023 | H71: 30 Jun 2024 | I71: 30 Jun 2025
A72: Continuing operations
A73: Revenue | E73: 2479.9 | F73: 2373.3 | G73: 2434.4 | H73: 2338.9 | I73: 2614.6
A74: Other income | E74: 46.2 | F74: 7.2 | G74: 91 | H74: 18.4 | I74: 5.5
A75: Commissions and fees | E75: -1098 | F75: -1180.4 | G75: -1078.3 | H75: -1097.2 | I75: -1041.3
A76: Government taxes and levies | E76: -334.1 | F76: -359.9 | G76: -333.3 | H76: -358.1 | I76: -463.1
A77: Employment costs | E77: -368 | F77: -344 | G77: -314.5 | H77: -332.8 | I77: -337.5
A78: Communications and technology costs | E78: -105.9 | F78: -131.5 | G78: -125.2 | H78: -126.6 | I78: -145.6
A79: Advertising and promotions | E79: -100 | F79: -106.5 | G79: -98.3 | H79: -111.5 | I79: -127.5
A80: Other expenses | E80: -46.2 | F80: -41.9 | G80: -168.4 | H80: -161.3 | I80: -143.4
A81: Depreciation and amortisation | E81: -276.1 | F81: -286.4 | G81: -240.5 | H81: -220.3 | I81: -202.8
A82: Impairment - goodwill | E82: -121.5 | H82: -746
A83: Impairment - other | E83: -9.4 | F83: -5 | G83: -49 | H83: -785.6
A84: Profit/(loss) before income tax, net finance costs & equity accounted investment | B84: =B73+B74+SUM(B75:B83) -> 0 | C84: =C73+C74+SUM(C75:C83) -> 0 | D84: =D73+D74+SUM(D75:D83) -> 0 | E84: =E73+E74+SUM(E75:E83) -> 66.9 | F84: =F73+F74+SUM(F75:F83) -> -75.1 | G84: =G73+G74+SUM(G75:G83) -> 117.9 | H84: =H73+H74+SUM(H75:H83) -> -1582.1 | I84: =I73+I74+SUM(I75:I83) -> 158.9
A85: Profit/(loss) from equity accounted investment | G85: -2.7 | H85: -3.2 | I85: 3.8
A86: Finance income | E86: 1.1 | F86: 0.4 | G86: 4.6 | H86: 17.3 | I86: 9.5
A87: Finance costs | E87: -168.7 | F87: -61.5 | G87: -37.1 | H87: -51.8 | I87: -101
A88: Profit/(loss) from continuing operations before income tax | B88: =B84+B85+B86+B87 -> 0 | C88: =C84+C85+C86+C87 -> 0 | D88: =D84+D85+D86+D87 -> 0 | E88: =E84+E85+E86+E87 -> -100.7 | F88: =F84+F85+F86+F87 -> -136.2 | G88: =G84+G85+G86+G87 -> 82.7 | H88: =H84+H85+H86+H87 -> -1619.8 | I88: =I84+I85+I86+I87 -> 71.2
A89: Income tax (expense)/benefit | E89: -60.2 | F89: 17.8 | G89: -16.2 | H89: 260.1 | I89: -34.6
A90: Profit/(loss) from continuing operations after income tax | B90: =B88+B89 -> 0 | C90: =C88+C89 -> 0 | D90: =D88+D89 -> 0 | E90: =E88+E89 -> -160.9 | F90: =F88+F89 -> -118.4 | G90: =G88+G89 -> 66.5 | H90: =H88+H89 -> -1359.7 | I90: =I88+I89 -> 36.6
A91: Discontinued operations
A92: Profit/(loss) from discontinued operations after tax | E92: 430.3 | F92: 6894.3
A93: Net profit/(loss) after tax | B93: =B90+B92 -> 0 | C93: =C90+C92 -> 0 | D93: =D90+D92 -> 0 | E93: =E90+E92 -> 269.4 | F93: =F90+F92 -> 6775.9 | G93: =G90+G92 -> 66.5 | H93: =H90+H92 -> -1359.7 | I93: =I90+I92 -> 36.6
A94: Other comprehensive income
A95: Change in fair value of cash flow hedges | E95: -73.9 | F95: 65.9 | G95: -6.9 | H95: -12.6 | I95: -0.6
A96: Exchange differences on translation of foreign operations | E96: 0.9 | F96: -1.7 | G96: 7.9 | H96: 0.6 | I96: 5.1
A97: Income tax relating to these items | E97: 22.1 | F97: -19.8 | G97: 2.1 | H97: 3.8 | I97: 0.2
A98: Actuarial gains/(losses) on retirement benefit obligation | E98: 4.1 | F98: 0.5 | H98: 0.1 | I98: 0.1
A99: Income tax relating to actuarial items | E99: -1.4 | F99: -0.1
A100: Other comprehensive income for the year, net of tax | B100: =SUM(B95:B99) -> 0 | C100: =SUM(C95:C99) -> 0 | D100: =SUM(D95:D99) -> 0 | E100: =SUM(E95:E99) -> -48.2 | F100: =SUM(F95:F99) -> 44.8 | G100: =SUM(G95:G99) -> 3.1 | H100: =SUM(H95:H99) -> -8.1 | I100: =SUM(I95:I99) -> 4.8
A101: Total comprehensive income for the year | B101: =B93+B100 -> 0 | C101: =C93+C100 -> 0 | D101: =D93+D100 -> 0 | E101: =E93+E100 -> 221.2 | F101: =F93+F100 -> 6820.7 | G101: =G93+G100 -> 69.6 | H101: =H93+H100 -> -1367.8 | I101: =I93+I100 -> 41.4
A103: Per share (cents)
A104: Basic EPS - continuing operations | E104: -7.4 | F104: -5.3 | G104: 2.9 | H104: -59.6 | I104: 1.6
A105: Diluted EPS - continuing operations | E105: -7.3 | F105: -5.3 | G105: 2.9 | H105: -59.6 | I105: 1.6
A106: Basic EPS - total | E106: 12.3 | F106: 304.6 | G106: 2.9 | H106: -59.6 | I106: 1.6
A107: Diluted EPS - total | E107: 12.3 | F107: 304.6 | G107: 2.9 | H107: -59.6 | I107: 1.6
A108: DPS - declared and paid during the year | E108: 7.5 | F108: 483.9 | G108: 7.8 | H108: 2 | I108: 1.3
A109: DPS - determined in respect of the year | E109: 14.5 | F109: 13 | G109: 2.3 | H109: 1.3 | I109: 2

Sheet TAH
D4: FY18A | E4: FY19A | F4: FY20A | G4: FY21A | H4: FY22A | I4: FY23A | J4: FY24A | K4: FY25A
B5: Period End | C5: Units | D5: 43281 | E5: =EOMONTH(D5,12) -> 43646 | F5: =EOMONTH(E5,12) -> 44012 | G5: =EOMONTH(F5,12) -> 44377 | H5: =EOMONTH(G5,12) -> 44742 | I5: =EOMONTH(H5,12) -> 45107 | J5: =EOMONTH(I5,12) -> 45473 | K5: =EOMONTH(J5,12) -> 45838
B6: Turnover
B7: Racing | C7: A$m | H7: 11769.7 | I7: 11946.5 | J7: 11361.2 | K7: 10903
B8: Sport | C8: A$m | H8: 2124 | I8: 2604.3 | J8: 2696.5 | K8: 2840
B9: Total
B11: Digital Wagering
B12: Turnover | C12: A$m | H12: 9697 | I12: 9266.7 | J12: 8809.1 | K12: 8381.9
B13: Net Margin | C13: % | H13: =H14/H12 -> 0.13427864 | I13: =I14/I12 -> 0.12324776 | J13: =J14/J12 -> 0.12673258 | K13: =K14/K12 -> 0.12899223
B14: Net Digital Revenue pre VRI Share | C14: A$m | H14: 1302.1 | I14: 1142.1 | J14: 1116.4 | K14: 1081.2
B15: Other | C15: A$m | H15: -228.6 | I15: -199.4 | J15: -194.4 | K15: -11.5
B16: Digital Wagering Revenue | C16: A$m | H16: 1073.5 | I16: 942.7 | J16: 922 | K16: 1069.7
B18: Retail Wagering
B19: Turnover | C19: A$m | H19: 4196.7 | I19: 5284.1 | J19: 5248.6 | K19: 5361
B20: Net Margin | C20: % | H20: =H21/H19 -> 0.16651178 | I20: =I21/I19 -> 0.16691584 | J20: =J21/J19 -> 0.17067408 | K20: =K21/K19 -> 0.17112479
B21: Net Retail Revenue pre VRI Share | C21: A$m | H21: 698.8 | I21: 882 | J21: 895.8 | K21: 917.4
B22: Other | C22: A$m | H22: -44.8 | I22: -63.6 | J22: -74 | K22: 48.3
B23: Retail Wagering Revenue | C23: A$m | H23: 654 | I23: 818.4 | J23: 821.8 | K23: 965.7
B25: Wagering & Media P&L
B26: Digital | C26: A$m | H26: 1073.5 | I26: 942.7 | J26: 922 | K26: 1069.7
B27: Cash | C27: A$m | H27: 654 | I27: 818.4 | J27: 821.8 | K27: 965.7
B28: International | C28: A$m | I28: 249.3 | J28: 212.3 | K28: 232.2
B29: Media External | C29: A$m | I29: 220.4 | J29: 206.7 | K29: 171.2
B30: Revenue | C30: A$m | H30: 2181.9 | I30: 2230.8 | J30: 2162.8 | K30: 2438.8
B31: Taxes and Commissions | C31: A$m | H31: -1380.6 | I31: -1455.8 | J31: -1404.6 | K31: -1522.9
B32: Variable contribution | C32: A$m | H32: 801.3 | I32: 775 | J32: 758.2 | K32: 915.9
B33: Opex | C33: A$m | H33: -514.3 | I33: -467 | J33: -507 | K33: -586.8
B34: Normalised EBITDA | C34: A$m | H34: 287 | I34: 308 | J34: 251.2 | K34: 329.1
B36: Group P&L
B37: Revenue | H37: 2373.3 | I37: 2434.4 | J37: 2338.9 | K37: 2614.6
B38: Statutory EBITDA
B39: Statutory NPAT | H39: -118.4 | I39: 66.5 | J39: -1359.7 | K39: 36.6
B41: Wagering & Media Ratios
B42: Cost of Sales as a % of Revenue | C42: % | H42: =#REF!/#REF! -> #REF! | I42: =#REF!/#REF! -> #REF! | J42: =#REF!/#REF! -> #REF! | K42: =#REF!/#REF! -> #REF!
B43: Advertising & Marketing as a % of Revenue | C43: % | H43: =#REF!/#REF! -> #REF! | I43: =#REF!/#REF! -> #REF! | J43: =#REF!/#REF! -> #REF! | K43: =#REF!/#REF! -> #REF!
B44: EBITDA Margin (Statutory) | C44: % | H44: =H38/H37 -> 0 | I44: =I38/I37 -> 0 | J44: =J38/J37 -> 0 | K44: =K38/K37 -> 0
B45: NPAT Margin (Statutory) | C45: % | H45: =H39/H37 -> -0.049888341 | I45: =I39/I37 -> 0.027316793 | J45: =J39/J37 -> -0.58134166 | K45: =K39/K37 -> 0.013998317

Sheet Entain ASIC
B1: LB Australia Holdings Pty Ltd — Entain Australia / New Zealand
B2: Consolidated statement of profit or loss · ABN 96 165 597 482 · Ladbrokes / Neds · ultimate parent Entain plc
B3: All figures A$'000 unless stated · year ended 31 December · latest-reported basis (restated comparatives used where applicable)
D5: FY18 | E5: FY19 | F5: FY20 | G5: FY21 | H5: FY22 | I5: FY23 | J5: FY24 | K5: FY25
D6: 43465 | E6: =EOMONTH(D6,12) -> 43830 | F6: =EOMONTH(E6,12) -> 44196 | G6: =EOMONTH(F6,12) -> 44561 | H6: =EOMONTH(G6,12) -> 44926 | I6: =EOMONTH(H6,12) -> 45291 | J6: =EOMONTH(I6,12) -> 45657 | K6: =EOMONTH(J6,12) -> 46022
B8: REVENUE
B9: Net gaming revenue — Australia | D9: 293890 | E9: 419974 | F9: 650123 | G9: 765306 | H9: 831988 | I9: 763353 | J9: 771767 | K9: 724991
B10: Net gaming revenue — New Zealand | I10: 168278 | J10: 275090 | K10: 338985
B11: Net gaming revenue — total | D11: =SUM(D9:D10) -> 293890 | E11: =SUM(E9:E10) -> 419974 | F11: =SUM(F9:F10) -> 650123 | G11: =SUM(G9:G10) -> 765306 | H11: =SUM(H9:H10) -> 831988 | I11: =SUM(I9:I10) -> 931631 | J11: =SUM(J9:J10) -> 1046857 | K11: =SUM(K9:K10) -> 1063976
B12: Other revenue | D12: 492 | E12: 777 | F12: 243 | G12: 15 | H12: 46 | I12: 34797 | J12: 60162 | K12: 48530
B13: Total revenue | D13: =D11+D12 -> 294382 | E13: =E11+E12 -> 420751 | F13: =F11+F12 -> 650366 | G13: =G11+G12 -> 765321 | H13: =H11+H12 -> 832034 | I13: =I11+I12 -> 966428 | J13: =J11+J12 -> 1107019 | K13: =K11+K12 -> 1112506
B15: Pre GST | D15: =D9*1.1 -> 323279 | E15: =E9*1.1 -> 461971.4 | F15: =F9*1.1 -> 715135.3 | G15: =G9*1.1 -> 841836.6 | H15: =H9*1.1 -> 915186.8 | I15: =I9*1.1 -> 839688.3 | J15: =J9*1.1 -> 848943.7 | K15: =K9*1.1 -> 797490.1
D18: =D30/D11 -> 0.27357174 | E18: =E30/E11 -> 0.27042388 | F18: =F30/F11 -> 0.17128605 | G18: =G30/G11 -> 0.16775773 | H18: =H30/H11 -> 0.15984245 | I18: =I30/I11 -> 0.17820575 | J18: =J30/J11 -> 0.20175439 | K18: =K30/K11 -> 0.1632518
B20: COST OF SALES
B21: Licence fees | D21: 666 | E21: 938 | F21: 550 | G21: 500 | H21: 61 | I21: 1791 | J21: 2265 | K21: 1499
B22: Product fees | D22: 79966 | E22: 112228 | F22: 155084 | G22: 175839 | H22: 190803 | I22: 205559 | J22: 227615 | K22: 243899
B23: Point of consumption taxes | D23: 6437 | E23: 67870 | F23: 106840 | G23: 117979 | H23: 153626 | I23: 172552 | J23: 180545 | K23: 179155
B24: Other cost of sales | D24: 27507 | E24: 31334 | F24: 47417 | G24: 45340 | H24: 46587 | I24: 35314 | J24: 35226 | K24: 53662
B25: Total cost of sales | D25: =SUM(D21:D24) -> 114576 | E25: =SUM(E21:E24) -> 212370 | F25: =SUM(F21:F24) -> 309891 | G25: =SUM(G21:G24) -> 339658 | H25: =SUM(H21:H24) -> 391077 | I25: =SUM(I21:I24) -> 415216 | J25: =SUM(J21:J24) -> 445651 | K25: =SUM(K21:K24) -> 478215
B26: Gross profit | D26: =D13-D25 -> 179806 | E26: =E13-E25 -> 208381 | F26: =F13-F25 -> 340475 | G26: =G13-G25 -> 425663 | H26: =H13-H25 -> 440957 | I26: =I13-I25 -> 551212 | J26: =J13-J25 -> 661368 | K26: =K13-K25 -> 634291
B27: Gross margin % | D27: =D26/D13 -> 0.61079142 | E27: =E26/E13 -> 0.49525967 | F27: =F26/F13 -> 0.52351291 | G27: =G26/G13 -> 0.55618884 | H27: =H26/H13 -> 0.52997474 | I27: =I26/I13 -> 0.57036013 | J27: =J26/J13 -> 0.59743148 | K27: =K26/K13 -> 0.57014614
B29: OPERATING EXPENSES
B30: Marketing costs | D30: 80400 | E30: 113571 | F30: 111357 | G30: 128386 | H30: 132987 | I30: 166022 | J30: 211208 | K30: 173696
B31: Depreciation & amortisation | D31: 4895 | E31: 17770 | F31: 15451 | G31: 15902 | H31: 11841 | I31: 71442 | J31: 108547 | K31: 105433
B32: Other operating expenses | D32: 65871 | E32: 83214 | F32: 80221 | G32: 111935 | H32: 157597 | I32: 243955 | J32: 613100 | K32: 400910
B33: Total operating expenses | D33: =SUM(D30:D32) -> 151166 | E33: =SUM(E30:E32) -> 214555 | F33: =SUM(F30:F32) -> 207029 | G33: =SUM(G30:G32) -> 256223 | H33: =SUM(H30:H32) -> 302425 | I33: =SUM(I30:I32) -> 481419 | J33: =SUM(J30:J32) -> 932855 | K33: =SUM(K30:K32) -> 680039
B35: Finance expenses | F35: 1120 | G35: 781 | H35: 728 | I35: 120426 | J35: 215379 | K35: 171450
B36: Net changes in fair value | J36: 14662 | K36: 107474
B37: Loss before income tax | D37: =D26-D33-D35+D36 -> 28640 | E37: =E26-E33-E35+E36 -> -6174 | F37: =F26-F33-F35+F36 -> 132326 | G37: =G26-G33-G35+G36 -> 168659 | H37: =H26-H33-H35+H36 -> 137804 | I37: =I26-I33-I35+I36 -> -50633 | J37: =J26-J33-J35+J36 -> -472204 | K37: =K26-K33-K35+K36 -> -109724
B38: Reported loss before income tax | D38: 28640 | E38: -6174 | F38: 132326 | G38: 168659 | H38: 137804 | I38: -50633 | J38: -472204 | K38: -109724
B39: Check (nil = ties to filing) | D39: =D37-D38 -> 0 | E39: =E37-E38 -> 0 | F39: =F37-F38 -> 0 | G39: =G37-G38 -> 0 | H39: =H37-H38 -> 0 | I39: =I37-I38 -> 0 | J39: =J37-J38 -> 0 | K39: =K37-K38 -> 0
B41: MEMO — EBITDA BRIDGE
B42: Loss before income tax | D42: =D37 -> 28640 | E42: =E37 -> -6174 | F42: =F37 -> 132326 | G42: =G37 -> 168659 | H42: =H37 -> 137804 | I42: =I37 -> -50633 | J42: =J37 -> -472204 | K42: =K37 -> -109724
B43: add: Finance expenses (incl. amounts within opex, FY18–19) | D43: 7649 | E43: 10958 | F43: 1120 | G43: 781 | H43: 728 | I43: 120426 | J43: 215379 | K43: 171450
B44: add: Depreciation & amortisation | D44: =D31 -> 4895 | E44: =E31 -> 17770 | F44: =F31 -> 15451 | G44: =G31 -> 15902 | H44: =H31 -> 11841 | I44: =I31 -> 71442 | J44: =J31 -> 108547 | K44: =K31 -> 105433
B45: less: Net changes in fair value (gain) | D45: =D36 -> 0 | E45: =E36 -> 0 | F45: =F36 -> 0 | G45: =G36 -> 0 | H45: =H36 -> 0 | I45: =I36 -> 0 | J45: =J36 -> 14662 | K45: =K36 -> 107474
B46: Statutory EBITDA | D46: =D42+D43+D44-D45 -> 41184 | E46: =E42+E43+E44-E45 -> 22554 | F46: =F42+F43+F44-F45 -> 148897 | G46: =G42+G43+G44-G45 -> 185342 | H46: =H42+H43+H44-H45 -> 150373 | I46: =I42+I43+I44-I45 -> 141235 | J46: =J42+J43+J44-J45 -> -162940 | K46: =K42+K43+K44-K45 -> 59685
B47: add: Impairment | D47: 3000 | E47: 3364 | F47: 0 | G47: 0 | H47: 0 | I47: 6594 | J47: 308129 | K47: 7905
B48: add: AUSTRAC legal-dispute provision | D48: 0 | E48: 0 | F48: 0 | G48: 0 | H48: 0 | I48: 0 | J48: 0 | K48: 100000
B49: Underlying EBITDA | D49: =D46+D47+D48 -> 44184 | E49: =E46+E47+E48 -> 25918 | F49: =F46+F47+F48 -> 148897 | G49: =G46+G47+G48 -> 185342 | H49: =H46+H47+H48 -> 150373 | I49: =I46+I47+I48 -> 147829 | J49: =J46+J47+J48 -> 145189 | K49: =K46+K47+K48 -> 167590
B50: Underlying EBITDA margin % | D50: =D49/D13 -> 0.1500907 | E50: =E49/E13 -> 0.061599378 | F50: =F49/F13 -> 0.22894339 | G50: =G49/G13 -> 0.24217551 | H50: =H49/H13 -> 0.18072939 | I50: =I49/I13 -> 0.15296432 | J50: =J49/J13 -> 0.13115312 | K50: =K49/K13 -> 0.15064188
B52: Net profit/(loss) from continuing operations | D52: 19649 | E52: -5502 | F52: 90752 | G52: 113062 | H52: 96427 | I52: -37632 | J52: -403125 | K52: -142677
B53: Total comprehensive income/(loss) for the period | D53: 19649 | E53: -5502 | F53: 90752 | G53: 113062 | H53: 96435 | I53: -39599 | J53: -395906 | K53: -132310
B55: MEMO — RATIOS & TRENDS
B56: Net gaming revenue growth % | E56: =(E11/D11)-1 -> 0.42901766 | F56: =(F11/E11)-1 -> 0.54800773 | G56: =(G11/F11)-1 -> 0.17717109 | H56: =(H11/G11)-1 -> 0.087131161 | I56: =(I11/H11)-1 -> 0.11976495 | J56: =(J11/I11)-1 -> 0.12368202 | K56: =(K11/J11)-1 -> 0.016352759
B57: Australia net gaming growth % | E57: =(E9/D9)-1 -> 0.42901766 | F57: =(F9/E9)-1 -> 0.54800773 | G57: =(G9/F9)-1 -> 0.17717109 | H57: =(H9/G9)-1 -> 0.087131161 | I57: =(I9/H9)-1 -> -0.08249518 | J57: =(J9/I9)-1 -> 0.011022423 | K57: =(K9/J9)-1 -> -0.060608966
B58: New Zealand net gaming growth % | J58: =(J10/I10)-1 -> 0.63473538 | K58: =(K10/J10)-1 -> 0.23226944
B59: NZ % of total net gaming | D59: =D10/D11 -> 0 | E59: =E10/E11 -> 0 | F59: =F10/F11 -> 0 | G59: =G10/G11 -> 0 | H59: =H10/H11 -> 0 | I59: =I10/I11 -> 0.18062731 | J59: =J10/J11 -> 0.26277706 | K59: =K10/K11 -> 0.31860211
B60: Cost of sales % of total revenue | D60: =D25/D13 -> 0.38920858 | E60: =E25/E13 -> 0.50474033 | F60: =F25/F13 -> 0.47648709 | G60: =G25/G13 -> 0.44381116 | H60: =H25/H13 -> 0.47002526 | I60: =I25/I13 -> 0.42963987 | J60: =J25/J13 -> 0.40256852 | K60: =K25/K13 -> 0.42985386
B61: Product fees % of net gaming revenue | D61: =D22/D11 -> 0.272095 | E61: =E22/E11 -> 0.26722607 | F61: =F22/F11 -> 0.23854563 | G61: =G22/G11 -> 0.229763 | H61: =H22/H11 -> 0.22933384 | I61: =I22/I11 -> 0.22064423 | J61: =J22/J11 -> 0.21742702 | K61: =K22/K11 -> 0.22923355
B62: POC taxes % of net gaming revenue | D62: =D23/D11 -> 0.021902753 | E62: =E23/E11 -> 0.16160524 | F62: =F23/F11 -> 0.16433813 | G62: =G23/G11 -> 0.15415925 | H62: =H23/H11 -> 0.1846493 | I62: =I23/I11 -> 0.18521496 | J62: =J23/J11 -> 0.17246386 | K62: =K23/K11 -> 0.16838256
B63: Marketing % of net gaming revenue | D63: =D30/D11 -> 0.27357174 | E63: =E30/E11 -> 0.27042388 | F63: =F30/F11 -> 0.17128605 | G63: =G30/G11 -> 0.16775773 | H63: =H30/H11 -> 0.15984245 | I63: =I30/I11 -> 0.17820575 | J63: =J30/J11 -> 0.20175439 | K63: =K30/K11 -> 0.1632518
B66: Notes
B67: All figures A$'000 unless stated. Negatives in brackets; nil / not-applicable shown as "-"; a blank cell = the item was not disclosed as a separate line that year. Blue text = hardcoded inputs from the filings; black text = formulas.
B68: Source: LB Australia Holdings Pty Ltd (Entain's Australian entity; brands Ladbrokes & Neds; ultimate parent Entain plc) — ASIC financial statements for the years ended 31 December (FY19–FY25 filings). Latest-reported basis: where a later filing restated or reclassified a comparative, the later figures are used. FY18 is taken from the FY19 report comparative.
B69: Build logic: Net gaming revenue (total) = Australia + New Zealand. Other revenue = Total revenue − Net gaming revenue. Total cost of sales = sum of the four cost lines. Gross profit = Total revenue − Total cost of sales. Other operating expenses = Total operating expenses − Marketing − D&A. Loss before income tax = Gross profit − Total operating expenses − Finance expenses + Net changes in fair value. The check row ties the built loss-before-tax to the figure reported on the face of each filing (nil difference every year).
B70: Restatements / reclassifications (each nil impact on loss before tax): FY24 — ~A$14.7m moved from overseas racing revenue into Net changes in fair value in the FY25 report. FY20 — the FY21 report moved ~A$13.2m into cost of sales and separated finance costs out of operating expenses. FY18–FY19 finance costs were not separated and remain within Operating expenses (and within the EBITDA-bridge add-back).
B71: EBITDA is not a disclosed measure (these are plain IFRS statements with no adjusted metrics); the bridge above is built by E&P. The 'underlying' line adds back impairment and the FY25 AUSTRAC provision only — it does not normalise for the TAB NZ consideration interest or other items, and is not comparable to an Entain plc group figure.
B72: Prepared for internal E&P research use. Reconstructed from the source filings; if the original workbook template is provided it can be transposed into that exact layout.
D74: FY18A | E74: FY19A | F74: FY20A | G74: FY21A | H74: FY22A | I74: FY23A | J74: FY24A | K74: FY25A
B75: Period End | C75: Units | D75: 43465 | E75: =EOMONTH(D75,12) -> 43830 | F75: =EOMONTH(E75,12) -> 44196 | G75: =EOMONTH(F75,12) -> 44561 | H75: =EOMONTH(G75,12) -> 44926 | I75: =EOMONTH(H75,12) -> 45291 | J75: =EOMONTH(I75,12) -> 45657 | K75: =EOMONTH(J75,12) -> 46022
B76: P&L
B77: Net Gaming Revenue — Australia | C77: A$m | D77: 293.89 | E77: 419.974 | F77: 650.123 | G77: 765.306 | H77: 831.988 | I77: 763.353 | J77: 771.767 | K77: 724.991
B78: Net Gaming Revenue — New Zealand | C78: A$m | I78: 168.278 | J78: 275.09 | K78: 338.985
B79: Net Gaming Revenue | C79: A$m | D79: =SUM(D77:D78) -> 293.89 | E79: =SUM(E77:E78) -> 419.974 | F79: =SUM(F77:F78) -> 650.123 | G79: =SUM(G77:G78) -> 765.306 | H79: =SUM(H77:H78) -> 831.988 | I79: =SUM(I77:I78) -> 931.631 | J79: =SUM(J77:J78) -> 1046.857 | K79: =SUM(K77:K78) -> 1063.976
B80: Other Revenue | C80: A$m | D80: 0.492 | E80: 0.777 | F80: 0.243 | G80: 0.015 | H80: 0.046 | I80: 34.797 | J80: 60.162 | K80: 48.53
B81: Total Revenue | C81: A$m | D81: =D79+D80 -> 294.382 | E81: =E79+E80 -> 420.751 | F81: =F79+F80 -> 650.366 | G81: =G79+G80 -> 765.321 | H81: =H79+H80 -> 832.034 | I81: =I79+I80 -> 966.428 | J81: =J79+J80 -> 1107.019 | K81: =K79+K80 -> 1112.506
B83: Licence Fees | C83: A$m | D83: -0.666 | E83: -0.938 | F83: -0.55 | G83: -0.5 | H83: -0.061 | I83: -1.791 | J83: -2.265 | K83: -1.499 | M83: 0.001
B84: Product Fees | C84: A$m | D84: -79.966 | E84: -112.228 | F84: -155.084 | G84: -175.839 | H84: -190.803 | I84: -205.559 | J84: -227.615 | K84: -243.899
B85: POCT | C85: A$m | D85: -6.437 | E85: -67.87 | F85: -106.84 | G85: -117.979 | H85: -153.626 | I85: -172.552 | J85: -180.545 | K85: -179.155
B86: Other COGS | C86: A$m | D86: -27.507 | E86: -31.334 | F86: -47.417 | G86: -45.34 | H86: -46.587 | I86: -35.314 | J86: -35.226 | K86: -53.662
B87: Total Cost of Sales | C87: A$m | D87: =SUM(D83:D86) -> -114.576 | E87: =SUM(E83:E86) -> -212.37 | F87: =SUM(F83:F86) -> -309.891 | G87: =SUM(G83:G86) -> -339.658 | H87: =SUM(H83:H86) -> -391.077 | I87: =SUM(I83:I86) -> -415.216 | J87: =SUM(J83:J86) -> -445.651 | K87: =SUM(K83:K86) -> -478.215
B88: Gross Profit | C88: A$m | D88: =D81+D87 -> 179.806 | E88: =E81+E87 -> 208.381 | F88: =F81+F87 -> 340.475 | G88: =G81+G87 -> 425.663 | H88: =H81+H87 -> 440.957 | I88: =I81+I87 -> 551.212 | J88: =J81+J87 -> 661.368 | K88: =K81+K87 -> 634.291
B90: Marketing Costs | C90: A$m | D90: -80.4 | E90: -113.571 | F90: -111.357 | G90: -128.386 | H90: -132.987 | I90: -166.022 | J90: -211.208 | K90: -173.696
B91: Other Opex | C91: A$m | D91: -65.871 | E91: -83.214 | F91: -80.221 | G91: -111.935 | H91: -157.597 | I91: -243.955 | J91: -613.1 | K91: -400.91
B92: EBITDA (Statutory) | C92: A$m | D92: 33.535 | E92: 11.596 | F92: 148.897 | G92: 185.342 | H92: 150.373 | I92: 141.235 | J92: -162.94 | K92: 59.685
B93: NPAT (Statutory) | C93: A$m | D93: 19.649 | E93: -5.502 | F93: 90.752 | G93: 113.062 | H93: 96.427 | I93: -37.632 | J93: -403.125 | K93: -142.677
B95: Ratios
B96: Cost of Sales as a % of Revenue | C96: % | D96: =D87/D81 -> -0.38920858 | E96: =E87/E81 -> -0.50474033 | F96: =F87/F81 -> -0.47648709 | G96: =G87/G81 -> -0.44381116 | H96: =H87/H81 -> -0.47002526 | I96: =I87/I81 -> -0.42963987 | J96: =J87/J81 -> -0.40256852 | K96: =K87/K81 -> -0.42985386
B97: Marketing as a % of Revenue | C97: % | D97: =D90/D81 -> -0.27311452 | E97: =E90/E81 -> -0.26992449 | F97: =F90/F81 -> -0.17122205 | G97: =G90/G81 -> -0.16775445 | H97: =H90/H81 -> -0.15983361 | I97: =I90/I81 -> -0.17178931 | J97: =J90/J81 -> -0.19078986 | K97: =K90/K81 -> -0.15613039
B98: EBITDA Margin (Statutory) | C98: % | D98: =D92/D81 -> 0.11391661 | E98: =E92/E81 -> 0.027560243 | F98: =F92/F81 -> 0.22894339 | G98: =G92/G81 -> 0.24217551 | H98: =H92/H81 -> 0.18072939 | I98: =I92/I81 -> 0.14614125 | J98: =J92/J81 -> -0.14718808 | K98: =K92/K81 -> 0.053649149
B99: NPAT Margin (Statutory) | C99: % | D99: =D93/D81 -> 0.066746608 | E99: =E93/E81 -> -0.013076618 | F99: =F93/F81 -> 0.13953989 | G99: =G93/G81 -> 0.14773147 | H99: =H93/H81 -> 0.1158931 | I99: =I93/I81 -> -0.038939269 | J99: =J93/J81 -> -0.36415364 | K99: =K93/K81 -> -0.1282483

Sheet Bet365 ASIC
B1: Hillside (Australia New Media) Pty Ltd — bet365 Australia
B2: Statement of profit or loss · ABN 75 148 920 665 · online sports & racing wagering · ultimate parent bet365 Group Ltd (UK)
B3: All figures A$'000 unless stated · ~52/53-week period ending late March (FY25 ended 30 Mar 2025) · latest-reported basis
D5: FY18 | E5: FY19 | F5: FY20 | G5: FY21 | H5: FY22 | I5: FY23 | J5: FY24 | K5: FY25
D6: 43190 | E6: =EOMONTH(D6,12) -> 43555 | F6: =EOMONTH(E6,12) -> 43921 | G6: =EOMONTH(F6,12) -> 44286 | H6: =EOMONTH(G6,12) -> 44651 | I6: =EOMONTH(H6,12) -> 45016 | J6: =EOMONTH(I6,12) -> 45382 | K6: =EOMONTH(J6,12) -> 45747
B7: REVENUE & OTHER INCOME
B8: Revenue from contracts with customers (net betting revenue) | D8: 114999 | E8: 120914 | F8: 147173 | G8: 190321 | H8: 200429 | I8: 201286 | J8: 261002 | K8: 292645
B9: Other revenue | D9: 178 | E9: 422 | F9: 151 | G9: 20 | H9: 1 | I9: 217 | J9: 2099 | K9: 3142
B10: Other income | D10: 30 | E10: 35 | F10: -19 | G10: 45 | H10: 22 | I10: 9
B11: Total revenue & other income | D11: =SUM(D8:D10) -> 115207 | E11: =SUM(E8:E10) -> 121371 | F11: =SUM(F8:F10) -> 147305 | G11: =SUM(G8:G10) -> 190386 | H11: =SUM(H8:H10) -> 200452 | I11: =SUM(I8:I10) -> 201512 | J11: =SUM(J8:J10) -> 263101 | K11: =SUM(K8:K10) -> 295787
D14: =D20 -> -30324 | E14: =E20 -> -36799 | F14: =F20 -> -32768 | G14: =G20 -> -37038 | H14: =H20 -> -41518 | I14: =I20 -> -44618 | J14: =J20 -> -42113 | K14: =K20 -> -49748
B17: EXPENSES
B18: Government taxes & levies | D18: -29906 | E18: -41267 | F18: -56073 | G18: -70855 | H18: -74595 | I18: -80187 | J18: -99073 | K18: -115865
B19: Employee benefits expense | D19: -34214 | E19: -40664 | F19: -43577 | G19: -48696 | H19: -49796 | I19: -54732 | J19: -67589 | K19: -77474
B20: Advertising expense | D20: -30324 | E20: -36799 | F20: -32768 | G20: -37038 | H20: -41518 | I20: -44618 | J20: -42113 | K20: -49748
B21: Allocation of group costs (intercompany) | D21: -11763 | E21: -5715 | F21: -24711 | G21: -22645 | H21: -10530 | I21: 1098 | J21: -7519 | K21: -7259
B22: Depreciation & amortisation | D22: -951 | E22: -1925 | F22: -3252 | G22: -4066 | H22: -3495 | I22: -3608 | J22: -4577 | K22: -5374
B23: Finance costs | E23: -54 | F23: -198 | G23: -363 | H23: -346 | I23: -527 | J23: -942 | K23: -970
B24: Other expenses | D24: -6730 | E24: -7315 | F24: -6634 | G24: -5246 | H24: -5878 | I24: -9875 | J24: -16563 | K24: -17896
B25: Total expenses | D25: =SUM(D18:D24) -> -113888 | E25: =SUM(E18:E24) -> -133739 | F25: =SUM(F18:F24) -> -167213 | G25: =SUM(G18:G24) -> -188909 | H25: =SUM(H18:H24) -> -186158 | I25: =SUM(I18:I24) -> -192449 | J25: =SUM(J18:J24) -> -238376 | K25: =SUM(K18:K24) -> -274586
B27: Profit / (loss) before income tax | D27: =D11+D25 -> 1319 | E27: =E11+E25 -> -12368 | F27: =F11+F25 -> -19908 | G27: =G11+G25 -> 1477 | H27: =H11+H25 -> 14294 | I27: =I11+I25 -> 9063 | J27: =J11+J25 -> 24725 | K27: =K11+K25 -> 21201
B28: Reported profit / (loss) before income tax | D28: 1319 | E28: -12368 | F28: -19908 | G28: 1477 | H28: 14294 | I28: 9063 | J28: 24725 | K28: 21201
B29: Check (nil = ties to filing) | D29: =D27-D28 -> 0 | E29: =E27-E28 -> 0 | F29: =F27-F28 -> 0 | G29: =G27-G28 -> 0 | H29: =H27-H28 -> 0 | I29: =I27-I28 -> 0 | J29: =J27-J28 -> 0 | K29: =K27-K28 -> 0
B30: Income tax (expense) / benefit | D30: -397 | E30: 3705 | F30: 5969 | G30: -473 | H30: -4294 | I30: -2746 | J30: -7462 | K30: -6400
B31: Net profit / (loss) for the period | D31: =D27+D30 -> 922 | E31: =E27+E30 -> -8663 | F31: =F27+F30 -> -13939 | G31: =G27+G30 -> 1004 | H31: =H27+H30 -> 10000 | I31: =I27+I30 -> 6317 | J31: =J27+J30 -> 17263 | K31: =K27+K30 -> 14801
B33: MEMO — EBITDA BRIDGE
B34: Profit / (loss) before income tax | D34: =D27 -> 1319 | E34: =E27 -> -12368 | F34: =F27 -> -19908 | G34: =G27 -> 1477 | H34: =H27 -> 14294 | I34: =I27 -> 9063 | J34: =J27 -> 24725 | K34: =K27 -> 21201
B35: add back: Depreciation & amortisation | D35: =-D22 -> 951 | E35: =-E22 -> 1925 | F35: =-F22 -> 3252 | G35: =-G22 -> 4066 | H35: =-H22 -> 3495 | I35: =-I22 -> 3608 | J35: =-J22 -> 4577 | K35: =-K22 -> 5374
B36: add back: Finance costs | D36: =-D23 -> 0 | E36: =-E23 -> 54 | F36: =-F23 -> 198 | G36: =-G23 -> 363 | H36: =-H23 -> 346 | I36: =-I23 -> 527 | J36: =-J23 -> 942 | K36: =-K23 -> 970
B37: Statutory EBITDA | D37: =SUM(D34:D36) -> 2270 | E37: =SUM(E34:E36) -> -10389 | F37: =SUM(F34:F36) -> -16458 | G37: =SUM(G34:G36) -> 5906 | H37: =SUM(H34:H36) -> 18135 | I37: =SUM(I34:I36) -> 13198 | J37: =SUM(J34:J36) -> 30244 | K37: =SUM(K34:K36) -> 27545
B38: add back: Allocation of group costs (intercompany) | D38: =-D21 -> 11763 | E38: =-E21 -> 5715 | F38: =-F21 -> 24711 | G38: =-G21 -> 22645 | H38: =-H21 -> 10530 | I38: =-I21 -> -1098 | J38: =-J21 -> 7519 | K38: =-K21 -> 7259
B39: EBITDA before group-cost allocation | D39: =D37+D38 -> 14033 | E39: =E37+E38 -> -4674 | F39: =F37+F38 -> 8253 | G39: =G37+G38 -> 28551 | H39: =H37+H38 -> 28665 | I39: =I37+I38 -> 12100 | J39: =J37+J38 -> 37763 | K39: =K37+K38 -> 34804
B41: MEMO — RATIOS & TRENDS
B42: Revenue growth % (net betting revenue) | E42: =(E8/D8)-1 -> 0.05143523 | F42: =(F8/E8)-1 -> 0.21717088 | G42: =(G8/F8)-1 -> 0.29317878 | H42: =(H8/G8)-1 -> 0.053110272 | I42: =(I8/H8)-1 -> 0.0042758283 | J42: =(J8/I8)-1 -> 0.2966724 | K42: =(K8/J8)-1 -> 0.12123662
B43: Government taxes & levies % of revenue | D43: =-D18/D8 -> 0.26005444 | E43: =-E18/E8 -> 0.34129216 | F43: =-F18/F8 -> 0.38100059 | G43: =-G18/G8 -> 0.37229207 | H43: =-H18/H8 -> 0.37217668 | I43: =-I18/I8 -> 0.39837346 | J43: =-J18/J8 -> 0.37958713 | K43: =-K18/K8 -> 0.39592339
B44: Advertising % of revenue | D44: =-D20/D8 -> 0.26368925 | E44: =-E20/E8 -> 0.30434027 | F44: =-F20/F8 -> 0.22264953 | G44: =-G20/G8 -> 0.19460806 | H44: =-H20/H8 -> 0.20714567 | I44: =-I20/I8 -> 0.2216647 | J44: =-J20/J8 -> 0.16135125 | K44: =-K20/K8 -> 0.16999436
B45: Employee benefits % of revenue | D45: =-D19/D8 -> 0.29751563 | E45: =-E19/E8 -> 0.33630514 | F45: =-F19/F8 -> 0.29609371 | G45: =-G19/G8 -> 0.25586246 | H45: =-H19/H8 -> 0.24844708 | I45: =-I19/I8 -> 0.27191161 | J45: =-J19/J8 -> 0.2589597 | K45: =-K19/K8 -> 0.26473714
B46: Statutory EBITDA margin % | D46: =D37/D8 -> 0.019739302 | E46: =E37/E8 -> -0.085920572 | F46: =F37/F8 -> -0.11182758 | G46: =G37/G8 -> 0.031031783 | H46: =H37/H8 -> 0.090480918 | I46: =I37/I8 -> 0.065568395 | J46: =J37/J8 -> 0.11587651 | K46: =K37/K8 -> 0.09412428
B47: EBITDA (excl. group allocation) margin % | D47: =D39/D8 -> 0.12202715 | E47: =E39/E8 -> -0.038655573 | F47: =F39/F8 -> 0.056076862 | G47: =G39/G8 -> 0.15001497 | H47: =H39/H8 -> 0.14301823 | I47: =I39/I8 -> 0.06011347 | J47: =J39/J8 -> 0.14468472 | K47: =K39/K8 -> 0.11892908
