Workbook

Sheet NAV
B2: betr
B3: Model navigation
B6: COMPANY DETAILS | G6: ANALYST CONTACTS | J6: COMPANY CONTACTS
B7: Name | E7: betr | G7: Sam Bradshaw | J7: Andrew Menz | L7: CEO | P7: andrew.menz@betr.com.au
B8: Ticker | E8: BBT-ASX | G8: 0488063503 | J8: Bill Richmond | L8: COO | P8: bill.richmond@betr.com.au
B9: Exchange | E9: Australia | G9: sam.bradshaw@eandp.com.au | J9: Blake Matthews | L9: CFO | P9: blake.matthews@betr.com.au
B10: Sector | E10: Gaming
B11: Industry | E11: Wagering
B14: VALUATION | G14: Trading Multiples | J14: FY26 | K14: FY27 | L14: FY28 | M14: FY29 | N14: FY30 | P14: No Visible Alpha Data avaliable
B15: Share price (A$) | E15: =HY!D610 -> 0.2 | G15: EV/AEBITDA | J15: =IFERROR(FY!I271,"Needs Link") -> Needs Link | K15: =IFERROR(FY!J271,"Needs Link") -> Needs Link | L15: =IFERROR(FY!K271,"Needs Link") -> Needs Link | M15: =IFERROR(FY!L271,"Needs Link") -> Needs Link | N15: =IFERROR(FY!M271,"Needs Link") -> Needs Link
B16: Valuation (A$) | E16: =HY!D607 -> 0.27 | G16: P/E | J16: =IFERROR(FY!I273,"Needs Link") -> Needs Link | K16: =IFERROR(FY!J273,"Needs Link") -> Needs Link | L16: =IFERROR(FY!K273,"Needs Link") -> Needs Link | M16: =IFERROR(FY!L273,"Needs Link") -> Needs Link | N16: =IFERROR(FY!M273,"Needs Link") -> Needs Link
B17: Upside / (downside) | E17: =E16/E15-1 -> 0.35
B20: Revs
B21: Consensus
B22: check QTR CFO's & expenses
B23: Qtr First Take

Sheet BM
B1: =D8 -> BBT-ASX
A2: Industrial ResearchWise Sheet | R2: BlueMatrix formulas
C3: Company static items | E3: =+E114 -> FY2022A | F3: =+F114 -> FY2023A | G3: =+G114 -> FY2024A | H3: =+H114 -> FY2025F | I3: =+I114 -> FY2026F | J3: =+J114 -> FY2027F | K3: =+K114 -> FY2028F | L3: =+L114 -> FY2029F | ... Q3: =+Q114 -> FY2034F | S3: 2022 | T3: =S3+1 -> 2023 | U3: =T3+1 -> 2024 | V3: =U3+1 -> 2025 | W3: =V3+1 -> 2026 | X3: =W3+1 -> 2027 | Y3: =X3+1 -> 2028 | Z3: =Y3+1 -> 2029 | AA3: =Z3+1 -> 2030 | ... AE3: =AD3+1 -> 2034
A4: @BEGINSTATIC | D4: @ENDSTATIC
A5: @INSTTYPE | C5: Instrument type | D5: EQ
A6: @CTYPE | C6: Instrument code type | D6: @BB
A7: @VERSION | C7: Version information (Do not change) | D7: 1
A8: @CODE | C8: Ticker | D8: BBT-ASX
A9: @MULT | C9: Multiplier | D9: 1000000
A10: @RCURR | C10: Reporting Currency | D10: $
A11: @ANALYST | C11: Lead analyst | D11: Sam Bradshaw
A13: @TARGET | B13: PRICE_TARGET | C13: Valuation | D13: =HY!D607 -> 0.27 | R13: =_xll.BLUEMATRIX2("/servlet/excelData",$D13,$B$1,$B13) -> #
A14: @REC | B14: REC | C14: Recommendation | D14: Positive | R14: =_xll.BLUEMATRIX2("/servlet/excelData",$D14,$B$1,$B14) -> #
A15: @SHARE_OUT | B15: SHARE_OUT | C15: Shares outstanding | D15: =HY!D565 -> 1054.3063 | R15: =_xll.BLUEMATRIX2("/servlet/excelData",$D15,$B$1,$B15) -> #
A16: @FLOATPER | B16: free_float | C16: Free Float % | D16: 42.66 | R16: =_xll.BLUEMATRIX2("/servlet/excelData",$D16,$B$1,$B16) -> #
B17: PRICE | C17: Current Share Price | D17: 0.195 | R17: =_xll.BLUEMATRIX2("/servlet/excelData",$D17,$B$1,$B17) -> #
C18: Historic Share Price (Closing) | H18: =FY!H302 -> 0.27 | I18: =FY!I302 -> 0.19 | J18: =FY!J302 -> 0.20108205 | K18: =FY!K302 -> 0.21281047 | L18: =FY!L302 -> 0.22522297 | M18: =FY!M302 -> 0.23835946 | N18: =FY!N302 -> 0.25226214 | O18: =FY!O302 -> 0.26697573 | ... Q18: =FY!Q302 -> 0.29902753
C20: TSR
B21: upside_valuation | C21: Upside to valuation | D21: =(D13/D17-1)*100 -> 38.461538 | R21: =_xll.BLUEMATRIX2("/servlet/excelData",$D21,$B$1,$B21) -> #
B22: div_yield | C22: Dividend yield | D22: =I303*100 -> 0 | R22: =_xll.BLUEMATRIX2("/servlet/excelData",$D22,$B$1,$B22) -> #
B23: exp_total_return | C23: Expected total SH return | D23: =D21+D22 -> 38.461538 | R23: =_xll.BLUEMATRIX2("/servlet/excelData",$D23,$B$1,$B23) -> #
C25: Trading Data test
B26: 12_month_high | C26: 12 month high
B27: 12_month_low | C27: 12 month low
B28: MARKET_CAP | C28: Market cap | D28: =D17*D15 -> 205.58973 | R28: =_xll.BLUEMATRIX2("/servlet/excelData",$D28,$B$1,$B28) -> #
B29: free_float | C29: Free Float
B30: 12_month_return | C30: 12 month return (historical)
A31: @pricing_date
C34: Blended Valuation
A35: @DCF_VAL | B35: DCF_VAL | C35: Valuation - DCF | R35: =_xll.BLUEMATRIX2("/servlet/excelData",$D35,$B$1,$B35) -> #
A36: @CAPPER_VAL | B36: CAPPER_VAL | C36: Valuation - Capitalisation of Earnings | R36: =_xll.BLUEMATRIX2("/servlet/excelData",$D36,$B$1,$B36) -> #
A37: @PER_VAL | B37: PER_VAL | C37: Valuation - PER | R37: =_xll.BLUEMATRIX2("/servlet/excelData",$D37,$B$1,$B37) -> #
A38: @SOTP_VAL | B38: SOTP_VAL | C38: Valuation - SOTP | R38: =_xll.BLUEMATRIX2("/servlet/excelData",$D38,$B$1,$B38) -> #
A39: @BLEND_VAL | B39: PRICE_TARGET | C39: Valuation - Blended | R39: =_xll.BLUEMATRIX2("/servlet/excelData",$D39,$B$1,$B39) -> #
A40: @DCF_WT | B40: DCF_WT | C40: DCF Weightage | D40: 50 | R40: =_xll.BLUEMATRIX2("/servlet/excelData",$D40,$B$1,$B40) -> #
A41: @CAPPER_WT | B41: CAPPER_WT | C41: Capitalisation of Earnings Weightage | D41: 50 | R41: =_xll.BLUEMATRIX2("/servlet/excelData",$D41,$B$1,$B41) -> #
A42: @PER_WT | B42: PER_WT | C42: PER Weightage | R42: =_xll.BLUEMATRIX2("/servlet/excelData",$D42,$B$1,$B42) -> #
A43: @SOTP_WT | B43: SOTP_WT | C43: SOTP Weightage | R43: =_xll.BLUEMATRIX2("/servlet/excelData",$D43,$B$1,$B43) -> #
C45: Divisional Summary
A46: @SEG1_NAME | C46: Name of Segment 1 | D46: Turnover | R46: =_xll.BLUEMATRIX2("/servlet/excelData",$D46,$B$1,$B46) -> #
A47: @SEG2_NAME | C47: Name of Segment 2 | D47: Gross Win | R47: =_xll.BLUEMATRIX2("/servlet/excelData",$D47,$B$1,$B47) -> #
A48: @SEG3_NAME | C48: Name of Segment 3 | D48: Net Win | R48: =_xll.BLUEMATRIX2("/servlet/excelData",$D48,$B$1,$B48) -> #
A49: @SEG4_NAME | C49: Name of Segment 4
A50: @SEG5_NAME | C50: Name of Segment 5
A51: @SEG6_NAME | C51: Name of Segment 6
A52: @SEG7_NAME | C52: Name of Segment 7
A53: @SEG8_NAME | C53: Name of Segment 8
A54: @SEG9_NAME | C54: Name of Segment 9
A55: @SEG10_NAME | C55: Name of Segment 10
A57: @SEG_PROFIT1 | C57: Type of Segmental Results
A59: @SEG_PROFIT2 | C59: Type of Segmental Results
C61: Core Drivers, Investment Thesis, Near Term Catalysts
A62: @COREDRIVER1 | C62: Core Driver 1 | R62: =_xll.BLUEMATRIX2("/servlet/excelData",D62,$B$1,"BOILER_PLATE[[eap_core_drivers]]") -> #
A63: @COREDRIVER1 | C63: Core Driver 2 | R63: =_xll.BLUEMATRIX2("/servlet/excelData",D63,$B$1,"BOILER_PLATE[[eap_core_drivers]]") -> #
A64: @COREDRIVER1 | C64: Core Driver 3 | R64: =_xll.BLUEMATRIX2("/servlet/excelData",D64,$B$1,"BOILER_PLATE[[eap_core_drivers]]") -> #
A65: @COREDRIVER1 | C65: Core Driver 4 | R65: =_xll.BLUEMATRIX2("/servlet/excelData",D65,$B$1,"BOILER_PLATE[[eap_core_drivers]]") -> #
A66: @COREDRIVER1 | C66: Core Driver 5
A68: @THESIS1 | C68: Investment Thesis 1 | R68: =_xll.BLUEMATRIX2("/servlet/excelData",D68,$B$1,"BOILER_PLATE[[Investment_thesis]]") -> #
A69: @THESIS1 | C69: Investment Thesis 2 | R69: =_xll.BLUEMATRIX2("/servlet/excelData",D69,$B$1,"BOILER_PLATE[[Investment_thesis]]") -> #
A70: @THESIS1 | C70: Investment Thesis 3 | R70: =_xll.BLUEMATRIX2("/servlet/excelData",D70,$B$1,"BOILER_PLATE[[Investment_thesis]]") -> #
A71: @THESIS1 | C71: Investment Thesis 4
A72: @THESIS1 | C72: Investment Thesis 5
A74: @CATALYST1 | C74: Near Term Catalyst 1
A76: @NOTES | C76: Notes
C78: Key Macro Assumptions
A79: @KEYMAC1 | C79: Name of Key Macro Assumption 1
A80: @KEYMAC2 | C80: Name of Key Macro Assumption 2
A81: @KEYMAC3 | C81: Name of Key Macro Assumption 3
A82: @KEYMAC4 | C82: Name of Key Macro Assumption 4
A83: @KEYMAC5 | C83: Name of Key Macro Assumption 5
A84: @KEYMAC6 | C84: Name of Key Macro Assumption 6
A85: @KEYMAC7 | C85: Name of Key Macro Assumption 7
A86: @KEYMAC8 | C86: Name of Key Macro Assumption 8
A87: @KEYMAC9 | C87: Name of Key Macro Assumption 9
A88: @KEYMAC10 | C88: Name of Key Macro Assumption 10
C90: Type of Key Macro Assumption
A91: @KEYMACTYPE1 | C91: Type of Key Macro Assumption 1
A92: @KEYMACTYPE2 | C92: Type of Key Macro Assumption 2
A93: @KEYMACTYPE3 | C93: Type of Key Macro Assumption 3
A94: @KEYMACTYPE4 | C94: Type of Key Macro Assumption 4
A95: @KEYMACTYPE5 | C95: Type of Key Macro Assumption 5
A96: @KEYMACTYPE6 | C96: Type of Key Macro Assumption 6
A97: @KEYMACTYPE7 | C97: Type of Key Macro Assumption 7
A98: @KEYMACTYPE8 | C98: Type of Key Macro Assumption 8
A99: @KEYMACTYPE9 | C99: Type of Key Macro Assumption 9
A100: @KEYMACTYPE10 | C100: Type of Key Macro Assumption 10
C102: Companies for Relative Chart
A103: @COM1 | C103: Company 1
A104: @COM2 | C104: Company 2
A105: @COM3 | C105: Company 3
A106: @COM4 | C106: Company 4
A107: @COM5 | C107: Company 5
A108: @COM6 | C108: Company 6
A109: @INDEX | C109: Index
A111: @ENDSTATIC
C113: Financials & other data
A114: @BEGIN | C114: Year | E114: =E117&E115&E116 -> FY2022A | F114: =F117&F115&F116 -> FY2023A | G114: =G117&G115&G116 -> FY2024A | H114: =H117&H115&H116 -> FY2025F | I114: =I117&I115&I116 -> FY2026F | J114: =J117&J115&J116 -> FY2027F | K114: =K117&K115&K116 -> FY2028F | L114: =L117&L115&L116 -> FY2029F | ... Q114: =Q117&Q115&Q116 -> FY2034F | R114: AN
A115: @DATE | C115: Reporting Financial Year | E115: 2022 | F115: =E115+1 -> 2023 | G115: =F115+1 -> 2024 | H115: =G115+1 -> 2025 | I115: =H115+1 -> 2026 | J115: =I115+1 -> 2027 | K115: =J115+1 -> 2028 | L115: =K115+1 -> 2029 | M115: =L115+1 -> 2030 | ... Q115: =P115+1 -> 2034
A116: @FSTATUS | C116: Accounts Status | E116: A | F116: A | G116: A | H116: F | I116: F | J116: F | K116: F | L116: F | M116: F | N116: F | O116: F | P116: F | Q116: F
A117: @FPERIOD | C117: Reporting Period | E117: FY | F117: FY | G117: FY | H117: FY | I117: FY | J117: FY | K117: FY | L117: FY | M117: FY | N117: FY | O117: FY | P117: FY | Q117: FY
...

Sheet I

Sheet QTR
A2: X | B2: Valuation | D2: VAL | E2: =E8&E12 -> 1Q22A | F2: =F8&F12 -> 2Q22A | G2: =G8&G12 -> 3Q22A | H2: =H8&H12 -> 4Q22A | I2: =I8&I12 -> 1Q23A | J2: =J8&J12 -> 2Q23A | K2: =K8&K12 -> 3Q23A | L2: =L8&L12 -> 4Q23A | ... CB2: =CB8&CB12 -> 4Q40E
B3: Period End | E3: 44469 | F3: =EOMONTH(E3,3) -> 44561 | G3: =EOMONTH(F3,3) -> 44651 | H3: =EOMONTH(G3,3) -> 44742 | I3: =EOMONTH(H3,3) -> 44834 | J3: =EOMONTH(I3,3) -> 44926 | K3: =EOMONTH(J3,3) -> 45016 | L3: =EOMONTH(K3,3) -> 45107 | M3: =EOMONTH(L3,3) -> 45199 | ... CB3: =EOMONTH(CA3,3) -> 51317
B5: Quarter | E5: {=_xlfn.IFS(AND(MONTH(E$3)>=1,MONTH(E$3)<=3),"3Q",AND(MONTH(E$3)>=4,MONTH(E$3)<=6),"4Q",AND(MONTH(E$3)>=7,MONTH(E$3)<=9),"1Q",AND(MONTH(E$3)>=10,MONTH(E$3)<=12),"2Q")} -> 1Q | F5: {=_xlfn.IFS(AND(MONTH(F$3)>=1,MONTH(F$3)<=3),"3Q",AND(MONTH(F$3)>=4,MONTH(F$3)<=6),"4Q",AND(MONTH(F$3)>=7,MONTH(F$3)<=9),"1Q",AND(MONTH(F$3)>=10,MONTH(F$3)<=12),"2Q")} -> 2Q | G5: {=_xlfn.IFS(AND(MONTH(G$3)>=1,MONTH(G$3)<=3),"3Q",AND(MONTH(G$3)>=4,MONTH(G$3)<=6),"4Q",AND(MONTH(G$3)>=7,MONTH(G$3)<=9),"1Q",AND(MONTH(G$3)>=10,MONTH(G$3)<=12),"2Q")} -> 3Q | H5: {=_xlfn.IFS(AND(MONTH(H$3)>=1,MONTH(H$3)<=3),"3Q",AND(MONTH(H$3)>=4,MONTH(H$3)<=6),"4Q",AND(MONTH(H$3)>=7,MONTH(H$3)<=9),"1Q",AND(MONTH(H$3)>=10,MONTH(H$3)<=12),"2Q")} -> 4Q | I5: {=_xlfn.IFS(AND(MONTH(I$3)>=1,MONTH(I$3)<=3),"3Q",AND(MONTH(I$3)>=4,MONTH(I$3)<=6),"4Q",AND(MONTH(I$3)>=7,MONTH(I$3)<=9),"1Q",AND(MONTH(I$3)>=10,MONTH(I$3)<=12),"2Q")} -> 1Q | J5: {=_xlfn.IFS(AND(MONTH(J$3)>=1,MONTH(J$3)<=3),"3Q",AND(MONTH(J$3)>=4,MONTH(J$3)<=6),"4Q",AND(MONTH(J$3)>=7,MONTH(J$3)<=9),"1Q",AND(MONTH(J$3)>=10,MONTH(J$3)<=12),"2Q")} -> 2Q | K5: {=_xlfn.IFS(AND(MONTH(K$3)>=1,MONTH(K$3)<=3),"3Q",AND(MONTH(K$3)>=4,MONTH(K$3)<=6),"4Q",AND(MONTH(K$3)>=7,MONTH(K$3)<=9),"1Q",AND(MONTH(K$3)>=10,MONTH(K$3)<=12),"2Q")} -> 3Q | L5: {=_xlfn.IFS(AND(MONTH(L$3)>=1,MONTH(L$3)<=3),"3Q",AND(MONTH(L$3)>=4,MONTH(L$3)<=6),"4Q",AND(MONTH(L$3)>=7,MONTH(L$3)<=9),"1Q",AND(MONTH(L$3)>=10,MONTH(L$3)<=12),"2Q")} -> 4Q | ... CB5: {=_xlfn.IFS(AND(MONTH(CB$3)>=1,MONTH(CB$3)<=3),"3Q",AND(MONTH(CB$3)>=4,MONTH(CB$3)<=6),"4Q",AND(MONTH(CB$3)>=7,MONTH(CB$3)<=9),"1Q",AND(MONTH(CB$3)>=10,MONTH(CB$3)<=12),"2Q")} -> 4Q
B6: Half | E6: {=_xlfn.IFS(AND(MONTH(E$3)>=1,MONTH(E$3)<=6),"2H",AND(MONTH(E$3)>=7,MONTH(E$3)<=12),"1H")} -> 1H | F6: {=_xlfn.IFS(AND(MONTH(F$3)>=1,MONTH(F$3)<=6),"2H",AND(MONTH(F$3)>=7,MONTH(F$3)<=12),"1H")} -> 1H | G6: {=_xlfn.IFS(AND(MONTH(G$3)>=1,MONTH(G$3)<=6),"2H",AND(MONTH(G$3)>=7,MONTH(G$3)<=12),"1H")} -> 2H | H6: {=_xlfn.IFS(AND(MONTH(H$3)>=1,MONTH(H$3)<=6),"2H",AND(MONTH(H$3)>=7,MONTH(H$3)<=12),"1H")} -> 2H | I6: {=_xlfn.IFS(AND(MONTH(I$3)>=1,MONTH(I$3)<=6),"2H",AND(MONTH(I$3)>=7,MONTH(I$3)<=12),"1H")} -> 1H | J6: {=_xlfn.IFS(AND(MONTH(J$3)>=1,MONTH(J$3)<=6),"2H",AND(MONTH(J$3)>=7,MONTH(J$3)<=12),"1H")} -> 1H | K6: {=_xlfn.IFS(AND(MONTH(K$3)>=1,MONTH(K$3)<=6),"2H",AND(MONTH(K$3)>=7,MONTH(K$3)<=12),"1H")} -> 2H | L6: {=_xlfn.IFS(AND(MONTH(L$3)>=1,MONTH(L$3)<=6),"2H",AND(MONTH(L$3)>=7,MONTH(L$3)<=12),"1H")} -> 2H | ... CB6: {=_xlfn.IFS(AND(MONTH(CB$3)>=1,MONTH(CB$3)<=6),"2H",AND(MONTH(CB$3)>=7,MONTH(CB$3)<=12),"1H")} -> 2H
B7: FY | E7: {=_xlfn.IFS(AND(MONTH(E$3)>=1,MONTH(E$3)<=6),RIGHT(YEAR(E3),2),AND(MONTH(E$3)>=7,MONTH(E$3)<=12),RIGHT(YEAR(E3)+1,2))} -> 22 | F7: {=_xlfn.IFS(AND(MONTH(F$3)>=1,MONTH(F$3)<=6),RIGHT(YEAR(F3),2),AND(MONTH(F$3)>=7,MONTH(F$3)<=12),RIGHT(YEAR(F3)+1,2))} -> 22 | G7: {=_xlfn.IFS(AND(MONTH(G$3)>=1,MONTH(G$3)<=6),RIGHT(YEAR(G3),2),AND(MONTH(G$3)>=7,MONTH(G$3)<=12),RIGHT(YEAR(G3)+1,2))} -> 22 | H7: {=_xlfn.IFS(AND(MONTH(H$3)>=1,MONTH(H$3)<=6),RIGHT(YEAR(H3),2),AND(MONTH(H$3)>=7,MONTH(H$3)<=12),RIGHT(YEAR(H3)+1,2))} -> 22 | I7: {=_xlfn.IFS(AND(MONTH(I$3)>=1,MONTH(I$3)<=6),RIGHT(YEAR(I3),2),AND(MONTH(I$3)>=7,MONTH(I$3)<=12),RIGHT(YEAR(I3)+1,2))} -> 23 | J7: {=_xlfn.IFS(AND(MONTH(J$3)>=1,MONTH(J$3)<=6),RIGHT(YEAR(J3),2),AND(MONTH(J$3)>=7,MONTH(J$3)<=12),RIGHT(YEAR(J3)+1,2))} -> 23 | K7: {=_xlfn.IFS(AND(MONTH(K$3)>=1,MONTH(K$3)<=6),RIGHT(YEAR(K3),2),AND(MONTH(K$3)>=7,MONTH(K$3)<=12),RIGHT(YEAR(K3)+1,2))} -> 23 | L7: {=_xlfn.IFS(AND(MONTH(L$3)>=1,MONTH(L$3)<=6),RIGHT(YEAR(L3),2),AND(MONTH(L$3)>=7,MONTH(L$3)<=12),RIGHT(YEAR(L3)+1,2))} -> 23 | ... CB7: {=_xlfn.IFS(AND(MONTH(CB$3)>=1,MONTH(CB$3)<=6),RIGHT(YEAR(CB3),2),AND(MONTH(CB$3)>=7,MONTH(CB$3)<=12),RIGHT(YEAR(CB3)+1,2))} -> 40
B8: QTR FY | E8: =E$5&TEXT(E$7,"00") -> 1Q22 | F8: =F$5&TEXT(F$7,"00") -> 2Q22 | G8: =G$5&TEXT(G$7,"00") -> 3Q22 | H8: =H$5&TEXT(H$7,"00") -> 4Q22 | I8: =I$5&TEXT(I$7,"00") -> 1Q23 | J8: =J$5&TEXT(J$7,"00") -> 2Q23 | K8: =K$5&TEXT(K$7,"00") -> 3Q23 | L8: =L$5&TEXT(L$7,"00") -> 4Q23 | ... CB8: =CB$5&TEXT(CB$7,"00") -> 4Q40
B9: HY FY | E9: =E$6&TEXT(E$7,"00") -> 1H22 | F9: =F$6&TEXT(F$7,"00") -> 1H22 | G9: =G$6&TEXT(G$7,"00") -> 2H22 | H9: =H$6&TEXT(H$7,"00") -> 2H22 | I9: =I$6&TEXT(I$7,"00") -> 1H23 | J9: =J$6&TEXT(J$7,"00") -> 1H23 | K9: =K$6&TEXT(K$7,"00") -> 2H23 | L9: =L$6&TEXT(L$7,"00") -> 2H23 | ... CB9: =CB$6&TEXT(CB$7,"00") -> 2H40
B10: FY | E10: ="FY"&E7 -> FY22 | F10: ="FY"&F7 -> FY22 | G10: ="FY"&G7 -> FY22 | H10: ="FY"&H7 -> FY22 | I10: ="FY"&I7 -> FY23 | J10: ="FY"&J7 -> FY23 | K10: ="FY"&K7 -> FY23 | L10: ="FY"&L7 -> FY23 | ... CB10: ="FY"&CB7 -> FY40
B11: Calendar Year | E11: =YEAR(E3) -> 2021 | F11: =YEAR(F3) -> 2021 | G11: =YEAR(G3) -> 2022 | H11: =YEAR(H3) -> 2022 | I11: =YEAR(I3) -> 2022 | J11: =YEAR(J3) -> 2022 | K11: =YEAR(K3) -> 2023 | L11: =YEAR(L3) -> 2023 | ... CB11: =YEAR(CB3) -> 2040
B12: Actual/Estimate | E12: =E17 -> A | F12: =F17 -> A | G12: =G17 -> A | H12: =H17 -> A | I12: =I17 -> A | J12: =J17 -> A | K12: =K17 -> A | L12: =L17 -> A | ... CB12: =CB17 -> E
B13: Days in period | E13: 92 | F13: =F3-E3 -> 92 | G13: =G3-F3 -> 90 | H13: =H3-G3 -> 91 | I13: =I3-H3 -> 92 | J13: =J3-I3 -> 92 | K13: =K3-J3 -> 90 | L13: =L3-K3 -> 91 | M13: =M3-L3 -> 92 | ... CB13: =CB3-CA3 -> 91
A15: X | B15: GENERAL
B17: Actual/Estimate | C17: A/E | E17: A | F17: A | G17: A | H17: A | I17: A | J17: A | K17: A | L17: A | M17: A | N17: A | O17: A | P17: A | Q17: A | R17: A | S17: A | T17: A | U17: A | V17: A | W17: E | X17: E | Y17: E | Z17: E | AA17: E | AB17: E | AC17: E | AD17: E | AE17: E | AF17: E | AG17: E | AH17: E | AI17: E | AJ17: E | AK17: E | AL17: E | AM17: E | AN17: E | AO17: E | AP17: E | AQ17: E | AR17: E | AS17: E | AT17: E | AU17: E | AV17: E | AW17: E | AX17: E | AY17: E | AZ17: E | BA17: E | BB17: E | BC17: E | BD17: E | BE17: E | BF17: E | BG17: E | BH17: E | BI17: E | BJ17: E | BK17: E | BL17: E | BM17: E | BN17: E | BO17: E | BP17: E | BQ17: E | BR17: E | BS17: E | BT17: E | BU17: E | BV17: E | BW17: E | BX17: E | BY17: E | BZ17: E | CA17: E | CB17: E
A19: X | B19: KPI's
B21: AUSTRALIA
P22: ~
B23: Underlying | C23: A$m | R23: 357 | V23: =R23*(1+V24) -> 403.41
B24: growth | C24: % | V24: 0.13
B26: TopSport | C26: A$m | V26: =V29-V23 -> 40.99
B27: growth | C27: % | V27: =V26/R26-1 -> #DIV/0!
B29: Turnover | C29: A$m | M29: 143.9 | N29: 154.8 | O29: 139.2 | P29: 153.6 | Q29: 286.6 | R29: 357 | S29: 376 | T29: 399.5 | U29: 363 | V29: 444.4 | W29: 383 | X29: 404.3 | Y29: =U29*(1+Y30) -> 413.82 | Z29: =V29*(1+Z30) -> 473.286
B30: growth | C30: % | Q30: =Q29/M29-1 -> 0.99166088 | R30: =R29/N29-1 -> 1.3062016 | S30: =S29/O29-1 -> 1.7011494 | T30: =T29/P29-1 -> 1.6009115 | U30: =U29/Q29-1 -> 0.26657362 | V30: =V29/R29-1 -> 0.24481793 | W30: =W29/S29-1 -> 0.018617021 | X30: =X29/T29-1 -> 0.012015019 | Y30: 0.14 | Z30: 0.065
B32: Active Customers | C32: 000's | Q32: 120.2 | R32: 144.7 | S32: 153 | T32: 155.4 | U32: 154.7 | V32: 163.5 | W32: 157.264 | X32: 156.479
B33: XX | C33: %
B35: Gross Win | C35: A$m | M35: 18.8 | N35: 21.2 | O35: 18.6 | P35: 20.8 | Q35: 38.8 | R35: 52.2 | S35: 51.7 | T35: 53.1 | U35: 51.8 | V35: 55.9 | W35: 50.3 | X35: 57.1 | Y35: =Y29*Y36 -> 59.17626 | Z35: =Z29*Z36 -> 67.679898
B36: margin | C36: % | M36: =M35/M29 -> 0.13064628 | N36: =N35/N29 -> 0.1369509 | O36: =O35/O29 -> 0.13362069 | P36: =P35/P29 -> 0.13541667 | Q36: =Q35/Q29 -> 0.13538032 | R36: =R35/R29 -> 0.14621849 | S36: =S35/S29 -> 0.1375 | T36: =T35/T29 -> 0.13291615 | ... X36: =X35/X29 -> 0.14123176 | Y36: 0.143 | Z36: 0.143
B38: Promos | C38: A$m | M38: =M41-M35 -> -4.3 | N38: =N41-N35 -> -5 | O38: =O41-O35 -> -3.3 | P38: =P41-P35 -> -3.5 | Q38: =Q41-Q35 -> -10.9 | R38: =R41-R35 -> -13 | S38: =S41-S35 -> -13.9 | T38: =T41-T35 -> -12.9 | ... X38: =X41-X35 -> -13.2 | Y38: =Y29*Y39 -> -14.89752 | Z38: =Z29*Z39 -> -17.984868
B39: Promo % | C39: % | M39: =M38/M29 -> -0.029881862 | N39: =N38/N29 -> -0.032299742 | O39: =O38/O29 -> -0.023706897 | P39: =P38/P29 -> -0.022786458 | Q39: =Q38/Q29 -> -0.0380321 | R39: =R38/R29 -> -0.036414566 | S39: =S38/S29 -> -0.036968085 | T39: =T38/T29 -> -0.032290363 | ... X39: =X38/X29 -> -0.032649023 | Y39: -0.036 | Z39: -0.038
B41: Net Win | C41: A$m | M41: 14.5 | N41: 16.2 | O41: 15.3 | P41: 17.3 | Q41: 27.9 | R41: 39.2 | S41: 37.8 | T41: 40.2 | U41: 38 | V41: 37.9 | W41: 38.2 | X41: 43.9 | Y41: =Y35+Y38 -> 44.27874 | Z41: =Z35+Z38 -> 49.69503
B42: margin | C42: % | M42: =M41/M29 -> 0.10076442 | N42: =N41/N29 -> 0.10465116 | O42: =O41/O29 -> 0.10991379 | P42: =P41/P29 -> 0.11263021 | Q42: =Q41/Q29 -> 0.097348221 | R42: =R41/R29 -> 0.10980392 | S42: =S41/S29 -> 0.10053191 | T42: =T41/T29 -> 0.10062578 | ... Z42: =Z41/Z29 -> 0.105
B43: growth | C43: % | M43: =M41/I41-1 -> #DIV/0! | N43: =N41/J41-1 -> #DIV/0! | O43: =O41/K41-1 -> #DIV/0! | P43: =P41/L41-1 -> #DIV/0! | Q43: =Q41/M41-1 -> 0.92413793 | R43: =R41/N41-1 -> 1.4197531 | S43: =S41/O41-1 -> 1.4705882 | T43: =T41/P41-1 -> 1.3236994 | ... Z43: =Z41/V41-1 -> 0.31121451
B45: Q2 Net Win by ~1.75pp | V45: =V42+1.75% -> 0.10278353
B46: Adjusted Net Win | V46: =V29*V45 -> 45.677
B48: Advertising & Marketing | Q48: -2.9 | R48: -7 | S48: -3.6 | T48: -5.5 | U48: -11.5 | V48: -10.3 | W48: -7.7023 | X48: -4.0542
B49: % of Turnover | M49: =M48/M29 -> 0 | N49: =N48/N29 -> 0 | O49: =O48/O29 -> 0 | P49: =P48/P29 -> 0 | Q49: =Q48/Q29 -> -0.010118632 | R49: =R48/R29 -> -0.019607843 | S49: =S48/S29 -> -0.0095744681 | T49: =T48/T29 -> -0.013767209 | ... X49: =X48/X29 -> -0.010027702
B50: % of Net Win | M50: =M48/M41 -> 0 | N50: =N48/N41 -> 0 | O50: =O48/O41 -> 0 | P50: =P48/P41 -> 0 | Q50: =Q48/Q41 -> -0.10394265 | R50: =R48/R41 -> -0.17857143 | S50: =S48/S41 -> -0.095238095 | T50: =T48/T41 -> -0.13681592 | ... X50: =X48/X41 -> -0.092350797
B52: Operating Cash Flows
B53: Receipts from customers (Client deposits) | Q53: 95.2173 | R53: 124.1533 | S53: 123.82 | T53: 127.4679 | U53: 128.332 | V53: 155.3913 | W53: 136.5391 | X53: 150.7245
B54: Payments to customers (Client withdrawals) | Q54: -72.2125 | R54: -86.8197 | S54: -84.8136 | T54: -95.5732 | U54: -91.9765 | V54: -117.291 | W54: -99.5739 | X54: -106.6411
B55: Cost of Sales | Q55: -10.6027 | R55: -19.7536 | S55: -17.3842 | T55: -22.2244 | U55: -18.4506 | V55: -19.9761 | W55: -21.2051 | X55: -23.3236
B56: Advertising & Marketing | Q56: -2.8566 | R56: -7.0287 | S56: -3.6047 | T56: -5.515 | U56: -11.5128 | V56: -10.2818 | W56: -7.7023 | X56: -4.0542
B57: Staff Costs | Q57: -5.3441 | R57: -5.8688 | S57: -5.3764 | T57: -3.9015 | U57: -5.5151 | V57: -8.6579 | W57: -6.3165 | X57: -4.9624
B58: Administration and Corporate costs | U58: -6.2475 | V58: -7.8092 | W58: -6.9811 | X58: -7.7759
B59: Leased Assets | U59: -0.4224 | V59: -0.3782 | W59: -2.8637 | X59: -0.5237
B60: Interest Received | U60: 0.9052 | V60: 0.3187 | W60: 0.0206 | X60: 0.0186
B61: Interest & Other Finance Costs | U61: -0.8465 | V61: -1.0202 | W61: -0.8166 | X61: -0.8422
B62: Net Cash used from Operating Activities | U62: -5.7343 | V62: -9.7044 | W62: -8.8995 | X62: 2.6
B63: Check | U63: =U62-SUM(U53:U61) -> -0.0001 | V63: =V62-SUM(V53:V61) -> 0 | W63: =W62-SUM(W53:W61) -> 0 | X63: =X62-SUM(X53:X61) -> -0.02
B65: Investing Cash Flows
B66: Payments to acquire:
B67: Businesses | U67: -2.1975 | V67: -1.4255 | W67: -1.1733 | X67: -0.8484
B68: PPE | U68: -0.0661 | V68: -0.1512 | W68: -0.0505 | X68: -0.0295
B69: Investments | U69: 0 | V69: -40.6495 | W69: 0 | X69: 0
B70: Intellectual Property | U70: -1.869 | V70: -2.2416 | W70: -2.1994 | X70: -2.3063
B71: Net Cash used from Operating Activities | U71: -4.1326 | V71: -44.4678 | W71: -3.4232 | X71: -3.1843
B72: Check | U72: =U71-SUM(U67:U70) -> 0 | V72: =V71-SUM(V67:V70) -> 0 | W72: =W71-SUM(W67:W70) -> 0 | X72: =X71-SUM(X67:X70) -> -0.0001
B74: Net Cash from / (used in) Operating Activities | U74: =U62 -> -5.7343 | V74: =V62 -> -9.7044 | W74: =W62 -> -8.8995 | X74: =X62 -> 2.6
B75: Net Cash from / (used in) Investing Activities | U75: =U71 -> -4.1326 | V75: =V71 -> -44.4678 | W75: =W71 -> -3.4232 | X75: =X71 -> -3.1843
B76: Net Cash from / (used in) Financing Activities | U76: 0 | V76: 0 | W76: 0 | X76: -0.3837
B77: Net increase / (decrease) in cash and cash equivalents | U77: -9.8669 | V77: -54.1721 | W77: -12.3226 | X77: -0.9481
B78: Check | U78: =U77-SUM(U74:U76) -> 0 | V78: =V77-SUM(V74:V76) -> 0.0001 | W78: =W77-SUM(W74:W76) -> 0.0001 | X78: =X77-SUM(X74:X76) -> 0.0199
B80: Cash and Cash Equivalents at the end of the Quarter | U80: 95.2027 | V80: 41.0306 | W80: 28.7079 | X80: 27.7599
B83: Net Win Check
B84: Net Deposits | Q84: =Q53+Q54 -> 23.0048 | R84: =R53+R54 -> 37.3336 | S84: =S53+S54 -> 39.0064 | T84: =T53+T54 -> 31.8947 | U84: =U53+U54 -> 36.3555 | V84: =V53+V54 -> 38.1003 | W84: =W53+W54 -> 36.9652 | X84: =X53+X54 -> 44.0834
B85: Net Win | Q85: =Q41 -> 27.9 | R85: =R41 -> 39.2 | S85: =S41 -> 37.8 | T85: =T41 -> 40.2 | U85: =U41 -> 38 | V85: =V41 -> 37.9 | W85: =W41 -> 38.2 | X85: =X41 -> 43.9
B87: Difference | Q87: =Q84-Q85 -> -4.8952 | R87: =R84-R85 -> -1.8664 | S87: =S84-S85 -> 1.2064 | T87: =T84-T85 -> -8.3053 | U87: =U84-U85 -> -1.6445 | V87: =V84-V85 -> 0.2003 | W87: =W84-W85 -> -1.2348 | X87: =X84-X85 -> 0.1834
B89: Client Balance | Q89: 13.1 | R89: 12 | S89: 12.6 | T89: 13.8 | U89: 13.7 | V89: 13.6 | W89: 12.7 | X89: 11
B90: Change | R90: =R89-Q89 -> -1.1 | S90: =S89-R89 -> 0.6 | T90: =T89-S89 -> 1.2 | U90: =U89-T89 -> -0.1 | V90: =V89-U89 -> -0.1 | W90: =W89-V89 -> -0.9 | X90: =X89-W89 -> -1.7
B92: Cash Net of Client Balances | U92: =U80-U89 -> 81.5027 | V92: =V80-V89 -> 27.4306 | W92: =W80-W89 -> 16.0079 | X92: =X80-X89 -> 16.7599

Sheet HY
K1: =K255 -> 4.3410829 | L1: =L255 -> 7.4191626
B3: Management EBITDA Target (normalised) | I3: 2H26 | J3: $5m-$8m | K3: FY27 | L3: $13m-$19m
B4: E&P | J4: =J119 -> 6.1 | L4: =K119+L119 -> 16.471693 | N4: =M119+N119 -> 21.580368 | P4: =O119+P119 -> 25.531054 | R4: =Q119+R119 -> 28.423656
B6: Checks | C6: =SUM(E6:AL6) -> 0 | E6: =E334 -> 0 | F6: =F334 -> 0 | G6: =G334 -> 0 | H6: =H334 -> 0 | I6: =I334 -> 0 | J6: =J334 -> 0 | K6: =K334 -> 0 | L6: =L334 -> 0 | ... AL6: =AL334 -> 0
A7: X | B7: Valuation | C7: =$D$607 -> 0.27 | D7: VAL | E7: =E13&E16 -> 1H24A | F7: =F13&F16 -> 2H24A | G7: =G13&G16 -> 1H25A | H7: =H13&H16 -> 2H25A | I7: =I13&I16 -> 1H26A | J7: =J13&J16 -> 2H26A | K7: =K13&K16 -> 1H27E | L7: =L13&L16 -> 2H27E | ... AL7: =AL13&AL16 -> 2H40E
B8: Period End | E8: 45291 | F8: =EOMONTH(E8,6) -> 45473 | G8: =EOMONTH(F8,6) -> 45657 | H8: =EOMONTH(G8,6) -> 45838 | I8: =EOMONTH(H8,6) -> 46022 | J8: =EOMONTH(I8,6) -> 46203 | K8: =EOMONTH(J8,6) -> 46387 | L8: =EOMONTH(K8,6) -> 46568 | M8: =EOMONTH(L8,6) -> 46752 | ... AL8: =EOMONTH(AK8,6) -> 51317
B10: Quarter | E10: {=_xlfn.IFS(AND(MONTH(E$8)>=1,MONTH(E$8)<=3),"3Q",AND(MONTH(E$8)>=4,MONTH(E$8)<=6),"4Q",AND(MONTH(E$8)>=7,MONTH(E$8)<=9),"1Q",AND(MONTH(E$8)>=10,MONTH(E$8)<=12),"2Q")} -> 2Q | F10: {=_xlfn.IFS(AND(MONTH(F$8)>=1,MONTH(F$8)<=3),"3Q",AND(MONTH(F$8)>=4,MONTH(F$8)<=6),"4Q",AND(MONTH(F$8)>=7,MONTH(F$8)<=9),"1Q",AND(MONTH(F$8)>=10,MONTH(F$8)<=12),"2Q")} -> 4Q | G10: {=_xlfn.IFS(AND(MONTH(G$8)>=1,MONTH(G$8)<=3),"3Q",AND(MONTH(G$8)>=4,MONTH(G$8)<=6),"4Q",AND(MONTH(G$8)>=7,MONTH(G$8)<=9),"1Q",AND(MONTH(G$8)>=10,MONTH(G$8)<=12),"2Q")} -> 2Q | H10: {=_xlfn.IFS(AND(MONTH(H$8)>=1,MONTH(H$8)<=3),"3Q",AND(MONTH(H$8)>=4,MONTH(H$8)<=6),"4Q",AND(MONTH(H$8)>=7,MONTH(H$8)<=9),"1Q",AND(MONTH(H$8)>=10,MONTH(H$8)<=12),"2Q")} -> 4Q | I10: {=_xlfn.IFS(AND(MONTH(I$8)>=1,MONTH(I$8)<=3),"3Q",AND(MONTH(I$8)>=4,MONTH(I$8)<=6),"4Q",AND(MONTH(I$8)>=7,MONTH(I$8)<=9),"1Q",AND(MONTH(I$8)>=10,MONTH(I$8)<=12),"2Q")} -> 2Q | J10: {=_xlfn.IFS(AND(MONTH(J$8)>=1,MONTH(J$8)<=3),"3Q",AND(MONTH(J$8)>=4,MONTH(J$8)<=6),"4Q",AND(MONTH(J$8)>=7,MONTH(J$8)<=9),"1Q",AND(MONTH(J$8)>=10,MONTH(J$8)<=12),"2Q")} -> 4Q | K10: {=_xlfn.IFS(AND(MONTH(K$8)>=1,MONTH(K$8)<=3),"3Q",AND(MONTH(K$8)>=4,MONTH(K$8)<=6),"4Q",AND(MONTH(K$8)>=7,MONTH(K$8)<=9),"1Q",AND(MONTH(K$8)>=10,MONTH(K$8)<=12),"2Q")} -> 2Q | L10: {=_xlfn.IFS(AND(MONTH(L$8)>=1,MONTH(L$8)<=3),"3Q",AND(MONTH(L$8)>=4,MONTH(L$8)<=6),"4Q",AND(MONTH(L$8)>=7,MONTH(L$8)<=9),"1Q",AND(MONTH(L$8)>=10,MONTH(L$8)<=12),"2Q")} -> 4Q | ... AL10: {=_xlfn.IFS(AND(MONTH(AL$8)>=1,MONTH(AL$8)<=3),"3Q",AND(MONTH(AL$8)>=4,MONTH(AL$8)<=6),"4Q",AND(MONTH(AL$8)>=7,MONTH(AL$8)<=9),"1Q",AND(MONTH(AL$8)>=10,MONTH(AL$8)<=12),"2Q")} -> 4Q
B11: Half | E11: {=_xlfn.IFS(AND(MONTH(E$8)>=1,MONTH(E$8)<=6),"2H",AND(MONTH(E$8)>=7,MONTH(E$8)<=12),"1H")} -> 1H | F11: {=_xlfn.IFS(AND(MONTH(F$8)>=1,MONTH(F$8)<=6),"2H",AND(MONTH(F$8)>=7,MONTH(F$8)<=12),"1H")} -> 2H | G11: {=_xlfn.IFS(AND(MONTH(G$8)>=1,MONTH(G$8)<=6),"2H",AND(MONTH(G$8)>=7,MONTH(G$8)<=12),"1H")} -> 1H | H11: {=_xlfn.IFS(AND(MONTH(H$8)>=1,MONTH(H$8)<=6),"2H",AND(MONTH(H$8)>=7,MONTH(H$8)<=12),"1H")} -> 2H | I11: {=_xlfn.IFS(AND(MONTH(I$8)>=1,MONTH(I$8)<=6),"2H",AND(MONTH(I$8)>=7,MONTH(I$8)<=12),"1H")} -> 1H | J11: {=_xlfn.IFS(AND(MONTH(J$8)>=1,MONTH(J$8)<=6),"2H",AND(MONTH(J$8)>=7,MONTH(J$8)<=12),"1H")} -> 2H | K11: {=_xlfn.IFS(AND(MONTH(K$8)>=1,MONTH(K$8)<=6),"2H",AND(MONTH(K$8)>=7,MONTH(K$8)<=12),"1H")} -> 1H | L11: {=_xlfn.IFS(AND(MONTH(L$8)>=1,MONTH(L$8)<=6),"2H",AND(MONTH(L$8)>=7,MONTH(L$8)<=12),"1H")} -> 2H | ... AL11: {=_xlfn.IFS(AND(MONTH(AL$8)>=1,MONTH(AL$8)<=6),"2H",AND(MONTH(AL$8)>=7,MONTH(AL$8)<=12),"1H")} -> 2H
B12: FY | E12: {=_xlfn.IFS(AND(MONTH(E$8)>=1,MONTH(E$8)<=6),RIGHT(YEAR(E8),2),AND(MONTH(E$8)>=7,MONTH(E$8)<=12),RIGHT(YEAR(E8)+1,2))} -> 24 | F12: {=_xlfn.IFS(AND(MONTH(F$8)>=1,MONTH(F$8)<=6),RIGHT(YEAR(F8),2),AND(MONTH(F$8)>=7,MONTH(F$8)<=12),RIGHT(YEAR(F8)+1,2))} -> 24 | G12: {=_xlfn.IFS(AND(MONTH(G$8)>=1,MONTH(G$8)<=6),RIGHT(YEAR(G8),2),AND(MONTH(G$8)>=7,MONTH(G$8)<=12),RIGHT(YEAR(G8)+1,2))} -> 25 | H12: {=_xlfn.IFS(AND(MONTH(H$8)>=1,MONTH(H$8)<=6),RIGHT(YEAR(H8),2),AND(MONTH(H$8)>=7,MONTH(H$8)<=12),RIGHT(YEAR(H8)+1,2))} -> 25 | I12: {=_xlfn.IFS(AND(MONTH(I$8)>=1,MONTH(I$8)<=6),RIGHT(YEAR(I8),2),AND(MONTH(I$8)>=7,MONTH(I$8)<=12),RIGHT(YEAR(I8)+1,2))} -> 26 | J12: {=_xlfn.IFS(AND(MONTH(J$8)>=1,MONTH(J$8)<=6),RIGHT(YEAR(J8),2),AND(MONTH(J$8)>=7,MONTH(J$8)<=12),RIGHT(YEAR(J8)+1,2))} -> 26 | K12: {=_xlfn.IFS(AND(MONTH(K$8)>=1,MONTH(K$8)<=6),RIGHT(YEAR(K8),2),AND(MONTH(K$8)>=7,MONTH(K$8)<=12),RIGHT(YEAR(K8)+1,2))} -> 27 | L12: {=_xlfn.IFS(AND(MONTH(L$8)>=1,MONTH(L$8)<=6),RIGHT(YEAR(L8),2),AND(MONTH(L$8)>=7,MONTH(L$8)<=12),RIGHT(YEAR(L8)+1,2))} -> 27 | ... AL12: {=_xlfn.IFS(AND(MONTH(AL$8)>=1,MONTH(AL$8)<=6),RIGHT(YEAR(AL8),2),AND(MONTH(AL$8)>=7,MONTH(AL$8)<=12),RIGHT(YEAR(AL8)+1,2))} -> 40
B13: HY FY | E13: =E$11&TEXT(E$12,"00") -> 1H24 | F13: =F$11&TEXT(F$12,"00") -> 2H24 | G13: =G$11&TEXT(G$12,"00") -> 1H25 | H13: =H$11&TEXT(H$12,"00") -> 2H25 | I13: =I$11&TEXT(I$12,"00") -> 1H26 | J13: =J$11&TEXT(J$12,"00") -> 2H26 | K13: =K$11&TEXT(K$12,"00") -> 1H27 | L13: =L$11&TEXT(L$12,"00") -> 2H27 | ... AL13: =AL$11&TEXT(AL$12,"00") -> 2H40
B14: HY FY | E14: ="FY"&E12 -> FY24 | F14: ="FY"&F12 -> FY24 | G14: ="FY"&G12 -> FY25 | H14: ="FY"&H12 -> FY25 | I14: ="FY"&I12 -> FY26 | J14: ="FY"&J12 -> FY26 | K14: ="FY"&K12 -> FY27 | L14: ="FY"&L12 -> FY27 | ... AL14: ="FY"&AL12 -> FY40
B15: Calendar Year | E15: =YEAR(E8) -> 2023 | F15: =YEAR(F8) -> 2024 | G15: =YEAR(G8) -> 2024 | H15: =YEAR(H8) -> 2025 | I15: =YEAR(I8) -> 2025 | J15: =YEAR(J8) -> 2026 | K15: =YEAR(K8) -> 2026 | L15: =YEAR(L8) -> 2027 | ... AL15: =YEAR(AL8) -> 2040
B16: Actual/Estimate | E16: =E21 -> A | F16: =F21 -> A | G16: =G21 -> A | H16: =H21 -> A | I16: =I21 -> A | J16: =J21 -> A | K16: =K21 -> E | L16: =L21 -> E | ... AL16: =AL21 -> E
B17: Days in period | E17: 184 | F17: =F8-E8 -> 182 | G17: =G8-F8 -> 184 | H17: =H8-G8 -> 181 | I17: =I8-H8 -> 184 | J17: =J8-I8 -> 181 | K17: =K8-J8 -> 184 | L17: =L8-K8 -> 181 | M17: =M8-L8 -> 184 | ... AL17: =AL8-AK8 -> 182
A19: X | B19: GENERAL
B21: Actual/Estimate | C21: A/E | E21: A | F21: A | G21: A | H21: A | I21: A | J21: A | K21: E | L21: E | M21: E | N21: E | O21: E | P21: E | Q21: E | R21: E | S21: E | T21: E | U21: E | V21: E | W21: E | X21: E | Y21: E | Z21: E | AA21: E | AB21: E | AC21: E | AD21: E | AE21: E | AF21: E | AG21: E | AH21: E | AI21: E | AJ21: E | AK21: E | AL21: E
B23: Commentary
A24: 1Q | B24: Marketing spend is front-weighted. So, the output in half two will be a reduction on that, approximately circa AUD 10 million for the second half of the year
A25: 2Q | B25: On net win margin, we're modeling that at that 10.4% historical rate that we've been able to achieve over a significant period of time
A26: 2Q | B26: We are assuming that the turnover – that the market will continue to grow in that low-single digits number. And we're assuming that we do continue to take share as we have. It does not need to be at 4 times the market for us to get to the guidance number
A27: 2Q | B27: But we do assume that we continue to take share as we get payback from the investment that we've made in those brand and product initiatives in the first half.
A28: 2Q | B28: This model is designed to enhance productivity, while maintaining service quality, and from Q4 onwards is expected to deliver approximately AUD 6 million in annualized run rate savings.
A29: 3Q | B29: We're confident that we grow in FY 2027 at mid- to high-single digits at the top line
A30: 3Q | B30: What we're not seeing is a reduction in customers or in active user days. We have seen in small cohorts of customers either a reduction in frequency or a reduction in bet size. Now, interestingly, when you have a reduction in bet size, it often translates to higher margin activities. So the impact on revenue has been really negligible in that respect with how the customers have continued to engage with us
A34: X | B34: SEGMENTS
B36: TOP SPORT
B37: Turnover
B38: BBT Underlying | C38: A$m | G38: =G64 -> 645.1 | I38: =G38*(1+I39) -> 728.963
B39: growth | C39: % | I39: 0.13
B41: TopSport | C41: A$m | G41: 198.9 | I41: =I64-I38 -> 78.337
B42: growth | C42: % | I42: =I41/G41-1 -> -0.60614882
B44: Combined | C44: A$m | G44: =G38+G41 -> 844 | I44: =I38+I41 -> 807.3
B45: growth | C45: % | I45: =I44/G44-1 -> -0.043483412
B47: Gross Win
B48: BBT Underlying | C48: A$m | G48: =G68 -> 91.3
B49: TopSport | C49: A$m | G49: 14.4
B50: Combined | C50: A$m | G50: =SUM(G48:G49) -> 105.7 | I50: =I68 -> 108.3
B51: growth | C51: % | I51: =I50/G50-1 -> 0.024597919
B53: Net Win
B54: BBT Underlying | C54: A$m | G54: =G75 -> 67.4
B55: TopSport | C55: A$m | G55: 11.8
B56: Combined | C56: A$m | G56: =SUM(G54:G55) -> 79.2 | I56: =I75 -> 75.8
B57: growth | C57: % | I57: =I56/G56-1 -> -0.042929293
B61: AUSTRALIA
L62: Advertising Ban
B63: QTR Sum | C63: A$m | E63: =SUMIFS(QTR!$E29:$CB29,QTR!$E$9:$CB$9,E$13) -> 298.7 | F63: =SUMIFS(QTR!$E29:$CB29,QTR!$E$9:$CB$9,F$13) -> 292.8 | G63: =SUMIFS(QTR!$E29:$CB29,QTR!$E$9:$CB$9,G$13) -> 643.6 | H63: =SUMIFS(QTR!$E29:$CB29,QTR!$E$9:$CB$9,H$13) -> 775.5 | I63: =SUMIFS(QTR!$E29:$CB29,QTR!$E$9:$CB$9,I$13) -> 807.4 | J63: =SUMIFS(QTR!$E29:$CB29,QTR!$E$9:$CB$9,J$13) -> 787.3 | K63: =SUMIFS(QTR!$E29:$CB29,QTR!$E$9:$CB$9,K$13) -> 887.106
B64: Turnover | C64: A$m | E64: 298.8 | F64: =591.9-E64 -> 293.1 | G64: 645.1 | H64: =1420.4-G64 -> 775.3 | I64: 807.3 | J64: =1594.7-I64 -> 787.4 | K64: =I64*(1+K65) -> 888.03 | L64: =J64*(1+L65) -> 834.644 | M64: =K64*(1+M65) -> 932.4315 | N64: =L64*(1+N65) -> 876.3762 | O64: =M64*(1+O65) -> 979.05308 | P64: =N64*(1+P65) -> 920.19501 | Q64: =O64*(1+Q65) -> 1028.0057 | R64: =P64*(1+R65) -> 966.20476 | ... AL64: =AJ64*(1+AL65) -> 1573.8457
B65: growth | C65: % | G65: =G64/E64-1 -> 1.1589692 | H65: =H64/F64-1 -> 1.6451723 | I65: =I64/G64-1 -> 0.25143389 | J65: =J64/H64-1 -> 0.015606862 | K65: 0.1 | L65: 0.06 | M65: 0.05 | N65: 0.05 | O65: 0.05 | P65: 0.05 | Q65: 0.05 | R65: 0.05 | S65: 0.05 | T65: 0.05 | U65: 0.05 | V65: 0.05 | W65: 0.05 | X65: 0.05 | Y65: 0.05 | Z65: 0.05 | AA65: 0.05 | AB65: 0.05 | AC65: 0.05 | AD65: 0.05 | AE65: 0.05 | AF65: 0.05 | AG65: 0.05 | AH65: 0.05 | AI65: 0.05 | AJ65: 0.05 | AK65: 0.05 | AL65: 0.05
B67: QTR Sum | C67: A$m | E67: =SUMIFS(QTR!$E35:$CB35,QTR!$E$9:$CB$9,E$13) -> 40 | F67: =SUMIFS(QTR!$E35:$CB35,QTR!$E$9:$CB$9,F$13) -> 39.4 | G67: =SUMIFS(QTR!$E35:$CB35,QTR!$E$9:$CB$9,G$13) -> 91 | H67: =SUMIFS(QTR!$E35:$CB35,QTR!$E$9:$CB$9,H$13) -> 104.8 | I67: =SUMIFS(QTR!$E35:$CB35,QTR!$E$9:$CB$9,I$13) -> 107.7 | J67: =SUMIFS(QTR!$E35:$CB35,QTR!$E$9:$CB$9,J$13) -> 107.4 | K67: =SUMIFS(QTR!$E35:$CB35,QTR!$E$9:$CB$9,K$13) -> 126.85616
B68: Gross Win | C68: A$m | E68: 40 | F68: =79.5-E68 -> 39.5 | G68: 91.3 | H68: =196.2-G68 -> 104.9 | I68: 108.3 | J68: =215.7-I68 -> 107.4 | K68: =K64*K69 -> 126.10026 | L68: =L64*L69 -> 116.85016 | M68: =M64*M69 -> 132.40527 | N68: =N64*N69 -> 122.69267 | O68: =O64*O69 -> 139.02554 | P68: =P64*P69 -> 128.8273 | Q68: =Q64*Q69 -> 145.97681 | R68: =R64*R69 -> 135.26867 | ... AL68: =AL64*AL69 -> 220.3384
B69: margin | C69: % | E69: =E68/E64 -> 0.13386881 | F69: =F68/F64 -> 0.13476629 | G69: =G68/G64 -> 0.14152845 | H69: =H68/H64 -> 0.13530246 | I69: =I68/I64 -> 0.13415087 | J69: =J68/J64 -> 0.13639827 | K69: 0.142 | L69: 0.14 | M69: =K69 -> 0.142 | N69: =L69 -> 0.14 | O69: =M69 -> 0.142 | P69: =N69 -> 0.14 | Q69: =O69 -> 0.142 | R69: =P69 -> 0.14 | S69: =Q69 -> 0.142 | T69: =R69 -> 0.14 | ... AL69: =AJ69 -> 0.14
B71: Promos | C71: A$m | E71: =E75-E68 -> -9.3 | F71: =F75-F68 -> -7.2 | G71: =G75-G68 -> -23.9 | H71: =H75-H68 -> -24.5 | I71: =I75-I68 -> -32.5 | J71: =J75-J68 -> -25.1 | K71: =K64*K72 -> -33.74514 | L71: =L64*L72 -> -25.873964 | M71: =M64*M72 -> -35.432397 | N71: =N64*N72 -> -27.167662 | O71: =O64*O72 -> -37.204017 | P71: =P64*P72 -> -28.526045 | Q71: =Q64*Q72 -> -39.064218 | R71: =R64*R72 -> -29.952348 | ... AL71: =AL64*AL72 -> -48.789218
B72: Promo % | C72: % | E72: =E71/E64 -> -0.031124498 | F72: =F71/F64 -> -0.024564995 | G72: =G71/G64 -> -0.03704852 | H72: =H71/H64 -> -0.031600671 | I72: =I71/I64 -> -0.040257649 | J72: =J71/J64 -> -0.031877064 | K72: -0.038 | L72: -0.031 | M72: =K72 -> -0.038 | N72: =L72 -> -0.031 | O72: =M72 -> -0.038 | P72: =N72 -> -0.031 | Q72: =O72 -> -0.038 | R72: =P72 -> -0.031 | S72: =Q72 -> -0.038 | T72: =R72 -> -0.031 | ... AL72: =AJ72 -> -0.031
B74: QTR Sum | C74: A$m | E74: =SUMIFS(QTR!$E41:$CB41,QTR!$E$9:$CB$9,E$13) -> 30.7 | F74: =SUMIFS(QTR!$E41:$CB41,QTR!$E$9:$CB$9,F$13) -> 32.6 | G74: =SUMIFS(QTR!$E41:$CB41,QTR!$E$9:$CB$9,G$13) -> 67.1 | H74: =SUMIFS(QTR!$E41:$CB41,QTR!$E$9:$CB$9,H$13) -> 78 | I74: =SUMIFS(QTR!$E41:$CB41,QTR!$E$9:$CB$9,I$13) -> 75.9 | J74: =SUMIFS(QTR!$E41:$CB41,QTR!$E$9:$CB$9,J$13) -> 82.1 | K74: =SUMIFS(QTR!$E41:$CB41,QTR!$E$9:$CB$9,K$13) -> 93.97377
B75: Net Win | C75: A$m | E75: 30.7 | F75: =63-E75 -> 32.3 | G75: 67.4 | H75: =147.8-G75 -> 80.4 | I75: 75.8 | J75: =158.1-I75 -> 82.3 | K75: =K68+K71 -> 92.35512 | L75: =L68+L71 -> 90.976196 | M75: =M68+M71 -> 96.972876 | N75: =N68+N71 -> 95.525006 | O75: =O68+O71 -> 101.82152 | P75: =P68+P71 -> 100.30126 | Q75: =Q68+Q71 -> 106.9126 | R75: =R68+R71 -> 105.31632 | ... AL75: =AL68+AL71 -> 171.54919
B76: margin | C76: % | E76: =E75/E64 -> 0.10274431 | F76: =F75/F64 -> 0.1102013 | G76: =G75/G64 -> 0.10447993 | H76: =H75/H64 -> 0.10370179 | I76: =I75/I64 -> 0.093893224 | J76: =J75/J64 -> 0.10452121 | K76: =K75/K64 -> 0.104 | L76: =L75/L64 -> 0.109 | ... AL76: =AL75/AL64 -> 0.109
B78: Active Customers | C78: 000's | G78: 144.697 | H78: 155.42 | I78: 163.504 | J78: 156.479
B79: Turnover per Customer | C79: $ | G79: =G64/G78*1000 -> 4458.2818 | H79: =H64/H78*1000 -> 4988.4185 | I79: =I64/I78*1000 -> 4937.4939 | J79: =J64/J78*1000 -> 5031.9851
B80: Net Win per Customer | C80: $ | G80: =G75/G78*1000 -> 465.80095 | H80: =H75/H78*1000 -> 517.30794 | I80: =I75/I78*1000 -> 463.59722 | J80: =J75/J78*1000 -> 525.94917
B82: By Event
B83: Sport | E83: 542 | F83: =9068-E83 -> 8526 | G83: 8160 | H83: =22388-G83 -> 14228 | I83: 9658 | J83: =26037-I83 -> 16379
B84: Horse racing | E84: 15295 | F84: =25554-E84 -> 10259 | G84: 28983 | H84: =57718-G84 -> 28735 | I84: 32894 | J84: =66099-I84 -> 33205
B85: Greyhounds | E85: 9370 | F85: =18225-E85 -> 8855 | G85: 18252 | H85: =38964-G85 -> 20712 | I85: 20432 | J85: =40490-I85 -> 20058
B86: Harness Racing | E86: 2610 | F86: =4742-E86 -> 2132 | G86: 6145 | H86: =12968-G86 -> 6823 | I86: 5879 | J86: =11130-I86 -> 5251
B87: Revenue | E87: 27817 | F87: =57589-E87 -> 29772 | G87: 61540 | H87: =132038-G87 -> 70498 | I87: 68863 | J87: =143756-I87 -> 74893
B89: Growth
B90: Sport | G90: =G83/E83-1 -> 14.055351 | H90: =H83/F83-1 -> 0.66877786 | I90: =I83/G83-1 -> 0.18357843 | J90: =J83/H83-1 -> 0.15118077
B91: Horse racing | G91: =G84/E84-1 -> 0.89493298 | H91: =H84/F84-1 -> 1.8009553 | I91: =I84/G84-1 -> 0.13494117 | J91: =J84/H84-1 -> 0.15555942
B92: Greyhounds | G92: =G85/E85-1 -> 0.94791889 | H92: =H85/F85-1 -> 1.3390175 | I92: =I85/G85-1 -> 0.11943897 | J92: =J85/H85-1 -> -0.031575898
B93: Harness Racing | G93: =G86/E86-1 -> 1.3544061 | H93: =H86/F86-1 -> 2.2002814 | I93: =I86/G86-1 -> -0.043287225 | J93: =J86/H86-1 -> -0.23039719
B94: Revenue | G94: =G87/E87-1 -> 1.2123162 | H94: =H87/F87-1 -> 1.3679296 | I94: =I87/G87-1 -> 0.11899578 | J94: =J87/H87-1 -> 0.062342194
B96: Splits
B97: Sport | E97: =E83/E$87 -> 0.019484488 | F97: =F83/F$87 -> 0.28637646 | G97: =G83/G$87 -> 0.13259669 | H97: =H83/H$87 -> 0.20182133 | I97: =I83/I$87 -> 0.14024948 | J97: =J83/J$87 -> 0.21869868
B98: Horse racing | E98: =E84/E$87 -> 0.54984362 | F98: =F84/F$87 -> 0.34458552 | G98: =G84/G$87 -> 0.47096198 | H98: =H84/H$87 -> 0.40760022 | I98: =I84/I$87 -> 0.47767306 | J98: =J84/J$87 -> 0.44336587
B99: Greyhounds | E99: =E85/E$87 -> 0.33684438 | F99: =F85/F$87 -> 0.29742711 | G99: =G85/G$87 -> 0.29658759 | H99: =H85/H$87 -> 0.29379557 | I99: =I85/I$87 -> 0.29670505 | J99: =J85/J$87 -> 0.26782209
B100: Harness Racing | E100: =E86/E$87 -> 0.093827516 | F100: =F86/F$87 -> 0.07161091 | G100: =G86/G$87 -> 0.099853754 | H100: =H86/H$87 -> 0.096782887 | I100: =I86/I$87 -> 0.085372406 | J100: =J86/J$87 -> 0.070113362
A102: X | B102: BBT P&L
B104: P&L - NORMALISED
B105: Turnover (gross of GST) | C105: A$m | E105: 298.8 | F105: =591.5-E105 -> 292.7 | G105: 645.1 | H105: =1420.4-G105 -> 775.3 | I105: 807.3 | J105: =1594.7-I105 -> 787.4 | K105: =K64 -> 888.03 | L105: =L64 -> 834.644 | M105: =M64 -> 932.4315 | N105: =N64 -> 876.3762 | O105: =O64 -> 979.05308 | P105: =P64 -> 920.19501 | Q105: =Q64 -> 1028.0057 | R105: =R64 -> 966.20476 | ... AL105: =AL64 -> 1573.8457
B106: Payouts (gross of GST) | C106: A$m | E106: -258.8 | F106: =-511.7-E106 -> -252.9 | G106: -553.8 | H106: =-1224.2-G106 -> -670.4 | I106: -699.1 | J106: =-1379-I106 -> -679.9 | K106: =K108-K105 -> -761.92974 | L106: =L108-L105 -> -717.79384 | M106: =M108-M105 -> -800.02623 | N106: =N108-N105 -> -753.68353 | O106: =O108-O105 -> -840.02754 | P106: =P108-P105 -> -791.36771 | Q106: =Q108-Q105 -> -882.02892 | R106: =R108-R105 -> -830.93609 | ... AL106: =AL108-AL105 -> -1353.5073
B107: ---------- | C107: ---------- | E107: ---------- | F107: ---------- | G107: ---------- | H107: ---------- | I107: ---------- | J107: ---------- | K107: ---------- | L107: ---------- | M107: ---------- | N107: ---------- | O107: ---------- | P107: ---------- | Q107: ---------- | R107: ---------- | S107: ---------- | T107: ---------- | U107: ---------- | V107: ---------- | W107: ---------- | X107: ---------- | Y107: ---------- | Z107: ---------- | AA107: ---------- | AB107: ---------- | AC107: ---------- | AD107: ---------- | AE107: ---------- | AF107: ---------- | AG107: ---------- | AH107: ---------- | AI107: ---------- | AJ107: ---------- | AK107: ---------- | AL107: ----------
B108: Gross Revenue | C108: A$m | E108: 40 | F108: =79.8-E108 -> 39.8 | G108: 91.3 | H108: =196.2-G108 -> 104.9 | I108: 108.3 | J108: =215.7-I108 -> 107.4 | K108: =K68 -> 126.10026 | L108: =L68 -> 116.85016 | M108: =M68 -> 132.40527 | N108: =N68 -> 122.69267 | O108: =O68 -> 139.02554 | P108: =P68 -> 128.8273 | Q108: =Q68 -> 145.97681 | R108: =R68 -> 135.26867 | ... AL108: =AL68 -> 220.3384
B109: Promotions given (gross of GST) | C109: A$m | E109: -9.3 | F109: =-16.5-E109 -> -7.2 | G109: -21.4 | H109: =-48.4-G109 -> -27 | I109: -32.5 | J109: =-55.8-I109 -> -23.3 | K109: =K71 -> -33.74514 | L109: =L71 -> -25.873964 | M109: =M71 -> -35.432397 | N109: =N71 -> -27.167662 | O109: =O71 -> -37.204017 | P109: =P71 -> -28.526045 | Q109: =Q71 -> -39.064218 | R109: =R71 -> -29.952348 | ... AL109: =AL71 -> -48.789218
B110: GST | C110: A$m | E110: -2.8 | F110: =-5.7-E110 -> -2.9 | G110: -6.3 | H110: =-13.2-G110 -> -6.9 | I110: -6.9 | J110: =-14.5-I110 -> -7.6 | K110: =(K108+K109)*-1/11 -> -8.39592 | L110: =(L108+L109)*-1/11 -> -8.2705633 | M110: =(M108+M109)*-1/11 -> -8.815716 | N110: =(N108+N109)*-1/11 -> -8.6840914 | O110: =(O108+O109)*-1/11 -> -9.2565018 | P110: =(P108+P109)*-1/11 -> -9.118296 | Q110: =(Q108+Q109)*-1/11 -> -9.7193269 | R110: =(R108+R109)*-1/11 -> -9.5742108 | ... AL110: =(AL108+AL109)*-1/11 -> -15.595381
B111: ---------- | C111: ---------- | E111: ---------- | F111: ---------- | G111: ---------- | H111: ---------- | I111: ---------- | J111: ---------- | K111: ---------- | L111: ---------- | M111: ---------- | N111: ---------- | O111: ---------- | P111: ---------- | Q111: ---------- | R111: ---------- | S111: ---------- | T111: ---------- | U111: ---------- | V111: ---------- | W111: ---------- | X111: ---------- | Y111: ---------- | Z111: ---------- | AA111: ---------- | AB111: ---------- | AC111: ---------- | AD111: ---------- | AE111: ---------- | AF111: ---------- | AG111: ---------- | AH111: ---------- | AI111: ---------- | AJ111: ---------- | AK111: ---------- | AL111: ----------
B112: Revenue | C112: A$m | E112: 27.9 | F112: =57.6-E112 -> 29.7 | G112: 63.6 | H112: =134.6-G112 -> 71 | I112: 68.9 | J112: =145.4-I112 -> 76.5 | K112: =SUM(K108:K111) -> 83.9592 | L112: =SUM(L108:L111) -> 82.705633 | M112: =SUM(M108:M111) -> 88.15716 | N112: =SUM(N108:N111) -> 86.840914 | O112: =SUM(O108:O111) -> 92.565018 | P112: =SUM(P108:P111) -> 91.18296 | Q112: =SUM(Q108:Q111) -> 97.193269 | R112: =SUM(R108:R111) -> 95.742108 | ... AL112: =SUM(AL108:AL111) -> 155.95381
B113: Cost of Sales | C113: A$m | E113: -12.8 | F113: =-26.8-E113 -> -14 | G113: -33.7 | H113: =-73.4-G113 -> -39.7 | I113: -43 | J113: =-84.9-I113 -> -41.9 | K113: =K203 -> -49.291071 | L113: =L203 -> -46.555656 | M113: =M203 -> -50.725896 | N113: =N203 -> -48.658439 | O113: =O203 -> -53.25619 | P113: =P203 -> -51.085361 | Q113: =Q203 -> -55.91282 | R113: =R203 -> -53.633449 | ... AL113: =AL203 -> -87.272536
B114: ---------- | C114: ---------- | E114: ---------- | F114: ---------- | G114: ---------- | H114: ---------- | I114: ---------- | J114: ---------- | K114: ---------- | L114: ---------- | M114: ---------- | N114: ---------- | O114: ---------- | P114: ---------- | Q114: ---------- | R114: ---------- | S114: ---------- | T114: ---------- | U114: ---------- | V114: ---------- | W114: ---------- | X114: ---------- | Y114: ---------- | Z114: ---------- | AA114: ---------- | AB114: ---------- | AC114: ---------- | AD114: ---------- | AE114: ---------- | AF114: ---------- | AG114: ---------- | AH114: ---------- | AI114: ---------- | AJ114: ---------- | AK114: ---------- | AL114: ----------
B115: Gross Profit | C115: A$m | E115: 15.1 | F115: =30.8-E115 -> 15.7 | G115: 29.9 | H115: =61.2-G115 -> 31.3 | I115: 25.9 | J115: =60.5-I115 -> 34.6 | K115: =SUM(K112:K114) -> 34.668129 | L115: =SUM(L112:L114) -> 36.149977 | M115: =SUM(M112:M114) -> 37.431264 | N115: =SUM(N112:N114) -> 38.182476 | O115: =SUM(O112:O114) -> 39.308828 | P115: =SUM(P112:P114) -> 40.097599 | Q115: =SUM(Q112:Q114) -> 41.280449 | R115: =SUM(R112:R114) -> 42.108659 | ... AL115: =SUM(AL112:AL114) -> 68.681269
B116: Other Income | C116: A$m | E116: 0 | F116: =0.5-E116 -> 0.5 | G116: 0.4 | H116: =1.1-G116 -> 0.7 | I116: 0.2 | J116: =0.5-I116 -> 0.3 | K116: =K238 -> 0.32925176 | L116: =L238 -> 0.32433581 | M116: =M238 -> 0.34571435 | N116: =N238 -> 0.34055261 | O116: =O238 -> 0.36300007 | P116: =P238 -> 0.35758024 | Q116: =Q238 -> 0.38115007 | R116: =R238 -> 0.37545925 | ... AL116: =AL238 -> 0.61158355
B117: Opex | C117: A$m | E117: -16.8 | F117: -14.3 | G117: -28.7 | H117: -26.4 | I117: -39.3 | J117: =-68.2-I117 -> -28.9 | K117: =K229 -> -29.5 | L117: =L229 -> -25.5 | M117: =M229 -> -29.149063 | N117: =N229 -> -25.570576 | O117: =O229 -> -29.019133 | P117: =P229 -> -25.57682 | Q117: =Q229 -> -28.866401 | R117: =R229 -> -26.855661 | ... AL117: =AL229 -> -42.887296
B118: ---------- | C118: ---------- | E118: ---------- | F118: ---------- | G118: ---------- | H118: ---------- | I118: ---------- | J118: ---------- | K118: ---------- | L118: ---------- | M118: ---------- | N118: ---------- | O118: ---------- | P118: ---------- | Q118: ---------- | R118: ---------- | S118: ---------- | T118: ---------- | U118: ---------- | V118: ---------- | W118: ---------- | X118: ---------- | Y118: ---------- | Z118: ---------- | AA118: ---------- | AB118: ---------- | AC118: ---------- | AD118: ---------- | AE118: ---------- | AF118: ---------- | AG118: ---------- | AH118: ---------- | AI118: ---------- | AJ118: ---------- | AK118: ---------- | AL118: ----------
B119: EBITDA | C119: A$m | E119: -1.7 | F119: =0.2-E119 -> 1.9 | G119: 1.7 | H119: =7.2-G119 -> 5.5 | I119: -13.2 | J119: =-7.1-I119 -> 6.1 | K119: =SUM(K115:K118) -> 5.4973804 | L119: =SUM(L115:L118) -> 10.974313 | M119: =SUM(M115:M118) -> 8.6279154 | N119: =SUM(N115:N118) -> 12.952452 | O119: =SUM(O115:O118) -> 10.652695 | P119: =SUM(P115:P118) -> 14.878359 | Q119: =SUM(Q115:Q118) -> 12.795198 | R119: =SUM(R115:R118) -> 15.628457 | ... AL119: =SUM(AL115:AL118) -> 26.405556
B120: Depreciation, Amortization and Impairments | C120: A$m | G120: -1.9 | H120: =-4.1-G120 -> -2.2 | I120: -6.2 | J120: =-12.9-I120 -> -6.7 | K120: =K341 -> -5.0869565 | L120: =L341 -> -5.0827794 | M120: =M341 -> -5.0708631 | N120: =N341 -> -5.0958729 | O120: =O341 -> -5.1095613 | P120: =P341 -> -5.1591744 | Q120: =Q341 -> -5.1943616 | R120: =R341 -> -5.2108038 | ... AL120: =AL341 -> -7.2227077
B121: Finance Costs | C121: A$m | G121: -0.2 | H121: -2.7 | I121: 0.3 | J121: =-0.8-I121 -> -1.1 | K121: =K424-K177 -> -0.57509041 | L121: =L424-L177 -> -0.55642588 | M121: =M424-M177 -> -0.55756182 | N121: =N424-N177 -> -1.5146909 | O121: =O424-O177 -> -1.4920629 | P121: =P424-P177 -> -1.4261052 | Q121: =Q424-Q177 -> -1.3989036 | R121: =R424-R177 -> -1.3156043 | ... AL121: =AL424-AL177 -> 0.42757327
B122: ---------- | C122: ---------- | E122: ---------- | F122: ---------- | G122: ---------- | H122: ---------- | I122: ---------- | J122: ---------- | K122: ---------- | L122: ---------- | M122: ---------- | N122: ---------- | O122: ---------- | P122: ---------- | Q122: ---------- | R122: ---------- | S122: ---------- | T122: ---------- | U122: ---------- | V122: ---------- | W122: ---------- | X122: ---------- | Y122: ---------- | Z122: ---------- | AA122: ---------- | AB122: ---------- | AC122: ---------- | AD122: ---------- | AE122: ---------- | AF122: ---------- | AG122: ---------- | AH122: ---------- | AI122: ---------- | AJ122: ---------- | AK122: ---------- | AL122: ----------
B123: Profit/(loss) before income tax expense | C123: A$m | G123: -0.4 | H123: =0.2-G123 -> 0.6 | I123: -19 | J123: =-20.8-I123 -> -1.8 | K123: =SUM(K119:K122) -> -0.16466657 | L123: =SUM(L119:L122) -> 5.3351073 | M123: =SUM(M119:M122) -> 2.9994905 | N123: =SUM(N119:N122) -> 6.3418885 | O123: =SUM(O119:O122) -> 4.0510704 | P123: =SUM(P119:P122) -> 8.2930798 | Q123: =SUM(Q119:Q122) -> 6.2019331 | R123: =SUM(R119:R122) -> 9.1020493 | ... AL123: =SUM(AL119:AL122) -> 19.610422
B124: Income tax expense | C124: A$m | G124: 2.4 | H124: =4.6-G124 -> 2.2 | I124: 0 | J124: =0.1-I124 -> 0.1 | K124: =K242 -> 0.04939997 | L124: =L242 -> -1.6005322 | M124: =M242 -> -0.89984715 | N124: =N242 -> -1.9025665 | O124: =O242 -> -1.2153211 | P124: =P242 -> -2.4879239 | Q124: =Q242 -> -1.8605799 | R124: =R242 -> -2.7306148 | ... AL124: =AL242 -> -5.8831265
B125: ---------- | C125: ---------- | E125: ---------- | F125: ---------- | G125: ---------- | H125: ---------- | I125: ---------- | J125: ---------- | K125: ---------- | L125: ---------- | M125: ---------- | N125: ---------- | O125: ---------- | P125: ---------- | Q125: ---------- | R125: ---------- | S125: ---------- | T125: ---------- | U125: ---------- | V125: ---------- | W125: ---------- | X125: ---------- | Y125: ---------- | Z125: ---------- | AA125: ---------- | AB125: ---------- | AC125: ---------- | AD125: ---------- | AE125: ---------- | AF125: ---------- | AG125: ---------- | AH125: ---------- | AI125: ---------- | AJ125: ---------- | AK125: ---------- | AL125: ----------
B126: Profit/(loss) after income tax | C126: A$m | G126: 2 | H126: =4.8-G126 -> 2.8 | I126: -19 | J126: =-20.7-I126 -> -1.7 | K126: =SUM(K123:K125) -> -0.1152666 | L126: =SUM(L123:L125) -> 3.7345751 | M126: =SUM(M123:M125) -> 2.0996434 | N126: =SUM(N123:N125) -> 4.4393219 | O126: =SUM(O123:O125) -> 2.8357493 | P126: =SUM(P123:P125) -> 5.8051559 | Q126: =SUM(Q123:Q125) -> 4.3413532 | R126: =SUM(R123:R125) -> 6.3714345 | ... AL126: =SUM(AL123:AL125) -> 13.727295
...

Sheet FY
E2: 2022 | F2: =E2+1 -> 2023 | G2: =F2+1 -> 2024 | H2: =G2+1 -> 2025 | I2: =H2+1 -> 2026 | J2: =I2+1 -> 2027 | K2: =J2+1 -> 2028 | L2: =K2+1 -> 2029 | M2: =L2+1 -> 2030 | ... Q2: =P2+1 -> 2034
E3: A | F3: A | G3: A | H3: A | I3: A | J3: E | K3: E | L3: E | M3: E | N3: E | O3: E | P3: E | Q3: E
E4: FY22 | F4: FY23 | G4: FY24 | H4: FY25 | I4: FY26 | J4: FY27 | K4: FY28 | L4: FY29 | M4: FY30 | N4: FY31 | O4: FY32 | P4: FY33 | Q4: FY34
C6: Units | E6: =E4&E3 -> FY22A | F6: =F4&F3 -> FY23A | G6: =G4&G3 -> FY24A | H6: =H4&H3 -> FY25A | I6: =I4&I3 -> FY26A | J6: =J4&J3 -> FY27E | K6: =K4&K3 -> FY28E | L6: =L4&L3 -> FY29E | ... Q6: =Q4&Q3 -> FY34E
E7: 44742 | F7: =EOMONTH(E7,12) -> 45107 | G7: =EOMONTH(F7,12) -> 45473 | H7: =EOMONTH(G7,12) -> 45838 | I7: =EOMONTH(H7,12) -> 46203 | J7: =EOMONTH(I7,12) -> 46568 | K7: =EOMONTH(J7,12) -> 46934 | L7: =EOMONTH(K7,12) -> 47299 | M7: =EOMONTH(L7,12) -> 47664 | ... Q7: =EOMONTH(P7,12) -> 49125
A9: X | B9: AUSTRALIAN WAGERING
B11: KPI's
B12: Turnover | G12: =SUMIFS(HY!64:64,HY!$14:$14,FY!G$4) -> 591.9 | H12: =SUMIFS(HY!64:64,HY!$14:$14,FY!H$4) -> 1420.4 | I12: =SUMIFS(HY!64:64,HY!$14:$14,FY!I$4) -> 1594.7 | J12: =SUMIFS(HY!64:64,HY!$14:$14,FY!J$4) -> 1722.674 | K12: =SUMIFS(HY!64:64,HY!$14:$14,FY!K$4) -> 1808.8077 | L12: =SUMIFS(HY!64:64,HY!$14:$14,FY!L$4) -> 1899.2481 | M12: =SUMIFS(HY!64:64,HY!$14:$14,FY!M$4) -> 1994.2105 | N12: =SUMIFS(HY!64:64,HY!$14:$14,FY!N$4) -> 2093.921 | ... Q12: =SUMIFS(HY!64:64,HY!$14:$14,FY!Q$4) -> 2423.9753
B14: Gross Win | G14: =SUMIFS(HY!68:68,HY!$14:$14,FY!G$4) -> 79.5 | H14: =SUMIFS(HY!68:68,HY!$14:$14,FY!H$4) -> 196.2 | I14: =SUMIFS(HY!68:68,HY!$14:$14,FY!I$4) -> 215.7 | J14: =SUMIFS(HY!68:68,HY!$14:$14,FY!J$4) -> 242.95042 | K14: =SUMIFS(HY!68:68,HY!$14:$14,FY!K$4) -> 255.09794 | L14: =SUMIFS(HY!68:68,HY!$14:$14,FY!L$4) -> 267.85284 | M14: =SUMIFS(HY!68:68,HY!$14:$14,FY!M$4) -> 281.24548 | N14: =SUMIFS(HY!68:68,HY!$14:$14,FY!N$4) -> 295.30775 | ... Q14: =SUMIFS(HY!68:68,HY!$14:$14,FY!Q$4) -> 341.85564
B15: Gross Margin | G15: =G14/G12 -> 0.13431323 | H15: =H14/H12 -> 0.1381301 | I15: =I14/I12 -> 0.13526055 | J15: =J14/J12 -> 0.14103099 | K15: =K14/K12 -> 0.14103099 | L15: =L14/L12 -> 0.14103099 | M15: =M14/M12 -> 0.14103099 | N15: =N14/N12 -> 0.14103099 | ... Q15: =Q14/Q12 -> 0.14103099
B17: Promos | G17: =SUMIFS(HY!71:71,HY!$14:$14,FY!G$4) -> -16.5 | H17: =SUMIFS(HY!71:71,HY!$14:$14,FY!H$4) -> -48.4 | I17: =SUMIFS(HY!71:71,HY!$14:$14,FY!I$4) -> -57.6 | J17: =SUMIFS(HY!71:71,HY!$14:$14,FY!J$4) -> -59.619104 | K17: =SUMIFS(HY!71:71,HY!$14:$14,FY!K$4) -> -62.600059 | L17: =SUMIFS(HY!71:71,HY!$14:$14,FY!L$4) -> -65.730062 | M17: =SUMIFS(HY!71:71,HY!$14:$14,FY!M$4) -> -69.016565 | N17: =SUMIFS(HY!71:71,HY!$14:$14,FY!N$4) -> -72.467394 | ... Q17: =SUMIFS(HY!71:71,HY!$14:$14,FY!Q$4) -> -83.890066
B18: Promo % | G18: =G17/G12 -> -0.02787633 | H18: =H17/H12 -> -0.034074908 | I18: =I17/I12 -> -0.036119646 | J18: =J17/J12 -> -0.034608466 | K18: =K17/K12 -> -0.034608466 | L18: =L17/L12 -> -0.034608466 | M18: =M17/M12 -> -0.034608466 | N18: =N17/N12 -> -0.034608466 | ... Q18: =Q17/Q12 -> -0.034608466
B20: New Win | G20: =SUMIFS(HY!75:75,HY!$14:$14,FY!G$4) -> 63 | H20: =SUMIFS(HY!75:75,HY!$14:$14,FY!H$4) -> 147.8 | I20: =SUMIFS(HY!75:75,HY!$14:$14,FY!I$4) -> 158.1 | J20: =SUMIFS(HY!75:75,HY!$14:$14,FY!J$4) -> 183.33132 | K20: =SUMIFS(HY!75:75,HY!$14:$14,FY!K$4) -> 192.49788 | L20: =SUMIFS(HY!75:75,HY!$14:$14,FY!L$4) -> 202.12278 | M20: =SUMIFS(HY!75:75,HY!$14:$14,FY!M$4) -> 212.22891 | N20: =SUMIFS(HY!75:75,HY!$14:$14,FY!N$4) -> 222.84036 | ... Q20: =SUMIFS(HY!75:75,HY!$14:$14,FY!Q$4) -> 257.96557
B21: Net Margin | G21: =G20/G12 -> 0.1064369 | H21: =H20/H12 -> 0.1040552 | I21: =I20/I12 -> 0.099140904 | J21: =J20/J12 -> 0.10642252 | K21: =K20/K12 -> 0.10642252 | L21: =L20/L12 -> 0.10642252 | M21: =M20/M12 -> 0.10642252 | N21: =N20/N12 -> 0.10642252 | ... Q21: =Q20/Q12 -> 0.10642252
B23: Active Customers | H23: =_xlfn.XLOOKUP(FY!H$7,HY!$8:$8,HY!78:78) -> 155.42 | I23: =_xlfn.XLOOKUP(FY!I$7,HY!$8:$8,HY!78:78) -> 156.479
B25: Growth Rates
B26: Turnover | H26: =H12/G12-1 -> 1.3997297 | I26: =I12/H12-1 -> 0.12271191 | J26: =J12/I12-1 -> 0.080249577 | K26: =K12/J12-1 -> 0.05 | L26: =L12/K12-1 -> 0.05 | M26: =M12/L12-1 -> 0.05 | N26: =N12/M12-1 -> 0.05 | O26: =O12/N12-1 -> 0.05 | ... Q26: =Q12/P12-1 -> 0.05
B27: Gross Win | H27: =H14/G14-1 -> 1.4679245 | I27: =I14/H14-1 -> 0.099388379 | J27: =J14/I14-1 -> 0.12633482 | K27: =K14/J14-1 -> 0.05 | L27: =L14/K14-1 -> 0.05 | M27: =M14/L14-1 -> 0.05 | N27: =N14/M14-1 -> 0.05 | O27: =O14/N14-1 -> 0.05 | ... Q27: =Q14/P14-1 -> 0.05
B28: Promos | H28: =H17/G17-1 -> 1.9333333 | I28: =I17/H17-1 -> 0.19008264 | J28: =J17/I17-1 -> 0.035053889 | K28: =K17/J17-1 -> 0.05 | L28: =L17/K17-1 -> 0.05 | M28: =M17/L17-1 -> 0.05 | N28: =N17/M17-1 -> 0.05 | O28: =O17/N17-1 -> 0.05 | ... Q28: =Q17/P17-1 -> 0.05
B29: New Win | H29: =H20/G20-1 -> 1.3460317 | I29: =I20/H20-1 -> 0.069688769 | J29: =J20/I20-1 -> 0.15959087 | K29: =K20/J20-1 -> 0.05 | L29: =L20/K20-1 -> 0.05 | M29: =M20/L20-1 -> 0.05 | N29: =N20/M20-1 -> 0.05 | O29: =O20/N20-1 -> 0.05 | ... Q29: =Q20/P20-1 -> 0.05
B31: COST OF SALES
B32: POCT | G32: =SUMIFS(HY!197:197,HY!$14:$14,FY!G$4) -> -13.86 | H32: =SUMIFS(HY!197:197,HY!$14:$14,FY!H$4) -> -32.516 | I32: =SUMIFS(HY!197:197,HY!$14:$14,FY!I$4) -> -34.782 | J32: =SUMIFS(HY!197:197,HY!$14:$14,FY!J$4) -> -40.33289 | K32: =SUMIFS(HY!197:197,HY!$14:$14,FY!K$4) -> -42.349534 | L32: =SUMIFS(HY!197:197,HY!$14:$14,FY!L$4) -> -44.467011 | M32: =SUMIFS(HY!197:197,HY!$14:$14,FY!M$4) -> -46.690361 | N32: =SUMIFS(HY!197:197,HY!$14:$14,FY!N$4) -> -49.024879 | ... Q32: =SUMIFS(HY!197:197,HY!$14:$14,FY!Q$4) -> -56.752426
B33: Product Fees | G33: =SUMIFS(HY!198:198,HY!$14:$14,FY!G$4) -> -12.4299 | H33: =SUMIFS(HY!198:198,HY!$14:$14,FY!H$4) -> -29.8284 | I33: =SUMIFS(HY!198:198,HY!$14:$14,FY!I$4) -> -33.4887 | J33: =SUMIFS(HY!198:198,HY!$14:$14,FY!J$4) -> -36.176154 | K33: =SUMIFS(HY!198:198,HY!$14:$14,FY!K$4) -> -37.984962 | L33: =SUMIFS(HY!198:198,HY!$14:$14,FY!L$4) -> -39.88421 | M33: =SUMIFS(HY!198:198,HY!$14:$14,FY!M$4) -> -41.87842 | N33: =SUMIFS(HY!198:198,HY!$14:$14,FY!N$4) -> -43.972341 | ... Q33: =SUMIFS(HY!198:198,HY!$14:$14,FY!Q$4) -> -50.903482
B34: NT Licencing Fees | G34: =SUMIFS(HY!199:199,HY!$14:$14,FY!G$4) -> 0 | H34: =SUMIFS(HY!199:199,HY!$14:$14,FY!H$4) -> -1.4 | I34: =SUMIFS(HY!199:199,HY!$14:$14,FY!I$4) -> -2.9 | J34: =SUMIFS(HY!199:199,HY!$14:$14,FY!J$4) -> -1.5 | K34: =SUMIFS(HY!199:199,HY!$14:$14,FY!K$4) -> -0.6 | L34: =SUMIFS(HY!199:199,HY!$14:$14,FY!L$4) -> -0.618 | M34: =SUMIFS(HY!199:199,HY!$14:$14,FY!M$4) -> -0.63654 | N34: =SUMIFS(HY!199:199,HY!$14:$14,FY!N$4) -> -0.6556362 | ... Q34: =SUMIFS(HY!199:199,HY!$14:$14,FY!Q$4) -> -0.71643138
B35: SkyRacing | G35: =SUMIFS(HY!200:200,HY!$14:$14,FY!G$4) -> 0 | H35: =SUMIFS(HY!200:200,HY!$14:$14,FY!H$4) -> 0 | I35: =SUMIFS(HY!200:200,HY!$14:$14,FY!I$4) -> -5.1496 | J35: =SUMIFS(HY!200:200,HY!$14:$14,FY!J$4) -> -6.890696 | K35: =SUMIFS(HY!200:200,HY!$14:$14,FY!K$4) -> -7.2352308 | L35: =SUMIFS(HY!200:200,HY!$14:$14,FY!L$4) -> -7.5969923 | M35: =SUMIFS(HY!200:200,HY!$14:$14,FY!M$4) -> -7.976842 | N35: =SUMIFS(HY!200:200,HY!$14:$14,FY!N$4) -> -8.3756841 | ... Q35: =SUMIFS(HY!200:200,HY!$14:$14,FY!Q$4) -> -9.6959013
B36: Other | G36: =SUMIFS(HY!201:201,HY!$14:$14,FY!G$4) -> -0.5101 | H36: =SUMIFS(HY!201:201,HY!$14:$14,FY!H$4) -> -10.3556 | I36: =SUMIFS(HY!201:201,HY!$14:$14,FY!I$4) -> -8.5797 | J36: =SUMIFS(HY!201:201,HY!$14:$14,FY!J$4) -> -10.946988 | K36: =SUMIFS(HY!201:201,HY!$14:$14,FY!K$4) -> -11.214608 | L36: =SUMIFS(HY!201:201,HY!$14:$14,FY!L$4) -> -11.775338 | M36: =SUMIFS(HY!201:201,HY!$14:$14,FY!M$4) -> -12.364105 | N36: =SUMIFS(HY!201:201,HY!$14:$14,FY!N$4) -> -12.98231 | ... Q36: =SUMIFS(HY!201:201,HY!$14:$14,FY!Q$4) -> -15.028647
B37: ---------- | G37: ---------- | H37: ---------- | I37: ---------- | J37: ---------- | K37: ---------- | L37: ---------- | M37: ---------- | N37: ---------- | O37: ---------- | P37: ---------- | Q37: ----------
B38: Cost of Sales | G38: =SUMIFS(HY!203:203,HY!$14:$14,FY!G$4) -> -26.8 | H38: =SUMIFS(HY!203:203,HY!$14:$14,FY!H$4) -> -73.4 | I38: =SUMIFS(HY!203:203,HY!$14:$14,FY!I$4) -> -84.9 | J38: =SUMIFS(HY!203:203,HY!$14:$14,FY!J$4) -> -95.846727 | K38: =SUMIFS(HY!203:203,HY!$14:$14,FY!K$4) -> -99.384334 | L38: =SUMIFS(HY!203:203,HY!$14:$14,FY!L$4) -> -104.34155 | M38: =SUMIFS(HY!203:203,HY!$14:$14,FY!M$4) -> -109.54627 | N38: =SUMIFS(HY!203:203,HY!$14:$14,FY!N$4) -> -115.01085 | ... Q38: =SUMIFS(HY!203:203,HY!$14:$14,FY!Q$4) -> -133.09689
B40: Cost of Sales % of Net Win | G40: =G38/G20 -> -0.42539683 | H40: =H38/H20 -> -0.49661705 | I40: =I38/I20 -> -0.5370019 | J40: =J38/J20 -> -0.52280608 | K40: =K38/K20 -> -0.51628794 | L40: =L38/L20 -> -0.51622857 | M40: =M38/M20 -> -0.51617033 | N40: =N38/N20 -> -0.5161132 | ... Q40: =Q38/Q20 -> -0.51594826
B41: Cost of Sales % of Turnover | G41: =G38/G12 -> -0.045277919 | H41: =H38/H12 -> -0.051675584 | I41: =I38/I12 -> -0.053238854 | J41: =J38/J12 -> -0.055638343 | K41: =K38/K12 -> -0.054944666 | L41: =L38/L12 -> -0.054938347 | M41: =M38/M12 -> -0.054932149 | N41: =N38/N12 -> -0.054926069 | ... Q41: =Q38/Q12 -> -0.054908516
B43: OPEX
B44: Employee benefits expense | G44: =SUMIFS(HY!221:221,HY!$14:$14,FY!G$4) -> -10 | H44: =SUMIFS(HY!221:221,HY!$14:$14,FY!H$4) -> -21 | I44: =SUMIFS(HY!221:221,HY!$14:$14,FY!I$4) -> -22.4
B45: Licencing, platform and subscriptions | G45: =SUMIFS(HY!222:222,HY!$14:$14,FY!G$4) -> -3.6 | H45: =SUMIFS(HY!222:222,HY!$14:$14,FY!H$4) -> -3.7 | I45: =SUMIFS(HY!222:222,HY!$14:$14,FY!I$4) -> -5.9
B46: Product & Technology expense | G46: =SUMIFS(HY!223:223,HY!$14:$14,FY!G$4) -> -4 | H46: =SUMIFS(HY!223:223,HY!$14:$14,FY!H$4) -> -5.3 | I46: =SUMIFS(HY!223:223,HY!$14:$14,FY!I$4) -> -5.5
B47: Administration and other expenses | G47: =SUMIFS(HY!224:224,HY!$14:$14,FY!G$4) -> -3 | H47: =SUMIFS(HY!224:224,HY!$14:$14,FY!H$4) -> -5.6 | I47: =SUMIFS(HY!224:224,HY!$14:$14,FY!I$4) -> -6.1
B48: ---------- | G48: ---------- | H48: ---------- | I48: ---------- | J48: ---------- | K48: ---------- | L48: ---------- | M48: ---------- | N48: ---------- | O48: ---------- | P48: ---------- | Q48: ----------
B49: Other Opex | G49: =SUMIFS(HY!226:226,HY!$14:$14,FY!G$4) -> -20.6 | H49: =SUMIFS(HY!226:226,HY!$14:$14,FY!H$4) -> -35.6 | I49: =SUMIFS(HY!226:226,HY!$14:$14,FY!I$4) -> -39.9 | J49: =SUMIFS(HY!226:226,HY!$14:$14,FY!J$4) -> -33.5 | K49: =SUMIFS(HY!226:226,HY!$14:$14,FY!K$4) -> -33.219639 | L49: =SUMIFS(HY!226:226,HY!$14:$14,FY!L$4) -> -32.856353 | M49: =SUMIFS(HY!226:226,HY!$14:$14,FY!M$4) -> -32.895482 | N49: =SUMIFS(HY!226:226,HY!$14:$14,FY!N$4) -> -33.426054 | ... Q49: =SUMIFS(HY!226:226,HY!$14:$14,FY!Q$4) -> -38.694836
B50: Advertising & Marketing expense | G50: =SUMIFS(HY!227:227,HY!$14:$14,FY!G$4) -> -10.5 | H50: =SUMIFS(HY!227:227,HY!$14:$14,FY!H$4) -> -19.5 | I50: =SUMIFS(HY!227:227,HY!$14:$14,FY!I$4) -> -28.2 | J50: =SUMIFS(HY!227:227,HY!$14:$14,FY!J$4) -> -21.5 | K50: =SUMIFS(HY!227:227,HY!$14:$14,FY!K$4) -> -21.5 | L50: =SUMIFS(HY!227:227,HY!$14:$14,FY!L$4) -> -21.7396 | M50: =SUMIFS(HY!227:227,HY!$14:$14,FY!M$4) -> -22.82658 | N50: =SUMIFS(HY!227:227,HY!$14:$14,FY!N$4) -> -23.967909 | ... Q50: =SUMIFS(HY!227:227,HY!$14:$14,FY!Q$4) -> -27.745851
B51: ---------- | G51: ---------- | H51: ---------- | I51: ---------- | J51: ---------- | K51: ---------- | L51: ---------- | M51: ---------- | N51: ---------- | O51: ---------- | P51: ---------- | Q51: ----------
B52: Total Operating Expenses | G52: =SUMIFS(HY!229:229,HY!$14:$14,FY!G$4) -> -31.1 | H52: =SUMIFS(HY!229:229,HY!$14:$14,FY!H$4) -> -55.1 | I52: =SUMIFS(HY!229:229,HY!$14:$14,FY!I$4) -> -68.2 | J52: =SUMIFS(HY!229:229,HY!$14:$14,FY!J$4) -> -55 | K52: =SUMIFS(HY!229:229,HY!$14:$14,FY!K$4) -> -54.719639 | L52: =SUMIFS(HY!229:229,HY!$14:$14,FY!L$4) -> -54.595953 | M52: =SUMIFS(HY!229:229,HY!$14:$14,FY!M$4) -> -55.722062 | N52: =SUMIFS(HY!229:229,HY!$14:$14,FY!N$4) -> -57.393963 | ... Q52: =SUMIFS(HY!229:229,HY!$14:$14,FY!Q$4) -> -66.440687
B54: Other Opex % of Net Win | G54: =G49/G20 -> -0.32698413 | H54: =H49/H20 -> -0.24086604 | I54: =I49/I20 -> -0.25237192 | J54: =J49/J20 -> -0.18272928 | K54: =K49/K20 -> -0.17257145 | L54: =L49/L20 -> -0.16255641 | M54: =M49/M20 -> -0.155 | N54: =N49/N20 -> -0.15 | ... Q54: =Q49/Q20 -> -0.15
B55: Advertising & Marketing Opex % of Net Win | G55: =G50/G20 -> -0.16666667 | H55: =H50/H20 -> -0.13193505 | I55: =I50/I20 -> -0.17836812 | J55: =J50/J20 -> -0.11727402 | K55: =K50/K20 -> -0.11168954 | L55: =L50/L20 -> -0.10755641 | M55: =M50/M20 -> -0.10755641 | N55: =N50/N20 -> -0.10755641 | ... Q55: =Q50/Q20 -> -0.10755641
B56: Total Opex % of Net Win | G56: =G52/G20 -> -0.49365079 | H56: =H52/H20 -> -0.37280108 | I56: =I52/I20 -> -0.43137255 | J56: =J52/J20 -> -0.3000033 | K56: =K52/K20 -> -0.28426099 | L56: =L52/L20 -> -0.27011282 | M56: =M52/M20 -> -0.26255641 | N56: =N52/N20 -> -0.25755641 | ... Q56: =Q52/Q20 -> -0.25755641
A58: X | B58: P&L
B60: NORMALISED P&L
B61: Turnover (gross of GST) | H61: =SUMIFS(HY!105:105,HY!$14:$14,FY!H$4) -> 1420.4 | I61: =SUMIFS(HY!105:105,HY!$14:$14,FY!I$4) -> 1594.7 | J61: =SUMIFS(HY!105:105,HY!$14:$14,FY!J$4) -> 1722.674 | K61: =SUMIFS(HY!105:105,HY!$14:$14,FY!K$4) -> 1808.8077 | L61: =SUMIFS(HY!105:105,HY!$14:$14,FY!L$4) -> 1899.2481 | M61: =SUMIFS(HY!105:105,HY!$14:$14,FY!M$4) -> 1994.2105 | N61: =SUMIFS(HY!105:105,HY!$14:$14,FY!N$4) -> 2093.921 | O61: =SUMIFS(HY!105:105,HY!$14:$14,FY!O$4) -> 2198.6171 | ... Q61: =SUMIFS(HY!105:105,HY!$14:$14,FY!Q$4) -> 2423.9753
B62: Payouts (gross of GST) | H62: =SUMIFS(HY!106:106,HY!$14:$14,FY!H$4) -> -1224.2 | I62: =SUMIFS(HY!106:106,HY!$14:$14,FY!I$4) -> -1379 | J62: =SUMIFS(HY!106:106,HY!$14:$14,FY!J$4) -> -1479.7236 | K62: =SUMIFS(HY!106:106,HY!$14:$14,FY!K$4) -> -1553.7098 | L62: =SUMIFS(HY!106:106,HY!$14:$14,FY!L$4) -> -1631.3952 | M62: =SUMIFS(HY!106:106,HY!$14:$14,FY!M$4) -> -1712.965 | N62: =SUMIFS(HY!106:106,HY!$14:$14,FY!N$4) -> -1798.6133 | O62: =SUMIFS(HY!106:106,HY!$14:$14,FY!O$4) -> -1888.5439 | ... Q62: =SUMIFS(HY!106:106,HY!$14:$14,FY!Q$4) -> -2082.1197
B63: ---------- | H63: -------------- | I63: ---------- | J63: ---------- | K63: ---------- | L63: ---------- | M63: ---------- | N63: ---------- | O63: ---------- | P63: ---------- | Q63: ----------
B64: Gross Revenue | H64: =SUMIFS(HY!108:108,HY!$14:$14,FY!H$4) -> 196.2 | I64: =SUMIFS(HY!108:108,HY!$14:$14,FY!I$4) -> 215.7 | J64: =SUMIFS(HY!108:108,HY!$14:$14,FY!J$4) -> 242.95042 | K64: =SUMIFS(HY!108:108,HY!$14:$14,FY!K$4) -> 255.09794 | L64: =SUMIFS(HY!108:108,HY!$14:$14,FY!L$4) -> 267.85284 | M64: =SUMIFS(HY!108:108,HY!$14:$14,FY!M$4) -> 281.24548 | N64: =SUMIFS(HY!108:108,HY!$14:$14,FY!N$4) -> 295.30775 | O64: =SUMIFS(HY!108:108,HY!$14:$14,FY!O$4) -> 310.07314 | ... Q64: =SUMIFS(HY!108:108,HY!$14:$14,FY!Q$4) -> 341.85564
B65: Promotions given (gross of GST) | H65: =SUMIFS(HY!109:109,HY!$14:$14,FY!H$4) -> -48.4 | I65: =SUMIFS(HY!109:109,HY!$14:$14,FY!I$4) -> -55.8 | J65: =SUMIFS(HY!109:109,HY!$14:$14,FY!J$4) -> -59.619104 | K65: =SUMIFS(HY!109:109,HY!$14:$14,FY!K$4) -> -62.600059 | L65: =SUMIFS(HY!109:109,HY!$14:$14,FY!L$4) -> -65.730062 | M65: =SUMIFS(HY!109:109,HY!$14:$14,FY!M$4) -> -69.016565 | N65: =SUMIFS(HY!109:109,HY!$14:$14,FY!N$4) -> -72.467394 | O65: =SUMIFS(HY!109:109,HY!$14:$14,FY!O$4) -> -76.090763 | ... Q65: =SUMIFS(HY!109:109,HY!$14:$14,FY!Q$4) -> -83.890066
B66: GST | H66: =SUMIFS(HY!110:110,HY!$14:$14,FY!H$4) -> -13.2 | I66: =SUMIFS(HY!110:110,HY!$14:$14,FY!I$4) -> -14.5 | J66: =SUMIFS(HY!110:110,HY!$14:$14,FY!J$4) -> -16.666483 | K66: =SUMIFS(HY!110:110,HY!$14:$14,FY!K$4) -> -17.499807 | L66: =SUMIFS(HY!110:110,HY!$14:$14,FY!L$4) -> -18.374798 | M66: =SUMIFS(HY!110:110,HY!$14:$14,FY!M$4) -> -19.293538 | N66: =SUMIFS(HY!110:110,HY!$14:$14,FY!N$4) -> -20.258215 | O66: =SUMIFS(HY!110:110,HY!$14:$14,FY!O$4) -> -21.271125 | ... Q66: =SUMIFS(HY!110:110,HY!$14:$14,FY!Q$4) -> -23.451416
B67: ---------- | H67: ---------- | I67: ---------- | J67: ---------- | K67: ---------- | L67: ---------- | M67: ---------- | N67: ---------- | O67: ---------- | P67: ---------- | Q67: ----------
B68: Revenue | H68: =SUMIFS(HY!112:112,HY!$14:$14,FY!H$4) -> 134.6 | I68: =SUMIFS(HY!112:112,HY!$14:$14,FY!I$4) -> 145.4 | J68: =SUMIFS(HY!112:112,HY!$14:$14,FY!J$4) -> 166.66483 | K68: =SUMIFS(HY!112:112,HY!$14:$14,FY!K$4) -> 174.99807 | L68: =SUMIFS(HY!112:112,HY!$14:$14,FY!L$4) -> 183.74798 | M68: =SUMIFS(HY!112:112,HY!$14:$14,FY!M$4) -> 192.93538 | N68: =SUMIFS(HY!112:112,HY!$14:$14,FY!N$4) -> 202.58215 | O68: =SUMIFS(HY!112:112,HY!$14:$14,FY!O$4) -> 212.71125 | ... Q68: =SUMIFS(HY!112:112,HY!$14:$14,FY!Q$4) -> 234.51416
B69: Cost of Sales | H69: =SUMIFS(HY!113:113,HY!$14:$14,FY!H$4) -> -73.4 | I69: =SUMIFS(HY!113:113,HY!$14:$14,FY!I$4) -> -84.9 | J69: =SUMIFS(HY!113:113,HY!$14:$14,FY!J$4) -> -95.846727 | K69: =SUMIFS(HY!113:113,HY!$14:$14,FY!K$4) -> -99.384334 | L69: =SUMIFS(HY!113:113,HY!$14:$14,FY!L$4) -> -104.34155 | M69: =SUMIFS(HY!113:113,HY!$14:$14,FY!M$4) -> -109.54627 | N69: =SUMIFS(HY!113:113,HY!$14:$14,FY!N$4) -> -115.01085 | O69: =SUMIFS(HY!113:113,HY!$14:$14,FY!O$4) -> -120.74828 | ... Q69: =SUMIFS(HY!113:113,HY!$14:$14,FY!Q$4) -> -133.09689
B70: ---------- | H70: ---------- | I70: ---------- | J70: ---------- | K70: ---------- | L70: ---------- | M70: ---------- | N70: ---------- | O70: ---------- | P70: ---------- | Q70: ----------
B71: Gross Profit | H71: =SUMIFS(HY!115:115,HY!$14:$14,FY!H$4) -> 61.2 | I71: =SUMIFS(HY!115:115,HY!$14:$14,FY!I$4) -> 60.5 | J71: =SUMIFS(HY!115:115,HY!$14:$14,FY!J$4) -> 70.818105 | K71: =SUMIFS(HY!115:115,HY!$14:$14,FY!K$4) -> 75.61374 | L71: =SUMIFS(HY!115:115,HY!$14:$14,FY!L$4) -> 79.406427 | M71: =SUMIFS(HY!115:115,HY!$14:$14,FY!M$4) -> 83.389108 | N71: =SUMIFS(HY!115:115,HY!$14:$14,FY!N$4) -> 87.571295 | O71: =SUMIFS(HY!115:115,HY!$14:$14,FY!O$4) -> 91.962972 | ... Q71: =SUMIFS(HY!115:115,HY!$14:$14,FY!Q$4) -> 101.41727
B72: Other Income | H72: =SUMIFS(HY!116:116,HY!$14:$14,FY!H$4) -> 1.1 | I72: =SUMIFS(HY!116:116,HY!$14:$14,FY!I$4) -> 0.5 | J72: =SUMIFS(HY!116:116,HY!$14:$14,FY!J$4) -> 0.65358758 | K72: =SUMIFS(HY!116:116,HY!$14:$14,FY!K$4) -> 0.68626696 | L72: =SUMIFS(HY!116:116,HY!$14:$14,FY!L$4) -> 0.72058031 | M72: =SUMIFS(HY!116:116,HY!$14:$14,FY!M$4) -> 0.75660932 | N72: =SUMIFS(HY!116:116,HY!$14:$14,FY!N$4) -> 0.79443979 | O72: =SUMIFS(HY!116:116,HY!$14:$14,FY!O$4) -> 0.83416178 | ... Q72: =SUMIFS(HY!116:116,HY!$14:$14,FY!Q$4) -> 0.91966336
B73: Opex | H73: =SUMIFS(HY!117:117,HY!$14:$14,FY!H$4) -> -55.1 | I73: =SUMIFS(HY!117:117,HY!$14:$14,FY!I$4) -> -68.2 | J73: =SUMIFS(HY!117:117,HY!$14:$14,FY!J$4) -> -55 | K73: =SUMIFS(HY!117:117,HY!$14:$14,FY!K$4) -> -54.719639 | L73: =SUMIFS(HY!117:117,HY!$14:$14,FY!L$4) -> -54.595953 | M73: =SUMIFS(HY!117:117,HY!$14:$14,FY!M$4) -> -55.722062 | N73: =SUMIFS(HY!117:117,HY!$14:$14,FY!N$4) -> -57.393963 | O73: =SUMIFS(HY!117:117,HY!$14:$14,FY!O$4) -> -60.263662 | ... Q73: =SUMIFS(HY!117:117,HY!$14:$14,FY!Q$4) -> -66.440687
B74: ---------- | H74: ---------- | I74: ---------- | J74: ---------- | K74: ---------- | L74: ---------- | M74: ---------- | N74: ---------- | O74: ---------- | P74: ---------- | Q74: ----------
B75: EBITDA | H75: =SUMIFS(HY!119:119,HY!$14:$14,FY!H$4) -> 7.2 | I75: =SUMIFS(HY!119:119,HY!$14:$14,FY!I$4) -> -7.1 | J75: =SUMIFS(HY!119:119,HY!$14:$14,FY!J$4) -> 16.471693 | K75: =SUMIFS(HY!119:119,HY!$14:$14,FY!K$4) -> 21.580368 | L75: =SUMIFS(HY!119:119,HY!$14:$14,FY!L$4) -> 25.531054 | M75: =SUMIFS(HY!119:119,HY!$14:$14,FY!M$4) -> 28.423656 | N75: =SUMIFS(HY!119:119,HY!$14:$14,FY!N$4) -> 30.971771 | O75: =SUMIFS(HY!119:119,HY!$14:$14,FY!O$4) -> 32.533472 | ... Q75: =SUMIFS(HY!119:119,HY!$14:$14,FY!Q$4) -> 35.896246
B76: Depreciation, Amortization and Impairments | H76: =SUMIFS(HY!120:120,HY!$14:$14,FY!H$4) -> -4.1 | I76: =SUMIFS(HY!120:120,HY!$14:$14,FY!I$4) -> -12.9 | J76: =SUMIFS(HY!120:120,HY!$14:$14,FY!J$4) -> -10.169736 | K76: =SUMIFS(HY!120:120,HY!$14:$14,FY!K$4) -> -10.166736 | L76: =SUMIFS(HY!120:120,HY!$14:$14,FY!L$4) -> -10.268736 | M76: =SUMIFS(HY!120:120,HY!$14:$14,FY!M$4) -> -10.405165 | N76: =SUMIFS(HY!120:120,HY!$14:$14,FY!N$4) -> -10.476624 | O76: =SUMIFS(HY!120:120,HY!$14:$14,FY!O$4) -> -10.643918 | ... Q76: =SUMIFS(HY!120:120,HY!$14:$14,FY!Q$4) -> -11.212503
B77: Finance Costs | H77: =SUMIFS(HY!121:121,HY!$14:$14,FY!H$4) -> -2.9 | I77: =SUMIFS(HY!121:121,HY!$14:$14,FY!I$4) -> -0.8 | J77: =SUMIFS(HY!121:121,HY!$14:$14,FY!J$4) -> -1.1315163 | K77: =SUMIFS(HY!121:121,HY!$14:$14,FY!K$4) -> -2.0722527 | L77: =SUMIFS(HY!121:121,HY!$14:$14,FY!L$4) -> -2.9181681 | M77: =SUMIFS(HY!121:121,HY!$14:$14,FY!M$4) -> -2.7145079 | N77: =SUMIFS(HY!121:121,HY!$14:$14,FY!N$4) -> -2.4678319 | O77: =SUMIFS(HY!121:121,HY!$14:$14,FY!O$4) -> -2.1998797 | ... Q77: =SUMIFS(HY!121:121,HY!$14:$14,FY!Q$4) -> -1.5930166
B78: ---------- | H78: ---------- | I78: ---------- | J78: ---------- | K78: ---------- | L78: ---------- | M78: ---------- | N78: ---------- | O78: ---------- | P78: ---------- | Q78: ----------
B79: Profit/(loss) before income tax expense | H79: =SUMIFS(HY!123:123,HY!$14:$14,FY!H$4) -> 0.2 | I79: =SUMIFS(HY!123:123,HY!$14:$14,FY!I$4) -> -20.8 | J79: =SUMIFS(HY!123:123,HY!$14:$14,FY!J$4) -> 5.1704408 | K79: =SUMIFS(HY!123:123,HY!$14:$14,FY!K$4) -> 9.341379 | L79: =SUMIFS(HY!123:123,HY!$14:$14,FY!L$4) -> 12.34415 | M79: =SUMIFS(HY!123:123,HY!$14:$14,FY!M$4) -> 15.303982 | N79: =SUMIFS(HY!123:123,HY!$14:$14,FY!N$4) -> 18.027315 | O79: =SUMIFS(HY!123:123,HY!$14:$14,FY!O$4) -> 19.689674 | ... Q79: =SUMIFS(HY!123:123,HY!$14:$14,FY!Q$4) -> 23.090726
B80: Income tax expense | H80: =SUMIFS(HY!124:124,HY!$14:$14,FY!H$4) -> 4.6 | I80: =SUMIFS(HY!124:124,HY!$14:$14,FY!I$4) -> 0.1 | J80: =SUMIFS(HY!124:124,HY!$14:$14,FY!J$4) -> -1.5511322 | K80: =SUMIFS(HY!124:124,HY!$14:$14,FY!K$4) -> -2.8024137 | L80: =SUMIFS(HY!124:124,HY!$14:$14,FY!L$4) -> -3.7032451 | M80: =SUMIFS(HY!124:124,HY!$14:$14,FY!M$4) -> -4.5911947 | N80: =SUMIFS(HY!124:124,HY!$14:$14,FY!N$4) -> -5.4081945 | O80: =SUMIFS(HY!124:124,HY!$14:$14,FY!O$4) -> -5.9069023 | ... Q80: =SUMIFS(HY!124:124,HY!$14:$14,FY!Q$4) -> -6.9272178
B81: ---------- | H81: ---------- | I81: ---------- | J81: ---------- | K81: ---------- | L81: ---------- | M81: ---------- | N81: ---------- | O81: ---------- | P81: ---------- | Q81: ----------
B82: Profit/(loss) after income tax | H82: =SUMIFS(HY!126:126,HY!$14:$14,FY!H$4) -> 4.8 | I82: =SUMIFS(HY!126:126,HY!$14:$14,FY!I$4) -> -20.7 | J82: =SUMIFS(HY!126:126,HY!$14:$14,FY!J$4) -> 3.6193085 | K82: =SUMIFS(HY!126:126,HY!$14:$14,FY!K$4) -> 6.5389653 | L82: =SUMIFS(HY!126:126,HY!$14:$14,FY!L$4) -> 8.6409052 | M82: =SUMIFS(HY!126:126,HY!$14:$14,FY!M$4) -> 10.712788 | N82: =SUMIFS(HY!126:126,HY!$14:$14,FY!N$4) -> 12.61912 | O82: =SUMIFS(HY!126:126,HY!$14:$14,FY!O$4) -> 13.782772 | ... Q82: =SUMIFS(HY!126:126,HY!$14:$14,FY!Q$4) -> 16.163508
B83: Normalised EPS | H83: =SUMIFS(HY!128:128,HY!$14:$14,FY!H$4) -> 0.79052288 | I83: =SUMIFS(HY!128:128,HY!$14:$14,FY!I$4) -> -1.9692283 | J83: =SUMIFS(HY!128:128,HY!$14:$14,FY!J$4) -> 0.34325694 | K83: =SUMIFS(HY!128:128,HY!$14:$14,FY!K$4) -> 0.61726717 | L83: =SUMIFS(HY!128:128,HY!$14:$14,FY!L$4) -> 0.81110895 | M83: =SUMIFS(HY!128:128,HY!$14:$14,FY!M$4) -> 1.0001776 | N83: =SUMIFS(HY!128:128,HY!$14:$14,FY!N$4) -> 1.171632 | O83: =SUMIFS(HY!128:128,HY!$14:$14,FY!O$4) -> 1.2725968 | ... Q83: =SUMIFS(HY!128:128,HY!$14:$14,FY!Q$4) -> 1.4760831
B85: FOR NOTE
B88: KPI's
B89: Turnover | C89: A$m | H89: =H12 -> 1420.4 | I89: =I12 -> 1594.7 | J89: =J12 -> 1722.674 | K89: =K12 -> 1808.8077 | L89: =L12 -> 1899.2481 | M89: =M12 -> 1994.2105 | N89: =N12 -> 2093.921 | O89: =O12 -> 2198.6171 | ... Q89: =Q12 -> 2423.9753
B90: Net Win | C90: A$m | H90: =H20 -> 147.8 | I90: =I20 -> 158.1 | J90: =J20 -> 183.33132 | K90: =K20 -> 192.49788 | L90: =L20 -> 202.12278 | M90: =M20 -> 212.22891 | N90: =N20 -> 222.84036 | O90: =O20 -> 233.98238 | ... Q90: =Q20 -> 257.96557
B91: Margin | C91: % | H91: =H21 -> 0.1040552 | I91: =I21 -> 0.099140904 | J91: =J21 -> 0.10642252 | K91: =K21 -> 0.10642252 | L91: =L21 -> 0.10642252 | M91: =M21 -> 0.10642252 | N91: =N21 -> 0.10642252 | O91: =O21 -> 0.10642252 | ... Q91: =Q21 -> 0.10642252
B93: Normalised P&L
B94: =B68 -> Revenue | C94: A$m | H94: =H68 -> 134.6 | I94: =I68 -> 145.4 | J94: =J68 -> 166.66483 | K94: =K68 -> 174.99807 | L94: =L68 -> 183.74798 | M94: =M68 -> 192.93538 | N94: =N68 -> 202.58215 | O94: =O68 -> 212.71125 | ... Q94: =Q68 -> 234.51416
B95: =B69 -> Cost of Sales | C95: A$m | H95: =H69 -> -73.4 | I95: =I69 -> -84.9 | J95: =J69 -> -95.846727 | K95: =K69 -> -99.384334 | L95: =L69 -> -104.34155 | M95: =M69 -> -109.54627 | N95: =N69 -> -115.01085 | O95: =O69 -> -120.74828 | ... Q95: =Q69 -> -133.09689
B96: =B70 -> ---------- | C96: ---------- | H96: =H70 -> ---------- | I96: =I70 -> ---------- | J96: =J70 -> ---------- | K96: =K70 -> ---------- | L96: =L70 -> ---------- | M96: =M70 -> ---------- | N96: =N70 -> ---------- | O96: =O70 -> ---------- | ... Q96: =Q70 -> ----------
B97: =B71 -> Gross Profit | C97: A$m | H97: =H71 -> 61.2 | I97: =I71 -> 60.5 | J97: =J71 -> 70.818105 | K97: =K71 -> 75.61374 | L97: =L71 -> 79.406427 | M97: =M71 -> 83.389108 | N97: =N71 -> 87.571295 | O97: =O71 -> 91.962972 | ... Q97: =Q71 -> 101.41727
B98: =B72 -> Other Income | C98: A$m | H98: =H72 -> 1.1 | I98: =I72 -> 0.5 | J98: =J72 -> 0.65358758 | K98: =K72 -> 0.68626696 | L98: =L72 -> 0.72058031 | M98: =M72 -> 0.75660932 | N98: =N72 -> 0.79443979 | O98: =O72 -> 0.83416178 | ... Q98: =Q72 -> 0.91966336
B99: =B73 -> Opex | C99: A$m | H99: =H73 -> -55.1 | I99: =I73 -> -68.2 | J99: =J73 -> -55 | K99: =K73 -> -54.719639 | L99: =L73 -> -54.595953 | M99: =M73 -> -55.722062 | N99: =N73 -> -57.393963 | O99: =O73 -> -60.263662 | ... Q99: =Q73 -> -66.440687
B100: =B74 -> ---------- | C100: ---------- | H100: =H74 -> ---------- | I100: =I74 -> ---------- | J100: =J74 -> ---------- | K100: =K74 -> ---------- | L100: =L74 -> ---------- | M100: =M74 -> ---------- | N100: =N74 -> ---------- | O100: =O74 -> ---------- | ... Q100: =Q74 -> ----------
B101: =B75 -> EBITDA | C101: A$m | H101: =H75 -> 7.2 | I101: =I75 -> -7.1 | J101: =J75 -> 16.471693 | K101: =K75 -> 21.580368 | L101: =L75 -> 25.531054 | M101: =M75 -> 28.423656 | N101: =N75 -> 30.971771 | O101: =O75 -> 32.533472 | ... Q101: =Q75 -> 35.896246
B102: =B76 -> Depreciation, Amortization and Impairments | C102: A$m | H102: =H76 -> -4.1 | I102: =I76 -> -12.9 | J102: =J76 -> -10.169736 | K102: =K76 -> -10.166736 | L102: =L76 -> -10.268736 | M102: =M76 -> -10.405165 | N102: =N76 -> -10.476624 | O102: =O76 -> -10.643918 | ... Q102: =Q76 -> -11.212503
B103: Finance Costs | C103: A$m | H103: =H77 -> -2.9 | I103: =I77 -> -0.8 | J103: =J77 -> -1.1315163 | K103: =K77 -> -2.0722527 | L103: =L77 -> -2.9181681 | M103: =M77 -> -2.7145079 | N103: =N77 -> -2.4678319 | O103: =O77 -> -2.1998797 | ... Q103: =Q77 -> -1.5930166
B104: =B78 -> ---------- | C104: ---------- | H104: =H78 -> ---------- | I104: =I78 -> ---------- | J104: =J78 -> ---------- | K104: =K78 -> ---------- | L104: =L78 -> ---------- | M104: =M78 -> ---------- | N104: =N78 -> ---------- | O104: =O78 -> ---------- | ... Q104: =Q78 -> ----------
B105: =B79 -> Profit/(loss) before income tax expense | C105: A$m | H105: =H79 -> 0.2 | I105: =I79 -> -20.8 | J105: =J79 -> 5.1704408 | K105: =K79 -> 9.341379 | L105: =L79 -> 12.34415 | M105: =M79 -> 15.303982 | N105: =N79 -> 18.027315 | O105: =O79 -> 19.689674 | ... Q105: =Q79 -> 23.090726
B106: =B80 -> Income tax expense | C106: A$m | H106: =H80 -> 4.6 | I106: =I80 -> 0.1 | J106: =J80 -> -1.5511322 | K106: =K80 -> -2.8024137 | L106: =L80 -> -3.7032451 | M106: =M80 -> -4.5911947 | N106: =N80 -> -5.4081945 | O106: =O80 -> -5.9069023 | ... Q106: =Q80 -> -6.9272178
B107: =B81 -> ---------- | C107: ---------- | H107: =H81 -> ---------- | I107: =I81 -> ---------- | J107: =J81 -> ---------- | K107: =K81 -> ---------- | L107: =L81 -> ---------- | M107: =M81 -> ---------- | N107: =N81 -> ---------- | O107: =O81 -> ---------- | ... Q107: =Q81 -> ----------
B108: =B82 -> Profit/(loss) after income tax | C108: A$m | H108: =H82 -> 4.8 | I108: =I82 -> -20.7 | J108: =J82 -> 3.6193085 | K108: =K82 -> 6.5389653 | L108: =L82 -> 8.6409052 | M108: =M82 -> 10.712788 | N108: =N82 -> 12.61912 | O108: =O82 -> 13.782772 | ... Q108: =Q82 -> 16.163508
B109: =B83 -> Normalised EPS | C109: cps | H109: =H83 -> 0.79052288 | I109: =I83 -> -1.9692283 | J109: =J83 -> 0.34325694 | K109: =K83 -> 0.61726717 | L109: =L83 -> 0.81110895 | M109: =M83 -> 1.0001776 | N109: =N83 -> 1.171632 | O109: =O83 -> 1.2725968 | ... Q109: =Q83 -> 1.4760831
B112: P&L - STATUTORY
B113: EBITDA | H113: =SUMIFS(HY!144:144,HY!$14:$14,FY!H$4) -> -7.4 | I113: =SUMIFS(HY!144:144,HY!$14:$14,FY!I$4) -> -24.3 | J113: =SUMIFS(HY!144:144,HY!$14:$14,FY!J$4) -> 7.8145602 | K113: =SUMIFS(HY!144:144,HY!$14:$14,FY!K$4) -> 16.001822 | L113: =SUMIFS(HY!144:144,HY!$14:$14,FY!L$4) -> 23.231109 | M113: =SUMIFS(HY!144:144,HY!$14:$14,FY!M$4) -> 26.120972 | N113: =SUMIFS(HY!144:144,HY!$14:$14,FY!N$4) -> 28.631947 | O113: =SUMIFS(HY!144:144,HY!$14:$14,FY!O$4) -> 30.076657 | ... Q113: =SUMIFS(HY!144:144,HY!$14:$14,FY!Q$4) -> 33.187607
B115: NPAT | H115: =SUMIFS(HY!146:146,HY!$14:$14,FY!H$4) -> -14.8 | I115: =SUMIFS(HY!146:146,HY!$14:$14,FY!I$4) -> -40.6 | J115: =SUMIFS(HY!146:146,HY!$14:$14,FY!J$4) -> -5.0378242 | K115: =SUMIFS(HY!146:146,HY!$14:$14,FY!K$4) -> 0.96041938 | L115: =SUMIFS(HY!146:146,HY!$14:$14,FY!L$4) -> 6.3409605 | M115: =SUMIFS(HY!146:146,HY!$14:$14,FY!M$4) -> 8.4101039 | N115: =SUMIFS(HY!146:146,HY!$14:$14,FY!N$4) -> 10.279297 | O115: =SUMIFS(HY!146:146,HY!$14:$14,FY!O$4) -> 11.325957 | ... Q115: =SUMIFS(HY!146:146,HY!$14:$14,FY!Q$4) -> 13.45487
B116: Discontinued Ops | H116: =SUMIFS(HY!147:147,HY!$14:$14,FY!H$4) -> 8 | I116: =SUMIFS(HY!147:147,HY!$14:$14,FY!I$4) -> 0.05 | J116: =SUMIFS(HY!147:147,HY!$14:$14,FY!J$4) -> 0 | K116: =SUMIFS(HY!147:147,HY!$14:$14,FY!K$4) -> 0 | L116: =SUMIFS(HY!147:147,HY!$14:$14,FY!L$4) -> 0 | M116: =SUMIFS(HY!147:147,HY!$14:$14,FY!M$4) -> 0 | N116: =SUMIFS(HY!147:147,HY!$14:$14,FY!N$4) -> 0 | O116: =SUMIFS(HY!147:147,HY!$14:$14,FY!O$4) -> 0 | ... Q116: =SUMIFS(HY!147:147,HY!$14:$14,FY!Q$4) -> 0
B117: ---------- | H117: ---------- | I117: ---------- | J117: ---------- | K117: ---------- | L117: ---------- | M117: ---------- | N117: ---------- | O117: ---------- | P117: ---------- | Q117: ----------
B118: NPAT attributable to Shareholders | H118: =SUMIFS(HY!149:149,HY!$14:$14,FY!H$4) -> -6.8 | I118: =SUMIFS(HY!149:149,HY!$14:$14,FY!I$4) -> -40.1 | J118: =SUMIFS(HY!149:149,HY!$14:$14,FY!J$4) -> -5.0378242 | K118: =SUMIFS(HY!149:149,HY!$14:$14,FY!K$4) -> 0.96041938 | L118: =SUMIFS(HY!149:149,HY!$14:$14,FY!L$4) -> 6.3409605 | M118: =SUMIFS(HY!149:149,HY!$14:$14,FY!M$4) -> 8.4101039 | N118: =SUMIFS(HY!149:149,HY!$14:$14,FY!N$4) -> 10.279297 | O118: =SUMIFS(HY!149:149,HY!$14:$14,FY!O$4) -> 11.325957 | ... Q118: =SUMIFS(HY!149:149,HY!$14:$14,FY!Q$4) -> 13.45487
B120: FX | H120: =SUMIFS(HY!151:151,HY!$14:$14,FY!H$4) -> 0.2 | I120: =SUMIFS(HY!151:151,HY!$14:$14,FY!I$4) -> -0.7 | J120: =SUMIFS(HY!151:151,HY!$14:$14,FY!J$4) -> 0 | K120: =SUMIFS(HY!151:151,HY!$14:$14,FY!K$4) -> 0 | L120: =SUMIFS(HY!151:151,HY!$14:$14,FY!L$4) -> 0 | M120: =SUMIFS(HY!151:151,HY!$14:$14,FY!M$4) -> 0 | N120: =SUMIFS(HY!151:151,HY!$14:$14,FY!N$4) -> 0 | O120: =SUMIFS(HY!151:151,HY!$14:$14,FY!O$4) -> 0 | ... Q120: =SUMIFS(HY!151:151,HY!$14:$14,FY!Q$4) -> 0
B121: Fair Value gain / loss on Investment | H121: =SUMIFS(HY!152:152,HY!$14:$14,FY!H$4) -> 6.1 | I121: =SUMIFS(HY!152:152,HY!$14:$14,FY!I$4) -> -19 | J121: =SUMIFS(HY!152:152,HY!$14:$14,FY!J$4) -> 0 | K121: =SUMIFS(HY!152:152,HY!$14:$14,FY!K$4) -> 0 | L121: =SUMIFS(HY!152:152,HY!$14:$14,FY!L$4) -> 0 | M121: =SUMIFS(HY!152:152,HY!$14:$14,FY!M$4) -> 0 | N121: =SUMIFS(HY!152:152,HY!$14:$14,FY!N$4) -> 0 | O121: =SUMIFS(HY!152:152,HY!$14:$14,FY!O$4) -> 0 | ... Q121: =SUMIFS(HY!152:152,HY!$14:$14,FY!Q$4) -> 0
B122: ---------- | H122: ---------- | I122: ---------- | J122: ---------- | K122: ---------- | L122: ---------- | M122: ---------- | N122: ---------- | O122: ---------- | P122: ---------- | Q122: ----------
B123: Other comprehensive (loss)/income for the half-year, net of tax | H123: =SUMIFS(HY!154:154,HY!$14:$14,FY!H$4) -> 6.3 | I123: =SUMIFS(HY!154:154,HY!$14:$14,FY!I$4) -> -19.7 | J123: =SUMIFS(HY!154:154,HY!$14:$14,FY!J$4) -> 0 | K123: =SUMIFS(HY!154:154,HY!$14:$14,FY!K$4) -> 0 | L123: =SUMIFS(HY!154:154,HY!$14:$14,FY!L$4) -> 0 | M123: =SUMIFS(HY!154:154,HY!$14:$14,FY!M$4) -> 0 | N123: =SUMIFS(HY!154:154,HY!$14:$14,FY!N$4) -> 0 | O123: =SUMIFS(HY!154:154,HY!$14:$14,FY!O$4) -> 0 | ... Q123: =SUMIFS(HY!154:154,HY!$14:$14,FY!Q$4) -> 0
...

Sheet II

Sheet QTR FT
C2: 4Q26 | AD2: 4Q25A | AE2: ="4Q26A" -> 4Q26A | AG2: 4Q26E | AI2: 1H26 | AL2: NOTES
C4: ="BBT " & $C$2 & " - First Take" -> BBT 4Q26 - First Take
E5: =QTR!M2 -> 1Q24A | F5: =QTR!N2 -> 2Q24A | G5: =QTR!O2 -> 3Q24A | H5: =QTR!P2 -> 4Q24A | I5: =QTR!Q2 -> 1Q25A | J5: =QTR!R2 -> 2Q25A | K5: =QTR!S2 -> 3Q25A | L5: =QTR!T2 -> 4Q25A | ... AB5: =QTR!AJ2 -> 4Q29E | AD5: =AD$2 -> 4Q25A | AE5: =AE$2 -> 4Q26A | AF5: YoY % | AG5: ="E&Pe "&AG$2 -> E&Pe 4Q26E | AH5: % diff | AI5: ="VA Cons. "&AG$2 -> VA Cons. 4Q26E | AJ5: % diff | AR5: 1H24 | AS5: 2H24 | AT5: 1H25 | AU5: 2H25 | AV5: 1H26 | AW5: 2H26 | AX5: 1H27 | AY5: 2H27 | AZ5: 1H28 | BA5: 2H28 | BB5: 1H29 | BC5: 2H29 | BD5: 1H30 | BE5: 2H30 | BF5: 1H31 | BG5: 2H31 | BH5: 1H32 | BI5: 2H32 | BJ5: 1H33 | BK5: 2H33 | BL5: 1H34 | BM5: 2H34 | BN5: 1H35 | BO5: 2H35 | BQ5: 1H24 | BR5: 2H24 | BS5: 1H25 | BT5: 2H25 | BU5: 1H26 | BV5: 2H26 | BW5: 1H27 | BX5: 2H27 | BY5: 1H28 | BZ5: 2H28 | CA5: 1H29 | CB5: 2H29 | CC5: 1H30 | CD5: 2H30 | CE5: 1H31 | CF5: 2H31 | CG5: 1H32 | CH5: 2H32 | CI5: 1H33 | CJ5: 2H33 | CK5: 1H34 | CL5: 2H34 | CM5: 1H35 | CN5: 2H35 | CP5: 1H24 | CQ5: 2H24 | CR5: 1H25 | CS5: 2H25 | CT5: 1H26 | CU5: 2H26 | CV5: 1H27 | CW5: 2H27 | CX5: 1H28 | CY5: 2H28 | CZ5: 1H29 | DA5: 2H29 | DB5: 1H30 | DC5: 2H30 | DD5: 1H31 | DE5: 2H31 | DF5: 1H32 | DG5: 2H32 | DH5: 1H33 | DI5: 2H33 | DJ5: 1H34 | DK5: 2H34 | DL5: 1H35 | DM5: 2H35
C6: Wagering KPI's
C7: Turnover | E7: =QTR!M29 -> 143.9 | F7: =QTR!N29 -> 154.8 | G7: =QTR!O29 -> 139.2 | H7: =QTR!P29 -> 153.6 | I7: =QTR!Q29 -> 286.6 | J7: =QTR!R29 -> 357 | K7: =QTR!S29 -> 376 | L7: =QTR!T29 -> 399.5 | ... AB7: =QTR!AJ29 -> 0 | AD7: =_xlfn.SINGLE(_xlfn.XLOOKUP(AD$2,$E$5:$AB$5,$E7:$AB7)) -> 399.5 | AE7: 404.3 | AF7: =AE7/AD7-1 -> 0.012015019 | AG7: =_xlfn.XLOOKUP(AG$2,$E$5:$AB$5,$E7:$AB7) -> 404.3 | AH7: =$AE7/AG7-1 -> 0
C8: Gross Win | E8: =QTR!M35 -> 18.8 | F8: =QTR!N35 -> 21.2 | G8: =QTR!O35 -> 18.6 | H8: =QTR!P35 -> 20.8 | I8: =QTR!Q35 -> 38.8 | J8: =QTR!R35 -> 52.2 | K8: =QTR!S35 -> 51.7 | L8: =QTR!T35 -> 53.1 | ... AB8: =QTR!AJ35 -> 0 | AD8: =_xlfn.SINGLE(_xlfn.XLOOKUP(AD$2,$E$5:$AB$5,$E8:$AB8)) -> 53.1 | AE8: 57.1 | AF8: =AE8/AD8-1 -> 0.075329567 | AG8: =_xlfn.XLOOKUP(AG$2,$E$5:$AB$5,$E8:$AB8) -> 57.1 | AH8: =$AE8/AG8-1 -> 0
C9: Gross Win Margin | E9: =E8/E7 -> 0.13064628 | F9: =F8/F7 -> 0.1369509 | G9: =G8/G7 -> 0.13362069 | H9: =H8/H7 -> 0.13541667 | I9: =I8/I7 -> 0.13538032 | J9: =J8/J7 -> 0.14621849 | K9: =K8/K7 -> 0.1375 | L9: =L8/L7 -> 0.13291615 | ... AB9: =AB8/AB7 -> #DIV/0! | AD9: =_xlfn.XLOOKUP(AD$2,$E$5:$AB$5,$E9:$AB9) -> 0.13291615 | AE9: =AE8/AE7 -> 0.14123176 | AF9: =(AE9-AD9)*100 -> 0.83156134 | AG9: =_xlfn.XLOOKUP(AG$2,$E$5:$AB$5,$E9:$AB9) -> 0.14123176 | AH9: =($AE9-AG9)*100 -> 0 | AI9: =_xlfn.XLOOKUP(AI$2,$BQ$5:$CN$5,$BQ9:$CN9) -> 0.48739496 | AJ9: =($AE9-AI9)*100 -> -34.61632 | AR9: =#REF!/AR3 -> #REF! | AS9: =#REF!/AS3 -> #REF! | AT9: =#REF!/AT3 -> #REF! | AU9: =#REF!/AU3 -> #REF! | AV9: =#REF!/AV3 -> #REF! | AW9: =#REF!/AW3 -> #REF! | AX9: =#REF!/AX3 -> #REF! | AY9: =#REF!/AY3 -> #REF! | ... BO9: =#REF!/BO3 -> #REF! | BQ9: 0.49164678 | BR9: 0.49469214 | BS9: 0.50537634 | BT9: 0.49395161 | BU9: 0.48739496 | BV9: 0.50463822 | BW9: 0.4972067 | BX9: 0.49902913 | BY9: 0.51313131 | BZ9: 0.53030303 | CA9: 0.54659498 | CB9: 0.5242251 | CC9: 0.53169414 | CD9: 0.53410454 | CE9: 0.53407219 | CF9: 0.5316757 | CG9: 0.53400953 | CH9: 0.53835522 | CI9: 0.53872768 | CJ9: 0.53741363 | CK9: 0.53880648 | CL9: 0.542856 | CM9: 0.54355125 | CN9: 0.54088254 | CP9: =E9-BQ9 -> -0.3610005 | CQ9: =F9-BR9 -> -0.35774124 | CR9: =G9-BS9 -> -0.37175565 | CS9: =H9-BT9 -> -0.35853495 | CT9: =I9-BU9 -> -0.35201464 | CU9: =J9-BV9 -> -0.35841973 | CV9: =K9-BW9 -> -0.3597067 | CW9: =L9-BX9 -> -0.36611298 | ... DM9: =AB9-CN9 -> #DIV/0!
C10: Net Win | E10: =QTR!M41 -> 14.5 | F10: =QTR!N41 -> 16.2 | G10: =QTR!O41 -> 15.3 | H10: =QTR!P41 -> 17.3 | I10: =QTR!Q41 -> 27.9 | J10: =QTR!R41 -> 39.2 | K10: =QTR!S41 -> 37.8 | L10: =QTR!T41 -> 40.2 | ... AB10: =QTR!AJ41 -> 0 | AD10: =_xlfn.SINGLE(_xlfn.XLOOKUP(AD$2,$E$5:$AB$5,$E10:$AB10)) -> 40.2 | AE10: 43.9 | AF10: =AE10/AD10-1 -> 0.092039801 | AG10: =_xlfn.XLOOKUP(AG$2,$E$5:$AB$5,$E10:$AB10) -> 43.9 | AH10: =$AE10/AG10-1 -> 0
C11: Net Win Margin | E11: =E10/E7 -> 0.10076442 | F11: =F10/F7 -> 0.10465116 | G11: =G10/G7 -> 0.10991379 | H11: =H10/H7 -> 0.11263021 | I11: =I10/I7 -> 0.097348221 | J11: =J10/J7 -> 0.10980392 | K11: =K10/K7 -> 0.10053191 | L11: =L10/L7 -> 0.10062578 | ... AB11: =AB10/AB7 -> #DIV/0! | AD11: =_xlfn.XLOOKUP(AD$2,$E$5:$AB$5,$E11:$AB11) -> 0.10062578 | AE11: =AE10/AE7 -> 0.10858274 | AF11: =(AE11-AD11)*100 -> 0.79569534 | AG11: =_xlfn.XLOOKUP(AG$2,$E$5:$AB$5,$E11:$AB11) -> 0.10858274 | AH11: =($AE11-AG11)*100 -> 0 | AI11: =_xlfn.XLOOKUP(AI$2,$BQ$5:$CN$5,$BQ11:$CN11) -> 0.48739496 | AJ11: =($AE11-AI11)*100 -> -37.881222 | AR11: =#REF!/AR5 -> #REF! | AS11: =#REF!/AS5 -> #REF! | AT11: =#REF!/AT5 -> #REF! | AU11: =#REF!/AU5 -> #REF! | AV11: =#REF!/AV5 -> #REF! | AW11: =#REF!/AW5 -> #REF! | AX11: =#REF!/AX5 -> #REF! | AY11: =#REF!/AY5 -> #REF! | ... BO11: =#REF!/BO5 -> #REF! | BQ11: 0.49164678 | BR11: 0.49469214 | BS11: 0.50537634 | BT11: 0.49395161 | BU11: 0.48739496 | BV11: 0.50463822 | BW11: 0.4972067 | BX11: 0.49902913 | BY11: 0.51313131 | BZ11: 0.53030303 | CA11: 0.54659498 | CB11: 0.5242251 | CC11: 0.53169414 | CD11: 0.53410454 | CE11: 0.53407219 | CF11: 0.5316757 | CG11: 0.53400953 | CH11: 0.53835522 | CI11: 0.53872768 | CJ11: 0.53741363 | CK11: 0.53880648 | CL11: 0.542856 | CM11: 0.54355125 | CN11: 0.54088254 | CP11: =E11-BQ11 -> -0.39088236 | CQ11: =F11-BR11 -> -0.39004098 | CR11: =G11-BS11 -> -0.39546255 | CS11: =H11-BT11 -> -0.3813214 | CT11: =I11-BU11 -> -0.39004674 | CU11: =J11-BV11 -> -0.3948343 | CV11: =K11-BW11 -> -0.39667479 | CW11: =L11-BX11 -> -0.39840334 | ... DM11: =AB11-CN11 -> #DIV/0!
E13: =E$5 -> 1Q24A | F13: =F$5 -> 2Q24A | G13: =G$5 -> 3Q24A | H13: =H$5 -> 4Q24A | I13: =I$5 -> 1Q25A | J13: =J$5 -> 2Q25A | K13: =K$5 -> 3Q25A | L13: =L$5 -> 4Q25A | ... AB13: =AB$5 -> 4Q29E | AD13: =AD$2 -> 4Q25A | AE13: =AE$2 -> 4Q26A | AF13: YoY % | AG13: ="E&Pe "&AG$2 -> E&Pe 4Q26E | AH13: % diff | AI13: ="VA Cons. "&AG$2 -> VA Cons. 4Q26E | AJ13: % diff | AR13: 1H24 | AS13: 2H24 | AT13: 1H25 | AU13: 2H25 | AV13: 1H26 | AW13: 2H26 | AX13: 1H27 | AY13: 2H27 | AZ13: 1H28 | BA13: 2H28 | BB13: 1H29 | BC13: 2H29 | BD13: 1H30 | BE13: 2H30 | BF13: 1H31 | BG13: 2H31 | BH13: 1H32 | BI13: 2H32 | BJ13: 1H33 | BK13: 2H33 | BL13: 1H34 | BM13: 2H34 | BN13: 1H35 | BO13: 2H35 | BQ13: 1H24 | BR13: 2H24 | BS13: 1H25 | BT13: 2H25 | BU13: 1H26 | BV13: 2H26 | BW13: 1H27 | BX13: 2H27 | BY13: 1H28 | BZ13: 2H28 | CA13: 1H29 | CB13: 2H29 | CC13: 1H30 | CD13: 2H30 | CE13: 1H31 | CF13: 2H31 | CG13: 1H32 | CH13: 2H32 | CI13: 1H33 | CJ13: 2H33 | CK13: 1H34 | CL13: 2H34 | CM13: 1H35 | CN13: 2H35 | CP13: 1H24 | CQ13: 2H24 | CR13: 1H25 | CS13: 2H25 | CT13: 1H26 | CU13: 2H26 | CV13: 1H27 | CW13: 2H27 | CX13: 1H28 | CY13: 2H28 | CZ13: 1H29 | DA13: 2H29 | DB13: 1H30 | DC13: 2H30 | DD13: 1H31 | DE13: 2H31 | DF13: 1H32 | DG13: 2H32 | DH13: 1H33 | DI13: 2H33 | DJ13: 1H34 | DK13: 2H34 | DL13: 1H35 | DM13: 2H35
C14: Costs
C15: Cost of Sales | E15: =QTR!M55 -> 0 | F15: =QTR!N55 -> 0 | G15: =QTR!O55 -> 0 | H15: =QTR!P55 -> 0 | I15: =QTR!Q55 -> -10.6027 | J15: =QTR!R55 -> -19.7536 | K15: =QTR!S55 -> -17.3842 | L15: =QTR!T55 -> -22.2244 | ... AB15: =QTR!AJ55 -> 0 | AD15: =_xlfn.XLOOKUP(AD$2,$E$5:$AB$5,$E15:$AB15) -> -22.2244 | AF15: =AE15/AD15-1 -> -1 | AG15: =_xlfn.XLOOKUP(AG$2,$E$5:$AB$5,$E15:$AB15) -> -23.3236 | AH15: =$AE15/AG15-1 -> -1 | AI15: =_xlfn.XLOOKUP(AI$2,$BQ$5:$CN$5,$BQ15:$CN15) -> 0 | AJ15: =$AE15/AI15-1 -> #DIV/0!
C16: Advertising & Marketing | E16: =QTR!M48 -> 0 | F16: =QTR!N48 -> 0 | G16: =QTR!O48 -> 0 | H16: =QTR!P48 -> 0 | I16: =QTR!Q48 -> -2.9 | J16: =QTR!R48 -> -7 | K16: =QTR!S48 -> -3.6 | L16: =QTR!T48 -> -5.5 | ... AB16: =QTR!AJ48 -> 0 | AD16: =_xlfn.XLOOKUP(AD$2,$E$5:$AB$5,$E16:$AB16) -> -5.5 | AF16: =AE16/AD16-1 -> -1 | AG16: =_xlfn.XLOOKUP(AG$2,$E$5:$AB$5,$E16:$AB16) -> -4.0542 | AH16: =$AE16/AG16-1 -> -1 | AI16: =_xlfn.XLOOKUP(AI$2,$BQ$5:$CN$5,$BQ16:$CN16) -> 0 | AJ16: =$AE16/AI16-1 -> #DIV/0!
C18: % of Net Win
C19: Cost of Sales | E19: =E15/E$10 -> 0 | F19: =F15/F$10 -> 0 | G19: =G15/G$10 -> 0 | H19: =H15/H$10 -> 0 | I19: =I15/I$10 -> -0.38002509 | J19: =J15/J$10 -> -0.50391837 | K19: =K15/K$10 -> -0.45989947 | L19: =L15/L$10 -> -0.55284577 | ... AB19: =AB15/AB$10 -> #DIV/0! | AD19: =_xlfn.XLOOKUP(AD$2,$E$5:$AB$5,$E19:$AB19) -> -0.55284577 | AE19: =AE15/AE10 -> 0 | AF19: =(AE19-AD19)*100 -> 55.284577 | AG19: =_xlfn.XLOOKUP(AG$2,$E$5:$AB$5,$E19:$AB19) -> -0.53128929 | AH19: =($AE19-AG19)*100 -> 53.128929 | AI19: =_xlfn.XLOOKUP(AI$2,$BQ$5:$CN$5,$BQ19:$CN19) -> 0.48739496 | AJ19: =($AE19-AI19)*100 -> -48.739496 | AR19: =AR14/AR11 -> #REF! | AS19: =AS14/AS11 -> #REF! | AT19: =AT14/AT11 -> #REF! | AU19: =AU14/AU11 -> #REF! | AV19: =AV14/AV11 -> #REF! | AW19: =AW14/AW11 -> #REF! | AX19: =AX14/AX11 -> #REF! | AY19: =AY14/AY11 -> #REF! | ... BO19: =BO14/BO11 -> #REF! | BQ19: 0.49164678 | BR19: 0.49469214 | BS19: 0.50537634 | BT19: 0.49395161 | BU19: 0.48739496 | BV19: 0.50463822 | BW19: 0.4972067 | BX19: 0.49902913 | BY19: 0.51313131 | BZ19: 0.53030303 | CA19: 0.54659498 | CB19: 0.5242251 | CC19: 0.53169414 | CD19: 0.53410454 | CE19: 0.53407219 | CF19: 0.5316757 | CG19: 0.53400953 | CH19: 0.53835522 | CI19: 0.53872768 | CJ19: 0.53741363 | CK19: 0.53880648 | CL19: 0.542856 | CM19: 0.54355125 | CN19: 0.54088254 | CP19: =E19-BQ19 -> -0.49164678 | CQ19: =F19-BR19 -> -0.49469214 | CR19: =G19-BS19 -> -0.50537634 | CS19: =H19-BT19 -> -0.49395161 | CT19: =I19-BU19 -> -0.86742005 | CU19: =J19-BV19 -> -1.0085566 | CV19: =K19-BW19 -> -0.95710617 | CW19: =L19-BX19 -> -1.0518749 | ... DM19: =AB19-CN19 -> #DIV/0!
C20: Advertising & Marketing | E20: =E16/E$10 -> 0 | F20: =F16/F$10 -> 0 | G20: =G16/G$10 -> 0 | H20: =H16/H$10 -> 0 | I20: =I16/I$10 -> -0.10394265 | J20: =J16/J$10 -> -0.17857143 | K20: =K16/K$10 -> -0.095238095 | L20: =L16/L$10 -> -0.13681592 | ... AB20: =AB16/AB$10 -> #DIV/0! | AD20: =_xlfn.XLOOKUP(AD$2,$E$5:$AB$5,$E20:$AB20) -> -0.13681592 | AE20: =AE16/AE10 -> 0 | AF20: =(AE20-AD20)*100 -> 13.681592 | AG20: =_xlfn.XLOOKUP(AG$2,$E$5:$AB$5,$E20:$AB20) -> -0.092350797 | AH20: =($AE20-AG20)*100 -> 9.2350797 | AI20: =_xlfn.XLOOKUP(AI$2,$BQ$5:$CN$5,$BQ20:$CN20) -> 0.48739496 | AJ20: =($AE20-AI20)*100 -> -48.739496 | AR20: =AR15/AR12 -> #DIV/0! | AS20: =AS15/AS12 -> #DIV/0! | AT20: =AT15/AT12 -> #DIV/0! | AU20: =AU15/AU12 -> #DIV/0! | AV20: =AV15/AV12 -> #DIV/0! | AW20: =AW15/AW12 -> #DIV/0! | AX20: =AX15/AX12 -> #DIV/0! | AY20: =AY15/AY12 -> #DIV/0! | ... BO20: =BO15/BO12 -> #DIV/0! | BQ20: 0.49164678 | BR20: 0.49469214 | BS20: 0.50537634 | BT20: 0.49395161 | BU20: 0.48739496 | BV20: 0.50463822 | BW20: 0.4972067 | BX20: 0.49902913 | BY20: 0.51313131 | BZ20: 0.53030303 | CA20: 0.54659498 | CB20: 0.5242251 | CC20: 0.53169414 | CD20: 0.53410454 | CE20: 0.53407219 | CF20: 0.5316757 | CG20: 0.53400953 | CH20: 0.53835522 | CI20: 0.53872768 | CJ20: 0.53741363 | CK20: 0.53880648 | CL20: 0.542856 | CM20: 0.54355125 | CN20: 0.54088254 | CP20: =E20-BQ20 -> -0.49164678 | CQ20: =F20-BR20 -> -0.49469214 | CR20: =G20-BS20 -> -0.50537634 | CS20: =H20-BT20 -> -0.49395161 | CT20: =I20-BU20 -> -0.59133761 | CU20: =J20-BV20 -> -0.68320965 | CV20: =K20-BW20 -> -0.5924448 | CW20: =L20-BX20 -> -0.63584505 | ... DM20: =AB20-CN20 -> #DIV/0!

Sheet HY FT
C2: 1H26 | AD2: 1H25A | AE2: ="1H26A" -> 1H26A | AG2: 1H27E | AI2: 1H27E | AL2: NOTES
C4: ="BBT " & $C$2 & " - First Take" -> BBT 1H26 - First Take
E5: =HY!E7 -> 1H24A | F5: =HY!F7 -> 2H24A | G5: =HY!G7 -> 1H25A | H5: =HY!H7 -> 2H25A | I5: =HY!I7 -> 1H26A | J5: =HY!J7 -> 2H26A | K5: =HY!K7 -> 1H27E | L5: =HY!L7 -> 2H27E | ... AB5: =HY!AB7 -> 2H35E | AD5: =AD$2 -> 1H25A | AE5: =AE$2 -> 1H26A | AF5: YoY % | AG5: ="E&Pe "&AG$2 -> E&Pe 1H27E | AH5: % diff | AI5: ="VA Cons. "&AG$2 -> VA Cons. 1H27E | AJ5: % diff | AR5: 1H24 | AS5: 2H24 | AT5: 1H25 | AU5: 2H25 | AV5: 1H26 | AW5: 2H26 | AX5: 1H27 | AY5: 2H27 | AZ5: 1H28 | BA5: 2H28 | BB5: 1H29 | BC5: 2H29 | BD5: 1H30 | BE5: 2H30 | BF5: 1H31 | BG5: 2H31 | BH5: 1H32 | BI5: 2H32 | BJ5: 1H33 | BK5: 2H33 | BL5: 1H34 | BM5: 2H34 | BN5: 1H35 | BO5: 2H35 | BQ5: 1H24 | BR5: 2H24 | BS5: 1H25 | BT5: 2H25 | BU5: 1H26 | BV5: 2H26 | BW5: 1H27 | BX5: 2H27 | BY5: 1H28 | BZ5: 2H28 | CA5: 1H29 | CB5: 2H29 | CC5: 1H30 | CD5: 2H30 | CE5: 1H31 | CF5: 2H31 | CG5: 1H32 | CH5: 2H32 | CI5: 1H33 | CJ5: 2H33 | CK5: 1H34 | CL5: 2H34 | CM5: 1H35 | CN5: 2H35 | CP5: 1H24 | CQ5: 2H24 | CR5: 1H25 | CS5: 2H25 | CT5: 1H26 | CU5: 2H26 | CV5: 1H27 | CW5: 2H27 | CX5: 1H28 | CY5: 2H28 | CZ5: 1H29 | DA5: 2H29 | DB5: 1H30 | DC5: 2H30 | DD5: 1H31 | DE5: 2H31 | DF5: 1H32 | DG5: 2H32 | DH5: 1H33 | DI5: 2H33 | DJ5: 1H34 | DK5: 2H34 | DL5: 1H35 | DM5: 2H35
C6: P&L - Normalised
C7: Revenue | E7: =HY!E112 -> 27.9 | F7: =HY!F112 -> 29.7 | G7: =HY!G112 -> 63.6 | H7: =HY!H112 -> 71 | I7: =HY!I112 -> 68.9 | J7: =HY!J112 -> 76.5 | K7: =HY!K112 -> 83.9592 | L7: =HY!L112 -> 82.705633 | ... AB7: =HY!AB112 -> 122.19389 | AD7: =_xlfn.XLOOKUP(AD$2,$E$5:$AB$5,$E7:$AB7) -> 63.6 | AF7: =AE7/AD7-1 -> -1 | AG7: =_xlfn.XLOOKUP(AG$2,$E$5:$AB$5,$E7:$AB7) -> 83.9592 | AH7: =$AE7/AG7-1 -> -1 | AI7: =_xlfn.XLOOKUP(AI$2,$BQ$5:$CN$5,$BQ7:$CN7) -> #N/A | AJ7: =$AE7/AI7-1 -> #N/A | AN7: BBT_AU | AO7: Total revenue | AP7: consensus.vaactuals | AR7: =_xll.VAData($AN7,AR$5,$AO7,$AP7) -> #NotAvailable | AS7: =_xll.VAData($AN7,AS$5,$AO7,$AP7) -> #NotAvailable | AT7: =_xll.VAData($AN7,AT$5,$AO7,$AP7) -> #NotAvailable | AU7: =_xll.VAData($AN7,AU$5,$AO7,$AP7) -> #NotAvailable | AV7: =_xll.VAData($AN7,AV$5,$AO7,$AP7) -> #NotAvailable | AW7: =_xll.VAData($AN7,AW$5,$AO7,$AP7) -> #NotAvailable | AX7: =_xll.VAData($AN7,AX$5,$AO7,$AP7) -> #NotAvailable | AY7: =_xll.VAData($AN7,AY$5,$AO7,$AP7) -> #NotAvailable | ... BO7: =_xll.VAData($AN7,BO$5,$AO7,$AP7) -> #NotAvailable | BQ7: 670 | BR7: 731 | BS7: 731 | BT7: 770 | BU7: 756 | BV7: 818 | BW7: 817 | BX7: 797 | BY7: 774 | BZ7: 809 | CA7: 841 | CB7: 905.3682 | CC7: 875.46347 | CD7: 898.12114 | CE7: 908.46086 | CF7: 944.75271 | CG7: 931.68799 | CH7: 950.03303 | CI7: 959.12289 | CJ7: 1007.0197 | CK7: 1002.1748 | CL7: 1019.648 | CM7: 1027.268 | CN7: 1068.7797 | CP7: =E7-BQ7 -> -642.1 | CQ7: =F7-BR7 -> -701.3 | CR7: =G7-BS7 -> -667.4 | CS7: =H7-BT7 -> -699 | CT7: =I7-BU7 -> -687.1 | CU7: =J7-BV7 -> -741.5 | CV7: =K7-BW7 -> -733.0408 | CW7: =L7-BX7 -> -714.29437 | ... DM7: =AB7-CN7 -> -946.58581
C8: AEBITDA | E8: =HY!E119 -> -1.7 | F8: =HY!F119 -> 1.9 | G8: =HY!G119 -> 1.7 | H8: =HY!H119 -> 5.5 | I8: =HY!I119 -> -13.2 | J8: =HY!J119 -> 6.1 | K8: =HY!K119 -> 5.4973804 | L8: =HY!L119 -> 10.974313 | ... AB8: =HY!AB119 -> 20.655618 | AD8: =_xlfn.XLOOKUP(AD$2,$E$5:$AB$5,$E8:$AB8) -> 1.7 | AF8: =AE8/AD8-1 -> -1 | AG8: =_xlfn.XLOOKUP(AG$2,$E$5:$AB$5,$E8:$AB8) -> 5.4973804 | AH8: =$AE8/AG8-1 -> -1 | AI8: =_xlfn.XLOOKUP(AI$2,$BQ$5:$CN$5,$BQ8:$CN8) -> #N/A | AJ8: =$AE8/AI8-1 -> #N/A | AN8: LNW_AU | AO8: EBITDA - operating (incl. equity investments) | AP8: consensus.vaactuals | AR8: =_xll.VAData($AN8,AR$5,$AO8,$AP8) -> 611 | AS8: =_xll.VAData($AN8,AS$5,$AO8,$AP8) -> 633 | AT8: =_xll.VAData($AN8,AT$5,$AO8,$AP8) -> 663 | AU8: =_xll.VAData($AN8,AU$5,$AO8,$AP8) -> 780 | AV8: =_xll.VAData($AN8,AV$5,$AO8,$AP8) -> 710 | AW8: =_xll.VAData($AN8,AW$5,$AO8,$AP8) -> 811.54578 | AX8: =_xll.VAData($AN8,AX$5,$AO8,$AP8) -> 787.47314 | AY8: =_xll.VAData($AN8,AY$5,$AO8,$AP8) -> 871.99966 | ... BO8: =_xll.VAData($AN8,BO$5,$AO8,$AP8) -> 1298.5502 | BQ8: 249 | BR8: 281 | BS8: 286 | BT8: 302 | BU8: 281 | BV8: 330 | BW8: 319 | BX8: 315 | BY8: 311 | BZ8: 352 | CA8: 375 | CB8: 398.4559 | CC8: 375.8389 | CD8: 393.4508 | CE8: 398.89711 | CF8: 420.22789 | CG8: 412.25929 | CH8: 427.15191 | CI8: 430.79264 | CJ8: 458.49148 | CK8: 453.39751 | CL8: 466.6607 | CM8: 470.28873 | CN8: 491.94915 | CP8: =E8-BQ8 -> -250.7 | CQ8: =F8-BR8 -> -279.1 | CR8: =G8-BS8 -> -284.3 | CS8: =H8-BT8 -> -296.5 | CT8: =I8-BU8 -> -294.2 | CU8: =J8-BV8 -> -323.9 | CV8: =K8-BW8 -> -313.50262 | CW8: =L8-BX8 -> -304.02569 | ... DM8: =AB8-CN8 -> -471.29353
C9: NPAT | E9: =HY!E123 -> 0 | F9: =HY!F123 -> 0 | G9: =HY!G123 -> -0.4 | H9: =HY!H123 -> 0.6 | I9: =HY!I123 -> -19 | J9: =HY!J123 -> -1.8 | K9: =HY!K123 -> -0.16466657 | L9: =HY!L123 -> 5.3351073 | ... AB9: =HY!AB123 -> 14.217181 | AD9: =_xlfn.XLOOKUP(AD$2,$E$5:$AB$5,$E9:$AB9) -> -0.4 | AF9: =AE9/AD9-1 -> -1 | AG9: =_xlfn.XLOOKUP(AG$2,$E$5:$AB$5,$E9:$AB9) -> -0.16466657 | AH9: =$AE9/AG9-1 -> -1 | AI9: =_xlfn.XLOOKUP(AI$2,$BQ$5:$CN$5,$BQ9:$CN9) -> #N/A | AJ9: =$AE9/AI9-1 -> #N/A | AN9: LNW_AU | AO9: NPATA - Operating | AP9: consensus.vaactuals | AR9: =_xll.VAData($AN9,AR$5,$AO9,$AP9) -> 235 | AS9: =_xll.VAData($AN9,AS$5,$AO9,$AP9) -> 249 | AT9: =_xll.VAData($AN9,AT$5,$AO9,$AP9) -> 252 | AU9: =_xll.VAData($AN9,AU$5,$AO9,$AP9) -> 315 | AV9: =_xll.VAData($AN9,AV$5,$AO9,$AP9) -> 271 | AW9: =_xll.VAData($AN9,AW$5,$AO9,$AP9) -> 328.9725 | AX9: =_xll.VAData($AN9,AX$5,$AO9,$AP9) -> 321.09662 | AY9: =_xll.VAData($AN9,AY$5,$AO9,$AP9) -> 383.19396 | ... BO9: =_xll.VAData($AN9,BO$5,$AO9,$AP9) -> 686.03927 | BQ9: 86 | BR9: 93 | BS9: 99 | BT9: 109 | BU9: 105 | BV9: 130 | BW9: 122 | BX9: 127 | BY9: 117 | BZ9: 135 | CA9: 153 | CB9: 151.96383 | CC9: 154.71254 | CD9: 160.77721 | CE9: 164.37328 | CF9: 176.85627 | CG9: 173.51213 | CH9: 182.93768 | CI9: 185.36362 | CJ9: 209.74325 | CK9: 205.58916 | CL9: 214.24141 | CM9: 218.22522 | CN9: 232.70408 | CP9: =E9-BQ9 -> -86 | CQ9: =F9-BR9 -> -93 | CR9: =G9-BS9 -> -99.4 | CS9: =H9-BT9 -> -108.4 | CT9: =I9-BU9 -> -124 | CU9: =J9-BV9 -> -131.8 | CV9: =K9-BW9 -> -122.16467 | CW9: =L9-BX9 -> -121.66489 | ... DM9: =AB9-CN9 -> -218.4869
C11: Wagering KPI's
C12: Turnover | E12: =HY!E64 -> 298.8 | F12: =HY!F64 -> 293.1 | G12: =HY!G64 -> 645.1 | H12: =HY!H64 -> 775.3 | I12: =HY!I64 -> 807.3 | J12: =HY!J64 -> 787.4 | K12: =HY!K64 -> 888.03 | L12: =HY!L64 -> 834.644 | ... AB12: =HY!AB64 -> 1233.1493 | AD12: =_xlfn.SINGLE(_xlfn.XLOOKUP(AD$2,$E$5:$AB$5,$E12:$AB12)) -> 645.1 | AF12: =AE12/AD12-1 -> -1 | AG12: =_xlfn.XLOOKUP(AG$2,$E$5:$AB$5,$E12:$AB12) -> 888.03 | AH12: =$AE12/AG12-1 -> -1
C13: Gross Win | E13: =HY!E68 -> 40 | F13: =HY!F68 -> 39.5 | G13: =HY!G68 -> 91.3 | H13: =HY!H68 -> 104.9 | I13: =HY!I68 -> 108.3 | J13: =HY!J68 -> 107.4 | K13: =HY!K68 -> 126.10026 | L13: =HY!L68 -> 116.85016 | ... AB13: =HY!AB68 -> 172.6409 | AD13: =_xlfn.SINGLE(_xlfn.XLOOKUP(AD$2,$E$5:$AB$5,$E13:$AB13)) -> 91.3 | AF13: =AE13/AD13-1 -> -1 | AG13: =_xlfn.XLOOKUP(AG$2,$E$5:$AB$5,$E13:$AB13) -> 126.10026 | AH13: =$AE13/AG13-1 -> -1
C14: Gross Win Margin | E14: =E13/E12 -> 0.13386881 | F14: =F13/F12 -> 0.13476629 | G14: =G13/G12 -> 0.14152845 | H14: =H13/H12 -> 0.13530246 | I14: =I13/I12 -> 0.13415087 | J14: =J13/J12 -> 0.13639827 | K14: =K13/K12 -> 0.142 | L14: =L13/L12 -> 0.14 | ... AB14: =AB13/AB12 -> 0.14 | AD14: =_xlfn.XLOOKUP(AD$2,$E$5:$AB$5,$E14:$AB14) -> 0.14152845 | AF14: =(AE14-AD14)*100 -> -14.152845 | AG14: =_xlfn.XLOOKUP(AG$2,$E$5:$AB$5,$E14:$AB14) -> 0.142 | AH14: =($AE14-AG14)*100 -> -14.2 | AI14: =_xlfn.XLOOKUP(AI$2,$BQ$5:$CN$5,$BQ14:$CN14) -> #N/A | AJ14: =($AE14-AI14)*100 -> #N/A | AR14: =AR8/AR3 -> #DIV/0! | AS14: =AS8/AS3 -> #DIV/0! | AT14: =AT8/AT3 -> #DIV/0! | AU14: =AU8/AU3 -> #DIV/0! | AV14: =AV8/AV3 -> #DIV/0! | AW14: =AW8/AW3 -> #DIV/0! | AX14: =AX8/AX3 -> #DIV/0! | AY14: =AY8/AY3 -> #DIV/0! | ... BO14: =BO8/BO3 -> #DIV/0! | BQ14: 0.49164678 | BR14: 0.49469214 | BS14: 0.50537634 | BT14: 0.49395161 | BU14: 0.48739496 | BV14: 0.50463822 | BW14: 0.4972067 | BX14: 0.49902913 | BY14: 0.51313131 | BZ14: 0.53030303 | CA14: 0.54659498 | CB14: 0.5242251 | CC14: 0.53169414 | CD14: 0.53410454 | CE14: 0.53407219 | CF14: 0.5316757 | CG14: 0.53400953 | CH14: 0.53835522 | CI14: 0.53872768 | CJ14: 0.53741363 | CK14: 0.53880648 | CL14: 0.542856 | CM14: 0.54355125 | CN14: 0.54088254 | CP14: =E14-BQ14 -> -0.35777797 | CQ14: =F14-BR14 -> -0.35992585 | CR14: =G14-BS14 -> -0.3638479 | CS14: =H14-BT14 -> -0.35864915 | CT14: =I14-BU14 -> -0.35324408 | CU14: =J14-BV14 -> -0.36823995 | CV14: =K14-BW14 -> -0.3552067 | CW14: =L14-BX14 -> -0.35902913 | ... DM14: =AB14-CN14 -> -0.40088254
C15: Net Win | E15: =HY!E75 -> 30.7 | F15: =HY!F75 -> 32.3 | G15: =HY!G75 -> 67.4 | H15: =HY!H75 -> 80.4 | I15: =HY!I75 -> 75.8 | J15: =HY!J75 -> 82.3 | K15: =HY!K75 -> 92.35512 | L15: =HY!L75 -> 90.976196 | ... AB15: =HY!AB75 -> 134.41328 | AD15: =_xlfn.SINGLE(_xlfn.XLOOKUP(AD$2,$E$5:$AB$5,$E15:$AB15)) -> 67.4 | AF15: =AE15/AD15-1 -> -1 | AG15: =_xlfn.XLOOKUP(AG$2,$E$5:$AB$5,$E15:$AB15) -> 92.35512 | AH15: =$AE15/AG15-1 -> -1
C16: Net Win Margin | E16: =E15/E12 -> 0.10274431 | F16: =F15/F12 -> 0.1102013 | G16: =G15/G12 -> 0.10447993 | H16: =H15/H12 -> 0.10370179 | I16: =I15/I12 -> 0.093893224 | J16: =J15/J12 -> 0.10452121 | K16: =K15/K12 -> 0.104 | L16: =L15/L12 -> 0.109 | ... AB16: =AB15/AB12 -> 0.109 | AD16: =_xlfn.XLOOKUP(AD$2,$E$5:$AB$5,$E16:$AB16) -> 0.10447993 | AF16: =(AE16-AD16)*100 -> -10.447993 | AG16: =_xlfn.XLOOKUP(AG$2,$E$5:$AB$5,$E16:$AB16) -> 0.104 | AH16: =($AE16-AG16)*100 -> -10.4 | AI16: =_xlfn.XLOOKUP(AI$2,$BQ$5:$CN$5,$BQ16:$CN16) -> #N/A | AJ16: =($AE16-AI16)*100 -> #N/A | AR16: =AR10/AR5 -> #VALUE! | AS16: =AS10/AS5 -> #VALUE! | AT16: =AT10/AT5 -> #VALUE! | AU16: =AU10/AU5 -> #VALUE! | AV16: =AV10/AV5 -> #VALUE! | AW16: =AW10/AW5 -> #VALUE! | AX16: =AX10/AX5 -> #VALUE! | AY16: =AY10/AY5 -> #VALUE! | ... BO16: =BO10/BO5 -> #VALUE! | BQ16: 0.49164678 | BR16: 0.49469214 | BS16: 0.50537634 | BT16: 0.49395161 | BU16: 0.48739496 | BV16: 0.50463822 | BW16: 0.4972067 | BX16: 0.49902913 | BY16: 0.51313131 | BZ16: 0.53030303 | CA16: 0.54659498 | CB16: 0.5242251 | CC16: 0.53169414 | CD16: 0.53410454 | CE16: 0.53407219 | CF16: 0.5316757 | CG16: 0.53400953 | CH16: 0.53835522 | CI16: 0.53872768 | CJ16: 0.53741363 | CK16: 0.53880648 | CL16: 0.542856 | CM16: 0.54355125 | CN16: 0.54088254 | CP16: =E16-BQ16 -> -0.38890247 | CQ16: =F16-BR16 -> -0.38449085 | CR16: =G16-BS16 -> -0.40089642 | CS16: =H16-BT16 -> -0.39024982 | CT16: =I16-BU16 -> -0.39350173 | CU16: =J16-BV16 -> -0.40011701 | CV16: =K16-BW16 -> -0.3932067 | CW16: =L16-BX16 -> -0.39002913 | ... DM16: =AB16-CN16 -> -0.43188254
E20: =E$5 -> 1H24A | F20: =F$5 -> 2H24A | G20: =G$5 -> 1H25A | H20: =H$5 -> 2H25A | I20: =I$5 -> 1H26A | J20: =J$5 -> 2H26A | K20: =K$5 -> 1H27E | L20: =L$5 -> 2H27E | ... AB20: =AB$5 -> 2H35E | AD20: =AD$2 -> 1H25A | AE20: =AE$2 -> 1H26A | AF20: YoY % | AG20: ="E&Pe "&AG$2 -> E&Pe 1H27E | AH20: % diff | AI20: ="VA Cons. "&AG$2 -> VA Cons. 1H27E | AJ20: % diff | AR20: 1H24 | AS20: 2H24 | AT20: 1H25 | AU20: 2H25 | AV20: 1H26 | AW20: 2H26 | AX20: 1H27 | AY20: 2H27 | AZ20: 1H28 | BA20: 2H28 | BB20: 1H29 | BC20: 2H29 | BD20: 1H30 | BE20: 2H30 | BF20: 1H31 | BG20: 2H31 | BH20: 1H32 | BI20: 2H32 | BJ20: 1H33 | BK20: 2H33 | BL20: 1H34 | BM20: 2H34 | BN20: 1H35 | BO20: 2H35 | BQ20: 1H24 | BR20: 2H24 | BS20: 1H25 | BT20: 2H25 | BU20: 1H26 | BV20: 2H26 | BW20: 1H27 | BX20: 2H27 | BY20: 1H28 | BZ20: 2H28 | CA20: 1H29 | CB20: 2H29 | CC20: 1H30 | CD20: 2H30 | CE20: 1H31 | CF20: 2H31 | CG20: 1H32 | CH20: 2H32 | CI20: 1H33 | CJ20: 2H33 | CK20: 1H34 | CL20: 2H34 | CM20: 1H35 | CN20: 2H35 | CP20: 1H24 | CQ20: 2H24 | CR20: 1H25 | CS20: 2H25 | CT20: 1H26 | CU20: 2H26 | CV20: 1H27 | CW20: 2H27 | CX20: 1H28 | CY20: 2H28 | CZ20: 1H29 | DA20: 2H29 | DB20: 1H30 | DC20: 2H30 | DD20: 1H31 | DE20: 2H31 | DF20: 1H32 | DG20: 2H32 | DH20: 1H33 | DI20: 2H33 | DJ20: 1H34 | DK20: 2H34 | DL20: 1H35 | DM20: 2H35
C21: Costs
C22: Cost of Sales | E22: =HY!E203 -> -12.8 | F22: =HY!F203 -> -14 | G22: =HY!G203 -> -33.7 | H22: =HY!H203 -> -39.7 | I22: =HY!I203 -> -43 | J22: =HY!J203 -> -41.9 | K22: =HY!K203 -> -49.291071 | L22: =HY!L203 -> -46.555656 | ... AB22: =HY!AB203 -> -68.414142 | AD22: =_xlfn.XLOOKUP(AD$2,$E$5:$AB$5,$E22:$AB22) -> -33.7 | AF22: =AE22/AD22-1 -> -1 | AG22: =_xlfn.XLOOKUP(AG$2,$E$5:$AB$5,$E22:$AB22) -> -49.291071 | AH22: =$AE22/AG22-1 -> -1 | AI22: =_xlfn.XLOOKUP(AI$2,$BQ$5:$CN$5,$BQ22:$CN22) -> #N/A | AJ22: =$AE22/AI22-1 -> #N/A
C23: Advertising & Marketing | E23: =HY!E217 -> -6.7 | F23: =HY!F217 -> -3.8 | G23: =HY!G217 -> -9.9 | H23: =HY!H217 -> -9.6 | I23: =HY!I217 -> -17.1 | J23: =HY!J217 -> -11.1 | K23: =HY!K217 -> -12 | L23: =HY!L217 -> -9.5 | ... AB23: =HY!AB217 -> -13.441328 | AD23: =_xlfn.XLOOKUP(AD$2,$E$5:$AB$5,$E23:$AB23) -> -9.9 | AF23: =AE23/AD23-1 -> -1 | AG23: =_xlfn.XLOOKUP(AG$2,$E$5:$AB$5,$E23:$AB23) -> -12 | AH23: =$AE23/AG23-1 -> -1 | AI23: =_xlfn.XLOOKUP(AI$2,$BQ$5:$CN$5,$BQ23:$CN23) -> #N/A | AJ23: =$AE23/AI23-1 -> #N/A
C24: Other Opex | E24: =HY!E226 -> -10.1 | F24: =HY!F226 -> -10.5 | G24: =HY!G226 -> -18.7 | H24: =HY!H226 -> -16.9 | I24: =HY!I226 -> -22.2 | J24: =HY!J226 -> -17.7 | K24: =HY!K226 -> -17.5 | L24: =HY!L226 -> -16 | ... AB24: =HY!AB226 -> -20.161991 | AD24: =_xlfn.XLOOKUP(AD$2,$E$5:$AB$5,$E24:$AB24) -> -18.7 | AF24: =AE24/AD24-1 -> -1 | AG24: =_xlfn.XLOOKUP(AG$2,$E$5:$AB$5,$E24:$AB24) -> -17.5 | AH24: =$AE24/AG24-1 -> -1 | AI24: =_xlfn.XLOOKUP(AI$2,$BQ$5:$CN$5,$BQ24:$CN24) -> #N/A | AJ24: =$AE24/AI24-1 -> #N/A
C26: Costs % of Net Win
C27: Cost of Sales | E27: =E22/E$15 -> -0.41693811 | F27: =F22/F$15 -> -0.43343653 | G27: =G22/G$15 -> -0.5 | H27: =H22/H$15 -> -0.49378109 | I27: =I22/I$15 -> -0.56728232 | J27: =J22/J$15 -> -0.509113 | K27: =K22/K$15 -> -0.53371239 | L27: =L22/L$15 -> -0.51173448 | ... AB27: =AB22/AB$15 -> -0.50898352 | AD27: =_xlfn.XLOOKUP(AD$2,$E$5:$AB$5,$E27:$AB27) -> -0.5 | AF27: =(AE27-AD27)*100 -> 50 | AG27: =_xlfn.XLOOKUP(AG$2,$E$5:$AB$5,$E27:$AB27) -> -0.53371239 | AH27: =($AE27-AG27)*100 -> 53.371239 | AI27: =_xlfn.XLOOKUP(AI$2,$BQ$5:$CN$5,$BQ27:$CN27) -> #N/A | AJ27: =($AE27-AI27)*100 -> #N/A | AR27: =AR21/AR16 -> #VALUE! | AS27: =AS21/AS16 -> #VALUE! | AT27: =AT21/AT16 -> #VALUE! | AU27: =AU21/AU16 -> #VALUE! | AV27: =AV21/AV16 -> #VALUE! | AW27: =AW21/AW16 -> #VALUE! | AX27: =AX21/AX16 -> #VALUE! | AY27: =AY21/AY16 -> #VALUE! | ... BO27: =BO21/BO16 -> #VALUE! | BQ27: 0.49164678 | BR27: 0.49469214 | BS27: 0.50537634 | BT27: 0.49395161 | BU27: 0.48739496 | BV27: 0.50463822 | BW27: 0.4972067 | BX27: 0.49902913 | BY27: 0.51313131 | BZ27: 0.53030303 | CA27: 0.54659498 | CB27: 0.5242251 | CC27: 0.53169414 | CD27: 0.53410454 | CE27: 0.53407219 | CF27: 0.5316757 | CG27: 0.53400953 | CH27: 0.53835522 | CI27: 0.53872768 | CJ27: 0.53741363 | CK27: 0.53880648 | CL27: 0.542856 | CM27: 0.54355125 | CN27: 0.54088254 | CP27: =E27-BQ27 -> -0.90858489 | CQ27: =F27-BR27 -> -0.92812868 | CR27: =G27-BS27 -> -1.0053763 | CS27: =H27-BT27 -> -0.98773271 | CT27: =I27-BU27 -> -1.0546773 | CU27: =J27-BV27 -> -1.0137512 | CV27: =K27-BW27 -> -1.0309191 | CW27: =L27-BX27 -> -1.0107636 | ... DM27: =AB27-CN27 -> -1.0498661
C28: Advertising & Marketing | E28: =E23/E$15 -> -0.21824104 | F28: =F23/F$15 -> -0.11764706 | G28: =G23/G$15 -> -0.14688427 | H28: =H23/H$15 -> -0.11940299 | I28: =I23/I$15 -> -0.22559367 | J28: =J23/J$15 -> -0.13487242 | K28: =K23/K$15 -> -0.12993324 | L28: =L23/L$15 -> -0.10442292 | ... AB28: =AB23/AB$15 -> -0.1 | AD28: =_xlfn.XLOOKUP(AD$2,$E$5:$AB$5,$E28:$AB28) -> -0.14688427 | AF28: =(AE28-AD28)*100 -> 14.688427 | AG28: =_xlfn.XLOOKUP(AG$2,$E$5:$AB$5,$E28:$AB28) -> -0.12993324 | AH28: =($AE28-AG28)*100 -> 12.993324 | AI28: =_xlfn.XLOOKUP(AI$2,$BQ$5:$CN$5,$BQ28:$CN28) -> #N/A | AJ28: =($AE28-AI28)*100 -> #N/A | AR28: =AR22/AR17 -> #DIV/0! | AS28: =AS22/AS17 -> #DIV/0! | AT28: =AT22/AT17 -> #DIV/0! | AU28: =AU22/AU17 -> #DIV/0! | AV28: =AV22/AV17 -> #DIV/0! | AW28: =AW22/AW17 -> #DIV/0! | AX28: =AX22/AX17 -> #DIV/0! | AY28: =AY22/AY17 -> #DIV/0! | ... BO28: =BO22/BO17 -> #DIV/0! | BQ28: 0.49164678 | BR28: 0.49469214 | BS28: 0.50537634 | BT28: 0.49395161 | BU28: 0.48739496 | BV28: 0.50463822 | BW28: 0.4972067 | BX28: 0.49902913 | BY28: 0.51313131 | BZ28: 0.53030303 | CA28: 0.54659498 | CB28: 0.5242251 | CC28: 0.53169414 | CD28: 0.53410454 | CE28: 0.53407219 | CF28: 0.5316757 | CG28: 0.53400953 | CH28: 0.53835522 | CI28: 0.53872768 | CJ28: 0.53741363 | CK28: 0.53880648 | CL28: 0.542856 | CM28: 0.54355125 | CN28: 0.54088254 | CP28: =E28-BQ28 -> -0.70988782 | CQ28: =F28-BR28 -> -0.6123392 | CR28: =G28-BS28 -> -0.65226062 | CS28: =H28-BT28 -> -0.6133546 | CT28: =I28-BU28 -> -0.71298863 | CU28: =J28-BV28 -> -0.63951064 | CV28: =K28-BW28 -> -0.62713994 | CW28: =L28-BX28 -> -0.60345205 | ... DM28: =AB28-CN28 -> -0.64088254
C29: Other Opex | E29: =E24/E$15 -> -0.32899023 | F29: =F24/F$15 -> -0.3250774 | G29: =G24/G$15 -> -0.27744807 | H29: =H24/H$15 -> -0.210199 | I29: =I24/I$15 -> -0.29287599 | J29: =J24/J$15 -> -0.21506683 | K29: =K24/K$15 -> -0.18948598 | L29: =L24/L$15 -> -0.17587018 | ... AB29: =AB24/AB$15 -> -0.15 | AD29: =_xlfn.XLOOKUP(AD$2,$E$5:$AB$5,$E29:$AB29) -> -0.27744807 | AF29: =(AE29-AD29)*100 -> 27.744807 | AG29: =_xlfn.XLOOKUP(AG$2,$E$5:$AB$5,$E29:$AB29) -> -0.18948598 | AH29: =($AE29-AG29)*100 -> 18.948598 | AI29: =_xlfn.XLOOKUP(AI$2,$BQ$5:$CN$5,$BQ29:$CN29) -> #N/A | AJ29: =($AE29-AI29)*100 -> #N/A | AR29: =AR23/AR18 -> #DIV/0! | AS29: =AS23/AS18 -> #DIV/0! | AT29: =AT23/AT18 -> #DIV/0! | AU29: =AU23/AU18 -> #DIV/0! | AV29: =AV23/AV18 -> #DIV/0! | AW29: =AW23/AW18 -> #DIV/0! | AX29: =AX23/AX18 -> #DIV/0! | AY29: =AY23/AY18 -> #DIV/0! | ... BO29: =BO23/BO18 -> #DIV/0! | BQ29: 0.49164678 | BR29: 0.49469214 | BS29: 0.50537634 | BT29: 0.49395161 | BU29: 0.48739496 | BV29: 0.50463822 | BW29: 0.4972067 | BX29: 0.49902913 | BY29: 0.51313131 | BZ29: 0.53030303 | CA29: 0.54659498 | CB29: 0.5242251 | CC29: 0.53169414 | CD29: 0.53410454 | CE29: 0.53407219 | CF29: 0.5316757 | CG29: 0.53400953 | CH29: 0.53835522 | CI29: 0.53872768 | CJ29: 0.53741363 | CK29: 0.53880648 | CL29: 0.542856 | CM29: 0.54355125 | CN29: 0.54088254 | CP29: =E29-BQ29 -> -0.82063701 | CQ29: =F29-BR29 -> -0.81976954 | CR29: =G29-BS29 -> -0.78282442 | CS29: =H29-BT29 -> -0.70415062 | CT29: =I29-BU29 -> -0.78027095 | CU29: =J29-BV29 -> -0.71970505 | CV29: =K29-BW29 -> -0.68669268 | CW29: =L29-BX29 -> -0.67489931 | ... DM29: =AB29-CN29 -> -0.69088254

Sheet FY FT
C2: FY26 | P2: FY25A | Q2: ="FY26A" -> FY26A | S2: FY26E | U2: FY26E | X2: NOTES
C4: ="BBT " & $C$2 & " - First Take" -> BBT FY26 - First Take
E5: =FY!H6 -> FY25A | F5: =FY!I6 -> FY26A | G5: =FY!J6 -> FY27E | H5: =FY!K6 -> FY28E | I5: =FY!L6 -> FY29E | J5: =FY!M6 -> FY30E | K5: =FY!N6 -> FY31E | L5: =FY!O6 -> FY32E | ... N5: =FY!Q6 -> FY34E | P5: =P$2 -> FY25A | Q5: =Q$2 -> FY26A | R5: YoY % | S5: ="E&Pe "&S$2 -> E&Pe FY26E | T5: % diff | U5: ="VA Cons. "&S$2 -> VA Cons. FY26E | V5: % diff | AD5: FY25 | AE5: FY26 | AF5: FY27 | AG5: FY28 | AH5: FY29 | AI5: FY30 | AJ5: FY31 | AK5: FY32 | AL5: FY33 | AM5: FY34 | AO5: FY25 | AP5: FY26 | AQ5: FY27 | AR5: FY28 | AS5: FY29 | AT5: FY30 | AU5: FY31 | AV5: FY32 | AW5: FY33 | AX5: FY34 | AZ5: FY25 | BA5: FY26 | BB5: FY27 | BC5: FY28 | BD5: FY29 | BE5: FY30 | BF5: FY31 | BG5: FY32 | BH5: FY33 | BI5: FY34
C6: P&L - Normalised
C7: Revenue | E7: =FY!H68 -> 134.6 | F7: =FY!I68 -> 145.4 | G7: =FY!J68 -> 166.66483 | H7: =FY!K68 -> 174.99807 | I7: =FY!L68 -> 183.74798 | J7: =FY!M68 -> 192.93538 | K7: =FY!N68 -> 202.58215 | L7: =FY!O68 -> 212.71125 | ... N7: =FY!Q68 -> 234.51416 | P7: =_xlfn.XLOOKUP(P$2,$E$5:$N$5,$E7:$N7) -> 134.6 | Q7: 145.4 | R7: =Q7/P7-1 -> 0.080237741 | S7: =_xlfn.XLOOKUP(S$2,$E$5:$N$5,$E7:$N7) -> #N/A | T7: =$Q7/S7-1 -> #N/A | U7: =_xlfn.XLOOKUP(U$2,$AO$5:$AX$5,$AO7:$AX7) -> #N/A | V7: =$Q7/U7-1 -> #N/A | Z7: BBT_AU | AA7: Total revenue | AB7: consensus.vaactuals | AD7: =_xll.VAData($Z7,AD$5,$AA7,$AB7) -> #NotAvailable | AE7: =_xll.VAData($Z7,AE$5,$AA7,$AB7) -> #NotAvailable | AF7: =_xll.VAData($Z7,AF$5,$AA7,$AB7) -> #NotAvailable | AG7: =_xll.VAData($Z7,AG$5,$AA7,$AB7) -> #NotAvailable | AH7: =_xll.VAData($Z7,AH$5,$AA7,$AB7) -> #NotAvailable | AI7: =_xll.VAData($Z7,AI$5,$AA7,$AB7) -> #NotAvailable | AJ7: =_xll.VAData($Z7,AJ$5,$AA7,$AB7) -> #NotAvailable | AK7: =_xll.VAData($Z7,AK$5,$AA7,$AB7) -> #NotAvailable | ... AM7: =_xll.VAData($Z7,AM$5,$AA7,$AB7) -> #NotAvailable | AO7: 670 | AP7: 731 | AQ7: 731 | AR7: 770 | AS7: 756 | AT7: 818 | AU7: 817 | AV7: 797 | AW7: 774 | AX7: 809 | AZ7: =E7-AO7 -> -535.4 | BA7: =F7-AP7 -> -585.6 | BB7: =G7-AQ7 -> -564.33517 | BC7: =H7-AR7 -> -595.00193 | BD7: =I7-AS7 -> -572.25202 | BE7: =J7-AT7 -> -625.06462 | BF7: =K7-AU7 -> -614.41785 | BG7: =L7-AV7 -> -584.28875 | ... BI7: =N7-AX7 -> -574.48584
C8: AEBITDA | E8: =FY!H75 -> 7.2 | F8: =FY!I75 -> -7.1 | G8: =FY!J75 -> 16.471693 | H8: =FY!K75 -> 21.580368 | I8: =FY!L75 -> 25.531054 | J8: =FY!M75 -> 28.423656 | K8: =FY!N75 -> 30.971771 | L8: =FY!O75 -> 32.533472 | ... N8: =FY!Q75 -> 35.896246 | P8: =_xlfn.XLOOKUP(P$2,$E$5:$N$5,$E8:$N8) -> 7.2 | Q8: -7.1 | R8: =Q8/P8-1 -> -1.9861111 | S8: =_xlfn.XLOOKUP(S$2,$E$5:$N$5,$E8:$N8) -> #N/A | T8: =$Q8/S8-1 -> #N/A | U8: =_xlfn.XLOOKUP(U$2,$AO$5:$AX$5,$AO8:$AX8) -> #N/A | V8: =$Q8/U8-1 -> #N/A | Z8: BBT_AU | AA8: EBITDA - operating (incl. equity investments) | AB8: consensus.vaactuals | AD8: =_xll.VAData($Z8,AD$5,$AA8,$AB8) -> #NotAvailable | AE8: =_xll.VAData($Z8,AE$5,$AA8,$AB8) -> #NotAvailable | AF8: =_xll.VAData($Z8,AF$5,$AA8,$AB8) -> #NotAvailable | AG8: =_xll.VAData($Z8,AG$5,$AA8,$AB8) -> #NotAvailable | AH8: =_xll.VAData($Z8,AH$5,$AA8,$AB8) -> #NotAvailable | AI8: =_xll.VAData($Z8,AI$5,$AA8,$AB8) -> #NotAvailable | AJ8: =_xll.VAData($Z8,AJ$5,$AA8,$AB8) -> #NotAvailable | AK8: =_xll.VAData($Z8,AK$5,$AA8,$AB8) -> #NotAvailable | ... AM8: =_xll.VAData($Z8,AM$5,$AA8,$AB8) -> #NotAvailable | AO8: 249 | AP8: 281 | AQ8: 286 | AR8: 302 | AS8: 281 | AT8: 330 | AU8: 319 | AV8: 315 | AW8: 311 | AX8: 352 | AZ8: =E8-AO8 -> -241.8 | BA8: =F8-AP8 -> -288.1 | BB8: =G8-AQ8 -> -269.52831 | BC8: =H8-AR8 -> -280.41963 | BD8: =I8-AS8 -> -255.46895 | BE8: =J8-AT8 -> -301.57634 | BF8: =K8-AU8 -> -288.02823 | BG8: =L8-AV8 -> -282.46653 | ... BI8: =N8-AX8 -> -316.10375
C9: NPAT | E9: =FY!H82 -> 4.8 | F9: =FY!I82 -> -20.7 | G9: =FY!J82 -> 3.6193085 | H9: =FY!K82 -> 6.5389653 | I9: =FY!L82 -> 8.6409052 | J9: =FY!M82 -> 10.712788 | K9: =FY!N82 -> 12.61912 | L9: =FY!O82 -> 13.782772 | ... N9: =FY!Q82 -> 16.163508 | P9: =_xlfn.XLOOKUP(P$2,$E$5:$N$5,$E9:$N9) -> 4.8 | Q9: -20.7 | R9: =Q9/P9-1 -> -5.3125 | S9: =_xlfn.XLOOKUP(S$2,$E$5:$N$5,$E9:$N9) -> #N/A | T9: =$Q9/S9-1 -> #N/A | U9: =_xlfn.XLOOKUP(U$2,$AO$5:$AX$5,$AO9:$AX9) -> #N/A | V9: =$Q9/U9-1 -> #N/A | Z9: BBT_AU | AA9: NPATA - Operating | AB9: consensus.vaactuals | AD9: =_xll.VAData($Z9,AD$5,$AA9,$AB9) -> #NotAvailable | AE9: =_xll.VAData($Z9,AE$5,$AA9,$AB9) -> #NotAvailable | AF9: =_xll.VAData($Z9,AF$5,$AA9,$AB9) -> #NotAvailable | AG9: =_xll.VAData($Z9,AG$5,$AA9,$AB9) -> #NotAvailable | AH9: =_xll.VAData($Z9,AH$5,$AA9,$AB9) -> #NotAvailable | AI9: =_xll.VAData($Z9,AI$5,$AA9,$AB9) -> #NotAvailable | AJ9: =_xll.VAData($Z9,AJ$5,$AA9,$AB9) -> #NotAvailable | AK9: =_xll.VAData($Z9,AK$5,$AA9,$AB9) -> #NotAvailable | ... AM9: =_xll.VAData($Z9,AM$5,$AA9,$AB9) -> #NotAvailable | AO9: 86 | AP9: 93 | AQ9: 99 | AR9: 109 | AS9: 105 | AT9: 130 | AU9: 122 | AV9: 127 | AW9: 117 | AX9: 135 | AZ9: =E9-AO9 -> -81.2 | BA9: =F9-AP9 -> -113.7 | BB9: =G9-AQ9 -> -95.380691 | BC9: =H9-AR9 -> -102.46103 | BD9: =I9-AS9 -> -96.359095 | BE9: =J9-AT9 -> -119.28721 | BF9: =K9-AU9 -> -109.38088 | BG9: =L9-AV9 -> -113.21723 | ... BI9: =N9-AX9 -> -118.83649
C11: Wagering KPI's
C12: Turnover | E12: =FY!H12 -> 1420.4 | F12: =FY!I12 -> 1594.7 | G12: =FY!J12 -> 1722.674 | H12: =FY!K12 -> 1808.8077 | I12: =FY!L12 -> 1899.2481 | J12: =FY!M12 -> 1994.2105 | K12: =FY!N12 -> 2093.921 | L12: =FY!O12 -> 2198.6171 | ... N12: =FY!Q12 -> 2423.9753 | P12: =_xlfn.SINGLE(_xlfn.XLOOKUP(P$2,$E$5:$N$5,$E12:$N12)) -> 1420.4 | Q12: 1594.7 | R12: =Q12/P12-1 -> 0.12271191 | S12: =_xlfn.XLOOKUP(S$2,$E$5:$N$5,$E12:$N12) -> #N/A | T12: =$Q12/S12-1 -> #N/A
C13: Gross Win | E13: =FY!H14 -> 196.2 | F13: =FY!I14 -> 215.7 | G13: =FY!J14 -> 242.95042 | H13: =FY!K14 -> 255.09794 | I13: =FY!L14 -> 267.85284 | J13: =FY!M14 -> 281.24548 | K13: =FY!N14 -> 295.30775 | L13: =FY!O14 -> 310.07314 | ... N13: =FY!Q14 -> 341.85564 | P13: =_xlfn.SINGLE(_xlfn.XLOOKUP(P$2,$E$5:$N$5,$E13:$N13)) -> 196.2 | Q13: 215.7 | R13: =Q13/P13-1 -> 0.099388379 | S13: =_xlfn.XLOOKUP(S$2,$E$5:$N$5,$E13:$N13) -> #N/A | T13: =$Q13/S13-1 -> #N/A
C14: Gross Win Margin | E14: =E13/E12 -> 0.1381301 | F14: =F13/F12 -> 0.13526055 | G14: =G13/G12 -> 0.14103099 | H14: =H13/H12 -> 0.14103099 | I14: =I13/I12 -> 0.14103099 | J14: =J13/J12 -> 0.14103099 | K14: =K13/K12 -> 0.14103099 | L14: =L13/L12 -> 0.14103099 | ... N14: =N13/N12 -> 0.14103099 | P14: =_xlfn.XLOOKUP(P$2,$E$5:$N$5,$E14:$N14) -> 0.1381301 | Q14: 0.135 | R14: =(Q14-P14)*100 -> -0.31301042 | S14: =_xlfn.XLOOKUP(S$2,$E$5:$N$5,$E14:$N14) -> #N/A | T14: =($Q14-S14)*100 -> #N/A | U14: =_xlfn.XLOOKUP(U$2,$AO$5:$AX$5,$AO14:$AX14) -> #N/A | V14: =($Q14-U14)*100 -> #N/A | AD14: =AD8/AD3 -> #VALUE! | AE14: =AE8/AE3 -> #VALUE! | AF14: =AF8/AF3 -> #VALUE! | AG14: =AG8/AG3 -> #VALUE! | AH14: =AH8/AH3 -> #VALUE! | AI14: =AI8/AI3 -> #VALUE! | AJ14: =AJ8/AJ3 -> #VALUE! | AK14: =AK8/AK3 -> #VALUE! | ... AM14: =AM8/AM3 -> #VALUE! | AO14: 0.49164678 | AP14: 0.49469214 | AQ14: 0.50537634 | AR14: 0.49395161 | AS14: 0.48739496 | AT14: 0.50463822 | AU14: 0.4972067 | AV14: 0.49902913 | AW14: 0.51313131 | AX14: 0.53030303 | AZ14: =E14-AO14 -> -0.35351667 | BA14: =F14-AP14 -> -0.35943159 | BB14: =G14-AQ14 -> -0.36434535 | BC14: =H14-AR14 -> -0.35292062 | BD14: =I14-AS14 -> -0.34636397 | BE14: =J14-AT14 -> -0.36360723 | BF14: =K14-AU14 -> -0.35617571 | BG14: =L14-AV14 -> -0.35799814 | ... BI14: =N14-AX14 -> -0.38927204
C15: Net Win | E15: =FY!H20 -> 147.8 | F15: =FY!I20 -> 158.1 | G15: =FY!J20 -> 183.33132 | H15: =FY!K20 -> 192.49788 | I15: =FY!L20 -> 202.12278 | J15: =FY!M20 -> 212.22891 | K15: =FY!N20 -> 222.84036 | L15: =FY!O20 -> 233.98238 | ... N15: =FY!Q20 -> 257.96557 | P15: =_xlfn.SINGLE(_xlfn.XLOOKUP(P$2,$E$5:$N$5,$E15:$N15)) -> 147.8 | Q15: 158.1 | R15: =Q15/P15-1 -> 0.069688769 | S15: =_xlfn.XLOOKUP(S$2,$E$5:$N$5,$E15:$N15) -> #N/A | T15: =$Q15/S15-1 -> #N/A
C16: Net Win Margin | E16: =E15/E12 -> 0.1040552 | F16: =F15/F12 -> 0.099140904 | G16: =G15/G12 -> 0.10642252 | H16: =H15/H12 -> 0.10642252 | I16: =I15/I12 -> 0.10642252 | J16: =J15/J12 -> 0.10642252 | K16: =K15/K12 -> 0.10642252 | L16: =L15/L12 -> 0.10642252 | ... N16: =N15/N12 -> 0.10642252 | P16: =_xlfn.XLOOKUP(P$2,$E$5:$N$5,$E16:$N16) -> 0.1040552 | Q16: 0.099 | R16: =(Q16-P16)*100 -> -0.50551957 | S16: =_xlfn.XLOOKUP(S$2,$E$5:$N$5,$E16:$N16) -> #N/A | T16: =($Q16-S16)*100 -> #N/A | U16: =_xlfn.XLOOKUP(U$2,$AO$5:$AX$5,$AO16:$AX16) -> #N/A | V16: =($Q16-U16)*100 -> #N/A | AD16: =AD10/AD5 -> #VALUE! | AE16: =AE10/AE5 -> #VALUE! | AF16: =AF10/AF5 -> #VALUE! | AG16: =AG10/AG5 -> #VALUE! | AH16: =AH10/AH5 -> #VALUE! | AI16: =AI10/AI5 -> #VALUE! | AJ16: =AJ10/AJ5 -> #VALUE! | AK16: =AK10/AK5 -> #VALUE! | ... AM16: =AM10/AM5 -> #VALUE! | AO16: 0.49164678 | AP16: 0.49469214 | AQ16: 0.50537634 | AR16: 0.49395161 | AS16: 0.48739496 | AT16: 0.50463822 | AU16: 0.4972067 | AV16: 0.49902913 | AW16: 0.51313131 | AX16: 0.53030303 | AZ16: =E16-AO16 -> -0.38759158 | BA16: =F16-AP16 -> -0.39555124 | BB16: =G16-AQ16 -> -0.39895382 | BC16: =H16-AR16 -> -0.38752909 | BD16: =I16-AS16 -> -0.38097243 | BE16: =J16-AT16 -> -0.39821569 | BF16: =K16-AU16 -> -0.39078418 | BG16: =L16-AV16 -> -0.3926066 | ... BI16: =N16-AX16 -> -0.42388051
E20: =E$5 -> FY25A | F20: =F$5 -> FY26A | G20: =G$5 -> FY27E | H20: =H$5 -> FY28E | I20: =I$5 -> FY29E | J20: =J$5 -> FY30E | K20: =K$5 -> FY31E | L20: =L$5 -> FY32E | ... N20: =N$5 -> FY34E | P20: =P$2 -> FY25A | Q20: =Q$2 -> FY26A | R20: YoY % | S20: ="E&Pe "&S$2 -> E&Pe FY26E | T20: % diff | U20: ="VA Cons. "&S$2 -> VA Cons. FY26E | V20: % diff | AD20: 1H24 | AE20: 2H24 | AF20: 1H25 | AG20: 2H25 | AH20: 1H26 | AI20: 2H26 | AJ20: 1H27 | AK20: 2H27 | AL20: 1H28 | AM20: 2H28 | AO20: 1H24 | AP20: 2H24 | AQ20: 1H25 | AR20: 2H25 | AS20: 1H26 | AT20: 2H26 | AU20: 1H27 | AV20: 2H27 | AW20: 1H28 | AX20: 2H28 | AZ20: 1H24 | BA20: 2H24 | BB20: 1H25 | BC20: 2H25 | BD20: 1H26 | BE20: 2H26 | BF20: 1H27 | BG20: 2H27 | BH20: 1H28 | BI20: 2H28
C21: Costs
C22: Cost of Sales | E22: =FY!H38 -> -73.4 | F22: =FY!I38 -> -84.9 | G22: =FY!J38 -> -95.846727 | H22: =FY!K38 -> -99.384334 | I22: =FY!L38 -> -104.34155 | J22: =FY!M38 -> -109.54627 | K22: =FY!N38 -> -115.01085 | L22: =FY!O38 -> -120.74828 | ... N22: =FY!Q38 -> -133.09689 | P22: =_xlfn.XLOOKUP(P$2,$E$5:$N$5,$E22:$N22) -> -73.4 | Q22: -84.9 | R22: =Q22/P22-1 -> 0.15667575 | S22: =_xlfn.XLOOKUP(S$2,$E$5:$N$5,$E22:$N22) -> #N/A | T22: =$Q22/S22-1 -> #N/A | U22: =_xlfn.XLOOKUP(U$2,$AO$5:$AX$5,$AO22:$AX22) -> #N/A | V22: =$Q22/U22-1 -> #N/A
C23: Advertising & Marketing | E23: =FY!H50 -> -19.5 | F23: =FY!I50 -> -28.2 | G23: =FY!J50 -> -21.5 | H23: =FY!K50 -> -21.5 | I23: =FY!L50 -> -21.7396 | J23: =FY!M50 -> -22.82658 | K23: =FY!N50 -> -23.967909 | L23: =FY!O50 -> -25.166305 | ... N23: =FY!Q50 -> -27.745851 | P23: =_xlfn.XLOOKUP(P$2,$E$5:$N$5,$E23:$N23) -> -19.5 | Q23: -28.2 | R23: =Q23/P23-1 -> 0.44615385 | S23: =_xlfn.XLOOKUP(S$2,$E$5:$N$5,$E23:$N23) -> #N/A | T23: =$Q23/S23-1 -> #N/A | U23: =_xlfn.XLOOKUP(U$2,$AO$5:$AX$5,$AO23:$AX23) -> #N/A | V23: =$Q23/U23-1 -> #N/A
C24: Other Opex | E24: =FY!H49 -> -35.6 | F24: =FY!I49 -> -39.9 | G24: =FY!J49 -> -33.5 | H24: =FY!K49 -> -33.219639 | I24: =FY!L49 -> -32.856353 | J24: =FY!M49 -> -32.895482 | K24: =FY!N49 -> -33.426054 | L24: =FY!O49 -> -35.097357 | ... N24: =FY!Q49 -> -38.694836 | P24: =_xlfn.XLOOKUP(P$2,$E$5:$N$5,$E24:$N24) -> -35.6 | Q24: =Q31-Q23 -> -40 | R24: =Q24/P24-1 -> 0.12359551 | S24: =_xlfn.XLOOKUP(S$2,$E$5:$N$5,$E24:$N24) -> #N/A | T24: =$Q24/S24-1 -> #N/A | U24: =_xlfn.XLOOKUP(U$2,$AO$5:$AX$5,$AO24:$AX24) -> #N/A | V24: =$Q24/U24-1 -> #N/A
C26: Costs % of Net Win
C27: Cost of Sales | E27: =E22/E$15 -> -0.49661705 | F27: =F22/F$15 -> -0.5370019 | G27: =G22/G$15 -> -0.52280608 | H27: =H22/H$15 -> -0.51628794 | I27: =I22/I$15 -> -0.51622857 | J27: =J22/J$15 -> -0.51617033 | K27: =K22/K$15 -> -0.5161132 | L27: =L22/L$15 -> -0.51605716 | ... N27: =N22/N$15 -> -0.51594826 | P27: =_xlfn.XLOOKUP(P$2,$E$5:$N$5,$E27:$N27) -> -0.49661705 | Q27: =Q22/Q15 -> -0.5370019 | R27: =(Q27-P27)*100 -> -4.0384847 | S27: =_xlfn.XLOOKUP(S$2,$E$5:$N$5,$E27:$N27) -> #N/A | T27: =($Q27-S27)*100 -> #N/A | U27: =_xlfn.XLOOKUP(U$2,$AO$5:$AX$5,$AO27:$AX27) -> #N/A | V27: =($Q27-U27)*100 -> #N/A | AD27: =AD21/AD16 -> #VALUE! | AE27: =AE21/AE16 -> #VALUE! | AF27: =AF21/AF16 -> #VALUE! | AG27: =AG21/AG16 -> #VALUE! | AH27: =AH21/AH16 -> #VALUE! | AI27: =AI21/AI16 -> #VALUE! | AJ27: =AJ21/AJ16 -> #VALUE! | AK27: =AK21/AK16 -> #VALUE! | ... AM27: =AM21/AM16 -> #VALUE! | AO27: 0.49164678 | AP27: 0.49469214 | AQ27: 0.50537634 | AR27: 0.49395161 | AS27: 0.48739496 | AT27: 0.50463822 | AU27: 0.4972067 | AV27: 0.49902913 | AW27: 0.51313131 | AX27: 0.53030303 | AZ27: =E27-AO27 -> -0.98826383 | BA27: =F27-AP27 -> -1.031694 | BB27: =G27-AQ27 -> -1.0281824 | BC27: =H27-AR27 -> -1.0102395 | BD27: =I27-AS27 -> -1.0036235 | BE27: =J27-AT27 -> -1.0208085 | BF27: =K27-AU27 -> -1.0133199 | BG27: =L27-AV27 -> -1.0150863 | ... BI27: =N27-AX27 -> -1.0462513
C28: Advertising & Marketing | E28: =E23/E$15 -> -0.13193505 | F28: =F23/F$15 -> -0.17836812 | G28: =G23/G$15 -> -0.11727402 | H28: =H23/H$15 -> -0.11168954 | I28: =I23/I$15 -> -0.10755641 | J28: =J23/J$15 -> -0.10755641 | K28: =K23/K$15 -> -0.10755641 | L28: =L23/L$15 -> -0.10755641 | ... N28: =N23/N$15 -> -0.10755641 | P28: =_xlfn.XLOOKUP(P$2,$E$5:$N$5,$E28:$N28) -> -0.13193505 | Q28: =Q23/Q15 -> -0.17836812 | R28: =(Q28-P28)*100 -> -4.6433074 | S28: =_xlfn.XLOOKUP(S$2,$E$5:$N$5,$E28:$N28) -> #N/A | T28: =($Q28-S28)*100 -> #N/A | U28: =_xlfn.XLOOKUP(U$2,$AO$5:$AX$5,$AO28:$AX28) -> #N/A | V28: =($Q28-U28)*100 -> #N/A | AD28: =AD22/AD17 -> #DIV/0! | AE28: =AE22/AE17 -> #DIV/0! | AF28: =AF22/AF17 -> #DIV/0! | AG28: =AG22/AG17 -> #DIV/0! | AH28: =AH22/AH17 -> #DIV/0! | AI28: =AI22/AI17 -> #DIV/0! | AJ28: =AJ22/AJ17 -> #DIV/0! | AK28: =AK22/AK17 -> #DIV/0! | ... AM28: =AM22/AM17 -> #DIV/0! | AO28: 0.49164678 | AP28: 0.49469214 | AQ28: 0.50537634 | AR28: 0.49395161 | AS28: 0.48739496 | AT28: 0.50463822 | AU28: 0.4972067 | AV28: 0.49902913 | AW28: 0.51313131 | AX28: 0.53030303 | AZ28: =E28-AO28 -> -0.62358183 | BA28: =F28-AP28 -> -0.67306027 | BB28: =G28-AQ28 -> -0.62265036 | BC28: =H28-AR28 -> -0.60564115 | BD28: =I28-AS28 -> -0.59495137 | BE28: =J28-AT28 -> -0.61219463 | BF28: =K28-AU28 -> -0.60476312 | BG28: =L28-AV28 -> -0.60658554 | ... BI28: =N28-AX28 -> -0.63785944
C29: Other Opex | E29: =E24/E$15 -> -0.24086604 | F29: =F24/F$15 -> -0.25237192 | G29: =G24/G$15 -> -0.18272928 | H29: =H24/H$15 -> -0.17257145 | I29: =I24/I$15 -> -0.16255641 | J29: =J24/J$15 -> -0.155 | K29: =K24/K$15 -> -0.15 | L29: =L24/L$15 -> -0.15 | ... N29: =N24/N$15 -> -0.15 | P29: =_xlfn.XLOOKUP(P$2,$E$5:$N$5,$E29:$N29) -> -0.24086604 | Q29: =Q24/Q15 -> -0.25300443 | R29: =(Q29-P29)*100 -> -1.2138392 | S29: =_xlfn.XLOOKUP(S$2,$E$5:$N$5,$E29:$N29) -> #N/A | T29: =($Q29-S29)*100 -> #N/A | U29: =_xlfn.XLOOKUP(U$2,$AO$5:$AX$5,$AO29:$AX29) -> #N/A | V29: =($Q29-U29)*100 -> #N/A | AD29: =AD23/AD18 -> #DIV/0! | AE29: =AE23/AE18 -> #DIV/0! | AF29: =AF23/AF18 -> #DIV/0! | AG29: =AG23/AG18 -> #DIV/0! | AH29: =AH23/AH18 -> #DIV/0! | AI29: =AI23/AI18 -> #DIV/0! | AJ29: =AJ23/AJ18 -> #DIV/0! | AK29: =AK23/AK18 -> #DIV/0! | ... AM29: =AM23/AM18 -> #DIV/0! | AO29: 0.49164678 | AP29: 0.49469214 | AQ29: 0.50537634 | AR29: 0.49395161 | AS29: 0.48739496 | AT29: 0.50463822 | AU29: 0.4972067 | AV29: 0.49902913 | AW29: 0.51313131 | AX29: 0.53030303 | AZ29: =E29-AO29 -> -0.73251281 | BA29: =F29-AP29 -> -0.74706406 | BB29: =G29-AQ29 -> -0.68810563 | BC29: =H29-AR29 -> -0.66652307 | BD29: =I29-AS29 -> -0.64995137 | BE29: =J29-AT29 -> -0.65963822 | BF29: =K29-AU29 -> -0.6472067 | BG29: =L29-AV29 -> -0.64902913 | ... BI29: =N29-AX29 -> -0.68030303
C31: Total Opex | E31: =FY!H52 -> -55.1 | F31: =FY!I52 -> -68.2 | G31: =FY!J52 -> -55 | H31: =FY!K52 -> -54.719639 | I31: =FY!L52 -> -54.595953 | J31: =FY!M52 -> -55.722062 | K31: =FY!N52 -> -57.393963 | L31: =FY!O52 -> -60.263662 | ... N31: =FY!Q52 -> -66.440687 | P31: =_xlfn.XLOOKUP(P$2,$E$5:$N$5,$E31:$N31) -> -55.1 | Q31: -68.2 | R31: =Q31/P31-1 -> 0.23774955 | S31: =_xlfn.XLOOKUP(S$2,$E$5:$N$5,$E31:$N31) -> #N/A | T31: =$Q31/S31-1 -> #N/A | U31: =_xlfn.XLOOKUP(U$2,$AO$5:$AX$5,$AO31:$AX31) -> #N/A | V31: =$Q31/U31-1 -> #N/A

Sheet Revision Tables
E2: FY25A | F2: FY26E | G2: =FY!J6 -> FY27E | H2: =FY!K6 -> FY28E | I2: =FY!L6 -> FY29E | J2: =FY!M6 -> FY30E | K2: =FY!N6 -> FY31E | L2: =FY!O6 -> FY32E | M2: =FY!P6 -> FY33E | N2: =FY!Q6 -> FY34E
C3: Revenue | D3: New | E3: =FY!H68 -> 134.6 | F3: =FY!I68 -> 145.4 | G3: =FY!J68 -> 166.66483 | H3: =FY!K68 -> 174.99807 | I3: =FY!L68 -> 183.74798 | J3: =FY!M68 -> 192.93538 | K3: =FY!N68 -> 202.58215 | L3: =FY!O68 -> 212.71125 | ... N3: =FY!Q68 -> 234.51416
D4: Old | E4: 134.6 | F4: 145.4 | G4: 166.66483 | H4: 174.99807 | I4: 183.74798 | J4: 192.93538 | K4: 202.58215 | L4: 212.71125 | M4: 223.34682 | N4: 234.51416 | P4: << | Q4: Initiation
D5: % change | E5: =E3/E4-1 -> 0 | F5: =F3/F4-1 -> 0 | G5: =G3/G4-1 -> 0 | H5: =H3/H4-1 -> 0 | I5: =I3/I4-1 -> 0 | J5: =J3/J4-1 -> 0 | K5: =K3/K4-1 -> 0 | L5: =L3/L4-1 -> 0 | ... N5: =N3/N4-1 -> 0
C6: EBITDA | D6: New | E6: =FY!H75 -> 7.2 | F6: =FY!I75 -> -7.1 | G6: =FY!J75 -> 16.471693 | H6: =FY!K75 -> 21.580368 | I6: =FY!L75 -> 25.531054 | J6: =FY!M75 -> 28.423656 | K6: =FY!N75 -> 30.971771 | L6: =FY!O75 -> 32.533472 | ... N6: =FY!Q75 -> 35.896246
D7: Old | E7: 7.2 | F7: -7.1 | G7: 16.471693 | H7: 21.580368 | I7: 25.531054 | J7: 28.423656 | K7: 30.971771 | L7: 32.533472 | M7: 34.173652 | N7: 35.896246
D8: % change | E8: =E6/E7-1 -> 0 | F8: =F6/F7-1 -> 0 | G8: =G6/G7-1 -> 0 | H8: =H6/H7-1 -> 0 | I8: =I6/I7-1 -> 0 | J8: =J6/J7-1 -> 0 | K8: =K6/K7-1 -> 0 | L8: =L6/L7-1 -> 0 | ... N8: =N6/N7-1 -> 0
C9: NPAT | D9: New | E9: =FY!H82 -> 4.8 | F9: =FY!I82 -> -20.7 | G9: =FY!J82 -> 3.6193085 | H9: =FY!K82 -> 6.5389653 | I9: =FY!L82 -> 8.6409052 | J9: =FY!M82 -> 10.712788 | K9: =FY!N82 -> 12.61912 | L9: =FY!O82 -> 13.782772 | ... N9: =FY!Q82 -> 16.163508
D10: Old | E10: 4.8 | F10: -20.7 | G10: 3.6193085 | H10: 6.5389653 | I10: 8.6409052 | J10: 10.712788 | K10: 12.61912 | L10: 13.782772 | M10: 14.964468 | N10: 16.163508
D11: % change | E11: =E9/E10-1 -> 0 | F11: =F9/F10-1 -> 0 | G11: =G9/G10-1 -> 0 | H11: =H9/H10-1 -> 0 | I11: =I9/I10-1 -> 0 | J11: =J9/J10-1 -> 0 | K11: =K9/K10-1 -> 0 | L11: =L9/L10-1 -> 0 | ... N11: =N9/N10-1 -> 0
C12: Valuation | D12: New | G12: =HY!D607 -> 0.27
D13: Old | G13: 0.27
D14: % change | G14: =G12/G13-1 -> 0
E16: FY25A | F16: FY26E | G16: =FY!J6 -> FY27E | H16: =FY!K6 -> FY28E | I16: =FY!L6 -> FY29E | J16: =FY!M6 -> FY30E | K16: =FY!N6 -> FY31E | L16: =FY!O6 -> FY32E | M16: =FY!P6 -> FY33E | N16: =FY!Q6 -> FY34E
C17: Turnover | D17: New | E17: =FY!H12 -> 1420.4 | F17: =FY!I12 -> 1594.7 | G17: =FY!J12 -> 1722.674 | H17: =FY!K12 -> 1808.8077 | I17: =FY!L12 -> 1899.2481 | J17: =FY!M12 -> 1994.2105 | K17: =FY!N12 -> 2093.921 | L17: =FY!O12 -> 2198.6171 | ... N17: =FY!Q12 -> 2423.9753
D18: Old | E18: 1420.4 | F18: 1594.7 | G18: 1722.674 | H18: 1808.8077 | I18: 1899.2481 | J18: 1994.2105 | K18: 2093.921 | L18: 2198.6171 | M18: 2308.5479 | N18: 2423.9753
D19: % change | E19: =E17/E18-1 -> 0 | F19: =F17/F18-1 -> 0 | G19: =G17/G18-1 -> 0 | H19: =H17/H18-1 -> 0 | I19: =I17/I18-1 -> 0 | J19: =J17/J18-1 -> 0 | K19: =K17/K18-1 -> 0 | L19: =L17/L18-1 -> 0 | ... N19: =N17/N18-1 -> 0
C20: Gross Win | D20: New | E20: =FY!H14 -> 196.2 | F20: =FY!I14 -> 215.7 | G20: =FY!J14 -> 242.95042 | H20: =FY!K14 -> 255.09794 | I20: =FY!L14 -> 267.85284 | J20: =FY!M14 -> 281.24548 | K20: =FY!N14 -> 295.30775 | L20: =FY!O14 -> 310.07314 | ... N20: =FY!Q14 -> 341.85564
D21: Old | E21: 196.2 | F21: 215.7 | G21: 242.95042 | H21: 255.09794 | I21: 267.85284 | J21: 281.24548 | K21: 295.30775 | L21: 310.07314 | M21: 325.5768 | N21: 341.85564
D22: % change | E22: =E20/E21-1 -> 0 | F22: =F20/F21-1 -> 0 | G22: =G20/G21-1 -> 0 | H22: =H20/H21-1 -> 0 | I22: =I20/I21-1 -> 0 | J22: =J20/J21-1 -> 0 | K22: =K20/K21-1 -> 0 | L22: =L20/L21-1 -> 0 | ... N22: =N20/N21-1 -> 0
C23: Net Win | D23: New | E23: =FY!H20 -> 147.8 | F23: =FY!I20 -> 158.1 | G23: =FY!J20 -> 183.33132 | H23: =FY!K20 -> 192.49788 | I23: =FY!L20 -> 202.12278 | J23: =FY!M20 -> 212.22891 | K23: =FY!N20 -> 222.84036 | L23: =FY!O20 -> 233.98238 | ... N23: =FY!Q20 -> 257.96557
D24: Old | E24: 147.8 | F24: 158.1 | G24: 183.33132 | H24: 192.49788 | I24: 202.12278 | J24: 212.22891 | K24: 222.84036 | L24: 233.98238 | M24: 245.6815 | N24: 257.96557
D25: % change | E25: =E23/E24-1 -> 0 | F25: =F23/F24-1 -> 0 | G25: =G23/G24-1 -> 0 | H25: =H23/H24-1 -> 0 | I25: =I23/I24-1 -> 0 | J25: =J23/J24-1 -> 0 | K25: =K23/K24-1 -> 0 | L25: =L23/L24-1 -> 0 | ... N25: =N23/N24-1 -> 0

Sheet III

Sheet Templates
C2: 1H27 | D2: FY27 | E2: FY28 | F2: FY29 | H2: 1Q27 | I2: 2Q27
B3: Turnover | C3: =HY!K64 -> 888.03 | D3: =FY!J12 -> 1722.674 | E3: =FY!K12 -> 1808.8077 | F3: =FY!L12 -> 1899.2481 | H3: =QTR!Y29 -> 413.82 | I3: =QTR!Z29 -> 473.286
B4: Gross Win | C4: =HY!K68 -> 126.10026 | D4: =FY!J14 -> 242.95042 | E4: =FY!K14 -> 255.09794 | F4: =FY!L14 -> 267.85284 | H4: =QTR!Y35 -> 59.17626 | I4: =QTR!Z35 -> 67.679898
B5: % | C5: =HY!K69 -> 0.142 | D5: =FY!J15 -> 0.14103099 | E5: =FY!K15 -> 0.14103099 | F5: =FY!L15 -> 0.14103099 | H5: =QTR!Y36 -> 0.143 | I5: =QTR!Z36 -> 0.143
B6: Net Win | C6: =HY!K75 -> 92.35512 | D6: =FY!J20 -> 183.33132 | E6: =FY!K20 -> 192.49788 | F6: =FY!L20 -> 202.12278 | H6: =QTR!Y41 -> 44.27874 | I6: =QTR!Z41 -> 49.69503
B7: % | C7: =HY!K76 -> 0.104 | D7: =FY!J21 -> 0.10642252 | E7: =FY!K21 -> 0.10642252 | F7: =FY!L21 -> 0.10642252 | H7: =QTR!Y42 -> 0.107 | I7: =QTR!Z42 -> 0.105
B8: Opex | C8: =HY!K117 -> -29.5 | D8: =FY!J52 -> -55 | E8: =FY!K52 -> -54.719639 | F8: =FY!L52 -> -54.595953
B9: EBITDA | C9: =HY!K119 -> 5.4973804 | D9: =FY!J75 -> 16.471693 | E9: =FY!K75 -> 21.580368 | F9: =FY!L75 -> 25.531054
B10: NPAT | C10: =HY!K126 -> -0.1152666 | D10: =FY!J82 -> 3.6193085 | E10: =FY!K82 -> 6.5389653 | F10: =FY!L82 -> 8.6409052
