Workbook

Sheet BM
B1: =D8 -> SKC-ASX
A2: Industrial ResearchWise Sheet
C3: Company static items | E3: =+E114 -> FY2018A | F3: =+F114 -> FY2019A | G3: =+G114 -> FY2020A | H3: =+H114 -> FY2021A | I3: =+I114 -> FY2022A | J3: =+J114 -> FY2023A | K3: =+K114 -> FY2024A | L3: =+L114 -> FY2025A | ... Q3: =+Q114 -> FY2030F | AJ3: BlueMatrix formulas
A4: @BEGINSTATIC | D4: @ENDSTATIC
A5: @INSTTYPE | C5: Instrument type | D5: EQ
A6: @CTYPE | C6: Instrument code type | D6: @BB
A7: @VERSION | C7: Version information (Do not change) | D7: 1
A8: @CODE | C8: Ticker | D8: SKC-ASX
A9: @MULT | C9: Multiplier | D9: 1000000 | E9: Please choose from the options available in the dropdown
A10: @RCURR | C10: Reporting Currency | D10: NZD | E10: Please choose from the options available in the dropdown
A11: @ANALYST | C11: Lead analyst | D11: Sam Bradshaw
A13: @TARGET | B13: PRICE_TARGET | C13: Valuation | D13: =HY!$D$654 -> 0.65016617 | AJ13: =_xll.BLUEMATRIX2("/servlet/excelData",$D13,$B$1,$B13) -> #
A14: @REC | B14: REC | C14: Recommendation | D14: Neutral | E14: Please choose from the options available in the dropdown | AJ14: =_xll.BLUEMATRIX2("/servlet/excelData",$D14,$B$1,$B14) -> #
A15: @SHARE_OUT | B15: SHARE_OUT | C15: Shares outstanding | D15: =HY!D628 -> 1103.055 | AJ15: =_xll.BLUEMATRIX2("/servlet/excelData",$D15,$B$1,$B15) -> #
A16: @FLOATPER | B16: free_float | C16: Free Float % | D16: 100 | AJ16: =_xll.BLUEMATRIX2("/servlet/excelData",#REF!,$B$1,$B16) -> #VALUE!
B17: PRICE | C17: Current Share Price | D17: =HY!D656 -> 0.5 | AJ17: =_xll.BLUEMATRIX2("/servlet/excelData",$D17,$B$1,$B17) -> #
C18: Historic Share Price (Closing) | E18: 4.04 | F18: 3.79 | G18: 2.39 | H18: 3.51 | I18: 2.91 | J18: 2.28 | K18: =$D$17 -> 0.5 | L18: =$D$17 -> 0.5 | M18: =$D$17 -> 0.5 | N18: =$D$17 -> 0.5 | O18: =$D$17 -> 0.5 | P18: =$D$17 -> 0.5 | Q18: =$D$17 -> 0.5
C20: TSR
B21: upside_valuation | C21: Upside to valuation | D21: =(D13/D17-1)*100 -> 30.033234 | AJ21: =_xll.BLUEMATRIX2("/servlet/excelData",$D21,$B$1,$B21) -> #
B22: div_yield | C22: Dividend yield | D22: =L304*100 -> 0 | AJ22: =_xll.BLUEMATRIX2("/servlet/excelData",$D22,$B$1,$B22) -> #
B23: exp_total_return | C23: Expected total SH return | D23: =D21+D22 -> 30.033234 | AJ23: =_xll.BLUEMATRIX2("/servlet/excelData",$D23,$B$1,$B23) -> #
C25: Trading Data test
B26: 12_month_high | C26: 12 month high | AJ26: =_xll.BLUEMATRIX2("/servlet/excelData",$D26,$B$1,$B26) -> #
B27: 12_month_low | C27: 12 month low | AJ27: =_xll.BLUEMATRIX2("/servlet/excelData",$D27,$B$1,$B27) -> #
B28: MARKET_CAP | C28: Market cap | D28: =D15*D17 -> 551.52752 | AJ28: =_xll.BLUEMATRIX2("/servlet/excelData",$D28,$B$1,$B28) -> #
B29: free_float | C29: Free Float | AJ29: =_xll.BLUEMATRIX2("/servlet/excelData",$D29,$B$1,$B29) -> #
B30: 12_month_return | C30: 12 month return (historical) | AJ30: =_xll.BLUEMATRIX2("/servlet/excelData",$D30,$B$1,$B30) -> #
A31: @pricing_date
C34: Blended Valuation
A35: @DCF_VAL | B35: DCF_VAL | C35: Valuation - DCF | D35: =HY!$D$654 -> 0.65016617 | AJ35: =_xll.BLUEMATRIX2("/servlet/excelData",$D35,$B$1,$B35) -> #
A36: @CAPPER_VAL | B36: CAPPER_VAL | C36: Valuation - Capitalisation of Earnings | AJ36: =_xll.BLUEMATRIX2("/servlet/excelData",$D36,$B$1,$B36) -> #
A37: @PER_VAL | B37: PER_VAL | C37: Valuation - PER | AJ37: =_xll.BLUEMATRIX2("/servlet/excelData",$D37,$B$1,$B37) -> #
A38: @SOTP_VAL | B38: SOTP_VAL | C38: Valuation - SOTP | AJ38: =_xll.BLUEMATRIX2("/servlet/excelData",$D38,$B$1,$B38) -> #
A39: @BLEND_VAL | B39: PRICE_TARGET | C39: Valuation - Blended | AJ39: =_xll.BLUEMATRIX2("/servlet/excelData",$D39,$B$1,$B39) -> #
A40: @DCF_WT | B40: DCF_WT | C40: DCF Weightage | AJ40: =_xll.BLUEMATRIX2("/servlet/excelData",$D16,$B$1,$B40) -> #
A41: @CAPPER_WT | B41: CAPPER_WT | C41: Capitalisation of Earnings Weightage | AJ41: =_xll.BLUEMATRIX2("/servlet/excelData",$D41,$B$1,$B41) -> #
A42: @PER_WT | B42: PER_WT | C42: PER Weightage | AJ42: =_xll.BLUEMATRIX2("/servlet/excelData",$D42,$B$1,$B42) -> #
A43: @SOTP_WT | B43: SOTP_WT | C43: SOTP Weightage | AJ43: =_xll.BLUEMATRIX2("/servlet/excelData",$D43,$B$1,$B43) -> #
C45: Divisional Summary
A46: @SEG1_NAME | C46: Name of Segment 1 | D46: Auckland
A47: @SEG2_NAME | C47: Name of Segment 2 | D47: Hamilton & Queenstown
A48: @SEG3_NAME | C48: Name of Segment 3 | D48: Adelaide
A49: @SEG4_NAME | C49: Name of Segment 4 | D49: Online (from segments)
A50: @SEG5_NAME | C50: Name of Segment 5 | D50: Corporate Costs
A51: @SEG6_NAME | C51: Name of Segment 6 | D51: Other
A52: @SEG7_NAME | C52: Name of Segment 7 | D52: Segment
A53: @SEG8_NAME | C53: Name of Segment 8
A54: @SEG9_NAME | C54: Name of Segment 9
A55: @SEG10_NAME | C55: Name of Segment 10
A57: @SEG_PROFIT1 | C57: Type of Segmental Results | D57: EBITDA | E57: Please choose from the options available in the dropdown
A59: @SEG_PROFIT2 | C59: Type of Segmental Results | D59: EBITDA Margin | E59: Please choose from the options available in the dropdown
C61: Core Drivers, Investment Thesis, Near Term Catalysts
A62: @COREDRIVER1 | C62: Core Driver 1 | D62: Mass market revenues (household spend, wealth effect, tourism) and VIP revenues (Chinese macro, ANZ share of regional market). | AJ62: =_xll.BLUEMATRIX2("/servlet/excelData",$D62,$B$1,$B62) -> #
A63: @COREDRIVER1 | C63: Core Driver 2 | D63: Margins (earnings mix, gambling taxes and operating expenses). | AJ63: =_xll.BLUEMATRIX2("/servlet/excelData",$D63,$B$1,$B63) -> #
A64: @COREDRIVER1 | C64: Core Driver 3 | D64: Expansion projects (NZICC, Adelaide expansion). | AJ64: =_xll.BLUEMATRIX2("/servlet/excelData",$D64,$B$1,$B64) -> #
A65: @COREDRIVER1 | C65: Core Driver 4 | D65: Competition (new casino openings, local pubs/clubs). | AJ65: =_xll.BLUEMATRIX2("/servlet/excelData",$D65,$B$1,$B65) -> #
A66: @COREDRIVER1 | C66: Core Driver 5 | D66: Regulatory risks in NZ, Australia and China. | AJ66: =_xll.BLUEMATRIX2("/servlet/excelData",$D66,$B$1,$B66) -> #
A68: @THESIS1 | C68: Investment Thesis 1 | D68: Near-term earnings risk as revenues slow and cost pressures build | AJ68: =_xll.BLUEMATRIX2("/servlet/excelData",$D68,$B$1,$B68) -> #
A69: @THESIS1 | C69: Investment Thesis 2 | D69: Reasonable medium-term growth as following the completion of the NZICC and Adelaide expansion | AJ69: =_xll.BLUEMATRIX2("/servlet/excelData",$D69,$B$1,$B69) -> #
A70: @THESIS1 | C70: Investment Thesis 3 | D70: Exclusive licences with minimal competition risk in foreseeable future. | AJ70: =_xll.BLUEMATRIX2("/servlet/excelData",$D70,$B$1,$B70) -> #
A71: @THESIS1 | C71: Investment Thesis 4 | AJ71: =_xll.BLUEMATRIX2("/servlet/excelData",$D71,$B$1,$B71) -> #
A72: @THESIS1 | C72: Investment Thesis 5 | AJ72: =_xll.BLUEMATRIX2("/servlet/excelData",$D72,$B$1,$B72) -> #
A74: @CATALYST1 | C74: Near Term Catalyst 1 | AJ74: =_xll.BLUEMATRIX2("/servlet/excelData",$D74,$B$1,$B74) -> #
A76: @NOTES | C76: Notes
C78: Key Macro Assumptions
A79: @KEYMAC1 | C79: Name of Key Macro Assumption 1
A80: @KEYMAC2 | C80: Name of Key Macro Assumption 2
A81: @KEYMAC3 | C81: Name of Key Macro Assumption 3
A82: @KEYMAC4 | C82: Name of Key Macro Assumption 4
A83: @KEYMAC5 | C83: Name of Key Macro Assumption 5
A84: @KEYMAC6 | C84: Name of Key Macro Assumption 6
A85: @KEYMAC7 | C85: Name of Key Macro Assumption 7
A86: @KEYMAC8 | C86: Name of Key Macro Assumption 8
A87: @KEYMAC9 | C87: Name of Key Macro Assumption 9
A88: @KEYMAC10 | C88: Name of Key Macro Assumption 10
C90: Type of Key Macro Assumption
A91: @KEYMACTYPE1 | C91: Type of Key Macro Assumption 1
A92: @KEYMACTYPE2 | C92: Type of Key Macro Assumption 2
A93: @KEYMACTYPE3 | C93: Type of Key Macro Assumption 3
A94: @KEYMACTYPE4 | C94: Type of Key Macro Assumption 4
A95: @KEYMACTYPE5 | C95: Type of Key Macro Assumption 5
A96: @KEYMACTYPE6 | C96: Type of Key Macro Assumption 6
A97: @KEYMACTYPE7 | C97: Type of Key Macro Assumption 7
A98: @KEYMACTYPE8 | C98: Type of Key Macro Assumption 8
A99: @KEYMACTYPE9 | C99: Type of Key Macro Assumption 9
A100: @KEYMACTYPE10 | C100: Type of Key Macro Assumption 10
C102: Companies for Relative Chart
A103: @COM1 | C103: Company 1
A104: @COM2 | C104: Company 2
A105: @COM3 | C105: Company 3
A106: @COM4 | C106: Company 4
A107: @COM5 | C107: Company 5
A108: @COM6 | C108: Company 6
A109: @INDEX | C109: Index
A111: @ENDSTATIC
C113: Financials & other data
A114: @BEGIN | C114: Year | E114: =E117&E115&E116 -> FY2018A | F114: =F117&F115&F116 -> FY2019A | G114: =G117&G115&G116 -> FY2020A | H114: =H117&H115&H116 -> FY2021A | I114: =I117&I115&I116 -> FY2022A | J114: =J117&J115&J116 -> FY2023A | K114: =K117&K115&K116 -> FY2024A | L114: =L117&L115&L116 -> FY2025A | ... Q114: =Q117&Q115&Q116 -> FY2030F | T114: =T117&T115&T116 | U114: =U117&U115&U116 | V114: =V117&V115&V116 | W114: =W117&W115&W116 | X114: =X117&X115&X116 | Y114: =Y117&Y115&Y116 | Z114: =Z117&Z115&Z116 | AA114: =AA117&AA115&AA116 | ... AH114: =AH117&AH115&AH116 | AI114: AN
A115: @DATE | C115: Reporting Financial Year | E115: 2018 | F115: 2019 | G115: 2020 | H115: 2021 | I115: 2022 | J115: 2023 | K115: 2024 | L115: 2025 | M115: 2026 | N115: 2027 | O115: 2028 | P115: 2029 | Q115: 2030
A116: @FSTATUS | C116: Accounts Status | E116: A | F116: A | G116: A | H116: A | I116: A | J116: A | K116: A | L116: A | M116: A | N116: F | O116: F | P116: F | Q116: F
A117: @FPERIOD | C117: Reporting Period | E117: FY | F117: FY | G117: FY | H117: FY | I117: FY | J117: FY | K117: FY | L117: FY | M117: FY | N117: FY | O117: FY | P117: FY | Q117: FY
...

Sheet I

Sheet HY
E1: IB Reported Seperately & Ex GST Calcs | O1: Restated | S1: FY25 EBITDA | T1: =S325+T325 -> 233.7 | U1: FY26 EBITDA | V1: =U325+V325 -> 181.6 | W1: FY27 EBITDA | X1: =W325+X325 -> 183.18614 | Y1: FY28 EBITDA | Z1: =Y325+Z325 -> 204.83215
B2: Checks | C2: =SUM(E2:AL2) -> 0 | E2: =E623 -> 0 | F2: =F623 -> 0 | G2: =G623 -> 0 | H2: =H623 -> 0 | I2: =I623 -> 0 | J2: =J623 -> 0 | K2: =K623 -> 0 | L2: =L623 -> 0 | ... AN2: =AN623 -> 0
A3: X | B3: Valuation | C3: =D654 -> 0.65016617 | D3: VAL | E3: =E8&E10 -> 1H18A | F3: =F8&F10 -> 2H18A | G3: =G8&G10 -> 1H19A | H3: =H8&H10 -> 2H19A | I3: =I8&I10 -> 1H20A | J3: =J8&J10 -> 2H20A | K3: =K8&K10 -> 1H21A | L3: =L8&L10 -> 2H21A | ... AN3: =AN8&AN10 -> 2H35E
B4: Period End | E4: 43100 | F4: =EOMONTH(E4,6) -> 43281 | G4: =EOMONTH(F4,6) -> 43465 | H4: =EOMONTH(G4,6) -> 43646 | I4: =EOMONTH(H4,6) -> 43830 | J4: =EOMONTH(I4,6) -> 44012 | K4: =EOMONTH(J4,6) -> 44196 | L4: =EOMONTH(K4,6) -> 44377 | M4: =EOMONTH(L4,6) -> 44561 | ... AN4: =EOMONTH(AM4,6) -> 49490
B6: Half | E6: {=_xlfn.IFS(AND(MONTH(E$4)>=7,MONTH(E$4)<=12),"1H",AND(MONTH(E$4)>=1,MONTH(E$4)<=6),"2H")} -> 1H | F6: {=_xlfn.IFS(AND(MONTH(F$4)>=7,MONTH(F$4)<=12),"1H",AND(MONTH(F$4)>=1,MONTH(F$4)<=6),"2H")} -> 2H | G6: {=_xlfn.IFS(AND(MONTH(G$4)>=7,MONTH(G$4)<=12),"1H",AND(MONTH(G$4)>=1,MONTH(G$4)<=6),"2H")} -> 1H | H6: {=_xlfn.IFS(AND(MONTH(H$4)>=7,MONTH(H$4)<=12),"1H",AND(MONTH(H$4)>=1,MONTH(H$4)<=6),"2H")} -> 2H | I6: {=_xlfn.IFS(AND(MONTH(I$4)>=7,MONTH(I$4)<=12),"1H",AND(MONTH(I$4)>=1,MONTH(I$4)<=6),"2H")} -> 1H | J6: {=_xlfn.IFS(AND(MONTH(J$4)>=7,MONTH(J$4)<=12),"1H",AND(MONTH(J$4)>=1,MONTH(J$4)<=6),"2H")} -> 2H | K6: {=_xlfn.IFS(AND(MONTH(K$4)>=7,MONTH(K$4)<=12),"1H",AND(MONTH(K$4)>=1,MONTH(K$4)<=6),"2H")} -> 1H | L6: {=_xlfn.IFS(AND(MONTH(L$4)>=7,MONTH(L$4)<=12),"1H",AND(MONTH(L$4)>=1,MONTH(L$4)<=6),"2H")} -> 2H | ... AN6: {=_xlfn.IFS(AND(MONTH(AN$4)>=7,MONTH(AN$4)<=12),"1H",AND(MONTH(AN$4)>=1,MONTH(AN$4)<=6),"2H")} -> 2H
B7: FY | E7: =IF(MONTH(E4)>6,RIGHT(YEAR(E4),2)+1,RIGHT(YEAR(E4),2)) -> 18 | F7: =IF(MONTH(F4)>6,RIGHT(YEAR(F4),2)+1,RIGHT(YEAR(F4),2)) -> 18 | G7: =IF(MONTH(G4)>6,RIGHT(YEAR(G4),2)+1,RIGHT(YEAR(G4),2)) -> 19 | H7: =IF(MONTH(H4)>6,RIGHT(YEAR(H4),2)+1,RIGHT(YEAR(H4),2)) -> 19 | I7: =IF(MONTH(I4)>6,RIGHT(YEAR(I4),2)+1,RIGHT(YEAR(I4),2)) -> 20 | J7: =IF(MONTH(J4)>6,RIGHT(YEAR(J4),2)+1,RIGHT(YEAR(J4),2)) -> 20 | K7: =IF(MONTH(K4)>6,RIGHT(YEAR(K4),2)+1,RIGHT(YEAR(K4),2)) -> 21 | L7: =IF(MONTH(L4)>6,RIGHT(YEAR(L4),2)+1,RIGHT(YEAR(L4),2)) -> 21 | ... AN7: =IF(MONTH(AN4)>6,RIGHT(YEAR(AN4),2)+1,RIGHT(YEAR(AN4),2)) -> 35
B8: FY Year | E8: =E$6&TEXT(E$7,"00") -> 1H18 | F8: =F$6&TEXT(F$7,"00") -> 2H18 | G8: =G$6&TEXT(G$7,"00") -> 1H19 | H8: =H$6&TEXT(H$7,"00") -> 2H19 | I8: =I$6&TEXT(I$7,"00") -> 1H20 | J8: =J$6&TEXT(J$7,"00") -> 2H20 | K8: =K$6&TEXT(K$7,"00") -> 1H21 | L8: =L$6&TEXT(L$7,"00") -> 2H21 | ... AN8: =AN$6&TEXT(AN$7,"00") -> 2H35
B9: Financial Year | E9: {=_xlfn.IFS(MONTH(E$4)=12,YEAR(E$4)+1,MONTH(E$4)=6,YEAR(E$4))} -> 2018 | F9: {=_xlfn.IFS(MONTH(F$4)=12,YEAR(F$4)+1,MONTH(F$4)=6,YEAR(F$4))} -> 2018 | G9: {=_xlfn.IFS(MONTH(G$4)=12,YEAR(G$4)+1,MONTH(G$4)=6,YEAR(G$4))} -> 2019 | H9: {=_xlfn.IFS(MONTH(H$4)=12,YEAR(H$4)+1,MONTH(H$4)=6,YEAR(H$4))} -> 2019 | I9: {=_xlfn.IFS(MONTH(I$4)=12,YEAR(I$4)+1,MONTH(I$4)=6,YEAR(I$4))} -> 2020 | J9: {=_xlfn.IFS(MONTH(J$4)=12,YEAR(J$4)+1,MONTH(J$4)=6,YEAR(J$4))} -> 2020 | K9: {=_xlfn.IFS(MONTH(K$4)=12,YEAR(K$4)+1,MONTH(K$4)=6,YEAR(K$4))} -> 2021 | L9: {=_xlfn.IFS(MONTH(L$4)=12,YEAR(L$4)+1,MONTH(L$4)=6,YEAR(L$4))} -> 2021 | ... AN9: {=_xlfn.IFS(MONTH(AN$4)=12,YEAR(AN$4)+1,MONTH(AN$4)=6,YEAR(AN$4))} -> 2035
B10: Actual/Estimate | E10: A | F10: A | G10: A | H10: A | I10: A | J10: A | K10: A | L10: A | M10: A | N10: A | O10: A | P10: A | Q10: A | R10: A | S10: A | T10: A | U10: A | V10: =IF(ISNUMBER(#REF!),"A","E") -> E | W10: =IF(ISNUMBER(#REF!),"A","E") -> E | X10: =IF(ISNUMBER(#REF!),"A","E") -> E | Y10: =IF(ISNUMBER(#REF!),"A","E") -> E | Z10: =IF(ISNUMBER(#REF!),"A","E") -> E | AA10: =IF(ISNUMBER(#REF!),"A","E") -> E | AB10: =IF(ISNUMBER(#REF!),"A","E") -> E | AC10: =IF(ISNUMBER(#REF!),"A","E") -> E | ... AN10: =IF(ISNUMBER(#REF!),"A","E") -> E
A12: X | B12: FOREIGN EXCHANGE
B13: Days in period | E13: =E4-EOMONTH(E4,-6) -> 184 | F13: =F4-E4 -> 181 | G13: =G4-F4 -> 184 | H13: =H4-G4 -> 181 | I13: =I4-H4 -> 184 | J13: =J4-I4 -> 182 | K13: =K4-J4 -> 184 | L13: =L4-K4 -> 181 | M13: =M4-L4 -> 184 | ... AN13: =AN4-AM4 -> 181
A14: CUT
B15: Foreign exchange (NZDAUD) - Average
B16: Reported Average | C16: NZD/AUD | E16: 0.9141 | F16: =AVERAGE(0.9199,E16) -> 0.917 | G16: 0.9291 | H16: =AVERAGE(0.9398,G16) -> 0.93445 | I16: 0.9449 | J16: =AVERAGE(0.9483,I16) -> 0.9466 | K16: 0.9334 | L16: =AVERAGE(0.9323,K16) -> 0.93285 | M16: 0.9525 | N16: =AVERAGE(0.9362,M16) -> 0.94435 | O16: 0.9061 | P16: 0.92347713 | Q16: 0.9246 | R16: =0.9232*2-Q16 -> 0.9218 | S16: 0.9062 | T16: 0.9032 | U16: =T16 -> 0.9032 | V16: =U16 -> 0.9032 | W16: =V16 -> 0.9032 | X16: =W16 -> 0.9032 | Y16: =X16 -> 0.9032 | Z16: =Y16 -> 0.9032 | AA16: =Z16 -> 0.9032 | AB16: =AA16 -> 0.9032 | ... AN16: =AM16 -> 0.9032
B17: Consensus | C17: NZD/AUD | E17: =1/E18 -> 0.93118434 | F17: =1/F18 -> 0.92372396 | G17: =1/G18 -> 0.93465748 | H17: =1/H18 -> 0.95144423 | I17: =1/I18 -> 0.9449 | J17: =1/J18 -> 0.94778741 | K17: =1/K18 -> 0.92712119 | L17: =1/L18 -> 0.93052097 | ... Z17: =1/Z18 -> 0.92929461
B18: Consensus | C18: AUD/NZD | E18: 1.0739012 | F18: 1.0825745 | G18: 1.0699107 | H18: 1.0510338 | I18: 1.058313 | J18: 1.0550889 | K18: 1.0786076 | L18: 1.0746668 | M18: 1.0648957 | N18: 1.0778125 | O18: 1.1036309 | P18: 1.0896318 | Q18: 1.0901836 | R18: 1.0914007 | S18: 1.0847758 | T18: 1.0825061 | U18: 1.0817353 | V18: 1.080588 | W18: 1.0794494 | X18: 1.0783195 | Y18: 1.077198 | Z18: 1.076085
A20: X | B20: GUIDANCE/COMMENTARY
B22: FY26 Result
B24: EBITDA
B25: FY27 EBITDA triangulates to ~$185–190m ex-online: 4Q26 run-rate of just under $40m/qtr continuing into 1Q27 → ~$156–160m annualised, plus $30m net cost-out — management didn't dispute this bridge [Directional]. Then subtract the online launch drag and part-year Grand removal to land the number. Skew 1H-soft (weak run-rate persists early).
B27: COST OUT
B28: $30m net realised FY27 → $70m annualised FY28. Both net [Guidance].
B29: FY27 is organisational/headcount-led; FY28 uplift skews to external spend, process improvement and revenue [Directional].
B30: Adelaide allocation included, but the majority is NZ [Directional].
B31: One-off restructuring costs hit reported (not underlying) FY27 — unquantified; you need a below-EBITDA charge (200–250 NZ roles)
B33: AUCKLAND
B34: Auckland gaming: rebased, not recovering — a full year of MCP is lapped; model growth off the new base, not a snap-back [Directional].
B35: Non-gaming grows faster than gaming, at lower margin → mix is a structural margin drag even as revenue grows [Directional].
B36: Auckland margin "improves demonstrably" FY27 on the NZICC full-year/conference ramp — but stated before any Grand sale [Directional].
... B73: Adelaide ETR: ~A$180m unrecognised tax losses shelter Adelaide tax
A80: X | B80: LAND BASED DOMESTIC SEGMENTS REVENUE
A82: add in other lines | B82: Auckland
B83: Slots | C83: NZ$m | E83: 109.359 | F83: =(252.2-E83)*0.87 -> 124.27167 | G83: 117.189 | H83: =(271-G83)*0.87 -> 133.81557 | I83: 121.278 | J83: =(230.8-I83)*0.87 -> 95.28414 | K83: 105.096 | L83: =(264.3-K83)*0.87 -> 138.50748 | M83: 52.2 | N83: 109.185 | O83: 135.6 | P83: =265.3-O83 -> 129.7 | Q83: 127.9 | R83: =247.7-Q83 -> 119.8 | S83: 118.3 | T83: =233.9-S83 -> 115.6 | U83: 110.9 | V83: =214-U83 -> 103.1 | W83: =W125 -> 99 | X83: =X125 -> 103 | Y83: =Y125 -> 110 | Z83: =Z125 -> 108.665 | AA83: =AA125 -> 113.3 | AB83: =AB125 -> 111.92495 | AC83: =AC125 -> 116.699 | AD83: =AD125 -> 115.2827 | ... AN83: =AN125 -> 133.64424
B84: Tables | C84: NZ$m | E84: 70.557 | F84: =(161.9-E84)*0.87 -> 79.46841 | G84: 73.95 | H84: =(163.3-G84)*0.87 -> 77.7345 | I84: 74.385 | J84: =(128-I84)*0.87 -> 46.64505 | K84: 54.897 | L84: =(133.1-K84)*0.87 -> 68.03661 | M84: 20.445 | N84: 44.805 | O84: 57.7 | P84: =121.6-O84 -> 63.9 | Q84: 66.4 | R84: =127.6-Q84 -> 61.2 | S84: 57.1 | T84: =114.7-S84 -> 57.6 | U84: 54.5 | V84: =104.4-U84 -> 49.9 | W84: =W154 -> 47 | X84: =X154 -> 48 | Y84: =Y154 -> 49 | Z84: =Z154 -> 49.92 | AA84: =AA154 -> 49.49 | AB84: =AB154 -> 50.4192 | AC84: =AC154 -> 49.9849 | AD84: =AD154 -> 50.923392 | ... AN84: =AN154 -> 53.520997
B85: Premium Tables | C85: NZ$m | O85: 6.4 | P85: =7.2-O85 -> 0.8 | Q85: 12.6 | R85: =19.6-Q85 -> 7 | S85: 5.9 | T85: =9.2-S85 -> 3.3 | U85: -0.8 | V85: =-1.1-U85 -> -0.3 | W85: =W165 -> 3 | X85: =X165 -> 3 | Y85: =Y165 -> 3 | Z85: =Z165 -> 3.12 | AA85: =AA165 -> 3.12 | AB85: =AB165 -> 3.2448 | AC85: =AC165 -> 3.2448 | AD85: =AD165 -> 3.374592 | ... AN85: =AN165 -> 4.1057072
B86: Non Gaming | C86: NZ$m | E86: 83.2 | F86: =170.5-E86 -> 87.3 | G86: 88.1 | H86: =172.3-G86 -> 84.2 | I86: 80.7 | J86: =138.5-I86 -> 57.8 | K86: 46.9 | L86: =90.9-K86 -> 44 | M86: 35 | N86: 35.1 | O86: 58.6 | P86: =123.9-O86 -> 65.3 | Q86: 73.7 | R86: =151.8-Q86 -> 78.1 | S86: 77 | T86: =156.4-S86 -> 79.4 | U86: 83.5 | V86: =181.4-U86 -> 97.9 | W86: =W212 -> 107 | X86: =X212 -> 104 | Y86: =Y212 -> 110 | Z86: =Z212 -> 109.72 | AA86: =AA212 -> 114.4 | AB86: =AB212 -> 114.1088 | AC86: =AC212 -> 118.976 | AD86: =AD212 -> 118.67315 | ... AN86: =AN212 -> 144.38403
B87: Total Domestic | C87: NZ$m | E87: =SUM(E83:E86) -> 263.116 | F87: =SUM(F83:F86) -> 291.04008 | G87: =SUM(G83:G86) -> 279.239 | H87: =SUM(H83:H86) -> 295.75007 | I87: =SUM(I83:I86) -> 276.363 | J87: =SUM(J83:J86) -> 199.72919 | K87: =SUM(K83:K86) -> 206.893 | L87: =SUM(L83:L86) -> 250.54409 | ... R87: =SUM(R83:R86) -> 266.1 | S87: 258.3 | T87: =514.3-S87 -> 256 | U87: 248.1 | V87: =498.6-U87 -> 250.5 | W87: =SUM(W83:W86) -> 256 | X87: =SUM(X83:X86) -> 258 | Y87: =SUM(Y83:Y86) -> 272 | Z87: =SUM(Z83:Z86) -> 271.425 | AA87: =SUM(AA83:AA86) -> 280.31 | AB87: =SUM(AB83:AB86) -> 279.69775 | AC87: =SUM(AC83:AC86) -> 288.9047 | AD87: =SUM(AD83:AD86) -> 288.25383 | ... AN87: =SUM(AN83:AN86) -> 335.65498
S88: =S87-SUM(S83:S86) -> 0 | T88: =T87-SUM(T83:T86) -> 0.1 | U88: =U87-SUM(U83:U86) -> 0 | V88: =V87-SUM(V83:V86) -> -0.1
B89: Hamilton & Queenstown
B90: Slots | C90: NZ$m | E90: 18.531 | F90: =(42.9-E90)*0.87 -> 21.20103 | G90: 19.836 | H90: =(44.5-G90)*0.87 -> 21.45768 | I90: 21.054 | J90: =(41.4-I90)*0.87 -> 17.70102 | K90: 23.055 | L90: =(53-K90)*0.87 -> 26.05215 | M90: 17.661 | N90: 24.099 | O90: 28.2 | P90: =54-O90 -> 25.8 | Q90: 26.4 | R90: =52.3-Q90 -> 25.9 | S90: 26 | T90: =50.7-S90 -> 24.7 | U90: 24.8 | V90: =49.8-U90 -> 25 | W90: =W126 -> 25.296 | X90: =X126 -> 25.5 | Y90: =Y126 -> 26.30784 | Z90: =Z126 -> 26.52 | AA90: =AA126 -> 27.360154 | AB90: =AB126 -> 27.3156 | AC90: =AC126 -> 28.180958 | AD90: =AD126 -> 28.135068 | ... AN90: =AN126 -> 32.616255
B91: Tables | C91: NZ$m | E91: 4.176 | F91: =(9.4-E91)*0.87 -> 4.54488 | G91: 3.741 | H91: =(8.9-G91)*0.87 -> 4.48833 | I91: 4.437 | J91: =(8.4-I91)*0.87 -> 3.44781 | K91: 4.524 | L91: =(11.5-K91)*0.87 -> 6.06912 | M91: 3.741 | N91: 4.959 | O91: 6.6 | P91: =12.5-O91 -> 5.9 | Q91: 6.5 | R91: =13.3-Q91 -> 6.8 | S91: 6.5 | T91: =13.5-S91 -> 7 | U91: 7 | V91: =13.9-U91 -> 6.9 | W91: =W155 -> 6.969 | X91: =X155 -> 6.969 | Y91: =Y155 -> 7.1407 | Z91: =Z155 -> 7.03869 | AA91: =AA155 -> 7.212107 | AB91: =AB155 -> 7.1090769 | AC91: =AC155 -> 7.2842281 | AD91: =AD155 -> 7.1801677 | ... AN91: =AN155 -> 7.5464284
B92: Premium Tables | C92: NZ$m | O92: 1.7 | P92: =0.7-O92 -> -1 | Q92: 0.4 | R92: =1.1-Q92 -> 0.7 | S92: 0.4 | T92: =-0.1-S92 -> -0.5 | U92: 0.1 | V92: =0.1-U92 -> 0 | W92: =W166 -> 0.3 | X92: =X166 -> 0.3 | Y92: =Y166 -> 0.3 | Z92: =Z166 -> 0.312 | AA92: =AA166 -> 0.312 | AB92: =AB166 -> 0.32448 | AC92: =AC166 -> 0.32448 | AD92: =AD166 -> 0.3374592 | ... AN92: =AN166 -> 0.41057072
B93: Non Gaming | C93: NZ$m | E93: 5.3 | F93: 4.6 | G93: 5.2 | H93: 4.7 | I93: 5.5 | J93: 5.1 | K93: 5.9 | L93: 4.6 | M93: 4.7 | N93: 3.8 | O93: 5.7 | P93: =10.7-O93 -> 5 | Q93: 5.4 | R93: =10.4-Q93 -> 5 | S93: 5.4 | T93: =10.1-S93 -> 4.7 | U93: 5.4 | V93: =10-U93 -> 4.6 | W93: =W213 -> 5 | X93: =X213 -> 4.5 | Y93: =Y213 -> 5 | Z93: =Z213 -> 4.5 | AA93: =AA213 -> 5.2 | AB93: =AB213 -> 4.68 | AC93: =AC213 -> 5.408 | AD93: =AD213 -> 4.8672 | ... AN93: =AN213 -> 5.921693
B94: Total Domestic | C94: NZ$m | E94: =SUM(E90:E93) -> 28.007 | F94: =SUM(F90:F93) -> 30.34591 | G94: =SUM(G90:G93) -> 28.777 | H94: =SUM(H90:H93) -> 30.64601 | I94: =SUM(I90:I93) -> 30.991 | J94: =SUM(J90:J93) -> 26.24883 | K94: =SUM(K90:K93) -> 33.479 | L94: =SUM(L90:L93) -> 36.72127 | ... R94: =SUM(R90:R93) -> 38.4 | S94: 38.3 | T94: =74.2-S94 -> 35.9 | U94: 37.4 | V94: =73.9-U94 -> 36.5 | W94: =SUM(W90:W93) -> 37.565 | X94: =SUM(X90:X93) -> 37.269 | Y94: =SUM(Y90:Y93) -> 38.74854 | Z94: =SUM(Z90:Z93) -> 38.37069 | AA94: =SUM(AA90:AA93) -> 40.084261 | AB94: =SUM(AB90:AB93) -> 39.429157 | AC94: =SUM(AC90:AC93) -> 41.197666 | AD94: =SUM(AD90:AD93) -> 40.519895 | ... AN94: =SUM(AN90:AN93) -> 46.494947
S95: =S94-SUM(S90:S93) -> 0 | T95: =T94-SUM(T90:T93) -> 0 | U95: =U94-SUM(U90:U93) -> 0.1 | V95: =V94-SUM(V90:V93) -> 0
B96: Adelaide
B97: Slots | C97: NZ$m | E97: 25.697407 | F97: 23.405227 | G97: 25.476267 | H97: 22.241674 | I97: 25.240766 | J97: 9.7498772 | K97: 24.876795 | L97: 36.236485 | M97: 32.503937 | N97: 38.597977 | O97: 51.6 | P97: =99.8-O97 -> 48.2 | Q97: 46.6 | R97: =97.9-Q97 -> 51.3 | S97: 50.3 | T97: =95.9-S97 -> 45.6 | U97: 50.2 | V97: =103-U97 -> 52.8 | W97: =W127 -> 52 | X97: =X127 -> 52 | Y97: =Y127 -> 44 | Z97: =Z127 -> 44 | AA97: =AA127 -> 46.64 | AB97: =AB127 -> 46.64 | AC97: =AC127 -> 49.4384 | AD97: =AD127 -> 49.4384 | ... AN97: =AN127 -> 62.467835
B98: Tables | C98: NZ$m | E98: 40.17066 | F98: 29.704842 | G98: 39.715854 | H98: 32.140988 | I98: 37.623029 | J98: 14.353445 | K98: 36.929505 | L98: 39.910484 | M98: 34.110236 | N98: 27.447451 | O98: 39.9 | P98: =70.2-O98 -> 30.3 | Q98: 29.1 | R98: =58.1-Q98 -> 29 | S98: 30.3 | T98: =57.5-S98 -> 27.2 | U98: 31.4 | V98: =61.5-U98 -> 30.1 | W98: =W156 -> 29 | X98: =X156 -> 30.1 | Y98: =Y156 -> 25 | Z98: =Z156 -> 25 | AA98: =AA156 -> 26.5 | AB98: =AB156 -> 26.5 | AC98: =AC156 -> 28.09 | AD98: =AD156 -> 28.09 | ... AN98: =AN156 -> 34.128098
B99: Premium Tables | C99: NZ$m | M99: 0 | N99: 0 | O99: 3.6 | P99: =8.5-O99 -> 4.9 | Q99: 5.3 | R99: =11.7-Q99 -> 6.4 | S99: 3.7 | T99: =5.8-S99 -> 2.1 | U99: 1.7 | V99: =1.6-U99 -> -0.1 | W99: =W167 -> 1.7 | X99: =X167 -> 1.7 | Y99: =Y167 -> 1.7 | Z99: =Z167 -> 1.768 | AA99: =AA167 -> 1.768 | AB99: =AB167 -> 1.83872 | AC99: =AC167 -> 1.83872 | AD99: =AD167 -> 1.9122688 | ... AN99: =AN167 -> 2.3265674
B100: Non Gaming | C100: NZ$m | E100: 11.3 | F100: =21.7-E100 -> 10.4 | G100: 10.6 | H100: =19.8-G100 -> 9.2 | I100: 11.4 | J100: =25.8-I100 -> 14.4 | K100: 25.4 | L100: =49.3-K100 -> 23.9 | M100: 23.412073 | N100: 23.720019 | O100: 34.8 | P100: =71.3-O100 -> 36.5 | Q100: 35.799265 | R100: =69-Q100 -> 33.200735 | S100: 38.9 | T100: =72.7-S100 -> 33.8 | U100: 41.1 | V100: =80.4-U100 -> 39.3 | W100: =W214 -> 42.3 | X100: =X214 -> 40.3 | Y100: =Y214 -> 42.3 | Z100: =Z214 -> 40.3 | AA100: =AA214 -> 43.992 | AB100: =AB214 -> 41.912 | AC100: =AC214 -> 45.75168 | AD100: =AD214 -> 43.58848 | ... AN100: =AN214 -> 53.032051
B101: Total Domestic | C101: NZ$m | E101: =SUM(E97:E100) -> 77.168067 | F101: =SUM(F97:F100) -> 63.510069 | G101: =SUM(G97:G100) -> 75.792121 | H101: =SUM(H97:H100) -> 63.582662 | I101: =SUM(I97:I100) -> 74.263795 | J101: =SUM(J97:J100) -> 38.503322 | K101: =SUM(K97:K100) -> 87.2063 | L101: =SUM(L97:L100) -> 100.04697 | ... R101: =SUM(R97:R100) -> 119.90074 | S101: 123.2 | T101: =232-S101 -> 108.8 | U101: 124.5 | V101: =246.6-U101 -> 122.1 | W101: =SUM(W97:W100) -> 125 | X101: =SUM(X97:X100) -> 124.1 | Y101: =SUM(Y97:Y100) -> 113 | Z101: =SUM(Z97:Z100) -> 111.068 | AA101: =SUM(AA97:AA100) -> 118.9 | AB101: =SUM(AB97:AB100) -> 116.89072 | AC101: =SUM(AC97:AC100) -> 125.1188 | AD101: =SUM(AD97:AD100) -> 123.02915 | ... AN101: =SUM(AN97:AN100) -> 151.95455
S102: =S101-SUM(S97:S100) -> 0 | T102: =T101-SUM(T97:T100) -> 0.1 | U102: =U101-SUM(U97:U100) -> 0.1 | V102: =V101-SUM(V97:V100) -> 0
B104: SLOTS REVENUE MODELLING
A106: CUT | B106: Number of Slots
B107: Auckland | C107: # | E107: 1808 | F107: 1808 | G107: 1808 | H107: 1808 | I107: 1808 | J107: 1808 | K107: 1808 | L107: 1808 | M107: 1808 | N107: 1808 | O107: 1808 | P107: 1808 | Q107: 1808 | R107: 1808 | S107: 1715 | T107: =S107 -> 1715 | U107: =T107 -> 1715 | V107: =U107 -> 1715 | W107: =V107 -> 1715 | X107: =W107 -> 1715 | Y107: =X107 -> 1715 | Z107: =Y107 -> 1715 | AA107: =Z107 -> 1715 | ... AN107: =AM107 -> 1715
B108: Hamilton & Queenstown | C108: # | E108: =F108 -> 339 | F108: 339 | G108: =H108 -> 339 | H108: 339 | I108: =J108 -> 339 | J108: 339 | K108: =L108 -> 339 | L108: 339 | M108: 425 | N108: 425 | O108: 425 | P108: 425 | Q108: 425 | R108: 425 | S108: 425 | T108: 425 | U108: 425 | V108: 425 | W108: 425 | X108: 425 | Y108: 425 | Z108: 425 | AA108: 425 | AB108: 425 | AC108: 425 | AD108: 425 | AE108: 425 | AF108: 425 | AG108: 425 | AH108: 425 | AI108: 425 | AJ108: 425 | AK108: 425 | AL108: 425 | AM108: 425 | AN108: 425
B109: Adelaide | C109: # | E109: =F109 -> 828 | F109: 828 | G109: =H109 -> 828 | H109: 828 | I109: =J109 -> 828 | J109: 828 | K109: 1035 | L109: 1080 | M109: =N109 -> 1075 | N109: 1075 | O109: =P109 -> 1080 | P109: 1080 | Q109: =R109 -> 1080 | R109: =S109 -> 1080 | S109: 1080 | T109: =S109 -> 1080 | U109: =T109 -> 1080 | V109: =U109 -> 1080 | W109: =V109 -> 1080 | X109: =W109 -> 1080 | Y109: =X109 -> 1080 | Z109: =Y109 -> 1080 | AA109: =Z109 -> 1080 | ... AN109: =AM109 -> 1080
B110: Allowance
B111: Auckland | C111: # | E111: =F111 -> 1877 | F111: 1877 | G111: =H111 -> 1877 | H111: 1877 | I111: =J111 -> 1877 | J111: 1877 | K111: =L111 -> 1877 | L111: 1877 | M111: =N111 -> 1877 | N111: 1877 | O111: =P111 -> 1877 | P111: 1877 | Q111: 1877 | R111: 1877 | S111: 1877 | T111: 1877 | U111: 1877 | V111: 1877 | W111: 1877 | X111: 1877 | Y111: 1877 | Z111: 1877 | AA111: 1877 | AB111: 1877 | AC111: 1877 | AD111: 1877 | AE111: 1877 | AF111: 1877 | AG111: 1877 | AH111: 1877 | AI111: 1877 | AJ111: 1877 | AK111: 1877 | AL111: 1877 | AM111: 1877 | AN111: 1877
B112: Hamilton & Queenstown | C112: # | E112: =F112 -> 339 | F112: 339 | G112: =H112 -> 339 | H112: 339 | I112: =J112 -> 339 | J112: 339 | K112: =L112 -> 339 | L112: 339 | M112: 425 | N112: 425 | O112: 425 | P112: 425 | Q112: 425 | R112: 425 | S112: 425 | T112: 425 | U112: 425 | V112: 425 | W112: 425 | X112: 425 | Y112: 425 | Z112: 425 | AA112: 425 | AB112: 425 | AC112: 425 | AD112: 425 | AE112: 425 | AF112: 425 | AG112: 425 | AH112: 425 | AI112: 425 | AJ112: 425 | AK112: 425 | AL112: 425 | AM112: 425 | AN112: 425
B113: Adelaide | C113: # | E113: =F113 -> 1500 | F113: 1500 | G113: =H113 -> 1500 | H113: 1500 | I113: =J113 -> 1500 | J113: 1500 | K113: =L113 -> 1500 | L113: 1500 | M113: =N113 -> 1500 | N113: 1500 | O113: =P113 -> 1500 | P113: 1500 | Q113: 1500 | R113: 1500 | S113: 1500 | T113: 1500 | U113: 1500 | V113: 1500 | W113: 1500 | X113: 1500 | Y113: 1500 | Z113: 1500 | AA113: 1500 | AB113: 1500 | AC113: 1500 | AD113: 1500 | AE113: 1500 | AF113: 1500 | AG113: 1500 | AH113: 1500 | AI113: 1500 | AJ113: 1500 | AK113: 1500 | AL113: 1500 | AM113: 1500 | AN113: 1500
B115: Average Daily Revenue per Machine
B116: Auckland | C116: NZ$ | E116: =E125*1000000/E107/E$13 -> 328.7292 | F116: =F125*1000000/F107/F$13 -> 379.74768 | G116: =G125*1000000/G107/G$13 -> 352.2659 | H116: =H125*1000000/H107/H$13 -> 408.9118 | I116: =I125*1000000/I107/I$13 -> 364.55728 | J116: =J125*1000000/J107/J$13 -> 289.56816 | K116: =K125*1000000/K107/K$13 -> 315.91477 | L116: =L125*1000000/L107/L$13 -> 423.24928 | ... V116: =V125*1000000/V107/V$13 -> 332.13601 | W116: 365 | X116: =V116*(1+X120) -> 358.70689 | Y116: =W116*(1+Y120) -> 385.075 | Z116: =X116*(1+Z120) -> 378.43577 | AA116: =Y116*(1+AA120) -> 396.62725 | AB116: =Z116*(1+AB120) -> 389.78884 | AC116: =AA116*(1+AC120) -> 408.52607 | AD116: =AB116*(1+AD120) -> 401.48251 | AE116: =AC116*(1+AE120) -> 420.78185 | ... AN116: =AL116*(1+AN120) -> 465.42827
B117: Hamilton & Queenstown | C117: NZ$ | E117: =E126*1000000/E108/E$13 -> 297.08542 | F117: =F126*1000000/F108/F$13 -> 345.52437 | G117: =G126*1000000/G108/G$13 -> 318.00693 | H117: =H126*1000000/H108/H$13 -> 349.70713 | I117: =I126*1000000/I108/I$13 -> 337.53367 | J117: =J126*1000000/J108/J$13 -> 286.89779 | K117: =K126*1000000/K108/K$13 -> 369.61331 | L117: =L126*1000000/L108/L$13 -> 424.58564 | ... V117: =V126*1000000/V108/V$13 -> 324.99188 | W117: =U117*(1+W121) -> 323.47826 | X117: =V117*(1+X121) -> 331.49171 | Y117: =W117*(1+Y121) -> 336.41739 | Z117: =X117*(1+Z121) -> 344.75138 | AA117: =Y117*(1+AA121) -> 349.87409 | AB117: =Z117*(1+AB121) -> 355.09392 | AC117: =AA117*(1+AC121) -> 360.37031 | AD117: =AB117*(1+AD121) -> 365.74674 | ... AN117: =AL117*(1+AN121) -> 424.00071
B118: Adelaide | C118: A$ | E118: =E127*1000000/E109/E$13 -> 168.67128 | F118: =F127*1000000/F109/F$13 -> 156.17228 | G118: =G127*1000000/G109/G$13 -> 167.21978 | H118: =H127*1000000/H109/H$13 -> 148.40843 | I118: =I127*1000000/I109/I$13 -> 165.67401 | J118: =J127*1000000/J109/J$13 -> 64.698978 | K118: =K127*1000000/K109/K$13 -> 130.62799 | L118: =L127*1000000/L109/L$13 -> 185.37183 | ... V118: =V127*1000000/V109/V$13 -> 270.10436 | W118: 230 | X118: 215 | Y118: 215 | Z118: =X118*(1+Z122) -> 227.9 | AA118: =Y118*(1+AA122) -> 227.9 | AB118: =Z118*(1+AB122) -> 241.574 | AC118: =AA118*(1+AC122) -> 241.574 | AD118: =AB118*(1+AD122) -> 256.06844 | AE118: =AC118*(1+AE122) -> 256.06844 | AF118: =AD118*(1+AF122) -> 271.43255 | AG118: =AE118*(1+AG122) -> 271.43255 | ... AN118: =AL118*(1+AN122) -> 323.55499
B119: ADR Growth rates
B120: Auckland | C120: % | G120: =G116/E116-1 -> 0.071599045 | H120: =H116/F116-1 -> 0.076798678 | I120: =I116/G116-1 -> 0.034892353 | J120: =J116/H116-1 -> -0.29185669 | K120: =K116/I116-1 -> -0.13342898 | L120: =L116/J116-1 -> 0.46165684 | M120: =M116/K116-1 -> -0.50331126 | N120: =N116/L116-1 -> -0.21170322 | ... V120: =V116/T116-1 -> -0.10813149 | W120: 0.08 | X120: 0.08 | Y120: 0.055 | Z120: 0.055 | AA120: 0.03 | AB120: 0.03 | AC120: 0.03 | AD120: 0.03 | AE120: 0.03 | AF120: 0.03 | AG120: 0.03 | AH120: 0.03 | AI120: 0.03 | AJ120: 0.03 | AK120: 0.03 | AL120: 0.03 | AM120: 0.03 | AN120: 0.03
B121: Hamilton & Queenstown | C121: % | G121: =G117/E117-1 -> 0.070422535 | H121: =H117/F117-1 -> 0.012105544 | I121: =I117/G117-1 -> 0.061403509 | J121: =J117/H117-1 -> -0.17960555 | K121: =K117/I117-1 -> 0.095041322 | L121: =L117/J117-1 -> 0.47991949 | M121: =M117/K117-1 -> -0.38897225 | N121: =N117/L117-1 -> -0.26215316 | ... V121: =V117/T117-1 -> 0.012145749 | W121: 0.02 | X121: 0.02 | Y121: 0.04 | Z121: 0.04 | AA121: 0.04 | AB121: 0.03 | AC121: 0.03 | AD121: 0.03 | AE121: 0.03 | AF121: 0.03 | AG121: 0.03 | AH121: 0.03 | AI121: 0.03 | AJ121: 0.03 | AK121: 0.03 | AL121: 0.03 | AM121: 0.03 | AN121: 0.03
B122: Adelaide | C122: % | G122: =G118/E118-1 -> -0.0086055347 | H122: =H118/F118-1 -> -0.049713346 | I122: =I118/G118-1 -> -0.009243942 | J122: =J118/H118-1 -> -0.56404782 | K122: =K118/I118-1 -> -0.211536 | L122: =L118/J118-1 -> 1.8651431 | M122: =M118/K118-1 -> 0.25797912 | N122: =N118/L118-1 -> 0.070123176 | ... V122: =V118/T118-1 -> 0.15789474 | W122: 0 | X122: 0 | Y122: 0.03 | Z122: 0.06 | AA122: 0.06 | AB122: 0.06 | AC122: 0.06 | AD122: 0.06 | AE122: 0.06 | AF122: 0.06 | AG122: 0.06 | AH122: 0.06 | AI122: 0.06 | AJ122: 0.06 | AK122: 0.03 | AL122: 0.03 | AM122: 0.03 | AN122: 0.03
B124: Slots Revenue
B125: Auckland | C125: NZ$m | E125: =E83 -> 109.359 | F125: =F83 -> 124.27167 | G125: =G83 -> 117.189 | H125: =H83 -> 133.81557 | I125: =I83 -> 121.278 | J125: =J83 -> 95.28414 | K125: =K83 -> 105.096 | L125: =L83 -> 138.50748 | ... V125: =V83 -> 103.1 | W125: 99 | X125: 103 | Y125: 110 | Z125: =X125*(1+Z129) -> 108.665 | AA125: =Y125*(1+AA129) -> 113.3 | AB125: =Z125*(1+AB129) -> 111.92495 | AC125: =AA125*(1+AC129) -> 116.699 | AD125: =AB125*(1+AD129) -> 115.2827 | AE125: =AC125*(1+AE129) -> 120.19997 | AF125: =AD125*(1+AF129) -> 118.74118 | AG125: =AE125*(1+AG129) -> 123.80597 | ... AN125: =AL125*(1+AN129) -> 133.64424
B126: Hamilton & Queenstown | C126: NZ$m | E126: =E90 -> 18.531 | F126: =F90 -> 21.20103 | G126: =G90 -> 19.836 | H126: =H90 -> 21.45768 | I126: =I90 -> 21.054 | J126: =J90 -> 17.70102 | K126: =K90 -> 23.055 | L126: =L90 -> 26.05215 | ... V126: =V90 -> 25 | W126: =W108*W117*W$13/1000000 -> 25.296 | X126: =X108*X117*X$13/1000000 -> 25.5 | Y126: =Y108*Y117*Y$13/1000000 -> 26.30784 | Z126: =X126*(1+Z130) -> 26.52 | AA126: =Y126*(1+AA130) -> 27.360154 | AB126: =Z126*(1+AB130) -> 27.3156 | AC126: =AA126*(1+AC130) -> 28.180958 | AD126: =AB126*(1+AD130) -> 28.135068 | AE126: =AC126*(1+AE130) -> 29.026387 | AF126: =AD126*(1+AF130) -> 28.97912 | AG126: =AE126*(1+AG130) -> 29.897179 | ... AN126: =AL126*(1+AN130) -> 32.616255
B127: Adelaide | C127: A$m | E127: =E97 -> 25.697407 | F127: =F97 -> 23.405227 | G127: =G97 -> 25.476267 | H127: =H97 -> 22.241674 | I127: =I97 -> 25.240766 | J127: =J97 -> 9.7498772 | K127: =K97 -> 24.876795 | L127: =L97 -> 36.236485 | ... V127: =V97 -> 52.8 | W127: 52 | X127: 52 | Y127: 44 | Z127: 44 | AA127: =Y127*(1+AA131) -> 46.64 | AB127: =Z127*(1+AB131) -> 46.64 | AC127: =AA127*(1+AC131) -> 49.4384 | AD127: =AB127*(1+AD131) -> 49.4384 | AE127: =AC127*(1+AE131) -> 52.404704 | AF127: =AD127*(1+AF131) -> 52.404704 | AG127: =AE127*(1+AG131) -> 55.548986 | AH127: =AF127*(1+AH131) -> 55.548986 | ... AN127: =AL127*(1+AN131) -> 62.467835
B128: Growth Rates
B129: Auckland | C129: % | G129: =G125/E125-1 -> 0.071599045 | H129: =H125/F125-1 -> 0.076798678 | I129: =I125/G125-1 -> 0.034892353 | J129: =J125/H125-1 -> -0.2879443 | K129: =K125/I125-1 -> -0.13342898 | L129: =L125/J125-1 -> 0.45362576 | M129: =M125/K125-1 -> -0.50331126 | N129: =N125/L125-1 -> -0.21170322 | ... Y129: =Y125/W125-1 -> 0.11111111 | Z129: 0.055 | AA129: 0.03 | AB129: 0.03 | AC129: 0.03 | AD129: 0.03 | AE129: 0.03 | AF129: 0.03 | AG129: 0.03 | AH129: 0.03 | AI129: 0.03 | AJ129: 0.03 | AK129: 0.03 | AL129: 0.03 | AM129: 0.03 | AN129: 0.03
B130: Hamilton & Queenstown | C130: % | G130: =G126/E126-1 -> 0.070422535 | H130: =H126/F126-1 -> 0.012105544 | I130: =I126/G126-1 -> 0.061403509 | J130: =J126/H126-1 -> -0.17507298 | K130: =K126/I126-1 -> 0.095041322 | L130: =L126/J126-1 -> 0.47178807 | M130: =M126/K126-1 -> -0.23396226 | N130: =N126/L126-1 -> -0.07497078 | ... Y130: =Y126/W126-1 -> 0.04 | Z130: 0.04 | AA130: 0.04 | AB130: 0.03 | AC130: 0.03 | AD130: 0.03 | AE130: 0.03 | AF130: 0.03 | AG130: 0.03 | AH130: 0.03 | AI130: 0.03 | AJ130: 0.03 | AK130: 0.03 | AL130: 0.03 | AM130: 0.03 | AN130: 0.03
B131: Adelaide | C131: % | G131: =G127/E127-1 -> -0.0086055347 | H131: =H127/F127-1 -> -0.049713346 | I131: =I127/G127-1 -> -0.009243942 | J131: =J127/H127-1 -> -0.56163924 | K131: =K127/I127-1 -> -0.014419994 | L131: =L127/J127-1 -> 2.7166094 | M131: =M127/K127-1 -> 0.30659668 | N131: =N127/L127-1 -> 0.065168902 | ... Z131: =Z127/X127-1 -> -0.15384615 | AA131: 0.06 | AB131: 0.06 | AC131: 0.06 | AD131: 0.06 | AE131: 0.06 | AF131: 0.06 | AG131: 0.06 | AH131: 0.06 | AI131: 0.06 | AJ131: 0.06 | AK131: 0.03 | AL131: 0.03 | AM131: 0.03 | AN131: 0.03
B133: TABLE GAMES REVENUE MODELLING
A135: CUT | B135: Tables Combined
B136: Auckland | C136: NZ$ | E136: 297 | F136: 297 | G136: 297 | H136: 297 | I136: 297 | J136: 297 | K136: 297 | L136: 297 | M136: 297 | N136: 297 | O136: 297 | P136: 297 | Q136: 297 | R136: 297 | S136: 297 | T136: =R136 -> 297 | U136: =S136 -> 297 | V136: =T136 -> 297 | W136: =U136 -> 297 | X136: =V136 -> 297 | Y136: =W136 -> 297 | Z136: =X136 -> 297 | AA136: =Y136 -> 297 | ... AN136: =AL136 -> 297
B137: Hamilton & Queenstown | C137: NZ$ | E137: 30 | F137: 30 | G137: 30 | H137: 30 | I137: 30 | J137: 30 | K137: 30 | L137: 30 | M137: 30 | N137: 30 | O137: 30 | P137: 30 | Q137: 30 | R137: 30 | S137: 30 | T137: =R137 -> 30 | U137: =S137 -> 30 | V137: =T137 -> 30 | W137: =U137 -> 30 | X137: =V137 -> 30 | Y137: =W137 -> 30 | Z137: =X137 -> 30 | AA137: =Y137 -> 30 | ... AN137: =AL137 -> 30
B138: Adelaide | C138: A$ | E138: 81 | F138: 81 | G138: 81 | H138: 81 | I138: 81 | J138: 81 | K138: 81 | L138: 81 | M138: 81 | N138: 81 | O138: 81 | P138: 81 | Q138: 81 | R138: 81 | S138: 81 | T138: =R138 -> 81 | U138: =S138 -> 81 | V138: =T138 -> 81 | W138: =U138 -> 81 | X138: =V138 -> 81 | Y138: =W138 -> 81 | Z138: =X138 -> 81 | AA138: =Y138 -> 81 | ... AN138: =AL138 -> 81
B139: Allowance
B140: Auckland | C140: # | E140: 1808 | F140: 1808 | G140: 1808 | H140: 1808 | I140: 1808 | J140: 1808 | K140: 1808 | L140: 1808 | M140: 390 | N140: 390 | O140: 390 | P140: 390 | Q140: 390 | R140: 390 | S140: 390 | T140: 390 | U140: 390 | V140: 390 | W140: 390 | X140: 390 | Y140: 390 | Z140: 390 | AA140: 390 | AB140: 390 | AC140: 390 | AD140: 390 | AE140: 390 | AF140: 390 | AG140: 390 | AH140: 390 | AI140: 390 | AJ140: 390 | AK140: 390 | AL140: 390 | AM140: 390 | AN140: 390
B141: Hamilton & Queenstown | C141: # | E141: =F141 -> 339 | F141: 339 | G141: =H141 -> 339 | H141: 339 | I141: =J141 -> 339 | J141: 339 | K141: =L141 -> 339 | L141: 339 | M141: 35 | N141: 35 | O141: 35 | P141: 35 | Q141: 35 | R141: 35 | S141: 35 | T141: 35 | U141: 35 | V141: 35 | W141: 35 | X141: 35 | Y141: 35 | Z141: 35 | AA141: 35 | AB141: 35 | AC141: 35 | AD141: 35 | AE141: 35 | AF141: 35 | AG141: 35 | AH141: 35 | AI141: 35 | AJ141: 35 | AK141: 35 | AL141: 35 | AM141: 35 | AN141: 35
B142: Adelaide | C142: # | E142: =F142 -> 828 | F142: 828 | G142: =H142 -> 828 | H142: 828 | I142: =J142 -> 828 | J142: 828 | K142: 1035 | L142: 1080 | M142: 200 | N142: 200 | O142: 200 | P142: 200 | Q142: 200 | R142: 200 | S142: 200 | T142: 200 | U142: 200 | V142: 200 | W142: 200 | X142: 200 | Y142: 200 | Z142: 200 | AA142: 200 | AB142: 200 | AC142: 200 | AD142: 200 | AE142: 200 | AF142: 200 | AG142: 200 | AH142: 200 | AI142: 200 | AJ142: 200 | AK142: 200 | AL142: 200 | AM142: 200 | AN142: 200
B144: Average Daily Revenue per Table
B145: Auckland | C145: NZ$ | E145: =E154*1000000/E136/E$13 -> 1291.1177 | F145: =F154*1000000/F136/F$13 -> 1478.2895 | G145: =G154*1000000/G136/G$13 -> 1353.206 | H145: =H154*1000000/H136/H$13 -> 1446.0349 | I145: =I154*1000000/I136/I$13 -> 1361.166 | J145: =J154*1000000/J136/J$13 -> 862.93429 | K145: =K154*1000000/K136/K$13 -> 1004.5564 | L145: =L154*1000000/L136/L$13 -> 1265.6326 | ... V145: =V154*1000000/V136/V$13 -> 928.2512 | W145: 1020 | X145: 1080 | Y145: =W145*(1+Y149) -> 1060.8 | Z145: =X145*(1+Z149) -> 1123.2 | AA145: =Y145*(1+AA149) -> 1071.408 | AB145: =Z145*(1+AB149) -> 1134.432 | AC145: =AA145*(1+AC149) -> 1082.1221 | AD145: =AB145*(1+AD149) -> 1145.7763 | AE145: =AC145*(1+AE149) -> 1092.9433 | AF145: =AD145*(1+AF149) -> 1157.2341 | ... AN145: =AL145*(1+AN149) -> 1204.2224
B146: Hamilton & Queenstown | C146: NZ$ | E146: =E155*1000000/E137/E$13 -> 756.52174 | F146: =F155*1000000/F137/F$13 -> 836.99448 | G146: =G155*1000000/G137/G$13 -> 677.71739 | H146: =H155*1000000/H137/H$13 -> 826.58011 | I146: =I155*1000000/I137/I$13 -> 803.80435 | J146: =J155*1000000/J137/J$13 -> 631.46703 | K146: =K155*1000000/K137/K$13 -> 819.56522 | L146: =L155*1000000/L137/L$13 -> 1117.7017 | ... V146: =V155*1000000/V137/V$13 -> 1270.7182 | W146: =U146*(1+W150) -> 1280.7971 | X146: =V146*(1+X150) -> 1283.4254 | Y146: =W146*(1+Y150) -> 1293.6051 | Z146: =X146*(1+Z150) -> 1296.2597 | AA146: =Y146*(1+AA150) -> 1306.5411 | AB146: =Z146*(1+AB150) -> 1309.2223 | AC146: =AA146*(1+AC150) -> 1319.6065 | AD146: =AB146*(1+AD150) -> 1322.3145 | ... AN146: =AL146*(1+AN150) -> 1389.7658
B147: Adelaide | C147: NZ$ | E147: =E156*1000000/E138/E$13 -> 2695.2939 | F147: =F156*1000000/F138/F$13 -> 2026.113 | G147: =G156*1000000/G138/G$13 -> 2664.7782 | H147: =H156*1000000/H138/H$13 -> 2192.278 | I147: =I156*1000000/I138/I$13 -> 2524.3578 | J147: =J156*1000000/J138/J$13 -> 973.643 | K147: =K156*1000000/K138/K$13 -> 2477.8251 | L147: =L156*1000000/L138/L$13 -> 2722.2211 | ... V147: =V156*1000000/V138/V$13 -> 2053.066 | W147: 1950 | X147: =V147*(1+X151) -> 2053.066 | Y147: =W147*(1+Y151) -> 1969.5 | Z147: =X147*(1+Z151) -> 2176.2499 | AA147: =Y147*(1+AA151) -> 2087.67 | AB147: =Z147*(1+AB151) -> 2306.8249 | AC147: =AA147*(1+AC151) -> 2212.9302 | AD147: =AB147*(1+AD151) -> 2445.2344 | AE147: =AC147*(1+AE151) -> 2345.706 | ... AN147: =AL147*(1+AN151) -> 2970.8508
B148: ADR growth rates
B149: Auckland | G149: =G145/E145-1 -> 0.048088779 | H149: =H145/F145-1 -> -0.021818859 | I149: =I145/G145-1 -> 0.0058823529 | J149: =J145/H145-1 -> -0.40324105 | K149: =K145/I145-1 -> -0.2619883 | L149: =L145/J145-1 -> 0.46666158 | M149: =M145/K145-1 -> -0.62757528 | N149: =N145/L145-1 -> -0.34145749 | ... X149: =X145/V145-1 -> 0.16347816 | Y149: 0.04 | Z149: 0.04 | AA149: 0.01 | AB149: 0.01 | AC149: 0.01 | AD149: 0.01 | AE149: 0.01 | AF149: 0.01 | AG149: 0.01 | AH149: 0.01 | AI149: 0.01 | AJ149: 0.01 | AK149: 0.01 | AL149: 0.01 | AM149: 0.01 | AN149: 0.01
B150: Hamilton & Queenstown | G150: =G146/E146-1 -> -0.10416667 | H150: =H146/F146-1 -> -0.012442573 | I150: =I146/G146-1 -> 0.18604651 | J150: =J146/H146-1 -> -0.2360486 | K150: =K146/I146-1 -> 0.019607843 | L150: =L146/J146-1 -> 0.77000793 | M150: =M146/K146-1 -> -0.17307692 | N150: =N146/L146-1 -> -0.18291284 | ... V150: =V146/T146-1 -> -0.014285714 | W150: 0.01 | X150: 0.01 | Y150: 0.01 | Z150: 0.01 | AA150: 0.01 | AB150: 0.01 | AC150: 0.01 | AD150: 0.01 | AE150: 0.01 | AF150: 0.01 | AG150: 0.01 | AH150: 0.01 | AI150: 0.01 | AJ150: 0.01 | AK150: 0.01 | AL150: 0.01 | AM150: 0.01 | AN150: 0.01
B151: Adelaide | G151: =G147/E147-1 -> -0.011321836 | H151: =H147/F147-1 -> 0.082011728 | I151: =I147/G147-1 -> -0.052694955 | J151: =J147/H147-1 -> -0.55587613 | K151: =K147/I147-1 -> -0.018433493 | L151: =L147/J147-1 -> 1.795913 | M151: =M147/K147-1 -> -0.076341906 | N151: =N147/L147-1 -> -0.31227467 | ... V151: =V147/T147-1 -> 0.10661765 | W151: 0 | X151: 0 | Y151: 0.01 | Z151: 0.06 | AA151: 0.06 | AB151: 0.06 | AC151: 0.06 | AD151: 0.06 | AE151: 0.06 | AF151: 0.06 | AG151: 0.06 | AH151: 0.06 | AI151: 0.06 | AJ151: 0.06 | AK151: 0.01 | AL151: 0.01 | AM151: 0.01 | AN151: 0.01
B153: Table Revenue
B154: Auckland | C154: NZ$m | E154: =E84 -> 70.557 | F154: =F84 -> 79.46841 | G154: =G84 -> 73.95 | H154: =H84 -> 77.7345 | I154: =I84 -> 74.385 | J154: =J84 -> 46.64505 | K154: =K84 -> 54.897 | L154: =L84 -> 68.03661 | ... V154: =V84 -> 49.9 | W154: 47 | X154: 48 | Y154: 49 | Z154: =X154*(1+Z158) -> 49.92 | AA154: =Y154*(1+AA158) -> 49.49 | AB154: =Z154*(1+AB158) -> 50.4192 | AC154: =AA154*(1+AC158) -> 49.9849 | AD154: =AB154*(1+AD158) -> 50.923392 | AE154: =AC154*(1+AE158) -> 50.484749 | AF154: =AD154*(1+AF158) -> 51.432626 | AG154: =AE154*(1+AG158) -> 50.989596 | ... AN154: =AL154*(1+AN158) -> 53.520997
B155: Hamilton & Queenstown | C155: NZ$m | E155: =E91 -> 4.176 | F155: =F91 -> 4.54488 | G155: =G91 -> 3.741 | H155: =H91 -> 4.48833 | I155: =I91 -> 4.437 | J155: =J91 -> 3.44781 | K155: =K91 -> 4.524 | L155: =L91 -> 6.06912 | ... V155: =V91 -> 6.9 | W155: 6.969 | X155: 6.969 | Y155: 7.1407 | Z155: =X155*(1+Z159) -> 7.03869 | AA155: =Y155*(1+AA159) -> 7.212107 | AB155: =Z155*(1+AB159) -> 7.1090769 | AC155: =AA155*(1+AC159) -> 7.2842281 | AD155: =AB155*(1+AD159) -> 7.1801677 | AE155: =AC155*(1+AE159) -> 7.3570704 | AF155: =AD155*(1+AF159) -> 7.2519693 | AG155: =AE155*(1+AG159) -> 7.4306411 | ... AN155: =AL155*(1+AN159) -> 7.5464284
B156: Adelaide | C156: NZ$m | E156: =E98 -> 40.17066 | F156: =F98 -> 29.704842 | G156: =G98 -> 39.715854 | H156: =H98 -> 32.140988 | I156: =I98 -> 37.623029 | J156: =J98 -> 14.353445 | K156: =K98 -> 36.929505 | L156: =L98 -> 39.910484 | ... V156: =V98 -> 30.1 | W156: 29 | X156: 30.1 | Y156: 25 | Z156: 25 | AA156: =Y156*(1+AA160) -> 26.5 | AB156: =Z156*(1+AB160) -> 26.5 | AC156: =AA156*(1+AC160) -> 28.09 | AD156: =AB156*(1+AD160) -> 28.09 | AE156: =AC156*(1+AE160) -> 29.7754 | AF156: =AD156*(1+AF160) -> 29.7754 | AG156: =AE156*(1+AG160) -> 31.561924 | AH156: =AF156*(1+AH160) -> 31.561924 | ... AN156: =AL156*(1+AN160) -> 34.128098
B157: Growth Rates
B158: Auckland | C158: NZ$m | G158: =G154/E154-1 -> 0.048088779 | H158: =H154/F154-1 -> -0.021818859 | I158: =I154/G154-1 -> 0.0058823529 | J158: =J154/H154-1 -> -0.39994404 | K158: =K154/I154-1 -> -0.2619883 | L158: =L154/J154-1 -> 0.458603 | M158: =M154/K154-1 -> -0.62757528 | N158: =N154/L154-1 -> -0.34145749 | ... Y158: =Y154/W154-1 -> 0.042553191 | Z158: 0.04 | AA158: 0.01 | AB158: 0.01 | AC158: 0.01 | AD158: 0.01 | AE158: 0.01 | AF158: 0.01 | AG158: 0.01 | AH158: 0.01 | AI158: 0.01 | AJ158: 0.01 | AK158: 0.01 | AL158: 0.01 | AM158: 0.01 | AN158: 0.01
...

Sheet FY
B2: SKC | C2: 2018 | D2: =C2+1 -> 2019 | E2: =D2+1 -> 2020 | F2: =E2+1 -> 2021 | G2: =F2+1 -> 2022 | H2: =G2+1 -> 2023 | I2: =H2+1 -> 2024 | J2: =I2+1 -> 2025 | K2: =J2+1 -> 2026 | ... S2: =R2+1 -> 2034
C3: 43281 | D3: =EOMONTH(C3,12) -> 43646 | E3: =EOMONTH(D3,12) -> 44012 | F3: =EOMONTH(E3,12) -> 44377 | G3: =EOMONTH(F3,12) -> 44742 | H3: =EOMONTH(G3,12) -> 45107 | I3: =EOMONTH(H3,12) -> 45473 | J3: =EOMONTH(I3,12) -> 45838 | K3: =EOMONTH(J3,12) -> 46203 | ... S3: =EOMONTH(R3,12) -> 49125 | U3: COMMENTS
A5: X | B5: SEGMENTS - NORMALISED | C5: 2018A | D5: 2019A | E5: 2020A | F5: 2021 | G5: 2022 | H5: 2023 | I5: 2024 | J5: 2025 | K5: 2026 | L5: 2027 | M5: 2028 | N5: 2029 | O5: 2030 | P5: 2031 | Q5: 2032 | R5: 2033 | S5: 2034 | U5: <<< POST RESTATEMENT
B6: Auckland | D6: =SUMIFS(HY!$G306:$AN306,HY!$G$9:$AN$9,FY!D$2) -> 550.4 | E6: =SUMIFS(HY!$G306:$AN306,HY!$G$9:$AN$9,FY!E$2) -> 450.9 | F6: =SUMIFS(HY!$G306:$AN306,HY!$G$9:$AN$9,FY!F$2) -> 436.7 | G6: =SUMIFS(HY!$G306:$AN306,HY!$G$9:$AN$9,FY!G$2) -> 296.8 | H6: =SUMIFS(HY!$G306:$AN306,HY!$G$9:$AN$9,FY!H$2) -> 518 | I6: =SUMIFS(HY!$G306:$AN306,HY!$G$9:$AN$9,FY!I$2) -> 546.7 | J6: =SUMIFS(HY!$G306:$AN306,HY!$G$9:$AN$9,FY!J$2) -> 514.3 | K6: =SUMIFS(HY!$G306:$AN306,HY!$G$9:$AN$9,FY!K$2) -> 498.6 | ... S6: =SUMIFS(HY!$G306:$AN306,HY!$G$9:$AN$9,FY!S$2) -> 651.86267
B7: Hamilton & Queenstown | D7: =SUMIFS(HY!$G307:$AN307,HY!$G$9:$AN$9,FY!D$2) -> 59.42301 | E7: =SUMIFS(HY!$G307:$AN307,HY!$G$9:$AN$9,FY!E$2) -> 57.23983 | F7: =SUMIFS(HY!$G307:$AN307,HY!$G$9:$AN$9,FY!F$2) -> 70.20027 | G7: =SUMIFS(HY!$G307:$AN307,HY!$G$9:$AN$9,FY!G$2) -> 58.96 | H7: =SUMIFS(HY!$G307:$AN307,HY!$G$9:$AN$9,FY!H$2) -> 77.9 | I7: =SUMIFS(HY!$G307:$AN307,HY!$G$9:$AN$9,FY!I$2) -> 77.1 | J7: =SUMIFS(HY!$G307:$AN307,HY!$G$9:$AN$9,FY!J$2) -> 74.2 | K7: =SUMIFS(HY!$G307:$AN307,HY!$G$9:$AN$9,FY!K$2) -> 73.9 | ... S7: =SUMIFS(HY!$G307:$AN307,HY!$G$9:$AN$9,FY!S$2) -> 91.230798
B8: Adelaide | D8: =SUMIFS(HY!$G308:$AN308,HY!$G$9:$AN$9,FY!D$2) -> 139.37478 | E8: =SUMIFS(HY!$G308:$AN308,HY!$G$9:$AN$9,FY!E$2) -> 112.76712 | F8: =SUMIFS(HY!$G308:$AN308,HY!$G$9:$AN$9,FY!F$2) -> 187.25327 | G8: =SUMIFS(HY!$G308:$AN308,HY!$G$9:$AN$9,FY!G$2) -> 179.79169 | H8: =SUMIFS(HY!$G308:$AN308,HY!$G$9:$AN$9,FY!H$2) -> 249.8 | I8: =SUMIFS(HY!$G308:$AN308,HY!$G$9:$AN$9,FY!I$2) -> 236.7 | J8: =SUMIFS(HY!$G308:$AN308,HY!$G$9:$AN$9,FY!J$2) -> 232 | K8: =SUMIFS(HY!$G308:$AN308,HY!$G$9:$AN$9,FY!K$2) -> 246.6 | ... S8: =SUMIFS(HY!$G308:$AN308,HY!$G$9:$AN$9,FY!S$2) -> 297.78064
B9: Online (from segments) | D9: =SUMIFS(HY!$G309:$AN309,HY!$G$9:$AN$9,FY!D$2) -> 0 | E9: =SUMIFS(HY!$G309:$AN309,HY!$G$9:$AN$9,FY!E$2) -> 4.5 | F9: =SUMIFS(HY!$G309:$AN309,HY!$G$9:$AN$9,FY!F$2) -> 13.1 | G9: =SUMIFS(HY!$G309:$AN309,HY!$G$9:$AN$9,FY!G$2) -> 16.9 | H9: =SUMIFS(HY!$G309:$AN309,HY!$G$9:$AN$9,FY!H$2) -> 15.4 | I9: =SUMIFS(HY!$G309:$AN309,HY!$G$9:$AN$9,FY!I$2) -> 9.3 | J9: =SUMIFS(HY!$G309:$AN309,HY!$G$9:$AN$9,FY!J$2) -> 4.1 | K9: =SUMIFS(HY!$G309:$AN309,HY!$G$9:$AN$9,FY!K$2) -> 2.8 | ... S9: =SUMIFS(HY!$G309:$AN309,HY!$G$9:$AN$9,FY!S$2) -> 51.46641
B10: Other (balancing) | D10: =SUMIFS(HY!$G310:$AN310,HY!$G$9:$AN$9,FY!D$2) -> 188.58893 | E10: =SUMIFS(HY!$G310:$AN310,HY!$G$9:$AN$9,FY!E$2) -> 79.826988 | F10: =SUMIFS(HY!$G310:$AN310,HY!$G$9:$AN$9,FY!F$2) -> 24.382942 | G10: =SUMIFS(HY!$G310:$AN310,HY!$G$9:$AN$9,FY!G$2) -> 22.96835 | H10: =SUMIFS(HY!$G310:$AN310,HY!$G$9:$AN$9,FY!H$2) -> 1.5 | I10: =SUMIFS(HY!$G310:$AN310,HY!$G$9:$AN$9,FY!I$2) -> 0.7 | J10: =SUMIFS(HY!$G310:$AN310,HY!$G$9:$AN$9,FY!J$2) -> 0.6 | K10: =SUMIFS(HY!$G310:$AN310,HY!$G$9:$AN$9,FY!K$2) -> 0.8 | ... S10: =SUMIFS(HY!$G310:$AN310,HY!$G$9:$AN$9,FY!S$2) -> 0
B11: Normalised Revenue | D11: =SUMIFS(HY!$G311:$AN311,HY!$G$9:$AN$9,FY!D$2) -> 937.78672 | E11: =SUMIFS(HY!$G311:$AN311,HY!$G$9:$AN$9,FY!E$2) -> 705.23394 | F11: =SUMIFS(HY!$G311:$AN311,HY!$G$9:$AN$9,FY!F$2) -> 731.63648 | G11: =SUMIFS(HY!$G311:$AN311,HY!$G$9:$AN$9,FY!G$2) -> 575.42004 | H11: =SUMIFS(HY!$G311:$AN311,HY!$G$9:$AN$9,FY!H$2) -> 862.6 | I11: =SUMIFS(HY!$G311:$AN311,HY!$G$9:$AN$9,FY!I$2) -> 870.5 | J11: =SUMIFS(HY!$G311:$AN311,HY!$G$9:$AN$9,FY!J$2) -> 825.2 | K11: =SUMIFS(HY!$G311:$AN311,HY!$G$9:$AN$9,FY!K$2) -> 822.7 | ... S11: =SUMIFS(HY!$G311:$AN311,HY!$G$9:$AN$9,FY!S$2) -> 1092.3405
B13: Auckland | D13: =SUMIFS(HY!$G319:$AN319,HY!$G$9:$AN$9,FY!D$2) -> 267.4 | E13: =SUMIFS(HY!$G319:$AN319,HY!$G$9:$AN$9,FY!E$2) -> 193.9 | F13: =SUMIFS(HY!$G319:$AN319,HY!$G$9:$AN$9,FY!F$2) -> 203.4 | G13: =SUMIFS(HY!$G319:$AN319,HY!$G$9:$AN$9,FY!G$2) -> 100.9 | H13: =SUMIFS(HY!$G319:$AN319,HY!$G$9:$AN$9,FY!H$2) -> 251.5 | I13: =SUMIFS(HY!$G319:$AN319,HY!$G$9:$AN$9,FY!I$2) -> 237 | J13: =SUMIFS(HY!$G319:$AN319,HY!$G$9:$AN$9,FY!J$2) -> 209.6 | K13: =SUMIFS(HY!$G319:$AN319,HY!$G$9:$AN$9,FY!K$2) -> 179.8 | ... S13: =SUMIFS(HY!$G319:$AN319,HY!$G$9:$AN$9,FY!S$2) -> 243.3139
B14: Hamilton & Queenstown | D14: =SUMIFS(HY!$G320:$AN320,HY!$G$9:$AN$9,FY!D$2) -> 29.2 | E14: =SUMIFS(HY!$G320:$AN320,HY!$G$9:$AN$9,FY!E$2) -> 26.6 | F14: =SUMIFS(HY!$G320:$AN320,HY!$G$9:$AN$9,FY!F$2) -> 38.4 | G14: =SUMIFS(HY!$G320:$AN320,HY!$G$9:$AN$9,FY!G$2) -> 27.5 | H14: =SUMIFS(HY!$G320:$AN320,HY!$G$9:$AN$9,FY!H$2) -> 39.3 | I14: =SUMIFS(HY!$G320:$AN320,HY!$G$9:$AN$9,FY!I$2) -> 35 | J14: =SUMIFS(HY!$G320:$AN320,HY!$G$9:$AN$9,FY!J$2) -> 33.7 | K14: =SUMIFS(HY!$G320:$AN320,HY!$G$9:$AN$9,FY!K$2) -> 31.4 | ... S14: =SUMIFS(HY!$G320:$AN320,HY!$G$9:$AN$9,FY!S$2) -> 40.780371
B15: Adelaide | D15: =SUMIFS(HY!$G321:$AN321,HY!$G$9:$AN$9,FY!D$2) -> 22.549524 | E15: =SUMIFS(HY!$G321:$AN321,HY!$G$9:$AN$9,FY!E$2) -> 11.856147 | F15: =SUMIFS(HY!$G321:$AN321,HY!$G$9:$AN$9,FY!F$2) -> 44.365029 | G15: =SUMIFS(HY!$G321:$AN321,HY!$G$9:$AN$9,FY!G$2) -> 21.610198 | H15: =SUMIFS(HY!$G321:$AN321,HY!$G$9:$AN$9,FY!H$2) -> 36.1 | I15: =SUMIFS(HY!$G321:$AN321,HY!$G$9:$AN$9,FY!I$2) -> 39.6 | J15: =SUMIFS(HY!$G321:$AN321,HY!$G$9:$AN$9,FY!J$2) -> 31.1 | K15: =SUMIFS(HY!$G321:$AN321,HY!$G$9:$AN$9,FY!K$2) -> 22.8 | ... S15: =SUMIFS(HY!$G321:$AN321,HY!$G$9:$AN$9,FY!S$2) -> 43.967352
B16: Online (from segments) | D16: =SUMIFS(HY!$G322:$AN322,HY!$G$9:$AN$9,FY!D$2) -> 0 | E16: =SUMIFS(HY!$G322:$AN322,HY!$G$9:$AN$9,FY!E$2) -> 2.2 | F16: =SUMIFS(HY!$G322:$AN322,HY!$G$9:$AN$9,FY!F$2) -> 9.1 | G16: =SUMIFS(HY!$G322:$AN322,HY!$G$9:$AN$9,FY!G$2) -> 12.9 | H16: =SUMIFS(HY!$G322:$AN322,HY!$G$9:$AN$9,FY!H$2) -> 10.7 | I16: =SUMIFS(HY!$G322:$AN322,HY!$G$9:$AN$9,FY!I$2) -> 3.6 | J16: =SUMIFS(HY!$G322:$AN322,HY!$G$9:$AN$9,FY!J$2) -> -1.8 | K16: =SUMIFS(HY!$G322:$AN322,HY!$G$9:$AN$9,FY!K$2) -> -6.4 | ... S16: =SUMIFS(HY!$G322:$AN322,HY!$G$9:$AN$9,FY!S$2) -> 20.586564
B17: Corporate Costs | D17: =SUMIFS(HY!$G323:$AN323,HY!$G$9:$AN$9,FY!D$2) -> -33.8 | E17: =SUMIFS(HY!$G323:$AN323,HY!$G$9:$AN$9,FY!E$2) -> -31.5 | F17: =SUMIFS(HY!$G323:$AN323,HY!$G$9:$AN$9,FY!F$2) -> -37.9 | G17: =SUMIFS(HY!$G323:$AN323,HY!$G$9:$AN$9,FY!G$2) -> -24.7 | H17: =SUMIFS(HY!$G323:$AN323,HY!$G$9:$AN$9,FY!H$2) -> -37.2 | I17: =SUMIFS(HY!$G323:$AN323,HY!$G$9:$AN$9,FY!I$2) -> -37.9 | J17: =SUMIFS(HY!$G323:$AN323,HY!$G$9:$AN$9,FY!J$2) -> -39.5 | K17: =SUMIFS(HY!$G323:$AN323,HY!$G$9:$AN$9,FY!K$2) -> -46.8 | ... S17: =SUMIFS(HY!$G323:$AN323,HY!$G$9:$AN$9,FY!S$2) -> -72.550098
B18: Other (balancing) | D18: =SUMIFS(HY!$G324:$AN324,HY!$G$9:$AN$9,FY!D$2) -> 36.850476 | E18: =SUMIFS(HY!$G324:$AN324,HY!$G$9:$AN$9,FY!E$2) -> -2.3561471 | F18: =SUMIFS(HY!$G324:$AN324,HY!$G$9:$AN$9,FY!F$2) -> -8.7650288 | G18: =SUMIFS(HY!$G324:$AN324,HY!$G$9:$AN$9,FY!G$2) -> -0.31019807 | H18: =SUMIFS(HY!$G324:$AN324,HY!$G$9:$AN$9,FY!H$2) -> 1.4 | I18: =SUMIFS(HY!$G324:$AN324,HY!$G$9:$AN$9,FY!I$2) -> 0.5 | J18: =SUMIFS(HY!$G324:$AN324,HY!$G$9:$AN$9,FY!J$2) -> 0.6 | K18: =SUMIFS(HY!$G324:$AN324,HY!$G$9:$AN$9,FY!K$2) -> 0.8 | ... S18: =SUMIFS(HY!$G324:$AN324,HY!$G$9:$AN$9,FY!S$2) -> 0
B19: Normalised EBITDA | D19: =SUMIFS(HY!$G325:$AN325,HY!$G$9:$AN$9,FY!D$2) -> 322.2 | E19: =SUMIFS(HY!$G325:$AN325,HY!$G$9:$AN$9,FY!E$2) -> 200.7 | F19: =SUMIFS(HY!$G325:$AN325,HY!$G$9:$AN$9,FY!F$2) -> 248.6 | G19: =SUMIFS(HY!$G325:$AN325,HY!$G$9:$AN$9,FY!G$2) -> 137.9 | H19: =SUMIFS(HY!$G325:$AN325,HY!$G$9:$AN$9,FY!H$2) -> 301.8 | I19: =SUMIFS(HY!$G325:$AN325,HY!$G$9:$AN$9,FY!I$2) -> 277.8 | J19: =SUMIFS(HY!$G325:$AN325,HY!$G$9:$AN$9,FY!J$2) -> 233.7 | K19: =SUMIFS(HY!$G325:$AN325,HY!$G$9:$AN$9,FY!K$2) -> 181.6 | ... S19: =SUMIFS(HY!$G325:$AN325,HY!$G$9:$AN$9,FY!S$2) -> 276.09809
A21: X | B21: P&L - NORMALISED | C21: 2018A | D21: 2019A | E21: 2020A | F21: 2021 | G21: 2022 | H21: 2023 | I21: 2024 | J21: 2025 | K21: 2026 | L21: 2027 | M21: 2028 | N21: 2029 | O21: 2030 | P21: 2030 | Q21: 2030 | R21: 2030 | S21: 2030
B22: Sales Revenue | D22: =SUMIFS(HY!$G311:$AN311,HY!$G$9:$AN$9,FY!D$2) -> 937.78672 | E22: =SUMIFS(HY!$G311:$AN311,HY!$G$9:$AN$9,FY!E$2) -> 705.23394 | F22: =SUMIFS(HY!$G311:$AN311,HY!$G$9:$AN$9,FY!F$2) -> 731.63648 | G22: =SUMIFS(HY!$G311:$AN311,HY!$G$9:$AN$9,FY!G$2) -> 575.42004 | H22: =SUMIFS(HY!$G311:$AN311,HY!$G$9:$AN$9,FY!H$2) -> 862.6 | I22: =SUMIFS(HY!$G311:$AN311,HY!$G$9:$AN$9,FY!I$2) -> 870.5 | J22: =SUMIFS(HY!$G311:$AN311,HY!$G$9:$AN$9,FY!J$2) -> 825.2 | K22: =SUMIFS(HY!$G311:$AN311,HY!$G$9:$AN$9,FY!K$2) -> 822.7 | ... S22: =SUMIFS(HY!$G311:$AN311,HY!$G$9:$AN$9,FY!S$2) -> 1092.3405
B23: Other Income | D23: =SUMIFS(HY!$G$517:$AN$517,HY!$G$9:$AN$9,FY!D$2) -> 0 | E23: =SUMIFS(HY!$G$517:$AN$517,HY!$G$9:$AN$9,FY!E$2) -> 0 | F23: =SUMIFS(HY!$G$517:$AN$517,HY!$G$9:$AN$9,FY!F$2) -> 0 | G23: =SUMIFS(HY!$G$517:$AN$517,HY!$G$9:$AN$9,FY!G$2) -> 0 | H23: =SUMIFS(HY!$G$517:$AN$517,HY!$G$9:$AN$9,FY!H$2) -> 0 | I23: =SUMIFS(HY!$G$517:$AN$517,HY!$G$9:$AN$9,FY!I$2) -> 0 | J23: =SUMIFS(HY!$G$517:$AN$517,HY!$G$9:$AN$9,FY!J$2) -> 0 | K23: =SUMIFS(HY!$G$517:$AN$517,HY!$G$9:$AN$9,FY!K$2) -> 0 | ... S23: =SUMIFS(HY!$G$517:$AN$517,HY!$G$9:$AN$9,FY!S$2) -> 0
B24: ----- | D24: ----- | E24: ----- | F24: ----- | G24: ----- | H24: ----- | I24: ----- | J24: ----- | K24: ----- | L24: ----- | M24: ----- | N24: ----- | O24: ----- | P24: ----- | Q24: ----- | R24: ----- | S24: -----
B25: Total revenue | D25: =D23+D22 -> 937.78672 | E25: =E23+E22 -> 705.23394 | F25: =F23+F22 -> 731.63648 | G25: =G23+G22 -> 575.42004 | H25: =H23+H22 -> 862.6 | I25: =I23+I22 -> 870.5 | J25: =J23+J22 -> 825.2 | K25: =K23+K22 -> 822.7 | ... S25: =S23+S22 -> 1092.3405
B26: COGS | D26: =SUMIFS(HY!$G$518:$AN$518,HY!$G$9:$AN$9,FY!D$2) -> 0 | E26: =SUMIFS(HY!$G$518:$AN$518,HY!$G$9:$AN$9,FY!E$2) -> 0 | F26: =SUMIFS(HY!$G$518:$AN$518,HY!$G$9:$AN$9,FY!F$2) -> 0 | G26: =SUMIFS(HY!$G$518:$AN$518,HY!$G$9:$AN$9,FY!G$2) -> 0 | H26: =SUMIFS(HY!$G$518:$AN$518,HY!$G$9:$AN$9,FY!H$2) -> 0 | I26: =SUMIFS(HY!$G$518:$AN$518,HY!$G$9:$AN$9,FY!I$2) -> 0 | J26: =SUMIFS(HY!$G$518:$AN$518,HY!$G$9:$AN$9,FY!J$2) -> 0 | K26: =SUMIFS(HY!$G$518:$AN$518,HY!$G$9:$AN$9,FY!K$2) -> 0 | ... S26: =SUMIFS(HY!$G$518:$AN$518,HY!$G$9:$AN$9,FY!S$2) -> 0
B27: OPEX | D27: =SUMIFS(HY!$G$313:$AN$313,HY!$G$9:$AN$9,FY!D$2) -> -615.58672 | E27: =SUMIFS(HY!$G$313:$AN$313,HY!$G$9:$AN$9,FY!E$2) -> -504.53394 | F27: =SUMIFS(HY!$G$313:$AN$313,HY!$G$9:$AN$9,FY!F$2) -> -483.03648 | G27: =SUMIFS(HY!$G$313:$AN$313,HY!$G$9:$AN$9,FY!G$2) -> -437.52004 | H27: =SUMIFS(HY!$G$313:$AN$313,HY!$G$9:$AN$9,FY!H$2) -> -560.8 | I27: =SUMIFS(HY!$G$313:$AN$313,HY!$G$9:$AN$9,FY!I$2) -> -592.7 | J27: =SUMIFS(HY!$G$313:$AN$313,HY!$G$9:$AN$9,FY!J$2) -> -591.5 | K27: =SUMIFS(HY!$G$313:$AN$313,HY!$G$9:$AN$9,FY!K$2) -> -641.1 | ... S27: =SUMIFS(HY!$G$313:$AN$313,HY!$G$9:$AN$9,FY!S$2) -> -816.24242
B28: ----- | D28: ----- | E28: ----- | F28: ----- | G28: ----- | H28: ----- | I28: ----- | J28: ----- | K28: ----- | L28: ----- | M28: ----- | N28: ----- | O28: ----- | P28: ----- | Q28: ----- | R28: ----- | S28: -----
B29: EBITDA | D29: =SUMIFS(HY!$G$325:$AN$325,HY!$G$9:$AN$9,FY!D$2) -> 322.2 | E29: =SUMIFS(HY!$G$325:$AN$325,HY!$G$9:$AN$9,FY!E$2) -> 200.7 | F29: =SUMIFS(HY!$G$325:$AN$325,HY!$G$9:$AN$9,FY!F$2) -> 248.6 | G29: =SUMIFS(HY!$G$325:$AN$325,HY!$G$9:$AN$9,FY!G$2) -> 137.9 | H29: =SUMIFS(HY!$G$325:$AN$325,HY!$G$9:$AN$9,FY!H$2) -> 301.8 | I29: =SUMIFS(HY!$G$325:$AN$325,HY!$G$9:$AN$9,FY!I$2) -> 277.8 | J29: =SUMIFS(HY!$G$325:$AN$325,HY!$G$9:$AN$9,FY!J$2) -> 233.7 | K29: =SUMIFS(HY!$G$325:$AN$325,HY!$G$9:$AN$9,FY!K$2) -> 181.6 | ... S29: =SUMIFS(HY!$G$325:$AN$325,HY!$G$9:$AN$9,FY!S$2) -> 276.09809
B30: Depreciation | D30: =SUMIFS(HY!$G$524:$AN$524,HY!$G$9:$AN$9,FY!D$2) -> -67.187398 | E30: =SUMIFS(HY!$G$524:$AN$524,HY!$G$9:$AN$9,FY!E$2) -> -68.613 | F30: =SUMIFS(HY!$G$524:$AN$524,HY!$G$9:$AN$9,FY!F$2) -> -74.995 | G30: =SUMIFS(HY!$G$524:$AN$524,HY!$G$9:$AN$9,FY!G$2) -> -81.499 | H30: =SUMIFS(HY!$G$524:$AN$524,HY!$G$9:$AN$9,FY!H$2) -> -77.343 | I30: =SUMIFS(HY!$G$524:$AN$524,HY!$G$9:$AN$9,FY!I$2) -> -80.266 | J30: =SUMIFS(HY!$G$524:$AN$524,HY!$G$9:$AN$9,FY!J$2) -> -82.918 | K30: =SUMIFS(HY!$G$524:$AN$524,HY!$G$9:$AN$9,FY!K$2) -> -90.655 | ... S30: =SUMIFS(HY!$G$524:$AN$524,HY!$G$9:$AN$9,FY!S$2) -> -86.364261
B31: Amortisation | D31: =SUMIFS(HY!$G$525:$AN$525,HY!$G$9:$AN$9,FY!D$2) -> -12.812602 | E31: =SUMIFS(HY!$G$525:$AN$525,HY!$G$9:$AN$9,FY!E$2) -> -17.987 | F31: =SUMIFS(HY!$G$525:$AN$525,HY!$G$9:$AN$9,FY!F$2) -> -13.405 | G31: =SUMIFS(HY!$G$525:$AN$525,HY!$G$9:$AN$9,FY!G$2) -> -13.201 | H31: =SUMIFS(HY!$G$525:$AN$525,HY!$G$9:$AN$9,FY!H$2) -> -13.329 | I31: =SUMIFS(HY!$G$525:$AN$525,HY!$G$9:$AN$9,FY!I$2) -> -11.755 | J31: =SUMIFS(HY!$G$525:$AN$525,HY!$G$9:$AN$9,FY!J$2) -> -11.295 | K31: =SUMIFS(HY!$G$525:$AN$525,HY!$G$9:$AN$9,FY!K$2) -> -12.802 | ... S31: =SUMIFS(HY!$G$525:$AN$525,HY!$G$9:$AN$9,FY!S$2) -> -13.431597
B32: ----- | D32: ----- | E32: ----- | F32: ----- | G32: ----- | H32: ----- | I32: ----- | J32: ----- | K32: ----- | L32: ----- | M32: ----- | N32: ----- | O32: ----- | P32: ----- | Q32: ----- | R32: ----- | S32: -----
B33: EBIT | D33: =SUMIFS(HY!$G$338:$AN$338,HY!$G$9:$AN$9,FY!D$2) -> 242.2 | E33: =SUMIFS(HY!$G$338:$AN$338,HY!$G$9:$AN$9,FY!E$2) -> 114.1 | F33: =SUMIFS(HY!$G$338:$AN$338,HY!$G$9:$AN$9,FY!F$2) -> 160.2 | G33: =SUMIFS(HY!$G$338:$AN$338,HY!$G$9:$AN$9,FY!G$2) -> 43.2 | H33: =SUMIFS(HY!$G$338:$AN$338,HY!$G$9:$AN$9,FY!H$2) -> 211.128 | I33: =SUMIFS(HY!$G$338:$AN$338,HY!$G$9:$AN$9,FY!I$2) -> 185.779 | J33: =SUMIFS(HY!$G$338:$AN$338,HY!$G$9:$AN$9,FY!J$2) -> 139.487 | K33: =SUMIFS(HY!$G$338:$AN$338,HY!$G$9:$AN$9,FY!K$2) -> 78.143 | ... S33: =SUMIFS(HY!$G$338:$AN$338,HY!$G$9:$AN$9,FY!S$2) -> 176.30223
B34: Net interest expense | D34: =SUMIFS(HY!$G$528:$AN$528,HY!$G$9:$AN$9,FY!D$2)+SUMIFS(HY!$G$529:$AN$529,HY!$G$9:$AN$9,FY!D$2) -> -37.064 | E34: =SUMIFS(HY!$G$528:$AN$528,HY!$G$9:$AN$9,FY!E$2)+SUMIFS(HY!$G$529:$AN$529,HY!$G$9:$AN$9,FY!E$2) -> -40.384 | F34: =SUMIFS(HY!$G$528:$AN$528,HY!$G$9:$AN$9,FY!F$2)+SUMIFS(HY!$G$529:$AN$529,HY!$G$9:$AN$9,FY!F$2) -> -37.65 | G34: =SUMIFS(HY!$G$528:$AN$528,HY!$G$9:$AN$9,FY!G$2)+SUMIFS(HY!$G$529:$AN$529,HY!$G$9:$AN$9,FY!G$2) -> -30.003 | H34: =SUMIFS(HY!$G$528:$AN$528,HY!$G$9:$AN$9,FY!H$2)+SUMIFS(HY!$G$529:$AN$529,HY!$G$9:$AN$9,FY!H$2) -> -37.094 | I34: =SUMIFS(HY!$G$528:$AN$528,HY!$G$9:$AN$9,FY!I$2)+SUMIFS(HY!$G$529:$AN$529,HY!$G$9:$AN$9,FY!I$2) -> -48.011 | J34: =SUMIFS(HY!$G$528:$AN$528,HY!$G$9:$AN$9,FY!J$2)+SUMIFS(HY!$G$529:$AN$529,HY!$G$9:$AN$9,FY!J$2) -> -59.514 | K34: =SUMIFS(HY!$G$528:$AN$528,HY!$G$9:$AN$9,FY!K$2)+SUMIFS(HY!$G$529:$AN$529,HY!$G$9:$AN$9,FY!K$2) -> -53.2875 | ... S34: =SUMIFS(HY!$G$528:$AN$528,HY!$G$9:$AN$9,FY!S$2)+SUMIFS(HY!$G$529:$AN$529,HY!$G$9:$AN$9,FY!S$2) -> -10.619647
B35: Other Financing | D35: =SUMIFS(HY!$G$530:$AD$530,HY!$G$9:$AD$9,FY!D$2) -> 26.864 | E35: =SUMIFS(HY!$G$530:$AD$530,HY!$G$9:$AD$9,FY!E$2) -> 11.784 | F35: =SUMIFS(HY!$G$530:$AD$530,HY!$G$9:$AD$9,FY!F$2) -> 5.15 | G35: =SUMIFS(HY!$G$530:$AD$530,HY!$G$9:$AD$9,FY!G$2) -> -4.997 | H35: =SUMIFS(HY!$G$530:$AD$530,HY!$G$9:$AD$9,FY!H$2) -> 8.968 | I35: =SUMIFS(HY!$G$530:$AD$530,HY!$G$9:$AD$9,FY!I$2) -> 32.011 | J35: =SUMIFS(HY!$G$530:$AD$530,HY!$G$9:$AD$9,FY!J$2) -> 33.114 | K35: =SUMIFS(HY!$G$530:$AD$530,HY!$G$9:$AD$9,FY!K$2) -> 26.6875 | ... S35: =SUMIFS(HY!$G$530:$AD$530,HY!$G$9:$AD$9,FY!S$2) -> 0
B36: Other | D36: =SUMIFS(HY!$G$531:$AN$531,HY!$G$9:$AN$9,FY!D$2) -> 0 | E36: =SUMIFS(HY!$G$531:$AN$531,HY!$G$9:$AN$9,FY!E$2) -> 0 | F36: =SUMIFS(HY!$G$531:$AN$531,HY!$G$9:$AN$9,FY!F$2) -> 0 | G36: =SUMIFS(HY!$G$531:$AN$531,HY!$G$9:$AN$9,FY!G$2) -> 0 | H36: =SUMIFS(HY!$G$531:$AN$531,HY!$G$9:$AN$9,FY!H$2) -> 0 | I36: =SUMIFS(HY!$G$531:$AN$531,HY!$G$9:$AN$9,FY!I$2) -> 0 | J36: =SUMIFS(HY!$G$531:$AN$531,HY!$G$9:$AN$9,FY!J$2) -> 0 | K36: =SUMIFS(HY!$G$531:$AN$531,HY!$G$9:$AN$9,FY!K$2) -> 0 | ... S36: =SUMIFS(HY!$G$531:$AN$531,HY!$G$9:$AN$9,FY!S$2) -> 0
B37: ----- | D37: ----- | E37: ----- | F37: ----- | G37: ----- | H37: ----- | I37: ----- | J37: ----- | K37: ----- | L37: ----- | M37: ----- | N37: ----- | O37: ----- | P37: ----- | Q37: ----- | R37: ----- | S37: -----
B38: NPBT | D38: =SUMIFS(HY!$G$343:$AN$343,HY!$G$9:$AN$9,FY!D$2) -> 232 | E38: =SUMIFS(HY!$G$343:$AN$343,HY!$G$9:$AN$9,FY!E$2) -> 85.5 | F38: =SUMIFS(HY!$G$343:$AN$343,HY!$G$9:$AN$9,FY!F$2) -> 127.7 | G38: =SUMIFS(HY!$G$343:$AN$343,HY!$G$9:$AN$9,FY!G$2) -> 8.2 | H38: =SUMIFS(HY!$G$343:$AN$343,HY!$G$9:$AN$9,FY!H$2) -> 183.002 | I38: =SUMIFS(HY!$G$343:$AN$343,HY!$G$9:$AN$9,FY!I$2) -> 169.779 | J38: =SUMIFS(HY!$G$343:$AN$343,HY!$G$9:$AN$9,FY!J$2) -> 113.087 | K38: =SUMIFS(HY!$G$343:$AN$343,HY!$G$9:$AN$9,FY!K$2) -> 51.543 | ... S38: =SUMIFS(HY!$G$343:$AN$343,HY!$G$9:$AN$9,FY!S$2) -> 165.68259
B39: Tax | D39: =SUMIFS(HY!$G$344:$AN$344,HY!$G$9:$AN$9,FY!D$2) -> -67.4 | E39: =SUMIFS(HY!$G$344:$AN$344,HY!$G$9:$AN$9,FY!E$2) -> -19.2 | F39: =SUMIFS(HY!$G$344:$AN$344,HY!$G$9:$AN$9,FY!F$2) -> -37.7 | G39: =SUMIFS(HY!$G$344:$AN$344,HY!$G$9:$AN$9,FY!G$2) -> 1.5 | H39: =SUMIFS(HY!$G$344:$AN$344,HY!$G$9:$AN$9,FY!H$2) -> -50.302 | I39: =SUMIFS(HY!$G$344:$AN$344,HY!$G$9:$AN$9,FY!I$2) -> -46.579 | J39: =SUMIFS(HY!$G$344:$AN$344,HY!$G$9:$AN$9,FY!J$2) -> -41.587 | K39: =SUMIFS(HY!$G$344:$AN$344,HY!$G$9:$AN$9,FY!K$2) -> -13.543 | ... S39: =SUMIFS(HY!$G$344:$AN$344,HY!$G$9:$AN$9,FY!S$2) -> -49.704776
B40: Effective Tax Rate (%) | D40: =D39/-D38 -> 0.29051724 | E40: =E39/-E38 -> 0.2245614 | F40: =F39/-F38 -> 0.29522318 | G40: =G39/-G38 -> -0.18292683 | H40: =H39/-H38 -> 0.27487131 | I40: =I39/-I38 -> 0.27435077 | J40: =J39/-J38 -> 0.36774342 | K40: =K39/-K38 -> 0.26275149 | ... S40: =S39/-S38 -> 0.3
B41: NPAT | D41: =SUMIFS(HY!$G$348:$AN$348,HY!$G$9:$AN$9,FY!D$2) -> 164.6 | E41: =SUMIFS(HY!$G$348:$AN$348,HY!$G$9:$AN$9,FY!E$2) -> 66.3 | F41: =SUMIFS(HY!$G$348:$AN$348,HY!$G$9:$AN$9,FY!F$2) -> 90 | G41: =SUMIFS(HY!$G$348:$AN$348,HY!$G$9:$AN$9,FY!G$2) -> 9.7 | H41: =SUMIFS(HY!$G$348:$AN$348,HY!$G$9:$AN$9,FY!H$2) -> 132.7 | I41: =SUMIFS(HY!$G$348:$AN$348,HY!$G$9:$AN$9,FY!I$2) -> 123.2 | J41: =SUMIFS(HY!$G$348:$AN$348,HY!$G$9:$AN$9,FY!J$2) -> 71.5 | K41: =SUMIFS(HY!$G$348:$AN$348,HY!$G$9:$AN$9,FY!K$2) -> 38 | ... S41: =SUMIFS(HY!$G$348:$AN$348,HY!$G$9:$AN$9,FY!S$2) -> 115.97781
B42: NPAT Growth | E42: =E41/D41-1 -> -0.59720535 | F42: =F41/E41-1 -> 0.35746606 | G42: =G41/F41-1 -> -0.89222222 | H42: =H41/G41-1 -> 12.680412 | I42: =I41/H41-1 -> -0.071590053 | J42: =J41/I41-1 -> -0.41964286 | K42: =K41/J41-1 -> -0.46853147 | L42: =L41/K41-1 -> -0.19867571 | ... S42: =S41/R41-1 -> 0.047101486
A44: X | B44: P&L - Underlying | D44: 2019A | E44: 2020A | F44: 2021 | G44: 2022 | H44: 2023 | I44: 2024 | J44: 2025 | K44: 2026 | L44: 2027 | M44: 2028 | N44: 2029 | O44: 2030 | P44: 2030 | Q44: 2030 | R44: 2030 | S44: 2030
B45: Sales Revenue | D45: =SUMIFS(HY!$G$516:$AN$516,HY!$G$9:$AN$9,FY!D$2) -> 937.78672 | E45: =SUMIFS(HY!$G$516:$AN$516,HY!$G$9:$AN$9,FY!E$2) -> 705.23394 | F45: =SUMIFS(HY!$G$516:$AN$516,HY!$G$9:$AN$9,FY!F$2) -> 731.63648 | G45: =SUMIFS(HY!$G$516:$AN$516,HY!$G$9:$AN$9,FY!G$2) -> 575.42004 | H45: =SUMIFS(HY!$G$516:$AN$516,HY!$G$9:$AN$9,FY!H$2) -> 862.6 | I45: =SUMIFS(HY!$G$516:$AN$516,HY!$G$9:$AN$9,FY!I$2) -> 870.5 | J45: =SUMIFS(HY!$G$516:$AN$516,HY!$G$9:$AN$9,FY!J$2) -> 825.2 | K45: =SUMIFS(HY!$G$516:$AN$516,HY!$G$9:$AN$9,FY!K$2) -> 822.7 | ... S45: =SUMIFS(HY!$G$516:$AN$516,HY!$G$9:$AN$9,FY!S$2) -> 1092.3405
B46: Other Income | D46: =SUMIFS(HY!$G$517:$AN$517,HY!$G$9:$AN$9,FY!D$2) -> 0 | E46: =SUMIFS(HY!$G$517:$AN$517,HY!$G$9:$AN$9,FY!E$2) -> 0 | F46: =SUMIFS(HY!$G$517:$AN$517,HY!$G$9:$AN$9,FY!F$2) -> 0 | G46: =SUMIFS(HY!$G$517:$AN$517,HY!$G$9:$AN$9,FY!G$2) -> 0 | H46: =SUMIFS(HY!$G$517:$AN$517,HY!$G$9:$AN$9,FY!H$2) -> 0 | I46: =SUMIFS(HY!$G$517:$AN$517,HY!$G$9:$AN$9,FY!I$2) -> 0 | J46: =SUMIFS(HY!$G$517:$AN$517,HY!$G$9:$AN$9,FY!J$2) -> 0 | K46: =SUMIFS(HY!$G$517:$AN$517,HY!$G$9:$AN$9,FY!K$2) -> 0 | ... S46: =SUMIFS(HY!$G$517:$AN$517,HY!$G$9:$AN$9,FY!S$2) -> 0
B47: ----- | D47: ----- | E47: ----- | F47: ----- | G47: ----- | H47: ----- | I47: ----- | J47: ----- | K47: ----- | L47: ----- | M47: ----- | N47: ----- | O47: ----- | P47: ----- | Q47: ----- | R47: ----- | S47: -----
B48: Total revenue | D48: =D46+D45 -> 937.78672 | E48: =E46+E45 -> 705.23394 | F48: =F46+F45 -> 731.63648 | G48: =G46+G45 -> 575.42004 | H48: =H46+H45 -> 862.6 | I48: =I46+I45 -> 870.5 | J48: =J46+J45 -> 825.2 | K48: =K46+K45 -> 822.7 | ... S48: =S46+S45 -> 1092.3405
B49: COGS | D49: =SUMIFS(HY!$G$518:$AN$518,HY!$G$9:$AN$9,FY!D$2) -> 0 | E49: =SUMIFS(HY!$G$518:$AN$518,HY!$G$9:$AN$9,FY!E$2) -> 0 | F49: =SUMIFS(HY!$G$518:$AN$518,HY!$G$9:$AN$9,FY!F$2) -> 0 | G49: =SUMIFS(HY!$G$518:$AN$518,HY!$G$9:$AN$9,FY!G$2) -> 0 | H49: =SUMIFS(HY!$G$518:$AN$518,HY!$G$9:$AN$9,FY!H$2) -> 0 | I49: =SUMIFS(HY!$G$518:$AN$518,HY!$G$9:$AN$9,FY!I$2) -> 0 | J49: =SUMIFS(HY!$G$518:$AN$518,HY!$G$9:$AN$9,FY!J$2) -> 0 | K49: =SUMIFS(HY!$G$518:$AN$518,HY!$G$9:$AN$9,FY!K$2) -> 0 | ... S49: =SUMIFS(HY!$G$518:$AN$518,HY!$G$9:$AN$9,FY!S$2) -> 0
B50: OPEX | D50: =SUMIFS(HY!$G$521:$AN$521,HY!$G$9:$AN$9,FY!D$2) -> -615.58672 | E50: =SUMIFS(HY!$G$521:$AN$521,HY!$G$9:$AN$9,FY!E$2) -> -504.53394 | F50: =SUMIFS(HY!$G$521:$AN$521,HY!$G$9:$AN$9,FY!F$2) -> -483.03648 | G50: =SUMIFS(HY!$G$521:$AN$521,HY!$G$9:$AN$9,FY!G$2) -> -437.52004 | H50: =SUMIFS(HY!$G$521:$AN$521,HY!$G$9:$AN$9,FY!H$2) -> -560.8 | I50: =SUMIFS(HY!$G$521:$AN$521,HY!$G$9:$AN$9,FY!I$2) -> -592.7 | J50: =SUMIFS(HY!$G$521:$AN$521,HY!$G$9:$AN$9,FY!J$2) -> -591.5 | K50: =SUMIFS(HY!$G$521:$AN$521,HY!$G$9:$AN$9,FY!K$2) -> -641.1 | ... S50: =SUMIFS(HY!$G$521:$AN$521,HY!$G$9:$AN$9,FY!S$2) -> -816.24242
B51: ----- | D51: ----- | E51: ----- | F51: ----- | G51: ----- | H51: ----- | I51: ----- | J51: ----- | K51: ----- | L51: ----- | M51: ----- | N51: ----- | O51: ----- | P51: ----- | Q51: ----- | R51: ----- | S51: -----
B52: EBITDA | D52: =SUMIFS(HY!$G$523:$AN$523,HY!$G$9:$AN$9,FY!D$2) -> 322.2 | E52: =SUMIFS(HY!$G$523:$AN$523,HY!$G$9:$AN$9,FY!E$2) -> 200.7 | F52: =SUMIFS(HY!$G$523:$AN$523,HY!$G$9:$AN$9,FY!F$2) -> 248.6 | G52: =SUMIFS(HY!$G$523:$AN$523,HY!$G$9:$AN$9,FY!G$2) -> 137.9 | H52: =SUMIFS(HY!$G$523:$AN$523,HY!$G$9:$AN$9,FY!H$2) -> 301.8 | I52: =SUMIFS(HY!$G$523:$AN$523,HY!$G$9:$AN$9,FY!I$2) -> 277.8 | J52: =SUMIFS(HY!$G$523:$AN$523,HY!$G$9:$AN$9,FY!J$2) -> 233.7 | K52: =SUMIFS(HY!$G$523:$AN$523,HY!$G$9:$AN$9,FY!K$2) -> 181.6 | ... S52: =SUMIFS(HY!$G$523:$AN$523,HY!$G$9:$AN$9,FY!S$2) -> 276.09809
B53: Depreciation | D53: =SUMIFS(HY!$G$524:$AN$524,HY!$G$9:$AN$9,FY!D$2) -> -67.187398 | E53: =SUMIFS(HY!$G$524:$AN$524,HY!$G$9:$AN$9,FY!E$2) -> -68.613 | F53: =SUMIFS(HY!$G$524:$AN$524,HY!$G$9:$AN$9,FY!F$2) -> -74.995 | G53: =SUMIFS(HY!$G$524:$AN$524,HY!$G$9:$AN$9,FY!G$2) -> -81.499 | H53: =SUMIFS(HY!$G$524:$AN$524,HY!$G$9:$AN$9,FY!H$2) -> -77.343 | I53: =SUMIFS(HY!$G$524:$AN$524,HY!$G$9:$AN$9,FY!I$2) -> -80.266 | J53: =SUMIFS(HY!$G$524:$AN$524,HY!$G$9:$AN$9,FY!J$2) -> -82.918 | K53: =SUMIFS(HY!$G$524:$AN$524,HY!$G$9:$AN$9,FY!K$2) -> -90.655 | ... S53: =SUMIFS(HY!$G$524:$AN$524,HY!$G$9:$AN$9,FY!S$2) -> -86.364261
B54: Amortisation | D54: =SUMIFS(HY!$G$525:$AN$525,HY!$G$9:$AN$9,FY!D$2) -> -12.812602 | E54: =SUMIFS(HY!$G$525:$AN$525,HY!$G$9:$AN$9,FY!E$2) -> -17.987 | F54: =SUMIFS(HY!$G$525:$AN$525,HY!$G$9:$AN$9,FY!F$2) -> -13.405 | G54: =SUMIFS(HY!$G$525:$AN$525,HY!$G$9:$AN$9,FY!G$2) -> -13.201 | H54: =SUMIFS(HY!$G$525:$AN$525,HY!$G$9:$AN$9,FY!H$2) -> -13.329 | I54: =SUMIFS(HY!$G$525:$AN$525,HY!$G$9:$AN$9,FY!I$2) -> -11.755 | J54: =SUMIFS(HY!$G$525:$AN$525,HY!$G$9:$AN$9,FY!J$2) -> -11.295 | K54: =SUMIFS(HY!$G$525:$AN$525,HY!$G$9:$AN$9,FY!K$2) -> -12.802 | ... S54: =SUMIFS(HY!$G$525:$AN$525,HY!$G$9:$AN$9,FY!S$2) -> -13.431597
B55: ----- | D55: ----- | E55: ----- | F55: ----- | G55: ----- | H55: ----- | I55: ----- | J55: ----- | K55: ----- | L55: ----- | M55: ----- | N55: ----- | O55: ----- | P55: ----- | Q55: ----- | R55: ----- | S55: -----
B56: EBIT | D56: =SUMIFS(HY!$G$527:$AN$527,HY!$G$9:$AN$9,FY!D$2) -> 242.2 | E56: =SUMIFS(HY!$G$527:$AN$527,HY!$G$9:$AN$9,FY!E$2) -> 114.1 | F56: =SUMIFS(HY!$G$527:$AN$527,HY!$G$9:$AN$9,FY!F$2) -> 160.2 | G56: =SUMIFS(HY!$G$527:$AN$527,HY!$G$9:$AN$9,FY!G$2) -> 43.2 | H56: =SUMIFS(HY!$G$527:$AN$527,HY!$G$9:$AN$9,FY!H$2) -> 211.128 | I56: =SUMIFS(HY!$G$527:$AN$527,HY!$G$9:$AN$9,FY!I$2) -> 185.779 | J56: =SUMIFS(HY!$G$527:$AN$527,HY!$G$9:$AN$9,FY!J$2) -> 139.487 | K56: =SUMIFS(HY!$G$527:$AN$527,HY!$G$9:$AN$9,FY!K$2) -> 78.143 | ... S56: =SUMIFS(HY!$G$527:$AN$527,HY!$G$9:$AN$9,FY!S$2) -> 176.30223
B57: Net interest expense | D57: =SUMIFS(HY!$G$528:$AN$528,HY!$G$9:$AN$9,FY!D$2)+SUMIFS(HY!$G$529:$AN$529,HY!$G$9:$AN$9,FY!D$2)+SUMIFS(HY!$G$530:$AN$530,HY!$G$9:$AN$9,FY!D$2) -> -10.2 | E57: =SUMIFS(HY!$G$528:$AN$528,HY!$G$9:$AN$9,FY!E$2)+SUMIFS(HY!$G$529:$AN$529,HY!$G$9:$AN$9,FY!E$2)+SUMIFS(HY!$G$530:$AN$530,HY!$G$9:$AN$9,FY!E$2) -> -28.6 | F57: =SUMIFS(HY!$G$528:$AN$528,HY!$G$9:$AN$9,FY!F$2)+SUMIFS(HY!$G$529:$AN$529,HY!$G$9:$AN$9,FY!F$2)+SUMIFS(HY!$G$530:$AN$530,HY!$G$9:$AN$9,FY!F$2) -> -32.5 | G57: =SUMIFS(HY!$G$528:$AN$528,HY!$G$9:$AN$9,FY!G$2)+SUMIFS(HY!$G$529:$AN$529,HY!$G$9:$AN$9,FY!G$2)+SUMIFS(HY!$G$530:$AN$530,HY!$G$9:$AN$9,FY!G$2) -> -35 | H57: =SUMIFS(HY!$G$528:$AN$528,HY!$G$9:$AN$9,FY!H$2)+SUMIFS(HY!$G$529:$AN$529,HY!$G$9:$AN$9,FY!H$2)+SUMIFS(HY!$G$530:$AN$530,HY!$G$9:$AN$9,FY!H$2) -> -28.126 | I57: =SUMIFS(HY!$G$528:$AN$528,HY!$G$9:$AN$9,FY!I$2)+SUMIFS(HY!$G$529:$AN$529,HY!$G$9:$AN$9,FY!I$2)+SUMIFS(HY!$G$530:$AN$530,HY!$G$9:$AN$9,FY!I$2) -> -16 | J57: =SUMIFS(HY!$G$528:$AN$528,HY!$G$9:$AN$9,FY!J$2)+SUMIFS(HY!$G$529:$AN$529,HY!$G$9:$AN$9,FY!J$2)+SUMIFS(HY!$G$530:$AN$530,HY!$G$9:$AN$9,FY!J$2) -> -26.4 | K57: =SUMIFS(HY!$G$528:$AN$528,HY!$G$9:$AN$9,FY!K$2)+SUMIFS(HY!$G$529:$AN$529,HY!$G$9:$AN$9,FY!K$2)+SUMIFS(HY!$G$530:$AN$530,HY!$G$9:$AN$9,FY!K$2) -> -26.6 | ... S57: =SUMIFS(HY!$G$528:$AN$528,HY!$G$9:$AN$9,FY!S$2)+SUMIFS(HY!$G$529:$AN$529,HY!$G$9:$AN$9,FY!S$2)+SUMIFS(HY!$G$530:$AN$530,HY!$G$9:$AN$9,FY!S$2) -> -10.619647
B58: Share of associates | D58: =SUMIFS(HY!$G$531:$AN$531,HY!$G$9:$AN$9,FY!D$2) -> 0 | E58: =SUMIFS(HY!$G$531:$AN$531,HY!$G$9:$AN$9,FY!E$2) -> 0 | F58: =SUMIFS(HY!$G$531:$AN$531,HY!$G$9:$AN$9,FY!F$2) -> 0 | G58: =SUMIFS(HY!$G$531:$AN$531,HY!$G$9:$AN$9,FY!G$2) -> 0 | H58: =SUMIFS(HY!$G$531:$AN$531,HY!$G$9:$AN$9,FY!H$2) -> 0 | I58: =SUMIFS(HY!$G$531:$AN$531,HY!$G$9:$AN$9,FY!I$2) -> 0 | J58: =SUMIFS(HY!$G$531:$AN$531,HY!$G$9:$AN$9,FY!J$2) -> 0 | K58: =SUMIFS(HY!$G$531:$AN$531,HY!$G$9:$AN$9,FY!K$2) -> 0 | ... S58: =SUMIFS(HY!$G$531:$AN$531,HY!$G$9:$AN$9,FY!S$2) -> 0
B59: ----- | D59: ----- | E59: ----- | F59: ----- | G59: ----- | H59: ----- | I59: ----- | J59: ----- | K59: ----- | L59: ----- | M59: ----- | N59: ----- | O59: ----- | P59: ----- | Q59: ----- | R59: ----- | S59: -----
B60: NPBT | D60: =SUMIFS(HY!$G$533:$AN$533,HY!$G$9:$AN$9,FY!D$2) -> 232 | E60: =SUMIFS(HY!$G$533:$AN$533,HY!$G$9:$AN$9,FY!E$2) -> 85.5 | F60: =SUMIFS(HY!$G$533:$AN$533,HY!$G$9:$AN$9,FY!F$2) -> 127.7 | G60: =SUMIFS(HY!$G$533:$AN$533,HY!$G$9:$AN$9,FY!G$2) -> 8.2 | H60: =SUMIFS(HY!$G$533:$AN$533,HY!$G$9:$AN$9,FY!H$2) -> 183.002 | I60: =SUMIFS(HY!$G$533:$AN$533,HY!$G$9:$AN$9,FY!I$2) -> 169.779 | J60: =SUMIFS(HY!$G$533:$AN$533,HY!$G$9:$AN$9,FY!J$2) -> 113.087 | K60: =SUMIFS(HY!$G$533:$AN$533,HY!$G$9:$AN$9,FY!K$2) -> 51.543 | ... S60: =SUMIFS(HY!$G$533:$AN$533,HY!$G$9:$AN$9,FY!S$2) -> 165.68259
B61: Tax | D61: =SUMIFS(HY!$G$534:$AN$534,HY!$G$9:$AN$9,FY!D$2) -> -67.4 | E61: =SUMIFS(HY!$G$534:$AN$534,HY!$G$9:$AN$9,FY!E$2) -> -19.2 | F61: =SUMIFS(HY!$G$534:$AN$534,HY!$G$9:$AN$9,FY!F$2) -> -37.7 | G61: =SUMIFS(HY!$G$534:$AN$534,HY!$G$9:$AN$9,FY!G$2) -> 1.5 | H61: =SUMIFS(HY!$G$534:$AN$534,HY!$G$9:$AN$9,FY!H$2) -> -50.302 | I61: =SUMIFS(HY!$G$534:$AN$534,HY!$G$9:$AN$9,FY!I$2) -> -46.579 | J61: =SUMIFS(HY!$G$534:$AN$534,HY!$G$9:$AN$9,FY!J$2) -> -41.587 | K61: =SUMIFS(HY!$G$534:$AN$534,HY!$G$9:$AN$9,FY!K$2) -> -13.543 | ... S61: =SUMIFS(HY!$G$534:$AN$534,HY!$G$9:$AN$9,FY!S$2) -> -49.704776
B62: Discontinued Ops | D62: 0 | E62: 0 | F62: 0 | G62: 0 | H62: 0 | I62: 0 | J62: 0 | K62: 0 | L62: 0 | M62: 0 | N62: 0 | O62: 0 | P62: 0 | Q62: 0 | R62: 0 | S62: 0
B63: NPAT | D63: =SUMIFS(HY!$G$537:$AN$537,HY!$G$9:$AN$9,FY!D$2) -> 164.6 | E63: =SUMIFS(HY!$G$537:$AN$537,HY!$G$9:$AN$9,FY!E$2) -> 66.3 | F63: =SUMIFS(HY!$G$537:$AN$537,HY!$G$9:$AN$9,FY!F$2) -> 90 | G63: =SUMIFS(HY!$G$537:$AN$537,HY!$G$9:$AN$9,FY!G$2) -> 9.7 | H63: =SUMIFS(HY!$G$537:$AN$537,HY!$G$9:$AN$9,FY!H$2) -> 132.7 | I63: =SUMIFS(HY!$G$537:$AN$537,HY!$G$9:$AN$9,FY!I$2) -> 123.2 | J63: =SUMIFS(HY!$G$537:$AN$537,HY!$G$9:$AN$9,FY!J$2) -> 71.5 | K63: =SUMIFS(HY!$G$537:$AN$537,HY!$G$9:$AN$9,FY!K$2) -> 38 | ... S63: =SUMIFS(HY!$G$537:$AN$537,HY!$G$9:$AN$9,FY!S$2) -> 115.97781
B65: Adjustments | D65: =SUMIFS(HY!$G$367:$AN$367,HY!$G$9:$AN$9,FY!D$2) -> -20 | E65: =SUMIFS(HY!$G$367:$AN$367,HY!$G$9:$AN$9,FY!E$2) -> 169.1 | F65: =SUMIFS(HY!$G$367:$AN$367,HY!$G$9:$AN$9,FY!F$2) -> 65.8 | G65: =SUMIFS(HY!$G$367:$AN$367,HY!$G$9:$AN$9,FY!G$2) -> -43.3 | H65: =SUMIFS(HY!$G$367:$AN$367,HY!$G$9:$AN$9,FY!H$2) -> -124.725 | I65: =SUMIFS(HY!$G$367:$AN$367,HY!$G$9:$AN$9,FY!I$2) -> -266.5 | J65: =SUMIFS(HY!$G$367:$AN$367,HY!$G$9:$AN$9,FY!J$2) -> -42.3 | K65: =SUMIFS(HY!$G$367:$AN$367,HY!$G$9:$AN$9,FY!K$2) -> -19.8 | ... S65: =SUMIFS(HY!$G$367:$AN$367,HY!$G$9:$AN$9,FY!S$2) -> 0
B66: Reported NPAT | D66: =SUMIFS(HY!$G$368:$AN$368,HY!$G$9:$AN$9,FY!D$2) -> 144.6 | E66: =SUMIFS(HY!$G$368:$AN$368,HY!$G$9:$AN$9,FY!E$2) -> 235.4 | F66: =SUMIFS(HY!$G$368:$AN$368,HY!$G$9:$AN$9,FY!F$2) -> 155.8 | G66: =SUMIFS(HY!$G$368:$AN$368,HY!$G$9:$AN$9,FY!G$2) -> -33.6 | H66: =SUMIFS(HY!$G$368:$AN$368,HY!$G$9:$AN$9,FY!H$2) -> 7.975 | I66: =SUMIFS(HY!$G$368:$AN$368,HY!$G$9:$AN$9,FY!I$2) -> -143.3 | J66: =SUMIFS(HY!$G$368:$AN$368,HY!$G$9:$AN$9,FY!J$2) -> 29.2 | K66: =SUMIFS(HY!$G$368:$AN$368,HY!$G$9:$AN$9,FY!K$2) -> 18.2 | ... S66: =SUMIFS(HY!$G$368:$AN$368,HY!$G$9:$AN$9,FY!S$2) -> 115.97781
A68: X | B68: CASH FLOW STATEMENT | D68: 2019A | E68: 2020A | F68: 2021 | G68: 2022 | H68: 2023 | I68: 2024 | J68: 2025 | K68: 2026 | L68: 2027 | M68: 2028 | N68: 2029 | O68: 2030 | P68: 2030 | Q68: 2030 | R68: 2030 | S68: 2030
B69: EBITDA | D69: =SUMIFS(HY!$G$541:$AN$541,HY!$G$9:$AN$9,FY!D$2) -> 322.2 | E69: =SUMIFS(HY!$G$541:$AN$541,HY!$G$9:$AN$9,FY!E$2) -> 200.7 | F69: =SUMIFS(HY!$G$541:$AN$541,HY!$G$9:$AN$9,FY!F$2) -> 248.6 | G69: =SUMIFS(HY!$G$541:$AN$541,HY!$G$9:$AN$9,FY!G$2) -> 137.9 | H69: =SUMIFS(HY!$G$541:$AN$541,HY!$G$9:$AN$9,FY!H$2) -> 301.8 | I69: =SUMIFS(HY!$G$541:$AN$541,HY!$G$9:$AN$9,FY!I$2) -> 277.8 | J69: =SUMIFS(HY!$G$541:$AN$541,HY!$G$9:$AN$9,FY!J$2) -> 233.7 | K69: =SUMIFS(HY!$G$541:$AN$541,HY!$G$9:$AN$9,FY!K$2) -> 181.6 | ... S69: =SUMIFS(HY!$G$541:$AN$541,HY!$G$9:$AN$9,FY!S$2) -> 276.09809
B70: Tax paid | D70: =SUMIFS(HY!$G$542:$AN$542,HY!$G$9:$AN$9,FY!D$2) -> -50.626 | E70: =SUMIFS(HY!$G$542:$AN$542,HY!$G$9:$AN$9,FY!E$2) -> -41.057 | F70: =SUMIFS(HY!$G$542:$AN$542,HY!$G$9:$AN$9,FY!F$2) -> -15.569 | G70: =SUMIFS(HY!$G$542:$AN$542,HY!$G$9:$AN$9,FY!G$2) -> -25.679 | H70: =SUMIFS(HY!$G$542:$AN$542,HY!$G$9:$AN$9,FY!H$2) -> -7.034 | I70: =SUMIFS(HY!$G$542:$AN$542,HY!$G$9:$AN$9,FY!I$2) -> -54.672 | J70: =SUMIFS(HY!$G$542:$AN$542,HY!$G$9:$AN$9,FY!J$2) -> -60.167 | K70: =SUMIFS(HY!$G$542:$AN$542,HY!$G$9:$AN$9,FY!K$2) -> -38.945 | ... S70: =SUMIFS(HY!$G$542:$AN$542,HY!$G$9:$AN$9,FY!S$2) -> -49.704776
B71: Interest paid | D71: =SUMIFS(HY!$G$560:$AN$560,HY!$G$9:$AN$9,FY!D$2)+SUMIFS(HY!$G$558:$AN$558,HY!$G$9:$AN$9,FY!D$2) -> -37.064 | E71: =SUMIFS(HY!$G$560:$AN$560,HY!$G$9:$AN$9,FY!E$2)+SUMIFS(HY!$G$558:$AN$558,HY!$G$9:$AN$9,FY!E$2) -> -40.384 | F71: =SUMIFS(HY!$G$560:$AN$560,HY!$G$9:$AN$9,FY!F$2)+SUMIFS(HY!$G$558:$AN$558,HY!$G$9:$AN$9,FY!F$2) -> -37.65 | G71: =SUMIFS(HY!$G$560:$AN$560,HY!$G$9:$AN$9,FY!G$2)+SUMIFS(HY!$G$558:$AN$558,HY!$G$9:$AN$9,FY!G$2) -> -30.003 | H71: =SUMIFS(HY!$G$560:$AN$560,HY!$G$9:$AN$9,FY!H$2)+SUMIFS(HY!$G$558:$AN$558,HY!$G$9:$AN$9,FY!H$2) -> -37.094 | I71: =SUMIFS(HY!$G$560:$AN$560,HY!$G$9:$AN$9,FY!I$2)+SUMIFS(HY!$G$558:$AN$558,HY!$G$9:$AN$9,FY!I$2) -> -48.011 | J71: =SUMIFS(HY!$G$560:$AN$560,HY!$G$9:$AN$9,FY!J$2)+SUMIFS(HY!$G$558:$AN$558,HY!$G$9:$AN$9,FY!J$2) -> -43.0015 | K71: =SUMIFS(HY!$G$560:$AN$560,HY!$G$9:$AN$9,FY!K$2)+SUMIFS(HY!$G$558:$AN$558,HY!$G$9:$AN$9,FY!K$2) -> -54.2875 | ... S71: =SUMIFS(HY!$G$560:$AN$560,HY!$G$9:$AN$9,FY!S$2)+SUMIFS(HY!$G$558:$AN$558,HY!$G$9:$AN$9,FY!S$2) -> -10.619647
B72: Other Financing | D72: =SUMIFS(HY!$G$559:$AN$559,HY!$G$9:$AN$9,FY!D$2) -> 26.864 | E72: =SUMIFS(HY!$G$559:$AN$559,HY!$G$9:$AN$9,FY!E$2) -> 11.784 | F72: =SUMIFS(HY!$G$559:$AN$559,HY!$G$9:$AN$9,FY!F$2) -> 5.15 | G72: =SUMIFS(HY!$G$559:$AN$559,HY!$G$9:$AN$9,FY!G$2) -> -4.997 | H72: =SUMIFS(HY!$G$559:$AN$559,HY!$G$9:$AN$9,FY!H$2) -> 8.968 | I72: =SUMIFS(HY!$G$559:$AN$559,HY!$G$9:$AN$9,FY!I$2) -> 32.011 | J72: =SUMIFS(HY!$G$559:$AN$559,HY!$G$9:$AN$9,FY!J$2) -> 16.2265 | K72: =SUMIFS(HY!$G$559:$AN$559,HY!$G$9:$AN$9,FY!K$2) -> 12.2755 | ... S72: =SUMIFS(HY!$G$559:$AN$559,HY!$G$9:$AN$9,FY!S$2) -> 0
B73: Other | D73: =SUMIFS(HY!$G$543:$AN$543,HY!$G$9:$AN$9,FY!D$2) -> -28.111 | E73: =SUMIFS(HY!$G$543:$AN$543,HY!$G$9:$AN$9,FY!E$2) -> -39.019 | F73: =SUMIFS(HY!$G$543:$AN$543,HY!$G$9:$AN$9,FY!F$2) -> 66.229 | G73: =SUMIFS(HY!$G$543:$AN$543,HY!$G$9:$AN$9,FY!G$2) -> -13.471 | H73: =SUMIFS(HY!$G$543:$AN$543,HY!$G$9:$AN$9,FY!H$2) -> -11.241 | I73: =SUMIFS(HY!$G$543:$AN$543,HY!$G$9:$AN$9,FY!I$2) -> 11.736 | J73: =SUMIFS(HY!$G$543:$AN$543,HY!$G$9:$AN$9,FY!J$2) -> -116.358 | K73: =SUMIFS(HY!$G$543:$AN$543,HY!$G$9:$AN$9,FY!K$2) -> -112.668 | ... S73: =SUMIFS(HY!$G$543:$AN$543,HY!$G$9:$AN$9,FY!S$2) -> 0
B74: ----- | D74: ----- | E74: ----- | F74: ----- | G74: ----- | H74: ----- | I74: ----- | J74: ----- | K74: ----- | L74: ----- | M74: ----- | N74: ----- | O74: ----- | P74: ----- | Q74: ----- | R74: ----- | S74: -----
B75: FFO | D75: =SUMIFS(HY!$G$545:$AN$545,HY!$G$9:$AN$9,FY!D$2) -> 243.463 | E75: =SUMIFS(HY!$G$545:$AN$545,HY!$G$9:$AN$9,FY!E$2) -> 120.624 | F75: =SUMIFS(HY!$G$545:$AN$545,HY!$G$9:$AN$9,FY!F$2) -> 299.26 | G75: =SUMIFS(HY!$G$545:$AN$545,HY!$G$9:$AN$9,FY!G$2) -> 98.75 | H75: =SUMIFS(HY!$G$545:$AN$545,HY!$G$9:$AN$9,FY!H$2) -> 283.525 | I75: =SUMIFS(HY!$G$545:$AN$545,HY!$G$9:$AN$9,FY!I$2) -> 234.864 | J75: =SUMIFS(HY!$G$545:$AN$545,HY!$G$9:$AN$9,FY!J$2) -> 57.175 | K75: =SUMIFS(HY!$G$545:$AN$545,HY!$G$9:$AN$9,FY!K$2) -> 29.987 | ... S75: =SUMIFS(HY!$G$545:$AN$545,HY!$G$9:$AN$9,FY!S$2) -> 226.39332
B76: FFO Growth (%) | E76: =(E75/D75)-1 -> -0.50454895 | F76: =(F75/E75)-1 -> 1.4809325 | G76: =(G75/F75)-1 -> -0.67001938 | H76: =(H75/G75)-1 -> 1.8711392 | I76: =(I75/H75)-1 -> -0.1716286 | J76: =(J75/I75)-1 -> -0.75656124 | K76: =(K75/J75)-1 -> -0.47552252 | L76: =(L75/K75)-1 -> 3.1063126 | ... S76: =(S75/R75)-1 -> 0.01802677
B77: Change in working capital | D77: =SUMIFS(HY!$G$546:$AN$546,HY!$G$9:$AN$9,FY!D$2) -> 9.584 | E77: =SUMIFS(HY!$G$546:$AN$546,HY!$G$9:$AN$9,FY!E$2) -> 0.602 | F77: =SUMIFS(HY!$G$546:$AN$546,HY!$G$9:$AN$9,FY!F$2) -> -13.389 | G77: =SUMIFS(HY!$G$546:$AN$546,HY!$G$9:$AN$9,FY!G$2) -> -5.728 | H77: =SUMIFS(HY!$G$546:$AN$546,HY!$G$9:$AN$9,FY!H$2) -> 2.737 | I77: =SUMIFS(HY!$G$546:$AN$546,HY!$G$9:$AN$9,FY!I$2) -> -25.039 | J77: =SUMIFS(HY!$G$546:$AN$546,HY!$G$9:$AN$9,FY!J$2) -> -12.013 | K77: =SUMIFS(HY!$G$546:$AN$546,HY!$G$9:$AN$9,FY!K$2) -> 91.689 | ... S77: =SUMIFS(HY!$G$546:$AN$546,HY!$G$9:$AN$9,FY!S$2) -> 5.4487976
B78: Operating cash flow | D78: =SUMIFS(HY!$G$548:$AN$548,HY!$G$9:$AN$9,FY!D$2) -> 253.047 | E78: =SUMIFS(HY!$G$548:$AN$548,HY!$G$9:$AN$9,FY!E$2) -> 121.226 | F78: =SUMIFS(HY!$G$548:$AN$548,HY!$G$9:$AN$9,FY!F$2) -> 285.871 | G78: =SUMIFS(HY!$G$548:$AN$548,HY!$G$9:$AN$9,FY!G$2) -> 93.022 | H78: =SUMIFS(HY!$G$548:$AN$548,HY!$G$9:$AN$9,FY!H$2) -> 286.262 | I78: =SUMIFS(HY!$G$548:$AN$548,HY!$G$9:$AN$9,FY!I$2) -> 209.825 | J78: =SUMIFS(HY!$G$548:$AN$548,HY!$G$9:$AN$9,FY!J$2) -> 45.162 | K78: =SUMIFS(HY!$G$548:$AN$548,HY!$G$9:$AN$9,FY!K$2) -> 121.676 | ... S78: =SUMIFS(HY!$G$548:$AN$548,HY!$G$9:$AN$9,FY!S$2) -> 231.84211
B79: OCF Growth (%) | E79: =(E78/D78)-1 -> -0.52093485 | F79: =(F78/E78)-1 -> 1.3581657 | G79: =(G78/F78)-1 -> -0.67460148 | H79: =(H78/G78)-1 -> 2.077358 | I79: =(I78/H78)-1 -> -0.26701763 | J79: =(J78/I78)-1 -> -0.78476349 | K79: =(K78/J78)-1 -> 1.6942119 | L79: =(L78/K78)-1 -> 0.025729121 | ... S79: =(S78/R78)-1 -> 0.015420925
B81: CAPEX | D81: =SUMIFS(HY!$G$550:$AN$550,HY!$G$9:$AN$9,FY!D$2) -> -303.651 | E81: =SUMIFS(HY!$G$550:$AN$550,HY!$G$9:$AN$9,FY!E$2) -> -326.877 | F81: =SUMIFS(HY!$G$550:$AN$550,HY!$G$9:$AN$9,FY!F$2) -> -171.673 | G81: =SUMIFS(HY!$G$550:$AN$550,HY!$G$9:$AN$9,FY!G$2) -> -100.065 | H81: =SUMIFS(HY!$G$550:$AN$550,HY!$G$9:$AN$9,FY!H$2) -> -254.746 | I81: =SUMIFS(HY!$G$550:$AN$550,HY!$G$9:$AN$9,FY!I$2) -> -303.689 | J81: =SUMIFS(HY!$G$550:$AN$550,HY!$G$9:$AN$9,FY!J$2) -> -161.589 | K81: =SUMIFS(HY!$G$550:$AN$550,HY!$G$9:$AN$9,FY!K$2) -> -102.967 | ... S81: =SUMIFS(HY!$G$550:$AN$550,HY!$G$9:$AN$9,FY!S$2) -> -87.387241
B82: Intangibles Capex | D82: =SUMIFS(HY!$G$551:$AN$551,HY!$G$9:$AN$9,FY!D$2) -> -29.129 | E82: =SUMIFS(HY!$G$551:$AN$551,HY!$G$9:$AN$9,FY!E$2) -> -20.515 | F82: =SUMIFS(HY!$G$551:$AN$551,HY!$G$9:$AN$9,FY!F$2) -> -2.399 | G82: =SUMIFS(HY!$G$551:$AN$551,HY!$G$9:$AN$9,FY!G$2) -> -11.411 | H82: =SUMIFS(HY!$G$551:$AN$551,HY!$G$9:$AN$9,FY!H$2) -> -8.113 | I82: =SUMIFS(HY!$G$551:$AN$551,HY!$G$9:$AN$9,FY!I$2) -> -7.047 | J82: =SUMIFS(HY!$G$551:$AN$551,HY!$G$9:$AN$9,FY!J$2) -> -2.256 | K82: =SUMIFS(HY!$G$551:$AN$551,HY!$G$9:$AN$9,FY!K$2) -> -10.66 | ... S82: =SUMIFS(HY!$G$551:$AN$551,HY!$G$9:$AN$9,FY!S$2) -> -10.923405
B83: Divestments | D83: =SUMIFS(HY!$G$553:$AN$553,HY!$G$9:$AN$9,FY!D$2) -> 224.861 | E83: =SUMIFS(HY!$G$553:$AN$553,HY!$G$9:$AN$9,FY!E$2) -> 128.946 | F83: =SUMIFS(HY!$G$553:$AN$553,HY!$G$9:$AN$9,FY!F$2) -> 0 | G83: =SUMIFS(HY!$G$553:$AN$553,HY!$G$9:$AN$9,FY!G$2) -> 3.25 | H83: =SUMIFS(HY!$G$553:$AN$553,HY!$G$9:$AN$9,FY!H$2) -> 7.812 | I83: =SUMIFS(HY!$G$553:$AN$553,HY!$G$9:$AN$9,FY!I$2) -> 0 | J83: =SUMIFS(HY!$G$553:$AN$553,HY!$G$9:$AN$9,FY!J$2) -> 56.755 | K83: =SUMIFS(HY!$G$553:$AN$553,HY!$G$9:$AN$9,FY!K$2) -> 0 | ... S83: =SUMIFS(HY!$G$553:$AN$553,HY!$G$9:$AN$9,FY!S$2) -> 0
B84: Other Investments | D84: =SUMIFS(HY!$G$552:$AN$552,HY!$G$9:$AN$9,FY!D$2)+SUMIFS(HY!$G$554:$AN$554,HY!$G$9:$AN$9,FY!D$2) -> -8.564 | E84: =SUMIFS(HY!$G$552:$AN$552,HY!$G$9:$AN$9,FY!E$2)+SUMIFS(HY!$G$554:$AN$554,HY!$G$9:$AN$9,FY!E$2) -> 119.177 | F84: =SUMIFS(HY!$G$552:$AN$552,HY!$G$9:$AN$9,FY!F$2)+SUMIFS(HY!$G$554:$AN$554,HY!$G$9:$AN$9,FY!F$2) -> -77.507 | G84: =SUMIFS(HY!$G$552:$AN$552,HY!$G$9:$AN$9,FY!G$2)+SUMIFS(HY!$G$554:$AN$554,HY!$G$9:$AN$9,FY!G$2) -> 76.547 | H84: =SUMIFS(HY!$G$552:$AN$552,HY!$G$9:$AN$9,FY!H$2)+SUMIFS(HY!$G$554:$AN$554,HY!$G$9:$AN$9,FY!H$2) -> 203.611 | I84: =SUMIFS(HY!$G$552:$AN$552,HY!$G$9:$AN$9,FY!I$2)+SUMIFS(HY!$G$554:$AN$554,HY!$G$9:$AN$9,FY!I$2) -> -8.676 | J84: =SUMIFS(HY!$G$552:$AN$552,HY!$G$9:$AN$9,FY!J$2)+SUMIFS(HY!$G$554:$AN$554,HY!$G$9:$AN$9,FY!J$2) -> 12.392 | K84: =SUMIFS(HY!$G$552:$AN$552,HY!$G$9:$AN$9,FY!K$2)+SUMIFS(HY!$G$554:$AN$554,HY!$G$9:$AN$9,FY!K$2) -> -0.043 | ... S84: =SUMIFS(HY!$G$552:$AN$552,HY!$G$9:$AN$9,FY!S$2)+SUMIFS(HY!$G$554:$AN$554,HY!$G$9:$AN$9,FY!S$2) -> 0
B85: ----- | D85: ----- | E85: ----- | F85: ----- | G85: ----- | H85: ----- | I85: ----- | J85: ----- | K85: ----- | L85: ----- | M85: ----- | N85: ----- | O85: ----- | P85: ----- | Q85: ----- | R85: ----- | S85: -----
B86: Investing cash flow | D86: =SUMIFS(HY!$G$556:$AD$556,HY!$G$9:$AD$9,FY!D$2) -> -116.483 | E86: =SUMIFS(HY!$G$556:$AD$556,HY!$G$9:$AD$9,FY!E$2) -> -99.269 | F86: =SUMIFS(HY!$G$556:$AD$556,HY!$G$9:$AD$9,FY!F$2) -> -251.579 | G86: =SUMIFS(HY!$G$556:$AD$556,HY!$G$9:$AD$9,FY!G$2) -> -31.679 | H86: =SUMIFS(HY!$G$556:$AD$556,HY!$G$9:$AD$9,FY!H$2) -> -51.436 | I86: =SUMIFS(HY!$G$556:$AD$556,HY!$G$9:$AD$9,FY!I$2) -> -319.412 | J86: =SUMIFS(HY!$G$556:$AD$556,HY!$G$9:$AD$9,FY!J$2) -> -94.698 | K86: =SUMIFS(HY!$G$556:$AD$556,HY!$G$9:$AD$9,FY!K$2) -> -113.67 | ... S86: =SUMIFS(HY!$G$556:$AD$556,HY!$G$9:$AD$9,FY!S$2) -> 0
B87: ICF Growth (%) | E87: =(E86/D86)-1 -> -0.14778122 | F87: =(F86/E86)-1 -> 1.5343158 | G87: =(G86/F86)-1 -> -0.87407932 | H87: =(H86/G86)-1 -> 0.62366236 | I87: =(I86/H86)-1 -> 5.2098919 | J87: =(J86/I86)-1 -> -0.70352398 | K87: =(K86/J86)-1 -> 0.20034214 | L87: =(L86/K86)-1 -> -2.7211811 | ... S87: =(S86/R86)-1 -> #DIV/0!
B89: Movement in borrowing | D89: =SUMIFS(HY!$G$565:$AN$565,HY!$G$9:$AN$9,FY!D$2) -> 36.587 | E89: =SUMIFS(HY!$G$565:$AN$565,HY!$G$9:$AN$9,FY!E$2) -> 92.873 | F89: =SUMIFS(HY!$G$565:$AN$565,HY!$G$9:$AN$9,FY!F$2) -> -30.111 | G89: =SUMIFS(HY!$G$565:$AN$565,HY!$G$9:$AN$9,FY!G$2) -> 42.676 | H89: =SUMIFS(HY!$G$565:$AN$565,HY!$G$9:$AN$9,FY!H$2) -> 40.887 | I89: =SUMIFS(HY!$G$565:$AN$565,HY!$G$9:$AN$9,FY!I$2) -> 39.564 | J89: =SUMIFS(HY!$G$565:$AN$565,HY!$G$9:$AN$9,FY!J$2) -> 47.541 | K89: =SUMIFS(HY!$G$565:$AN$565,HY!$G$9:$AN$9,FY!K$2) -> -150.014 | ... S89: =SUMIFS(HY!$G$565:$AN$565,HY!$G$9:$AN$9,FY!S$2) -> 0
B90: Equity Raised | D90: =SUMIFS(HY!$G$561:$AN$561,HY!$G$9:$AN$9,FY!D$2) -> 0 | E90: =SUMIFS(HY!$G$561:$AN$561,HY!$G$9:$AN$9,FY!E$2) -> 177.597 | F90: =SUMIFS(HY!$G$561:$AN$561,HY!$G$9:$AN$9,FY!F$2) -> 48.737 | G90: =SUMIFS(HY!$G$561:$AN$561,HY!$G$9:$AN$9,FY!G$2) -> 0 | H90: =SUMIFS(HY!$G$561:$AN$561,HY!$G$9:$AN$9,FY!H$2) -> 0 | I90: =SUMIFS(HY!$G$561:$AN$561,HY!$G$9:$AN$9,FY!I$2) -> 0 | J90: =SUMIFS(HY!$G$561:$AN$561,HY!$G$9:$AN$9,FY!J$2) -> 0 | K90: =SUMIFS(HY!$G$561:$AN$561,HY!$G$9:$AN$9,FY!K$2) -> 229.027 | ... S90: =SUMIFS(HY!$G$561:$AN$561,HY!$G$9:$AN$9,FY!S$2) -> 0
B91: Buybacks | D91: =SUMIFS(HY!$G$562:$AN$562,HY!$G$9:$AN$9,FY!D$2) -> 0 | E91: =SUMIFS(HY!$G$562:$AN$562,HY!$G$9:$AN$9,FY!E$2) -> -19.993 | F91: =SUMIFS(HY!$G$562:$AN$562,HY!$G$9:$AN$9,FY!F$2) -> 0 | G91: =SUMIFS(HY!$G$562:$AN$562,HY!$G$9:$AN$9,FY!G$2) -> 0 | H91: =SUMIFS(HY!$G$562:$AN$562,HY!$G$9:$AN$9,FY!H$2) -> 0 | I91: =SUMIFS(HY!$G$562:$AN$562,HY!$G$9:$AN$9,FY!I$2) -> 0 | J91: =SUMIFS(HY!$G$562:$AN$562,HY!$G$9:$AN$9,FY!J$2) -> 0 | K91: =SUMIFS(HY!$G$562:$AN$562,HY!$G$9:$AN$9,FY!K$2) -> 0 | ... S91: =SUMIFS(HY!$G$562:$AN$562,HY!$G$9:$AN$9,FY!S$2) -> 0
B92: Distributions paid | D92: =SUMIFS(HY!$G$563:$AN$563,HY!$G$9:$AN$9,FY!D$2) -> -127.098 | E92: =SUMIFS(HY!$G$563:$AN$563,HY!$G$9:$AN$9,FY!E$2) -> -133.288 | F92: =SUMIFS(HY!$G$563:$AN$563,HY!$G$9:$AN$9,FY!F$2) -> 0 | G92: =SUMIFS(HY!$G$563:$AN$563,HY!$G$9:$AN$9,FY!G$2) -> -53.082 | H92: =SUMIFS(HY!$G$563:$AN$563,HY!$G$9:$AN$9,FY!H$2) -> -45.533 | I92: =SUMIFS(HY!$G$563:$AN$563,HY!$G$9:$AN$9,FY!I$2) -> -85.382 | J92: =SUMIFS(HY!$G$563:$AN$563,HY!$G$9:$AN$9,FY!J$2) -> 0 | K92: =SUMIFS(HY!$G$563:$AN$563,HY!$G$9:$AN$9,FY!K$2) -> 0 | ... S92: =SUMIFS(HY!$G$563:$AN$563,HY!$G$9:$AN$9,FY!S$2) -> -90.707364
B93: Minority Distributions paid | D93: =SUMIFS(HY!$G$564:$AN$564,HY!$G$9:$AN$9,FY!D$2) -> 0 | E93: =SUMIFS(HY!$G$564:$AN$564,HY!$G$9:$AN$9,FY!E$2) -> 0 | F93: =SUMIFS(HY!$G$564:$AN$564,HY!$G$9:$AN$9,FY!F$2) -> 0 | G93: =SUMIFS(HY!$G$564:$AN$564,HY!$G$9:$AN$9,FY!G$2) -> 0 | H93: =SUMIFS(HY!$G$564:$AN$564,HY!$G$9:$AN$9,FY!H$2) -> 0 | I93: =SUMIFS(HY!$G$564:$AN$564,HY!$G$9:$AN$9,FY!I$2) -> 0 | J93: =SUMIFS(HY!$G$564:$AN$564,HY!$G$9:$AN$9,FY!J$2) -> 0 | K93: =SUMIFS(HY!$G$564:$AN$564,HY!$G$9:$AN$9,FY!K$2) -> 0 | ... S93: =SUMIFS(HY!$G$564:$AN$564,HY!$G$9:$AN$9,FY!S$2) -> 0
B94: Other | D94: =SUMIFS(HY!$G$566:$AN$566,HY!$G$9:$AN$9,FY!D$2) -> -80.434 | E94: =SUMIFS(HY!$G$566:$AN$566,HY!$G$9:$AN$9,FY!E$2) -> -126.496 | F94: =SUMIFS(HY!$G$566:$AN$566,HY!$G$9:$AN$9,FY!F$2) -> -57.202 | G94: =SUMIFS(HY!$G$566:$AN$566,HY!$G$9:$AN$9,FY!G$2) -> -52.179 | H94: =SUMIFS(HY!$G$566:$AN$566,HY!$G$9:$AN$9,FY!H$2) -> -33.865 | I94: =SUMIFS(HY!$G$566:$AN$566,HY!$G$9:$AN$9,FY!I$2) -> -29.072 | J94: =SUMIFS(HY!$G$566:$AN$566,HY!$G$9:$AN$9,FY!J$2) -> 19.733 | K94: =SUMIFS(HY!$G$566:$AN$566,HY!$G$9:$AN$9,FY!K$2) -> -12.091 | ... S94: =SUMIFS(HY!$G$566:$AN$566,HY!$G$9:$AN$9,FY!S$2) -> 0
B95: ----- | D95: ----- | E95: ----- | F95: ----- | G95: ----- | H95: ----- | I95: ----- | J95: ----- | K95: ----- | L95: ----- | M95: ----- | N95: ----- | O95: ----- | P95: ----- | Q95: ----- | R95: ----- | S95: -----
B96: Financing cash flow | D96: =SUMIFS(HY!$G$567:$AN$567,HY!$G$9:$AN$9,FY!D$2) -> -170.945 | E96: =SUMIFS(HY!$G$567:$AN$567,HY!$G$9:$AN$9,FY!E$2) -> -9.307 | F96: =SUMIFS(HY!$G$567:$AN$567,HY!$G$9:$AN$9,FY!F$2) -> -38.576 | G96: =SUMIFS(HY!$G$567:$AN$567,HY!$G$9:$AN$9,FY!G$2) -> -62.585 | H96: =SUMIFS(HY!$G$567:$AN$567,HY!$G$9:$AN$9,FY!H$2) -> -38.511 | I96: =SUMIFS(HY!$G$567:$AN$567,HY!$G$9:$AN$9,FY!I$2) -> -74.89 | J96: =SUMIFS(HY!$G$567:$AN$567,HY!$G$9:$AN$9,FY!J$2) -> 40.499 | K96: =SUMIFS(HY!$G$567:$AN$567,HY!$G$9:$AN$9,FY!K$2) -> 24.91 | ... S96: =SUMIFS(HY!$G$567:$AN$567,HY!$G$9:$AN$9,FY!S$2) -> -101.32701
B98: Change in cash and cash equivalents | D98: =SUMIFS(HY!$G$570:$AN$570,HY!$G$9:$AN$9,FY!D$2) -> -34.381 | E98: =SUMIFS(HY!$G$570:$AN$570,HY!$G$9:$AN$9,FY!E$2) -> 12.65 | F98: =SUMIFS(HY!$G$570:$AN$570,HY!$G$9:$AN$9,FY!F$2) -> -4.284 | G98: =SUMIFS(HY!$G$570:$AN$570,HY!$G$9:$AN$9,FY!G$2) -> -1.242 | H98: =SUMIFS(HY!$G$570:$AN$570,HY!$G$9:$AN$9,FY!H$2) -> 196.315 | I98: =SUMIFS(HY!$G$570:$AN$570,HY!$G$9:$AN$9,FY!I$2) -> -184.477 | J98: =SUMIFS(HY!$G$570:$AN$570,HY!$G$9:$AN$9,FY!J$2) -> -9.037 | K98: =SUMIFS(HY!$G$570:$AN$570,HY!$G$9:$AN$9,FY!K$2) -> 32.916 | ... S98: =SUMIFS(HY!$G$570:$AN$570,HY!$G$9:$AN$9,FY!S$2) -> 32.204458
B99: FX adjustments | D99: =SUMIFS(HY!$G$571:$AN$571,HY!$G$9:$AN$9,FY!D$2) -> 0 | E99: =SUMIFS(HY!$G$571:$AN$571,HY!$G$9:$AN$9,FY!E$2) -> 0 | F99: =SUMIFS(HY!$G$571:$AN$571,HY!$G$9:$AN$9,FY!F$2) -> 0 | G99: =SUMIFS(HY!$G$571:$AN$571,HY!$G$9:$AN$9,FY!G$2) -> 0 | H99: =SUMIFS(HY!$G$571:$AN$571,HY!$G$9:$AN$9,FY!H$2) -> 0 | I99: =SUMIFS(HY!$G$571:$AN$571,HY!$G$9:$AN$9,FY!I$2) -> 0 | J99: =SUMIFS(HY!$G$571:$AN$571,HY!$G$9:$AN$9,FY!J$2) -> 0 | K99: =SUMIFS(HY!$G$571:$AN$571,HY!$G$9:$AN$9,FY!K$2) -> 0 | ... S99: =SUMIFS(HY!$G$571:$AN$571,HY!$G$9:$AN$9,FY!S$2) -> 0
B100: Net cash flow | D100: =D98+D99 -> -34.381 | E100: =E98+E99 -> 12.65 | F100: =F98+F99 -> -4.284 | G100: =G98+G99 -> -1.242 | H100: =H98+H99 -> 196.315 | I100: =I98+I99 -> -184.477 | J100: =J98+J99 -> -9.037 | K100: =K98+K99 -> 32.916 | ... S100: =S98+S99 -> 32.204458
B101: Opening cash | D101: =C102 -> 75.955 | E101: =D102 -> 41.574 | F101: =E102 -> 54.224 | G101: =F102 -> 49.94 | H101: =G102 -> 48.698 | I101: =H102 -> 245.013 | J101: =I102 -> 60.536 | K101: =J102 -> 51.499 | ... S101: =R102 -> 469.15869
B102: Closing cash | C102: =HY!F573 -> 75.955 | D102: =INDEX(HY!$G573:$AN573,MATCH(D$3,HY!$G$4:$AN$4,0)) -> 41.574 | E102: =INDEX(HY!$G573:$AN573,MATCH(E$3,HY!$G$4:$AN$4,0)) -> 54.224 | F102: =INDEX(HY!$G573:$AN573,MATCH(F$3,HY!$G$4:$AN$4,0)) -> 49.94 | G102: =INDEX(HY!$G573:$AN573,MATCH(G$3,HY!$G$4:$AN$4,0)) -> 48.698 | H102: =INDEX(HY!$G573:$AN573,MATCH(H$3,HY!$G$4:$AN$4,0)) -> 245.013 | I102: =INDEX(HY!$G573:$AN573,MATCH(I$3,HY!$G$4:$AN$4,0)) -> 60.536 | J102: =INDEX(HY!$G573:$AN573,MATCH(J$3,HY!$G$4:$AN$4,0)) -> 51.499 | K102: =INDEX(HY!$G573:$AN573,MATCH(K$3,HY!$G$4:$AN$4,0)) -> 84.415 | ... S102: =INDEX(HY!$G573:$AN573,MATCH(S$3,HY!$G$4:$AN$4,0)) -> 501.36315
B104: Check | D104: =D102-(D101+D78+D86+D96) -> 0 | E104: =E102-(E101+E78+E86+E96) -> 0 | F104: =F102-(F101+F78+F86+F96) -> 0 | G104: =G102-(G101+G78+G86+G96) -> 0 | H104: =H102-(H101+H78+H86+H96) -> 0 | I104: =I102-(I101+I78+I86+I96) -> 0 | J104: =J102-(J101+J78+J86+J96) -> 0 | K104: =K102-(K101+K78+K86+K96) -> 0 | ... S104: =S102-(S101+S78+S86+S96) -> -98.310646
A106: X | B106: BALANCE SHEET | D106: 2019A | E106: 2020A | F106: 2021 | G106: 2022 | H106: 2023 | I106: 2024 | J106: 2025 | K106: 2026 | L106: 2027 | M106: 2028 | N106: 2029 | O106: 2030 | P106: 2030 | Q106: 2030 | R106: 2030 | S106: 2030
B107: Cash | D107: =INDEX(HY!$G578:$AN578,MATCH(D$3,HY!$G$4:$AN$4,0)) -> 41.574 | E107: =INDEX(HY!$G578:$AN578,MATCH(E$3,HY!$G$4:$AN$4,0)) -> 54.224 | F107: =INDEX(HY!$G578:$AN578,MATCH(F$3,HY!$G$4:$AN$4,0)) -> 49.94 | G107: =INDEX(HY!$G578:$AN578,MATCH(G$3,HY!$G$4:$AN$4,0)) -> 48.698 | H107: =INDEX(HY!$G578:$AN578,MATCH(H$3,HY!$G$4:$AN$4,0)) -> 245.013 | I107: =INDEX(HY!$G578:$AN578,MATCH(I$3,HY!$G$4:$AN$4,0)) -> 60.536 | J107: =INDEX(HY!$G578:$AN578,MATCH(J$3,HY!$G$4:$AN$4,0)) -> 51.499 | K107: =INDEX(HY!$G578:$AN578,MATCH(K$3,HY!$G$4:$AN$4,0)) -> 84.415 | ... S107: =INDEX(HY!$G578:$AN578,MATCH(S$3,HY!$G$4:$AN$4,0)) -> 501.36315
B108: Receivables | D108: =INDEX(HY!$G579:$AN579,MATCH(D$3,HY!$G$4:$AN$4,0)) -> 49.293 | E108: =INDEX(HY!$G579:$AN579,MATCH(E$3,HY!$G$4:$AN$4,0)) -> 42.252 | F108: =INDEX(HY!$G579:$AN579,MATCH(F$3,HY!$G$4:$AN$4,0)) -> 33.405 | G108: =INDEX(HY!$G579:$AN579,MATCH(G$3,HY!$G$4:$AN$4,0)) -> 25.826 | H108: =INDEX(HY!$G579:$AN579,MATCH(H$3,HY!$G$4:$AN$4,0)) -> 50.833 | I108: =INDEX(HY!$G579:$AN579,MATCH(I$3,HY!$G$4:$AN$4,0)) -> 86.878 | J108: =INDEX(HY!$G579:$AN579,MATCH(J$3,HY!$G$4:$AN$4,0)) -> 23.98 | K108: =INDEX(HY!$G579:$AN579,MATCH(K$3,HY!$G$4:$AN$4,0)) -> 29.821 | ... S108: =INDEX(HY!$G579:$AN579,MATCH(S$3,HY!$G$4:$AN$4,0)) -> 39.442211
B109: Inventory | D109: =INDEX(HY!$G580:$AN580,MATCH(D$3,HY!$G$4:$AN$4,0)) -> 6.459 | E109: =INDEX(HY!$G580:$AN580,MATCH(E$3,HY!$G$4:$AN$4,0)) -> 6.628 | F109: =INDEX(HY!$G580:$AN580,MATCH(F$3,HY!$G$4:$AN$4,0)) -> 7.187 | G109: =INDEX(HY!$G580:$AN580,MATCH(G$3,HY!$G$4:$AN$4,0)) -> 7.528 | H109: =INDEX(HY!$G580:$AN580,MATCH(H$3,HY!$G$4:$AN$4,0)) -> 8.582 | I109: =INDEX(HY!$G580:$AN580,MATCH(I$3,HY!$G$4:$AN$4,0)) -> 8.375 | J109: =INDEX(HY!$G580:$AN580,MATCH(J$3,HY!$G$4:$AN$4,0)) -> 8.111 | K109: =INDEX(HY!$G580:$AN580,MATCH(K$3,HY!$G$4:$AN$4,0)) -> 8.194 | ... S109: =INDEX(HY!$G580:$AN580,MATCH(S$3,HY!$G$4:$AN$4,0)) -> 10.541189
B110: Tax Assets | D110: =INDEX(HY!$G581:$AN581,MATCH(D$3,HY!$G$4:$AN$4,0)) -> 0.93 | E110: =INDEX(HY!$G581:$AN581,MATCH(E$3,HY!$G$4:$AN$4,0)) -> 1.989 | F110: =INDEX(HY!$G581:$AN581,MATCH(F$3,HY!$G$4:$AN$4,0)) -> 0 | G110: =INDEX(HY!$G581:$AN581,MATCH(G$3,HY!$G$4:$AN$4,0)) -> 4.431 | H110: =INDEX(HY!$G581:$AN581,MATCH(H$3,HY!$G$4:$AN$4,0)) -> 0.012 | I110: =INDEX(HY!$G581:$AN581,MATCH(I$3,HY!$G$4:$AN$4,0)) -> 0.007 | J110: =INDEX(HY!$G581:$AN581,MATCH(J$3,HY!$G$4:$AN$4,0)) -> 0 | K110: =INDEX(HY!$G581:$AN581,MATCH(K$3,HY!$G$4:$AN$4,0)) -> 29.086 | ... S110: =INDEX(HY!$G581:$AN581,MATCH(S$3,HY!$G$4:$AN$4,0)) -> 29.086
B111: Assets Held for Sale | D111: =INDEX(HY!$G582:$AN582,MATCH(D$3,HY!$G$4:$AN$4,0)) -> 115.687 | E111: =INDEX(HY!$G582:$AN582,MATCH(E$3,HY!$G$4:$AN$4,0)) -> 11.019 | F111: =INDEX(HY!$G582:$AN582,MATCH(F$3,HY!$G$4:$AN$4,0)) -> 13.517 | G111: =INDEX(HY!$G582:$AN582,MATCH(G$3,HY!$G$4:$AN$4,0)) -> 26.646 | H111: =INDEX(HY!$G582:$AN582,MATCH(H$3,HY!$G$4:$AN$4,0)) -> 0 | I111: =INDEX(HY!$G582:$AN582,MATCH(I$3,HY!$G$4:$AN$4,0)) -> 13 | J111: =INDEX(HY!$G582:$AN582,MATCH(J$3,HY!$G$4:$AN$4,0)) -> 0 | K111: =INDEX(HY!$G582:$AN582,MATCH(K$3,HY!$G$4:$AN$4,0)) -> 74.056 | ... S111: =INDEX(HY!$G582:$AN582,MATCH(S$3,HY!$G$4:$AN$4,0)) -> 0
B112: Other | D112: =INDEX(HY!$G583:$AN583,MATCH(D$3,HY!$G$4:$AN$4,0)) -> 0.085 | E112: =INDEX(HY!$G583:$AN583,MATCH(E$3,HY!$G$4:$AN$4,0)) -> 102.859 | F112: =INDEX(HY!$G583:$AN583,MATCH(F$3,HY!$G$4:$AN$4,0)) -> 175.508 | G112: =INDEX(HY!$G583:$AN583,MATCH(G$3,HY!$G$4:$AN$4,0)) -> 212.838 | H112: =INDEX(HY!$G583:$AN583,MATCH(H$3,HY!$G$4:$AN$4,0)) -> 14.102 | I112: =INDEX(HY!$G583:$AN583,MATCH(I$3,HY!$G$4:$AN$4,0)) -> 20.393 | J112: =INDEX(HY!$G583:$AN583,MATCH(J$3,HY!$G$4:$AN$4,0)) -> 0.165 | K112: =INDEX(HY!$G583:$AN583,MATCH(K$3,HY!$G$4:$AN$4,0)) -> 30.017 | ... S112: =INDEX(HY!$G583:$AN583,MATCH(S$3,HY!$G$4:$AN$4,0)) -> 30.017
...

Sheet II

Sheet FT Tables
Q1: EBITDA
C3: SkyCity 1H26 Result - Headline (NZ$m) | BV3: SkyCity FY26 Result - Headline (NZ$m)
D4: 1H22A | E4: 2H22A | F4: 1H23A | G4: 2H23A | H4: 1H24A | I4: 2H24E | J4: 1H25E | K4: 2H25E | L4: 1H26E | M4: 2H26E | N4: 1H27E | O4: 2H27E | Q4: 1H25A | R4: ="1H26A" -> 1H26A | S4: % change | T4: E&Pe 1H26E | U4: % diff | V4: VA Cons. 1H26E | W4: % diff | AB4: 1H25 | AG4: 1H22 | AH4: 2H22 | AI4: 1H23 | AJ4: 2H23 | AK4: 1H24 | AL4: 2H24 | AM4: 1H25 | AN4: 2H25 | AO4: 1H26 | AP4: 2H26 | AQ4: 1H27 | AR4: 2H27 | AT4: 1H22 | AU4: 2H22 | AV4: 1H23 | AW4: 2H23 | AX4: 1H24 | AY4: 2H24 | AZ4: 1H25 | BA4: 2H25 | BB4: 1H26 | BC4: 2H26 | BD4: 1H27 | BE4: 2H27 | BG4: 1H22 | BH4: 2H22 | BI4: 1H23 | BJ4: 2H23 | BK4: 1H24 | BL4: 2H24 | BM4: 1H25 | BN4: 2H25 | BO4: 1H26 | BP4: 2H26 | BQ4: 1H27 | BR4: 2H27 | BW4: FY22A | BX4: FY23A | BY4: FY24E | BZ4: FY25E | CA4: FY26E | CB4: FY27E | CD4: FY25A | CE4: ="FY26A" -> FY26A | CF4: % change | CG4: E&Pe FY26E | CH4: % diff | CI4: VA Cons. FY26E | CJ4: % diff | CM4: FY24 | CR4: FY22 | CS4: FY23 | CT4: FY24 | CU4: FY25 | CV4: FY26 | CW4: FY27 | CY4: FY22 | CZ4: FY23 | DA4: FY24 | DB4: FY25 | DC4: FY26 | DD4: FY27 | DF4: FY22 | DG4: FY23 | DH4: FY24 | DI4: FY25 | DJ4: FY26 | DK4: FY27
C5: P&L - Normalised | BV5: P&L - Normalised
C6: Revenue | F6: =HY!O311 -> 438.9 | G6: =HY!P311 -> 423.7 | H6: =HY!Q311 -> 442.8 | I6: =HY!R311 -> 427.7 | J6: =HY!S311 -> 422 | K6: =HY!T311 -> 403.2 | L6: =HY!U311 -> 411.7 | M6: =HY!V311 -> 411 | ... O6: =HY!X311 -> 421.369 | Q6: =J6 -> 422 | R6: 411.7 | S6: =R6/Q6-1 -> -0.024407583 | T6: =L6 -> 411.7 | U6: =$R6/T6-1 -> 0 | V6: =AB6 -> 385.86341 | W6: =$R6/V6-1 -> 0.066957865 | AB6: =BB6 -> 385.86341 | AD6: SKC_NZ | AE6: Total revenue - Operating | AF6: consensus.vaactuals | AG6: =_xll.VAData($AD6,AG$4,$AE6,$AF6) -> 260.8 | AH6: =_xll.VAData($AD6,AH$4,$AE6,$AF6) -> 370.7 | AI6: =_xll.VAData($AD6,AI$4,$AE6,$AF6) -> 438.9 | AJ6: =_xll.VAData($AD6,AJ$4,$AE6,$AF6) -> 423.7 | AK6: =_xll.VAData($AD6,AK$4,$AE6,$AF6) -> 442.8 | AL6: =_xll.VAData($AD6,AL$4,$AE6,$AF6) -> 427.702 | AM6: =_xll.VAData($AD6,AM$4,$AE6,$AF6) -> 422 | AN6: =_xll.VAData($AD6,AN$4,$AE6,$AF6) -> 403.2 | ... AR6: =_xll.VAData($AD6,AR$4,$AE6,$AF6) -> 403.74455 | AT6: 260.8 | AU6: 370.7 | AV6: 438.9 | AW6: 423.7 | AX6: 442.8 | AY6: 427.7 | AZ6: 422 | BA6: 403.2 | BB6: 385.86341 | BC6: 402.90399 | BD6: 430.51721 | BE6: 434.22619 | BI6: =F6-AV6 -> 0 | BJ6: =G6-AW6 -> 0 | BK6: =H6-AX6 -> 0 | BL6: =I6-AY6 -> 0 | BM6: =J6-AZ6 -> 0 | BN6: =K6-BA6 -> 0 | BO6: =L6-BB6 -> 25.83659 | BP6: =M6-BC6 -> 8.0960121 | ... BR6: =O6-BE6 -> -12.857194 | BV6: Revenue | BW6: =FY!G25 -> 575.42004 | BX6: =FY!H25 -> 862.6 | BY6: =FY!I25 -> 870.5 | BZ6: =FY!J25 -> 825.2 | CA6: =FY!K25 -> 822.7 | CB6: =FY!L25 -> 840.934 | CD6: =BZ6 -> 825.2 | CE6: 822.7 | CF6: =CE6/CD6-1 -> -0.0030295686 | CG6: =CA6 -> 822.7 | CH6: =$CE6/CG6-1 -> 0 | CI6: =CM6 -> 815.21503 | CJ6: =$CE6/CI6-1 -> 0.00918159 | CM6: =DC6 -> 815.21503 | CO6: SKC_NZ | CP6: Total revenue - Operating | CQ6: consensus.vaactuals | CR6: =_xll.VAData($AD6,CR$4,$AE6,$AF6) -> 631.5 | CS6: =_xll.VAData($AD6,CS$4,$AE6,$AF6) -> 862.6 | CT6: =_xll.VAData($AD6,CT$4,$AE6,$AF6) -> 870.5 | CU6: =_xll.VAData($AD6,CU$4,$AE6,$AF6) -> 825.2 | CV6: =_xll.VAData($AD6,CV$4,$AE6,$AF6) -> 822.7 | CW6: =_xll.VAData($AD6,CW$4,$AE6,$AF6) -> 824.73077 | CY6: 631.5 | CZ6: 862.6 | DA6: 870.5 | DB6: 825.2 | DC6: 815.21503 | DD6: 851.50262 | DF6: =BW6-CY6 -> -56.079956 | DG6: =BX6-CZ6 -> 0 | DH6: =BY6-DA6 -> 0 | DI6: =BZ6-DB6 -> 0 | DJ6: =CA6-DC6 -> 7.4849702 | DK6: =CB6-DD6 -> -10.568621
C7: EBITDA | F7: =HY!O325 -> 161.8 | G7: =HY!P325 -> 140 | H7: =HY!Q325 -> 144.3 | I7: =HY!R325 -> 133.5 | J7: =HY!S325 -> 119.5 | K7: =HY!T325 -> 114.2 | L7: =HY!U325 -> 85.5 | M7: =HY!V325 -> 96.1 | ... O7: =HY!X325 -> 94.050503 | Q7: 119.5 | R7: 85.5 | S7: =R7/Q7-1 -> -0.28451883 | T7: =L7 -> 85.5 | U7: =$R7/T7-1 -> 0 | V7: =AB7 -> 88.187782 | W7: =$R7/V7-1 -> -0.030477938 | AB7: =BB7 -> 88.187782 | AD7: SKC_NZ | AE7: EBITDA - Operating | AF7: consensus.vaactuals | AG7: =_xll.VAData($AD7,AG$4,$AE7,$AF7) -> 36.2 | AH7: =_xll.VAData($AD7,AH$4,$AE7,$AF7) -> 101.7 | AI7: =_xll.VAData($AD7,AI$4,$AE7,$AF7) -> 161.8 | AJ7: =_xll.VAData($AD7,AJ$4,$AE7,$AF7) -> 140 | AK7: =_xll.VAData($AD7,AK$4,$AE7,$AF7) -> 144.25346 | AL7: =_xll.VAData($AD7,AL$4,$AE7,$AF7) -> 133.5 | AM7: =_xll.VAData($AD7,AM$4,$AE7,$AF7) -> 119.529 | AN7: =_xll.VAData($AD7,AN$4,$AE7,$AF7) -> 114.2 | ... AR7: =_xll.VAData($AD7,AR$4,$AE7,$AF7) -> 93.164145 | AT7: 36.2 | AU7: 101.7 | AV7: 161.7 | AW7: 140.1 | AX7: 144.3 | AY7: 133.5 | AZ7: 113.1 | BA7: 120.6 | BB7: 88.187782 | BC7: 106.32547 | BD7: 108.19785 | BE7: 118.38289 | BI7: =F7-AV7 -> 0.1 | BJ7: =G7-AW7 -> -0.1 | BK7: =H7-AX7 -> 0 | BL7: =I7-AY7 -> 0 | BM7: =J7-AZ7 -> 6.4 | BN7: =K7-BA7 -> -6.4 | BO7: =L7-BB7 -> -2.6877817 | BP7: =M7-BC7 -> -10.22547 | ... BR7: =O7-BE7 -> -24.332389 | BV7: EBITDA | BW7: =FY!G29 -> 137.9 | BX7: =FY!H29 -> 301.8 | BY7: =FY!I29 -> 277.8 | BZ7: =FY!J29 -> 233.7 | CA7: =FY!K29 -> 181.6 | CB7: =FY!L29 -> 183.18614 | CD7: =BZ7 -> 233.7 | CE7: 181.6 | CF7: =CE7/CD7-1 -> -0.22293539 | CG7: =CA7 -> 181.6 | CH7: =$CE7/CG7-1 -> 0 | CI7: =CM7 -> 182.49152 | CJ7: =$CE7/CI7-1 -> -0.0048852946 | CM7: =DC7 -> 182.49152 | CO7: SKC_NZ | CP7: EBITDA - Operating | CQ7: consensus.vaactuals | CR7: =_xll.VAData($AD7,CR$4,$AE7,$AF7) -> 137.9 | CS7: =_xll.VAData($AD7,CS$4,$AE7,$AF7) -> 301.8 | CT7: =_xll.VAData($AD7,CT$4,$AE7,$AF7) -> 277.8 | CU7: =_xll.VAData($AD7,CU$4,$AE7,$AF7) -> 233.7 | CV7: =_xll.VAData($AD7,CV$4,$AE7,$AF7) -> 181.6 | CW7: =_xll.VAData($AD7,CW$4,$AE7,$AF7) -> 181.26337 | CY7: 137.9 | CZ7: 301.8 | DA7: 277.8 | DB7: 233.7 | DC7: 182.49152 | DD7: 197.49483 | DF7: =BW7-CY7 -> 0 | DG7: =BX7-CZ7 -> 0 | DH7: =BY7-DA7 -> 0 | DI7: =BZ7-DB7 -> 0 | DJ7: =CA7-DC7 -> -0.89152487 | DK7: =CB7-DD7 -> -14.308693
C8: EBIT | F8: =HY!O338 -> 116.336 | G8: =HY!P338 -> 94.792 | H8: =HY!Q338 -> 100.053 | I8: =HY!R338 -> 85.726 | J8: =HY!S338 -> 74.171 | K8: =HY!T338 -> 65.316 | L8: =HY!U338 -> 35.621 | M8: =HY!V338 -> 42.522 | ... O8: =HY!X338 -> 41.32371 | Q8: =J8 -> 74.171 | S8: =R8/Q8-1 -> -1 | T8: =L8 -> 35.621 | U8: =$R8/T8-1 -> -1 | V8: =AB8 -> 35.083138 | W8: =$R8/V8-1 -> -1 | AB8: =BB8 -> 35.083138 | AD8: SKC_NZ | AE8: Operating income/(loss) - Operating | AF8: consensus.vaactuals | AG8: =_xll.VAData($AD8,AG$4,$AE8,$AF8) -> -11.6 | AH8: =_xll.VAData($AD8,AH$4,$AE8,$AF8) -> 54.8 | AI8: =_xll.VAData($AD8,AI$4,$AE8,$AF8) -> 116.3 | AJ8: =_xll.VAData($AD8,AJ$4,$AE8,$AF8) -> 94.8 | AK8: =_xll.VAData($AD8,AK$4,$AE8,$AF8) -> 100 | AL8: =_xll.VAData($AD8,AL$4,$AE8,$AF8) -> 85.8 | AM8: =_xll.VAData($AD8,AM$4,$AE8,$AF8) -> 74.201015 | AN8: =_xll.VAData($AD8,AN$4,$AE8,$AF8) -> 65.3 | ... AR8: =_xll.VAData($AD8,AR$4,$AE8,$AF8) -> 36.268601 | AT8: -17.6 | AU8: 54.8 | AV8: 116.3 | AW8: 94.8 | AX8: 100 | AY8: 85.8 | AZ8: 67.8 | BA8: 71.7 | BB8: 35.083138 | BC8: 52.515608 | BD8: 53.556982 | BE8: 59.38207 | BI8: =F8-AV8 -> 0.036 | BJ8: =G8-AW8 -> -0.008 | BK8: =H8-AX8 -> 0.053 | BL8: =I8-AY8 -> -0.074 | BM8: =J8-AZ8 -> 6.371 | BN8: =K8-BA8 -> -6.384 | BO8: =L8-BB8 -> 0.53786181 | BP8: =M8-BC8 -> -9.9936078 | ... BR8: =O8-BE8 -> -18.058359 | BV8: EBIT | CD8: =BZ8 -> 0 | CF8: =CE8/CD8-1 -> #DIV/0! | CG8: =CA8 -> 0 | CH8: =$CE8/CG8-1 -> #DIV/0! | CI8: =CM8 -> 76.887933 | CJ8: =$CE8/CI8-1 -> -1 | CM8: =DC8 -> 76.887933 | CO8: SKC_NZ | CP8: Operating income/(loss) - Operating | CQ8: consensus.vaactuals | CR8: =_xll.VAData($AD8,CR$4,$AE8,$AF8) -> 43.3 | CS8: =_xll.VAData($AD8,CS$4,$AE8,$AF8) -> 211.1 | CT8: =_xll.VAData($AD8,CT$4,$AE8,$AF8) -> 185.8 | CU8: =_xll.VAData($AD8,CU$4,$AE8,$AF8) -> 139.5 | CV8: =_xll.VAData($AD8,CV$4,$AE8,$AF8) -> 76.5 | CW8: =_xll.VAData($AD8,CW$4,$AE8,$AF8) -> 66.937245 | CY8: 43.3 | CZ8: 211.1 | DA8: 185.8 | DB8: 139.5 | DC8: 76.887933 | DD8: 88.292753 | DF8: =BW8-CY8 -> -43.3 | DG8: =BX8-CZ8 -> -211.1 | DH8: =BY8-DA8 -> -185.8 | DI8: =BZ8-DB8 -> -139.5 | DJ8: =CA8-DC8 -> -76.887933 | DK8: =CB8-DD8 -> -88.292753
C9: NPAT | F9: =HY!O348 -> 72.8 | G9: =HY!P348 -> 59.9 | H9: =HY!Q348 -> 64.5 | I9: =HY!R348 -> 58.7 | J9: =HY!S348 -> 44.2 | K9: =HY!T348 -> 27.3 | L9: =HY!U348 -> 14.4 | M9: =HY!V348 -> 23.6 | ... O9: =HY!X348 -> 21.030314 | Q9: =J9 -> 44.2 | R9: 14.4 | S9: =R9/Q9-1 -> -0.67420814 | T9: =L9 -> 14.4 | U9: =$R9/T9-1 -> 0 | V9: =AB9 -> 10.080031 | W9: =$R9/V9-1 -> 0.42856702 | AB9: =BB9 -> 10.080031 | AD9: SKC_NZ | AE9: Net income/(loss) - Operating | AF9: consensus.vaactuals | AG9: =_xll.VAData($AD9,AG$4,$AE9,$AF9) -> -19.5 | AH9: =_xll.VAData($AD9,AH$4,$AE9,$AF9) -> 29.2 | AI9: =_xll.VAData($AD9,AI$4,$AE9,$AF9) -> 72.8 | AJ9: =_xll.VAData($AD9,AJ$4,$AE9,$AF9) -> 60 | AK9: =_xll.VAData($AD9,AK$4,$AE9,$AF9) -> 64.503335 | AL9: =_xll.VAData($AD9,AL$4,$AE9,$AF9) -> 58.7 | AM9: =_xll.VAData($AD9,AM$4,$AE9,$AF9) -> 44.2 | AN9: =_xll.VAData($AD9,AN$4,$AE9,$AF9) -> 27.3 | ... AR9: =_xll.VAData($AD9,AR$4,$AE9,$AF9) -> 15.845529 | AT9: -19.5 | AU9: 29.3 | AV9: 72.8 | AW9: 60 | AX9: 64.5 | AY9: 58.7 | AZ9: 37.8 | BA9: 33.7 | BB9: 10.080031 | BC9: 21.188801 | BD9: 24.288062 | BE9: 28.693163 | BI9: =F9-AV9 -> 0 | BJ9: =G9-AW9 -> -0.1 | BK9: =H9-AX9 -> 0 | BL9: =I9-AY9 -> 0 | BM9: =J9-AZ9 -> 6.4 | BN9: =K9-BA9 -> -6.4 | BO9: =L9-BB9 -> 4.3199689 | BP9: =M9-BC9 -> 2.4111986 | ... BR9: =O9-BE9 -> -7.6628485 | BV9: NPAT | BW9: =FY!G41 -> 9.7 | BX9: =FY!H41 -> 132.7 | BY9: =FY!I41 -> 123.2 | BZ9: =FY!J41 -> 71.5 | CA9: =FY!K41 -> 38 | CB9: =FY!L41 -> 30.450323 | CD9: =BZ9 -> 71.5 | CE9: 38 | CF9: =CE9/CD9-1 -> -0.46853147 | CG9: =CA9 -> 38 | CH9: =$CE9/CG9-1 -> 0 | CI9: =CM9 -> 28.643992 | CJ9: =$CE9/CI9-1 -> 0.32663075 | CM9: =DC9 -> 28.643992 | CO9: SKC_NZ | CP9: Net income/(loss) - Operating | CQ9: consensus.vaactuals | CR9: =_xll.VAData($AD9,CR$4,$AE9,$AF9) -> 9.7 | CS9: =_xll.VAData($AD9,CS$4,$AE9,$AF9) -> 132.8 | CT9: =_xll.VAData($AD9,CT$4,$AE9,$AF9) -> 123.2 | CU9: =_xll.VAData($AD9,CU$4,$AE9,$AF9) -> 71.5 | CV9: =_xll.VAData($AD9,CV$4,$AE9,$AF9) -> 38 | CW9: =_xll.VAData($AD9,CW$4,$AE9,$AF9) -> 23.612459 | CY9: 9.7 | CZ9: 132.8 | DA9: 123.2 | DB9: 71.5 | DC9: 28.643992 | DD9: 35.23831 | DF9: =BW9-CY9 -> 0 | DG9: =BX9-CZ9 -> -0.1 | DH9: =BY9-DA9 -> 0 | DI9: =BZ9-DB9 -> 0 | DJ9: =CA9-DC9 -> 9.3560084 | DK9: =CB9-DD9 -> -4.7879876
C10: EPS (cps) | F10: =HY!O349 -> 9.6 | G10: =HY!P349 -> 8.7 | H10: =HY!Q349 -> 8.8 | I10: =HY!R349 -> 7.4 | J10: =HY!S349 -> 5 | K10: =HY!T349 -> 4.4 | L10: =HY!U349 -> 1.5 | M10: =HY!V349 -> 2.2 | ... O10: =HY!X349 -> 1.9065517 | Q10: =J10 -> 5 | R10: 1.5 | S10: =R10/Q10-1 -> -0.7 | T10: =L10 -> 1.5 | U10: =$R10/T10-1 -> 0 | V10: =AB10 -> 1.1334306 | W10: =$R10/V10-1 -> 0.32341584 | AB10: =BB10 -> 1.1334306 | AD10: SKC_NZ | AE10: EPS - Basic - Operating | AF10: consensus.vaactuals | AG10: =_xll.VAData($AD10,AG$4,$AE10,$AF10) -> -2.5651057 | AH10: =_xll.VAData($AD10,AH$4,$AE10,$AF10) -> 3.9 | AI10: =_xll.VAData($AD10,AI$4,$AE10,$AF10) -> 9.6 | AJ10: =_xll.VAData($AD10,AJ$4,$AE10,$AF10) -> 7.9143433 | AK10: =_xll.VAData($AD10,AK$4,$AE10,$AF10) -> 8.8 | AL10: =_xll.VAData($AD10,AL$4,$AE10,$AF10) -> 7.4 | AM10: =_xll.VAData($AD10,AM$4,$AE10,$AF10) -> 5 | AN10: =_xll.VAData($AD10,AN$4,$AE10,$AF10) -> 3.5963322 | ... AR10: =_xll.VAData($AD10,AR$4,$AE10,$AF10) -> 1.436513 | AT10: -2.6 | AU10: 3.9 | AV10: 9.6 | AW10: 7.9143433 | AX10: 8.8 | AY10: 7.4 | AZ10: 5 | BA10: 4.4175734 | BB10: 1.1334306 | BC10: 1.5638408 | BD10: 2.2099132 | BE10: 2.6095536 | BI10: =F10-AV10 -> 0 | BJ10: =G10-AW10 -> 0.78565674 | BK10: =H10-AX10 -> 0 | BL10: =I10-AY10 -> 0 | BM10: =J10-AZ10 -> 0 | BN10: =K10-BA10 -> -0.017573412 | BO10: =L10-BB10 -> 0.36656941 | BP10: =M10-BC10 -> 0.63615918 | ... BR10: =O10-BE10 -> -0.70300198 | BV10: EPS (cps) | BW10: =FY!G161 -> 1.3 | BX10: =FY!H161 -> 18.3 | BY10: =FY!I161 -> 16.2 | BZ10: =FY!J161 -> 9.4 | CA10: =FY!K161 -> 3.7 | CB10: =FY!L161 -> 2.7605443 | CD10: =BZ10 -> 9.4 | CF10: =CE10/CD10-1 -> -1 | CG10: =CA10 -> 3.7 | CH10: =$CE10/CG10-1 -> -1 | CI10: =CM10 -> 2.7808761 | CJ10: =$CE10/CI10-1 -> -1 | CM10: =DC10 -> 2.7808761 | CO10: SKC_NZ | CP10: EPS - Basic - Operating | CQ10: consensus.vaactuals | CR10: =_xll.VAData($AD10,CR$4,$AE10,$AF10) -> 1.2805147 | CS10: =_xll.VAData($AD10,CS$4,$AE10,$AF10) -> 17.466665 | CT10: =_xll.VAData($AD10,CT$4,$AE10,$AF10) -> 16.2 | CU10: =_xll.VAData($AD10,CU$4,$AE10,$AF10) -> 9.4175734 | CV10: =_xll.VAData($AD10,CV$4,$AE10,$AF10) -> 3.6639162 | CW10: =_xll.VAData($AD10,CW$4,$AE10,$AF10) -> 2.1618546 | CY10: 1.2775501 | CZ10: 17.51708 | DA10: 16.2 | DB10: 9.4175734 | DC10: 2.7808761 | DD10: 3.1950591 | DF10: =BW10-CY10 -> 0.02244987 | DG10: =BX10-CZ10 -> 0.78292024 | DH10: =BY10-DA10 -> 0 | DI10: =BZ10-DB10 -> -0.017573412 | DJ10: =CA10-DC10 -> 0.91912395 | DK10: =CB10-DD10 -> -0.43451484
C11: DPS (cps) | F11: =HY!O493 -> 6 | G11: =HY!P493 -> 6 | H11: =HY!Q493 -> 5.25 | I11: =HY!R493 -> 0 | J11: =HY!S493 -> 0 | K11: =HY!T493 -> 0 | L11: =HY!U493 -> 0 | M11: =HY!V493 -> 0 | ... O11: =HY!X493 -> 0 | Q11: =J11 -> 0 | R11: 0 | S11: na | T11: =L11 -> 0 | U11: na | V11: =AB11 -> 0 | W11: na | Z11: na'd | AB11: =BB11 -> 0 | AD11: SKC_NZ | AE11: Dividend per share | AF11: consensus.vaactuals | AG11: =_xll.VAData($AD11,AG$4,$AE11,$AF11) -> 0 | AH11: =_xll.VAData($AD11,AH$4,$AE11,$AF11) -> 0 | AI11: =_xll.VAData($AD11,AI$4,$AE11,$AF11) -> 6 | AJ11: =_xll.VAData($AD11,AJ$4,$AE11,$AF11) -> 6 | AK11: =_xll.VAData($AD11,AK$4,$AE11,$AF11) -> 5.25 | AL11: =_xll.VAData($AD11,AL$4,$AE11,$AF11) -> 0 | AM11: =_xll.VAData($AD11,AM$4,$AE11,$AF11) -> 0 | AN11: =_xll.VAData($AD11,AN$4,$AE11,$AF11) -> 0 | ... AR11: =_xll.VAData($AD11,AR$4,$AE11,$AF11) -> 0 | AT11: 0 | AU11: 0 | AV11: 6 | AW11: 6 | AX11: 5.25 | AY11: 0 | AZ11: 0 | BA11: 0 | BB11: 0 | BC11: 0 | BD11: 0.096985175 | BE11: 0.76641862 | BI11: =F11-AV11 -> 0 | BJ11: =G11-AW11 -> 0 | BK11: =H11-AX11 -> 0 | BL11: =I11-AY11 -> 0 | BM11: =J11-AZ11 -> 0 | BN11: =K11-BA11 -> 0 | BO11: =L11-BB11 -> 0 | BP11: =M11-BC11 -> 0 | ... BR11: =O11-BE11 -> -0.76641862 | BV11: DPS (cps) | BW11: =FY!G163 -> 0 | BX11: =FY!H163 -> 12 | BY11: =FY!I163 -> 5.25 | BZ11: =FY!J163 -> 0 | CA11: =FY!K163 -> 0 | CB11: =FY!L163 -> 0 | CD11: =BZ11 -> 0 | CE11: 0 | CF11: na | CG11: =CA11 -> 0 | CH11: na | CI11: =CM11 -> 0 | CJ11: na | CM11: =DC11 -> 0 | CO11: SKC_NZ | CP11: Dividend per share | CQ11: consensus.vaactuals | CR11: =_xll.VAData($AD11,CR$4,$AE11,$AF11) -> 0 | CS11: =_xll.VAData($AD11,CS$4,$AE11,$AF11) -> 12 | CT11: =_xll.VAData($AD11,CT$4,$AE11,$AF11) -> 5.25 | CU11: =_xll.VAData($AD11,CU$4,$AE11,$AF11) -> 0 | CV11: =_xll.VAData($AD11,CV$4,$AE11,$AF11) -> 0 | CW11: =_xll.VAData($AD11,CW$4,$AE11,$AF11) -> 0 | CY11: 0 | CZ11: 12 | DA11: 5.25 | DB11: 0 | DC11: 0 | DD11: 1.2740925 | DF11: =BW11-CY11 -> 0 | DG11: =BX11-CZ11 -> 0 | DH11: =BY11-DA11 -> 0 | DI11: =BZ11-DB11 -> 0 | DJ11: =CA11-DC11 -> 0 | DK11: =CB11-DD11 -> -1.2740925
C13: P&L - Reported | BV13: P&L - Reported
C14: Revenue | F14: =HY!O356 -> 462.6 | G14: =HY!P356 -> 463.6 | H14: =HY!Q356 -> 445.2 | I14: =HY!R356 -> 483.3 | J14: =HY!S356 -> 422 | K14: =HY!T356 -> 403.2 | L14: =HY!U356 -> 411.7 | M14: =HY!V356 -> 467.2 | ... O14: =HY!X356 -> 421.369 | Q14: =J14 -> 422 | S14: =R14/Q14-1 -> -1 | T14: =L14 -> 411.7 | U14: =$R14/T14-1 -> -1 | V14: =AB14 -> 391.40876 | W14: =$R14/V14-1 -> -1 | AB14: =BB14 -> 391.40876 | AD14: SKC_NZ | AE14: Total revenue | AF14: consensus.vaactuals | AG14: =_xll.VAData($AD14,AG$4,$AE14,$AF14) -> 289.8 | AH14: =_xll.VAData($AD14,AH$4,$AE14,$AF14) -> 349.2 | AI14: =_xll.VAData($AD14,AI$4,$AE14,$AF14) -> 462.6 | AJ14: =_xll.VAData($AD14,AJ$4,$AE14,$AF14) -> 463.6 | AK14: =_xll.VAData($AD14,AK$4,$AE14,$AF14) -> 445.2 | AL14: =_xll.VAData($AD14,AL$4,$AE14,$AF14) -> 483.3 | AM14: =_xll.VAData($AD14,AM$4,$AE14,$AF14) -> 422 | AN14: =_xll.VAData($AD14,AN$4,$AE14,$AF14) -> 403.2 | ... AR14: =_xll.VAData($AD14,AR$4,$AE14,$AF14) -> 421.369 | AT14: 289.8 | AU14: 349.2 | AV14: 462.6 | AW14: 463.6 | AX14: 445.2 | AY14: 483.3 | AZ14: 422 | BA14: 403.2 | BB14: 391.40876 | BC14: 404.70455 | BD14: 426.30925 | BE14: 441.15811 | BI14: =F14-AV14 -> 0 | BJ14: =G14-AW14 -> 0 | BK14: =H14-AX14 -> 0 | BL14: =I14-AY14 -> 0 | BM14: =J14-AZ14 -> 0 | BN14: =K14-BA14 -> 0 | BO14: =L14-BB14 -> 20.29124 | BP14: =M14-BC14 -> 62.49545 | ... BR14: =O14-BE14 -> -19.789107 | BV14: Revenue | CD14: =BZ14 -> 0 | CF14: =CE14/CD14-1 -> #DIV/0! | CG14: =CA14 -> 0 | CH14: =$CE14/CG14-1 -> #DIV/0! | CI14: =CM14 -> 831.03512 | CJ14: =$CE14/CI14-1 -> -1 | CM14: =DC14 -> 831.03512 | CO14: SKC_NZ | CP14: Total revenue | CQ14: consensus.vaactuals | CR14: =_xll.VAData($AD14,CR$4,$AE14,$AF14) -> 639 | CS14: =_xll.VAData($AD14,CS$4,$AE14,$AF14) -> 926.2 | CT14: =_xll.VAData($AD14,CT$4,$AE14,$AF14) -> 928.5 | CU14: =_xll.VAData($AD14,CU$4,$AE14,$AF14) -> 825.2 | CV14: =_xll.VAData($AD14,CV$4,$AE14,$AF14) -> 878.9 | CW14: =_xll.VAData($AD14,CW$4,$AE14,$AF14) -> 824.16048 | CY14: 639 | CZ14: 926.2 | DA14: 928.5 | DB14: 825.2 | DC14: 831.03512 | DD14: 865.96229 | DG14: =BX14-CZ14 -> -926.2 | DH14: =BY14-DA14 -> -928.5 | DI14: =BZ14-DB14 -> -825.2 | DJ14: =CA14-DC14 -> -831.03512 | DK14: =CB14-DD14 -> -865.96229
C15: EBITDA | F15: =HY!#REF! -> #REF! | G15: =HY!#REF! -> #REF! | H15: =HY!#REF! -> #REF! | I15: =HY!#REF! -> #REF! | J15: =HY!#REF! -> #REF! | K15: =HY!#REF! -> #REF! | L15: =HY!#REF! -> #REF! | M15: =HY!#REF! -> #REF! | ... O15: =HY!#REF! -> #REF! | Q15: =J15 -> #REF! | S15: =R15/Q15-1 -> #REF! | T15: =L15 -> #REF! | U15: =$R15/T15-1 -> #REF! | V15: =AB15 -> 48.042084 | W15: =$R15/V15-1 -> -1 | AB15: =BB15 -> 48.042084 | AD15: SKC_NZ | AE15: EBITDA | AF15: consensus.vaactuals | AG15: =_xll.VAData($AD15,AG$4,$AE15,$AF15) -> 20.4 | AH15: =_xll.VAData($AD15,AH$4,$AE15,$AF15) -> 76.5 | AI15: =_xll.VAData($AD15,AI$4,$AE15,$AF15) -> 106.34 | AJ15: =_xll.VAData($AD15,AJ$4,$AE15,$AF15) -> 59.559 | AK15: =_xll.VAData($AD15,AK$4,$AE15,$AF15) -> 100.99 | AL15: =_xll.VAData($AD15,AL$4,$AE15,$AF15) -> 37.167 | AM15: =_xll.VAData($AD15,AM$4,$AE15,$AF15) -> 113.084 | AN15: =_xll.VAData($AD15,AN$4,$AE15,$AF15) -> 103.011 | ... AR15: =_xll.VAData($AD15,AR$4,$AE15,$AF15) -> 84.050503 | AT15: 20.4 | AU15: 76.5 | AV15: 106.34 | AW15: 59.559 | AX15: 100.99 | AY15: 37.167 | AZ15: 113.084 | BA15: 103.011 | BB15: 48.042084 | BC15: 99.040578 | BD15: 103.68748 | BE15: 118.45959 | BI15: =F15-AV15 -> #REF! | BJ15: =G15-AW15 -> #REF! | BK15: =H15-AX15 -> #REF! | BL15: =I15-AY15 -> #REF! | BM15: =J15-AZ15 -> #REF! | BN15: =K15-BA15 -> #REF! | BO15: =L15-BB15 -> #REF! | BP15: =M15-BC15 -> #REF! | ... BR15: =O15-BE15 -> #REF! | BV15: EBITDA | CD15: =BZ15 -> 0 | CF15: =CE15/CD15-1 -> #DIV/0! | CG15: =CA15 -> 0 | CH15: =$CE15/CG15-1 -> #DIV/0! | CI15: =CM15 -> 149.96293 | CJ15: =$CE15/CI15-1 -> -1 | CM15: =DC15 -> 149.96293 | CO15: SKC_NZ | CP15: EBITDA | CQ15: consensus.vaactuals | CR15: =_xll.VAData($AD15,CR$4,$AE15,$AF15) -> 96.9 | CS15: =_xll.VAData($AD15,CS$4,$AE15,$AF15) -> 165.899 | CT15: =_xll.VAData($AD15,CT$4,$AE15,$AF15) -> 138.157 | CU15: =_xll.VAData($AD15,CU$4,$AE15,$AF15) -> 216.095 | CV15: =_xll.VAData($AD15,CV$4,$AE15,$AF15) -> 120.474 | CW15: =_xll.VAData($AD15,CW$4,$AE15,$AF15) -> 158.87317 | CY15: 96.9 | CZ15: 165.899 | DA15: 138.157 | DB15: 216.095 | DC15: 149.96293 | DD15: 174.81695 | DG15: =BX15-CZ15 -> -165.899 | DH15: =BY15-DA15 -> -138.157 | DI15: =BZ15-DB15 -> -216.095 | DJ15: =CA15-DC15 -> -149.96293 | DK15: =CB15-DD15 -> -174.81695
C16: EBIT | F16: =HY!#REF! -> #REF! | G16: =HY!#REF! -> #REF! | H16: =HY!#REF! -> #REF! | I16: =HY!#REF! -> #REF! | J16: =HY!#REF! -> #REF! | K16: =HY!#REF! -> #REF! | L16: =HY!#REF! -> #REF! | M16: =HY!#REF! -> #REF! | ... O16: =HY!#REF! -> #REF! | Q16: =J16 -> #REF! | S16: =R16/Q16-1 -> #REF! | T16: =L16 -> #REF! | U16: =$R16/T16-1 -> #REF! | V16: =AB16 -> -4.7813367 | W16: =$R16/V16-1 -> -1 | AB16: =BB16 -> -4.7813367 | AD16: SKC_NZ | AE16: Operating income/(loss) | AF16: consensus.vaactuals | AG16: =_xll.VAData($AD16,AG$4,$AE16,$AF16) -> -27.4 | AH16: =_xll.VAData($AD16,AH$4,$AE16,$AF16) -> 29.68 | AI16: =_xll.VAData($AD16,AI$4,$AE16,$AF16) -> 60.9 | AJ16: =_xll.VAData($AD16,AJ$4,$AE16,$AF16) -> 14.351 | AK16: =_xll.VAData($AD16,AK$4,$AE16,$AF16) -> 56.7 | AL16: =_xll.VAData($AD16,AL$4,$AE16,$AF16) -> -10.5 | AM16: =_xll.VAData($AD16,AM$4,$AE16,$AF16) -> 67.8 | AN16: =_xll.VAData($AD16,AN$4,$AE16,$AF16) -> 54.1 | ... AR16: =_xll.VAData($AD16,AR$4,$AE16,$AF16) -> 31.32371 | AT16: -27.4 | AU16: 29.68 | AV16: 60.9 | AW16: 14.351 | AX16: 56.7 | AY16: -10.5 | AZ16: 67.8 | BA16: 54.1 | BB16: -4.7813367 | BC16: 46.128097 | BD16: 50.846733 | BE16: 65.959904 | BI16: =F16-AV16 -> #REF! | BJ16: =G16-AW16 -> #REF! | BK16: =H16-AX16 -> #REF! | BL16: =I16-AY16 -> #REF! | BM16: =J16-AZ16 -> #REF! | BN16: =K16-BA16 -> #REF! | BO16: =L16-BB16 -> #REF! | BP16: =M16-BC16 -> #REF! | ... BR16: =O16-BE16 -> #REF! | BV16: EBIT | CD16: =BZ16 -> 0 | CF16: =CE16/CD16-1 -> #DIV/0! | CG16: =CA16 -> 0 | CH16: =$CE16/CG16-1 -> #DIV/0! | CI16: =CM16 -> 43.313477 | CJ16: =$CE16/CI16-1 -> -1 | CM16: =DC16 -> 43.313477 | CO16: SKC_NZ | CP16: Operating income/(loss) | CQ16: consensus.vaactuals | CR16: =_xll.VAData($AD16,CR$4,$AE16,$AF16) -> 2.3 | CS16: =_xll.VAData($AD16,CS$4,$AE16,$AF16) -> 75.2 | CT16: =_xll.VAData($AD16,CT$4,$AE16,$AF16) -> 46.2 | CU16: =_xll.VAData($AD16,CU$4,$AE16,$AF16) -> 121.9 | CV16: =_xll.VAData($AD16,CV$4,$AE16,$AF16) -> 15.4 | CW16: =_xll.VAData($AD16,CW$4,$AE16,$AF16) -> 41.524461 | CY16: 2.3 | CZ16: 75.2 | DA16: 46.2 | DB16: 121.9 | DC16: 43.313477 | DD16: 58.423408 | DG16: =BX16-CZ16 -> -75.2 | DH16: =BY16-DA16 -> -46.2 | DI16: =BZ16-DB16 -> -121.9 | DJ16: =CA16-DC16 -> -43.313477 | DK16: =CB16-DD16 -> -58.423408
C17: NPAT | F17: =HY!O368 -> 22.8 | G17: =HY!P368 -> -14.825 | H17: =HY!Q368 -> 22.5 | I17: =HY!R368 -> -165.8 | J17: =HY!S368 -> 6.1 | K17: =HY!T368 -> 23.1 | L17: =HY!U368 -> 12.1 | M17: =HY!V368 -> 6.1 | ... O17: =HY!X368 -> 11.030314 | Q17: =J17 -> 6.1 | S17: =R17/Q17-1 -> -1 | T17: =L17 -> 12.1 | U17: =$R17/T17-1 -> -1 | V17: =AB17 -> -8.8603279 | W17: =$R17/V17-1 -> -1 | AB17: =BB17 -> -8.8603279 | AD17: SKC_NZ | AE17: Net income/(loss) | AF17: consensus.vaactuals | AG17: =_xll.VAData($AD17,AG$4,$AE17,$AF17) -> -33.7 | AH17: =_xll.VAData($AD17,AH$4,$AE17,$AF17) -> 0.1 | AI17: =_xll.VAData($AD17,AI$4,$AE17,$AF17) -> 22.8 | AJ17: =_xll.VAData($AD17,AJ$4,$AE17,$AF17) -> -14.8 | AK17: =_xll.VAData($AD17,AK$4,$AE17,$AF17) -> 22.5 | AL17: =_xll.VAData($AD17,AL$4,$AE17,$AF17) -> -165.8 | AM17: =_xll.VAData($AD17,AM$4,$AE17,$AF17) -> 6.1110154 | AN17: =_xll.VAData($AD17,AN$4,$AE17,$AF17) -> 23.1 | ... AR17: =_xll.VAData($AD17,AR$4,$AE17,$AF17) -> 4.2131086 | AT17: -33.7 | AU17: 0.1 | AV17: 22.8 | AW17: -14.8 | AX17: 22.5 | AY17: -165.8 | AZ17: 6.1 | BA17: 23.1 | BB17: -8.8603279 | BC17: 3.8827136 | BD17: 17.022978 | BE17: 23.209881 | BI17: =F17-AV17 -> 0 | BJ17: =G17-AW17 -> -0.025 | BK17: =H17-AX17 -> 0 | BL17: =I17-AY17 -> 0 | BM17: =J17-AZ17 -> 0 | BN17: =K17-BA17 -> 0 | BO17: =L17-BB17 -> 20.960328 | BP17: =M17-BC17 -> 2.2172864 | ... BR17: =O17-BE17 -> -12.179566 | BV17: NPAT | CD17: =BZ17 -> 0 | CF17: =CE17/CD17-1 -> #DIV/0! | CG17: =CA17 -> 0 | CH17: =$CE17/CG17-1 -> #DIV/0! | CI17: =CM17 -> 7.5803362 | CJ17: =$CE17/CI17-1 -> -1 | CM17: =DC17 -> 7.5803362 | CO17: SKC_NZ | CP17: Net income/(loss) | CQ17: consensus.vaactuals | CR17: =_xll.VAData($AD17,CR$4,$AE17,$AF17) -> -33.595 | CS17: =_xll.VAData($AD17,CS$4,$AE17,$AF17) -> 8 | CT17: =_xll.VAData($AD17,CT$4,$AE17,$AF17) -> -143.3 | CU17: =_xll.VAData($AD17,CU$4,$AE17,$AF17) -> 29.2 | CV17: =_xll.VAData($AD17,CV$4,$AE17,$AF17) -> 18.2 | CW17: =_xll.VAData($AD17,CW$4,$AE17,$AF17) -> 38.052519 | CY17: -33.595 | CZ17: 8 | DA17: -143.3 | DB17: 29.2 | DC17: 7.5803362 | DD17: 25.979537 | DG17: =BX17-CZ17 -> -8 | DH17: =BY17-DA17 -> 143.3 | DI17: =BZ17-DB17 -> -29.2 | DJ17: =CA17-DC17 -> -7.5803362 | DK17: =CB17-DD17 -> -25.979537
C18: EPS (cps) | F18: =HY!O370 -> 3 | G18: =HY!P370 -> -1.9 | H18: =HY!Q370 -> 3 | I18: =HY!R370 -> -1.9 | J18: =HY!S370 -> 3 | K18: =HY!T370 -> 0.9 | L18: =HY!U370 -> 1.2 | M18: =HY!V370 -> 0.6 | ... O18: =HY!X370 -> 0.99997859 | Q18: =J18 -> 3 | S18: =R18/Q18-1 -> -1 | T18: =L18 -> 1.2 | U18: =$R18/T18-1 -> -1 | V18: =AB18 -> -1.2256675 | W18: =$R18/V18-1 -> -1 | AB18: =BB18 -> -1.2256675 | AD18: SKC_NZ | AE18: EPS - Basic | AF18: consensus.vaactuals | AG18: =_xll.VAData($AD18,AG$4,$AE18,$AF18) -> -4.5 | AH18: =_xll.VAData($AD18,AH$4,$AE18,$AF18) -> - | AI18: =_xll.VAData($AD18,AI$4,$AE18,$AF18) -> 2.9991902 | AJ18: =_xll.VAData($AD18,AJ$4,$AE18,$AF18) -> -1.9501313 | AK18: =_xll.VAData($AD18,AK$4,$AE18,$AF18) -> 3 | AL18: =_xll.VAData($AD18,AL$4,$AE18,$AF18) -> -21.9 | AM18: =_xll.VAData($AD18,AM$4,$AE18,$AF18) -> 0.8 | AN18: =_xll.VAData($AD18,AN$4,$AE18,$AF18) -> 3.1 | ... AR18: =_xll.VAData($AD18,AR$4,$AE18,$AF18) -> 0.57505937 | AT18: -4.5 | AU18: - | AV18: 2.9976117 | AW18: -1.9522047 | AX18: 3 | AY18: -21.9 | AZ18: 0.8 | BA18: 3.1 | BB18: -1.2256675 | BC18: 0.046419996 | BD18: 1.5480426 | BE18: 2.1091099 | BI18: =F18-AV18 -> 0.002388338 | BJ18: =G18-AW18 -> 0.052204672 | BK18: =H18-AX18 -> 0 | BL18: =I18-AY18 -> 20 | BM18: =J18-AZ18 -> 2.2 | BN18: =K18-BA18 -> -2.2 | BO18: =L18-BB18 -> 2.4256675 | BP18: =M18-BC18 -> 0.55358 | ... BR18: =O18-BE18 -> -1.1091313 | BV18: EPS (cps) | CD18: =BZ18 -> 0 | CF18: =CE18/CD18-1 -> #DIV/0! | CG18: =CA18 -> 0 | CH18: =$CE18/CG18-1 -> #DIV/0! | CI18: =CM18 -> 0.78529166 | CJ18: =$CE18/CI18-1 -> -1 | CM18: =DC18 -> 0.78529166 | CO18: SKC_NZ | CP18: EPS - Basic | CQ18: consensus.vaactuals | CR18: =_xll.VAData($AD18,CR$4,$AE18,$AF18) -> -4.4355975 | CS18: =_xll.VAData($AD18,CS$4,$AE18,$AF18) -> 1.1 | CT18: =_xll.VAData($AD18,CT$4,$AE18,$AF18) -> -18.9 | CU18: =_xll.VAData($AD18,CU$4,$AE18,$AF18) -> 3.850541 | CV18: =_xll.VAData($AD18,CV$4,$AE18,$AF18) -> 1.8 | CW18: =_xll.VAData($AD18,CW$4,$AE18,$AF18) -> 3.4571239 | CY18: -4.4355975 | CZ18: 1.1 | DA18: -18.9 | DB18: 3.850541 | DC18: 0.78529166 | DD18: 2.3553094 | DG18: =BX18-CZ18 -> -1.1 | DH18: =BY18-DA18 -> 18.9 | DI18: =BZ18-DB18 -> -3.850541 | DJ18: =CA18-DC18 -> -0.78529166 | DK18: =CB18-DD18 -> -2.3553094
C21: SkyCity 1H26 Result - Locations (NZ$m) | BV21: SkyCity FY26 Result - Locations (NZ$m)
D22: =D$4 -> 1H22A | E22: =E$4 -> 2H22A | F22: =F$4 -> 1H23A | G22: =G$4 -> 2H23A | H22: =H$4 -> 1H24A | I22: =I$4 -> 2H24E | J22: =J$4 -> 1H25E | K22: =K$4 -> 2H25E | ... O22: =O$4 -> 2H27E | Q22: =Q$4 -> 1H25A | R22: =R$4 -> 1H26A | S22: =S$4 -> % change | T22: =T$4 -> E&Pe 1H26E | U22: =U$4 -> % diff | V22: =V$4 -> VA Cons. 1H26E | W22: =W$4 -> % diff | AB22: 1H25 | AG22: 1H22 | AH22: 2H22 | AI22: 1H23 | AJ22: 2H23 | AK22: 1H24 | AL22: 2H24 | AM22: 1H25 | AN22: 2H25 | AO22: 1H26 | AP22: 2H26 | AQ22: 1H27 | AR22: 2H27 | AT22: 1H22 | AU22: 2H22 | AV22: 1H23 | AW22: 2H23 | AX22: 1H24 | AY22: 2H24 | AZ22: 1H25 | BA22: 2H25 | BB22: 1H26 | BC22: 2H26 | BD22: 1H27 | BE22: 2H27 | BG22: 1H22 | BH22: 2H22 | BI22: 1H23 | BJ22: 2H23 | BK22: 1H24 | BL22: 2H24 | BM22: 1H25 | BN22: 2H25 | BO22: 1H26 | BP22: 2H26 | BQ22: 1H27 | BR22: 2H27 | BW22: =BW$4 -> FY22A | BX22: =BX$4 -> FY23A | BY22: =BY$4 -> FY24E | BZ22: =BZ$4 -> FY25E | CA22: =CA$4 -> FY26E | CB22: =CB$4 -> FY27E | CD22: =CD$4 -> FY25A | CE22: =CE$4 -> FY26A | CF22: =CF$4 -> % change | CG22: =CG$4 -> E&Pe FY26E | CH22: =CH$4 -> % diff | CI22: =CI$4 -> VA Cons. FY26E | CJ22: =CJ$4 -> % diff | CM22: FY24 | CR22: FY22 | CS22: FY23 | CT22: FY24 | CU22: FY25 | CV22: FY26 | CW22: FY27 | CY22: FY22 | CZ22: FY23 | DA22: FY24 | DB22: FY25 | DC22: FY26 | DD22: FY27 | DF22: FY22 | DG22: FY23 | DH22: FY24 | DI22: FY25 | DJ22: FY26 | DK22: FY27
C23: Location Revenue | BV23: Location Revenue
C24: Auckland | F24: =HY!O306 -> 258.3 | G24: =HY!P306 -> 259.7 | H24: =HY!Q306 -> 280.6 | I24: =HY!R306 -> 266.1 | J24: =HY!S306 -> 258.3 | K24: =HY!T306 -> 256 | L24: =HY!U306 -> 248.1 | M24: =HY!V306 -> 250.5 | ... O24: =HY!X306 -> 258 | Q24: =J24 -> 258.3 | R24: 248.1 | S24: =R24/Q24-1 -> -0.039488966 | T24: =L24 -> 248.1 | U24: =$R24/T24-1 -> 0 | V24: =AB24 -> 237.62699 | W24: =$R24/V24-1 -> 0.044073307 | AB24: =BB24 -> 237.62699 | AD24: SKC_NZ | AE24: Total revenue - Domestic - Auckland | AF24: consensus.vaactuals | AG24: =_xll.VAData($AD24,AG$4,$AE24,$AF24) -> 118.5 | AH24: =_xll.VAData($AD24,AH$4,$AE24,$AF24) -> 212.11 | AI24: =_xll.VAData($AD24,AI$4,$AE24,$AF24) -> 258.3 | AJ24: =_xll.VAData($AD24,AJ$4,$AE24,$AF24) -> 259.7 | AK24: =_xll.VAData($AD24,AK$4,$AE24,$AF24) -> 280.6 | AL24: =_xll.VAData($AD24,AL$4,$AE24,$AF24) -> 266.1 | AM24: =_xll.VAData($AD24,AM$4,$AE24,$AF24) -> 258.3 | AN24: =_xll.VAData($AD24,AN$4,$AE24,$AF24) -> 256 | ... AR24: =_xll.VAData($AD24,AR$4,$AE24,$AF24) -> 246.03909 | AT24: 118.5 | AU24: 212.11 | AV24: 258.3 | AW24: 259.7 | AX24: 280.6 | AY24: 266.1 | AZ24: 258.3 | BA24: 256 | BB24: 237.62699 | BC24: 258.19953 | BD24: 271.57176 | BE24: 277.34608 | BI24: =F24-AV24 -> 0 | BJ24: =G24-AW24 -> 0 | BK24: =H24-AX24 -> 0 | BL24: =I24-AY24 -> 0 | BM24: =J24-AZ24 -> 0 | BN24: =K24-BA24 -> 0 | BO24: =L24-BB24 -> 10.473007 | BP24: =M24-BC24 -> -7.6995332 | ... BR24: =O24-BE24 -> -19.346084 | BV24: Auckland | BX24: =FY!H6 -> 518 | BY24: =FY!I6 -> 546.7 | BZ24: =FY!J6 -> 514.3 | CA24: =FY!K6 -> 498.6 | CB24: =FY!L6 -> 514 | CD24: =BZ24 -> 514.3 | CE24: 498.6 | CF24: =CE24/CD24-1 -> -0.03052693 | CG24: =CA24 -> 498.6 | CH24: =$CE24/CG24-1 -> 0 | CI24: =CM24 -> 498.8008 | CJ24: =$CE24/CI24-1 -> -0.00040256126 | CM24: =DC24 -> 498.8008 | CO24: SKC_NZ | CP24: Total revenue - Domestic - Auckland | CQ24: consensus.vaactuals | CR24: =_xll.VAData($AD24,CR$4,$AE24,$AF24) -> 331.2 | CS24: =_xll.VAData($AD24,CS$4,$AE24,$AF24) -> 584 | CT24: =_xll.VAData($AD24,CT$4,$AE24,$AF24) -> 546.7 | CU24: =_xll.VAData($AD24,CU$4,$AE24,$AF24) -> 514.3 | CV24: =_xll.VAData($AD24,CV$4,$AE24,$AF24) -> 498.6 | CW24: =_xll.VAData($AD24,CW$4,$AE24,$AF24) -> 521.02657 | CY24: 331.2 | CZ24: 584 | DA24: 546.7 | DB24: 514.3 | DC24: 498.8008 | DD24: 551.4415 | DG24: =BX24-CZ24 -> -66 | DH24: =BY24-DA24 -> 0 | DI24: =BZ24-DB24 -> 0 | DJ24: =CA24-DC24 -> -0.20079788 | DK24: =CB24-DD24 -> -37.441497
C25: Hamilton & Queenstown | F25: =HY!O307 -> 42.2 | G25: =HY!P307 -> 35.7 | H25: =HY!Q307 -> 38.7 | I25: =HY!R307 -> 38.4 | J25: =HY!S307 -> 38.3 | K25: =HY!T307 -> 35.9 | L25: =HY!U307 -> 37.4 | M25: =HY!V307 -> 36.5 | ... O25: =HY!X307 -> 37.269 | Q25: =J25 -> 38.3 | R25: 37.4 | S25: =R25/Q25-1 -> -0.023498695 | T25: =L25 -> 37.4 | U25: =$R25/T25-1 -> 0 | V25: =AB25 -> 35.243064 | W25: =$R25/V25-1 -> 0.061201725 | AB25: =BB25 -> 35.243064 | AD25: SKC_NZ | AE25: Total revenue - Domestic - Hamilton and Queenstown | AF25: consensus.vaactuals | AG25: =_xll.VAData($AD25,AG$4,$AE25,$AF25) -> 29.3 | AH25: =_xll.VAData($AD25,AH$4,$AE25,$AF25) -> 37.2 | AI25: =_xll.VAData($AD25,AI$4,$AE25,$AF25) -> 47.7 | AJ25: =_xll.VAData($AD25,AJ$4,$AE25,$AF25) -> 40.3 | AK25: =_xll.VAData($AD25,AK$4,$AE25,$AF25) -> 38.8 | AL25: =_xll.VAData($AD25,AL$4,$AE25,$AF25) -> 38.2 | AM25: =_xll.VAData($AD25,AM$4,$AE25,$AF25) -> 38.3 | AN25: =_xll.VAData($AD25,AN$4,$AE25,$AF25) -> 35.9 | ... AR25: =_xll.VAData($AD25,AR$4,$AE25,$AF25) -> 39.288313 | AT25: 29.3 | AU25: 37.2 | AV25: 47.7 | AW25: 40.3 | AX25: 38.8 | AY25: 38.2 | AZ25: 38.3 | BA25: 35.9 | BB25: 35.243064 | BC25: 35.049783 | BD25: 36.539264 | BE25: 36.112668 | BI25: =F25-AV25 -> -5.5 | BJ25: =G25-AW25 -> -4.6 | BK25: =H25-AX25 -> -0.1 | BL25: =I25-AY25 -> 0.2 | BM25: =J25-AZ25 -> 0 | BN25: =K25-BA25 -> 0 | BO25: =L25-BB25 -> 2.1569363 | BP25: =M25-BC25 -> 1.4502172 | ... BR25: =O25-BE25 -> 1.1563324 | BV25: Hamilton & Queenstown | BX25: =FY!H7 -> 77.9 | BY25: =FY!I7 -> 77.1 | BZ25: =FY!J7 -> 74.2 | CA25: =FY!K7 -> 73.9 | CB25: =FY!L7 -> 74.834 | CD25: =BZ25 -> 74.2 | CE25: 73.9 | CF25: =CE25/CD25-1 -> -0.0040431267 | CG25: =CA25 -> 73.9 | CH25: =$CE25/CG25-1 -> 0 | CI25: =CM25 -> 74.700097 | CJ25: =$CE25/CI25-1 -> -0.010710789 | CM25: =DC25 -> 74.700097 | CO25: SKC_NZ | CP25: Total revenue - Domestic - Hamilton and Queenstown | CQ25: consensus.vaactuals | CR25: =_xll.VAData($AD25,CR$4,$AE25,$AF25) -> 66.5 | CS25: =_xll.VAData($AD25,CS$4,$AE25,$AF25) -> 77.9 | CT25: =_xll.VAData($AD25,CT$4,$AE25,$AF25) -> 77 | CU25: =_xll.VAData($AD25,CU$4,$AE25,$AF25) -> 74.2 | CV25: =_xll.VAData($AD25,CV$4,$AE25,$AF25) -> 73.9 | CW25: =_xll.VAData($AD25,CW$4,$AE25,$AF25) -> 77.995653 | CY25: 66.5 | CZ25: 77.9 | DA25: 77 | DB25: 74.2 | DC25: 74.700097 | DD25: 76.221059 | DG25: =BX25-CZ25 -> 0 | DH25: =BY25-DA25 -> 0.1 | DI25: =BZ25-DB25 -> 0 | DJ25: =CA25-DC25 -> -0.80009695 | DK25: =CB25-DD25 -> -1.3870587
C26: Adelaide | F26: =HY!O101 -> 129.9 | G26: =HY!P101 -> 119.9 | H26: =HY!Q101 -> 116.79926 | I26: =HY!R101 -> 119.90074 | J26: =HY!S101 -> 123.2 | K26: =HY!T101 -> 108.8 | L26: =HY!U101 -> 124.5 | M26: =HY!V101 -> 122.1 | ... O26: =HY!X101 -> 124.1 | Q26: =J26 -> 123.2 | R26: 124.5 | S26: =R26/Q26-1 -> 0.010551948 | T26: =L26 -> 124.5 | U26: =$R26/T26-1 -> 0 | V26: =AB26 -> 115.06806 | W26: =$R26/V26-1 -> 0.081968368 | AB26: =BB26 -> 115.06806 | AD26: SKC_NZ | AE26: Total revenue - Domestic - Adelaide | AF26: consensus.vaactuals | AG26: =_xll.VAData($AD26,AG$4,$AE26,$AF26) -> 98.571501 | AH26: =_xll.VAData($AD26,AH$4,$AE26,$AF26) -> 101.27738 | AI26: =_xll.VAData($AD26,AI$4,$AE26,$AF26) -> 129.9 | AJ26: =_xll.VAData($AD26,AJ$4,$AE26,$AF26) -> 122.87945 | AK26: =_xll.VAData($AD26,AK$4,$AE26,$AF26) -> 116.8 | AL26: =_xll.VAData($AD26,AL$4,$AE26,$AF26) -> 120.1 | AM26: =_xll.VAData($AD26,AM$4,$AE26,$AF26) -> 123.2 | AN26: =_xll.VAData($AD26,AN$4,$AE26,$AF26) -> 108.8 | ... AR26: =_xll.VAData($AD26,AR$4,$AE26,$AF26) -> 124.50123 | AT26: 98.571501 | AU26: 101.27738 | AV26: 129.9 | AW26: 122.87945 | AX26: 116.8 | AY26: 120.1 | AZ26: 123.22307 | BA26: 108.8 | BB26: 115.06806 | BC26: 114.06841 | BD26: 119.46338 | BE26: 112.12379 | BI26: =F26-AV26 -> 0 | BJ26: =G26-AW26 -> -2.9794542 | BK26: =H26-AX26 -> -0.00073545317 | BL26: =I26-AY26 -> -0.19926455 | BM26: =J26-AZ26 -> -0.023067404 | BN26: =K26-BA26 -> 0 | BO26: =L26-BB26 -> 9.431941 | BP26: =M26-BC26 -> 8.0315902 | ... BR26: =O26-BE26 -> 11.976206 | BV26: Adelaide | BX26: =FY!H8 -> 249.8 | BY26: =FY!I8 -> 236.7 | BZ26: =FY!J8 -> 232 | CA26: =FY!K8 -> 246.6 | CB26: =FY!L8 -> 249.1 | CD26: 245.1 | CE26: 246.6 | CF26: =CE26/CD26-1 -> 0.006119951 | CG26: =CA26 -> 246.6 | CH26: =$CE26/CG26-1 -> 0 | CI26: =CM26 -> 230.30217 | CJ26: =$CE26/CI26-1 -> 0.070767136 | CM26: =DC26 -> 230.30217 | CO26: SKC_NZ | CP26: Total revenue - Domestic - Adelaide | CQ26: consensus.vaactuals | CR26: =_xll.VAData($AD26,CR$4,$AE26,$AF26) -> 197.07327 | CS26: =_xll.VAData($AD26,CS$4,$AE26,$AF26) -> 266.0579 | CT26: =_xll.VAData($AD26,CT$4,$AE26,$AF26) -> 236.9 | CU26: =_xll.VAData($AD26,CU$4,$AE26,$AF26) -> 232 | CV26: =_xll.VAData($AD26,CV$4,$AE26,$AF26) -> 246.6 | CW26: =_xll.VAData($AD26,CW$4,$AE26,$AF26) -> 254.08558 | CY26: 197.07327 | CZ26: 266.0579 | DA26: 236.9 | DB26: 232 | DC26: 230.30217 | DD26: 238.05399 | DG26: =BX26-CZ26 -> -16.257899 | DH26: =BY26-DA26 -> -0.2 | DI26: =BZ26-DB26 -> 0 | DJ26: =CA26-DC26 -> 16.297825 | DK26: =CB26-DD26 -> 11.046012
C27: Online | F27: =HY!O309 -> 7.9 | G27: =HY!P309 -> 7.5 | H27: =HY!Q309 -> 5.6 | I27: =HY!R309 -> 3.7 | J27: =HY!S309 -> 2.1 | K27: =HY!T309 -> 2 | L27: =HY!U309 -> 1.6 | M27: =HY!V309 -> 1.2 | ... O27: =HY!X309 -> 2 | Q27: =J27 -> 2.1 | R27: 1.6 | S27: =R27/Q27-1 -> -0.23809524 | T27: =L27 -> 1.6 | U27: =$R27/T27-1 -> 0 | V27: =AB27 -> 2.3415385 | W27: =$R27/V27-1 -> -0.31668857 | AB27: =BB27 -> 2.3415385 | AD27: SKC_NZ | AE27: Total revenue - Online & e-sports | AF27: consensus.vaactuals | AG27: =_xll.VAData($AD27,AG$4,$AE27,$AF27) -> 9.3 | AH27: =_xll.VAData($AD27,AH$4,$AE27,$AF27) -> 7.6 | AI27: =_xll.VAData($AD27,AI$4,$AE27,$AF27) -> 7.9 | AJ27: =_xll.VAData($AD27,AJ$4,$AE27,$AF27) -> 7.5 | AK27: =_xll.VAData($AD27,AK$4,$AE27,$AF27) -> 5.6 | AL27: =_xll.VAData($AD27,AL$4,$AE27,$AF27) -> 3.8 | AM27: =_xll.VAData($AD27,AM$4,$AE27,$AF27) -> 2.1 | AN27: =_xll.VAData($AD27,AN$4,$AE27,$AF27) -> 2 | ... AR27: =_xll.VAData($AD27,AR$4,$AE27,$AF27) -> 5.761 | AT27: 9.3 | AU27: 7.6 | AV27: 7.9 | AW27: 7.5 | AX27: 5.6 | AY27: 3.8 | AZ27: 2.1 | BA27: 2 | BB27: 2.3415385 | BC27: 1.85 | BD27: 9.7647946 | BE27: 13.398981 | BI27: =F27-AV27 -> 0 | BJ27: =G27-AW27 -> 0 | BK27: =H27-AX27 -> 0 | BL27: =I27-AY27 -> -0.1 | BM27: =J27-AZ27 -> 0 | BN27: =K27-BA27 -> 0 | BO27: =L27-BB27 -> -0.74153846 | BP27: =M27-BC27 -> -0.65 | ... BR27: =O27-BE27 -> -11.398981 | BV27: Online | BX27: =FY!H9 -> 15.4 | BY27: =FY!I9 -> 9.3 | BZ27: =FY!J9 -> 4.1 | CA27: =FY!K9 -> 2.8 | CB27: =FY!L9 -> 3 | CD27: =BZ27 -> 4.1 | CE27: 2.8 | CF27: =CE27/CD27-1 -> -0.31707317 | CG27: =CA27 -> 2.8 | CH27: =$CE27/CG27-1 -> 0 | CI27: =CM27 -> 3.9826667 | CJ27: =$CE27/CI27-1 -> -0.29695347 | CM27: =DC27 -> 3.9826667 | CO27: SKC_NZ | CP27: Total revenue - Online & e-sports | CQ27: consensus.vaactuals | CR27: =_xll.VAData($AD27,CR$4,$AE27,$AF27) -> 16.9 | CS27: =_xll.VAData($AD27,CS$4,$AE27,$AF27) -> 15.4 | CT27: =_xll.VAData($AD27,CT$4,$AE27,$AF27) -> 9.4 | CU27: =_xll.VAData($AD27,CU$4,$AE27,$AF27) -> 4.1 | CV27: =_xll.VAData($AD27,CV$4,$AE27,$AF27) -> 2.8 | CW27: =_xll.VAData($AD27,CW$4,$AE27,$AF27) -> 11.453153 | CY27: 16.9 | CZ27: 15.4 | DA27: 9.4 | DB27: 4.1 | DC27: 3.9826667 | DD27: 14.804191 | DG27: =BX27-CZ27 -> 0 | DH27: =BY27-DA27 -> -0.1 | DI27: =BZ27-DB27 -> 0 | DJ27: =CA27-DC27 -> -1.1826667 | DK27: =CB27-DD27 -> -11.804191
C28: Segment Revenue | F28: =HY!O311 -> 438.9 | G28: =HY!P311 -> 423.7 | H28: =HY!Q311 -> 442.8 | I28: =HY!R311 -> 427.7 | J28: =HY!S311 -> 422 | K28: =HY!T311 -> 403.2 | L28: =HY!U311 -> 411.7 | M28: =HY!V311 -> 411 | ... O28: =HY!X311 -> 421.369 | Q28: =J28 -> 422 | R28: 411.7 | S28: =R28/Q28-1 -> -0.024407583 | T28: =L28 -> 411.7 | U28: =$R28/T28-1 -> 0 | V28: =AB28 -> 385.86341 | W28: =$R28/V28-1 -> 0.066957865 | AB28: =BB28 -> 385.86341 | AD28: SKC_NZ | AE28: Total revenue - Operating | AF28: consensus.vaactuals | AG28: =_xll.VAData($AD28,AG$4,$AE28,$AF28) -> 260.8 | AH28: =_xll.VAData($AD28,AH$4,$AE28,$AF28) -> 370.7 | AI28: =_xll.VAData($AD28,AI$4,$AE28,$AF28) -> 438.9 | AJ28: =_xll.VAData($AD28,AJ$4,$AE28,$AF28) -> 423.7 | AK28: =_xll.VAData($AD28,AK$4,$AE28,$AF28) -> 442.8 | AL28: =_xll.VAData($AD28,AL$4,$AE28,$AF28) -> 427.702 | AM28: =_xll.VAData($AD28,AM$4,$AE28,$AF28) -> 422 | AN28: =_xll.VAData($AD28,AN$4,$AE28,$AF28) -> 403.2 | ... AR28: =_xll.VAData($AD28,AR$4,$AE28,$AF28) -> 403.74455 | AT28: 260.8 | AU28: 370.7 | AV28: 438.9 | AW28: 423.7 | AX28: 442.8 | AY28: 427.7 | AZ28: 422 | BA28: 403.2 | BB28: 385.86341 | BC28: 402.90399 | BD28: 430.51721 | BE28: 434.22619 | BI28: =F28-AV28 -> 0 | BJ28: =G28-AW28 -> 0 | BK28: =H28-AX28 -> 0 | BL28: =I28-AY28 -> 0 | BM28: =J28-AZ28 -> 0 | BN28: =K28-BA28 -> 0 | BO28: =L28-BB28 -> 25.83659 | BP28: =M28-BC28 -> 8.0960121 | ... BR28: =O28-BE28 -> -12.857194 | BV28: Segment Revenue | BX28: =FY!H11 -> 862.6 | BY28: =FY!I11 -> 870.5 | BZ28: =FY!J11 -> 825.2 | CA28: =FY!K11 -> 822.7 | CB28: =FY!L11 -> 840.934 | CD28: =BZ28 -> 825.2 | CE28: =CE6 -> 822.7 | CF28: =CE28/CD28-1 -> -0.0030295686 | CG28: =CA28 -> 822.7 | CH28: =$CE28/CG28-1 -> 0 | CI28: =CM28 -> 815.21503 | CJ28: =$CE28/CI28-1 -> 0.00918159 | CM28: =DC28 -> 815.21503 | CO28: SKC_NZ | CP28: Total revenue - Operating | CQ28: consensus.vaactuals | CR28: =_xll.VAData($AD28,CR$4,$AE28,$AF28) -> 631.5 | CS28: =_xll.VAData($AD28,CS$4,$AE28,$AF28) -> 862.6 | CT28: =_xll.VAData($AD28,CT$4,$AE28,$AF28) -> 870.5 | CU28: =_xll.VAData($AD28,CU$4,$AE28,$AF28) -> 825.2 | CV28: =_xll.VAData($AD28,CV$4,$AE28,$AF28) -> 822.7 | CW28: =_xll.VAData($AD28,CW$4,$AE28,$AF28) -> 824.73077 | CY28: 631.5 | CZ28: 862.6 | DA28: 870.5 | DB28: 825.2 | DC28: 815.21503 | DD28: 851.50262 | DG28: =BX28-CZ28 -> 0 | DH28: =BY28-DA28 -> 0 | DI28: =BZ28-DB28 -> 0 | DJ28: =CA28-DC28 -> 7.4849702 | DK28: =CB28-DD28 -> -10.568621
C30: Location EBITDA | BV30: Location EBITDA
C31: Auckland | F31: =HY!O319 -> 130.6 | G31: =HY!P319 -> 120.9 | H31: =HY!Q319 -> 125.7 | I31: =HY!R319 -> 111.3 | J31: =HY!S319 -> 107.7 | K31: =HY!T319 -> 101.9 | L31: =HY!U319 -> 89.6 | M31: =HY!V319 -> 90.2 | ... O31: =HY!X319 -> 93.7312 | Q31: =J31 -> 107.7 | R31: 89.6 | S31: =R31/Q31-1 -> -0.16805942 | T31: =L31 -> 89.6 | U31: =$R31/T31-1 -> 0 | V31: =AB31 -> 80.770042 | W31: =$R31/V31-1 -> 0.1093222 | AB31: =BB31 -> 80.770042 | AD31: SKC_NZ | AE31: EBITDA - Domestic - Auckland | AF31: consensus.vaactuals | AG31: =_xll.VAData($AD31,AG$4,$AE31,$AF31) -> 16 | AH31: =_xll.VAData($AD31,AH$4,$AE31,$AF31) -> 84.9 | AI31: =_xll.VAData($AD31,AI$4,$AE31,$AF31) -> 130.6 | AJ31: =_xll.VAData($AD31,AJ$4,$AE31,$AF31) -> 120.9 | AK31: =_xll.VAData($AD31,AK$4,$AE31,$AF31) -> 125.7 | AL31: =_xll.VAData($AD31,AL$4,$AE31,$AF31) -> 111.3 | AM31: =_xll.VAData($AD31,AM$4,$AE31,$AF31) -> 107.7 | AN31: =_xll.VAData($AD31,AN$4,$AE31,$AF31) -> 101.9 | ... AR31: =_xll.VAData($AD31,AR$4,$AE31,$AF31) -> 91.345115 | AT31: 16 | AU31: 84.9 | AV31: 130.6 | AW31: 120.9 | AX31: 125.7 | AY31: 111.3 | AZ31: 107.7 | BA31: 101.9 | BB31: 80.770042 | BC31: 98.663665 | BD31: 102.55552 | BE31: 107.16716 | BI31: =F31-AV31 -> 0 | BJ31: =G31-AW31 -> 0 | BK31: =H31-AX31 -> 0 | BL31: =I31-AY31 -> 0 | BM31: =J31-AZ31 -> 0 | BN31: =K31-BA31 -> 0 | BO31: =L31-BB31 -> 8.8299585 | BP31: =M31-BC31 -> -8.4636652 | ... BR31: =O31-BE31 -> -13.435965 | BV31: Auckland | BX31: =FY!H13 -> 251.5 | BY31: =FY!I13 -> 237 | BZ31: =FY!J13 -> 209.6 | CA31: =FY!K13 -> 179.8 | CB31: =FY!L13 -> 185.6984 | CD31: =BZ31 -> 209.6 | CE31: 179.8 | CF31: =CE31/CD31-1 -> -0.14217557 | CG31: =CA31 -> 179.8 | CH31: =$CE31/CG31-1 -> 0 | CI31: =CM31 -> 181.93592 | CJ31: =$CE31/CI31-1 -> -0.011739941 | CM31: =DC31 -> 181.93592 | CO31: SKC_NZ | CP31: EBITDA - Domestic - Auckland | CQ31: consensus.vaactuals | CR31: =_xll.VAData($AD31,CR$4,$AE31,$AF31) -> 100.9 | CS31: =_xll.VAData($AD31,CS$4,$AE31,$AF31) -> 251.5 | CT31: =_xll.VAData($AD31,CT$4,$AE31,$AF31) -> 237 | CU31: =_xll.VAData($AD31,CU$4,$AE31,$AF31) -> 209.6 | CV31: =_xll.VAData($AD31,CV$4,$AE31,$AF31) -> 179.8 | CW31: =_xll.VAData($AD31,CW$4,$AE31,$AF31) -> 179.28118 | CY31: 100.9 | CZ31: 251.5 | DA31: 237 | DB31: 209.6 | DC31: 181.93592 | DD31: 198.27076 | DG31: =BX31-CZ31 -> 0 | DH31: =BY31-DA31 -> 0 | DI31: =BZ31-DB31 -> 0 | DJ31: =CA31-DC31 -> -2.135917 | DK31: =CB31-DD31 -> -12.572362
C32: Hamilton | F32: =HY!O320 -> 22.9 | G32: =HY!P320 -> 16.4 | H32: =HY!Q320 -> 16.7 | I32: =HY!R320 -> 18.3 | J32: =HY!S320 -> 17.5 | K32: =HY!T320 -> 16.2 | L32: =HY!U320 -> 15.5 | M32: =HY!V320 -> 15.9 | ... O32: =HY!X320 -> 16.722303 | Q32: =J32 -> 17.5 | R32: 15.5 | S32: =R32/Q32-1 -> -0.11428571 | T32: =L32 -> 15.5 | U32: =$R32/T32-1 -> 0 | V32: =AB32 -> 15.21218 | W32: =$R32/V32-1 -> 0.018920343 | AB32: =BB32 -> 15.21218 | AD32: SKC_NZ | AE32: EBITDA - Domestic - Hamilton and Queenstown | AF32: consensus.vaactuals | AG32: =_xll.VAData($AD32,AG$4,$AE32,$AF32) -> 11 | AH32: =_xll.VAData($AD32,AH$4,$AE32,$AF32) -> 16.5 | AI32: =_xll.VAData($AD32,AI$4,$AE32,$AF32) -> 22.9 | AJ32: =_xll.VAData($AD32,AJ$4,$AE32,$AF32) -> 16.3 | AK32: =_xll.VAData($AD32,AK$4,$AE32,$AF32) -> 16.8 | AL32: =_xll.VAData($AD32,AL$4,$AE32,$AF32) -> 18.3 | AM32: =_xll.VAData($AD32,AM$4,$AE32,$AF32) -> 17.5 | AN32: =_xll.VAData($AD32,AN$4,$AE32,$AF32) -> 16.2 | ... AR32: =_xll.VAData($AD32,AR$4,$AE32,$AF32) -> 16.547592 | AT32: 11 | AU32: 16.5 | AV32: 22.9 | AW32: 16.3 | AX32: 16.8 | AY32: 18.3 | AZ32: 17.5 | BA32: 16.2 | BB32: 15.21218 | BC32: 15.164841 | BD32: 15.695056 | BE32: 15.640291 | BI32: =F32-AV32 -> 0 | BJ32: =G32-AW32 -> 0.1 | BK32: =H32-AX32 -> -0.1 | BL32: =I32-AY32 -> 0 | BM32: =J32-AZ32 -> 0 | BN32: =K32-BA32 -> 0 | BO32: =L32-BB32 -> 0.28781967 | BP32: =M32-BC32 -> 0.73515908 | ... BR32: =O32-BE32 -> 1.0820121 | BV32: Hamilton & Queenstown | BX32: =FY!H14 -> 39.3 | BY32: =FY!I14 -> 35 | BZ32: =FY!J14 -> 33.7 | CA32: =FY!K14 -> 31.4 | CB32: =FY!L14 -> 33.750235 | CD32: =BZ32 -> 33.7 | CE32: 31.4 | CF32: =CE32/CD32-1 -> -0.068249258 | CG32: =CA32 -> 31.4 | CH32: =$CE32/CG32-1 -> 0 | CI32: =CM32 -> 31.390959 | CJ32: =$CE32/CI32-1 -> 0.00028800705 | CM32: =DC32 -> 31.390959 | CO32: SKC_NZ | CP32: EBITDA - Domestic - Hamilton and Queenstown | CQ32: consensus.vaactuals | CR32: =_xll.VAData($AD32,CR$4,$AE32,$AF32) -> 27.5 | CS32: =_xll.VAData($AD32,CS$4,$AE32,$AF32) -> 39.3 | CT32: =_xll.VAData($AD32,CT$4,$AE32,$AF32) -> 35.009 | CU32: =_xll.VAData($AD32,CU$4,$AE32,$AF32) -> 33.7 | CV32: =_xll.VAData($AD32,CV$4,$AE32,$AF32) -> 31.4 | CW32: =_xll.VAData($AD32,CW$4,$AE32,$AF32) -> 32.832798 | CY32: 27.5 | CZ32: 39.3 | DA32: 35.009 | DB32: 33.7 | DC32: 31.390959 | DD32: 32.15462 | DG32: =BX32-CZ32 -> 0 | DH32: =BY32-DA32 -> -0.009 | DI32: =BZ32-DB32 -> 0 | DJ32: =CA32-DC32 -> 0.0090408177 | DK32: =CB32-DD32 -> 1.5956149
C33: Adelaide | F33: =HY!O321 -> 20.7 | G33: =HY!P321 -> 15.4 | H33: =HY!Q321 -> 18.2 | I33: =HY!R321 -> 21.4 | J33: =HY!S321 -> 21.6 | K33: =HY!T321 -> 9.5 | L33: =HY!U321 -> 9.7 | M33: =HY!V321 -> 13.1 | ... O33: =HY!X321 -> 13.597 | Q33: 21.6 | R33: 9.7 | S33: =R33/Q33-1 -> -0.55092593 | T33: =L33 -> 9.7 | U33: =$R33/T33-1 -> 0 | V33: =AB33 -> 12.974328 | W33: =$R33/V33-1 -> -0.25236973 | AB33: =BB33 -> 12.974328 | AD33: SKC_NZ | AE33: EBITDA - Domestic - Adelaide | AF33: consensus.vaactuals | AG33: =_xll.VAData($AD33,AG$4,$AE33,$AF33) -> 11.338583 | AH33: =_xll.VAData($AD33,AH$4,$AE33,$AF33) -> 11.191631 | AI33: =_xll.VAData($AD33,AI$4,$AE33,$AF33) -> 20.7 | AJ33: =_xll.VAData($AD33,AJ$4,$AE33,$AF33) -> 15.282072 | AK33: =_xll.VAData($AD33,AK$4,$AE33,$AF33) -> 18.2 | AL33: =_xll.VAData($AD33,AL$4,$AE33,$AF33) -> 21.4 | AM33: =_xll.VAData($AD33,AM$4,$AE33,$AF33) -> 21.6 | AN33: =_xll.VAData($AD33,AN$4,$AE33,$AF33) -> 9.5 | ... AR33: =_xll.VAData($AD33,AR$4,$AE33,$AF33) -> 8.1437419 | AT33: 11.338583 | AU33: 11.191631 | AV33: 20.7 | AW33: 15.282072 | AX33: 18.2 | AY33: 21.4 | AZ33: 15.2 | BA33: 15.9 | BB33: 12.974328 | BC33: 13.129714 | BD33: 9.8071827 | BE33: 10.328983 | BI33: =F33-AV33 -> 0 | BJ33: =G33-AW33 -> 0.11792826 | BK33: =H33-AX33 -> 0 | BL33: =I33-AY33 -> 0 | BM33: =J33-AZ33 -> 6.4 | BN33: =K33-BA33 -> -6.4 | BO33: =L33-BB33 -> -3.2743275 | BP33: =M33-BC33 -> -0.02971373 | ... BR33: =O33-BE33 -> 3.2680172 | BV33: Adelaide | BX33: =FY!H15 -> 36.1 | BY33: =FY!I15 -> 39.6 | BZ33: =FY!J15 -> 31.1 | CA33: =FY!K15 -> 22.8 | CB33: =FY!L15 -> 28.2975 | CD33: 32.9 | CE33: 22.8 | CF33: =CE33/CD33-1 -> -0.30699088 | CG33: =CA33 -> 22.8 | CH33: =$CE33/CG33-1 -> 0 | CI33: =CM33 -> 13.855728 | CJ33: =$CE33/CI33-1 -> 0.64552885 | CM33: =DC33 -> 13.855728 | CO33: SKC_NZ | CP33: EBITDA - Domestic - Adelaide | CQ33: consensus.vaactuals | CR33: =_xll.VAData($AD33,CR$4,$AE33,$AF33) -> 22.663314 | CS33: =_xll.VAData($AD33,CS$4,$AE33,$AF33) -> 35.983813 | CT33: =_xll.VAData($AD33,CT$4,$AE33,$AF33) -> 39.6 | CU33: =_xll.VAData($AD33,CU$4,$AE33,$AF33) -> 31.1 | CV33: =_xll.VAData($AD33,CV$4,$AE33,$AF33) -> 22.8 | CW33: =_xll.VAData($AD33,CW$4,$AE33,$AF33) -> 20.296879 | CY33: 22.663314 | CZ33: 35.983813 | DA33: 39.6 | DB33: 31.1 | DC33: 13.855728 | DD33: 10.280997 | DG33: =BX33-CZ33 -> 0.11618725 | DH33: =BY33-DA33 -> 0 | DI33: =BZ33-DB33 -> 0 | DJ33: =CA33-DC33 -> 8.9442721 | DK33: =CB33-DD33 -> 18.016503
C34: Online (ex GiG equity) | F34: =HY!O293 -> 5.6 | G34: =HY!P293 -> 5.1 | H34: =HY!Q293 -> 3 | I34: =HY!R293 -> 0.6 | J34: =HY!S293 -> -1.1 | K34: =HY!T293 -> -0.7 | L34: =HY!U293 -> -2.1 | M34: =HY!V293 -> -4.3 | ... O34: =HY!X293 -> -7 | Q34: =J34 -> -1.1 | R34: -2.1 | S34: =R34/Q34-1 -> 0.90909091 | T34: =L34 -> -2.1 | U34: =$R34/T34-1 -> 0 | V34: =AB34 -> -2.9205833 | W34: =$R34/V34-1 -> -0.28096556 | AB34: =BB34 -> -2.9205833 | AD34: SKC_NZ | AE34: EBITDA - Online & e-sports | AF34: consensus.vaactuals | AG34: =_xll.VAData($AD34,AG$4,$AE34,$AF34) -> 7 | AH34: =_xll.VAData($AD34,AH$4,$AE34,$AF34) -> 5.9 | AI34: =_xll.VAData($AD34,AI$4,$AE34,$AF34) -> 5.6 | AJ34: =_xll.VAData($AD34,AJ$4,$AE34,$AF34) -> 5.1 | AK34: =_xll.VAData($AD34,AK$4,$AE34,$AF34) -> 3 | AL34: =_xll.VAData($AD34,AL$4,$AE34,$AF34) -> 0.6 | AM34: =_xll.VAData($AD34,AM$4,$AE34,$AF34) -> -1.1 | AN34: =_xll.VAData($AD34,AN$4,$AE34,$AF34) -> -0.7 | ... AR34: =_xll.VAData($AD34,AR$4,$AE34,$AF34) -> -5.5575639 | AT34: 7 | AU34: 5.9 | AV34: 5.6 | AW34: 5.1 | AX34: 3 | AY34: 0.6 | AZ34: -1.1 | BA34: -0.7 | BB34: -2.9205833 | BC34: -2.0112083 | BD34: -1.0213194 | BE34: 2.084057 | BI34: =F34-AV34 -> 0 | BJ34: =G34-AW34 -> 0 | BK34: =H34-AX34 -> 0 | BL34: =I34-AY34 -> 0 | BM34: =J34-AZ34 -> 0 | BN34: =K34-BA34 -> 0 | BO34: =L34-BB34 -> 0.82058333 | BP34: =M34-BC34 -> -2.2887917 | ... BR34: =O34-BE34 -> -9.084057 | BV34: Online | BX34: =FY!H16 -> 10.7 | BY34: =FY!I16 -> 3.6 | BZ34: =FY!J16 -> -1.8 | CA34: =FY!K16 -> -6.4 | CB34: =FY!L16 -> -13 | CD34: =BZ34 -> -1.8 | CE34: -6.4 | CF34: =CE34/CD34-1 -> 2.5555556 | CG34: =CA34 -> -6.4 | CH34: =$CE34/CG34-1 -> 0 | CI34: =CM34 -> -4.6675937 | CJ34: =$CE34/CI34-1 -> 0.37115618 | CM34: =DC34 -> -4.6675937 | CO34: SKC_NZ | CP34: EBITDA - Online & e-sports | CQ34: consensus.vaactuals | CR34: =_xll.VAData($AD34,CR$4,$AE34,$AF34) -> 12.9 | CS34: =_xll.VAData($AD34,CS$4,$AE34,$AF34) -> 10.7 | CT34: =_xll.VAData($AD34,CT$4,$AE34,$AF34) -> 3.6 | CU34: =_xll.VAData($AD34,CU$4,$AE34,$AF34) -> -1.8 | CV34: =_xll.VAData($AD34,CV$4,$AE34,$AF34) -> -6.4 | CW34: =_xll.VAData($AD34,CW$4,$AE34,$AF34) -> -9.2418805 | CY34: 12.9 | CZ34: 10.7 | DA34: 3.6 | DB34: -1.8 | DC34: -4.6675937 | DD34: -2.9445601 | DG34: =BX34-CZ34 -> 0 | DH34: =BY34-DA34 -> 0 | DI34: =BZ34-DB34 -> 0 | DJ34: =CA34-DC34 -> -1.7324063 | DK34: =CB34-DD34 -> -10.05544
C35: Corporate Costs | F35: =HY!O323 -> -18.6 | G35: =HY!P323 -> -18.6 | H35: =HY!Q323 -> -20.5 | I35: =HY!R323 -> -17.4 | J35: =HY!S323 -> -26.3 | K35: =HY!T323 -> -13.2 | L35: =HY!U323 -> -27.2 | M35: =HY!V323 -> -19.6 | ... O35: =HY!X323 -> -23 | Q35: =J35 -> -26.3 | R35: -27.2 | S35: =R35/Q35-1 -> 0.034220532 | T35: =L35 -> -27.2 | U35: =$R35/T35-1 -> 0 | V35: =AB35 -> -18.14211 | W35: =$R35/V35-1 -> 0.49927432 | AB35: =BB35 -> -18.14211 | AD35: SKC_NZ | AE35: EBITDA - Corporate costs | AF35: consensus.vaactuals | AG35: =_xll.VAData($AD35,AG$4,$AE35,$AF35) -> -7.6915934 | AH35: =_xll.VAData($AD35,AH$4,$AE35,$AF35) -> -17.583406 | AI35: =_xll.VAData($AD35,AI$4,$AE35,$AF35) -> -18.1 | AJ35: =_xll.VAData($AD35,AJ$4,$AE35,$AF35) -> -17.816053 | AK35: =_xll.VAData($AD35,AK$4,$AE35,$AF35) -> -19.4 | AL35: =_xll.VAData($AD35,AL$4,$AE35,$AF35) -> -17.9 | AM35: =_xll.VAData($AD35,AM$4,$AE35,$AF35) -> -26.2 | AN35: =_xll.VAData($AD35,AN$4,$AE35,$AF35) -> -12.7 | ... AR35: =_xll.VAData($AD35,AR$4,$AE35,$AF35) -> -19.514737 | AT35: -7.6915934 | AU35: -17.583406 | AV35: -18.1 | AW35: -17.816053 | AX35: -19.4 | AY35: -17.9 | AZ35: -26.2 | BA35: -12.7 | BB35: -18.14211 | BC35: -15.697268 | BD35: -16.563296 | BE35: -16.56665 | BI35: =F35-AV35 -> -0.5 | BJ35: =G35-AW35 -> -0.78394684 | BK35: =H35-AX35 -> -1.1 | BL35: =I35-AY35 -> 0.5 | BM35: =J35-AZ35 -> -0.1 | BN35: =K35-BA35 -> -0.5 | BO35: =L35-BB35 -> -9.0578898 | BP35: =M35-BC35 -> -3.9027322 | ... BR35: =O35-BE35 -> -6.4333495 | BV35: Corporate Costs | BX35: =FY!H17 -> -37.2 | BY35: =FY!I17 -> -37.9 | BZ35: =FY!J17 -> -39.5 | CA35: =FY!K17 -> -46.8 | CB35: =FY!L17 -> -51.56 | CD35: =BZ35 -> -39.5 | CE35: -46 | CF35: =CE35/CD35-1 -> 0.16455696 | CG35: =CA35 -> -46.8 | CH35: =$CE35/CG35-1 -> -0.017094017 | CI35: =CM35 -> -43.061468 | CJ35: =$CE35/CI35-1 -> 0.068240413 | CM35: =DC35 -> -43.061468 | CO35: SKC_NZ | CP35: EBITDA - Corporate costs | CQ35: consensus.vaactuals | CR35: =_xll.VAData($AD35,CR$4,$AE35,$AF35) -> -25.275 | CS35: =_xll.VAData($AD35,CS$4,$AE35,$AF35) -> -36.025528 | CT35: =_xll.VAData($AD35,CT$4,$AE35,$AF35) -> -37.4 | CU35: =_xll.VAData($AD35,CU$4,$AE35,$AF35) -> -38.9 | CV35: =_xll.VAData($AD35,CV$4,$AE35,$AF35) -> -46 | CW35: =_xll.VAData($AD35,CW$4,$AE35,$AF35) -> -43.125444 | CY35: -25.275 | CZ35: -36.025528 | DA35: -37.4 | DB35: -38.9 | DC35: -43.061468 | DD35: -44.440773 | DG35: =BX35-CZ35 -> -1.1744722 | DH35: =BY35-DA35 -> -0.5 | DI35: =BZ35-DB35 -> -0.6 | DJ35: =CA35-DC35 -> -3.7385323 | DK35: =CB35-DD35 -> -7.1192269
C36: Segment EBITDA | F36: =HY!O325 -> 161.8 | G36: =HY!P325 -> 140 | H36: =HY!Q325 -> 144.3 | I36: =HY!R325 -> 133.5 | J36: =HY!S325 -> 119.5 | K36: =HY!T325 -> 114.2 | L36: =HY!U325 -> 85.5 | M36: =HY!V325 -> 96.1 | ... O36: =HY!X325 -> 94.050503 | Q36: 119.5 | R36: 85.5 | S36: =R36/Q36-1 -> -0.28451883 | T36: =L36 -> 85.5 | U36: =$R36/T36-1 -> 0 | V36: =AB36 -> 88.187782 | W36: =$R36/V36-1 -> -0.030477938 | AB36: =BB36 -> 88.187782 | AD36: SKC_NZ | AE36: EBITDA - Operating | AF36: consensus.vaactuals | AG36: =_xll.VAData($AD36,AG$4,$AE36,$AF36) -> 36.2 | AH36: =_xll.VAData($AD36,AH$4,$AE36,$AF36) -> 101.7 | AI36: =_xll.VAData($AD36,AI$4,$AE36,$AF36) -> 161.8 | AJ36: =_xll.VAData($AD36,AJ$4,$AE36,$AF36) -> 140 | AK36: =_xll.VAData($AD36,AK$4,$AE36,$AF36) -> 144.25346 | AL36: =_xll.VAData($AD36,AL$4,$AE36,$AF36) -> 133.5 | AM36: =_xll.VAData($AD36,AM$4,$AE36,$AF36) -> 119.529 | AN36: =_xll.VAData($AD36,AN$4,$AE36,$AF36) -> 114.2 | ... AR36: =_xll.VAData($AD36,AR$4,$AE36,$AF36) -> 93.164145 | AT36: 36.2 | AU36: 101.7 | AV36: 161.7 | AW36: 140.1 | AX36: 144.3 | AY36: 133.5 | AZ36: 113.1 | BA36: 120.6 | BB36: 88.187782 | BC36: 106.32547 | BD36: 108.19785 | BE36: 118.38289 | BI36: =F36-AV36 -> 0.1 | BJ36: =G36-AW36 -> -0.1 | BK36: =H36-AX36 -> 0 | BL36: =I36-AY36 -> 0 | BM36: =J36-AZ36 -> 6.4 | BN36: =K36-BA36 -> -6.4 | BO36: =L36-BB36 -> -2.6877817 | BP36: =M36-BC36 -> -10.22547 | ... BR36: =O36-BE36 -> -24.332389 | BV36: Segment EBITDA | BX36: =FY!H19 -> 301.8 | BY36: =FY!I19 -> 277.8 | BZ36: =FY!J19 -> 233.7 | CA36: =FY!K19 -> 181.6 | CB36: =FY!L19 -> 183.18614 | CD36: =BZ36 -> 233.7 | CE36: =CE7 -> 181.6 | CF36: =CE36/CD36-1 -> -0.22293539 | CG36: =CA36 -> 181.6 | CH36: =$CE36/CG36-1 -> 0 | CI36: =CM36 -> 182.49152 | CJ36: =$CE36/CI36-1 -> -0.0048852946 | CM36: =DC36 -> 182.49152 | CO36: SKC_NZ | CP36: EBITDA - Operating | CQ36: consensus.vaactuals | CR36: =_xll.VAData($AD36,CR$4,$AE36,$AF36) -> 137.9 | CS36: =_xll.VAData($AD36,CS$4,$AE36,$AF36) -> 301.8 | CT36: =_xll.VAData($AD36,CT$4,$AE36,$AF36) -> 277.8 | CU36: =_xll.VAData($AD36,CU$4,$AE36,$AF36) -> 233.7 | CV36: =_xll.VAData($AD36,CV$4,$AE36,$AF36) -> 181.6 | CW36: =_xll.VAData($AD36,CW$4,$AE36,$AF36) -> 181.26337 | CY36: 137.9 | CZ36: 301.8 | DA36: 277.8 | DB36: 233.7 | DC36: 182.49152 | DD36: 197.49483 | DG36: =BX36-CZ36 -> 0 | DH36: =BY36-DA36 -> 0 | DI36: =BZ36-DB36 -> 0 | DJ36: =CA36-DC36 -> -0.89152487 | DK36: =CB36-DD36 -> -14.308693
C38: Margins | BV38: Margins
C39: Auckland | F39: =F31/F24 -> 0.50561363 | G39: =G31/G24 -> 0.46553716 | H39: =H31/H24 -> 0.44796864 | I39: =I31/I24 -> 0.41826381 | J39: =J31/J24 -> 0.41695703 | K39: =K31/K24 -> 0.39804688 | L39: =L31/L24 -> 0.3611447 | M39: =M31/M24 -> 0.36007984 | ... O39: =O31/O24 -> 0.36329922 | Q39: =Q31/Q24 -> 0.41695703 | R39: =R31/R24 -> 0.3611447 | S39: =($R39-Q39)*100 -> -5.5812327 | T39: =T31/T24 -> 0.3611447 | U39: =($R39-T39)*100 -> 0 | V39: =V31/V24 -> 0.33990264 | W39: =($R39-V39)*100 -> 2.1242062 | AB39: =AB31/AB24 -> 0.33990264 | BI39: =F39-AV39 -> 0.50561363 | BJ39: =G39-AW39 -> 0.46553716 | BK39: =H39-AX39 -> 0.44796864 | BL39: =I39-AY39 -> 0.41826381 | BM39: =J39-AZ39 -> 0.41695703 | BN39: =K39-BA39 -> 0.39804688 | BO39: =L39-BB39 -> 0.3611447 | BP39: =M39-BC39 -> 0.36007984 | ... BR39: =O39-BE39 -> 0.36329922 | BV39: Auckland | BX39: =BX31/BX24 -> 0.48552124 | BY39: =BY31/BY24 -> 0.43351015 | BZ39: =BZ31/BZ24 -> 0.40754423 | CA39: =CA31/CA24 -> 0.36060971 | CB39: =CB31/CB24 -> 0.36128093 | CD39: =CD31/CD24 -> 0.40754423 | CE39: =CE31/CE24 -> 0.36060971 | CF39: =($CE39-CD39)*100 -> -4.6934528 | CG39: =CG31/CG24 -> 0.36060971 | CH39: =($CE39-CG39)*100 -> 0 | CI39: =CI31/CI24 -> 0.36474664 | CJ39: =($CE39-CI39)*100 -> -0.41369367 | CM39: =CM31/CM24 -> 0.36474664
C40: Hamilton | F40: =F32/F25 -> 0.54265403 | G40: =G32/G25 -> 0.45938375 | H40: =H32/H25 -> 0.43152455 | I40: =I32/I25 -> 0.4765625 | J40: =J32/J25 -> 0.45691906 | K40: =K32/K25 -> 0.45125348 | L40: =L32/L25 -> 0.4144385 | M40: =M32/M25 -> 0.43561644 | ... O40: =O32/O25 -> 0.44869203 | Q40: =Q32/Q25 -> 0.45691906 | R40: =R32/R25 -> 0.4144385 | S40: =($R40-Q40)*100 -> -4.2480557 | T40: =T32/T25 -> 0.4144385 | U40: =($R40-T40)*100 -> 0 | V40: =V32/V25 -> 0.43163615 | W40: =($R40-V40)*100 -> -1.7197647 | AB40: =AB32/AB25 -> 0.43163615 | BI40: =F40-AV40 -> 0.54265403 | BJ40: =G40-AW40 -> 0.45938375 | BK40: =H40-AX40 -> 0.43152455 | BL40: =I40-AY40 -> 0.4765625 | BM40: =J40-AZ40 -> 0.45691906 | BN40: =K40-BA40 -> 0.45125348 | BO40: =L40-BB40 -> 0.4144385 | BP40: =M40-BC40 -> 0.43561644 | ... BR40: =O40-BE40 -> 0.44869203 | BV40: Hamilton | BX40: =BX32/BX25 -> 0.50449294 | BY40: =BY32/BY25 -> 0.4539559 | BZ40: =BZ32/BZ25 -> 0.4541779 | CA40: =CA32/CA25 -> 0.42489851 | CB40: =CB32/CB25 -> 0.45100135 | CD40: =CD32/CD25 -> 0.4541779 | CE40: =CE32/CE25 -> 0.42489851 | CF40: =($CE40-CD40)*100 -> -2.9279386 | CG40: =CG32/CG25 -> 0.42489851 | CH40: =($CE40-CG40)*100 -> 0 | CI40: =CI32/CI25 -> 0.42022649 | CJ40: =($CE40-CI40)*100 -> 0.46720264 | CM40: =CM32/CM25 -> 0.42022649
C41: Adelaide (A$) | F41: =F33/F26 -> 0.15935335 | G41: =G33/G26 -> 0.12844037 | H41: =H33/H26 -> 0.1558229 | I41: =I33/I26 -> 0.17848097 | J41: =J33/J26 -> 0.17532468 | K41: =K33/K26 -> 0.087316176 | L41: =L33/L26 -> 0.077911647 | M41: =M33/M26 -> 0.10728911 | ... O41: =O33/O26 -> 0.10956487 | Q41: =Q33/Q26 -> 0.17532468 | R41: =R33/R26 -> 0.077911647 | S41: =($R41-Q41)*100 -> -9.7413029 | T41: =T33/T26 -> 0.077911647 | U41: =($R41-T41)*100 -> 0 | V41: =V33/V26 -> 0.11275351 | W41: =($R41-V41)*100 -> -3.4841863 | AB41: =AB33/AB26 -> 0.11275351 | BI41: =F41-AV41 -> 0.15935335 | BJ41: =G41-AW41 -> 0.12844037 | BK41: =H41-AX41 -> 0.1558229 | BL41: =I41-AY41 -> 0.17848097 | BM41: =J41-AZ41 -> 0.17532468 | BN41: =K41-BA41 -> 0.087316176 | BO41: =L41-BB41 -> 0.077911647 | BP41: =M41-BC41 -> 0.10728911 | ... BR41: =O41-BE41 -> 0.10956487 | BV41: Adelaide | BX41: =BX33/BX26 -> 0.14451561 | BY41: =BY33/BY26 -> 0.16730038 | BZ41: =BZ33/BZ26 -> 0.13405172 | CA41: =CA33/CA26 -> 0.092457421 | CB41: =CB33/CB26 -> 0.11359896 | CD41: =CD33/CD26 -> 0.13423093 | CE41: =CE33/CE26 -> 0.092457421 | CF41: =($CE41-CD41)*100 -> -4.1773505 | CG41: =CG33/CG26 -> 0.092457421 | CH41: =($CE41-CG41)*100 -> 0 | CI41: =CI33/CI26 -> 0.060163252 | CJ41: =($CE41-CI41)*100 -> 3.2294169 | CM41: =CM33/CM26 -> 0.060163252
C42: Segment EBITDA | F42: =F36/F28 -> 0.36864889 | G42: =G36/G28 -> 0.33042247 | H42: =H36/H28 -> 0.32588076 | I42: =I36/I28 -> 0.31213467 | J42: =J36/J28 -> 0.28317536 | K42: =K36/K28 -> 0.28323413 | L42: =L36/L28 -> 0.20767549 | M42: =M36/M28 -> 0.23381995 | ... O42: =O36/O28 -> 0.22320224 | Q42: =Q36/Q28 -> 0.28317536 | R42: =R36/R28 -> 0.20767549 | S42: =($R42-Q42)*100 -> -7.5499864 | T42: =T36/T28 -> 0.20767549 | U42: =($R42-T42)*100 -> 0 | V42: =V36/V28 -> 0.22854663 | W42: =($R42-V42)*100 -> -2.0871138 | AB42: =AB36/AB28 -> 0.22854663 | BI42: =F42-AV42 -> 0.36864889 | BJ42: =G42-AW42 -> 0.33042247 | BK42: =H42-AX42 -> 0.32588076 | BL42: =I42-AY42 -> 0.31213467 | BM42: =J42-AZ42 -> 0.28317536 | BN42: =K42-BA42 -> 0.28323413 | BO42: =L42-BB42 -> 0.20767549 | BP42: =M42-BC42 -> 0.23381995 | ... BR42: =O42-BE42 -> 0.22320224 | BV42: Segment EBITDA | BX42: =BX36/BX28 -> 0.34987248 | BY42: =BY36/BY28 -> 0.31912694 | BZ42: =BZ36/BZ28 -> 0.28320407 | CA42: =CA36/CA28 -> 0.2207366 | CB42: =CB36/CB28 -> 0.21783652 | CD42: =CD36/CD28 -> 0.28320407 | CE42: =CE36/CE28 -> 0.2207366 | CF42: =($CE42-CD42)*100 -> -6.2467473 | CG42: =CG36/CG28 -> 0.2207366 | CH42: =($CE42-CG42)*100 -> 0 | CI42: =CI36/CI28 -> 0.22385692 | CJ42: =($CE42-CI42)*100 -> -0.312032 | CM42: =CM36/CM28 -> 0.22385692
C44: SkyCity 1H26 Result - Segments (NZ$m) | BV44: SkyCity FY26 Result - Segments (NZ$m)
D45: =D$4 -> 1H22A | E45: =E$4 -> 2H22A | F45: =F$4 -> 1H23A | G45: =G$4 -> 2H23A | H45: =H$4 -> 1H24A | I45: =I$4 -> 2H24E | J45: =J$4 -> 1H25E | K45: =K$4 -> 2H25E | ... O45: =O$4 -> 2H27E | Q45: =Q$4 -> 1H25A | R45: =R$4 -> 1H26A | S45: =S$4 -> % change | T45: =T$4 -> E&Pe 1H26E | U45: =U$4 -> % diff | V45: =V$4 -> VA Cons. 1H26E | W45: =W$4 -> % diff | AB45: 1H25 | AG45: 1H22 | AH45: 2H22 | AI45: 1H23 | AJ45: 2H23 | AK45: 1H24 | AL45: 2H24 | AM45: 1H25 | AN45: 2H25 | AO45: 1H26 | AP45: 2H26 | AQ45: 1H27 | AR45: 2H27 | AT45: 1H22 | AU45: 2H22 | AV45: 1H23 | AW45: 2H23 | AX45: 1H24 | AY45: 2H24 | AZ45: 1H25 | BA45: 2H25 | BB45: 1H26 | BC45: 2H26 | BD45: 1H27 | BE45: 2H27 | BG45: 1H22 | BH45: 2H22 | BI45: 1H23 | BJ45: 2H23 | BK45: 1H24 | BL45: 2H24 | BM45: 1H25 | BN45: 2H25 | BO45: 1H26 | BP45: 2H26 | BQ45: 1H27 | BR45: 2H27 | BW45: =BW$4 -> FY22A | BX45: =BX$4 -> FY23A | BY45: =BY$4 -> FY24E | BZ45: =BZ$4 -> FY25E | CA45: =CA$4 -> FY26E | CB45: =CB$4 -> FY27E | CD45: =CD$4 -> FY25A | CE45: =CE$4 -> FY26A | CF45: =CF$4 -> % change | CG45: =CG$4 -> E&Pe FY26E | CH45: =CH$4 -> % diff | CI45: =CI$4 -> VA Cons. FY26E | CJ45: =CJ$4 -> % diff | CM45: FY24 | CR45: FY22 | CS45: FY23 | CT45: FY24 | CU45: FY25 | CV45: FY26 | CW45: FY27 | CY45: FY22 | CZ45: FY23 | DA45: FY24 | DB45: FY25 | DC45: FY26 | DD45: FY27 | DF45: FY22 | DG45: FY23 | DH45: FY24 | DI45: FY25 | DJ45: FY26 | DK45: FY27
C46: Slots | BV46: Slots
C47: Auckland | F47: =HY!O83 -> 135.6 | G47: =HY!P83 -> 129.7 | H47: =HY!Q83 -> 127.9 | I47: =HY!R83 -> 119.8 | J47: =HY!S83 -> 118.3 | K47: =HY!T83 -> 115.6 | L47: =HY!U83 -> 110.9 | M47: =HY!V83 -> 103.1 | ... O47: =HY!X83 -> 103 | Q47: =J47 -> 118.3 | R47: 110.9 | S47: =R47/Q47-1 -> -0.062552832 | T47: =L47 -> 110.9 | U47: =$R47/T47-1 -> 0 | V47: =AB47 -> 109.71972 | W47: =$R47/V47-1 -> 0.010757259 | AB47: =BB47 -> 109.71972 | AD47: SKC_NZ | AE47: Total revenue - Slot - Auckland | AF47: consensus.vaactuals | AG47: =_xll.VAData($AD47,AG$4,$AE47,$AF47) -> 60 | AH47: =_xll.VAData($AD47,AH$4,$AE47,$AF47) -> 125.51 | AI47: =_xll.VAData($AD47,AI$4,$AE47,$AF47) -> 135.6 | AJ47: =_xll.VAData($AD47,AJ$4,$AE47,$AF47) -> 129.7 | AK47: =_xll.VAData($AD47,AK$4,$AE47,$AF47) -> 127.9 | AL47: =_xll.VAData($AD47,AL$4,$AE47,$AF47) -> 119.8 | AM47: =_xll.VAData($AD47,AM$4,$AE47,$AF47) -> 118.3 | AN47: =_xll.VAData($AD47,AN$4,$AE47,$AF47) -> 115.6 | ... AR47: =_xll.VAData($AD47,AR$4,$AE47,$AF47) -> 102.8127 | AT47: 60 | AU47: 125.51 | AV47: 135.6 | AW47: 129.7 | AX47: 127.9 | AY47: 119.8 | AZ47: 118.3 | BA47: 115.6 | BB47: 109.71972 | BC47: 109.84645 | BD47: 116.36932 | BE47: 115.8313 | BI47: =F47-AV47 -> 0 | BJ47: =G47-AW47 -> 0 | BK47: =H47-AX47 -> 0 | BL47: =I47-AY47 -> 0 | BM47: =J47-AZ47 -> 0 | BN47: =K47-BA47 -> 0 | BO47: =L47-BB47 -> 1.1802834 | BP47: =M47-BC47 -> -6.7464511 | ... BR47: =O47-BE47 -> -12.831298 | BV47: Auckland | BW47: =FY!G208 -> 161.385 | BX47: =FY!H208 -> 265.3 | BY47: =FY!I208 -> 247.7 | BZ47: =FY!J208 -> 233.9 | CA47: =FY!K208 -> 214 | CB47: =FY!L208 -> 202 | CD47: =BZ47 -> 233.9 | CE47: 214 | CF47: =CE47/CD47-1 -> -0.085079094 | CG47: =CA47 -> 214 | CH47: =$CE47/CG47-1 -> 0 | CI47: =CM47 -> 217.76915 | CJ47: =$CE47/CI47-1 -> -0.017308027 | CM47: =DC47 -> 217.76915 | CO47: SKC_NZ | CP47: Total revenue - Slot - Auckland | CQ47: consensus.vaactuals | CR47: =_xll.VAData($AD47,CR$4,$AE47,$AF47) -> 185.5 | CS47: =_xll.VAData($AD47,CS$4,$AE47,$AF47) -> 265.3 | CT47: =_xll.VAData($AD47,CT$4,$AE47,$AF47) -> 247.7 | CU47: =_xll.VAData($AD47,CU$4,$AE47,$AF47) -> 233.9 | CV47: =_xll.VAData($AD47,CV$4,$AE47,$AF47) -> 214 | CW47: =_xll.VAData($AD47,CW$4,$AE47,$AF47) -> 202.13798 | CY47: 185.5 | CZ47: 265.3 | DA47: 247.7 | DB47: 233.9 | DC47: 217.76915 | DD47: 223.93094 | DF47: =BW47-CY47 -> -24.115 | DG47: =BX47-CZ47 -> 0 | DH47: =BY47-DA47 -> 0 | DI47: =BZ47-DB47 -> 0 | DJ47: =CA47-DC47 -> -3.7691545 | DK47: =CB47-DD47 -> -21.930936
C48: Hamilton | F48: =HY!O90 -> 28.2 | G48: =HY!P90 -> 25.8 | H48: =HY!Q90 -> 26.4 | I48: =HY!R90 -> 25.9 | J48: =HY!S90 -> 26 | K48: =HY!T90 -> 24.7 | L48: =HY!U90 -> 24.8 | M48: =HY!V90 -> 25 | ... O48: =HY!X90 -> 25.5 | Q48: =J48 -> 26 | R48: 24.8 | S48: =R48/Q48-1 -> -0.046153846 | T48: =L48 -> 24.8 | U48: =$R48/T48-1 -> 0 | V48: =AB48 -> 21.92406 | W48: =$R48/V48-1 -> 0.13117736 | AB48: =BB48 -> 21.92406 | AD48: SKC_NZ | AE48: Total revenue - Slot - Hamilton | AF48: consensus.vaactuals | AG48: =_xll.VAData($AD48,AG$4,$AE48,$AF48) -> 16.9 | AH48: =_xll.VAData($AD48,AH$4,$AE48,$AF48) -> 23.9 | AI48: =_xll.VAData($AD48,AI$4,$AE48,$AF48) -> 28.3 | AJ48: =_xll.VAData($AD48,AJ$4,$AE48,$AF48) -> 25.8 | AK48: =_xll.VAData($AD48,AK$4,$AE48,$AF48) -> 26.7 | AL48: =_xll.VAData($AD48,AL$4,$AE48,$AF48) -> 25.9 | AM48: =_xll.VAData($AD48,AM$4,$AE48,$AF48) -> 26 | AN48: =_xll.VAData($AD48,AN$4,$AE48,$AF48) -> 24.7 | ... AR48: =_xll.VAData($AD48,AR$4,$AE48,$AF48) -> 25.75 | AT48: 16.9 | AU48: 23.9 | AV48: 28.3 | AW48: 25.8 | AX48: 26.7 | AY48: 25.9 | AZ48: 22.37149 | BA48: 21.107625 | BB48: 21.92406 | BC48: 20.896549 | BD48: 22.362541 | BE48: 21.31448 | BI48: =F48-AV48 -> -0.1 | BJ48: =G48-AW48 -> 0 | BK48: =H48-AX48 -> -0.3 | BL48: =I48-AY48 -> 0 | BM48: =J48-AZ48 -> 3.6285104 | BN48: =K48-BA48 -> 3.592375 | BO48: =L48-BB48 -> 2.8759402 | BP48: =M48-BC48 -> 4.1034512 | ... BR48: =O48-BE48 -> 4.1855203 | BV48: Hamilton & Queenstown | BW48: =FY!G209 -> 41.76 | BX48: =FY!H209 -> 54 | BY48: =FY!I209 -> 52.3 | BZ48: =FY!J209 -> 50.7 | CA48: =FY!K209 -> 49.8 | CB48: =FY!L209 -> 50.796 | CD48: =BZ48 -> 50.7 | CE48: 49.8 | CF48: =CE48/CD48-1 -> -0.017751479 | CG48: =CA48 -> 49.8 | CH48: =$CE48/CG48-1 -> 0 | CI48: =CM48 -> 45.485473 | CJ48: =$CE48/CI48-1 -> 0.094855066 | CM48: =DC48 -> 45.485473 | CO48: SKC_NZ | CP48: Total revenue - Slot - Hamilton and Queenstown | CQ48: consensus.vaactuals | CR48: =_xll.VAData($AD48,CR$4,$AE48,$AF48) -> 40.8 | CS48: =_xll.VAData($AD48,CS$4,$AE48,$AF48) -> 54.1 | CT48: =_xll.VAData($AD48,CT$4,$AE48,$AF48) -> 52.6 | CU48: =_xll.VAData($AD48,CU$4,$AE48,$AF48) -> 50.7 | CV48: =_xll.VAData($AD48,CV$4,$AE48,$AF48) -> 49.8 | CW48: =_xll.VAData($AD48,CW$4,$AE48,$AF48) -> 51.17 | CY48: 40.8 | CZ48: 54.1 | DA48: 52.6 | DB48: 47.107625 | DC48: 45.485473 | DD48: 46.726037 | DF48: =BW48-CY48 -> 0.96 | DG48: =BX48-CZ48 -> -0.1 | DH48: =BY48-DA48 -> -0.3 | DI48: =BZ48-DB48 -> 3.592375 | DJ48: =CA48-DC48 -> 4.3145275 | DK48: =CB48-DD48 -> 4.0699633
C49: Adelaide | F49: =HY!O97 -> 51.6 | G49: =HY!P97 -> 48.2 | H49: =HY!Q97 -> 46.6 | I49: =HY!R97 -> 51.3 | J49: =HY!S97 -> 50.3 | K49: =HY!T97 -> 45.6 | L49: =HY!U97 -> 50.2 | M49: =HY!V97 -> 52.8 | ... O49: =HY!X97 -> 52 | Q49: =J49 -> 50.3 | R49: 50.2 | S49: =R49/Q49-1 -> -0.0019880716 | T49: =L49 -> 50.2 | U49: =$R49/T49-1 -> 0 | V49: =AB49 -> 48.53938 | W49: =$R49/V49-1 -> 0.034211807 | AB49: =BB49 -> 48.53938 | AD49: SKC_NZ | AE49: Total revenue - Slot - Adelaide | AF49: consensus.vaactuals | AG49: =_xll.VAData($AD49,AG$4,$AE49,$AF49) -> 36.539436 | AH49: =_xll.VAData($AD49,AH$4,$AE49,$AF49) -> 44.663312 | AI49: =_xll.VAData($AD49,AI$4,$AE49,$AF49) -> 51.539565 | AJ49: =_xll.VAData($AD49,AJ$4,$AE49,$AF49) -> 48.117041 | AK49: =_xll.VAData($AD49,AK$4,$AE49,$AF49) -> 46.6 | AL49: =_xll.VAData($AD49,AL$4,$AE49,$AF49) -> 51.3 | AM49: =_xll.VAData($AD49,AM$4,$AE49,$AF49) -> 50.3 | AN49: =_xll.VAData($AD49,AN$4,$AE49,$AF49) -> 45.6 | ... AR49: =_xll.VAData($AD49,AR$4,$AE49,$AF49) -> 51.593934 | AT49: 36.539436 | AU49: 44.663312 | AV49: 51.539565 | AW49: 48.117041 | AX49: 46.6 | AY49: 51.3 | AZ49: 50.3 | BA49: 45.6 | BB49: 48.53938 | BC49: 47.099024 | BD49: 47.019449 | BE49: 45.363988 | BI49: =F49-AV49 -> 0.060434831 | BJ49: =G49-AW49 -> 0.082958548 | BK49: =H49-AX49 -> 0 | BL49: =I49-AY49 -> 0 | BM49: =J49-AZ49 -> 0 | BN49: =K49-BA49 -> 0 | BO49: =L49-BB49 -> 1.6606199 | BP49: =M49-BC49 -> 5.7009757 | ... BR49: =O49-BE49 -> 6.6360122 | BV49: Adelaide | BW49: =FY!G210 -> 71.101914 | BX49: =FY!H210 -> 99.8 | BY49: =FY!I210 -> 97.9 | BZ49: =FY!J210 -> 95.9 | CA49: =FY!K210 -> 103 | CB49: =FY!L210 -> 104 | CD49: =BZ49 -> 95.9 | CE49: 103 | CF49: =CE49/CD49-1 -> 0.074035454 | CG49: =CA49 -> 103 | CH49: =$CE49/CG49-1 -> 0 | CI49: =CM49 -> 96.563492 | CJ49: =$CE49/CI49-1 -> 0.066655704 | CM49: =DC49 -> 96.563492 | CO49: SKC_NZ | CP49: Total revenue - Slot - Adelaide | CQ49: consensus.vaactuals | CR49: =_xll.VAData($AD49,CR$4,$AE49,$AF49) -> 82.804011 | CS49: =_xll.VAData($AD49,CS$4,$AE49,$AF49) -> 109.09351 | CT49: =_xll.VAData($AD49,CT$4,$AE49,$AF49) -> 97.9 | CU49: =_xll.VAData($AD49,CU$4,$AE49,$AF49) -> 95.902545 | CV49: =_xll.VAData($AD49,CV$4,$AE49,$AF49) -> 103 | CW49: =_xll.VAData($AD49,CW$4,$AE49,$AF49) -> 104.78193 | CY49: 82.804011 | CZ49: 109.09351 | DA49: 97.9 | DB49: 95.9 | DC49: 96.563492 | DD49: 92.522348 | DF49: =BW49-CY49 -> -11.702096 | DG49: =BX49-CZ49 -> -9.2935083 | DH49: =BY49-DA49 -> 0 | DI49: =BZ49-DB49 -> 0 | DJ49: =CA49-DC49 -> 6.4365076 | DK49: =CB49-DD49 -> 11.477652
C51: Local Tables | BV51: Local Tables
C52: Auckland | F52: =HY!O84 -> 57.7 | G52: =HY!P84 -> 63.9 | H52: =HY!Q84 -> 66.4 | I52: =HY!R84 -> 61.2 | J52: =HY!S84 -> 57.1 | K52: =HY!T84 -> 57.6 | L52: =HY!U84 -> 54.5 | M52: =HY!V84 -> 49.9 | ... O52: =HY!X84 -> 48 | Q52: =J52 -> 57.1 | R52: 54.5 | S52: =R52/Q52-1 -> -0.045534151 | T52: =L52 -> 54.5 | U52: =$R52/T52-1 -> 0 | V52: =AB52 -> 54.817097 | W52: =$R52/V52-1 -> -0.0057846456 | AB52: =BB52 -> 54.817097 | AD52: SKC_NZ | AE52: Total revenue - Local table - Auckland | AF52: consensus.vaactuals | AG52: =_xll.VAData($AD52,AG$4,$AE52,$AF52) -> 21.969946 | AH52: =_xll.VAData($AD52,AH$4,$AE52,$AF52) -> 48.146902 | AI52: =_xll.VAData($AD52,AI$4,$AE52,$AF52) -> 57.7 | AJ52: =_xll.VAData($AD52,AJ$4,$AE52,$AF52) -> 63.9 | AK52: =_xll.VAData($AD52,AK$4,$AE52,$AF52) -> 66.4 | AL52: =_xll.VAData($AD52,AL$4,$AE52,$AF52) -> 61.2 | AM52: =_xll.VAData($AD52,AM$4,$AE52,$AF52) -> 57.1 | AN52: =_xll.VAData($AD52,AN$4,$AE52,$AF52) -> 57.6 | ... AR52: =_xll.VAData($AD52,AR$4,$AE52,$AF52) -> 49.702615 | AT52: 21.969946 | AU52: 48.146902 | AV52: 57.7 | AW52: 63.9 | AX52: 66.4 | AY52: 61.2 | AZ52: 57.1 | BA52: 57.6 | BB52: 54.817097 | BC52: 55.042802 | BD52: 58.096085 | BE52: 57.970688 | BI52: =F52-AV52 -> 0 | BJ52: =G52-AW52 -> 0 | BK52: =H52-AX52 -> 0 | BL52: =I52-AY52 -> 0 | BM52: =J52-AZ52 -> 0 | BN52: =K52-BA52 -> 0 | BO52: =L52-BB52 -> -0.31709748 | BP52: =M52-BC52 -> -5.1428023 | ... BR52: =O52-BE52 -> -9.9706875 | BV52: Auckland | BW52: =FY!G213 -> 65.25 | BX52: =FY!H213 -> 121.6 | BY52: =FY!I213 -> 127.6 | BZ52: =FY!J213 -> 114.7 | CA52: =FY!K213 -> 104.4 | CB52: =FY!L213 -> 95 | CD52: =BZ52 -> 114.7 | CE52: 104.4 | CF52: =CE52/CD52-1 -> -0.089799477 | CG52: =CA52 -> 104.4 | CH52: =$CE52/CG52-1 -> 0 | CI52: =CM52 -> 108.49372 | CJ52: =$CE52/CI52-1 -> -0.037732363 | CM52: =DC52 -> 108.49372 | CO52: SKC_NZ | CP52: Total revenue - Local table - Auckland | CQ52: consensus.vaactuals | CR52: =_xll.VAData($AD52,CR$4,$AE52,$AF52) -> 70.116848 | CS52: =_xll.VAData($AD52,CS$4,$AE52,$AF52) -> 121.6 | CT52: =_xll.VAData($AD52,CT$4,$AE52,$AF52) -> 127.6 | CU52: =_xll.VAData($AD52,CU$4,$AE52,$AF52) -> 114.7 | CV52: =_xll.VAData($AD52,CV$4,$AE52,$AF52) -> 104.4 | CW52: =_xll.VAData($AD52,CW$4,$AE52,$AF52) -> 98.931691 | CY52: 70.116848 | CZ52: 121.6 | DA52: 127.6 | DB52: 114.7 | DC52: 108.49372 | DD52: 111.22058 | DF52: =BW52-CY52 -> -4.8668478 | DG52: =BX52-CZ52 -> 0 | DH52: =BY52-DA52 -> 0 | DI52: =BZ52-DB52 -> 0 | DJ52: =CA52-DC52 -> -4.0937246 | DK52: =CB52-DD52 -> -16.220582
C53: Hamilton | F53: =HY!O91 -> 6.6 | G53: =HY!P91 -> 5.9 | H53: =HY!Q91 -> 6.5 | I53: =HY!R91 -> 6.8 | J53: =HY!S91 -> 6.5 | K53: =HY!T91 -> 7 | L53: =HY!U91 -> 7 | M53: =HY!V91 -> 6.9 | ... O53: =HY!X91 -> 6.969 | Q53: =J53 -> 6.5 | R53: 7 | S53: =R53/Q53-1 -> 0.076923077 | T53: =L53 -> 7 | U53: =$R53/T53-1 -> 0 | V53: =AB53 -> 6.5512433 | W53: =$R53/V53-1 -> 0.068499472 | AB53: =BB53 -> 6.5512433 | AD53: SKC_NZ | AE53: Total revenue - Local table - Hamilton and Queenstown | AF53: consensus.vaactuals | AG53: =_xll.VAData($AD53,AG$4,$AE53,$AF53) -> 3.7400652 | AH53: =_xll.VAData($AD53,AH$4,$AE53,$AF53) -> 4.9577609 | AI53: =_xll.VAData($AD53,AI$4,$AE53,$AF53) -> 6.6 | AJ53: =_xll.VAData($AD53,AJ$4,$AE53,$AF53) -> 5.95 | AK53: =_xll.VAData($AD53,AK$4,$AE53,$AF53) -> 6.5 | AL53: =_xll.VAData($AD53,AL$4,$AE53,$AF53) -> 6.8 | AM53: =_xll.VAData($AD53,AM$4,$AE53,$AF53) -> 7 | AN53: =_xll.VAData($AD53,AN$4,$AE53,$AF53) -> 6.5 | ... AR53: =_xll.VAData($AD53,AR$4,$AE53,$AF53) -> 7.0391396 | AT53: 3.7400652 | AU53: 4.9577609 | AV53: 6.6 | AW53: 5.95 | AX53: 6.5 | AY53: 6.8 | AZ53: 7 | BA53: 6.5 | BB53: 6.5512433 | BC53: 6.4332964 | BD53: 6.6792945 | BE53: 6.5625437 | BI53: =F53-AV53 -> 0 | BJ53: =G53-AW53 -> -0.05 | BK53: =H53-AX53 -> 0 | BL53: =I53-AY53 -> 0 | BM53: =J53-AZ53 -> -0.5 | BN53: =K53-BA53 -> 0.5 | BO53: =L53-BB53 -> 0.44875671 | BP53: =M53-BC53 -> 0.46670361 | ... BR53: =O53-BE53 -> 0.40645632 | BV53: Hamilton & Queenstown | BW53: =FY!G214 -> 8.7 | BX53: =FY!H214 -> 12.5 | BY53: =FY!I214 -> 13.3 | BZ53: =FY!J214 -> 13.5 | CA53: =FY!K214 -> 13.9 | CB53: =FY!L214 -> 13.938 | CD53: =BZ53 -> 13.5 | CE53: 13.9 | CF53: =CE53/CD53-1 -> 0.02962963 | CG53: =CA53 -> 13.9 | CH53: =$CE53/CG53-1 -> 0 | CI53: =CM53 -> 13.622917 | CJ53: =$CE53/CI53-1 -> 0.020339447 | CM53: =DC53 -> 13.622917 | CO53: SKC_NZ | CP53: Total revenue - Local table - Hamilton and Queenstown | CQ53: consensus.vaactuals | CR53: =_xll.VAData($AD53,CR$4,$AE53,$AF53) -> 8.6978261 | CS53: =_xll.VAData($AD53,CS$4,$AE53,$AF53) -> 12.55 | CT53: =_xll.VAData($AD53,CT$4,$AE53,$AF53) -> 13.3 | CU53: =_xll.VAData($AD53,CU$4,$AE53,$AF53) -> 13.5 | CV53: =_xll.VAData($AD53,CV$4,$AE53,$AF53) -> 13.9 | CW53: =_xll.VAData($AD53,CW$4,$AE53,$AF53) -> 14.153913 | CY53: 8.6978261 | CZ53: 12.55 | DA53: 13.3 | DB53: 13.5 | DC53: 13.622917 | DD53: 13.878088 | DF53: =BW53-CY53 -> 0.002173913 | DG53: =BX53-CZ53 -> -0.05 | DH53: =BY53-DA53 -> 0 | DI53: =BZ53-DB53 -> 0 | DJ53: =CA53-DC53 -> 0.27708261 | DK53: =CB53-DD53 -> 0.059911628
C54: Adelaide | F54: =HY!O98 -> 39.9 | G54: =HY!P98 -> 30.3 | H54: =HY!Q98 -> 29.1 | I54: =HY!R98 -> 29 | J54: =HY!S98 -> 30.3 | K54: =HY!T98 -> 27.2 | L54: =HY!U98 -> 31.4 | M54: =HY!V98 -> 30.1 | ... O54: =HY!X98 -> 30.1 | Q54: =J54 -> 30.3 | R54: 31.4 | S54: =R54/Q54-1 -> 0.03630363 | T54: =L54 -> 31.4 | U54: =$R54/T54-1 -> 0 | V54: =AB54 -> 30.782923 | W54: =$R54/V54-1 -> 0.020046097 | AB54: =BB54 -> 30.782923 | AD54: SKC_NZ | AE54: Total revenue - Local table - Adelaide | AF54: consensus.vaactuals | AG54: =_xll.VAData($AD54,AG$4,$AE54,$AF54) -> 36.285273 | AH54: =_xll.VAData($AD54,AH$4,$AE54,$AF54) -> 29.613538 | AI54: =_xll.VAData($AD54,AI$4,$AE54,$AF54) -> 39.95144 | AJ54: =_xll.VAData($AD54,AJ$4,$AE54,$AF54) -> 30.235708 | AK54: =_xll.VAData($AD54,AK$4,$AE54,$AF54) -> 29.1 | AL54: =_xll.VAData($AD54,AL$4,$AE54,$AF54) -> 29 | AM54: =_xll.VAData($AD54,AM$4,$AE54,$AF54) -> 30.3 | AN54: =_xll.VAData($AD54,AN$4,$AE54,$AF54) -> 27.2 | ... AR54: =_xll.VAData($AD54,AR$4,$AE54,$AF54) -> 28.272656 | AT54: 36.285273 | AU54: 29.613538 | AV54: 39.95144 | AW54: 30.235708 | AX54: 29.1 | AY54: 29 | AZ54: 30.3 | BA54: 27.2 | BB54: 30.782923 | BC54: 29.189557 | BD54: 29.872756 | BE54: 28.346 | BI54: =F54-AV54 -> -0.051440238 | BJ54: =G54-AW54 -> 0.06429152 | BK54: =H54-AX54 -> 0 | BL54: =I54-AY54 -> 0 | BM54: =J54-AZ54 -> 0 | BN54: =K54-BA54 -> 0 | BO54: =L54-BB54 -> 0.61707745 | BP54: =M54-BC54 -> 0.91044269 | ... BR54: =O54-BE54 -> 1.7540002 | BV54: Adelaide | BW54: =FY!G215 -> 61.557687 | BX54: =FY!H215 -> 70.2 | BY54: =FY!I215 -> 58.1 | BZ54: =FY!J215 -> 57.5 | CA54: =FY!K215 -> 61.5 | CB54: =FY!L215 -> 59.1 | CD54: =BZ54 -> 57.5 | CE54: 61.5 | CF54: =CE54/CD54-1 -> 0.069565217 | CG54: =CA54 -> 61.5 | CH54: =$CE54/CG54-1 -> 0 | CI54: =CM54 -> 62.069117 | CJ54: =$CE54/CI54-1 -> -0.0091690775 | CM54: =DC54 -> 62.069117 | CO54: SKC_NZ | CP54: Total revenue - Local table - Adelaide | CQ54: consensus.vaactuals | CR54: =_xll.VAData($AD54,CR$4,$AE54,$AF54) -> 65.813576 | CS54: =_xll.VAData($AD54,CS$4,$AE54,$AF54) -> 76.31118 | CT54: =_xll.VAData($AD54,CT$4,$AE54,$AF54) -> 58.1 | CU54: =_xll.VAData($AD54,CU$4,$AE54,$AF54) -> 57.5 | CV54: =_xll.VAData($AD54,CV$4,$AE54,$AF54) -> 61.5 | CW54: =_xll.VAData($AD54,CW$4,$AE54,$AF54) -> 61.035194 | CY54: 65.813576 | CZ54: 76.31118 | DA54: 58.1 | DB54: 57.5 | DC54: 62.069117 | DD54: 60.140795 | DF54: =BW54-CY54 -> -4.2558891 | DG54: =BX54-CZ54 -> -6.1111805 | DH54: =BY54-DA54 -> 0 | DI54: =BZ54-DB54 -> 0 | DJ54: =CA54-DC54 -> -0.56911654 | DK54: =CB54-DD54 -> -1.0407946
C56: Non Gaming | BV56: Non Gaming
C57: Auckland | F57: =HY!O86 -> 58.6 | G57: =HY!P86 -> 65.3 | H57: =HY!Q86 -> 73.7 | I57: =HY!R86 -> 78.1 | J57: =HY!S86 -> 77 | K57: =HY!T86 -> 79.4 | L57: =HY!U86 -> 83.5 | M57: =HY!V86 -> 97.9 | ... O57: =HY!X86 -> 104 | Q57: =J57 -> 77 | R57: 83.5 | S57: =R57/Q57-1 -> 0.084415584 | T57: =L57 -> 83.5 | U57: =$R57/T57-1 -> 0 | V57: =AB57 -> 79.817189 | W57: =$R57/V57-1 -> 0.046140579 | AB57: =BB57 -> 79.817189 | AD57: SKC_NZ | AE57: Total revenue - Non-Gaming - Auckland | AF57: consensus.vaactuals | AG57: =_xll.VAData($AD57,AG$4,$AE57,$AF57) -> 35 | AH57: =_xll.VAData($AD57,AH$4,$AE57,$AF57) -> 35.1 | AI57: =_xll.VAData($AD57,AI$4,$AE57,$AF57) -> 58.6 | AJ57: =_xll.VAData($AD57,AJ$4,$AE57,$AF57) -> 65.3 | AK57: =_xll.VAData($AD57,AK$4,$AE57,$AF57) -> 73.7 | AL57: =_xll.VAData($AD57,AL$4,$AE57,$AF57) -> 78.1 | AM57: =_xll.VAData($AD57,AM$4,$AE57,$AF57) -> 77 | AN57: =_xll.VAData($AD57,AN$4,$AE57,$AF57) -> 79.4 | ... AR57: =_xll.VAData($AD57,AR$4,$AE57,$AF57) -> 93.328841 | AT57: 35 | AU57: 35.1 | AV57: 58.6 | AW57: 65.3 | AX57: 73.7 | AY57: 78.1 | AZ57: 77 | BA57: 79.4 | BB57: 79.817189 | BC57: 93.103336 | BD57: 94.986243 | BE57: 101.24532 | BI57: =F57-AV57 -> 0 | BJ57: =G57-AW57 -> 0 | BK57: =H57-AX57 -> 0 | BL57: =I57-AY57 -> 0 | BM57: =J57-AZ57 -> 0 | BN57: =K57-BA57 -> 0 | BO57: =L57-BB57 -> 3.6828113 | BP57: =M57-BC57 -> 4.7966645 | ... BR57: =O57-BE57 -> 2.7546755 | BV57: Auckland | BW57: =FY!G218 -> 70.1 | BX57: =FY!H218 -> 123.9 | BY57: =FY!I218 -> 151.8 | BZ57: =FY!J218 -> 156.4 | CA57: =FY!K218 -> 181.4 | CB57: =FY!L218 -> 211 | CD57: =BZ57 -> 156.4 | CE57: 181.4 | CF57: =CE57/CD57-1 -> 0.15984655 | CG57: =CA57 -> 181.4 | CH57: =$CE57/CG57-1 -> 0 | CI57: =CM57 -> 177.67526 | CJ57: =$CE57/CI57-1 -> 0.020963764 | CM57: =DC57 -> 177.67526 | CO57: SKC_NZ | CP57: Total revenue - Non-Gaming - Auckland | CQ57: consensus.vaactuals | CR57: =_xll.VAData($AD57,CR$4,$AE57,$AF57) -> 70.1 | CS57: =_xll.VAData($AD57,CS$4,$AE57,$AF57) -> 123.9 | CT57: =_xll.VAData($AD57,CT$4,$AE57,$AF57) -> 151.8 | CU57: =_xll.VAData($AD57,CU$4,$AE57,$AF57) -> 156.4 | CV57: =_xll.VAData($AD57,CV$4,$AE57,$AF57) -> 181.4 | CW57: =_xll.VAData($AD57,CW$4,$AE57,$AF57) -> 201.50758 | CY57: 70.1 | CZ57: 123.9 | DA57: 151.8 | DB57: 156.4 | DC57: 177.67526 | DD57: 199.6598 | DF57: =BW57-CY57 -> 0 | DG57: =BX57-CZ57 -> 0 | DH57: =BY57-DA57 -> 0 | DI57: =BZ57-DB57 -> 0 | DJ57: =CA57-DC57 -> 3.7247421 | DK57: =CB57-DD57 -> 11.340198
C58: Hamilton | F58: =HY!O93 -> 5.7 | G58: =HY!P93 -> 5 | H58: =HY!Q93 -> 5.4 | I58: =HY!R93 -> 5 | J58: =HY!S93 -> 5.4 | K58: =HY!T93 -> 4.7 | L58: =HY!U93 -> 5.4 | M58: =HY!V93 -> 4.6 | ... O58: =HY!X93 -> 4.5 | Q58: =J58 -> 5.4 | R58: 5.4 | S58: =R58/Q58-1 -> 0 | T58: =L58 -> 5.4 | U58: =$R58/T58-1 -> 0 | V58: =AB58 -> 4.9944115 | W58: =$R58/V58-1 -> 0.081208458 | AB58: =BB58 -> 4.9944115 | AD58: SKC_NZ | AE58: Total revenue - Non-Gaming - Hamilton and Queenstown | AF58: consensus.vaactuals | AG58: =_xll.VAData($AD58,AG$4,$AE58,$AF58) -> 4.7 | AH58: =_xll.VAData($AD58,AH$4,$AE58,$AF58) -> 3.8 | AI58: =_xll.VAData($AD58,AI$4,$AE58,$AF58) -> 5.7 | AJ58: =_xll.VAData($AD58,AJ$4,$AE58,$AF58) -> 4.95 | AK58: =_xll.VAData($AD58,AK$4,$AE58,$AF58) -> 5.5 | AL58: =_xll.VAData($AD58,AL$4,$AE58,$AF58) -> 4.9 | AM58: =_xll.VAData($AD58,AM$4,$AE58,$AF58) -> 5.4 | AN58: =_xll.VAData($AD58,AN$4,$AE58,$AF58) -> 4.7 | ... AR58: =_xll.VAData($AD58,AR$4,$AE58,$AF58) -> 4.7464404 | AT58: 4.7 | AU58: 3.8 | AV58: 5.7 | AW58: 4.95 | AX58: 5.5 | AY58: 4.9 | AZ58: 5.4 | BA58: 4.7 | BB58: 4.9944115 | BC58: 4.7598975 | BD58: 5.1508547 | BE58: 4.9124454 | BI58: =F58-AV58 -> 0 | BJ58: =G58-AW58 -> 0.05 | BK58: =H58-AX58 -> -0.1 | BL58: =I58-AY58 -> 0.1 | BM58: =J58-AZ58 -> 0 | BN58: =K58-BA58 -> 0 | BO58: =L58-BB58 -> 0.40558846 | BP58: =M58-BC58 -> -0.1598975 | ... BR58: =O58-BE58 -> -0.41244543 | BV58: Hamilton & Queenstown | BW58: =FY!G219 -> 8.5 | BX58: =FY!H219 -> 10.7 | BY58: =FY!I219 -> 10.4 | BZ58: =FY!J219 -> 10.1 | CA58: =FY!K219 -> 10 | CB58: =FY!L219 -> 9.5 | CD58: =BZ58 -> 10.1 | CE58: 10 | CF58: =CE58/CD58-1 -> -0.0099009901 | CG58: =CA58 -> 10 | CH58: =$CE58/CG58-1 -> 0 | CI58: =CM58 -> 10.48084 | CJ58: =$CE58/CI58-1 -> -0.045878002 | CM58: =DC58 -> 10.48084 | CO58: SKC_NZ | CP58: Total revenue - Non-Gaming - Hamilton and Queenstown | CQ58: consensus.vaactuals | CR58: =_xll.VAData($AD58,CR$4,$AE58,$AF58) -> 8.5 | CS58: =_xll.VAData($AD58,CS$4,$AE58,$AF58) -> 10.65 | CT58: =_xll.VAData($AD58,CT$4,$AE58,$AF58) -> 10.4 | CU58: =_xll.VAData($AD58,CU$4,$AE58,$AF58) -> 10.1 | CV58: =_xll.VAData($AD58,CV$4,$AE58,$AF58) -> 10 | CW58: =_xll.VAData($AD58,CW$4,$AE58,$AF58) -> 10.021329 | CY58: 8.5 | CZ58: 10.65 | DA58: 10.4 | DB58: 10.1 | DC58: 10.48084 | DD58: 10.797958 | DF58: =BW58-CY58 -> 0 | DG58: =BX58-CZ58 -> 0.05 | DH58: =BY58-DA58 -> 0 | DI58: =BZ58-DB58 -> 0 | DJ58: =CA58-DC58 -> -0.48084 | DK58: =CB58-DD58 -> -1.2979582
C59: Adelaide | F59: =HY!O100 -> 34.8 | G59: =HY!P100 -> 36.5 | H59: =HY!Q100 -> 35.799265 | I59: =HY!R100 -> 33.200735 | J59: =HY!S100 -> 38.9 | K59: =HY!T100 -> 33.8 | L59: =HY!U100 -> 41.1 | M59: =HY!V100 -> 39.3 | ... O59: =HY!X100 -> 40.3 | Q59: =J59 -> 38.9 | R59: 41.1 | S59: =R59/Q59-1 -> 0.05655527 | T59: =L59 -> 41.1 | U59: =$R59/T59-1 -> 0 | V59: =AB59 -> 39.80214 | W59: =$R59/V59-1 -> 0.032607789 | AB59: =BB59 -> 39.80214 | AD59: SKC_NZ | AE59: Total revenue - Non-Gaming - Adelaide | AF59: consensus.vaactuals | AG59: =_xll.VAData($AD59,AG$4,$AE59,$AF59) -> 23.686902 | AH59: =_xll.VAData($AD59,AH$4,$AE59,$AF59) -> 24.774872 | AI59: =_xll.VAData($AD59,AI$4,$AE59,$AF59) -> 34.874738 | AJ59: =_xll.VAData($AD59,AJ$4,$AE59,$AF59) -> 36.581604 | AK59: =_xll.VAData($AD59,AK$4,$AE59,$AF59) -> 35.799265 | AL59: =_xll.VAData($AD59,AL$4,$AE59,$AF59) -> 33.195769 | AM59: =_xll.VAData($AD59,AM$4,$AE59,$AF59) -> 38.9 | AN59: =_xll.VAData($AD59,AN$4,$AE59,$AF59) -> 33.8 | ... AR59: =_xll.VAData($AD59,AR$4,$AE59,$AF59) -> 42.839311 | AT59: 23.686902 | AU59: 24.774872 | AV59: 34.874738 | AW59: 36.581604 | AX59: 35.799265 | AY59: 33.195769 | AZ59: 38.9 | BA59: 33.8 | BB59: 39.80214 | BC59: 37.088962 | BD59: 40.642689 | BE59: 38.130959 | BI59: =F59-AV59 -> -0.074737888 | BJ59: =G59-AW59 -> -0.081604291 | BK59: =H59-AX59 -> 0 | BL59: =I59-AY59 -> 0.0049668769 | BM59: =J59-AZ59 -> 0 | BN59: =K59-BA59 -> 0 | BO59: =L59-BB59 -> 1.2978598 | BP59: =M59-BC59 -> 2.2110375 | ... BR59: =O59-BE59 -> 2.1690406 | BV59: Adelaide | BW59: =FY!G220 -> 47.132093 | BX59: =FY!H220 -> 71.3 | BY59: =FY!I220 -> 69 | BZ59: =FY!J220 -> 72.7 | CA59: =FY!K220 -> 80.4 | CB59: =FY!L220 -> 82.6 | CD59: =BZ59 -> 72.7 | CE59: 80.4 | CF59: =CE59/CD59-1 -> 0.10591472 | CG59: =CA59 -> 80.4 | CH59: =$CE59/CG59-1 -> 0 | CI59: =CM59 -> 80.667936 | CJ59: =$CE59/CI59-1 -> -0.0033214682 | CM59: =DC59 -> 80.667936 | CO59: SKC_NZ | CP59: Total revenue - Non-Gaming - Adelaide | CQ59: consensus.vaactuals | CR59: =_xll.VAData($AD59,CR$4,$AE59,$AF59) -> 49.41708 | CS59: =_xll.VAData($AD59,CS$4,$AE59,$AF59) -> 71.3 | CT59: =_xll.VAData($AD59,CT$4,$AE59,$AF59) -> 69 | CU59: =_xll.VAData($AD59,CU$4,$AE59,$AF59) -> 72.7 | CV59: =_xll.VAData($AD59,CV$4,$AE59,$AF59) -> 80.4 | CW59: =_xll.VAData($AD59,CW$4,$AE59,$AF59) -> 86.122713 | CY59: 49.41708 | CZ59: 71.3 | DA59: 69 | DB59: 72.7 | DC59: 80.667936 | DD59: 81.735529 | DF59: =BW59-CY59 -> -2.2849873 | DG59: =BX59-CZ59 -> 0 | DH59: =BY59-DA59 -> 0 | DI59: =BZ59-DB59 -> 0 | DJ59: =CA59-DC59 -> -0.26793598 | DK59: =CB59-DD59 -> 0.86447062
AD64: SKC_NZ | AE64: EBITDA | AF64: consensus.vaactuals | CO64: SKC_NZ | CP64: EBITDA | CQ64: consensus.vaactuals | CR64: =_xll.VAData($AD64,CR$4,$AE64,$AF64) -> 96.9 | CS64: =_xll.VAData($AD64,CS$4,$AE64,$AF64) -> 165.899 | CT64: =_xll.VAData($AD64,CT$4,$AE64,$AF64) -> 138.157 | CU64: =_xll.VAData($AD64,CU$4,$AE64,$AF64) -> 216.095 | CV64: =_xll.VAData($AD64,CV$4,$AE64,$AF64) -> 120.474 | CW64: =_xll.VAData($AD64,CW$4,$AE64,$AF64) -> 158.87317 | CY64: 96.9 | CZ64: 165.899 | DA64: 138.157 | DB64: 216.095 | DC64: 149.96293 | DD64: 174.81695 | DG64: =BX64-CZ64 -> -165.899 | DH64: =BY64-DA64 -> -138.157 | DI64: =BZ64-DB64 -> -216.095 | DJ64: =CA64-DC64 -> -149.96293 | DK64: =CB64-DD64 -> -174.81695
M455: =HY!M83 -> 52.2

Sheet Rev Tables
E2: FY24A | F2: FY25A | G2: FY26E | H2: FY27E | I2: FY28E | J2: FY29E | K2: FY30E | L2: FY31E | M2: FY32E | N2: FY33E | O2: FY34E
C3: Revenue | D3: New | E3: =FY!I25 -> 870.5 | F3: =FY!J25 -> 825.2 | G3: =FY!K25 -> 822.7 | H3: =FY!L25 -> 840.934 | I3: =FY!M25 -> 859.61223 | J3: =FY!N25 -> 899.31189 | K3: =FY!O25 -> 935.82404 | L3: =FY!P25 -> 973.90198 | ... O3: =FY!S25 -> 1092.3405
D4: Old | E4: 870.5 | F4: 825.2 | G4: 822.79615 | H4: 840.934 | I4: 859.61223 | J4: 899.31189 | K4: 935.82404 | L4: 973.90198 | M4: 1013.4024 | N4: 1055.1144 | O4: 1092.3405
D5: % change | E5: =E3/E4-1 -> 0 | F5: =F3/F4-1 -> 0 | G5: =G3/G4-1 -> -0.00011685762 | H5: =H3/H4-1 -> 0 | I5: =I3/I4-1 -> 0 | J5: =J3/J4-1 -> 0 | K5: =K3/K4-1 -> 0 | L5: =L3/L4-1 -> 0 | ... O5: =O3/O4-1 -> 0
C6: EBITDA | D6: New | E6: =FY!I29 -> 277.8 | F6: =FY!J29 -> 233.7 | G6: =FY!K29 -> 181.6 | H6: =FY!L29 -> 183.18614 | I6: =FY!M29 -> 204.83215 | J6: =FY!N29 -> 229.3445 | K6: =FY!O29 -> 238.69844 | L6: =FY!P29 -> 248.54432 | ... O6: =FY!S29 -> 276.09809
D7: Old | E7: 277.8 | F7: 233.7 | G7: 181.85079 | H7: 183.18614 | I7: 204.83215 | J7: 229.3445 | K7: 238.69844 | L7: 248.54432 | M7: 258.82422 | N7: 269.85336 | O7: 276.09809
D8: % change | E8: =E6/E7-1 -> 0 | F8: =F6/F7-1 -> 0 | G8: =G6/G7-1 -> -0.001379108 | H8: =H6/H7-1 -> 0 | I8: =I6/I7-1 -> 0 | J8: =J6/J7-1 -> 0 | K8: =K6/K7-1 -> 0 | L8: =L6/L7-1 -> 0 | ... O8: =O6/O7-1 -> 0
C9: NPAT | D9: New | E9: =FY!I41 -> 123.2 | F9: =FY!J41 -> 71.5 | G9: =FY!K41 -> 38 | H9: =FY!L41 -> 30.450323 | I9: =FY!M41 -> 54.764411 | J9: =FY!N41 -> 74.577356 | K9: =FY!O41 -> 84.030967 | L9: =FY!P41 -> 93.483377 | ... O9: =FY!S41 -> 115.97781
D10: Old | E10: 123.2 | F10: 71.5 | G10: 22.749324 | H10: 30.450323 | I10: 54.764411 | J10: 74.577356 | K10: 84.030967 | L10: 93.483377 | M10: 101.95492 | N10: 110.76081 | O10: 115.97781
D11: % change | E11: =E9/E10-1 -> 0 | F11: =F9/F10-1 -> 0 | G11: =G9/G10-1 -> 0.67037933 | H11: =H9/H10-1 -> 0 | I11: =I9/I10-1 -> 0 | J11: =J9/J10-1 -> 0 | K11: =K9/K10-1 -> 0 | L11: =L9/L10-1 -> 0 | ... O11: =O9/O10-1 -> 0
C12: Valuation | D12: New | H12: =HY!D654 -> 0.65016617
D13: Old | H13: 0.64471468
D14: % change | H14: =H12/H13-1 -> 0.0084556719

Sheet III
E3: #NAME? | F3: Date | G3: ClosePrice
E4: AUDUSD.FX | F4: 44837 | G4: 0.6514
F5: 44838 | G5: 0.6494
F6: 44839 | G6: 0.6489
F7: 44840 | G7: 0.64032
F8: 44841 | G8: 0.63807
F9: 44844 | G9: 0.626215
F10: 44845 | G10: 0.627
F11: 44846 | G11: 0.627715
F12: 44847 | G12: 0.629865
F13: 44848 | G13: 0.61984
F14: 44851 | G14: 0.6292
F15: 44852 | G15: 0.63092
F16: 44853 | G16: 0.62644
... F133: 45016 | G133: 0.66855

Sheet IV

Sheet 4Q26
C4: 1H24A | D4: 2H24A | E4: 1H25A | F4: 2H25A | G4: 1H26A | H4: 2H26E
C5: 144.3 | D5: 133.5 | E5: 119.5 | F5: 114.2 | G5: 85.5 | H5: =181.6-G5 -> 96.1
G7: 3Q | H7: =(H5-20)/2+20 -> 58.05
G8: 4Q | H8: =H7-20 -> 38.05
G10: 4Q FY run rate (FY27) | H10: =H8*4 -> 152.2
G11: Consenus | H11: 197.49483

Sheet VA Cons
AO1: =AO2&"E" -> 1H24E | AP1: =AP2&"E" -> 2H24E | AQ1: =AQ2&"E" -> 1H25E | AR1: =AR2&"E" -> 2H25E | AS1: =AS2&"E" -> 1H26E | AT1: =AT2&"E" -> 2H26E | AU1: =AU2&"E" -> 1H27E | AV1: =AV2&"E" -> 2H27E | ... AX1: =AX2&"E" -> 2H28E | BP1: =BP2&"E" -> 1H24E | BQ1: =BQ2&"E" -> 2H24E | BR1: =BR2&"E" -> 1H25E | BS1: =BS2&"E" -> 2H25E | BT1: =BT2&"E" -> 1H26E | BU1: =BU2&"E" -> 2H26E | BV1: =BV2&"E" -> 1H27E | BW1: =BW2&"E" -> 2H27E | ... BY1: =BY2&"E" -> 2H28E
B2: BM Input/Calc | E2: 1H18 | F2: 2H18 | G2: 1H19 | H2: 2H19 | I2: 1H20 | J2: 2H20 | K2: 1H21 | L2: 2H21 | M2: 1H22 | N2: 2H22 | O2: 1H23 | P2: 2H23 | Q2: 1H24 | R2: 2H24 | S2: 1H25 | T2: 2H25 | U2: 1H26 | V2: 2H26 | W2: 1H27 | X2: 2H27 | Y2: 1H28 | Z2: 2H28 | AC2: 1H18 | AD2: 2H18 | AE2: 1H19 | AF2: 2H19 | AG2: 1H20 | AH2: 2H20 | AI2: 1H21 | AJ2: 2H21 | AK2: 1H22 | AL2: 2H22 | AM2: 1H23 | AN2: 2H23 | AO2: 1H24 | AP2: 2H24 | AQ2: 1H25 | AR2: 2H25 | AS2: 1H26 | AT2: 2H26 | AU2: 1H27 | AV2: 2H27 | AW2: 1H28 | AX2: 2H28 | BD2: 1H18 | BE2: 2H18 | BF2: 1H19 | BG2: 2H19 | BH2: 1H20 | BI2: 2H20 | BJ2: 1H21 | BK2: 2H21 | BL2: 1H22 | BM2: 2H22 | BN2: 1H23 | BO2: 2H23 | BP2: 1H24 | BQ2: 2H24 | BR2: 1H25 | BS2: 2H25 | BT2: 1H26 | BU2: 2H26 | BV2: 1H27 | BW2: 2H27 | BX2: 1H28 | BY2: 2H28
B3: Aristo Period
B4: Period | C4: Units | E4: 1H18A | F4: 2H18A | G4: 1H19A | H4: 2H19A | I4: 1H20A | J4: 2H20A | K4: 1H21A | L4: 2H21A | M4: 1H22A | N4: 2H22A | O4: 1H23A | P4: 2H23A | Q4: 1H24E | R4: 2H24E | S4: 1H25E | T4: 2H25E | U4: 1H26E | V4: 2H26E | W4: 1H27E | X4: 2H27E | Y4: 1H28E | Z4: 2H28E | AC4: 1H18A | AD4: 2H18A | AE4: 1H19A | AF4: 2H19A | AG4: 1H20A | AH4: 2H20A | AI4: 1H21A | AJ4: 2H21A | AK4: 1H22A | AL4: 2H22A | AM4: 1H23A | AN4: 2H23A | AO4: 1H24E | AP4: 2H24E | AQ4: 1H25E | AR4: 2H25E | AS4: 1H26E | AT4: 2H26E | AU4: 1H27E | AV4: 2H27E | AW4: 1H28E | AX4: 2H28E | BD4: 1H18A | BE4: 2H18A | BF4: 1H19A | BG4: 2H19A | BH4: 1H20A | BI4: 2H20A | BJ4: 1H21A | BK4: 2H21A | BL4: 1H22A | BM4: 2H22A | BN4: 1H23A | BO4: 2H23A | BP4: 1H24E | BQ4: 2H24E | BR4: 1H25E | BS4: 2H25E | BT4: 1H26E | BU4: 2H26E | BV4: 1H27E | BW4: 2H27E | BX4: 1H28E | BY4: 2H28E
B5: Date Ended | E5: 43100 | F5: =EOMONTH(E5,6) -> 43281 | G5: =EOMONTH(F5,6) -> 43465 | H5: =EOMONTH(G5,6) -> 43646 | I5: =EOMONTH(H5,6) -> 43830 | J5: =EOMONTH(I5,6) -> 44012 | K5: =EOMONTH(J5,6) -> 44196 | L5: =EOMONTH(K5,6) -> 44377 | M5: =EOMONTH(L5,6) -> 44561 | ... Z5: =EOMONTH(Y5,6) -> 46934 | AC5: 43100 | AD5: =EOMONTH(AC5,6) -> 43281 | AE5: =EOMONTH(AD5,6) -> 43465 | AF5: =EOMONTH(AE5,6) -> 43646 | AG5: =EOMONTH(AF5,6) -> 43830 | AH5: =EOMONTH(AG5,6) -> 44012 | AI5: =EOMONTH(AH5,6) -> 44196 | AJ5: =EOMONTH(AI5,6) -> 44377 | AK5: =EOMONTH(AJ5,6) -> 44561 | ... AX5: =EOMONTH(AW5,6) -> 46934 | BD5: 43100 | BE5: =EOMONTH(BD5,6) -> 43281 | BF5: =EOMONTH(BE5,6) -> 43465 | BG5: =EOMONTH(BF5,6) -> 43646 | BH5: =EOMONTH(BG5,6) -> 43830 | BI5: =EOMONTH(BH5,6) -> 44012 | BJ5: =EOMONTH(BI5,6) -> 44196 | BK5: =EOMONTH(BJ5,6) -> 44377 | BL5: =EOMONTH(BK5,6) -> 44561 | ... BY5: =EOMONTH(BX5,6) -> 46934
B8: REVENUE
B10: =BA10 -> Total revenue - Domestic - Auckland | C10: NZ$m | D10: VA | E10: =AC10 -> 289.98487 | F10: =AD10 -> 294.66518 | G10: =AE10 -> 307.78236 | H10: =AF10 -> 298.86533 | I10: =AG10 -> 305.6 | J10: =AH10 -> 191.7 | K10: =AI10 -> 230.8 | L10: =AJ10 -> 257.44202 | ... Z10: =AX10 -> 349.29741 | AC10: 289.98487 | AD10: 294.66518 | AE10: 307.78236 | AF10: 298.86533 | AG10: 305.6 | AH10: 191.7 | AI10: 230.8 | AJ10: 257.44202 | AK10: 118.5 | AL10: 212.1 | AM10: 280.9 | AN10: 287.9 | AO10: 300.02115 | AP10: 303.83159 | AQ10: 323.93105 | AR10: 319.55918 | AS10: 337.41024 | AT10: 331.68359 | AU10: 347.05359 | AV10: 339.7339 | AW10: 356.13237 | AX10: 349.29741 | AZ10: SKC_NZ | BA10: Total revenue - Domestic - Auckland | BB10: consensus.vaactuals | BD10: =_xll.VAData($AZ10,BD$2,$BA10,$BB10) -> 283.26261 | BE10: =_xll.VAData($AZ10,BE$2,$BA10,$BB10) -> 287.87169 | BF10: =_xll.VAData($AZ10,BF$2,$BA10,$BB10) -> 296.35885 | BG10: =_xll.VAData($AZ10,BG$2,$BA10,$BB10) -> 292.63708 | BH10: =_xll.VAData($AZ10,BH$2,$BA10,$BB10) -> 293.8917 | BI10: =_xll.VAData($AZ10,BI$2,$BA10,$BB10) -> 189.80597 | BJ10: =_xll.VAData($AZ10,BJ$2,$BA10,$BB10) -> 221.21224 | BK10: =_xll.VAData($AZ10,BK$2,$BA10,$BB10) -> 250.48128 | ... BY10: =_xll.VAData($AZ10,BY$2,$BA10,$BB10) -> 254.64943
C11: NZ$m | D11: E&P | E11: =HY!#REF! -> #REF! | F11: =HY!#REF! -> #REF! | G11: =HY!#REF! -> #REF! | H11: =HY!#REF! -> #REF! | I11: =HY!#REF! -> #REF! | J11: =HY!#REF! -> #REF! | K11: =HY!#REF! -> #REF! | L11: =HY!#REF! -> #REF! | ... Z11: =HY!#REF! -> #REF!
C12: % | D12: E&P vs. Cons | E12: =IFERROR(ROUND(E10/E11-1,3),"") | F12: =IFERROR(ROUND(F10/F11-1,3),"") | G12: =IFERROR(ROUND(G10/G11-1,3),"") | H12: =IFERROR(ROUND(H10/H11-1,3),"") | I12: =IFERROR(ROUND(I10/I11-1,3),"") | J12: =IFERROR(ROUND(J10/J11-1,3),"") | K12: =IFERROR(ROUND(K10/K11-1,3),"") | L12: =IFERROR(ROUND(L10/L11-1,3),"") | ... Z12: =IFERROR(ROUND(Z10/Z11-1,3),"")
B14: =BA14 -> Total revenue - Hamilton | C14: NZ$m | D14: VA | E14: =AC14 -> 30.6 | F14: =AD14 -> 30.044068 | G14: =AE14 -> 31.5 | H14: =AF14 -> 30.3 | I14: =AG14 -> 34.048711 | J14: =AH14 -> 24.767956 | K14: =AI14 -> 36.737049 | L14: =AJ14 -> 36.7 | ... Z14: =AX14 -> 40.872839 | AC14: 30.6 | AD14: 30.044068 | AE14: 31.5 | AF14: 30.3 | AG14: 34.048711 | AH14: 24.767956 | AI14: 36.737049 | AJ14: 36.7 | AK14: 24.3 | AL14: 32 | AM14: 39.5 | AN14: 35.4 | AO14: 38.32914 | AP14: 36.435417 | AQ14: 39.863276 | AR14: 37.486294 | AS14: 41.37835 | AT14: 38.619461 | AU14: 42.542836 | AV14: 39.70177 | AW14: 43.728641 | AX14: 40.872839 | AZ14: SKC_NZ | BA14: Total revenue - Hamilton | BB14: consensus.vaactuals | BD14: =_xll.VAData($AZ14,BD$2,$BA14,$BB14) -> 30.617625 | BE14: =_xll.VAData($AZ14,BE$2,$BA14,$BB14) -> 30.057205 | BF14: =_xll.VAData($AZ14,BF$2,$BA14,$BB14) -> 31.491703 | BG14: =_xll.VAData($AZ14,BG$2,$BA14,$BB14) -> 30.280357 | BH14: =_xll.VAData($AZ14,BH$2,$BA14,$BB14) -> 34.046133 | BI14: =_xll.VAData($AZ14,BI$2,$BA14,$BB14) -> 24.803867 | BJ14: =_xll.VAData($AZ14,BJ$2,$BA14,$BB14) -> 36.666146 | BK14: =_xll.VAData($AZ14,BK$2,$BA14,$BB14) -> 36.770351 | ... BY14: =_xll.VAData($AZ14,BY$2,$BA14,$BB14) -> 38.346275
C15: NZ$m | D15: E&P | E15: =HY!#REF! -> #REF! | F15: =HY!#REF! -> #REF! | G15: =HY!#REF! -> #REF! | H15: =HY!#REF! -> #REF! | I15: =HY!#REF! -> #REF! | J15: =HY!#REF! -> #REF! | K15: =HY!#REF! -> #REF! | L15: =HY!#REF! -> #REF! | ... Z15: =HY!#REF! -> #REF!
C16: % | D16: E&P vs. Cons | E16: =IFERROR(ROUND(E14/E15-1,3),"") | F16: =IFERROR(ROUND(F14/F15-1,3),"") | G16: =IFERROR(ROUND(G14/G15-1,3),"") | H16: =IFERROR(ROUND(H14/H15-1,3),"") | I16: =IFERROR(ROUND(I14/I15-1,3),"") | J16: =IFERROR(ROUND(J14/J15-1,3),"") | K16: =IFERROR(ROUND(K14/K15-1,3),"") | L16: =IFERROR(ROUND(L14/L15-1,3),"") | ... Z16: =IFERROR(ROUND(Z14/Z15-1,3),"")
B18: =BA18 -> Total revenue - Queenstown | C18: NZ$m | D18: VA | E18: =AC18 -> 6.4 | F18: =AD18 -> 6.6 | G18: =AE18 -> 6.5 | H18: =AF18 -> 6.6435273 | I18: =AG18 -> 7.1 | J18: =AH18 -> 4 | K18: =AI18 -> 5.9 | L18: =AJ18 -> 6.3914293 | ... Z18: =AX18 -> 6.8314272 | AC18: 6.4 | AD18: 6.6 | AE18: 6.5 | AF18: 6.6435273 | AG18: 7.1 | AH18: 4 | AI18: 5.9 | AJ18: 6.3914293 | AK18: 5 | AL18: 5.2 | AM18: 6.3 | AN18: 6 | AO18: 6.2818646 | AP18: 6.0582596 | AQ18: 6.4617268 | AR18: 6.18678 | AS18: 6.6953905 | AT18: 6.4456986 | AU18: 6.8893357 | AV18: 6.6311301 | AW18: 7.0871269 | AX18: 6.8314272 | AZ18: SKC_NZ | BA18: Total revenue - Queenstown | BB18: consensus.vaactuals | BD18: =_xll.VAData($AZ18,BD$2,$BA18,$BB18) -> 6.4123525 | BE18: =_xll.VAData($AZ18,BE$2,$BA18,$BB18) -> 6.4126475 | BF18: =_xll.VAData($AZ18,BF$2,$BA18,$BB18) -> 6.5002093 | BG18: =_xll.VAData($AZ18,BG$2,$BA18,$BB18) -> 6.6805818 | BH18: =_xll.VAData($AZ18,BH$2,$BA18,$BB18) -> 7.0948201 | BI18: =_xll.VAData($AZ18,BI$2,$BA18,$BB18) -> 4.0051799 | BJ18: =_xll.VAData($AZ18,BJ$2,$BA18,$BB18) -> 5.9018722 | BK18: =_xll.VAData($AZ18,BK$2,$BA18,$BB18) -> 6.4082878 | ... BY18: =_xll.VAData($AZ18,BY$2,$BA18,$BB18) -> 7.3300509
C19: NZ$m | D19: E&P | E19: =HY!#REF! -> #REF! | F19: =HY!#REF! -> #REF! | G19: =HY!#REF! -> #REF! | H19: =HY!#REF! -> #REF! | I19: =HY!#REF! -> #REF! | J19: =HY!#REF! -> #REF! | K19: =HY!#REF! -> #REF! | L19: =HY!#REF! -> #REF! | ... Z19: =HY!#REF! -> #REF!
C20: % | D20: E&P vs. Cons | E20: =IFERROR(ROUND(E18/E19-1,3),"") | F20: =IFERROR(ROUND(F18/F19-1,3),"") | G20: =IFERROR(ROUND(G18/G19-1,3),"") | H20: =IFERROR(ROUND(H18/H19-1,3),"") | I20: =IFERROR(ROUND(I18/I19-1,3),"") | J20: =IFERROR(ROUND(J18/J19-1,3),"") | K20: =IFERROR(ROUND(K18/K19-1,3),"") | L20: =IFERROR(ROUND(L18/L19-1,3),"") | ... Z20: =IFERROR(ROUND(Z18/Z19-1,3),"")
B22: =BA22 -> Total revenue - Domestic - Adelaide | C22: NZ$m | D22: VA | E22: =AC22 -> 84.932001 | F22: =AD22 -> 76.20362 | G22: =AE22 -> 83.844581 | H22: =AF22 -> 89.4158 | I22: =AG22 -> 81.91343 | J22: =AH22 -> 46.4059 | K22: =AI22 -> 96.492942 | L22: =AJ22 -> 115.19594 | ... Z22: =AX22 -> 140.99934 | AC22: 84.932001 | AD22: 76.20362 | AE22: 83.844581 | AF22: 89.4158 | AG22: 81.91343 | AH22: 46.4059 | AI22: 96.492942 | AJ22: 115.19594 | AK22: 98.571501 | AL22: 101.27738 | AM22: 135.74661 | AN22: 122.87945 | AO22: 125.48639 | AP22: 126.00743 | AQ22: 131.47225 | AR22: 130.80947 | AS22: 133.93482 | AT22: 133.59098 | AU22: 137.68898 | AV22: 137.14503 | AW22: 141.43623 | AX22: 140.99934 | AZ22: SKC_NZ | BA22: Total revenue - Domestic - Adelaide | BB22: consensus.vaactuals | BD22: =_xll.VAData($AZ22,BD$2,$BA22,$BB22) -> 83.03973 | BE22: =_xll.VAData($AZ22,BE$2,$BA22,$BB22) -> 74.433762 | BF22: =_xll.VAData($AZ22,BF$2,$BA22,$BB22) -> 83.844581 | BG22: =_xll.VAData($AZ22,BG$2,$BA22,$BB22) -> 71.057281 | BH22: =_xll.VAData($AZ22,BH$2,$BA22,$BB22) -> 81.91343 | BI22: =_xll.VAData($AZ22,BI$2,$BA22,$BB22) -> 43.836086 | BJ22: =_xll.VAData($AZ22,BJ$2,$BA22,$BB22) -> 93.201754 | BK22: =_xll.VAData($AZ22,BK$2,$BA22,$BB22) -> 110.7279 | ... BY22: =_xll.VAData($AZ22,BY$2,$BA22,$BB22) -> 123.38565
B23: currency | C23: NZ$m | D23: E&P | E23: =HY!#REF! -> #REF! | F23: =HY!#REF! -> #REF! | G23: =HY!#REF! -> #REF! | H23: =HY!#REF! -> #REF! | I23: =HY!#REF! -> #REF! | J23: =HY!#REF! -> #REF! | K23: =HY!#REF! -> #REF! | L23: =HY!#REF! -> #REF! | ... Z23: =HY!#REF! -> #REF!
C24: % | D24: E&P vs. Cons | E24: =IFERROR(ROUND(E22/E23-1,3),"") | F24: =IFERROR(ROUND(F22/F23-1,3),"") | G24: =IFERROR(ROUND(G22/G23-1,3),"") | H24: =IFERROR(ROUND(H22/H23-1,3),"") | I24: =IFERROR(ROUND(I22/I23-1,3),"") | J24: =IFERROR(ROUND(J22/J23-1,3),"") | K24: =IFERROR(ROUND(K22/K23-1,3),"") | L24: =IFERROR(ROUND(L22/L23-1,3),"") | ... Z24: =IFERROR(ROUND(Z22/Z23-1,3),"")
B26: =BA26 -> Total revenue - International - Operating | C26: NZ$m | D26: VA | E26: =AC26 -> 61.493475 | F26: =AD26 -> 98.806525 | G26: =AE26 -> 103.3 | H26: =AF26 -> 87.2 | I26: =AG26 -> 61.9 | J26: =AH26 -> 17 | K26: =AI26 -> 8.2 | L26: =AJ26 -> 13.9 | ... Z26: =AX26 -> 30.290232 | AC26: 61.493475 | AD26: 98.806525 | AE26: 103.3 | AF26: 87.2 | AG26: 61.9 | AH26: 17 | AI26: 8.2 | AJ26: 13.9 | AK26: 2.5 | AL26: 14 | AM26: 16.4 | AN26: 18.9 | AO26: 20.691619 | AP26: 23.687264 | AQ26: 22.407327 | AR26: 24.940602 | AS26: 24.03301 | AT26: 26.779183 | AU26: 25.789387 | AV26: 28.764241 | AW26: 27.167344 | AX26: 30.290232 | AZ26: SKC_NZ | BA26: Total revenue - International - Operating | BB26: consensus.vaactuals | BD26: =_xll.VAData($AZ26,BD$2,$BA26,$BB26) -> 64.767373 | BE26: =_xll.VAData($AZ26,BE$2,$BA26,$BB26) -> 95.532627 | BF26: =_xll.VAData($AZ26,BF$2,$BA26,$BB26) -> 103.30396 | BG26: =_xll.VAData($AZ26,BG$2,$BA26,$BB26) -> 87.157413 | BH26: =_xll.VAData($AZ26,BH$2,$BA26,$BB26) -> 61.879072 | BI26: =_xll.VAData($AZ26,BI$2,$BA26,$BB26) -> 16.995696 | BJ26: =_xll.VAData($AZ26,BJ$2,$BA26,$BB26) -> 8.2299166 | BK26: =_xll.VAData($AZ26,BK$2,$BA26,$BB26) -> 13.851492 | ... BY26: =_xll.VAData($AZ26,BY$2,$BA26,$BB26) -> -
C27: NZ$m | D27: E&P | E27: =HY!#REF! -> #REF! | F27: =HY!#REF! -> #REF! | G27: =HY!#REF! -> #REF! | H27: =HY!#REF! -> #REF! | I27: =HY!#REF! -> #REF! | J27: =HY!#REF! -> #REF! | K27: =HY!#REF! -> #REF! | L27: =HY!#REF! -> #REF! | ... Z27: =HY!#REF! -> #REF!
C28: % | D28: E&P vs. Cons | E28: =IFERROR(ROUND(E26/E27-1,3),"") | F28: =IFERROR(ROUND(F26/F27-1,3),"") | G28: =IFERROR(ROUND(G26/G27-1,3),"") | H28: =IFERROR(ROUND(H26/H27-1,3),"") | I28: =IFERROR(ROUND(I26/I27-1,3),"") | J28: =IFERROR(ROUND(J26/J27-1,3),"") | K28: =IFERROR(ROUND(K26/K27-1,3),"") | L28: =IFERROR(ROUND(L26/L27-1,3),"") | ... Z28: =IFERROR(ROUND(Z26/Z27-1,3),"")
B30: =BA30 -> Total revenue - Online & e-sports | C30: NZ$m | D30: VA | E30: =AC30 -> - | F30: =AD30 -> - | G30: =AE30 -> - | H30: =AF30 -> -0.5 | I30: =AG30 -> 0.35 | J30: =AH30 -> 4.625 | K30: =AI30 -> 7.5 | L30: =AJ30 -> 5.6 | ... Z30: =AX30 -> 13.181887 | AC30: - | AD30: - | AE30: - | AF30: -0.5 | AG30: 0.35 | AH30: 4.625 | AI30: 7.5 | AJ30: 5.6 | AK30: 9.3 | AL30: 7.6 | AM30: 7.9 | AN30: 7.5 | AO30: 7.6711948 | AP30: 7.4645804 | AQ30: 8.07523 | AR30: 7.8182041 | AS30: 11.317083 | AT30: 10.912611 | AU30: 12.578679 | AV30: 12.126234 | AW30: 13.672165 | AX30: 13.181887 | AZ30: SKC_NZ | BA30: Total revenue - Online & e-sports | BB30: consensus.vaactuals | BD30: =_xll.VAData($AZ30,BD$2,$BA30,$BB30) -> - | BE30: =_xll.VAData($AZ30,BE$2,$BA30,$BB30) -> - | BF30: =_xll.VAData($AZ30,BF$2,$BA30,$BB30) -> - | BG30: =_xll.VAData($AZ30,BG$2,$BA30,$BB30) -> - | BH30: =_xll.VAData($AZ30,BH$2,$BA30,$BB30) -> 0.3 | BI30: =_xll.VAData($AZ30,BI$2,$BA30,$BB30) -> 4.30525 | BJ30: =_xll.VAData($AZ30,BJ$2,$BA30,$BB30) -> 7.6565 | BK30: =_xll.VAData($AZ30,BK$2,$BA30,$BB30) -> 5.6785 | ... BY30: =_xll.VAData($AZ30,BY$2,$BA30,$BB30) -> 22.555753
C31: NZ$m | D31: E&P | E31: =HY!#REF! -> #REF! | F31: =HY!#REF! -> #REF! | G31: =HY!#REF! -> #REF! | H31: =HY!#REF! -> #REF! | I31: =HY!#REF! -> #REF! | J31: =HY!#REF! -> #REF! | K31: =HY!#REF! -> #REF! | L31: =HY!#REF! -> #REF! | ... Z31: =HY!#REF! -> #REF!
