Workbook

Sheet NAV
B2: ARISTOCRAT LEISURE LTD (ALL.ASX)
B3: MODEL NAVIGATION SHEET
B6: ANALYST CONTACTS | L6: COMPANY CONTACTS
B7: James Fuller, CFA | G7: Sam Bradshaw | L7: Trevor Croker (CEO)
B8: Associate | G8: Analyst
B9: Gaming & Leisure | G9: Research
B10: +61 3 9235 9748 | G10: +61 3 9235 9706 | L10: Linda Assatoury (IR)
B11: james.fuller@eap.com.au | G11: sbradshaw@eap.com.au
B14: RECOMMENDATION & VALUATION | G14: KEY MULTIPLES & RATIOS | L14: KEY
B15: Recommendation: | E15: Positive | G15: FY23e PE | J15: 17.949533 | L15: Calculations | O15: Black
B16: Target Price: | E16: 42.8 | G16: FY23e EV/EBITDA | J16: 11.072123 | L16: Actuals | O16: Red
B17: Current price: | E17: 33.73 | G17: FY23e Dividend yield | J17: 0.016777608 | L17: Estimates | O17: Blue
B18: TSR: | E18: 0.28431663 | G18: FY23e Net debt / EBITDA | J18: 0.64794574 | L18: Check | O18: Green
B21: ERROR CHECKS | G21: EARNINGS CHANGES | L21: GENERAL
B22: Model | E22: 0 | G22: Group | J22: 0 | L22: Reporting currency | O22: A$
B23: Segments | E23: 0 | G23: Americas | J23: 0 | L23: Valuation currency | O23: A$
B24: Master | E24: =IF( SUM( E22:E23) < 2, 0, 1) -> 0 | G24: ANZ | J24: 0 | L24: Standard monetary unit | O24: A$m
G25: Digital | J25: 0 | L25: Financial year end | O25: September
G26: Intl Class III | J26: 0 | L26: Reporting frequency | O26: Semi-annual
G27: iGaming | J27: 0 | L27: Rounding tollerance (A$m) | O27: 1

Sheet NAV 2
B2: =$E$7 -> Logitech Intl S.A.
B3: Model navigation
B6: COMPANY DETAILS | G6: ANALYST CONTACTS | L6: COMPANY CONTACTS
B7: Name | E7: Logitech Intl S.A. | G7: James Fuller, CFA | L7: Bracken Darrell, President and CEO
B8: Ticker | E8: LOGI | G8: +44 78 6933 6734 | L8: Nate Olmstead, CFO
B9: Exchange | E9: NASDAQ-GS | G9: james_ fuller@outlook.com | L9: Nate Melihercik, IR
B10: Sector | E10: Technology
B11: Industry | E11: Hardware, Storage and Peripherals
B14: RECOMMENDATION & VALUATION | G14: KEY MULTIPLES & RATIOS (FY24E) | L14: LEGEND
B15: Recommendation | E15: Buy | G15: P/E | J15: 14.544206 | L15: Calculations | O15: Black
B16: IRR | E16: 0.13966356 | G16: EV/EBIT (non-GAAP) | J16: 12.271032 | L16: Actuals | O16: Red
B17: TSR | E17: 0.22992113 | G17: Dividend yield | J17: 0.017188975 | L17: Estimates | O17: Blue
B18: Share price | E18: 66 | G18: Levered FCF/sh yield (excl. SBC) | J18: 0.063611937 | L18: Check | O18: Pink
B19: Valuation | E19: 80.040322 | L19: Offsheet reference | O19: Green
L20: Carry forward | O20: Grey
B23: ERROR CHECKS | G23: GENERAL | L23: PAGES
B24: Valn | E24: 0 | G24: Reporting currency | J24: US$ | L24: Summary
B25: Model | E25: 0 | G25: Standard monetary unit | J25: US$m | L25: Valn
B26: FY23 | E26: 0 | G26: Financial year end | J26: March | L26: Model
B27: Scenario | E27: 0 | G27: Reporting frequency | J27: Quarterly | L27: FY23
B28: Master | E28: =IF( SUM( E24:E27) = 0, 0, 1) -> 0 | G28: ="Rounding tolerance " & "(" & $J$25 & ")" -> Rounding tolerance (US$m) | J28: 1 | L28: Scenario
L29: Comps

Sheet BM
B1: =D8 -> TAH-ASX
A2: Industrial ResearchWise Sheet | R2: BlueMatrix formulas
C3: Company static items | E3: =+E114 -> FY2022A | F3: =+F114 -> FY2023A | G3: =+G114 -> FY2024F | H3: =+H114 -> FY2025F | I3: =+I114 -> FY2026F | J3: =+J114 -> FY2027F | K3: =+K114 -> FY2028F | L3: =+L114 -> FY2029F | ... Q3: =+Q114 -> FY2034F | S3: 2022 | T3: =S3+1 -> 2023 | U3: =T3+1 -> 2024 | V3: =U3+1 -> 2025 | W3: =V3+1 -> 2026 | X3: =W3+1 -> 2027 | Y3: =X3+1 -> 2028 | Z3: =Y3+1 -> 2029 | AA3: =Z3+1 -> 2030 | ... AE3: =AD3+1 -> 2034
A4: @BEGINSTATIC | D4: @ENDSTATIC
A5: @INSTTYPE | C5: Instrument type | D5: EQ
A6: @CTYPE | C6: Instrument code type | D6: @BB
A7: @VERSION | C7: Version information (Do not change) | D7: 1
A8: @CODE | C8: Ticker | D8: TAH-ASX
A9: @MULT | C9: Multiplier | D9: 1000000
A10: @RCURR | C10: Reporting Currency | D10: $
A11: @ANALYST | C11: Lead analyst | D11: Sam Bradshaw
A13: @TARGET | B13: PRICE_TARGET | C13: Valuation | D13: =HY!$D$740 -> 0.89457633 | R13: =_xll.BLUEMATRIX2("/servlet/excelData",$D13,$B$1,$B13) -> #
A14: @REC | B14: REC | C14: Recommendation | D14: Neutral | R14: =_xll.BLUEMATRIX2("/servlet/excelData",$D14,$B$1,$B14) -> #
A15: @SHARE_OUT | B15: SHARE_OUT | C15: Shares outstanding | D15: =HY!D744 -> 2292.6 | R15: =_xll.BLUEMATRIX2("/servlet/excelData",$D15,$B$1,$B15) -> #
A16: @FLOATPER | B16: free_float | C16: Free Float % | D16: 100 | R16: =_xll.BLUEMATRIX2("/servlet/excelData",$D16,$B$1,$B16) -> #
B17: PRICE | C17: Current Share Price | D17: =HY!D749 -> 0.91 | R17: =_xll.BLUEMATRIX2("/servlet/excelData",$D17,$B$1,$B17) -> #
C18: Historic Share Price (Closing) | E18: 1.065 | F18: 1.11 | G18: 0.7 | H18: 0.715 | I18: =$D$17 -> 0.91 | J18: =$D$17 -> 0.91 | K18: =$D$17 -> 0.91 | L18: =$D$17 -> 0.91 | M18: =$D$17 -> 0.91 | N18: =$D$17 -> 0.91 | O18: =$D$17 -> 0.91 | P18: =$D$17 -> 0.91 | Q18: =$D$17 -> 0.91
C20: TSR
B21: upside_valuation | C21: Upside to valuation | D21: =(D13/D17-1)*100 -> -1.6949089 | R21: =_xll.BLUEMATRIX2("/servlet/excelData",$D21,$B$1,$B21) -> #
B22: div_yield | C22: Dividend yield | D22: =H303*100 -> 2.7972028 | R22: =_xll.BLUEMATRIX2("/servlet/excelData",$D22,$B$1,$B22) -> #
B23: exp_total_return | C23: Expected total SH return | D23: =D21+D22 -> 1.1022939 | R23: =_xll.BLUEMATRIX2("/servlet/excelData",$D23,$B$1,$B23) -> #
C25: Trading Data test
B26: 12_month_high | C26: 12 month high
B27: 12_month_low | C27: 12 month low
B28: MARKET_CAP | C28: Market cap | D28: =D17*D15 -> 2086.266 | R28: =_xll.BLUEMATRIX2("/servlet/excelData",$D28,$B$1,$B28) -> #
B29: free_float | C29: Free Float
B30: 12_month_return | C30: 12 month return (historical)
A31: @pricing_date
C34: Blended Valuation
A35: @DCF_VAL | B35: DCF_VAL | C35: Valuation - DCF | D35: =HY!$D$740 -> 0.89457633 | R35: =_xll.BLUEMATRIX2("/servlet/excelData",$D35,$B$1,$B35) -> #
A36: @CAPPER_VAL | B36: CAPPER_VAL | C36: Valuation - Capitalisation of Earnings | R36: =_xll.BLUEMATRIX2("/servlet/excelData",$D36,$B$1,$B36) -> #
A37: @PER_VAL | B37: PER_VAL | C37: Valuation - PER | R37: =_xll.BLUEMATRIX2("/servlet/excelData",$D37,$B$1,$B37) -> #
A38: @SOTP_VAL | B38: SOTP_VAL | C38: Valuation - SOTP | R38: =_xll.BLUEMATRIX2("/servlet/excelData",$D38,$B$1,$B38) -> #
A39: @BLEND_VAL | B39: PRICE_TARGET | C39: Valuation - Blended | R39: =_xll.BLUEMATRIX2("/servlet/excelData",$D39,$B$1,$B39) -> #
A40: @DCF_WT | B40: DCF_WT | C40: DCF Weightage | D40: 100 | R40: =_xll.BLUEMATRIX2("/servlet/excelData",$D40,$B$1,$B40) -> #
A41: @CAPPER_WT | B41: CAPPER_WT | C41: Capitalisation of Earnings Weightage | R41: =_xll.BLUEMATRIX2("/servlet/excelData",$D41,$B$1,$B41) -> #
A42: @PER_WT | B42: PER_WT | C42: PER Weightage | R42: =_xll.BLUEMATRIX2("/servlet/excelData",$D42,$B$1,$B42) -> #
A43: @SOTP_WT | B43: SOTP_WT | C43: SOTP Weightage | R43: =_xll.BLUEMATRIX2("/servlet/excelData",$D43,$B$1,$B43) -> #
C45: Divisional Summary
A46: @SEG1_NAME | C46: Name of Segment 1 | D46: Wagering & Media | R46: =_xll.BLUEMATRIX2("/servlet/excelData",$D46,$B$1,$B46) -> #
A47: @SEG2_NAME | C47: Name of Segment 2 | D47: Integrity Services | R47: =_xll.BLUEMATRIX2("/servlet/excelData",$D47,$B$1,$B47) -> #
A48: @SEG3_NAME | C48: Name of Segment 3
A49: @SEG4_NAME | C49: Name of Segment 4
A50: @SEG5_NAME | C50: Name of Segment 5
A51: @SEG6_NAME | C51: Name of Segment 6
A52: @SEG7_NAME | C52: Name of Segment 7
A53: @SEG8_NAME | C53: Name of Segment 8
A54: @SEG9_NAME | C54: Name of Segment 9
A55: @SEG10_NAME | C55: Name of Segment 10
A57: @SEG_PROFIT1 | C57: Type of Segmental Results | D57: Revenue
A59: @SEG_PROFIT2 | C59: Type of Segmental Results | D59: EBITDA
C61: Core Drivers, Investment Thesis, Near Term Catalysts
A62: @COREDRIVER1 | C62: Core Driver 1 | D62: Wagering market growth & comptetive landscape | R62: =_xll.BLUEMATRIX2("/servlet/excelData",D62,$B$1,"BOILER_PLATE[[eap_core_drivers]]") -> #
A63: @COREDRIVER1 | C63: Core Driver 2 | D63: Performance & innovation of wagering apps | R63: =_xll.BLUEMATRIX2("/servlet/excelData",D63,$B$1,"BOILER_PLATE[[eap_core_drivers]]") -> #
A64: @COREDRIVER1 | C64: Core Driver 3 | D64: Stakeholder management including government (taxes) & the racing industry (product fees) | R64: =_xll.BLUEMATRIX2("/servlet/excelData",D64,$B$1,"BOILER_PLATE[[eap_core_drivers]]") -> #
A65: @COREDRIVER1 | C65: Core Driver 4
A66: @COREDRIVER1 | C66: Core Driver 5
A68: @THESIS1 | C68: Investment Thesis 1 | D68: New Tabcorp app to help stabilise digital share | R68: =_xll.BLUEMATRIX2("/servlet/excelData",D68,$B$1,"BOILER_PLATE[[Investment_thesis]]") -> #
A69: @THESIS1 | C69: Investment Thesis 2 | D69: "Leveling" of the playing field to help Tabcorp become more competitive | R69: =_xll.BLUEMATRIX2("/servlet/excelData",D69,$B$1,"BOILER_PLATE[[Investment_thesis]]") -> #
A70: @THESIS1 | C70: Investment Thesis 3 | D70: Potential advertsising ban on gambling will favour Tabcorp due to retail licenses | R70: =_xll.BLUEMATRIX2("/servlet/excelData",D70,$B$1,"BOILER_PLATE[[Investment_thesis]]") -> #
A71: @THESIS1 | C71: Investment Thesis 4 | D71: Gaming Machine business to have defensive qualities and potential asset sale | R71: =_xll.BLUEMATRIX2("/servlet/excelData",D71,$B$1,"BOILER_PLATE[[Investment_thesis]]") -> #
A72: @THESIS1 | C72: Investment Thesis 5
A74: @CATALYST1 | C74: Near Term Catalyst 1
A76: @NOTES | C76: Notes
C78: Key Macro Assumptions
A79: @KEYMAC1 | C79: Name of Key Macro Assumption 1
A80: @KEYMAC2 | C80: Name of Key Macro Assumption 2
A81: @KEYMAC3 | C81: Name of Key Macro Assumption 3
A82: @KEYMAC4 | C82: Name of Key Macro Assumption 4
A83: @KEYMAC5 | C83: Name of Key Macro Assumption 5
A84: @KEYMAC6 | C84: Name of Key Macro Assumption 6
A85: @KEYMAC7 | C85: Name of Key Macro Assumption 7
A86: @KEYMAC8 | C86: Name of Key Macro Assumption 8
A87: @KEYMAC9 | C87: Name of Key Macro Assumption 9
A88: @KEYMAC10 | C88: Name of Key Macro Assumption 10
C90: Type of Key Macro Assumption
A91: @KEYMACTYPE1 | C91: Type of Key Macro Assumption 1
A92: @KEYMACTYPE2 | C92: Type of Key Macro Assumption 2
A93: @KEYMACTYPE3 | C93: Type of Key Macro Assumption 3
A94: @KEYMACTYPE4 | C94: Type of Key Macro Assumption 4
A95: @KEYMACTYPE5 | C95: Type of Key Macro Assumption 5
A96: @KEYMACTYPE6 | C96: Type of Key Macro Assumption 6
A97: @KEYMACTYPE7 | C97: Type of Key Macro Assumption 7
A98: @KEYMACTYPE8 | C98: Type of Key Macro Assumption 8
A99: @KEYMACTYPE9 | C99: Type of Key Macro Assumption 9
A100: @KEYMACTYPE10 | C100: Type of Key Macro Assumption 10
C102: Companies for Relative Chart
A103: @COM1 | C103: Company 1
A104: @COM2 | C104: Company 2
A105: @COM3 | C105: Company 3
A106: @COM4 | C106: Company 4
A107: @COM5 | C107: Company 5
A108: @COM6 | C108: Company 6
A109: @INDEX | C109: Index
A111: @ENDSTATIC
C113: Financials & other data
A114: @BEGIN | C114: Year | E114: =E117&E115&E116 -> FY2022A | F114: =F117&F115&F116 -> FY2023A | G114: =G117&G115&G116 -> FY2024F | H114: =H117&H115&H116 -> FY2025F | I114: =I117&I115&I116 -> FY2026F | J114: =J117&J115&J116 -> FY2027F | K114: =K117&K115&K116 -> FY2028F | L114: =L117&L115&L116 -> FY2029F | ... Q114: =Q117&Q115&Q116 -> FY2034F | R114: AN
A115: @DATE | C115: Reporting Financial Year | E115: 2022 | F115: =E115+1 -> 2023 | G115: =F115+1 -> 2024 | H115: =G115+1 -> 2025 | I115: =H115+1 -> 2026 | J115: =I115+1 -> 2027 | K115: =J115+1 -> 2028 | L115: =K115+1 -> 2029 | M115: =L115+1 -> 2030 | ... Q115: =P115+1 -> 2034
A116: @FSTATUS | C116: Accounts Status | E116: A | F116: A | G116: F | H116: F | I116: F | J116: F | K116: F | L116: F | M116: F | N116: F | O116: F | P116: F | Q116: F
A117: @FPERIOD | C117: Reporting Period | E117: FY | F117: FY | G117: FY | H117: FY | I117: FY | J117: FY | K117: FY | L117: FY | M117: FY | N117: FY | O117: FY | P117: FY | Q117: FY
...

Sheet I

Sheet HY
C1: Retail Rev (no impact from margins) | R1: =R117+Q117 -> 821.8 | T1: =T117+S117 -> 965.7 | U1: 1H margin | V1: =V117+U117 -> 981.2 | X1: =X117+W117 -> 1015.2483 | Z1: =Z117+Y117 -> 1001.4025 | AB1: =AB117+AA117 -> 988.67399 | AD1: =AD117+AC117 -> 998.56073 | AF1: =AF117+AE117 -> 988.57513
T2: =T1-R1 -> 143.9 | U2: 22m rev | V2: =V1-T1 -> 15.5 | X2: =X1-V1 -> 34.048269 | Z2: =Z1-X1 -> -13.845724 | AB2: =AB1-Z1 -> -12.728552 | AD2: =AD1-AB1 -> 9.8867399 | AF2: =AF1-AD1 -> -9.9856073
C3: W&M VC | R3: =R279+Q279 -> 758.2 | T3: =T279+S279 -> 915.9 | V3: =V279+U279 -> 953.2 | X3: =X279+W279 -> 1001.5534 | Z3: =Z279+Y279 -> 1008.6638 | AB3: =AB279+AA279 -> 1017.4923 | AD3: =AD279+AC279 -> 1040.0833 | AF3: =AF279+AE279 -> 1055.3853
T4: =T3-R3 -> 157.7 | U4: 9m VC | V4: =V3-T3 -> 37.3 | X4: =X3-V3 -> 48.353435 | Z4: =Z3-X3 -> 7.110363 | AB4: =AB3-Z3 -> 8.8284798 | AD4: =AD3-AB3 -> 22.591004 | AF4: =AF3-AD3 -> 15.301999
C5: W&M EBITDA | R5: =R292+Q292 -> 251.2 | T5: =T292+S292 -> 329.1 | V5: =V292+U292 -> 361.8 | X5: =X292+W292 -> 390.48893 | Z5: =Z292+Y292 -> 379.26736 | AB5: =AB292+AA292 -> 369.21395 | AD5: =AD292+AC292 -> 372.3566 | AF5: =AF292+AE292 -> 374.30407
T6: =T5-R5 -> 77.9 | U6: 9m VC | V6: =V5-T5 -> 32.7 | X6: =X5-V5 -> 28.688935 | Z6: =Z5-X5 -> -11.221572 | AB6: =AB5-Z5 -> -10.053413 | AD6: =AD5-AB5 -> 3.1426539 | AF6: =AF5-AD5 -> 1.9474653
B8: Checks | C8: =SUM(M8:AL8) -> 0 | E8: =E710 -> 0 | F8: =F710 -> 0 | G8: =G710 -> 0 | H8: =H710 -> 0 | I8: =I710 -> 0 | J8: =J710 -> 0 | K8: =K710 -> 0 | L8: =L710 -> 73.7 | ... AN8: =AN710 -> 0
A9: X | B9: Valuation | C9: =D740 -> 0.89457633 | D9: VAL | E9: =E14&E16 -> 1H18A | F9: =F14&F16 -> 2H18A | G9: =G14&G16 -> 1H19A | H9: =H14&H16 -> 2H19A | I9: =I14&I16 -> 1H20A | J9: =J14&J16 -> 2H20A | K9: =K14&K16 -> 1H21A | L9: =L14&L16 -> 2H21A | ... AN9: =AN14&AN16 -> 2H35E
B10: Period End | E10: 43100 | F10: =EOMONTH(E10,6) -> 43281 | G10: =EOMONTH(F10,6) -> 43465 | H10: =EOMONTH(G10,6) -> 43646 | I10: =EOMONTH(H10,6) -> 43830 | J10: =EOMONTH(I10,6) -> 44012 | K10: =EOMONTH(J10,6) -> 44196 | L10: =EOMONTH(K10,6) -> 44377 | M10: =EOMONTH(L10,6) -> 44561 | ... AN10: =EOMONTH(AM10,6) -> 49490
B12: Half | E12: {=_xlfn.IFS(AND(MONTH(E$10)>=7,MONTH(E$10)<=12),"1H",AND(MONTH(E$10)>=1,MONTH(E$10)<=6),"2H")} -> 1H | F12: {=_xlfn.IFS(AND(MONTH(F$10)>=7,MONTH(F$10)<=12),"1H",AND(MONTH(F$10)>=1,MONTH(F$10)<=6),"2H")} -> 2H | G12: {=_xlfn.IFS(AND(MONTH(G$10)>=7,MONTH(G$10)<=12),"1H",AND(MONTH(G$10)>=1,MONTH(G$10)<=6),"2H")} -> 1H | H12: {=_xlfn.IFS(AND(MONTH(H$10)>=7,MONTH(H$10)<=12),"1H",AND(MONTH(H$10)>=1,MONTH(H$10)<=6),"2H")} -> 2H | I12: {=_xlfn.IFS(AND(MONTH(I$10)>=7,MONTH(I$10)<=12),"1H",AND(MONTH(I$10)>=1,MONTH(I$10)<=6),"2H")} -> 1H | J12: {=_xlfn.IFS(AND(MONTH(J$10)>=7,MONTH(J$10)<=12),"1H",AND(MONTH(J$10)>=1,MONTH(J$10)<=6),"2H")} -> 2H | K12: {=_xlfn.IFS(AND(MONTH(K$10)>=7,MONTH(K$10)<=12),"1H",AND(MONTH(K$10)>=1,MONTH(K$10)<=6),"2H")} -> 1H | L12: {=_xlfn.IFS(AND(MONTH(L$10)>=7,MONTH(L$10)<=12),"1H",AND(MONTH(L$10)>=1,MONTH(L$10)<=6),"2H")} -> 2H | ... AN12: {=_xlfn.IFS(AND(MONTH(AN$10)>=7,MONTH(AN$10)<=12),"1H",AND(MONTH(AN$10)>=1,MONTH(AN$10)<=6),"2H")} -> 2H
B13: FY | E13: =IF(MONTH(E10)>6,RIGHT(YEAR(E10),2)+1,RIGHT(YEAR(E10),2)) -> 18 | F13: =IF(MONTH(F10)>6,RIGHT(YEAR(F10),2)+1,RIGHT(YEAR(F10),2)) -> 18 | G13: =IF(MONTH(G10)>6,RIGHT(YEAR(G10),2)+1,RIGHT(YEAR(G10),2)) -> 19 | H13: =IF(MONTH(H10)>6,RIGHT(YEAR(H10),2)+1,RIGHT(YEAR(H10),2)) -> 19 | I13: =IF(MONTH(I10)>6,RIGHT(YEAR(I10),2)+1,RIGHT(YEAR(I10),2)) -> 20 | J13: =IF(MONTH(J10)>6,RIGHT(YEAR(J10),2)+1,RIGHT(YEAR(J10),2)) -> 20 | K13: =IF(MONTH(K10)>6,RIGHT(YEAR(K10),2)+1,RIGHT(YEAR(K10),2)) -> 21 | L13: =IF(MONTH(L10)>6,RIGHT(YEAR(L10),2)+1,RIGHT(YEAR(L10),2)) -> 21 | ... AN13: =IF(MONTH(AN10)>6,RIGHT(YEAR(AN10),2)+1,RIGHT(YEAR(AN10),2)) -> 35
B14: FY Year | E14: =E$12&TEXT(E$13,"00") -> 1H18 | F14: =F$12&TEXT(F$13,"00") -> 2H18 | G14: =G$12&TEXT(G$13,"00") -> 1H19 | H14: =H$12&TEXT(H$13,"00") -> 2H19 | I14: =I$12&TEXT(I$13,"00") -> 1H20 | J14: =J$12&TEXT(J$13,"00") -> 2H20 | K14: =K$12&TEXT(K$13,"00") -> 1H21 | L14: =L$12&TEXT(L$13,"00") -> 2H21 | ... AN14: =AN$12&TEXT(AN$13,"00") -> 2H35
B15: Financial Year | E15: {=_xlfn.IFS(MONTH(E$10)=12,YEAR(E$10)+1,MONTH(E$10)=6,YEAR(E$10))} -> 2018 | F15: {=_xlfn.IFS(MONTH(F$10)=12,YEAR(F$10)+1,MONTH(F$10)=6,YEAR(F$10))} -> 2018 | G15: {=_xlfn.IFS(MONTH(G$10)=12,YEAR(G$10)+1,MONTH(G$10)=6,YEAR(G$10))} -> 2019 | H15: {=_xlfn.IFS(MONTH(H$10)=12,YEAR(H$10)+1,MONTH(H$10)=6,YEAR(H$10))} -> 2019 | I15: {=_xlfn.IFS(MONTH(I$10)=12,YEAR(I$10)+1,MONTH(I$10)=6,YEAR(I$10))} -> 2020 | J15: {=_xlfn.IFS(MONTH(J$10)=12,YEAR(J$10)+1,MONTH(J$10)=6,YEAR(J$10))} -> 2020 | K15: {=_xlfn.IFS(MONTH(K$10)=12,YEAR(K$10)+1,MONTH(K$10)=6,YEAR(K$10))} -> 2021 | L15: {=_xlfn.IFS(MONTH(L$10)=12,YEAR(L$10)+1,MONTH(L$10)=6,YEAR(L$10))} -> 2021 | ... AN15: {=_xlfn.IFS(MONTH(AN$10)=12,YEAR(AN$10)+1,MONTH(AN$10)=6,YEAR(AN$10))} -> 2035
B16: Actual/Estimate | E16: =IF(ISNUMBER(E$260),"A","E") -> A | F16: =IF(ISNUMBER(F$260),"A","E") -> A | G16: =IF(ISNUMBER(G$260),"A","E") -> A | H16: =IF(ISNUMBER(H$260),"A","E") -> A | I16: =IF(ISNUMBER(I$260),"A","E") -> A | J16: =IF(ISNUMBER(J$260),"A","E") -> A | K16: =IF(ISNUMBER(K$260),"A","E") -> A | L16: =IF(ISNUMBER(L$260),"A","E") -> A | M16: =IF(ISNUMBER(M$217),"A","E") -> A | N16: =IF(ISNUMBER(N$217),"A","E") -> A | O16: =IF(ISNUMBER(O$217),"A","E") -> A | P16: =IF(ISNUMBER(P$217),"A","E") -> A | Q16: =IF(ISNUMBER(Q$217),"A","E") -> A | R16: =IF(ISNUMBER(R$217),"A","E") -> A | S16: =IF(ISNUMBER(S$217),"A","E") -> A | T16: =IF(ISNUMBER(T$217),"A","E") -> A | ... AN16: =IF(ISNUMBER(AN$217),"A","E") -> E
B17: Days in period | E17: =E10-EOMONTH(E10,-6) -> 184 | F17: =F10-E10 -> 181 | G17: =G10-F10 -> 184 | H17: =H10-G10 -> 181 | I17: =I10-H10 -> 184 | J17: =J10-I10 -> 182 | K17: =K10-J10 -> 184 | L17: =L10-K10 -> 181 | M17: =M10-L10 -> 184 | ... AN17: =AN10-AM10 -> 181
A19: X | B19: GUIDANCE
B21: FY27 Guidance/Commentary
B22: Capex up to $160m
B23: D&A $225–235m
B24: Opex growth +3.0–3.5% on the FY26 $700.7m base
B25: Tax expense will continue to be impacted by non-deductible items of approximately $67m in FY27 in relation to Victorian Licence amortisation and discount unwind on annual licence payments
B26: Betmakers completion targeted during the 3Q of FY27
B27: Domestic wagering turnover growth broadly consistent with FY26, ex-FWC — i.e. ~FY26's underlying, which after stripping the FWC benefit is roughly +0.4–0.6% (FY26 reported +0.9%).
B28: ~$26m incremental EBITDA in FY27
B29: Mechanics: $140m terminal capex × 25% = $35m EBIT; +~$13m D&A = ~$48m run-rate; −$22m already in FY26. Hits both VC and opex lines
B30: It's a net number — already after the removed EBT rental income (~$20.7m in FY26) and loyalty/generosity reinvestment
B31: Victorian Licence +$12m EBITDA in FY26. no further step-up in FY27
B32: ~$5m of FWC A&P in the FY26 opex base. About half the tournament fell in FY27
... B54: PGI
A57: X | B57: WAGERING & MEDIA
B59: WAGERING
B61: Per Customer
B62: Active Users | C62: 000's | I62: 688 | J62: 715 | K62: 777 | L62: 784 | M62: 780 | N62: 783 | O62: 797 | P62: 805 | Q62: 786 | R62: 798 | S62: 801 | T62: 792 | U62: 766 | V62: 786
B63: Turnover | C63: A$ | I63: =I84/AVERAGE(I$62,G$62)*1000 -> 5255.814 | J63: =J84/AVERAGE(J$62,H$62)*1000 -> 5373.4266 | K63: =K84/AVERAGE(K$62,I$62)*1000 -> 7053.9249 | L63: =L84/AVERAGE(L$62,J$62)*1000 -> 5755.8372 | M63: =M84/AVERAGE(M$62,K$62)*1000 -> 6755.2987 | N63: =N84/AVERAGE(N$62,L$62)*1000 -> 5664.3267 | O63: =O84/AVERAGE(O$62,M$62)*1000 -> 6240.3297 | P63: =P84/AVERAGE(P$62,N$62)*1000 -> 5473.8035 | ... V63: =V84/AVERAGE(V$62,T$62)*1000 -> 5200.1267
B64: GGR | C64: A$ | M64: =M93/AVERAGE(M$62,K$62)*1000 -> 1148.4008 | N64: =N93/AVERAGE(N$62,L$62)*1000 -> 950.55903 | O64: =O93/AVERAGE(O$62,M$62)*1000 -> 1023.4141 | P64: =P93/AVERAGE(P$62,N$62)*1000 -> 897.70378 | Q64: =Q93/AVERAGE(Q$62,O$62)*1000 -> 986.28932 | R64: =R93/AVERAGE(R$62,P$62)*1000 -> 875.10767 | S64: =S93/AVERAGE(S$62,Q$62)*1000 -> 932.78261 | T64: =T93/AVERAGE(T$62,R$62)*1000 -> 856.26667 | ... V64: =V93/AVERAGE(V$62,T$62)*1000 -> 873.62129
B65: Promos | C65: A$ | M65: =M94/AVERAGE(M$62,K$62)*1000 -> -246.28131 | N65: =N94/AVERAGE(N$62,L$62)*1000 -> -185.01978 | O65: =O94/AVERAGE(O$62,M$62)*1000 -> -263.49017 | P65: =P94/AVERAGE(P$62,N$62)*1000 -> -213.95063 | Q65: =Q94/AVERAGE(Q$62,O$62)*1000 -> -262.47378 | R65: =R94/AVERAGE(R$62,P$62)*1000 -> -197.00412 | S65: =S94/AVERAGE(S$62,Q$62)*1000 -> -229.69502 | T65: =T94/AVERAGE(T$62,R$62)*1000 -> -198.02767 | ... V65: =V94/AVERAGE(V$62,T$62)*1000 -> -200.99772
B66: NGR | C66: A$ | M66: =M95/AVERAGE(M$62,K$62)*1000 -> 902.11946 | N66: =N95/AVERAGE(N$62,L$62)*1000 -> 765.53925 | O66: =O95/AVERAGE(O$62,M$62)*1000 -> 759.92391 | P66: =P95/AVERAGE(P$62,N$62)*1000 -> 683.75315 | Q66: =Q95/AVERAGE(Q$62,O$62)*1000 -> 723.81554 | R66: =R95/AVERAGE(R$62,P$62)*1000 -> 678.10356 | S66: =S95/AVERAGE(S$62,Q$62)*1000 -> 703.08759 | T66: =T95/AVERAGE(T$62,R$62)*1000 -> 658.23899 | ... V66: =V95/AVERAGE(V$62,T$62)*1000 -> 672.62357
B68: TURNOVER
B69: Racing | C69: A$m | M69: 6032.2 | N69: =11769.7-M69 -> 5737.5 | O69: 6500.8 | P69: =11946.5-O69 -> 5445.7 | Q69: 6120.1 | R69: =11361.2-Q69 -> 5241.1 | S69: 5798.3 | T69: =10903-S69 -> 5104.7 | U69: 5728.3 | V69: =10785-U69 -> 5056.7
B70: Sport | C70: A$m | M70: 947.3 | N70: =2124-M70 -> 1176.7 | O70: 1258.7 | P70: =2604.3-O70 -> 1345.6 | Q70: 1343.5 | R70: =2696.5-Q70 -> 1353 | S70: 1347.4 | T70: =2840-S70 -> 1492.6 | U70: 1440.2 | V70: =3076-U70 -> 1635.8
B71: Total Turnover | C71: A$m | M71: =SUM(M69:M70) -> 6979.5 | N71: =SUM(N69:N70) -> 6914.2 | O71: =SUM(O69:O70) -> 7759.5 | P71: =SUM(P69:P70) -> 6791.3 | Q71: =SUM(Q69:Q70) -> 7463.6 | R71: =SUM(R69:R70) -> 6594.1 | S71: =SUM(S69:S70) -> 7145.7 | T71: =SUM(T69:T70) -> 6597.3 | ... V71: =SUM(V69:V70) -> 6692.5
B73: Growth | W73: WC
B74: Digital | C74: % | G74: =G78/E78-1 -> 0.094661167 | H74: =H78/F78-1 -> 0.025772275 | I74: =I78/G78-1 -> -0.053873728 | J74: =J78/H78-1 -> 0.11465707 | K74: =K78/I78-1 -> 0.42892699 | L74: =L78/J78-1 -> 0.12285268 | M74: =M78/K78-1 -> 0.017805303 | N74: =N78/L78-1 -> 0.028743625 | ... V74: =V78/T78-1 -> 0.018594836 | W74: 0.018 | X74: 0.009 | Y74: 0.01 | Z74: 0.03 | AA74: 0.02 | AB74: 0.02 | AC74: 0.03 | AD74: 0.03 | AE74: 0.03 | AF74: 0.03 | AG74: 0.03 | AH74: 0.03 | AI74: 0.03 | AJ74: 0.03 | AK74: 0.03 | AL74: 0.03 | AM74: 0.03 | AN74: 0.03
B75: Retail | C75: % | G75: =G79/E79-1 -> -0.066831218 | H75: =H79/F79-1 -> -0.081425612 | I75: =I79/G79-1 -> -0.090107565 | J75: =J79/H79-1 -> -0.49635712 | K75: =K79/I79-1 -> -0.28156146 | L75: =L79/J79-1 -> 0.55568312 | M75: =M79/K79-1 -> -0.33699422 | N75: =N79/L79-1 -> -0.086273063 | ... V75: =V79/T79-1 -> 0.0080959053 | W75: 0.007 | X75: -0.002 | Y75: -0.015 | Z75: -0.015 | AA75: -0.015 | AB75: -0.015 | AC75: 0.01 | AD75: 0.01 | AE75: -0.01 | AF75: -0.01 | AG75: -0.01 | AH75: -0.01 | AI75: -0.01 | AJ75: -0.01 | AK75: -0.01 | AL75: -0.01 | AM75: -0.01 | AN75: -0.01
B76: Total | C76: % | G76: =G80/E80-1 -> 0.0059648307 | H76: =H80/F80-1 -> -0.030874593 | I76: =I80/G80-1 -> -0.072334309 | J76: =J80/H80-1 -> -0.19138091 | K76: =K80/I80-1 -> 0.073879358 | L76: =L80/J80-1 -> 0.25787966 | M76: =M80/K80-1 -> -0.10081165 | N76: =N80/L80-1 -> -0.015632118 | ... AN76: =AN80/AL80-1 -> 0.016980197
B78: Digital | C78: A$m | E78: 3491.4 | F78: 3360.2 | G78: 3821.9 | H78: 3446.8 | I78: 3616 | J78: 3842 | K78: 5167 | L78: 4314 | M78: 5259 | N78: 4438 | O78: 4920.5 | P78: 4346.2 | Q78: 4731.2 | R78: =8809.1-Q78 -> 4077.9 | S78: 4353.9 | T78: =8381.9-S78 -> 4028 | U78: 4343.4 | V78: =8446.3-U78 -> 4102.9 | W78: =U78*(1+W74) -> 4421.5812 | X78: =V78*(1+X74) -> 4139.8261 | Y78: =W78*(1+Y74) -> 4465.797 | Z78: =X78*(1+Z74) -> 4264.0209 | AA78: =Y78*(1+AA74) -> 4555.113 | AB78: =Z78*(1+AB74) -> 4349.3013 | AC78: =AA78*(1+AC74) -> 4691.7663 | AD78: =AB78*(1+AD74) -> 4479.7803 | ... AN78: =AL78*(1+AN74) -> 5193.2932
B79: Retail | C79: A$m | E79: 4254 | F79: 3765.4 | G79: 3969.7 | H79: 3458.8 | I79: 3612 | J79: 1742 | K79: 2595 | L79: 2710 | M79: 1720.5 | N79: 2476.2 | O79: 2839 | P79: 2445.1 | Q79: 2732.4 | R79: =5248.6-Q79 -> 2516.2 | S79: 2791.8 | T79: =5361-S79 -> 2569.2 | U79: 2825.1 | V79: =5415.1-U79 -> 2590 | W79: =U79*(1+W75) -> 2844.8757 | X79: =V79*(1+X75) -> 2584.82 | Y79: =W79*(1+Y75) -> 2802.2026 | Z79: =X79*(1+Z75) -> 2546.0477 | AA79: =Y79*(1+AA75) -> 2760.1695 | AB79: =Z79*(1+AB75) -> 2507.857 | AC79: =AA79*(1+AC75) -> 2787.7712 | AD79: =AB79*(1+AD75) -> 2532.9356 | ... AN79: =AL79*(1+AN75) -> 2408.7965
B80: Total Turnover | C80: A$m | E80: 7745.4 | F80: 7125.6 | G80: 7791.6 | H80: 6905.6 | I80: 7228 | J80: 5584 | K80: 7762 | L80: 7024 | M80: 6979.5 | N80: 6914.2 | O80: 7759.5 | P80: 6791.3 | Q80: 7463.6 | R80: =14057.7-Q80 -> 6594.1 | S80: 7145.7 | T80: =13742.9-S80 -> 6597.2 | U80: 7168.5 | V80: =13861.4-U80 -> 6692.9 | W80: =SUM(W78:W79) -> 7266.4569 | X80: =SUM(X78:X79) -> 6724.6461 | Y80: =SUM(Y78:Y79) -> 7267.9996 | Z80: =SUM(Z78:Z79) -> 6810.0686 | AA80: =SUM(AA78:AA79) -> 7315.2825 | AB80: =SUM(AB78:AB79) -> 6857.1583 | AC80: =SUM(AC78:AC79) -> 7479.5376 | AD80: =SUM(AD78:AD79) -> 7012.7159 | ... AN80: =SUM(AN78:AN79) -> 7602.0897
B81: Check | M81: =M71-M80 -> 0 | N81: =N71-N80 -> 0 | O81: =O71-O80 -> 0 | P81: =P71-P80 -> 0 | Q81: =Q71-Q80 -> 0 | R81: =R71-R80 -> 0 | S81: =S71-S80 -> 0 | T81: =T71-T80 -> 0.1 | ... V81: =V71-V80 -> -0.4
B83: DIGITAL REVENUE
B84: Digital turnover | C84: A$m | E84: =E78 -> 3491.4 | F84: =F78 -> 3360.2 | G84: =G78 -> 3821.9 | H84: =H78 -> 3446.8 | I84: =I78 -> 3616 | J84: =J78 -> 3842 | K84: =K78 -> 5167 | L84: =L78 -> 4314 | ... AN84: =AN78 -> 5193.2932
B86: Gross Yield | C86: % | M86: 0.17 | N86: =N93/N84 -> 0.16781501 | O86: 0.164 | P86: 0.164 | Q86: 0.165 | R86: 0.172 | S86: 0.17 | T86: 0.169 | U86: 0.163 | V86: 0.168 | W86: 0.168 | X86: 0.168 | Y86: 0.168 | Z86: 0.168 | AA86: 0.168 | AB86: 0.168 | AC86: 0.168 | AD86: 0.168 | AE86: 0.168 | AF86: 0.168 | AG86: 0.168 | AH86: 0.168 | AI86: 0.168 | AJ86: 0.168 | AK86: 0.168 | AL86: 0.168 | AM86: 0.168 | AN86: 0.168
B87: Net Yield | C87: % | M87: 0.134 | N87: =N95/N84 -> 0.13515097 | O87: 0.122 | P87: 0.124 | Q87: 0.121 | R87: 0.133 | S87: 0.128 | T87: 0.13 | U87: 0.123 | V87: 0.129 | W87: =W86+W88 -> 0.128 | X87: =X86+X88 -> 0.1285 | Y87: =Y86+Y88 -> 0.128 | Z87: =Z86+Z88 -> 0.128 | AA87: =AA86+AA88 -> 0.128 | AB87: =AB86+AB88 -> 0.128 | AC87: =AC86+AC88 -> 0.128 | AD87: =AD86+AD88 -> 0.128 | ... AN87: =AN86+AN88 -> 0.128
B88: Generosities | C88: % | M88: =M94/M84 -> -0.036457501 | N88: =N94/N84 -> -0.032664038 | O88: -0.042 | P88: -0.04 | Q88: -0.044 | R88: -0.039 | S88: -0.042 | T88: -0.039 | U88: -0.04 | V88: -0.039 | W88: -0.04 | X88: -0.0395 | Y88: -0.04 | Z88: -0.04 | AA88: -0.04 | AB88: -0.04 | AC88: -0.04 | AD88: -0.04 | AE88: -0.04 | AF88: -0.04 | AG88: -0.04 | AH88: -0.04 | AI88: -0.04 | AJ88: -0.04 | AK88: -0.04 | AL88: -0.04 | AM88: -0.04 | AN88: -0.04
B90: Gross Yield - FY | C90: % | K90: FY21 >> | L90: 0.166 | M90: FY22 >> | N90: 0.169 | O90: FY23 >> | P90: 0.164 | Q90: FY24 >> | R90: 0.168 | S90: FY25>> | T90: 0.17 | V90: 0.166 | X90: =X93/X84 -> 0.168 | Z90: =Z93/Z84 -> 0.168 | AB90: =AB93/AB84 -> 0.168 | AD90: =AD93/AD84 -> 0.168 | AF90: =AF93/AF84 -> 0.168 | AH90: =AH93/AH84 -> 0.168 | AJ90: =AJ93/AJ84 -> 0.168 | AL90: =AL93/AL84 -> 0.168 | AN90: =AN93/AN84 -> 0.168
B91: Net Yield - FY | C91: % | L91: 0.136 | N91: 0.134 | P91: 0.123 | R91: 0.127 | T91: 0.129 | V91: 0.126 | X91: =X95/X84 -> 0.1285 | Z91: =Z95/Z84 -> 0.128 | AB91: =AB95/AB84 -> 0.128 | AD91: =AD95/AD84 -> 0.128 | AF91: =AF95/AF84 -> 0.128 | AH91: =AH95/AH84 -> 0.128 | AJ91: =AJ95/AJ84 -> 0.128 | AL91: =AL95/AL84 -> 0.128 | AN91: =AN95/AN84 -> 0.128
B93: Gross Revenue | C93: A$m | M93: =M84*M86 -> 894.03 | N93: 744.763 | O93: =O84*O86 -> 806.962 | P93: =P84*P86 -> 712.7768 | Q93: =Q84*Q86 -> 780.648 | R93: =R84*R86 -> 701.3988 | S93: =S84*S86 -> 740.163 | T93: =T84*T86 -> 680.732 | U93: =U84*U86 -> 707.9742 | V93: =V84*V86 -> 689.2872 | ... AN93: =AN84*AN86 -> 872.47326
B94: Promotions | C94: A$m | M94: =M95-M93 -> -191.73 | N94: =N95-N93 -> -144.963 | O94: =O95-O93 -> -207.762 | P94: =P95-P93 -> -169.8768 | Q94: =Q95-Q93 -> -207.748 | R94: =R95-R93 -> -157.8988 | S94: =S95-S93 -> -182.263 | T94: =T95-T93 -> -157.432 | ... V94: =V95-V93 -> -158.5872 | W94: =W88*W84 -> -176.86325 | X94: =X88*X84 -> -163.52313 | Y94: =Y88*Y84 -> -178.63188 | Z94: =Z88*Z84 -> -170.56084 | AA94: =AA88*AA84 -> -182.20452 | AB94: =AB88*AB84 -> -173.97205 | AC94: =AC88*AC84 -> -187.67065 | AD94: =AD88*AD84 -> -179.19121 | ... AN94: =AN88*AN84 -> -207.73173
B95: Net Digital Revenue pre VRI Share | C95: A$m | M95: 702.3 | N95: =1302.1-M95 -> 599.8 | O95: 599.2 | P95: =1142.1-O95 -> 542.9 | Q95: 572.9 | R95: =1116.4-Q95 -> 543.5 | S95: 557.9 | T95: =1081.2-S95 -> 523.3 | U95: 532.9 | V95: =1063.6-U95 -> 530.7 | W95: =SUM(W93:W94) -> 565.96239 | X95: =SUM(X93:X94) -> 531.96765 | Y95: =SUM(Y93:Y94) -> 571.62202 | Z95: =SUM(Z93:Z94) -> 545.79467 | AA95: =SUM(AA93:AA94) -> 583.05446 | AB95: =SUM(AB93:AB94) -> 556.71057 | AC95: =SUM(AC93:AC94) -> 600.54609 | AD95: =SUM(AD93:AD94) -> 573.41188 | ... AN95: =SUM(AN93:AN94) -> 664.74153
B96: Promotions as a % of NGR | C96: % | M96: =M94/M95 -> -0.27300299 | N96: =N94/N95 -> -0.24168556 | O96: =O94/O95 -> -0.34673231 | P96: =P94/P95 -> -0.31290624 | Q96: =Q94/Q95 -> -0.36262524 | R96: =R94/R95 -> -0.29052217 | S96: =S94/S95 -> -0.32669475 | T96: =T94/T95 -> -0.30084464 | ... AN96: =AN94/AN95 -> -0.3125
B98: Other | C98: A$m | M98: -122.4 | N98: =-228.6-M98 -> -106.2 | O98: -106.2 | P98: =-199.4-O98 -> -93.2 | Q98: -99.5 | R98: =-194.4-Q98 -> -94.9 | S98: -18.3 | T98: =-(11.5)-S98 -> 6.8 | U98: 4 | V98: =9.2-U98 -> 5.2 | W98: =V98 -> 5.2 | X98: =W98 -> 5.2 | Y98: =X98 -> 5.2 | Z98: =Y98 -> 5.2 | AA98: =Z98 -> 5.2 | AB98: =AA98 -> 5.2 | AC98: =AB98 -> 5.2 | AD98: =AC98 -> 5.2 | ... AN98: =AM98 -> 5.2
B99: Other as a % of NGR | C99: % | M99: =M98/M95 -> -0.17428449 | N99: =N98/N95 -> -0.17705902 | O99: =O98/O95 -> -0.17723632 | P99: =P98/P95 -> -0.17167066 | Q99: =Q98/Q95 -> -0.17367778 | R99: =R98/R95 -> -0.17460902 | S99: =S98/S95 -> -0.032801577 | T99: =T98/T95 -> 0.012994458 | ... AN99: =AN98/AN95 -> 0.0078225893
B100: growth | C100: % | O100: =O98/M98-1 -> -0.13235294 | P100: =P98/N98-1 -> -0.12241055 | Q100: =Q98/O98-1 -> -0.063088512 | R100: =R98/P98-1 -> 0.018240343 | S100: =S98/Q98-1 -> -0.8160804 | T100: =T98/R98-1 -> -1.0716544 | U100: =U98/S98-1 -> -1.2185792 | V100: =V98/T98-1 -> -0.23529412
B102: Digital Wagering Revenue | C102: A$m | M102: 579.9 | N102: =1073.5-M102 -> 493.6 | O102: 493 | P102: =942.7-O102 -> 449.7 | Q102: 473.4 | R102: =922-Q102 -> 448.6 | S102: 539.6 | T102: =1069.7-S102 -> 530.1 | U102: 536.9 | V102: =1072.8-U102 -> 535.9 | W102: =W95+W98 -> 571.16239 | X102: =X95+X98 -> 537.16765 | Y102: =Y95+Y98 -> 576.82202 | Z102: =Z95+Z98 -> 550.99467 | AA102: =AA95+AA98 -> 588.25446 | AB102: =AB95+AB98 -> 561.91057 | AC102: =AC95+AC98 -> 605.74609 | AD102: =AD95+AD98 -> 578.61188 | ... AN102: =AN95+AN98 -> 669.94153
B103: Check | M103: =SUM(M95,M98)-M102 -> 0 | N103: =SUM(N95,N98)-N102 -> 0 | O103: =SUM(O95,O98)-O102 -> 0 | P103: =SUM(P95,P98)-P102 -> 0 | Q103: =SUM(Q95,Q98)-Q102 -> 0 | R103: =SUM(R95,R98)-R102 -> 0 | S103: =SUM(S95,S98)-S102 -> 0 | T103: =SUM(T95,T98)-T102 -> 0 | ... AN103: =SUM(AN95,AN98)-AN102 -> 0
B105: RETAIL REVENUE
B106: Retail Turnover | C106: A$m | M106: =M79 -> 1720.5 | N106: =N79 -> 2476.2 | O106: =O79 -> 2839 | P106: =P79 -> 2445.1 | Q106: =Q79 -> 2732.4 | R106: =R79 -> 2516.2 | S106: =S79 -> 2791.8 | T106: =T79 -> 2569.2 | ... AN106: =AN79 -> 2408.7965
B107: Gross/Net Yield | C107: % | M107: 0.167 | N107: =N111/N106 -> 0.16585898 | O107: 0.166 | P107: =P111/P106 -> 0.1677232 | Q107: 0.168 | R107: =R111/R106 -> 0.17395279 | S107: 0.172 | T107: =T111/T106 -> 0.1698194 | U107: 0.17 | V107: =V111/V106 -> 0.17030888 | W107: 0.17 | X107: 0.17 | Y107: 0.17 | Z107: 0.17 | AA107: 0.17 | AB107: 0.17 | AC107: 0.17 | AD107: 0.17 | AE107: 0.17 | AF107: 0.17 | AG107: 0.17 | AH107: 0.17 | AI107: 0.17 | AJ107: 0.17 | AK107: 0.17 | AL107: 0.17 | AM107: 0.17 | AN107: 0.17
B108: Gross Yield - FY | C108: % | K108: FY21 >> | L108: 0.166 | M108: FY22 >> | N108: 0.167 | O108: FY23 >> | P108: 0.167 | Q108: FY24 >> | R108: 0.171 | S108: FY25 >> | T108: 0.171 | U108: FY26 >> | V108: 0.17 | W108: FY27>> | X108: =X107 -> 0.17 | Z108: =Z107 -> 0.17 | AB108: =AB107 -> 0.17 | AD108: =AD107 -> 0.17 | AF108: =AF107 -> 0.17 | AH108: =AH107 -> 0.17 | AJ108: =AJ107 -> 0.17 | AL108: =AL107 -> 0.17 | AN108: =AN107 -> 0.17
B111: Net Retail Revenue per VRI Share | M111: 288.1 | N111: =698.8-M111 -> 410.7 | O111: 471.9 | P111: =882-O111 -> 410.1 | Q111: 458.1 | R111: =895.8-Q111 -> 437.7 | S111: 481.1 | T111: =917.4-S111 -> 436.3 | U111: 479.9 | V111: =921-U111 -> 441.1 | W111: =W106*W107 -> 483.62887 | X111: =X106*X107 -> 439.4194 | Y111: =Y106*Y107 -> 476.37444 | Z111: =Z106*Z107 -> 432.82811 | AA111: =AA106*AA107 -> 469.22882 | AB111: =AB106*AB107 -> 426.33569 | AC111: =AC106*AC107 -> 473.92111 | AD111: =AD106*AD107 -> 430.59904 | ... AN111: =AN106*AN107 -> 409.49541
B113: Other | M113: -11.5 | N113: =-44.8-M113 -> -33.3 | O113: -34.5 | P113: =-63.6-O113 -> -29.1 | Q113: -37.5 | R113: =-74-Q113 -> -36.5 | S113: 16 | T113: =48.3-S113 -> 32.3 | U113: 31.2 | V113: =60.2-U113 -> 29 | W113: =U113+16 -> 47.2 | X113: =V113+16 -> 45 | Y113: =W113 -> 47.2 | Z113: =X113 -> 45 | AA113: =AA111*AA114 -> 48.784486 | AB113: =AB111*AB114 -> 44.325 | AC113: =AC111*AC114 -> 49.272331 | AD113: =AD111*AD114 -> 44.76825 | AE113: =AE111*AE114 -> 48.779608 | AF113: =AF111*AF114 -> 44.320567 | AG113: =AG111*AG114 -> 48.291812 | AH113: =AH111*AH114 -> 43.877362 | ... AN113: =AN111*AN114 -> 42.57416
B114: Other as a % of NGR | M114: =M113/M111 -> -0.039916696 | N114: =N113/N111 -> -0.081081081 | O114: =O113/O111 -> -0.073108709 | P114: =P113/P111 -> -0.070958303 | Q114: =Q113/Q111 -> -0.081859856 | R114: =R113/R111 -> -0.08339045 | S114: =S113/S111 -> 0.033257119 | T114: =T113/T111 -> 0.07403163 | ... Z114: =Z113/Z111 -> 0.10396737 | AA114: =Z114 -> 0.10396737 | AB114: =AA114 -> 0.10396737 | AC114: =AB114 -> 0.10396737 | AD114: =AC114 -> 0.10396737 | AE114: =AD114 -> 0.10396737 | AF114: =AE114 -> 0.10396737 | AG114: =AF114 -> 0.10396737 | AH114: =AG114 -> 0.10396737 | ... AN114: =AM114 -> 0.10396737
B115: growth | O115: =O113/M113-1 -> 2 | P115: =P113/N113-1 -> -0.12612613 | Q115: =Q113/O113-1 -> 0.086956522 | R115: =R113/P113-1 -> 0.25429553 | S115: =S113/Q113-1 -> -1.4266667 | T115: =T113/R113-1 -> -1.8849315 | U115: =U113/S113-1 -> 0.95 | V115: =V113/T113-1 -> -0.10216718 | ... AN115: =AN113/AL113-1 -> -0.01
B117: Retail Wagering Revenue | C117: A$m | M117: 276.6 | N117: =654-M117 -> 377.4 | O117: 437.4 | P117: =818.4-O117 -> 381 | Q117: 420.6 | R117: =821.8-Q117 -> 401.2 | S117: 497.1 | T117: =965.7-S117 -> 468.6 | U117: 511.1 | V117: =981.2-U117 -> 470.1 | W117: =W111+W113 -> 530.82887 | X117: =X111+X113 -> 484.4194 | Y117: =Y111+Y113 -> 523.57444 | Z117: =Z111+Z113 -> 477.82811 | AA117: =AA111+AA113 -> 518.01331 | AB117: =AB111+AB113 -> 470.66069 | AC117: =AC111+AC113 -> 523.19344 | AD117: =AD111+AD113 -> 475.36729 | ... AN117: =AN111+AN113 -> 452.06957
B118: Check | M118: =SUM(M111,M113)-M117 -> 0 | N118: =SUM(N111,N113)-N117 -> 0 | O118: =SUM(O111,O113)-O117 -> 0 | P118: =SUM(P111,P113)-P117 -> 0 | Q118: =SUM(Q111,Q113)-Q117 -> 0 | R118: =SUM(R111,R113)-R117 -> 0 | S118: =SUM(S111,S113)-S117 -> 0 | T118: =SUM(T111,T113)-T117 -> 0 | ... AN118: =SUM(AN111,AN113)-AN117 -> 0
B120: NSW LEVEL PLAYING FIELD
B121: Include (Yes = 1, No = 0) | C121: 0
B123: EBITDA cost offset per period ($120m py) | C123: A$m | W123: 60 | X123: 60 | Y123: 60 | Z123: 60 | AA123: 60 | AB123: 60 | AC123: 60 | AD123: 60 | AE123: 60 | AF123: 60 | AG123: 60 | AH123: 60 | AI123: 60 | AJ123: 60 | AK123: 60 | AL123: 60 | AM123: 60 | AN123: 60
B124: Binomial EBITDA | C124: A$m | W124: =IF($C$121=1,W123,0) -> 0 | X124: =IF($C$121=1,X123,0) -> 0 | Y124: =IF($C$121=1,Y123,0) -> 0 | Z124: =IF($C$121=1,Z123,0) -> 0 | AA124: =IF($C$121=1,AA123,0) -> 0 | AB124: =IF($C$121=1,AB123,0) -> 0 | AC124: =IF($C$121=1,AC123,0) -> 0 | AD124: =IF($C$121=1,AD123,0) -> 0 | ... AN124: =IF($C$121=1,AN123,0) -> 0
B126: COST (first yr $600m, $30m/yr thereafter 20yrs)
B128: Total Capex | C128: A$m | W128: 15 | X128: 15 | Y128: 15 | Z128: 15 | AA128: 15 | AB128: 15 | AC128: 15 | AD128: 15 | AE128: 15 | AF128: 15 | AG128: 15 | AH128: 15 | AI128: 15 | AJ128: 15 | AK128: 15 | AL128: 15 | AM128: 15 | AN128: 15
B129: Binomial Capex | C129: A$m | W129: =IF($C$121=1,W128,0) -> 0 | X129: =IF($C$121=1,X128,0) -> 0 | Y129: =IF($C$121=1,Y128,0) -> 0 | Z129: =IF($C$121=1,Z128,0) -> 0 | AA129: =IF($C$121=1,AA128,0) -> 0 | AB129: =IF($C$121=1,AB128,0) -> 0 | AC129: =IF($C$121=1,AC128,0) -> 0 | AD129: =IF($C$121=1,AD128,0) -> 0 | ... AN129: =IF($C$121=1,AN128,0) -> 0
B131: Total Ammortisation | C131: A$m | W131: -30 | X131: -30 | Y131: -30 | Z131: -30 | AA131: -30 | AB131: -30 | AC131: -30 | AD131: -30 | AE131: -30 | AF131: -30 | AG131: -30 | AH131: -30 | AI131: -30 | AJ131: -30 | AK131: -30 | AL131: -30 | AM131: -30 | AN131: -30
B132: Binomial Ammortisation | C132: A$m | W132: =IF($C$121=1,W131,0) -> 0 | X132: =IF($C$121=1,X131,0) -> 0 | Y132: =IF($C$121=1,Y131,0) -> 0 | Z132: =IF($C$121=1,Z131,0) -> 0 | AA132: =IF($C$121=1,AA131,0) -> 0 | AB132: =IF($C$121=1,AB131,0) -> 0 | AC132: =IF($C$121=1,AC131,0) -> 0 | AD132: =IF($C$121=1,AD131,0) -> 0 | ... AN132: =IF($C$121=1,AN131,0) -> 0
B134: Net Debt | C134: A$m | R134: =R577 -> 860 | S134: =S577 -> 753 | T134: =T577 -> 609 | U134: =U577 -> 631 | V134: =V577 -> 533 | W134: =W577 -> 461.44863 | X134: =X577 -> 744.66057 | Y134: =Y577 -> 671.00247 | ... AN134: =AN577 -> -610.48124
B135: Net Debt to EBITDA | C135: x | R135: =R579 -> 2.7 | S135: =S579 -> 2.2 | T135: =T579 -> 1.6 | U135: =U579 -> 1.5 | V135: =V579 -> 1.2 | W135: =W579 -> 1.0026835 | X135: =X579 -> 1.5965449 | Y135: =Y579 -> 1.418318 | ... AN135: =AN579 -> -1.140778
B137: INTERNATIONAL REVENUE
B138: International Wagering Revenue | C138: A$m | O138: 120.9 | P138: 128.4 | Q138: 109.3 | R138: =212.3-Q138 -> 103 | S138: 108 | T138: =232.2-S138 -> 124.2 | U138: 115.1 | V138: =223.7-U138 -> 108.6 | W138: 107 | X138: 109 | Y138: =W138*(1+Y139) -> 110.21 | Z138: =X138*(1+Z139) -> 112.27 | AA138: =Y138*(1+AA139) -> 113.5163 | AB138: =Z138*(1+AB139) -> 115.6381 | AC138: =AA138*(1+AC139) -> 116.92179 | AD138: =AB138*(1+AD139) -> 119.10724 | AE138: =AC138*(1+AE139) -> 120.42944 | AF138: =AD138*(1+AF139) -> 122.68046 | ... AN138: =AL138*(1+AN139) -> 138.07794
B139: growth | C139: % | Q139: =Q138/O138-1 -> -0.095947064 | R139: =R138/P138-1 -> -0.19781931 | S139: =S138/Q138-1 -> -0.01189387 | T139: =T138/R138-1 -> 0.20582524 | U139: =U138/S138-1 -> 0.065740741 | V139: =V138/T138-1 -> -0.12560386 | W139: =W138/U138-1 -> -0.070373588 | X139: =X138/V138-1 -> 0.0036832413 | Y139: 0.03 | Z139: 0.03 | AA139: 0.03 | AB139: 0.03 | AC139: 0.03 | AD139: 0.03 | AE139: 0.03 | AF139: 0.03 | AG139: 0.03 | AH139: 0.03 | AI139: 0.03 | AJ139: 0.03 | AK139: 0.03 | AL139: 0.03 | AM139: 0.03 | AN139: 0.03
B141: Total Wagering Revenue | C141: A$m | O141: =O102+O117+O138 -> 1051.3 | P141: =P102+P117+P138 -> 959.1 | Q141: =Q102+Q117+Q138 -> 1003.3 | R141: =R102+R117+R138 -> 952.8 | S141: =S102+S117+S138 -> 1144.7 | T141: =T102+T117+T138 -> 1122.9 | U141: =U102+U117+U138 -> 1163.1 | V141: =V102+V117+V138 -> 1114.6 | ... AN141: =AN102+AN117+AN138 -> 1260.089
B143: MEDIA & INTERSEGMENT ELIMINATION
B145: Media Revenue
B146: International | C146: A$m | S146: 44 | T146: =91-S146 -> 47 | U146: 48 | V146: =101-U146 -> 53
B147: Domestic Digital Distribution (incl Tabcorp) | C147: A$m | S147: 40 | T147: =72-S147 -> 32 | U147: 40 | V147: =75-U147 -> 35
B148: Venue Subscriptions | C148: A$m | S148: 12 | T148: =16-S148 -> 4 | U148: 7 | V148: =14-U148 -> 7
B149: Advertising Revenues | C149: A$m | S149: 2 | T149: =4-S149 -> 2 | U149: 1 | V149: =2-U149 -> 1
B150: External | C150: A$m | S150: =SUM(S146:S149) -> 98 | T150: =SUM(T146:T149) -> 85 | U150: =SUM(U146:U149) -> 96 | V150: =SUM(V146:V149) -> 96 | W150: 98 | X150: 98 | Y150: =W150*(1+Y151) -> 100.94 | Z150: =X150*(1+Z151) -> 100.94 | AA150: =Y150*(1+AA151) -> 103.9682 | AB150: =Z150*(1+AB151) -> 103.9682 | AC150: =AA150*(1+AC151) -> 107.08725 | AD150: =AB150*(1+AD151) -> 107.08725 | AE150: =AC150*(1+AE151) -> 110.29986 | AF150: =AD150*(1+AF151) -> 110.29986 | ... AN150: =AL150*(1+AN151) -> 124.14347
B151: growth | C151: % | U151: =U150/S150-1 -> -0.020408163 | V151: =V150/T150-1 -> 0.12941176 | W151: =W150/U150-1 -> 0.020833333 | X151: =X150/V150-1 -> 0.020833333 | Y151: 0.03 | Z151: 0.03 | AA151: 0.03 | AB151: 0.03 | AC151: 0.03 | AD151: 0.03 | AE151: 0.03 | AF151: 0.03 | AG151: 0.03 | AH151: 0.03 | AI151: 0.03 | AJ151: 0.03 | AK151: 0.03 | AL151: 0.03 | AM151: 0.03 | AN151: 0.03
B153: International | C153: A$m | S153: 18 | T153: =37-S153 -> 19 | U153: 20 | V153: =38-U153 -> 18
B154: Domestic Digital Distribution (incl Tabcorp) | C154: A$m | S154: 26 | T154: =37-S154 -> 11 | U154: 20 | V154: =37-U154 -> 17
...

Sheet FY
B2: TAH | C2: 2022 | D2: =C2+1 -> 2023 | E2: =D2+1 -> 2024 | F2: =E2+1 -> 2025 | G2: =F2+1 -> 2026 | H2: =G2+1 -> 2027 | I2: =H2+1 -> 2028 | J2: =I2+1 -> 2029 | K2: =J2+1 -> 2030 | ... O2: =N2+1 -> 2034
C3: A | D3: A | E3: E | F3: E | G3: E | H3: E | I3: E | J3: E | K3: E | L3: E | M3: E | N3: E | O3: E
C4: =C2&C3 -> 2022A | D4: =D2&D3 -> 2023A | E4: =E2&E3 -> 2024E | F4: =F2&F3 -> 2025E | G4: =G2&G3 -> 2026E | H4: =H2&H3 -> 2027E | I4: =I2&I3 -> 2028E | J4: =J2&J3 -> 2029E | ... O4: =O2&O3 -> 2034E
C5: 44742 | D5: =EOMONTH(C5,12) -> 45107 | E5: =EOMONTH(D5,12) -> 45473 | F5: =EOMONTH(E5,12) -> 45838 | G5: =EOMONTH(F5,12) -> 46203 | H5: =EOMONTH(G5,12) -> 46568 | I5: =EOMONTH(H5,12) -> 46934 | J5: =EOMONTH(I5,12) -> 47299 | K5: =EOMONTH(J5,12) -> 47664 | ... O5: =EOMONTH(N5,12) -> 49125
A7: X | B7: SEGMENTS - NORMALISED | C7: =C$4 -> 2022A | D7: =D$4 -> 2023A | E7: =E$4 -> 2024E | F7: =F$4 -> 2025E | G7: =G$4 -> 2026E | H7: =H$4 -> 2027E | I7: =I$4 -> 2028E | J7: =J$4 -> 2029E | ... O7: =O$4 -> 2034E | P7: CAGR 24-27
B8: Wagering & Media | C8: =SUMIFS(HY!$E268:$AL268,HY!$E$15:$AL$15,FY!C$2) -> 2181.9 | D8: =SUMIFS(HY!$E268:$AL268,HY!$E$15:$AL$15,FY!D$2) -> 2230.8 | E8: =SUMIFS(HY!$E268:$AL268,HY!$E$15:$AL$15,FY!E$2) -> 2162.8 | F8: =SUMIFS(HY!$E268:$AL268,HY!$E$15:$AL$15,FY!F$2) -> 2438.8 | G8: =SUMIFS(HY!$E268:$AL268,HY!$E$15:$AL$15,FY!G$2) -> 2454.7 | H8: =SUMIFS(HY!$E268:$AL268,HY!$E$15:$AL$15,FY!H$2) -> 2535.5783 | I8: =SUMIFS(HY!$E268:$AL268,HY!$E$15:$AL$15,FY!I$2) -> 2553.5792 | J8: =SUMIFS(HY!$E268:$AL268,HY!$E$15:$AL$15,FY!J$2) -> 2575.9298 | ... O8: =SUMIFS(HY!$E268:$AL268,HY!$E$15:$AL$15,FY!O$2) -> 2797.6215 | P8: =H8/E8-1 -> 0.17235913
B9: Gaming Services | C9: =SUMIFS(HY!$E269:$AL269,HY!$E$15:$AL$15,FY!C$2) -> 196.9 | D9: =SUMIFS(HY!$E269:$AL269,HY!$E$15:$AL$15,FY!D$2) -> 203.6 | E9: =SUMIFS(HY!$E269:$AL269,HY!$E$15:$AL$15,FY!E$2) -> 163.4 | F9: =SUMIFS(HY!$E269:$AL269,HY!$E$15:$AL$15,FY!F$2) -> 175.8 | G9: =SUMIFS(HY!$E269:$AL269,HY!$E$15:$AL$15,FY!G$2) -> 181.6 | H9: =SUMIFS(HY!$E269:$AL269,HY!$E$15:$AL$15,FY!H$2) -> 186.14 | I9: =SUMIFS(HY!$E269:$AL269,HY!$E$15:$AL$15,FY!I$2) -> 190.7935 | J9: =SUMIFS(HY!$E269:$AL269,HY!$E$15:$AL$15,FY!J$2) -> 196.5173 | ... O9: =SUMIFS(HY!$E269:$AL269,HY!$E$15:$AL$15,FY!O$2) -> 227.81742
B10: BetMakers | C10: =SUMIFS(HY!$E270:$AL270,HY!$E$15:$AL$15,FY!C$2) -> 0 | D10: =SUMIFS(HY!$E270:$AL270,HY!$E$15:$AL$15,FY!D$2) -> 0 | E10: =SUMIFS(HY!$E270:$AL270,HY!$E$15:$AL$15,FY!E$2) -> 0 | F10: =SUMIFS(HY!$E270:$AL270,HY!$E$15:$AL$15,FY!F$2) -> 0 | G10: =SUMIFS(HY!$E270:$AL270,HY!$E$15:$AL$15,FY!G$2) -> 0 | H10: =SUMIFS(HY!$E270:$AL270,HY!$E$15:$AL$15,FY!H$2) -> 25.25 | I10: =SUMIFS(HY!$E270:$AL270,HY!$E$15:$AL$15,FY!I$2) -> 102.485 | J10: =SUMIFS(HY!$E270:$AL270,HY!$E$15:$AL$15,FY!J$2) -> 105.55955 | ... O10: =SUMIFS(HY!$E270:$AL270,HY!$E$15:$AL$15,FY!O$2) -> 122.37245
B11: Normalised Revenue | C11: =SUMIFS(HY!$E271:$AL271,HY!$E$15:$AL$15,FY!C$2) -> 2377.3 | D11: =SUMIFS(HY!$E271:$AL271,HY!$E$15:$AL$15,FY!D$2) -> 2434.4 | E11: =SUMIFS(HY!$E271:$AL271,HY!$E$15:$AL$15,FY!E$2) -> 2338.9 | F11: =SUMIFS(HY!$E271:$AL271,HY!$E$15:$AL$15,FY!F$2) -> 2614.6 | G11: =SUMIFS(HY!$E271:$AL271,HY!$E$15:$AL$15,FY!G$2) -> 2636.3 | H11: =SUMIFS(HY!$E271:$AL271,HY!$E$15:$AL$15,FY!H$2) -> 2746.9683 | I11: =SUMIFS(HY!$E271:$AL271,HY!$E$15:$AL$15,FY!I$2) -> 2846.8577 | J11: =SUMIFS(HY!$E271:$AL271,HY!$E$15:$AL$15,FY!J$2) -> 2878.0067 | ... O11: =SUMIFS(HY!$E271:$AL271,HY!$E$15:$AL$15,FY!O$2) -> 3147.8114
B13: Wagering & Media | C13: =SUMIFS(HY!$E274:$AL274,HY!$E$15:$AL$15,FY!C$2) -> -1380.6 | D13: =SUMIFS(HY!$E274:$AL274,HY!$E$15:$AL$15,FY!D$2) -> -1455.8 | E13: =SUMIFS(HY!$E274:$AL274,HY!$E$15:$AL$15,FY!E$2) -> -1404.6 | F13: =SUMIFS(HY!$E274:$AL274,HY!$E$15:$AL$15,FY!F$2) -> -1522.9 | G13: =SUMIFS(HY!$E274:$AL274,HY!$E$15:$AL$15,FY!G$2) -> -1501.5 | H13: =SUMIFS(HY!$E274:$AL274,HY!$E$15:$AL$15,FY!H$2) -> -1534.0249 | I13: =SUMIFS(HY!$E274:$AL274,HY!$E$15:$AL$15,FY!I$2) -> -1544.9154 | J13: =SUMIFS(HY!$E274:$AL274,HY!$E$15:$AL$15,FY!J$2) -> -1558.4375 | ... O13: =SUMIFS(HY!$E274:$AL274,HY!$E$15:$AL$15,FY!O$2) -> -1692.561
B14: Gaming Services | C14: =SUMIFS(HY!$E275:$AL275,HY!$E$15:$AL$15,FY!C$2) -> -10.6 | D14: =SUMIFS(HY!$E275:$AL275,HY!$E$15:$AL$15,FY!D$2) -> -10.4 | E14: =SUMIFS(HY!$E275:$AL275,HY!$E$15:$AL$15,FY!E$2) -> -1.7 | F14: =SUMIFS(HY!$E275:$AL275,HY!$E$15:$AL$15,FY!F$2) -> -3 | G14: =SUMIFS(HY!$E275:$AL275,HY!$E$15:$AL$15,FY!G$2) -> -2.4 | H14: =SUMIFS(HY!$E275:$AL275,HY!$E$15:$AL$15,FY!H$2) -> -1.8634705 | I14: =SUMIFS(HY!$E275:$AL275,HY!$E$15:$AL$15,FY!I$2) -> -1.9100573 | J14: =SUMIFS(HY!$E275:$AL275,HY!$E$15:$AL$15,FY!J$2) -> -1.967359 | ... O14: =SUMIFS(HY!$E275:$AL275,HY!$E$15:$AL$15,FY!O$2) -> -2.2807083
B15: BetMakers | C15: =SUMIFS(HY!$E276:$AL276,HY!$E$15:$AL$15,FY!C$2) -> 0 | D15: =SUMIFS(HY!$E276:$AL276,HY!$E$15:$AL$15,FY!D$2) -> 0 | E15: =SUMIFS(HY!$E276:$AL276,HY!$E$15:$AL$15,FY!E$2) -> 0 | F15: =SUMIFS(HY!$E276:$AL276,HY!$E$15:$AL$15,FY!F$2) -> 0 | G15: =SUMIFS(HY!$E276:$AL276,HY!$E$15:$AL$15,FY!G$2) -> 0 | H15: =SUMIFS(HY!$E276:$AL276,HY!$E$15:$AL$15,FY!H$2) -> -8.35 | I15: =SUMIFS(HY!$E276:$AL276,HY!$E$15:$AL$15,FY!I$2) -> -27.402 | J15: =SUMIFS(HY!$E276:$AL276,HY!$E$15:$AL$15,FY!J$2) -> -20.43406 | ... O15: =SUMIFS(HY!$E276:$AL276,HY!$E$15:$AL$15,FY!O$2) -> -23.688676
B16: Taxes & Commissions | C16: =SUMIFS(HY!$E277:$AL277,HY!$E$15:$AL$15,FY!C$2) -> -1391.2 | D16: =SUMIFS(HY!$E277:$AL277,HY!$E$15:$AL$15,FY!D$2) -> -1466.2 | E16: =SUMIFS(HY!$E277:$AL277,HY!$E$15:$AL$15,FY!E$2) -> -1406.3 | F16: =SUMIFS(HY!$E277:$AL277,HY!$E$15:$AL$15,FY!F$2) -> -1525.9 | G16: =SUMIFS(HY!$E277:$AL277,HY!$E$15:$AL$15,FY!G$2) -> -1503.9 | H16: =SUMIFS(HY!$E277:$AL277,HY!$E$15:$AL$15,FY!H$2) -> -1544.2384 | I16: =SUMIFS(HY!$E277:$AL277,HY!$E$15:$AL$15,FY!I$2) -> -1574.2275 | J16: =SUMIFS(HY!$E277:$AL277,HY!$E$15:$AL$15,FY!J$2) -> -1580.839 | ... O16: =SUMIFS(HY!$E277:$AL277,HY!$E$15:$AL$15,FY!O$2) -> -1718.5304
B18: Wagering & Media | C18: =SUMIFS(HY!$E279:$AL279,HY!$E$15:$AL$15,FY!C$2) -> 801.3 | D18: =SUMIFS(HY!$E279:$AL279,HY!$E$15:$AL$15,FY!D$2) -> 775 | E18: =SUMIFS(HY!$E279:$AL279,HY!$E$15:$AL$15,FY!E$2) -> 758.2 | F18: =SUMIFS(HY!$E279:$AL279,HY!$E$15:$AL$15,FY!F$2) -> 915.9 | G18: =SUMIFS(HY!$E279:$AL279,HY!$E$15:$AL$15,FY!G$2) -> 953.2 | H18: =SUMIFS(HY!$E279:$AL279,HY!$E$15:$AL$15,FY!H$2) -> 1001.5534 | I18: =SUMIFS(HY!$E279:$AL279,HY!$E$15:$AL$15,FY!I$2) -> 1008.6638 | J18: =SUMIFS(HY!$E279:$AL279,HY!$E$15:$AL$15,FY!J$2) -> 1017.4923 | ... O18: =SUMIFS(HY!$E279:$AL279,HY!$E$15:$AL$15,FY!O$2) -> 1105.0605
B19: Gaming Services | C19: =SUMIFS(HY!$E280:$AL280,HY!$E$15:$AL$15,FY!C$2) -> 186.3 | D19: =SUMIFS(HY!$E280:$AL280,HY!$E$15:$AL$15,FY!D$2) -> 193.2 | E19: =SUMIFS(HY!$E280:$AL280,HY!$E$15:$AL$15,FY!E$2) -> 161.7 | F19: =SUMIFS(HY!$E280:$AL280,HY!$E$15:$AL$15,FY!F$2) -> 172.8 | G19: =SUMIFS(HY!$E280:$AL280,HY!$E$15:$AL$15,FY!G$2) -> 179.2 | H19: =SUMIFS(HY!$E280:$AL280,HY!$E$15:$AL$15,FY!H$2) -> 184.27653 | I19: =SUMIFS(HY!$E280:$AL280,HY!$E$15:$AL$15,FY!I$2) -> 188.88344 | J19: =SUMIFS(HY!$E280:$AL280,HY!$E$15:$AL$15,FY!J$2) -> 194.54995 | ... O19: =SUMIFS(HY!$E280:$AL280,HY!$E$15:$AL$15,FY!O$2) -> 225.53671
B20: BetMakers | C20: =SUMIFS(HY!$E281:$AL281,HY!$E$15:$AL$15,FY!C$2) -> 0 | D20: =SUMIFS(HY!$E281:$AL281,HY!$E$15:$AL$15,FY!D$2) -> 0 | E20: =SUMIFS(HY!$E281:$AL281,HY!$E$15:$AL$15,FY!E$2) -> 0 | F20: =SUMIFS(HY!$E281:$AL281,HY!$E$15:$AL$15,FY!F$2) -> 0 | G20: =SUMIFS(HY!$E281:$AL281,HY!$E$15:$AL$15,FY!G$2) -> 0 | H20: =SUMIFS(HY!$E281:$AL281,HY!$E$15:$AL$15,FY!H$2) -> 16.9 | I20: =SUMIFS(HY!$E281:$AL281,HY!$E$15:$AL$15,FY!I$2) -> 75.083 | J20: =SUMIFS(HY!$E281:$AL281,HY!$E$15:$AL$15,FY!J$2) -> 85.12549 | ... O20: =SUMIFS(HY!$E281:$AL281,HY!$E$15:$AL$15,FY!O$2) -> 98.683774
B21: Variable Contribution | C21: =SUMIFS(HY!$E282:$AL282,HY!$E$15:$AL$15,FY!C$2) -> 987.2 | D21: =SUMIFS(HY!$E282:$AL282,HY!$E$15:$AL$15,FY!D$2) -> 968.4 | E21: =SUMIFS(HY!$E282:$AL282,HY!$E$15:$AL$15,FY!E$2) -> 931.7 | F21: =SUMIFS(HY!$E282:$AL282,HY!$E$15:$AL$15,FY!F$2) -> 1088.7 | G21: =SUMIFS(HY!$E282:$AL282,HY!$E$15:$AL$15,FY!G$2) -> 1132.4 | H21: =SUMIFS(HY!$E282:$AL282,HY!$E$15:$AL$15,FY!H$2) -> 1202.73 | I21: =SUMIFS(HY!$E282:$AL282,HY!$E$15:$AL$15,FY!I$2) -> 1272.6302 | J21: =SUMIFS(HY!$E282:$AL282,HY!$E$15:$AL$15,FY!J$2) -> 1297.1677 | ... O21: =SUMIFS(HY!$E282:$AL282,HY!$E$15:$AL$15,FY!O$2) -> 1429.281
B23: Wagering & Media | C23: =SUMIFS(HY!$E285:$AL285,HY!$E$15:$AL$15,FY!C$2) -> -514.3 | D23: =SUMIFS(HY!$E285:$AL285,HY!$E$15:$AL$15,FY!D$2) -> -467 | E23: =SUMIFS(HY!$E285:$AL285,HY!$E$15:$AL$15,FY!E$2) -> -507 | F23: =SUMIFS(HY!$E285:$AL285,HY!$E$15:$AL$15,FY!F$2) -> -586.8 | G23: =SUMIFS(HY!$E285:$AL285,HY!$E$15:$AL$15,FY!G$2) -> -591.4 | H23: =SUMIFS(HY!$E285:$AL285,HY!$E$15:$AL$15,FY!H$2) -> -611.0645 | I23: =SUMIFS(HY!$E285:$AL285,HY!$E$15:$AL$15,FY!I$2) -> -629.39643 | J23: =SUMIFS(HY!$E285:$AL285,HY!$E$15:$AL$15,FY!J$2) -> -648.27833 | ... O23: =SUMIFS(HY!$E285:$AL285,HY!$E$15:$AL$15,FY!O$2) -> -722.76883
B24: Gaming Services | C24: =SUMIFS(HY!$E286:$AL286,HY!$E$15:$AL$15,FY!C$2) -> -113.1 | D24: =SUMIFS(HY!$E286:$AL286,HY!$E$15:$AL$15,FY!D$2) -> -110.1 | E24: =SUMIFS(HY!$E286:$AL286,HY!$E$15:$AL$15,FY!E$2) -> -102.7 | F24: =SUMIFS(HY!$E286:$AL286,HY!$E$15:$AL$15,FY!F$2) -> -110.4 | G24: =SUMIFS(HY!$E286:$AL286,HY!$E$15:$AL$15,FY!G$2) -> -109.3 | H24: =SUMIFS(HY!$E286:$AL286,HY!$E$15:$AL$15,FY!H$2) -> -113.5454 | I24: =SUMIFS(HY!$E286:$AL286,HY!$E$15:$AL$15,FY!I$2) -> -116.38403 | J24: =SUMIFS(HY!$E286:$AL286,HY!$E$15:$AL$15,FY!J$2) -> -119.87556 | ... O24: =SUMIFS(HY!$E286:$AL286,HY!$E$15:$AL$15,FY!O$2) -> -138.96862
B25: BetMakers | C25: =SUMIFS(HY!$E287:$AL287,HY!$E$15:$AL$15,FY!C$2) -> 0 | D25: =SUMIFS(HY!$E287:$AL287,HY!$E$15:$AL$15,FY!D$2) -> 0 | E25: =SUMIFS(HY!$E287:$AL287,HY!$E$15:$AL$15,FY!E$2) -> 0 | F25: =SUMIFS(HY!$E287:$AL287,HY!$E$15:$AL$15,FY!F$2) -> 0 | G25: =SUMIFS(HY!$E287:$AL287,HY!$E$15:$AL$15,FY!G$2) -> 0 | H25: =SUMIFS(HY!$E287:$AL287,HY!$E$15:$AL$15,FY!H$2) -> -11.7 | I25: =SUMIFS(HY!$E287:$AL287,HY!$E$15:$AL$15,FY!I$2) -> -41.204 | J25: =SUMIFS(HY!$E287:$AL287,HY!$E$15:$AL$15,FY!J$2) -> -34.65012 | ... O25: =SUMIFS(HY!$E287:$AL287,HY!$E$15:$AL$15,FY!O$2) -> -40.168986
B26: Opex | C26: =SUMIFS(HY!$E288:$AL288,HY!$E$15:$AL$15,FY!C$2) -> -626.6 | D26: =SUMIFS(HY!$E288:$AL288,HY!$E$15:$AL$15,FY!D$2) -> -577.4 | E26: =SUMIFS(HY!$E288:$AL288,HY!$E$15:$AL$15,FY!E$2) -> -614 | F26: =SUMIFS(HY!$E288:$AL288,HY!$E$15:$AL$15,FY!F$2) -> -697.2 | G26: =SUMIFS(HY!$E288:$AL288,HY!$E$15:$AL$15,FY!G$2) -> -700.7 | H26: =SUMIFS(HY!$E288:$AL288,HY!$E$15:$AL$15,FY!H$2) -> -736.3099 | I26: =SUMIFS(HY!$E288:$AL288,HY!$E$15:$AL$15,FY!I$2) -> -786.98447 | J26: =SUMIFS(HY!$E288:$AL288,HY!$E$15:$AL$15,FY!J$2) -> -802.804 | ... O26: =SUMIFS(HY!$E288:$AL288,HY!$E$15:$AL$15,FY!O$2) -> -901.90644
H27: =H26/G26-1 -> 0.050820465
H28: =(H23+H24)/(G23+G24)-1 -> 0.034122877 | I28: =(I23+I24)/(H23+H24)-1 -> 0.029216507
B30: Wagering & Media | C30: =SUMIFS(HY!$E292:$AL292,HY!$E$15:$AL$15,FY!C$2) -> 287 | D30: =SUMIFS(HY!$E292:$AL292,HY!$E$15:$AL$15,FY!D$2) -> 308 | E30: =SUMIFS(HY!$E292:$AL292,HY!$E$15:$AL$15,FY!E$2) -> 251.2 | F30: =SUMIFS(HY!$E292:$AL292,HY!$E$15:$AL$15,FY!F$2) -> 329.1 | G30: =SUMIFS(HY!$E292:$AL292,HY!$E$15:$AL$15,FY!G$2) -> 361.8 | H30: =SUMIFS(HY!$E292:$AL292,HY!$E$15:$AL$15,FY!H$2) -> 390.48893 | I30: =SUMIFS(HY!$E292:$AL292,HY!$E$15:$AL$15,FY!I$2) -> 379.26736 | J30: =SUMIFS(HY!$E292:$AL292,HY!$E$15:$AL$15,FY!J$2) -> 369.21395 | ... O30: =SUMIFS(HY!$E292:$AL292,HY!$E$15:$AL$15,FY!O$2) -> 382.29167
B31: Gaming Services | C31: =SUMIFS(HY!$E293:$AL293,HY!$E$15:$AL$15,FY!C$2) -> 73.2 | D31: =SUMIFS(HY!$E293:$AL293,HY!$E$15:$AL$15,FY!D$2) -> 83.1 | E31: =SUMIFS(HY!$E293:$AL293,HY!$E$15:$AL$15,FY!E$2) -> 59 | F31: =SUMIFS(HY!$E293:$AL293,HY!$E$15:$AL$15,FY!F$2) -> 62.4 | G31: =SUMIFS(HY!$E293:$AL293,HY!$E$15:$AL$15,FY!G$2) -> 69.9 | H31: =SUMIFS(HY!$E293:$AL293,HY!$E$15:$AL$15,FY!H$2) -> 70.731129 | I31: =SUMIFS(HY!$E293:$AL293,HY!$E$15:$AL$15,FY!I$2) -> 72.499408 | J31: =SUMIFS(HY!$E293:$AL293,HY!$E$15:$AL$15,FY!J$2) -> 74.67439 | ... O31: =SUMIFS(HY!$E293:$AL293,HY!$E$15:$AL$15,FY!O$2) -> 86.568084
B32: BetMakers | C32: =SUMIFS(HY!$E294:$AL294,HY!$E$15:$AL$15,FY!C$2) -> 0 | D32: =SUMIFS(HY!$E294:$AL294,HY!$E$15:$AL$15,FY!D$2) -> 0 | E32: =SUMIFS(HY!$E294:$AL294,HY!$E$15:$AL$15,FY!E$2) -> 0 | F32: =SUMIFS(HY!$E294:$AL294,HY!$E$15:$AL$15,FY!F$2) -> 0 | G32: =SUMIFS(HY!$E294:$AL294,HY!$E$15:$AL$15,FY!G$2) -> 0 | H32: =SUMIFS(HY!$E294:$AL294,HY!$E$15:$AL$15,FY!H$2) -> 5.2 | I32: =SUMIFS(HY!$E294:$AL294,HY!$E$15:$AL$15,FY!I$2) -> 33.879 | J32: =SUMIFS(HY!$E294:$AL294,HY!$E$15:$AL$15,FY!J$2) -> 50.47537 | ... O32: =SUMIFS(HY!$E294:$AL294,HY!$E$15:$AL$15,FY!O$2) -> 58.514788
B33: Normalised EBITDA | C33: =SUMIFS(HY!$E295:$AL295,HY!$E$15:$AL$15,FY!C$2) -> 360.6 | D33: =SUMIFS(HY!$E295:$AL295,HY!$E$15:$AL$15,FY!D$2) -> 391 | E33: =SUMIFS(HY!$E295:$AL295,HY!$E$15:$AL$15,FY!E$2) -> 317.7 | F33: =SUMIFS(HY!$E295:$AL295,HY!$E$15:$AL$15,FY!F$2) -> 391.5 | G33: =SUMIFS(HY!$E295:$AL295,HY!$E$15:$AL$15,FY!G$2) -> 431.7 | H33: =SUMIFS(HY!$E295:$AL295,HY!$E$15:$AL$15,FY!H$2) -> 466.42006 | I33: =SUMIFS(HY!$E295:$AL295,HY!$E$15:$AL$15,FY!I$2) -> 485.64577 | J33: =SUMIFS(HY!$E295:$AL295,HY!$E$15:$AL$15,FY!J$2) -> 494.36371 | ... O33: =SUMIFS(HY!$E295:$AL295,HY!$E$15:$AL$15,FY!O$2) -> 527.37455
B35: Check | C35: =C33-SUM(C11,C16,C26) -> 1.1 | D35: =D33-SUM(D11,D16,D26) -> 0.2 | E35: =E33-SUM(E11,E16,E26) -> -0.9 | F35: =F33-SUM(F11,F16,F26) -> 0 | G35: =G33-SUM(G11,G16,G26) -> -5.1159077e-13 | H35: =H33-SUM(H11,H16,H26) -> 0 | I35: =I33-SUM(I11,I16,I26) -> 0 | J35: =J33-SUM(J11,J16,J26) -> 0 | ... O35: =O33-SUM(O11,O16,O26) -> 0
A38: X | B38: P&L - NORMALISED | C38: =C$4 -> 2022A | D38: =D$4 -> 2023A | E38: =E$4 -> 2024E | F38: =F$4 -> 2025E | G38: =G$4 -> 2026E | H38: =H$4 -> 2027E | I38: =I$4 -> 2028E | J38: =J$4 -> 2029E | ... O38: =O$4 -> 2034E
B39: Sales Revenue | C39: =C11 -> 2377.3 | D39: =D11 -> 2434.4 | E39: =E11 -> 2338.9 | F39: =F11 -> 2614.6 | G39: =G11 -> 2636.3 | H39: =H11 -> 2746.9683 | I39: =I11 -> 2846.8577 | J39: =J11 -> 2878.0067 | ... O39: =O11 -> 3147.8114
B40: Other Income | C40: 0 | D40: 0 | E40: 0 | F40: 0 | G40: 0 | H40: 0 | I40: 0 | J40: 0 | K40: 0 | L40: 0 | M40: 0 | N40: 0 | O40: 0
B41: ---------- | C41: ---------- | D41: ---------- | E41: ---------- | F41: ---------- | G41: ---------- | H41: ---------- | I41: ---------- | J41: ---------- | K41: ---------- | L41: ---------- | M41: ---------- | N41: ---------- | O41: ----------
B42: Total revenue | C42: =C40+C39 -> 2377.3 | D42: =D40+D39 -> 2434.4 | E42: =E40+E39 -> 2338.9 | F42: =F40+F39 -> 2614.6 | G42: =G40+G39 -> 2636.3 | H42: =H40+H39 -> 2746.9683 | I42: =I40+I39 -> 2846.8577 | J42: =J40+J39 -> 2878.0067 | ... O42: =O40+O39 -> 3147.8114
B43: COGS | C43: =C46-C44-C42 -> -1390.1 | D43: =D46-D44-D42 -> -1466 | E43: =E46-E44-E42 -> -1407.2 | F43: =F46-F44-F42 -> -1525.9 | G43: =G46-G44-G42 -> -1503.9 | H43: =H46-H44-H42 -> -1544.2384 | I43: =I46-I44-I42 -> -1574.2275 | J43: =J46-J44-J42 -> -1580.839 | ... O43: =O46-O44-O42 -> -1718.5304
B44: OPEX | C44: =SUMIFS(HY!$E288:$AL288,HY!$E$15:$AL$15,FY!C$2) -> -626.6 | D44: =SUMIFS(HY!$E288:$AL288,HY!$E$15:$AL$15,FY!D$2) -> -577.4 | E44: =SUMIFS(HY!$E288:$AL288,HY!$E$15:$AL$15,FY!E$2) -> -614 | F44: =SUMIFS(HY!$E288:$AL288,HY!$E$15:$AL$15,FY!F$2) -> -697.2 | G44: =SUMIFS(HY!$E288:$AL288,HY!$E$15:$AL$15,FY!G$2) -> -700.7 | H44: =SUMIFS(HY!$E288:$AL288,HY!$E$15:$AL$15,FY!H$2) -> -736.3099 | I44: =SUMIFS(HY!$E288:$AL288,HY!$E$15:$AL$15,FY!I$2) -> -786.98447 | J44: =SUMIFS(HY!$E288:$AL288,HY!$E$15:$AL$15,FY!J$2) -> -802.804 | ... O44: =SUMIFS(HY!$E288:$AL288,HY!$E$15:$AL$15,FY!O$2) -> -901.90644
B45: ---------- | C45: ---------- | D45: ---------- | E45: ---------- | F45: ---------- | G45: ---------- | H45: ---------- | I45: ---------- | J45: ---------- | K45: ---------- | L45: ---------- | M45: ---------- | N45: ---------- | O45: ----------
B46: EBITDA | C46: =C33 -> 360.6 | D46: =D33 -> 391 | E46: =E33 -> 317.7 | F46: =F33 -> 391.5 | G46: =G33 -> 431.7 | H46: =H33 -> 466.42006 | I46: =I33 -> 485.64577 | J46: =J33 -> 494.36371 | ... O46: =O33 -> 527.37455
B47: D&A | C47: =SUMIFS(HY!$E301:$AL301,HY!$E$15:$AL$15,FY!C$2) -> -286.4 | D47: =SUMIFS(HY!$E301:$AL301,HY!$E$15:$AL$15,FY!D$2) -> -240.5 | E47: =SUMIFS(HY!$E301:$AL301,HY!$E$15:$AL$15,FY!E$2) -> -220.3 | F47: =SUMIFS(HY!$E301:$AL301,HY!$E$15:$AL$15,FY!F$2) -> -202.8 | G47: =SUMIFS(HY!$E301:$AL301,HY!$E$15:$AL$15,FY!G$2) -> -213 | H47: =SUMIFS(HY!$E301:$AL301,HY!$E$15:$AL$15,FY!H$2) -> -228.4 | I47: =SUMIFS(HY!$E301:$AL301,HY!$E$15:$AL$15,FY!I$2) -> -223.4 | J47: =SUMIFS(HY!$E301:$AL301,HY!$E$15:$AL$15,FY!J$2) -> -225.19597 | ... O47: =SUMIFS(HY!$E301:$AL301,HY!$E$15:$AL$15,FY!O$2) -> -199.66011
B48: ---------- | C48: ---------- | D48: ---------- | E48: ---------- | F48: ---------- | G48: ---------- | H48: ---------- | I48: ---------- | J48: ---------- | K48: ---------- | L48: ---------- | M48: ---------- | N48: ---------- | O48: ----------
B49: EBIT | C49: =SUMIFS(HY!$E311:$AL311,HY!$E$15:$AL$15,FY!C$2) -> 74.2 | D49: =SUMIFS(HY!$E311:$AL311,HY!$E$15:$AL$15,FY!D$2) -> 150.5 | E49: =SUMIFS(HY!$E311:$AL311,HY!$E$15:$AL$15,FY!E$2) -> 97.4 | F49: =SUMIFS(HY!$E311:$AL311,HY!$E$15:$AL$15,FY!F$2) -> 188.7 | G49: =SUMIFS(HY!$E311:$AL311,HY!$E$15:$AL$15,FY!G$2) -> 218.7 | H49: =SUMIFS(HY!$E311:$AL311,HY!$E$15:$AL$15,FY!H$2) -> 238.02006 | I49: =SUMIFS(HY!$E311:$AL311,HY!$E$15:$AL$15,FY!I$2) -> 262.24577 | J49: =SUMIFS(HY!$E311:$AL311,HY!$E$15:$AL$15,FY!J$2) -> 269.16774 | ... O49: =SUMIFS(HY!$E311:$AL311,HY!$E$15:$AL$15,FY!O$2) -> 327.71444
B50: Net Finance Costs | C50: =SUMIFS(HY!$E318:$AL318,HY!$E$15:$AL$15,FY!C$2) -> 0 | D50: =SUMIFS(HY!$E318:$AL318,HY!$E$15:$AL$15,FY!D$2) -> -32.5 | E50: =SUMIFS(HY!$E318:$AL318,HY!$E$15:$AL$15,FY!E$2) -> -42.2 | F50: =SUMIFS(HY!$E318:$AL318,HY!$E$15:$AL$15,FY!F$2) -> -91.5 | G50: =SUMIFS(HY!$E318:$AL318,HY!$E$15:$AL$15,FY!G$2) -> -86.2 | H50: =SUMIFS(HY!$E318:$AL318,HY!$E$15:$AL$15,FY!H$2) -> -87.43953 | I50: =SUMIFS(HY!$E318:$AL318,HY!$E$15:$AL$15,FY!I$2) -> -94.008241 | J50: =SUMIFS(HY!$E318:$AL318,HY!$E$15:$AL$15,FY!J$2) -> -93.699704 | ... O50: =SUMIFS(HY!$E318:$AL318,HY!$E$15:$AL$15,FY!O$2) -> -71.383154
B51: Share of associates | C51: =SUMIFS(HY!$E$600:$AL$600,HY!$E$15:$AL$15,FY!C$2) -> 0 | D51: =SUMIFS(HY!$E$600:$AL$600,HY!$E$15:$AL$15,FY!D$2) -> -2.7 | E51: =SUMIFS(HY!$E$600:$AL$600,HY!$E$15:$AL$15,FY!E$2) -> -3.2 | F51: =SUMIFS(HY!$E$600:$AL$600,HY!$E$15:$AL$15,FY!F$2) -> 3.8 | G51: =SUMIFS(HY!$E$600:$AL$600,HY!$E$15:$AL$15,FY!G$2) -> -3 | H51: =SUMIFS(HY!$E$600:$AL$600,HY!$E$15:$AL$15,FY!H$2) -> 1 | I51: =SUMIFS(HY!$E$600:$AL$600,HY!$E$15:$AL$15,FY!I$2) -> 12 | J51: =SUMIFS(HY!$E$600:$AL$600,HY!$E$15:$AL$15,FY!J$2) -> 22 | ... O51: =SUMIFS(HY!$E$600:$AL$600,HY!$E$15:$AL$15,FY!O$2) -> 33.765264
B52: ---------- | C52: ---------- | D52: ---------- | E52: ---------- | F52: ---------- | G52: ---------- | H52: ---------- | I52: ---------- | J52: ---------- | K52: ---------- | L52: ---------- | M52: ---------- | N52: ---------- | O52: ----------
B53: NPBT | D53: =SUMIFS(HY!$E320:$AL320,HY!$E$15:$AL$15,FY!D$2) -> 115.3 | E53: =SUMIFS(HY!$E320:$AL320,HY!$E$15:$AL$15,FY!E$2) -> 52 | F53: =SUMIFS(HY!$E320:$AL320,HY!$E$15:$AL$15,FY!F$2) -> 101 | G53: =SUMIFS(HY!$E320:$AL320,HY!$E$15:$AL$15,FY!G$2) -> 129.5 | H53: =SUMIFS(HY!$E320:$AL320,HY!$E$15:$AL$15,FY!H$2) -> 151.58053 | I53: =SUMIFS(HY!$E320:$AL320,HY!$E$15:$AL$15,FY!I$2) -> 180.23753 | J53: =SUMIFS(HY!$E320:$AL320,HY!$E$15:$AL$15,FY!J$2) -> 197.46803 | K53: =SUMIFS(HY!$E320:$AL320,HY!$E$15:$AL$15,FY!K$2) -> 225.04759 | ... O53: =SUMIFS(HY!$E320:$AL320,HY!$E$15:$AL$15,FY!O$2) -> 290.09655
B54: Tax | D54: =SUMIFS(HY!$E322:$AL322,HY!$E$15:$AL$15,FY!D$2) -> -31 | E54: =SUMIFS(HY!$E322:$AL322,HY!$E$15:$AL$15,FY!E$2) -> -24 | F54: =SUMIFS(HY!$E322:$AL322,HY!$E$15:$AL$15,FY!F$2) -> -51.5 | G54: =SUMIFS(HY!$E322:$AL322,HY!$E$15:$AL$15,FY!G$2) -> -58.4 | H54: =SUMIFS(HY!$E322:$AL322,HY!$E$15:$AL$15,FY!H$2) -> -61.87027 | I54: =SUMIFS(HY!$E322:$AL322,HY!$E$15:$AL$15,FY!I$2) -> -70.149896 | J54: =SUMIFS(HY!$E322:$AL322,HY!$E$15:$AL$15,FY!J$2) -> -76.810403 | K54: =SUMIFS(HY!$E322:$AL322,HY!$E$15:$AL$15,FY!K$2) -> -87.556331 | ... O54: =SUMIFS(HY!$E322:$AL322,HY!$E$15:$AL$15,FY!O$2) -> -87.028965
B55: NPAT | D55: =SUMIFS(HY!$E328:$AL328,HY!$E$15:$AL$15,FY!D$2) -> 84.3 | E55: =SUMIFS(HY!$E328:$AL328,HY!$E$15:$AL$15,FY!E$2) -> 28 | F55: =SUMIFS(HY!$E328:$AL328,HY!$E$15:$AL$15,FY!F$2) -> 49.5 | G55: =SUMIFS(HY!$E328:$AL328,HY!$E$15:$AL$15,FY!G$2) -> 71.1 | H55: =SUMIFS(HY!$E328:$AL328,HY!$E$15:$AL$15,FY!H$2) -> 89.710264 | I55: =SUMIFS(HY!$E328:$AL328,HY!$E$15:$AL$15,FY!I$2) -> 110.08763 | J55: =SUMIFS(HY!$E328:$AL328,HY!$E$15:$AL$15,FY!J$2) -> 120.65763 | K55: =SUMIFS(HY!$E328:$AL328,HY!$E$15:$AL$15,FY!K$2) -> 137.49126 | ... O55: =SUMIFS(HY!$E328:$AL328,HY!$E$15:$AL$15,FY!O$2) -> 203.06758
B56: Check | D56: =D55-SUM(D42,D43,D44,D47,D50,D51,D54) -> -1.1368684e-13 | E56: =E55-SUM(E42,E43,E44,E47,E50,E51,E54) -> -2.8421709e-14 | F56: =F55-SUM(F42,F43,F44,F47,F50,F51,F54) -> 0 | G56: =G55-SUM(G42,G43,G44,G47,G50,G51,G54) -> 0 | H56: =H55-SUM(H42,H43,H44,H47,H50,H51,H54) -> 0 | I56: =I55-SUM(I42,I43,I44,I47,I50,I51,I54) -> 0 | J56: =J55-SUM(J42,J43,J44,J47,J50,J51,J54) -> -1.1368684e-13 | K56: =K55-SUM(K42,K43,K44,K47,K50,K51,K54) -> 0 | ... O56: =O55-SUM(O42,O43,O44,O47,O50,O51,O54) -> 0
B58: REPORTED
A59: X | B59: P&L | C59: =C$4 -> 2022A | D59: =D$4 -> 2023A | E59: =E$4 -> 2024E | F59: =F$4 -> 2025E | G59: =G$4 -> 2026E | H59: =H$4 -> 2027E | I59: =I$4 -> 2028E | J59: =J$4 -> 2029E | ... O59: =O$4 -> 2034E | P59: CAGR 24-27
B60: Sales Revenue | C60: =SUMIFS(HY!$E$585:$AL$585,HY!$E$15:$AL$15,FY!C$2) -> 2373.3 | D60: =SUMIFS(HY!$E$585:$AL$585,HY!$E$15:$AL$15,FY!D$2) -> 2434.4 | E60: =SUMIFS(HY!$E$585:$AL$585,HY!$E$15:$AL$15,FY!E$2) -> 2338.9 | F60: =SUMIFS(HY!$E$585:$AL$585,HY!$E$15:$AL$15,FY!F$2) -> 2614.6 | G60: =SUMIFS(HY!$E$585:$AL$585,HY!$E$15:$AL$15,FY!G$2) -> 2636.3 | H60: =SUMIFS(HY!$E$585:$AL$585,HY!$E$15:$AL$15,FY!H$2) -> 2746.9683 | I60: =SUMIFS(HY!$E$585:$AL$585,HY!$E$15:$AL$15,FY!I$2) -> 2846.8577 | J60: =SUMIFS(HY!$E$585:$AL$585,HY!$E$15:$AL$15,FY!J$2) -> 2878.0067 | ... O60: =SUMIFS(HY!$E$585:$AL$585,HY!$E$15:$AL$15,FY!O$2) -> 3147.8114 | P60: =(H60/E60)^(1/3)-1 -> 0.055068521
B61: Other Income | C61: =SUMIFS(HY!$E$586:$AL$586,HY!$E$15:$AL$15,FY!C$2) -> 0 | D61: =SUMIFS(HY!$E$586:$AL$586,HY!$E$15:$AL$15,FY!D$2) -> 0 | E61: =SUMIFS(HY!$E$586:$AL$586,HY!$E$15:$AL$15,FY!E$2) -> 0 | F61: =SUMIFS(HY!$E$586:$AL$586,HY!$E$15:$AL$15,FY!F$2) -> 0 | G61: =SUMIFS(HY!$E$586:$AL$586,HY!$E$15:$AL$15,FY!G$2) -> 0 | H61: =SUMIFS(HY!$E$586:$AL$586,HY!$E$15:$AL$15,FY!H$2) -> 0 | I61: =SUMIFS(HY!$E$586:$AL$586,HY!$E$15:$AL$15,FY!I$2) -> 0 | J61: =SUMIFS(HY!$E$586:$AL$586,HY!$E$15:$AL$15,FY!J$2) -> 0 | ... O61: =SUMIFS(HY!$E$586:$AL$586,HY!$E$15:$AL$15,FY!O$2) -> 0
B62: ---------- | C62: ---------- | D62: ---------- | E62: ---------- | F62: ---------- | G62: ---------- | H62: ---------- | I62: ---------- | J62: ---------- | K62: ---------- | L62: ---------- | M62: ---------- | N62: ---------- | O62: ----------
B63: Total revenue | C63: =C61+C60 -> 2373.3 | D63: =D61+D60 -> 2434.4 | E63: =E61+E60 -> 2338.9 | F63: =F61+F60 -> 2614.6 | G63: =G61+G60 -> 2636.3 | H63: =H61+H60 -> 2746.9683 | I63: =I61+I60 -> 2846.8577 | J63: =J61+J60 -> 2878.0067 | ... O63: =O61+O60 -> 3147.8114 | P63: =(H63/E63)^(1/3)-1 -> 0.055068521
B64: COGS | C64: =SUMIFS(HY!$E$587:$AL$587,HY!$E$15:$AL$15,FY!C$2) -> -1392.1 | D64: =SUMIFS(HY!$E$587:$AL$587,HY!$E$15:$AL$15,FY!D$2) -> -1466.2 | E64: =SUMIFS(HY!$E$587:$AL$587,HY!$E$15:$AL$15,FY!E$2) -> -1406.3 | F64: =SUMIFS(HY!$E$587:$AL$587,HY!$E$15:$AL$15,FY!F$2) -> -1525.9 | G64: =SUMIFS(HY!$E$587:$AL$587,HY!$E$15:$AL$15,FY!G$2) -> -1503.9 | H64: =SUMIFS(HY!$E$587:$AL$587,HY!$E$15:$AL$15,FY!H$2) -> -1544.2384 | I64: =SUMIFS(HY!$E$587:$AL$587,HY!$E$15:$AL$15,FY!I$2) -> -1574.2275 | J64: =SUMIFS(HY!$E$587:$AL$587,HY!$E$15:$AL$15,FY!J$2) -> -1580.839 | ... O64: =SUMIFS(HY!$E$587:$AL$587,HY!$E$15:$AL$15,FY!O$2) -> -1718.5304
B65: OPEX | C65: =SUMIFS(HY!$E$590:$AL$590,HY!$E$15:$AL$15,FY!C$2) -> -599.6 | D65: =SUMIFS(HY!$E$590:$AL$590,HY!$E$15:$AL$15,FY!D$2) -> -577.4 | E65: =SUMIFS(HY!$E$590:$AL$590,HY!$E$15:$AL$15,FY!E$2) -> -614 | F65: =SUMIFS(HY!$E$590:$AL$590,HY!$E$15:$AL$15,FY!F$2) -> -697.2 | G65: =SUMIFS(HY!$E$590:$AL$590,HY!$E$15:$AL$15,FY!G$2) -> -700.7 | H65: =SUMIFS(HY!$E$590:$AL$590,HY!$E$15:$AL$15,FY!H$2) -> -736.3099 | I65: =SUMIFS(HY!$E$590:$AL$590,HY!$E$15:$AL$15,FY!I$2) -> -786.98447 | J65: =SUMIFS(HY!$E$590:$AL$590,HY!$E$15:$AL$15,FY!J$2) -> -802.804 | ... O65: =SUMIFS(HY!$E$590:$AL$590,HY!$E$15:$AL$15,FY!O$2) -> -901.90644
B66: ---------- | C66: ---------- | D66: ---------- | E66: ---------- | F66: ---------- | G66: ---------- | H66: ---------- | I66: ---------- | J66: ---------- | K66: ---------- | L66: ---------- | M66: ---------- | N66: ---------- | O66: ----------
B67: EBITDA | C67: =SUMIFS(HY!$E$592:$AL$592,HY!$E$15:$AL$15,FY!C$2) -> 381.6 | D67: =SUMIFS(HY!$E$592:$AL$592,HY!$E$15:$AL$15,FY!D$2) -> 391 | E67: =SUMIFS(HY!$E$592:$AL$592,HY!$E$15:$AL$15,FY!E$2) -> 317.7 | F67: =SUMIFS(HY!$E$592:$AL$592,HY!$E$15:$AL$15,FY!F$2) -> 391.5 | G67: =SUMIFS(HY!$E$592:$AL$592,HY!$E$15:$AL$15,FY!G$2) -> 431.7 | H67: =SUMIFS(HY!$E$592:$AL$592,HY!$E$15:$AL$15,FY!H$2) -> 466.42006 | I67: =SUMIFS(HY!$E$592:$AL$592,HY!$E$15:$AL$15,FY!I$2) -> 485.64577 | J67: =SUMIFS(HY!$E$592:$AL$592,HY!$E$15:$AL$15,FY!J$2) -> 494.36371 | ... O67: =SUMIFS(HY!$E$592:$AL$592,HY!$E$15:$AL$15,FY!O$2) -> 527.37455 | P67: =(H67/E67)^(1/3)-1 -> 0.13654509
B68: Depreciation | C68: =SUMIFS(HY!$E593:$AL593,HY!$E$15:$AL$15,FY!C$2) -> -84.5 | D68: =SUMIFS(HY!$E593:$AL593,HY!$E$15:$AL$15,FY!D$2) -> -82.7 | E68: =SUMIFS(HY!$E593:$AL593,HY!$E$15:$AL$15,FY!E$2) -> -71.1 | F68: =SUMIFS(HY!$E593:$AL593,HY!$E$15:$AL$15,FY!F$2) -> -57.5 | G68: =SUMIFS(HY!$E593:$AL593,HY!$E$15:$AL$15,FY!G$2) -> -58.4 | H68: =SUMIFS(HY!$E593:$AL593,HY!$E$15:$AL$15,FY!H$2) -> -71 | I68: =SUMIFS(HY!$E593:$AL593,HY!$E$15:$AL$15,FY!I$2) -> -60 | J68: =SUMIFS(HY!$E593:$AL593,HY!$E$15:$AL$15,FY!J$2) -> -59.932982 | ... O68: =SUMIFS(HY!$E593:$AL593,HY!$E$15:$AL$15,FY!O$2) -> -60.498796
B69: Amortisation | C69: =SUMIFS(HY!$E594:$AL594,HY!$E$15:$AL$15,FY!C$2) -> -201.9 | D69: =SUMIFS(HY!$E594:$AL594,HY!$E$15:$AL$15,FY!D$2) -> -157.8 | E69: =SUMIFS(HY!$E594:$AL594,HY!$E$15:$AL$15,FY!E$2) -> -149.2 | F69: =SUMIFS(HY!$E594:$AL594,HY!$E$15:$AL$15,FY!F$2) -> -145.3 | G69: =SUMIFS(HY!$E594:$AL594,HY!$E$15:$AL$15,FY!G$2) -> -154.6 | H69: =SUMIFS(HY!$E594:$AL594,HY!$E$15:$AL$15,FY!H$2) -> -157.4 | I69: =SUMIFS(HY!$E594:$AL594,HY!$E$15:$AL$15,FY!I$2) -> -163.4 | J69: =SUMIFS(HY!$E594:$AL594,HY!$E$15:$AL$15,FY!J$2) -> -165.26299 | ... O69: =SUMIFS(HY!$E594:$AL594,HY!$E$15:$AL$15,FY!O$2) -> -139.16131
B70: ---------- | C70: ---------- | D70: ---------- | E70: ---------- | F70: ---------- | G70: ---------- | H70: ---------- | I70: ---------- | J70: ---------- | K70: ---------- | L70: ---------- | M70: ---------- | N70: ---------- | O70: ----------
B71: EBIT | C71: =SUMIFS(HY!$E$596:$AL$596,HY!$E$15:$AL$15,FY!C$2) -> 95.2 | D71: =SUMIFS(HY!$E$596:$AL$596,HY!$E$15:$AL$15,FY!D$2) -> 150.5 | E71: =SUMIFS(HY!$E$596:$AL$596,HY!$E$15:$AL$15,FY!E$2) -> 97.4 | F71: =SUMIFS(HY!$E$596:$AL$596,HY!$E$15:$AL$15,FY!F$2) -> 188.7 | G71: =SUMIFS(HY!$E$596:$AL$596,HY!$E$15:$AL$15,FY!G$2) -> 218.7 | H71: =SUMIFS(HY!$E$596:$AL$596,HY!$E$15:$AL$15,FY!H$2) -> 238.02006 | I71: =SUMIFS(HY!$E$596:$AL$596,HY!$E$15:$AL$15,FY!I$2) -> 262.24577 | J71: =SUMIFS(HY!$E$596:$AL$596,HY!$E$15:$AL$15,FY!J$2) -> 269.16774 | ... O71: =SUMIFS(HY!$E$596:$AL$596,HY!$E$15:$AL$15,FY!O$2) -> 327.71444 | P71: =(H71/E71)^(1/3)-1 -> 0.34695019
B72: Interest Income | C72: =SUMIFS(HY!$E$597:$AL$597,HY!$E$15:$AL$15,FY!C$2) -> 0.4 | D72: =SUMIFS(HY!$E$597:$AL$597,HY!$E$15:$AL$15,FY!D$2) -> 4.6 | E72: =SUMIFS(HY!$E$597:$AL$597,HY!$E$15:$AL$15,FY!E$2) -> 17.3 | F72: =SUMIFS(HY!$E$597:$AL$597,HY!$E$15:$AL$15,FY!F$2) -> 9.5 | G72: =SUMIFS(HY!$E$597:$AL$597,HY!$E$15:$AL$15,FY!G$2) -> 6.9 | H72: =SUMIFS(HY!$E$597:$AL$597,HY!$E$15:$AL$15,FY!H$2) -> 9.2146042 | I72: =SUMIFS(HY!$E$597:$AL$597,HY!$E$15:$AL$15,FY!I$2) -> 7.6651237 | J72: =SUMIFS(HY!$E$597:$AL$597,HY!$E$15:$AL$15,FY!J$2) -> 9.7832958 | ... O72: =SUMIFS(HY!$E$597:$AL$597,HY!$E$15:$AL$15,FY!O$2) -> 30.085846
B73: Interest Expense | C73: =SUMIFS(HY!$E$598:$AL$598,HY!$E$15:$AL$15,FY!C$2) -> -116.3 | D73: =SUMIFS(HY!$E$598:$AL$598,HY!$E$15:$AL$15,FY!D$2) -> -28.4 | E73: =SUMIFS(HY!$E$598:$AL$598,HY!$E$15:$AL$15,FY!E$2) -> -40.5 | F73: =SUMIFS(HY!$E$598:$AL$598,HY!$E$15:$AL$15,FY!F$2) -> -68.8 | G73: =SUMIFS(HY!$E$598:$AL$598,HY!$E$15:$AL$15,FY!G$2) -> -59.3 | H73: =SUMIFS(HY!$E$598:$AL$598,HY!$E$15:$AL$15,FY!H$2) -> -64.654134 | I73: =SUMIFS(HY!$E$598:$AL$598,HY!$E$15:$AL$15,FY!I$2) -> -69.673364 | J73: =SUMIFS(HY!$E$598:$AL$598,HY!$E$15:$AL$15,FY!J$2) -> -69.483 | ... O73: =SUMIFS(HY!$E$598:$AL$598,HY!$E$15:$AL$15,FY!O$2) -> -67.469
B74: Share of associates | C74: =SUMIFS(HY!$E$600:$AL$600,HY!$E$15:$AL$15,FY!C$2) -> 0 | D74: =SUMIFS(HY!$E$600:$AL$600,HY!$E$15:$AL$15,FY!D$2) -> -2.7 | E74: =SUMIFS(HY!$E$600:$AL$600,HY!$E$15:$AL$15,FY!E$2) -> -3.2 | F74: =SUMIFS(HY!$E$600:$AL$600,HY!$E$15:$AL$15,FY!F$2) -> 3.8 | G74: =SUMIFS(HY!$E$600:$AL$600,HY!$E$15:$AL$15,FY!G$2) -> -3 | H74: =SUMIFS(HY!$E$600:$AL$600,HY!$E$15:$AL$15,FY!H$2) -> 1 | I74: =SUMIFS(HY!$E$600:$AL$600,HY!$E$15:$AL$15,FY!I$2) -> 12 | J74: =SUMIFS(HY!$E$600:$AL$600,HY!$E$15:$AL$15,FY!J$2) -> 22 | ... O74: =SUMIFS(HY!$E$600:$AL$600,HY!$E$15:$AL$15,FY!O$2) -> 33.765264
B75: Other | C75: =SUMIFS(HY!$E$599:$AL$599,HY!$E$15:$AL$15,FY!C$2) -> -9.5 | D75: =SUMIFS(HY!$E$599:$AL$599,HY!$E$15:$AL$15,FY!D$2) -> -8.7 | E75: =SUMIFS(HY!$E$599:$AL$599,HY!$E$15:$AL$15,FY!E$2) -> -19 | F75: =SUMIFS(HY!$E$599:$AL$599,HY!$E$15:$AL$15,FY!F$2) -> -32.2 | G75: =SUMIFS(HY!$E$599:$AL$599,HY!$E$15:$AL$15,FY!G$2) -> -33.8 | H75: =SUMIFS(HY!$E$599:$AL$599,HY!$E$15:$AL$15,FY!H$2) -> -32 | I75: =SUMIFS(HY!$E$599:$AL$599,HY!$E$15:$AL$15,FY!I$2) -> -32 | J75: =SUMIFS(HY!$E$599:$AL$599,HY!$E$15:$AL$15,FY!J$2) -> -34 | ... O75: =SUMIFS(HY!$E$599:$AL$599,HY!$E$15:$AL$15,FY!O$2) -> -34
B76: ---------- | C76: ---------- | D76: ---------- | E76: ---------- | F76: ---------- | G76: ---------- | H76: ---------- | I76: ---------- | J76: ---------- | K76: ---------- | L76: ---------- | M76: ---------- | N76: ---------- | O76: ----------
B77: NPBT | C77: =SUMIFS(HY!$E$602:$AL$602,HY!$E$15:$AL$15,FY!C$2) -> -30.2 | D77: =SUMIFS(HY!$E$602:$AL$602,HY!$E$15:$AL$15,FY!D$2) -> 115.3 | E77: =SUMIFS(HY!$E$602:$AL$602,HY!$E$15:$AL$15,FY!E$2) -> 52 | F77: =SUMIFS(HY!$E$602:$AL$602,HY!$E$15:$AL$15,FY!F$2) -> 101 | G77: =SUMIFS(HY!$E$602:$AL$602,HY!$E$15:$AL$15,FY!G$2) -> 129.5 | H77: =SUMIFS(HY!$E$602:$AL$602,HY!$E$15:$AL$15,FY!H$2) -> 151.58053 | I77: =SUMIFS(HY!$E$602:$AL$602,HY!$E$15:$AL$15,FY!I$2) -> 180.23753 | J77: =SUMIFS(HY!$E$602:$AL$602,HY!$E$15:$AL$15,FY!J$2) -> 197.46803 | ... O77: =SUMIFS(HY!$E$602:$AL$602,HY!$E$15:$AL$15,FY!O$2) -> 290.09655 | P77: =(H77/E77)^(1/3)-1 -> 0.42849929
B78: Tax | C78: =SUMIFS(HY!$E$603:$AL$603,HY!$E$15:$AL$15,FY!C$2) -> 12.1 | D78: =SUMIFS(HY!$E$603:$AL$603,HY!$E$15:$AL$15,FY!D$2) -> -31 | E78: =SUMIFS(HY!$E$603:$AL$603,HY!$E$15:$AL$15,FY!E$2) -> -24 | F78: =SUMIFS(HY!$E$603:$AL$603,HY!$E$15:$AL$15,FY!F$2) -> -51.5 | G78: =SUMIFS(HY!$E$603:$AL$603,HY!$E$15:$AL$15,FY!G$2) -> -58.4 | H78: =SUMIFS(HY!$E$603:$AL$603,HY!$E$15:$AL$15,FY!H$2) -> -61.87027 | I78: =SUMIFS(HY!$E$603:$AL$603,HY!$E$15:$AL$15,FY!I$2) -> -70.149896 | J78: =SUMIFS(HY!$E$603:$AL$603,HY!$E$15:$AL$15,FY!J$2) -> -76.810403 | ... O78: =SUMIFS(HY!$E$603:$AL$603,HY!$E$15:$AL$15,FY!O$2) -> -87.028965
B79: Effective Tax Rate (%) | C79: =C78/-C77 -> 0.40066225 | D79: =D78/-D77 -> 0.26886383 | E79: =E78/-E77 -> 0.46153846 | F79: =F78/-F77 -> 0.50990099 | G79: =G78/-G77 -> 0.45096525 | H79: =H78/-H77 -> 0.40816765 | I79: =I78/-I77 -> 0.38920804 | J79: =J78/-J77 -> 0.38897639 | ... O79: =O78/-O77 -> 0.3
B80: Discontinued Ops | C80: =SUMIFS(HY!$E$606:$AL$606,HY!$E$15:$AL$15,FY!C$2) -> 380.5 | D80: =SUMIFS(HY!$E$606:$AL$606,HY!$E$15:$AL$15,FY!D$2) -> 0 | E80: =SUMIFS(HY!$E$606:$AL$606,HY!$E$15:$AL$15,FY!E$2) -> 0 | F80: =SUMIFS(HY!$E$606:$AL$606,HY!$E$15:$AL$15,FY!F$2) -> 0 | G80: =SUMIFS(HY!$E$606:$AL$606,HY!$E$15:$AL$15,FY!G$2) -> 0 | H80: =SUMIFS(HY!$E$606:$AL$606,HY!$E$15:$AL$15,FY!H$2) -> 0 | I80: =SUMIFS(HY!$E$606:$AL$606,HY!$E$15:$AL$15,FY!I$2) -> 0 | J80: =SUMIFS(HY!$E$606:$AL$606,HY!$E$15:$AL$15,FY!J$2) -> 0 | ... O80: =SUMIFS(HY!$E$606:$AL$606,HY!$E$15:$AL$15,FY!O$2) -> 0
B81: NPAT | C81: =SUMIFS(HY!$E$608:$AL$608,HY!$E$15:$AL$15,FY!C$2) -> 362.4 | D81: =SUMIFS(HY!$E$608:$AL$608,HY!$E$15:$AL$15,FY!D$2) -> 84.3 | E81: =SUMIFS(HY!$E$608:$AL$608,HY!$E$15:$AL$15,FY!E$2) -> 28 | F81: =SUMIFS(HY!$E$608:$AL$608,HY!$E$15:$AL$15,FY!F$2) -> 49.5 | G81: =SUMIFS(HY!$E$608:$AL$608,HY!$E$15:$AL$15,FY!G$2) -> 71.1 | H81: =SUMIFS(HY!$E$608:$AL$608,HY!$E$15:$AL$15,FY!H$2) -> 89.710264 | I81: =SUMIFS(HY!$E$608:$AL$608,HY!$E$15:$AL$15,FY!I$2) -> 110.08763 | J81: =SUMIFS(HY!$E$608:$AL$608,HY!$E$15:$AL$15,FY!J$2) -> 120.65763 | ... O81: =SUMIFS(HY!$E$608:$AL$608,HY!$E$15:$AL$15,FY!O$2) -> 203.06758 | P81: =(H81/E81)^(1/3)-1 -> 0.47421684
B82: Significant Items | C82: =SUMIFS(HY!$E$609:$AL$609,HY!$E$15:$AL$15,FY!C$2) -> 6413.5 | D82: =SUMIFS(HY!$E$609:$AL$609,HY!$E$15:$AL$15,FY!D$2) -> -17.8 | E82: =SUMIFS(HY!$E$609:$AL$609,HY!$E$15:$AL$15,FY!E$2) -> -1387.7 | F82: =SUMIFS(HY!$E$609:$AL$609,HY!$E$15:$AL$15,FY!F$2) -> -12.9 | G82: =SUMIFS(HY!$E$609:$AL$609,HY!$E$15:$AL$15,FY!G$2) -> -24.8 | H82: =SUMIFS(HY!$E$609:$AL$609,HY!$E$15:$AL$15,FY!H$2) -> -37 | I82: =SUMIFS(HY!$E$609:$AL$609,HY!$E$15:$AL$15,FY!I$2) -> -5 | J82: =SUMIFS(HY!$E$609:$AL$609,HY!$E$15:$AL$15,FY!J$2) -> 0 | ... O82: =SUMIFS(HY!$E$609:$AL$609,HY!$E$15:$AL$15,FY!O$2) -> 0
B83: Shareholder Profit | C83: =SUM(C81:C82) -> 6775.9 | D83: =SUM(D81:D82) -> 66.5 | E83: =SUM(E81:E82) -> -1359.7 | F83: =SUM(F81:F82) -> 36.6 | G83: =SUM(G81:G82) -> 46.3 | H83: =SUM(H81:H82) -> 52.710264 | I83: =SUM(I81:I82) -> 105.08763 | J83: =SUM(J81:J82) -> 120.65763 | ... O83: =SUM(O81:O82) -> 203.06758
B85: Check | C85: =C81-SUM(C63,C64,C65,C68,C69,C72,C73,C74,C75,C78,C80) -> 0 | D85: =D81-SUM(D63,D64,D65,D68,D69,D72,D73,D74,D75,D78,D80) -> 0.2 | E85: =E81-SUM(E63,E64,E65,E68,E69,E72,E73,E74,E75,E78,E80) -> -0.9 | F85: =F81-SUM(F63,F64,F65,F68,F69,F72,F73,F74,F75,F78,F80) -> 2.4158453e-13 | G85: =G81-SUM(G63,G64,G65,G68,G69,G72,G73,G74,G75,G78,G80) -> -5.1159077e-13 | H85: =H81-SUM(H63,H64,H65,H68,H69,H72,H73,H74,H75,H78,H80) -> 0 | I85: =I81-SUM(I63,I64,I65,I68,I69,I72,I73,I74,I75,I78,I80) -> 0 | J85: =J81-SUM(J63,J64,J65,J68,J69,J72,J73,J74,J75,J78,J80) -> -1.4210855e-13 | ... O85: =O81-SUM(O63,O64,O65,O68,O69,O72,O73,O74,O75,O78,O80) -> 0
A87: X | B87: CASH FLOW STATEMENT | C87: =C$4 -> 2022A | D87: =D$4 -> 2023A | E87: =E$4 -> 2024E | F87: =F$4 -> 2025E | G87: =G$4 -> 2026E | H87: =H$4 -> 2027E | I87: =I$4 -> 2028E | J87: =J$4 -> 2029E | ... O87: =O$4 -> 2034E | P87: CAGR 24-27
B88: EBITDA | D88: =SUMIFS(HY!$E624:$AL624,HY!$E$15:$AL$15,FY!D$2) -> 391 | E88: =SUMIFS(HY!$E624:$AL624,HY!$E$15:$AL$15,FY!E$2) -> 317.7 | F88: =SUMIFS(HY!$E624:$AL624,HY!$E$15:$AL$15,FY!F$2) -> 391.5 | G88: =SUMIFS(HY!$E624:$AL624,HY!$E$15:$AL$15,FY!G$2) -> 431.7 | H88: =SUMIFS(HY!$E624:$AL624,HY!$E$15:$AL$15,FY!H$2) -> 466.42006 | I88: =SUMIFS(HY!$E624:$AL624,HY!$E$15:$AL$15,FY!I$2) -> 485.64577 | J88: =SUMIFS(HY!$E624:$AL624,HY!$E$15:$AL$15,FY!J$2) -> 494.36371 | K88: =SUMIFS(HY!$E624:$AL624,HY!$E$15:$AL$15,FY!K$2) -> 501.26086 | ... O88: =SUMIFS(HY!$E624:$AL624,HY!$E$15:$AL$15,FY!O$2) -> 527.37455
B89: Interest received | D89: =SUMIFS(HY!$E625:$AL625,HY!$E$15:$AL$15,FY!D$2) -> 4.6 | E89: =SUMIFS(HY!$E625:$AL625,HY!$E$15:$AL$15,FY!E$2) -> 22.7 | F89: =SUMIFS(HY!$E625:$AL625,HY!$E$15:$AL$15,FY!F$2) -> 9.4 | G89: =SUMIFS(HY!$E625:$AL625,HY!$E$15:$AL$15,FY!G$2) -> 6.8 | H89: =SUMIFS(HY!$E625:$AL625,HY!$E$15:$AL$15,FY!H$2) -> 9.2146042 | I89: =SUMIFS(HY!$E625:$AL625,HY!$E$15:$AL$15,FY!I$2) -> 7.6651237 | J89: =SUMIFS(HY!$E625:$AL625,HY!$E$15:$AL$15,FY!J$2) -> 9.7832958 | K89: =SUMIFS(HY!$E625:$AL625,HY!$E$15:$AL$15,FY!K$2) -> 12.624441 | ... O89: =SUMIFS(HY!$E625:$AL625,HY!$E$15:$AL$15,FY!O$2) -> 30.085846
B90: Interest paid | D90: =SUMIFS(HY!$E626:$AL626,HY!$E$15:$AL$15,FY!D$2) -> -28.1 | E90: =SUMIFS(HY!$E626:$AL626,HY!$E$15:$AL$15,FY!E$2) -> -49 | F90: =SUMIFS(HY!$E626:$AL626,HY!$E$15:$AL$15,FY!F$2) -> -74 | G90: =SUMIFS(HY!$E626:$AL626,HY!$E$15:$AL$15,FY!G$2) -> -93.8 | H90: =SUMIFS(HY!$E626:$AL626,HY!$E$15:$AL$15,FY!H$2) -> -96.654134 | I90: =SUMIFS(HY!$E626:$AL626,HY!$E$15:$AL$15,FY!I$2) -> -101.67336 | J90: =SUMIFS(HY!$E626:$AL626,HY!$E$15:$AL$15,FY!J$2) -> -103.483 | K90: =SUMIFS(HY!$E626:$AL626,HY!$E$15:$AL$15,FY!K$2) -> -103.483 | ... O90: =SUMIFS(HY!$E626:$AL626,HY!$E$15:$AL$15,FY!O$2) -> -101.469
B91: Tax paid | D91: =SUMIFS(HY!$E627:$AL627,HY!$E$15:$AL$15,FY!D$2) -> -30.2 | E91: =SUMIFS(HY!$E627:$AL627,HY!$E$15:$AL$15,FY!E$2) -> 113.3 | F91: =SUMIFS(HY!$E627:$AL627,HY!$E$15:$AL$15,FY!F$2) -> 1.3 | G91: =SUMIFS(HY!$E627:$AL627,HY!$E$15:$AL$15,FY!G$2) -> 2.9 | H91: =SUMIFS(HY!$E627:$AL627,HY!$E$15:$AL$15,FY!H$2) -> -61.87027 | I91: =SUMIFS(HY!$E627:$AL627,HY!$E$15:$AL$15,FY!I$2) -> -70.149896 | J91: =SUMIFS(HY!$E627:$AL627,HY!$E$15:$AL$15,FY!J$2) -> -76.810403 | K91: =SUMIFS(HY!$E627:$AL627,HY!$E$15:$AL$15,FY!K$2) -> -87.556331 | ... O91: =SUMIFS(HY!$E627:$AL627,HY!$E$15:$AL$15,FY!O$2) -> -87.028965
B92: Other | D92: =SUMIFS(HY!$E628:$AL628,HY!$E$15:$AL$15,FY!D$2) -> -154.6 | E92: =SUMIFS(HY!$E628:$AL628,HY!$E$15:$AL$15,FY!E$2) -> -148.3 | F92: =SUMIFS(HY!$E628:$AL628,HY!$E$15:$AL$15,FY!F$2) -> -4.2 | G92: =SUMIFS(HY!$E628:$AL628,HY!$E$15:$AL$15,FY!G$2) -> -45.6 | H92: =SUMIFS(HY!$E628:$AL628,HY!$E$15:$AL$15,FY!H$2) -> 0 | I92: =SUMIFS(HY!$E628:$AL628,HY!$E$15:$AL$15,FY!I$2) -> 0 | J92: =SUMIFS(HY!$E628:$AL628,HY!$E$15:$AL$15,FY!J$2) -> 0 | K92: =SUMIFS(HY!$E628:$AL628,HY!$E$15:$AL$15,FY!K$2) -> 0 | ... O92: =SUMIFS(HY!$E628:$AL628,HY!$E$15:$AL$15,FY!O$2) -> 0
B93: ---------- | D93: ---------- | E93: ---------- | F93: ---------- | G93: ---------- | H93: ---------- | I93: ---------- | J93: ---------- | K93: ---------- | L93: ---------- | M93: ---------- | N93: ---------- | O93: ----------
B94: FFO | D94: =SUMIFS(HY!$E$630:$AL$630,HY!$E$15:$AL$15,FY!D$2) -> 182.7 | E94: =SUMIFS(HY!$E$630:$AL$630,HY!$E$15:$AL$15,FY!E$2) -> 256.4 | F94: =SUMIFS(HY!$E$630:$AL$630,HY!$E$15:$AL$15,FY!F$2) -> 324 | G94: =SUMIFS(HY!$E$630:$AL$630,HY!$E$15:$AL$15,FY!G$2) -> 302 | H94: =SUMIFS(HY!$E$630:$AL$630,HY!$E$15:$AL$15,FY!H$2) -> 317.11026 | I94: =SUMIFS(HY!$E$630:$AL$630,HY!$E$15:$AL$15,FY!I$2) -> 321.48763 | J94: =SUMIFS(HY!$E$630:$AL$630,HY!$E$15:$AL$15,FY!J$2) -> 323.8536 | K94: =SUMIFS(HY!$E$630:$AL$630,HY!$E$15:$AL$15,FY!K$2) -> 322.84597 | ... O94: =SUMIFS(HY!$E$630:$AL$630,HY!$E$15:$AL$15,FY!O$2) -> 368.96243 | P94: =(H94/E94)^(1/3)-1 -> 0.073406184
B95: Change in working capital | D95: =SUMIFS(HY!$E$631:$AL$631,HY!$E$15:$AL$15,FY!D$2) -> -63.4 | E95: =SUMIFS(HY!$E$631:$AL$631,HY!$E$15:$AL$15,FY!E$2) -> -11.2 | F95: =SUMIFS(HY!$E$631:$AL$631,HY!$E$15:$AL$15,FY!F$2) -> 82.5 | G95: =SUMIFS(HY!$E$631:$AL$631,HY!$E$15:$AL$15,FY!G$2) -> 7.3 | H95: =SUMIFS(HY!$E$631:$AL$631,HY!$E$15:$AL$15,FY!H$2) -> 16.592371 | I95: =SUMIFS(HY!$E$631:$AL$631,HY!$E$15:$AL$15,FY!I$2) -> 3.459682 | J95: =SUMIFS(HY!$E$631:$AL$631,HY!$E$15:$AL$15,FY!J$2) -> 4.9800226 | K95: =SUMIFS(HY!$E$631:$AL$631,HY!$E$15:$AL$15,FY!K$2) -> 11.350531 | ... O95: =SUMIFS(HY!$E$631:$AL$631,HY!$E$15:$AL$15,FY!O$2) -> 8.7213637
B96: Operating cash flow | D96: =SUMIFS(HY!$E$633:$AL$633,HY!$E$15:$AL$15,FY!D$2) -> 119.3 | E96: =SUMIFS(HY!$E$633:$AL$633,HY!$E$15:$AL$15,FY!E$2) -> 245.2 | F96: =SUMIFS(HY!$E$633:$AL$633,HY!$E$15:$AL$15,FY!F$2) -> 406.5 | G96: =SUMIFS(HY!$E$633:$AL$633,HY!$E$15:$AL$15,FY!G$2) -> 309.3 | H96: =SUMIFS(HY!$E$633:$AL$633,HY!$E$15:$AL$15,FY!H$2) -> 333.70263 | I96: =SUMIFS(HY!$E$633:$AL$633,HY!$E$15:$AL$15,FY!I$2) -> 324.94732 | J96: =SUMIFS(HY!$E$633:$AL$633,HY!$E$15:$AL$15,FY!J$2) -> 328.83363 | K96: =SUMIFS(HY!$E$633:$AL$633,HY!$E$15:$AL$15,FY!K$2) -> 334.1965 | ... O96: =SUMIFS(HY!$E$633:$AL$633,HY!$E$15:$AL$15,FY!O$2) -> 377.68379
B98: Capex | D98: =SUMIFS(HY!$E635:$AL635,HY!$E$15:$AL$15,FY!D$2)+SUMIFS(HY!$E636:$AL636,HY!$E$15:$AL$15,FY!D$2) -> -196.9 | E98: =SUMIFS(HY!$E635:$AL635,HY!$E$15:$AL$15,FY!E$2)+SUMIFS(HY!$E636:$AL636,HY!$E$15:$AL$15,FY!E$2) -> -760.4 | F98: =SUMIFS(HY!$E635:$AL635,HY!$E$15:$AL$15,FY!F$2)+SUMIFS(HY!$E636:$AL636,HY!$E$15:$AL$15,FY!F$2) -> -117.8 | G98: =SUMIFS(HY!$E635:$AL635,HY!$E$15:$AL$15,FY!G$2)+SUMIFS(HY!$E636:$AL636,HY!$E$15:$AL$15,FY!G$2) -> -150.7 | H98: =SUMIFS(HY!$E635:$AL635,HY!$E$15:$AL$15,FY!H$2)+SUMIFS(HY!$E636:$AL636,HY!$E$15:$AL$15,FY!H$2) -> -160 | I98: =SUMIFS(HY!$E635:$AL635,HY!$E$15:$AL$15,FY!I$2)+SUMIFS(HY!$E636:$AL636,HY!$E$15:$AL$15,FY!I$2) -> -150 | J98: =SUMIFS(HY!$E635:$AL635,HY!$E$15:$AL$15,FY!J$2)+SUMIFS(HY!$E636:$AL636,HY!$E$15:$AL$15,FY!J$2) -> -129.5103 | K98: =SUMIFS(HY!$E635:$AL635,HY!$E$15:$AL$15,FY!K$2)+SUMIFS(HY!$E636:$AL636,HY!$E$15:$AL$15,FY!K$2) -> -129.5475 | ... O98: =SUMIFS(HY!$E635:$AL635,HY!$E$15:$AL$15,FY!O$2)+SUMIFS(HY!$E636:$AL636,HY!$E$15:$AL$15,FY!O$2) -> -138.5037
B99: Sale of NCA's | D99: =SUMIFS(HY!$E637:$AL637,HY!$E$15:$AL$15,FY!D$2) -> 41.2 | E99: =SUMIFS(HY!$E637:$AL637,HY!$E$15:$AL$15,FY!E$2) -> 1.4 | F99: =SUMIFS(HY!$E637:$AL637,HY!$E$15:$AL$15,FY!F$2) -> 0.8 | G99: =SUMIFS(HY!$E637:$AL637,HY!$E$15:$AL$15,FY!G$2) -> 0 | H99: =SUMIFS(HY!$E637:$AL637,HY!$E$15:$AL$15,FY!H$2) -> 0 | I99: =SUMIFS(HY!$E637:$AL637,HY!$E$15:$AL$15,FY!I$2) -> 0 | J99: =SUMIFS(HY!$E637:$AL637,HY!$E$15:$AL$15,FY!J$2) -> 0 | K99: =SUMIFS(HY!$E637:$AL637,HY!$E$15:$AL$15,FY!K$2) -> 0 | ... O99: =SUMIFS(HY!$E637:$AL637,HY!$E$15:$AL$15,FY!O$2) -> 0
B100: Divestments | D100: =SUMIFS(HY!$E638:$AL638,HY!$E$15:$AL$15,FY!D$2) -> 59 | E100: =SUMIFS(HY!$E638:$AL638,HY!$E$15:$AL$15,FY!E$2) -> 21 | F100: =SUMIFS(HY!$E638:$AL638,HY!$E$15:$AL$15,FY!F$2) -> 0 | G100: =SUMIFS(HY!$E638:$AL638,HY!$E$15:$AL$15,FY!G$2) -> 0 | H100: =SUMIFS(HY!$E638:$AL638,HY!$E$15:$AL$15,FY!H$2) -> -283 | I100: =SUMIFS(HY!$E638:$AL638,HY!$E$15:$AL$15,FY!I$2) -> 0 | J100: =SUMIFS(HY!$E638:$AL638,HY!$E$15:$AL$15,FY!J$2) -> 0 | K100: =SUMIFS(HY!$E638:$AL638,HY!$E$15:$AL$15,FY!K$2) -> 0 | ... O100: =SUMIFS(HY!$E638:$AL638,HY!$E$15:$AL$15,FY!O$2) -> 0
B101: Acquisition of Associate | D101: =SUMIFS(HY!$E639:$AL639,HY!$E$15:$AL$15,FY!D$2) -> -33.3 | E101: =SUMIFS(HY!$E639:$AL639,HY!$E$15:$AL$15,FY!E$2) -> -2.8 | F101: =SUMIFS(HY!$E639:$AL639,HY!$E$15:$AL$15,FY!F$2) -> 0 | G101: =SUMIFS(HY!$E639:$AL639,HY!$E$15:$AL$15,FY!G$2) -> 0 | H101: =SUMIFS(HY!$E639:$AL639,HY!$E$15:$AL$15,FY!H$2) -> 0 | I101: =SUMIFS(HY!$E639:$AL639,HY!$E$15:$AL$15,FY!I$2) -> 0 | J101: =SUMIFS(HY!$E639:$AL639,HY!$E$15:$AL$15,FY!J$2) -> 0 | K101: =SUMIFS(HY!$E639:$AL639,HY!$E$15:$AL$15,FY!K$2) -> 0 | ... O101: =SUMIFS(HY!$E639:$AL639,HY!$E$15:$AL$15,FY!O$2) -> 0
B102: Other | D102: =SUMIFS(HY!$E640:$AL640,HY!$E$15:$AL$15,FY!D$2) -> 0 | E102: =SUMIFS(HY!$E640:$AL640,HY!$E$15:$AL$15,FY!E$2) -> 1.1 | F102: =SUMIFS(HY!$E640:$AL640,HY!$E$15:$AL$15,FY!F$2) -> 0 | G102: =SUMIFS(HY!$E640:$AL640,HY!$E$15:$AL$15,FY!G$2) -> 0 | H102: =SUMIFS(HY!$E640:$AL640,HY!$E$15:$AL$15,FY!H$2) -> -29 | I102: =SUMIFS(HY!$E640:$AL640,HY!$E$15:$AL$15,FY!I$2) -> -18 | J102: =SUMIFS(HY!$E640:$AL640,HY!$E$15:$AL$15,FY!J$2) -> -8 | K102: =SUMIFS(HY!$E640:$AL640,HY!$E$15:$AL$15,FY!K$2) -> 0 | ... O102: =SUMIFS(HY!$E640:$AL640,HY!$E$15:$AL$15,FY!O$2) -> 3.7652643
B103: ---------- | D103: ---------- | E103: ---------- | F103: ---------- | G103: ---------- | H103: ---------- | I103: ---------- | J103: ---------- | K103: ---------- | L103: ---------- | M103: ---------- | N103: ---------- | O103: ----------
B104: Investing cash flow | D104: =SUMIFS(HY!$E$642:$AL$642,HY!$E$15:$AL$15,FY!D$2) -> -130 | E104: =SUMIFS(HY!$E$642:$AL$642,HY!$E$15:$AL$15,FY!E$2) -> -739.7 | F104: =SUMIFS(HY!$E$642:$AL$642,HY!$E$15:$AL$15,FY!F$2) -> -117 | G104: =SUMIFS(HY!$E$642:$AL$642,HY!$E$15:$AL$15,FY!G$2) -> -150.7 | H104: =SUMIFS(HY!$E$642:$AL$642,HY!$E$15:$AL$15,FY!H$2) -> -472 | I104: =SUMIFS(HY!$E$642:$AL$642,HY!$E$15:$AL$15,FY!I$2) -> -168 | J104: =SUMIFS(HY!$E$642:$AL$642,HY!$E$15:$AL$15,FY!J$2) -> -137.5103 | K104: =SUMIFS(HY!$E$642:$AL$642,HY!$E$15:$AL$15,FY!K$2) -> -129.5475 | ... O104: =SUMIFS(HY!$E$642:$AL$642,HY!$E$15:$AL$15,FY!O$2) -> -134.73844 | P104: =(H104/E104)^(1/3)-1 -> -0.13908133
B106: Equity Raised | D106: =SUMIFS(HY!$E644:$AL644,HY!$E$15:$AL$15,FY!D$2) -> 0 | E106: =SUMIFS(HY!$E644:$AL644,HY!$E$15:$AL$15,FY!E$2) -> 0 | F106: =SUMIFS(HY!$E644:$AL644,HY!$E$15:$AL$15,FY!F$2) -> 0 | G106: =SUMIFS(HY!$E644:$AL644,HY!$E$15:$AL$15,FY!G$2) -> 0 | H106: =SUMIFS(HY!$E644:$AL644,HY!$E$15:$AL$15,FY!H$2) -> 0 | I106: =SUMIFS(HY!$E644:$AL644,HY!$E$15:$AL$15,FY!I$2) -> 0 | J106: =SUMIFS(HY!$E644:$AL644,HY!$E$15:$AL$15,FY!J$2) -> 0 | K106: =SUMIFS(HY!$E644:$AL644,HY!$E$15:$AL$15,FY!K$2) -> 0 | ... O106: =SUMIFS(HY!$E644:$AL644,HY!$E$15:$AL$15,FY!O$2) -> 0
B107: Buybacks | D107: =SUMIFS(HY!$E645:$AL645,HY!$E$15:$AL$15,FY!D$2) -> -2.5 | E107: =SUMIFS(HY!$E645:$AL645,HY!$E$15:$AL$15,FY!E$2) -> -2.2 | F107: =SUMIFS(HY!$E645:$AL645,HY!$E$15:$AL$15,FY!F$2) -> -5 | G107: =SUMIFS(HY!$E645:$AL645,HY!$E$15:$AL$15,FY!G$2) -> 0 | H107: =SUMIFS(HY!$E645:$AL645,HY!$E$15:$AL$15,FY!H$2) -> 0 | I107: =SUMIFS(HY!$E645:$AL645,HY!$E$15:$AL$15,FY!I$2) -> 0 | J107: =SUMIFS(HY!$E645:$AL645,HY!$E$15:$AL$15,FY!J$2) -> 0 | K107: =SUMIFS(HY!$E645:$AL645,HY!$E$15:$AL$15,FY!K$2) -> 0 | ... O107: =SUMIFS(HY!$E645:$AL645,HY!$E$15:$AL$15,FY!O$2) -> 0
B108: Dividends Paid | D108: =SUMIFS(HY!$E646:$AL646,HY!$E$15:$AL$15,FY!D$2) -> -122.9 | E108: =SUMIFS(HY!$E646:$AL646,HY!$E$15:$AL$15,FY!E$2) -> -43.8 | F108: =SUMIFS(HY!$E646:$AL646,HY!$E$15:$AL$15,FY!F$2) -> -28.3 | G108: =SUMIFS(HY!$E646:$AL646,HY!$E$15:$AL$15,FY!G$2) -> -50.8 | H108: =SUMIFS(HY!$E646:$AL646,HY!$E$15:$AL$15,FY!H$2) -> -73.3632 | I108: =SUMIFS(HY!$E646:$AL646,HY!$E$15:$AL$15,FY!I$2) -> -73.3632 | J108: =SUMIFS(HY!$E646:$AL646,HY!$E$15:$AL$15,FY!J$2) -> -85.474577 | K108: =SUMIFS(HY!$E646:$AL646,HY!$E$15:$AL$15,FY!K$2) -> -75.645628 | ... O108: =SUMIFS(HY!$E646:$AL646,HY!$E$15:$AL$15,FY!O$2) -> 0
B109: Minority Dividends Paid | D109: =SUMIFS(HY!$E647:$AL647,HY!$E$15:$AL$15,FY!D$2) -> 0 | E109: =SUMIFS(HY!$E647:$AL647,HY!$E$15:$AL$15,FY!E$2) -> 0 | F109: =SUMIFS(HY!$E647:$AL647,HY!$E$15:$AL$15,FY!F$2) -> 0 | G109: =SUMIFS(HY!$E647:$AL647,HY!$E$15:$AL$15,FY!G$2) -> 0 | H109: =SUMIFS(HY!$E647:$AL647,HY!$E$15:$AL$15,FY!H$2) -> 0 | I109: =SUMIFS(HY!$E647:$AL647,HY!$E$15:$AL$15,FY!I$2) -> 0 | J109: =SUMIFS(HY!$E647:$AL647,HY!$E$15:$AL$15,FY!J$2) -> 0 | K109: =SUMIFS(HY!$E647:$AL647,HY!$E$15:$AL$15,FY!K$2) -> 0 | ... O109: =SUMIFS(HY!$E647:$AL647,HY!$E$15:$AL$15,FY!O$2) -> 0
B110: Debt Drawn/(Repaid) | D110: =SUMIFS(HY!$E648:$AL648,HY!$E$15:$AL$15,FY!D$2) -> 424.9 | E110: =SUMIFS(HY!$E648:$AL648,HY!$E$15:$AL$15,FY!E$2) -> 0 | F110: =SUMIFS(HY!$E648:$AL648,HY!$E$15:$AL$15,FY!F$2) -> 0 | G110: =SUMIFS(HY!$E648:$AL648,HY!$E$15:$AL$15,FY!G$2) -> 300 | H110: =SUMIFS(HY!$E648:$AL648,HY!$E$15:$AL$15,FY!H$2) -> 175 | I110: =SUMIFS(HY!$E648:$AL648,HY!$E$15:$AL$15,FY!I$2) -> 0 | J110: =SUMIFS(HY!$E648:$AL648,HY!$E$15:$AL$15,FY!J$2) -> 0 | K110: =SUMIFS(HY!$E648:$AL648,HY!$E$15:$AL$15,FY!K$2) -> 0 | ... O110: =SUMIFS(HY!$E648:$AL648,HY!$E$15:$AL$15,FY!O$2) -> 0
B111: Payment of Lease Liabilities | D111: =SUMIFS(HY!$E649:$AL649,HY!$E$15:$AL$15,FY!D$2) -> -45 | E111: =SUMIFS(HY!$E649:$AL649,HY!$E$15:$AL$15,FY!E$2) -> -36.5 | F111: =SUMIFS(HY!$E649:$AL649,HY!$E$15:$AL$15,FY!F$2) -> -33.4 | G111: =SUMIFS(HY!$E649:$AL649,HY!$E$15:$AL$15,FY!G$2) -> -33.4 | H111: =SUMIFS(HY!$E649:$AL649,HY!$E$15:$AL$15,FY!H$2) -> 0 | I111: =SUMIFS(HY!$E649:$AL649,HY!$E$15:$AL$15,FY!I$2) -> 0 | J111: =SUMIFS(HY!$E649:$AL649,HY!$E$15:$AL$15,FY!J$2) -> 0 | K111: =SUMIFS(HY!$E649:$AL649,HY!$E$15:$AL$15,FY!K$2) -> 0 | ... O111: =SUMIFS(HY!$E649:$AL649,HY!$E$15:$AL$15,FY!O$2) -> 0
B112: Net cash flows from revolving bank facilities | D112: =SUMIFS(HY!$E650:$AL650,HY!$E$15:$AL$15,FY!D$2) -> -140 | E112: =SUMIFS(HY!$E650:$AL650,HY!$E$15:$AL$15,FY!E$2) -> -750 | F112: =SUMIFS(HY!$E650:$AL650,HY!$E$15:$AL$15,FY!F$2) -> -300 | G112: =SUMIFS(HY!$E650:$AL650,HY!$E$15:$AL$15,FY!G$2) -> -300 | H112: =SUMIFS(HY!$E650:$AL650,HY!$E$15:$AL$15,FY!H$2) -> 0 | I112: =SUMIFS(HY!$E650:$AL650,HY!$E$15:$AL$15,FY!I$2) -> 0 | J112: =SUMIFS(HY!$E650:$AL650,HY!$E$15:$AL$15,FY!J$2) -> 0 | K112: =SUMIFS(HY!$E650:$AL650,HY!$E$15:$AL$15,FY!K$2) -> 0 | ... O112: =SUMIFS(HY!$E650:$AL650,HY!$E$15:$AL$15,FY!O$2) -> 0
B113: Other | D113: =SUMIFS(HY!$E651:$AL651,HY!$E$15:$AL$15,FY!D$2) -> -12.5 | E113: =SUMIFS(HY!$E651:$AL651,HY!$E$15:$AL$15,FY!E$2) -> 1350 | F113: =SUMIFS(HY!$E651:$AL651,HY!$E$15:$AL$15,FY!F$2) -> 0 | G113: =SUMIFS(HY!$E651:$AL651,HY!$E$15:$AL$15,FY!G$2) -> -5.1 | H113: =SUMIFS(HY!$E651:$AL651,HY!$E$15:$AL$15,FY!H$2) -> 0 | I113: =SUMIFS(HY!$E651:$AL651,HY!$E$15:$AL$15,FY!I$2) -> 0 | J113: =SUMIFS(HY!$E651:$AL651,HY!$E$15:$AL$15,FY!J$2) -> 0 | K113: =SUMIFS(HY!$E651:$AL651,HY!$E$15:$AL$15,FY!K$2) -> 0 | ... O113: =SUMIFS(HY!$E651:$AL651,HY!$E$15:$AL$15,FY!O$2) -> 0
B114: ---------- | D114: ---------- | E114: ---------- | F114: ---------- | G114: ---------- | H114: ---------- | I114: ---------- | J114: ---------- | K114: ---------- | L114: ---------- | M114: ---------- | N114: ---------- | O114: ----------
...

Sheet II

Sheet FT Tables
C2: Tabcorp 1H26 Result - Headline | BT2: Tabcorp FY26 Result - Headline
D3: 1H22A | E3: 2H22A | F3: 1H23A | G3: 2H23A | H3: 1H24A | I3: 2H24E | J3: 1H25E | K3: 2H25E | L3: 1H26E | M3: 2H26E | N3: 1H27E | O3: 2H27E | Q3: ="1H25A" -> 1H25A | R3: ="1H26A" -> 1H26A | S3: % change | T3: E&Pe 1H26E | U3: % diff | V3: VA Cons. 1H26E | W3: % diff | Z3: 1H25 | AE3: 1H22 | AF3: 2H22 | AG3: 1H23 | AH3: 2H23 | AI3: 1H24 | AJ3: 2H24 | AK3: 1H25 | AL3: 2H25 | AM3: 1H26 | AN3: 2H26 | AO3: 1H27 | AP3: 2H27 | AR3: 1H22 | AS3: 2H22 | AT3: 1H23 | AU3: 2H23 | AV3: 1H24 | AW3: 2H24 | AX3: 1H25 | AY3: 2H25 | AZ3: 1H26 | BA3: 2H26 | BB3: 1H27 | BC3: 2H27 | BE3: 1H22 | BF3: 2H22 | BG3: 1H23 | BH3: 2H23 | BI3: 1H24 | BJ3: 2H24 | BK3: 1H25 | BL3: 2H25 | BM3: 1H26 | BN3: 2H26 | BO3: 1H27 | BP3: 2H27 | BU3: FY22A | BV3: FY23A | BW3: FY24A | BX3: FY25E | BY3: FY26E | BZ3: FY27E | CA3: FY28E | CB3: FY29E | CC3: FY30E | CE3: FY25A | CF3: ="FY26A" -> FY26A | CG3: % change | CH3: E&Pe FY26E | CI3: % diff | CJ3: VA Cons. FY26E | CK3: % diff | CN3: =DG3 -> FY26 | CS3: FY22 | CT3: FY23 | CU3: FY24 | CV3: FY25 | CW3: FY26 | CX3: FY27 | CY3: FY28 | CZ3: FY29 | DA3: FY30 | DC3: FY22 | DD3: FY23 | DE3: FY24 | DF3: FY25 | DG3: FY26 | DH3: FY27 | DI3: FY28 | DJ3: FY29 | DK3: FY30 | DM3: FY22 | DN3: FY23 | DO3: FY24 | DP3: FY25 | DQ3: FY26 | DR3: FY27 | DS3: FY28 | DT3: FY29 | DU3: FY30
C4: P&L | BT4: P&L | CW4: =CX6-20 -> 2691.2841 | DH4: =DH6/DG6-1 -> 0.028666971
CW5: =CW4/CW6-1 -> 0.020856548 | CX5: =CX6/CW6-1 -> 0.028442938 | CY5: =CY6/CX6-1 -> 0.038182567 | CZ5: =CZ6/CY6-1 -> 0.019225772
C6: Revenue | F6: =HY!O271 -> 1274.5 | G6: =HY!P271 -> 1159.9 | H6: =HY!Q271 -> 1209.6 | I6: =HY!R271 -> 1129.3 | J6: =HY!S271 -> 1331.3 | K6: =HY!T271 -> 1283.3 | L6: =HY!U271 -> 1344.9 | M6: =HY!V271 -> 1291.4 | ... O6: =HY!X271 -> 1345.9846 | Q6: =J6 -> 1331.3 | R6: 1344.9 | S6: =R6/Q6-1 -> 0.010215579 | T6: =L6 -> 1344.9 | U6: =$R6/T6-1 -> 0 | V6: =Z6 -> 1325.1042 | W6: =$R6/V6-1 -> 0.014939085 | Z6: =AZ6 -> 1325.1042 | AB6: TAH_AU | AC6: Total revenue | AD6: consensus.vaactuals | AE6: =_xll.VAData($AB6,AE$3,$AC6,$AD6) -> 1152.3 | AF6: =_xll.VAData($AB6,AF$3,$AC6,$AD6) -> 1225 | AG6: =_xll.VAData($AB6,AG$3,$AC6,$AD6) -> 1274.5 | AH6: =_xll.VAData($AB6,AH$3,$AC6,$AD6) -> 1159.9 | AI6: =_xll.VAData($AB6,AI$3,$AC6,$AD6) -> 1209.6 | AJ6: =_xll.VAData($AB6,AJ$3,$AC6,$AD6) -> 1129.3 | AK6: =_xll.VAData($AB6,AK$3,$AC6,$AD6) -> 1331.3 | AL6: =_xll.VAData($AB6,AL$3,$AC6,$AD6) -> 1283.3 | ... AP6: =_xll.VAData($AB6,AP$3,$AC6,$AD6) -> 1320.0772 | AR6: 1152.3 | AS6: 1225 | AT6: 1274.5 | AU6: 1159.9 | AV6: 1209.6 | AW6: 1129.3 | AX6: 1331.3 | AY6: 1283.3 | AZ6: 1325.1042 | BA6: 1299.1995 | BB6: 1403.9844 | BC6: 1330.4886 | BE6: =D6-AR6 -> -1152.3 | BF6: =E6-AS6 -> -1225 | BG6: =F6-AT6 -> 0 | BH6: =G6-AU6 -> 0 | BI6: =H6-AV6 -> 0 | BJ6: =I6-AW6 -> 0 | BK6: =J6-AX6 -> 0 | BL6: =K6-AY6 -> 0 | ... BP6: =O6-BC6 -> 15.495959 | BT6: Revenue | BV6: =FY!D63 -> 2434.4 | BW6: =FY!E63 -> 2338.9 | BX6: =FY!F63 -> 2614.6 | BY6: =FY!G63 -> 2636.3 | BZ6: =FY!H63 -> 2746.9683 | CA6: =FY!I63 -> 2846.8577 | CB6: =FY!J63 -> 2878.0067 | CC6: =FY!K63 -> 2944.2614 | CE6: =BX6 -> 2614.6 | CF6: 2636.3 | CG6: =CF6/CE6-1 -> 0.0082995487 | CH6: =BY6 -> 2636.3 | CI6: =$CF6/CH6-1 -> 0 | CJ6: =CN6 -> 2648.8625 | CK6: =$CF6/CJ6-1 -> -0.0047426056 | CN6: =DG6 -> 2648.8625 | CP6: TAH_AU | CQ6: Total revenue | CR6: consensus.vaactuals | CS6: =_xll.VAData($AB6,CS$3,$AC6,$AD6) -> 2377.3 | CT6: =_xll.VAData($AB6,CT$3,$AC6,$AD6) -> 2434.4 | CU6: =_xll.VAData($AB6,CU$3,$AC6,$AD6) -> 2338.9 | CV6: =_xll.VAData($AB6,CV$3,$AC6,$AD6) -> 2614.6 | CW6: =_xll.VAData($AB6,CW$3,$AC6,$AD6) -> 2636.3 | CX6: =_xll.VAData($AB6,CX$3,$AC6,$AD6) -> 2711.2841 | CY6: =_xll.VAData($AB6,CY$3,$AC6,$AD6) -> 2814.8079 | CZ6: =_xll.VAData($AB6,CZ$3,$AC6,$AD6) -> 2868.9248 | DA6: =_xll.VAData($AB6,DA$3,$AC6,$AD6) -> 2923.4937 | DC6: 2377.3 | DD6: 2434.4 | DE6: 2338.9 | DF6: 2614.6 | DG6: 2648.8625 | DH6: 2724.7974 | DI6: 2805.8885 | DJ6: 2866.3854 | DK6: 2926.7643 | DN6: =BV6-DD6 -> 0 | DO6: =BW6-DE6 -> 0 | DP6: =BX6-DF6 -> 0 | DQ6: =BY6-DG6 -> -12.56251 | DR6: =BZ6-DH6 -> 22.170942 | DS6: =CA6-DI6 -> 40.969186 | DT6: =CB6-DJ6 -> 11.621313 | DU6: =CC6-DK6 -> 17.497128
C7: EBITDA | F7: =HY!O295 -> 196.6 | G7: =HY!P295 -> 194.4 | H7: =HY!Q295 -> 169.8 | I7: =HY!R295 -> 147.9 | J7: =HY!S295 -> 190.2 | K7: =HY!T295 -> 201.3 | L7: =HY!U295 -> 217.4 | M7: =HY!V295 -> 214.3 | ... O7: =HY!X295 -> 220.50641 | Q7: =J7 -> 190.2 | R7: 217.4 | S7: =R7/Q7-1 -> 0.14300736 | T7: =L7 -> 217.4 | U7: =$R7/T7-1 -> 0 | V7: =Z7 -> 195.97401 | W7: =$R7/V7-1 -> 0.10933079 | Z7: =AZ7 -> 195.97401 | AB7: TAH_AU | AC7: EBITDA - Operating | AD7: consensus.vaactuals | AE7: =_xll.VAData($AB7,AE$3,$AC7,$AD7) -> 159 | AF7: =_xll.VAData($AB7,AF$3,$AC7,$AD7) -> 201.6 | AG7: =_xll.VAData($AB7,AG$3,$AC7,$AD7) -> 196.6 | AH7: =_xll.VAData($AB7,AH$3,$AC7,$AD7) -> 194.4 | AI7: =_xll.VAData($AB7,AI$3,$AC7,$AD7) -> 169.8 | AJ7: =_xll.VAData($AB7,AJ$3,$AC7,$AD7) -> 147.9 | AK7: =_xll.VAData($AB7,AK$3,$AC7,$AD7) -> 190.2 | AL7: =_xll.VAData($AB7,AL$3,$AC7,$AD7) -> 201.3 | ... AP7: =_xll.VAData($AB7,AP$3,$AC7,$AD7) -> 221.70116 | AR7: 159 | AS7: 201.6 | AT7: 196.6 | AU7: 194.4 | AV7: 169.8 | AW7: 147.9 | AX7: 190.2 | AY7: 201.3 | AZ7: 195.97401 | BA7: 205.36811 | BB7: 218.32381 | BC7: 211.06276 | BE7: =D7-AR7 -> -159 | BF7: =E7-AS7 -> -201.6 | BG7: =F7-AT7 -> 0 | BH7: =G7-AU7 -> 0 | BI7: =H7-AV7 -> 0 | BJ7: =I7-AW7 -> 0 | BK7: =J7-AX7 -> 0 | BL7: =K7-AY7 -> 0 | ... BP7: =O7-BC7 -> 9.4436556 | BT7: EBITDA | BV7: =FY!D67 -> 391 | BW7: =FY!E67 -> 317.7 | BX7: =FY!F67 -> 391.5 | BY7: =FY!G67 -> 431.7 | BZ7: =FY!H67 -> 466.42006 | CA7: =FY!I67 -> 485.64577 | CB7: =FY!J67 -> 494.36371 | CC7: =FY!K67 -> 501.26086 | CE7: =BX7 -> 391.5 | CF7: 431.7 | CG7: =CF7/CE7-1 -> 0.10268199 | CH7: =BY7 -> 431.7 | CI7: =$CF7/CH7-1 -> 0 | CJ7: =CN7 -> 423.04047 | CK7: =$CF7/CJ7-1 -> 0.020469743 | CN7: =DG7 -> 423.04047 | CP7: TAH_AU | CQ7: EBITDA - Operating | CR7: consensus.vaactuals | CS7: =_xll.VAData($AB7,CS$3,$AC7,$AD7) -> 381.6 | CT7: =_xll.VAData($AB7,CT$3,$AC7,$AD7) -> 391 | CU7: =_xll.VAData($AB7,CU$3,$AC7,$AD7) -> 317.7 | CV7: =_xll.VAData($AB7,CV$3,$AC7,$AD7) -> 391.5 | CW7: =_xll.VAData($AB7,CW$3,$AC7,$AD7) -> 431.7 | CX7: =_xll.VAData($AB7,CX$3,$AC7,$AD7) -> 466.54104 | CY7: =_xll.VAData($AB7,CY$3,$AC7,$AD7) -> 489.5737 | CZ7: =_xll.VAData($AB7,CZ$3,$AC7,$AD7) -> 505.18115 | DA7: =_xll.VAData($AB7,DA$3,$AC7,$AD7) -> 518.4063 | DC7: 381.6 | DD7: 391 | DE7: 317.7 | DF7: 391.5 | DG7: 423.04047 | DH7: 440.67815 | DI7: 458.80963 | DJ7: 470.63364 | DK7: 483.28422 | DN7: =BV7-DD7 -> 0 | DO7: =BW7-DE7 -> 0 | DP7: =BX7-DF7 -> 0 | DQ7: =BY7-DG7 -> 8.6595296 | DR7: =BZ7-DH7 -> 25.741919 | DS7: =CA7-DI7 -> 26.836143 | DT7: =CB7-DJ7 -> 23.730071 | DU7: =CC7-DK7 -> 17.976638
C8: EBIT | F8: =HY!O311 -> 73.2 | G8: =HY!P311 -> 77.3 | H8: =HY!Q311 -> 50 | I8: =HY!R311 -> 47.4 | J8: =HY!S311 -> 92.7 | K8: =HY!T311 -> 96 | L8: =HY!U311 -> 110.2 | M8: =HY!V311 -> 108.5 | ... O8: =HY!X311 -> 106.30641 | Q8: =J8 -> 92.7 | R8: 110.2 | S8: =R8/Q8-1 -> 0.18878101 | T8: =L8 -> 110.2 | U8: =$R8/T8-1 -> 0 | V8: =Z8 -> 86.31809 | W8: =$R8/V8-1 -> 0.27667329 | Z8: =AZ8 -> 86.31809 | AB8: TAH_AU | AC8: Operating income/(loss) - Operating | AD8: consensus.vaactuals | AE8: =_xll.VAData($AB8,AE$3,$AC8,$AD8) -> 16.3 | AF8: =_xll.VAData($AB8,AF$3,$AC8,$AD8) -> 57.9 | AG8: =_xll.VAData($AB8,AG$3,$AC8,$AD8) -> 73.2 | AH8: =_xll.VAData($AB8,AH$3,$AC8,$AD8) -> 77.297995 | AI8: =_xll.VAData($AB8,AI$3,$AC8,$AD8) -> 50 | AJ8: =_xll.VAData($AB8,AJ$3,$AC8,$AD8) -> 47.4 | AK8: =_xll.VAData($AB8,AK$3,$AC8,$AD8) -> 92.7 | AL8: =_xll.VAData($AB8,AL$3,$AC8,$AD8) -> 96 | ... AP8: =_xll.VAData($AB8,AP$3,$AC8,$AD8) -> 105.43671 | AR8: 16.3 | AS8: 57.9 | AT8: 73.2 | AU8: 77.297995 | AV8: 50 | AW8: 47.4 | AX8: 92.7 | AY8: 96 | AZ8: 86.31809 | BA8: 95.631743 | BB8: 109.43267 | BC8: 101.31928 | BE8: =D8-AR8 -> -16.3 | BF8: =E8-AS8 -> -57.9 | BG8: =F8-AT8 -> 0 | BH8: =G8-AU8 -> 0.0020049496 | BI8: =H8-AV8 -> 0 | BJ8: =I8-AW8 -> 0 | BK8: =J8-AX8 -> 0 | BL8: =K8-AY8 -> 0 | ... BP8: =O8-BC8 -> 4.9871263 | BT8: EBIT | BV8: =FY!D71 -> 150.5 | BW8: =FY!E71 -> 97.4 | BX8: =FY!F71 -> 188.7 | BY8: =FY!G71 -> 218.7 | BZ8: =FY!H71 -> 238.02006 | CA8: =FY!I71 -> 262.24577 | CB8: =FY!J71 -> 269.16774 | CC8: =FY!K71 -> 285.90615 | CE8: =BX8 -> 188.7 | CF8: 218.7 | CG8: =CF8/CE8-1 -> 0.15898251 | CH8: =BY8 -> 218.7 | CI8: =$CF8/CH8-1 -> 0 | CJ8: =CN8 -> 207.08996 | CK8: =$CF8/CJ8-1 -> 0.056062785 | CN8: =DG8 -> 207.08996 | CP8: TAH_AU | CQ8: Operating income/(loss) - Operating | CR8: consensus.vaactuals | CS8: =_xll.VAData($AB8,CS$3,$AC8,$AD8) -> 95.2 | CT8: =_xll.VAData($AB8,CT$3,$AC8,$AD8) -> 150.5 | CU8: =_xll.VAData($AB8,CU$3,$AC8,$AD8) -> 97.4 | CV8: =_xll.VAData($AB8,CV$3,$AC8,$AD8) -> 188.7 | CW8: =_xll.VAData($AB8,CW$3,$AC8,$AD8) -> 218.7 | CX8: =_xll.VAData($AB8,CX$3,$AC8,$AD8) -> 235.01687 | CY8: =_xll.VAData($AB8,CY$3,$AC8,$AD8) -> 251.24654 | CZ8: =_xll.VAData($AB8,CZ$3,$AC8,$AD8) -> 264.73724 | DA8: =_xll.VAData($AB8,DA$3,$AC8,$AD8) -> 276.76132 | DC8: 95.2 | DD8: 150.5 | DE8: 97.4 | DF8: 188.7 | DG8: 207.08996 | DH8: 223.84775 | DI8: 237.84596 | DJ8: 248.86053 | DK8: 261.04487 | DN8: =BV8-DD8 -> 0 | DO8: =BW8-DE8 -> 0 | DP8: =BX8-DF8 -> 0 | DQ8: =BY8-DG8 -> 11.61004 | DR8: =BZ8-DH8 -> 14.172312 | DS8: =CA8-DI8 -> 24.399815 | DT8: =CB8-DJ8 -> 20.307201 | DU8: =CC8-DK8 -> 24.861272
C9: NPAT - before significant items | F9: =HY!O328 -> 47.3 | G9: =HY!P328 -> 37 | H9: =HY!Q328 -> 17.6 | I9: =HY!R328 -> 10.4 | J9: =HY!S328 -> 22.1 | K9: =HY!T328 -> 27.4 | L9: =HY!U328 -> 35.7 | M9: =HY!V328 -> 35.4 | ... O9: =HY!X328 -> 35.903642 | Q9: =J9 -> 22.1 | R9: 35.7 | S9: =R9/Q9-1 -> 0.61538462 | T9: =L9 -> 35.7 | U9: =$R9/T9-1 -> 0 | V9: =Z9 -> 25.068204 | W9: =$R9/V9-1 -> 0.42411477 | Z9: =AZ9 -> 25.068204 | AB9: TAH_AU | AC9: Net income/(loss) - Operating | AD9: consensus.vaactuals | AE9: =_xll.VAData($AB9,AE$3,$AC9,$AD9) -> 186.5 | AF9: =_xll.VAData($AB9,AF$3,$AC9,$AD9) -> 175.4 | AG9: =_xll.VAData($AB9,AG$3,$AC9,$AD9) -> 47.3 | AH9: =_xll.VAData($AB9,AH$3,$AC9,$AD9) -> 37 | AI9: =_xll.VAData($AB9,AI$3,$AC9,$AD9) -> 17.6 | AJ9: =_xll.VAData($AB9,AJ$3,$AC9,$AD9) -> 10.4 | AK9: =_xll.VAData($AB9,AK$3,$AC9,$AD9) -> 22.1 | AL9: =_xll.VAData($AB9,AL$3,$AC9,$AD9) -> 27.4 | ... AP9: =_xll.VAData($AB9,AP$3,$AC9,$AD9) -> 36.058029 | AR9: 186.5 | AS9: 175.4 | AT9: 47.3 | AU9: 37 | AV9: 17.6 | AW9: 10.4 | AX9: 22.1 | AY9: 27.4 | AZ9: 25.068204 | BA9: 33.062236 | BB9: 42.946837 | BC9: 39.784283 | BE9: =D9-AR9 -> -186.5 | BF9: =E9-AS9 -> -175.4 | BG9: =F9-AT9 -> 0 | BH9: =G9-AU9 -> 0 | BI9: =H9-AV9 -> 0 | BJ9: =I9-AW9 -> 0 | BK9: =J9-AX9 -> 0 | BL9: =K9-AY9 -> 0 | ... BP9: =O9-BC9 -> -3.8806414 | BT9: NPAT - before significant items | BV9: =FY!D81 -> 84.3 | BW9: =FY!E81 -> 28 | BX9: =FY!F81 -> 49.5 | BY9: =FY!G81 -> 71.1 | BZ9: =FY!H81 -> 89.710264 | CA9: =FY!I81 -> 110.08763 | CB9: =FY!J81 -> 120.65763 | CC9: =FY!K81 -> 137.49126 | CE9: =BX9 -> 49.5 | CF9: 71.1 | CG9: =CF9/CE9-1 -> 0.43636364 | CH9: =BY9 -> 71.1 | CI9: =$CF9/CH9-1 -> 0 | CJ9: =CN9 -> 67.058659 | CK9: =$CF9/CJ9-1 -> 0.060265757 | CN9: =DG9 -> 67.058659 | CP9: TAH_AU | CQ9: Net income/(loss) - Operating | CR9: consensus.vaactuals | CS9: =_xll.VAData($AB9,CS$3,$AC9,$AD9) -> 362.4 | CT9: =_xll.VAData($AB9,CT$3,$AC9,$AD9) -> 84.3 | CU9: =_xll.VAData($AB9,CU$3,$AC9,$AD9) -> 28 | CV9: =_xll.VAData($AB9,CV$3,$AC9,$AD9) -> 49.5 | CW9: =_xll.VAData($AB9,CW$3,$AC9,$AD9) -> 71.1 | CX9: =_xll.VAData($AB9,CX$3,$AC9,$AD9) -> 88.264785 | CY9: =_xll.VAData($AB9,CY$3,$AC9,$AD9) -> 101.01483 | CZ9: =_xll.VAData($AB9,CZ$3,$AC9,$AD9) -> 115.33058 | DA9: =_xll.VAData($AB9,DA$3,$AC9,$AD9) -> 129.83598 | DC9: 362.4 | DD9: 84.3 | DE9: 28 | DF9: 49.5 | DG9: 67.058659 | DH9: 85.12683 | DI9: 99.249123 | DJ9: 113.29612 | DK9: 126.2911 | DN9: =BV9-DD9 -> 0 | DO9: =BW9-DE9 -> 0 | DP9: =BX9-DF9 -> 0 | DQ9: =BY9-DG9 -> 4.0413409 | DR9: =BZ9-DH9 -> 4.5834341 | DS9: =CA9-DI9 -> 10.838511 | DT9: =CB9-DJ9 -> 7.3615068 | DU9: =CC9-DK9 -> 11.200154
C10: EPS (cps) | F10: =HY!O621 -> 2.2 | G10: =HY!P621 -> 1.6 | H10: =HY!Q621 -> 0.9 | I10: =HY!R621 -> 0.5 | J10: =HY!S621 -> 1.9 | K10: =HY!T621 -> 2 | L10: =HY!U621 -> 2.7 | M10: =HY!V621 -> 2.5 | ... O10: =HY!X621 -> 2.4776953 | Q10: =J10 -> 1.9 | R10: 2.7 | S10: =R10/Q10-1 -> 0.42105263 | T10: =L10 -> 2.7 | U10: =$R10/T10-1 -> 0 | V10: =Z10 -> 1.0951553 | W10: =$R10/V10-1 -> 1.4654038 | Z10: =AZ10 -> 1.0951553 | AB10: TAH_AU | AC10: EPS - Diluted - Operating | AD10: consensus.vaactuals | AE10: =_xll.VAData($AB10,AE$3,$AC10,$AD10) -> 8.3845126 | AF10: =_xll.VAData($AB10,AF$3,$AC10,$AD10) -> 2.1536655 | AG10: =_xll.VAData($AB10,AG$3,$AC10,$AD10) -> 2.0998424 | AH10: =_xll.VAData($AB10,AH$3,$AC10,$AD10) -> 1.620781 | AI10: =_xll.VAData($AB10,AI$3,$AC10,$AD10) -> 0.77139693 | AJ10: =_xll.VAData($AB10,AJ$3,$AC10,$AD10) -> 0.45554786 | AK10: =_xll.VAData($AB10,AK$3,$AC10,$AD10) -> 0.96750946 | AL10: =_xll.VAData($AB10,AL$3,$AC10,$AD10) -> 1.1988543 | ... AP10: =_xll.VAData($AB10,AP$3,$AC10,$AD10) -> 1.5514494 | AR10: 8.3845126 | AS10: 2.0859562 | AT10: 2.0998424 | AU10: 1.620781 | AV10: 0.77139693 | AW10: 0.45554786 | AX10: 0.96750946 | AY10: 1.1988543 | AZ10: 1.0951553 | BA10: 1.4429444 | BB10: 1.8759807 | BC10: 1.7358624 | BE10: =D10-AR10 -> -8.3845126 | BF10: =E10-AS10 -> -2.0859562 | BG10: =F10-AT10 -> 0.1001576 | BH10: =G10-AU10 -> -0.020781041 | BI10: =H10-AV10 -> 0.12860307 | BJ10: =I10-AW10 -> 0.044452138 | BK10: =J10-AX10 -> 0.93249054 | BL10: =K10-AY10 -> 0.80114568 | ... BP10: =O10-BC10 -> 0.74183284 | BT10: EPS (cps) - before significant items | BV10: =FY!D183 -> 3.8 | BW10: =FY!E183 -> 1.4 | BX10: =FY!F183 -> 3.9 | BY10: =FY!G183 -> 5.2 | BZ10: =FY!H183 -> 5.7799121 | CA10: =FY!I183 -> 6.1889398 | CB10: =FY!J183 -> 6.2138022 | CC10: =FY!K183 -> 6.5991127 | CE10: =BX10 -> 3.9 | CG10: =CF10/CE10-1 -> -1 | CH10: =BY10 -> 5.2 | CI10: =$CF10/CH10-1 -> -1 | CJ10: =CN10 -> 2.9258618 | CK10: =$CF10/CJ10-1 -> -1 | CN10: =DG10 -> 2.9258618 | CP10: TAH_AU | CQ10: EPS - Diluted - Operating | CR10: consensus.vaactuals | CS10: =_xll.VAData($AB10,CS$3,$AC10,$AD10) -> 16.288373 | CT10: =_xll.VAData($AB10,CT$3,$AC10,$AD10) -> 3.7174229 | CU10: =_xll.VAData($AB10,CU$3,$AC10,$AD10) -> 1.2266713 | CV10: =_xll.VAData($AB10,CV$3,$AC10,$AD10) -> 2.1570507 | CW10: =_xll.VAData($AB10,CW$3,$AC10,$AD10) -> 3.0560928 | CX10: =_xll.VAData($AB10,CX$3,$AC10,$AD10) -> 3.8066274 | CY10: =_xll.VAData($AB10,CY$3,$AC10,$AD10) -> 4.3149056 | CZ10: =_xll.VAData($AB10,CZ$3,$AC10,$AD10) -> 4.924777 | DA10: =_xll.VAData($AB10,DA$3,$AC10,$AD10) -> 5.5418836 | DC10: 16.288373 | DD10: 3.7174229 | DE10: 1.2266713 | DF10: 2.1570507 | DG10: 2.9258618 | DH10: 3.7081348 | DI10: 4.3047675 | DJ10: 4.9130597 | DK10: 5.4737282 | DN10: =BV10-DD10 -> 0.08257706 | DO10: =BW10-DE10 -> 0.17332866 | DP10: =BX10-DF10 -> 1.7429493 | DQ10: =BY10-DG10 -> 2.2741382 | DR10: =BZ10-DH10 -> 2.0717773 | DS10: =CA10-DI10 -> 1.8841723 | DT10: =CB10-DJ10 -> 1.3007424 | DU10: =CC10-DK10 -> 1.1253845
C11: DPS (cps) | F11: =HY!O527 -> 1.3 | G11: =HY!P527 -> 1 | H11: =HY!Q527 -> 1 | I11: =HY!R527 -> 0.3 | J11: =HY!S527 -> 1 | K11: =HY!T527 -> 1 | L11: =HY!U527 -> 1.5 | M11: =HY!V527 -> 1.5 | ... O11: =HY!X527 -> 1.6 | Q11: =J11 -> 1 | R11: 1.5 | S11: =R11/Q11-1 -> 0.5 | T11: =L11 -> 1.5 | U11: =$R11/T11-1 -> 0 | V11: =Z11 -> 0.8345962 | W11: =$R11/V11-1 -> 0.79727635 | Z11: =AZ11 -> 0.8345962 | AB11: TAH_AU | AC11: Dividend per share | AD11: consensus.vaactuals | AE11: =_xll.VAData($AB11,AE$3,$AC11,$AD11) -> 6.5 | AF11: =_xll.VAData($AB11,AF$3,$AC11,$AD11) -> 6.5 | AG11: =_xll.VAData($AB11,AG$3,$AC11,$AD11) -> 1.3 | AH11: =_xll.VAData($AB11,AH$3,$AC11,$AD11) -> 1 | AI11: =_xll.VAData($AB11,AI$3,$AC11,$AD11) -> 1 | AJ11: =_xll.VAData($AB11,AJ$3,$AC11,$AD11) -> 0.3 | AK11: =_xll.VAData($AB11,AK$3,$AC11,$AD11) -> 1 | AL11: =_xll.VAData($AB11,AL$3,$AC11,$AD11) -> 1 | ... AP11: =_xll.VAData($AB11,AP$3,$AC11,$AD11) -> 1.4208592 | AR11: 6.5 | AS11: 6.5 | AT11: 1.3 | AU11: 1 | AV11: 1 | AW11: 0.3 | AX11: 1 | AY11: 1 | AZ11: 0.8345962 | BA11: 1.0175185 | BB11: 1.3304097 | BC11: 1.2327437 | BE11: =D11-AR11 -> -6.5 | BF11: =E11-AS11 -> -6.5 | BG11: =F11-AT11 -> 0 | BH11: =G11-AU11 -> 0 | BI11: =H11-AV11 -> 0 | BJ11: =I11-AW11 -> 0 | BK11: =J11-AX11 -> 0 | BL11: =K11-AY11 -> 0 | ... BP11: =O11-BC11 -> 0.3672563 | BT11: DPS (cps) | BV11: =FY!D186 -> 2.3 | BW11: =FY!E186 -> 1.3 | BX11: =FY!F186 -> 2 | BY11: =FY!G186 -> 3 | BZ11: =FY!H186 -> 3.2 | CA11: =FY!I186 -> 3.2 | CB11: =FY!J186 -> 3.7282813 | CC11: =FY!K186 -> 3.2995563 | CE11: =BX11 -> 2 | CF11: 3 | CG11: =CF11/CE11-1 -> 0.5 | CH11: =BY11 -> 3 | CI11: =$CF11/CH11-1 -> 0 | CJ11: =CN11 -> 2.6905373 | CK11: =$CF11/CJ11-1 -> 0.11501894 | CN11: =DG11 -> 2.6905373 | CP11: TAH_AU | CQ11: Dividend per share | CR11: consensus.vaactuals | CS11: =_xll.VAData($AB11,CS$3,$AC11,$AD11) -> 13 | CT11: =_xll.VAData($AB11,CT$3,$AC11,$AD11) -> 2.3 | CU11: =_xll.VAData($AB11,CU$3,$AC11,$AD11) -> 1.3 | CV11: =_xll.VAData($AB11,CV$3,$AC11,$AD11) -> 2 | CW11: =_xll.VAData($AB11,CW$3,$AC11,$AD11) -> 3 | CX11: =_xll.VAData($AB11,CX$3,$AC11,$AD11) -> 3.3014117 | CY11: =_xll.VAData($AB11,CY$3,$AC11,$AD11) -> 3.5969058 | CZ11: =_xll.VAData($AB11,CZ$3,$AC11,$AD11) -> 4.0664096 | DA11: =_xll.VAData($AB11,DA$3,$AC11,$AD11) -> 4.4596903 | DC11: 13 | DD11: 2.3 | DE11: 1.3 | DF11: 2 | DG11: 2.6905373 | DH11: 3.0778477 | DI11: 3.2810497 | DJ11: 3.6919246 | DK11: 4.0219095 | DN11: =BV11-DD11 -> 0 | DO11: =BW11-DE11 -> 0 | DP11: =BX11-DF11 -> 0 | DQ11: =BY11-DG11 -> 0.30946274 | DR11: =BZ11-DH11 -> 0.12215228 | DS11: =CA11-DI11 -> -0.081049718 | DT11: =CB11-DJ11 -> 0.036356734 | DU11: =CC11-DK11 -> -0.72235321
C13: Tabcorp 1H26 Result - Segments | BT13: Tabcorp FY26 Result - Segments
D14: =D$3 -> 1H22A | E14: =E$3 -> 2H22A | F14: =F$3 -> 1H23A | G14: =G$3 -> 2H23A | H14: =H$3 -> 1H24A | I14: =I$3 -> 2H24E | J14: =J$3 -> 1H25E | K14: =K$3 -> 2H25E | ... O14: =O$3 -> 2H27E | Q14: =Q$3 -> 1H25A | R14: =R$3 -> 1H26A | S14: =S$3 -> % change | T14: =T$3 -> E&Pe 1H26E | U14: =U$3 -> % diff | V14: =V$3 -> VA Cons. 1H26E | W14: =W$3 -> % diff | Z14: 1H25 | AE14: 1H22 | AF14: 2H22 | AG14: 1H23 | AH14: 2H23 | AI14: 1H24 | AJ14: 2H24 | AK14: 1H25 | AL14: 2H25 | AM14: 1H26 | AN14: 2H26 | AO14: 1H27 | AP14: 2H27 | AR14: 1H22 | AS14: 2H22 | AT14: 1H23 | AU14: 2H23 | AV14: 1H24 | AW14: 2H24 | AX14: 1H25 | AY14: 2H25 | AZ14: 1H26 | BA14: 2H26 | BB14: 1H27 | BC14: 2H27 | BE14: 1H22 | BF14: 2H22 | BG14: 1H23 | BH14: 2H23 | BI14: 1H24 | BJ14: 2H24 | BK14: 1H25 | BL14: 2H25 | BM14: 1H26 | BN14: 2H26 | BO14: 1H27 | BP14: 2H27 | BU14: =BU$3 -> FY22A | BV14: =BV$3 -> FY23A | BW14: =BW$3 -> FY24A | BX14: =BX$3 -> FY25E | BY14: =BY$3 -> FY26E | BZ14: =BZ$3 -> FY27E | CA14: =CA$3 -> FY28E | CB14: =CB$3 -> FY29E | CC14: =CC$3 -> FY30E | CE14: =CE$3 -> FY25A | CF14: =CF$3 -> FY26A | CG14: =CG$3 -> % change | CH14: =CH$3 -> E&Pe FY26E | CI14: =CI$3 -> % diff | CJ14: =CJ$3 -> VA Cons. FY26E | CK14: =CK$3 -> % diff | CN14: =DG14 -> FY26 | CS14: FY22 | CT14: FY23 | CU14: FY24 | CV14: FY25 | CW14: FY26 | CX14: FY27 | CY14: FY27 | CZ14: FY27 | DA14: FY27 | DC14: FY22 | DD14: FY23 | DE14: FY24 | DF14: FY25 | DG14: FY26 | DH14: FY27 | DI14: FY27 | DJ14: FY27 | DK14: FY27 | DM14: FY22 | DN14: FY23 | DO14: FY24 | DP14: FY25 | DQ14: FY26 | DR14: FY27 | DS14: FY28 | DT14: FY29 | DU14: FY30
CW15: =CX17-20 -> 2500.6753
C16: Segments | BT16: Segments | CW16: =CW15/CW17-1 -> 0.018729488 | CX16: =CX17/CW17-1 -> 0.026877123 | CY16: =CY17/CX17-1 -> 0.025503622 | CZ16: =CZ17/CY17-1 -> 0.018435089 | DH16: 0.02790958 | DI16: 0.024634795 | DJ16: 0.021579666
C17: Wagering & Media | D17: =HY!M268 -> 1073.4 | E17: =HY!N268 -> 1108.5 | F17: =HY!O268 -> 1165.7 | G17: =HY!P268 -> 1065.1 | H17: =HY!Q268 -> 1116.6 | I17: =HY!R268 -> 1046.2 | J17: =HY!S268 -> 1243.2 | K17: =HY!T268 -> 1195.6 | ... O17: =HY!X268 -> 1228.5871 | Q17: =J17 -> 1243.2 | R17: 1253.2 | S17: =R17/Q17-1 -> 0.008043758 | T17: =L17 -> 1253.2 | U17: =$R17/T17-1 -> 0 | V17: =Z17 -> 1235.4444 | W17: =$R17/V17-1 -> 0.01437181 | Z17: =AZ17 -> 1235.4444 | AB17: TAH_AU | AC17: Total revenue - Wagering & media | AD17: consensus.vaactuals | AE17: =_xll.VAData($AB17,AE$3,$AC17,$AD17) -> 1073.4 | AF17: =_xll.VAData($AB17,AF$3,$AC17,$AD17) -> 1108.5 | AG17: =_xll.VAData($AB17,AG$3,$AC17,$AD17) -> 1165.7 | AH17: =_xll.VAData($AB17,AH$3,$AC17,$AD17) -> 1065.1 | AI17: =_xll.VAData($AB17,AI$3,$AC17,$AD17) -> 1116.7 | AJ17: =_xll.VAData($AB17,AJ$3,$AC17,$AD17) -> 1045.4 | AK17: =_xll.VAData($AB17,AK$3,$AC17,$AD17) -> 1243.2 | AL17: =_xll.VAData($AB17,AL$3,$AC17,$AD17) -> 1195.6 | ... AP17: =_xll.VAData($AB17,AP$3,$AC17,$AD17) -> 1223.8215 | AR17: 1073.4 | AS17: 1108.5 | AT17: 1165.7 | AU17: 1065.1 | AV17: 1116.7 | AW17: 1046.2 | AX17: 1243.2 | AY17: 1195.6 | AZ17: 1235.4444 | BA17: 1212.0123 | BB17: 1309.3178 | BC17: 1239.4595 | BE17: =D17-AR17 -> 0 | BF17: =E17-AS17 -> 0 | BG17: =F17-AT17 -> 0 | BH17: =G17-AU17 -> 0 | BI17: =H17-AV17 -> -0.1 | BJ17: =I17-AW17 -> 0 | BK17: =J17-AX17 -> 0 | BL17: =K17-AY17 -> 0 | ... BP17: =O17-BC17 -> -10.87241 | BT17: Wagering & Media | BU17: =FY!C8 -> 2181.9 | BV17: =FY!D8 -> 2230.8 | BW17: =FY!E8 -> 2162.8 | BX17: =FY!F8 -> 2438.8 | BY17: =FY!G8 -> 2454.7 | BZ17: =FY!H8 -> 2535.5783 | CA17: =FY!I8 -> 2553.5792 | CB17: =FY!J8 -> 2575.9298 | CC17: =FY!K8 -> 2633.1222 | CE17: =BX17 -> 2438.8 | CF17: 2454.7 | CG17: =CF17/CE17-1 -> 0.0065195998 | CH17: =BY17 -> 2454.7 | CI17: =$CF17/CH17-1 -> 0 | CJ17: =CN17 -> 2468.3065 | CK17: =$CF17/CJ17-1 -> -0.0055124919 | CN17: =DG17 -> 2468.3065 | CP17: TAH_AU | CQ17: Total revenue - Wagering & media | CR17: consensus.vaactuals | CS17: =_xll.VAData($AB17,CS$3,$AC17,$AD17) -> 2181.9 | CT17: =_xll.VAData($AB17,CT$3,$AC17,$AD17) -> 2230.8 | CU17: =_xll.VAData($AB17,CU$3,$AC17,$AD17) -> 2162.8 | CV17: =_xll.VAData($AB17,CV$3,$AC17,$AD17) -> 2438.8 | CW17: =_xll.VAData($AB17,CW$3,$AC17,$AD17) -> 2454.7 | CX17: =_xll.VAData($AB17,CX$3,$AC17,$AD17) -> 2520.6753 | CY17: =_xll.VAData($AB17,CY$3,$AC17,$AD17) -> 2584.9616 | CZ17: =_xll.VAData($AB17,CZ$3,$AC17,$AD17) -> 2632.6156 | DA17: =_xll.VAData($AB17,DA$3,$AC17,$AD17) -> 2680.5293 | DC17: 2181.9 | DD17: 2230.8 | DE17: 2162.8 | DF17: 2438.8 | DG17: 2468.3065 | DH17: 2537.1959 | DI17: 2599.6992 | DJ17: 2655.7999 | DK17: 2711.6151 | DM17: =BU17-DC17 -> 0 | DN17: =BV17-DD17 -> 0 | DO17: =BW17-DE17 -> 0 | DP17: =BX17-DF17 -> 0 | DQ17: =BY17-DG17 -> -13.60652 | DR17: =BZ17-DH17 -> -1.6176013 | DS17: =CA17-DI17 -> -46.119982 | DT17: =CB17-DJ17 -> -79.870041 | DU17: =CC17-DK17 -> -78.492871
C18: Integrity Services | D18: =HY!M269 -> 79.6 | E18: =HY!N269 -> 117.3 | F18: =HY!O269 -> 108.8 | G18: =HY!P269 -> 94.8 | H18: =HY!Q269 -> 80.3 | I18: =HY!R269 -> 83.1 | J18: =HY!S269 -> 88.1 | K18: =HY!T269 -> 87.7 | ... O18: =HY!X269 -> 92.1475 | Q18: =J18 -> 88.1 | R18: 91.7 | S18: =R18/Q18-1 -> 0.040862656 | T18: =L18 -> 91.7 | U18: =$R18/T18-1 -> 0 | V18: =Z18 -> 90.096278 | W18: =$R18/V18-1 -> 0.017800093 | Z18: =AZ18 -> 90.096278 | AB18: TAH_AU | AC18: Total revenue - Gaming services | AD18: consensus.vaactuals | AE18: =_xll.VAData($AB18,AE$3,$AC18,$AD18) -> 79.6 | AF18: =_xll.VAData($AB18,AF$3,$AC18,$AD18) -> 117.3 | AG18: =_xll.VAData($AB18,AG$3,$AC18,$AD18) -> 108.8 | AH18: =_xll.VAData($AB18,AH$3,$AC18,$AD18) -> 94.8 | AI18: =_xll.VAData($AB18,AI$3,$AC18,$AD18) -> 80.3 | AJ18: =_xll.VAData($AB18,AJ$3,$AC18,$AD18) -> 83.1 | AK18: =_xll.VAData($AB18,AK$3,$AC18,$AD18) -> 88.1 | AL18: =_xll.VAData($AB18,AL$3,$AC18,$AD18) -> 87.7 | ... AP18: =_xll.VAData($AB18,AP$3,$AC18,$AD18) -> 91.723117 | AR18: 79.6 | AS18: 117.3 | AT18: 108.8 | AU18: 94.8 | AV18: 93 | AW18: 83.1 | AX18: 88.1 | AY18: 87.7 | AZ18: 90.096278 | BA18: 89.817969 | BB18: 92.612824 | BC18: 92.312926 | BE18: =D18-AR18 -> 0 | BF18: =E18-AS18 -> 0 | BG18: =F18-AT18 -> 0 | BH18: =G18-AU18 -> 0 | BI18: =H18-AV18 -> -12.7 | BJ18: =I18-AW18 -> 0 | BK18: =J18-AX18 -> 0 | BL18: =K18-AY18 -> 0 | ... BP18: =O18-BC18 -> -0.16542612 | BT18: Integrity Services | BU18: =FY!C9 -> 196.9 | BV18: =FY!D9 -> 203.6 | BW18: =FY!E9 -> 163.4 | BX18: =FY!F9 -> 175.8 | BY18: =FY!G9 -> 181.6 | BZ18: =FY!H9 -> 186.14 | CA18: =FY!I9 -> 190.7935 | CB18: =FY!J9 -> 196.5173 | CC18: =FY!K9 -> 202.41282 | CE18: =BX18 -> 175.8 | CF18: 181.6 | CG18: =CF18/CE18-1 -> 0.032992036 | CH18: =BY18 -> 181.6 | CI18: =$CF18/CH18-1 -> 0 | CJ18: =CN18 -> 182.14801 | CK18: =$CF18/CJ18-1 -> -0.0030085891 | CN18: =DG18 -> 182.14801 | CP18: TAH_AU | CQ18: Total revenue - Gaming services | CR18: consensus.vaactuals | CS18: =_xll.VAData($AB18,CS$3,$AC18,$AD18) -> 196.9 | CT18: =_xll.VAData($AB18,CT$3,$AC18,$AD18) -> 203.6 | CU18: =_xll.VAData($AB18,CU$3,$AC18,$AD18) -> 163.4 | CV18: =_xll.VAData($AB18,CV$3,$AC18,$AD18) -> 175.8 | CW18: =_xll.VAData($AB18,CW$3,$AC18,$AD18) -> 181.6 | CX18: =_xll.VAData($AB18,CX$3,$AC18,$AD18) -> 185.16618 | CY18: =_xll.VAData($AB18,CY$3,$AC18,$AD18) -> 189.8524 | CZ18: =_xll.VAData($AB18,CZ$3,$AC18,$AD18) -> 194.58353 | DA18: =_xll.VAData($AB18,DA$3,$AC18,$AD18) -> 199.53644 | DC18: 196.9 | DD18: 203.6 | DE18: 163.4 | DF18: 175.8 | DG18: 182.14801 | DH18: 187.60247 | DI18: 192.69029 | DJ18: 197.68489 | DK18: 202.94352 | DM18: =BU18-DC18 -> 0 | DN18: =BV18-DD18 -> 0 | DO18: =BW18-DE18 -> 0 | DP18: =BX18-DF18 -> 0 | DQ18: =BY18-DG18 -> -0.54800851 | DR18: =BZ18-DH18 -> -1.4624651 | DS18: =CA18-DI18 -> -1.8967865 | DT18: =CB18-DJ18 -> -1.1675843 | DU18: =CC18-DK18 -> -0.53069124
C19: Revenue | D19: =HY!M271 -> 1152.3 | E19: =HY!N271 -> 1225 | F19: =HY!O271 -> 1274.5 | G19: =HY!P271 -> 1159.9 | H19: =HY!Q271 -> 1209.6 | I19: =HY!R271 -> 1129.3 | J19: =HY!S271 -> 1331.3 | K19: =HY!T271 -> 1283.3 | ... O19: =HY!X271 -> 1345.9846 | Q19: =J19 -> 1331.3 | R19: 1344.9 | S19: =R19/Q19-1 -> 0.010215579 | T19: =L19 -> 1344.9 | U19: =$R19/T19-1 -> 0 | V19: =Z19 -> 1325.1042 | W19: =$R19/V19-1 -> 0.014939085 | Z19: =AZ19 -> 1325.1042 | AB19: TAH_AU | AC19: Total revenue | AD19: consensus.vaactuals | AE19: =_xll.VAData($AB19,AE$3,$AC19,$AD19) -> 1152.3 | AF19: =_xll.VAData($AB19,AF$3,$AC19,$AD19) -> 1225 | AG19: =_xll.VAData($AB19,AG$3,$AC19,$AD19) -> 1274.5 | AH19: =_xll.VAData($AB19,AH$3,$AC19,$AD19) -> 1159.9 | AI19: =_xll.VAData($AB19,AI$3,$AC19,$AD19) -> 1209.6 | AJ19: =_xll.VAData($AB19,AJ$3,$AC19,$AD19) -> 1129.3 | AK19: =_xll.VAData($AB19,AK$3,$AC19,$AD19) -> 1331.3 | AL19: =_xll.VAData($AB19,AL$3,$AC19,$AD19) -> 1283.3 | ... AP19: =_xll.VAData($AB19,AP$3,$AC19,$AD19) -> 1320.0772 | AR19: 1152.3 | AS19: 1225 | AT19: 1274.5 | AU19: 1159.9 | AV19: 1209.6 | AW19: 1129.3 | AX19: 1331.3 | AY19: 1283.3 | AZ19: 1325.1042 | BA19: 1299.1995 | BB19: 1403.9844 | BC19: 1330.4886 | BE19: =D19-AR19 -> 0 | BF19: =E19-AS19 -> 0 | BG19: =F19-AT19 -> 0 | BH19: =G19-AU19 -> 0 | BI19: =H19-AV19 -> 0 | BJ19: =I19-AW19 -> 0 | BK19: =J19-AX19 -> 0 | BL19: =K19-AY19 -> 0 | ... BP19: =O19-BC19 -> 15.495959 | BT19: Revenue | BU19: =FY!C11 -> 2377.3 | BV19: =FY!D11 -> 2434.4 | BW19: =FY!E11 -> 2338.9 | BX19: =FY!F11 -> 2614.6 | BY19: =FY!G11 -> 2636.3 | BZ19: =FY!H11 -> 2746.9683 | CA19: =FY!I11 -> 2846.8577 | CB19: =FY!J11 -> 2878.0067 | CC19: =FY!K11 -> 2944.2614 | CE19: =BX19 -> 2614.6 | CF19: 2636.3 | CG19: =CF19/CE19-1 -> 0.0082995487 | CH19: =BY19 -> 2636.3 | CI19: =$CF19/CH19-1 -> 0 | CJ19: =CN19 -> 2648.8625 | CK19: =$CF19/CJ19-1 -> -0.0047426056 | CN19: =DG19 -> 2648.8625 | CP19: TAH_AU | CQ19: Total revenue | CR19: consensus.vaactuals | CS19: =_xll.VAData($AB19,CS$3,$AC19,$AD19) -> 2377.3 | CT19: =_xll.VAData($AB19,CT$3,$AC19,$AD19) -> 2434.4 | CU19: =_xll.VAData($AB19,CU$3,$AC19,$AD19) -> 2338.9 | CV19: =_xll.VAData($AB19,CV$3,$AC19,$AD19) -> 2614.6 | CW19: =_xll.VAData($AB19,CW$3,$AC19,$AD19) -> 2636.3 | CX19: =_xll.VAData($AB19,CX$3,$AC19,$AD19) -> 2711.2841 | CY19: =_xll.VAData($AB19,CY$3,$AC19,$AD19) -> 2814.8079 | CZ19: =_xll.VAData($AB19,CZ$3,$AC19,$AD19) -> 2868.9248 | DA19: =_xll.VAData($AB19,DA$3,$AC19,$AD19) -> 2923.4937 | DC19: 2377.3 | DD19: 2434.4 | DE19: 2338.9 | DF19: 2614.6 | DG19: 2648.8625 | DH19: 2724.7974 | DI19: 2805.8885 | DJ19: 2866.3854 | DK19: 2926.7643 | DM19: =BU19-DC19 -> 0 | DN19: =BV19-DD19 -> 0 | DO19: =BW19-DE19 -> 0 | DP19: =BX19-DF19 -> 0 | DQ19: =BY19-DG19 -> -12.56251 | DR19: =BZ19-DH19 -> 22.170942 | DS19: =CA19-DI19 -> 40.969186 | DT19: =CB19-DJ19 -> 11.621313 | DU19: =CC19-DK19 -> 17.497128
C21: Wagering & Media | D21: =HY!M279 -> 394.9 | E21: =HY!N279 -> 406.4 | F21: =HY!O279 -> 398.3 | G21: =HY!P279 -> 376.7 | H21: =HY!Q279 -> 393.9 | I21: =HY!R279 -> 364.3 | J21: =HY!S279 -> 458.1 | K21: =HY!T279 -> 457.8 | ... O21: =HY!X279 -> 485.29189 | Q21: =J21 -> 458.1 | R21: 477.4 | S21: =R21/Q21-1 -> 0.042130539 | T21: =L21 -> 477.4 | U21: =$R21/T21-1 -> 0 | V21: =Z21 -> 472.33448 | W21: =$R21/V21-1 -> 0.01072443 | Z21: =AZ21 -> 472.33448 | AB21: TAH_AU | AC21: Contribution - Wagering and media - Operating | AD21: consensus.vaactuals | AE21: =_xll.VAData($AB21,AE$3,$AC21,$AD21) -> 394.9 | AF21: =_xll.VAData($AB21,AF$3,$AC21,$AD21) -> 406.4 | AG21: =_xll.VAData($AB21,AG$3,$AC21,$AD21) -> 398.3 | AH21: =_xll.VAData($AB21,AH$3,$AC21,$AD21) -> 376.8 | AI21: =_xll.VAData($AB21,AI$3,$AC21,$AD21) -> 393.9 | AJ21: =_xll.VAData($AB21,AJ$3,$AC21,$AD21) -> 364.3 | AK21: =_xll.VAData($AB21,AK$3,$AC21,$AD21) -> 458.1 | AL21: =_xll.VAData($AB21,AL$3,$AC21,$AD21) -> 457.8 | ... AP21: =_xll.VAData($AB21,AP$3,$AC21,$AD21) -> 494.14367 | AR21: 394.9 | AS21: 406.4 | AT21: 398.3 | AU21: 376.8 | AV21: 393.9 | AW21: 364.3 | AX21: 458.1 | AY21: 457.8 | AZ21: 472.33448 | BA21: 463.97527 | BB21: 503.90303 | BC21: 475.44141 | BE21: =D21-AR21 -> 0 | BF21: =E21-AS21 -> 0 | BG21: =F21-AT21 -> 0 | BH21: =G21-AU21 -> -0.1 | BI21: =H21-AV21 -> 0 | BJ21: =I21-AW21 -> 0 | BK21: =J21-AX21 -> 0 | BL21: =K21-AY21 -> 0 | ... BP21: =O21-BC21 -> 9.8504749 | BT21: Wagering & Media | BU21: =FY!C18 -> 801.3 | BV21: =FY!D18 -> 775 | BW21: =FY!E18 -> 758.2 | BX21: =FY!F18 -> 915.9 | BY21: =FY!G18 -> 953.2 | BZ21: =FY!H18 -> 1001.5534 | CA21: =FY!I18 -> 1008.6638 | CB21: =FY!J18 -> 1017.4923 | CC21: =FY!K18 -> 1040.0833 | CE21: =BX21 -> 915.9 | CF21: 953.2 | CG21: =CF21/CE21-1 -> 0.04072497 | CH21: =BY21 -> 953.2 | CI21: =$CF21/CH21-1 -> 0 | CJ21: =CN21 -> 941.10641 | CK21: =$CF21/CJ21-1 -> 0.012850393 | CN21: =DG21 -> 941.10641 | CP21: TAH_AU | CQ21: Contribution - Wagering and media - Operating | CR21: consensus.vaactuals | CS21: =_xll.VAData($AB21,CS$3,$AC21,$AD21) -> 801.3 | CT21: =_xll.VAData($AB21,CT$3,$AC21,$AD21) -> 775.1 | CU21: =_xll.VAData($AB21,CU$3,$AC21,$AD21) -> 758.2 | CV21: =_xll.VAData($AB21,CV$3,$AC21,$AD21) -> 915.9 | CW21: =_xll.VAData($AB21,CW$3,$AC21,$AD21) -> 953.2 | CX21: =_xll.VAData($AB21,CX$3,$AC21,$AD21) -> 1010.3523 | CY21: =_xll.VAData($AB21,CY$3,$AC21,$AD21) -> 1040.9467 | CZ21: =_xll.VAData($AB21,CZ$3,$AC21,$AD21) -> 1062.9216 | DA21: =_xll.VAData($AB21,DA$3,$AC21,$AD21) -> 1085.1102 | DC21: 801.3 | DD21: 775.1 | DE21: 758.2 | DF21: 915.9 | DG21: 941.10641 | DH21: 975.26254 | DI21: 1004.1256 | DJ21: 1028.1106 | DK21: 1052.2287 | DM21: =BU21-DC21 -> 0 | DN21: =BV21-DD21 -> -0.1 | DO21: =BW21-DE21 -> 0 | DP21: =BX21-DF21 -> 0 | DQ21: =BY21-DG21 -> 12.093587 | DR21: =BZ21-DH21 -> 26.290899 | DS21: =CA21-DI21 -> 4.5381679 | DT21: =CB21-DJ21 -> -10.618372 | DU21: =CC21-DK21 -> -12.145444
C22: Integrity Services | D22: =HY!M280 -> 74.6 | E22: =HY!N280 -> 111.7 | F22: =HY!O280 -> 101.4 | G22: =HY!P280 -> 91.8 | H22: =HY!Q280 -> 79.9 | I22: =HY!R280 -> 81.8 | J22: =HY!S280 -> 86.3 | K22: =HY!T280 -> 86.5 | ... O22: =HY!X280 -> 91.225 | Q22: =J22 -> 86.3 | R22: 90.2 | S22: =R22/Q22-1 -> 0.045191194 | T22: =L22 -> 90.2 | U22: =$R22/T22-1 -> 0 | V22: =Z22 -> 88.748552 | W22: =$R22/V22-1 -> 0.016354609 | Z22: =AZ22 -> 88.748552 | AB22: TAH_AU | AC22: Contribution - Gaming Services - Operating | AD22: consensus.vaactuals | AE22: =_xll.VAData($AB22,AE$3,$AC22,$AD22) -> 74.6 | AF22: =_xll.VAData($AB22,AF$3,$AC22,$AD22) -> 111.7 | AG22: =_xll.VAData($AB22,AG$3,$AC22,$AD22) -> 101.4 | AH22: =_xll.VAData($AB22,AH$3,$AC22,$AD22) -> 91.8 | AI22: =_xll.VAData($AB22,AI$3,$AC22,$AD22) -> 79.9 | AJ22: =_xll.VAData($AB22,AJ$3,$AC22,$AD22) -> 81.8 | AK22: =_xll.VAData($AB22,AK$3,$AC22,$AD22) -> 86.3 | AL22: =_xll.VAData($AB22,AL$3,$AC22,$AD22) -> 86.5 | ... AP22: =_xll.VAData($AB22,AP$3,$AC22,$AD22) -> 91.158633 | AR22: 74.6 | AS22: 111.7 | AT22: 101.4 | AU22: 91.8 | AV22: 91.7 | AW22: 81.8 | AX22: 86.3 | AY22: 86.5 | AZ22: 88.748552 | BA22: 88.841533 | BB22: 91.343291 | BC22: 91.410007 | BE22: =D22-AR22 -> 0 | BF22: =E22-AS22 -> 0 | BG22: =F22-AT22 -> 0 | BH22: =G22-AU22 -> 0 | BI22: =H22-AV22 -> -11.8 | BJ22: =I22-AW22 -> 0 | BK22: =J22-AX22 -> 0 | BL22: =K22-AY22 -> 0 | ... BP22: =O22-BC22 -> -0.18500706 | BT22: Integrity Services | BU22: =FY!C19 -> 186.3 | BV22: =FY!D19 -> 193.2 | BW22: =FY!E19 -> 161.7 | BX22: =FY!F19 -> 172.8 | BY22: =FY!G19 -> 179.2 | BZ22: =FY!H19 -> 184.27653 | CA22: =FY!I19 -> 188.88344 | CB22: =FY!J19 -> 194.54995 | CC22: =FY!K19 -> 200.38644 | CE22: =BX22 -> 172.8 | CF22: 179.2 | CG22: =CF22/CE22-1 -> 0.037037037 | CH22: =BY22 -> 179.2 | CI22: =$CF22/CH22-1 -> 0 | CJ22: =CN22 -> 179.90309 | CK22: =$CF22/CJ22-1 -> -0.0039081835 | CN22: =DG22 -> 179.90309 | CP22: TAH_AU | CQ22: Contribution - Gaming Services - Operating | CR22: consensus.vaactuals | CS22: =_xll.VAData($AB22,CS$3,$AC22,$AD22) -> 186.3 | CT22: =_xll.VAData($AB22,CT$3,$AC22,$AD22) -> 193.2 | CU22: =_xll.VAData($AB22,CU$3,$AC22,$AD22) -> 161.7 | CV22: =_xll.VAData($AB22,CV$3,$AC22,$AD22) -> 172.8 | CW22: =_xll.VAData($AB22,CW$3,$AC22,$AD22) -> 179.2 | CX22: =_xll.VAData($AB22,CX$3,$AC22,$AD22) -> 183.79018 | CY22: =_xll.VAData($AB22,CY$3,$AC22,$AD22) -> 188.63159 | CZ22: =_xll.VAData($AB22,CZ$3,$AC22,$AD22) -> 193.51463 | DA22: =_xll.VAData($AB22,DA$3,$AC22,$AD22) -> 198.63536 | DC22: 186.3 | DD22: 193.2 | DE22: 161.7 | DF22: 172.8 | DG22: 179.90309 | DH22: 185.61277 | DI22: 190.85001 | DJ22: 195.97781 | DK22: 201.38644 | DM22: =BU22-DC22 -> 0 | DN22: =BV22-DD22 -> 0 | DO22: =BW22-DE22 -> 0 | DP22: =BX22-DF22 -> 0 | DQ22: =BY22-DG22 -> -0.70309431 | DR22: =BZ22-DH22 -> -1.3362433 | DS22: =CA22-DI22 -> -1.9665702 | DT22: =CB22-DJ22 -> -1.427868 | DU22: =CC22-DK22 -> -0.99999557
C23: Variable Contribution | D23: =HY!M282 -> 469.5 | E23: =HY!N282 -> 517.7 | F23: =HY!O282 -> 499.7 | G23: =HY!P282 -> 468.7 | H23: =HY!Q282 -> 485.6 | I23: =HY!R282 -> 446.1 | J23: =HY!S282 -> 544.4 | K23: =HY!T282 -> 544.3 | ... O23: =HY!X282 -> 593.41689 | Q23: =J23 -> 544.4 | R23: 567.6 | S23: =R23/Q23-1 -> 0.042615724 | T23: =L23 -> 567.6 | U23: =$R23/T23-1 -> 0 | V23: =Z23 -> 561.08303 | W23: =$R23/V23-1 -> 0.011614976 | Z23: =AZ23 -> 561.08303 | AB23: TAH_AU | AE23: =SUM(AE21:AE22) -> 469.5 | AF23: =SUM(AF21:AF22) -> 518.1 | AG23: =SUM(AG21:AG22) -> 499.7 | AH23: =SUM(AH21:AH22) -> 468.6 | AI23: =SUM(AI21:AI22) -> 473.8 | AJ23: =SUM(AJ21:AJ22) -> 446.1 | AK23: =SUM(AK21:AK22) -> 544.4 | AL23: =SUM(AL21:AL22) -> 544.3 | ... AP23: =SUM(AP21:AP22) -> 585.3023 | AR23: 469.5 | AS23: 518.1 | AT23: 499.7 | AU23: 468.6 | AV23: 485.6 | AW23: 446.1 | AX23: 544.4 | AY23: 544.3 | AZ23: 561.08303 | BA23: 552.8168 | BB23: 595.24632 | BC23: 566.85142 | BE23: =D23-AR23 -> 0 | BF23: =E23-AS23 -> -0.4 | BG23: =F23-AT23 -> 0 | BH23: =G23-AU23 -> 0.1 | BI23: =H23-AV23 -> 0 | BJ23: =I23-AW23 -> 0 | BK23: =J23-AX23 -> 0 | BL23: =K23-AY23 -> 0 | ... BP23: =O23-BC23 -> 26.565468 | BT23: Variable Contribution | BU23: =FY!C21 -> 987.2 | BV23: =FY!D21 -> 968.4 | BW23: =FY!E21 -> 931.7 | BX23: =FY!F21 -> 1088.7 | BY23: =FY!G21 -> 1132.4 | BZ23: =FY!H21 -> 1202.73 | CA23: =FY!I21 -> 1272.6302 | CB23: =FY!J21 -> 1297.1677 | CC23: =FY!K21 -> 1328.149 | CE23: =BX23 -> 1088.7 | CF23: 1132.4 | CG23: =CF23/CE23-1 -> 0.040139616 | CH23: =BY23 -> 1132.4 | CI23: =$CF23/CH23-1 -> 0 | CJ23: =CN23 -> 1121.0095 | CK23: =$CF23/CJ23-1 -> 0.010160924 | CN23: =SUM(CN21:CN22) -> 1121.0095 | CP23: TAH_AU | DM23: =BU23-DC23 -> 987.2 | DN23: =BV23-DD23 -> 968.4 | DO23: =BW23-DE23 -> 931.7 | DP23: =BX23-DF23 -> 1088.7 | DQ23: =BY23-DG23 -> 1132.4 | DR23: =BZ23-DH23 -> 1202.73 | DS23: =CA23-DI23 -> 1272.6302 | DT23: =CB23-DJ23 -> 1297.1677 | DU23: =CC23-DK23 -> 1328.149
C25: Wagering & Media | D25: =HY!M285 -> -257 | E25: =HY!N285 -> -257.3 | F25: =HY!O285 -> -243.9 | G25: =HY!P285 -> -223.1 | H25: =HY!Q285 -> -259.9 | I25: =HY!R285 -> -247.1 | J25: =HY!S285 -> -301.4 | K25: =HY!T285 -> -285.4 | ... O25: =HY!X285 -> -305.0005 | Q25: =J25 -> -301.4 | R25: -296 | S25: =R25/Q25-1 -> -0.01791639 | T25: =L25 -> -296 | U25: =$R25/T25-1 -> 0 | V25: =Z25 -> -309.08717 | W25: =$R25/V25-1 -> -0.042341356 | Z25: =AZ25 -> -309.08717 | AB25: TAH_AU | AC25: Operating expense excl depreciation - Wagering & media - Operating | AD25: consensus.vaactuals | AE25: =-_xll.VAData($AB25,AE$3,$AC25,$AD25) -> -257 | AF25: =-_xll.VAData($AB25,AF$3,$AC25,$AD25) -> -257.3 | AG25: =-_xll.VAData($AB25,AG$3,$AC25,$AD25) -> -243.9 | AH25: =-_xll.VAData($AB25,AH$3,$AC25,$AD25) -> -223.1 | AI25: =-_xll.VAData($AB25,AI$3,$AC25,$AD25) -> -259.9 | AJ25: =-_xll.VAData($AB25,AJ$3,$AC25,$AD25) -> -247.1 | AK25: =-_xll.VAData($AB25,AK$3,$AC25,$AD25) -> -301.4 | AL25: =-_xll.VAData($AB25,AL$3,$AC25,$AD25) -> -285.4 | ... AP25: =-_xll.VAData($AB25,AP$3,$AC25,$AD25) -> -307.53442 | AR25: -257 | AS25: -257.3 | AT25: -243.9 | AU25: -223.1 | AV25: -259.9 | AW25: -247.1 | AX25: -301.4 | AY25: -285.4 | AZ25: -309.08717 | BA25: -289.09663 | BB25: -318.07825 | BC25: -296.24051 | BE25: =D25-AR25 -> 0 | BF25: =E25-AS25 -> 0 | BG25: =F25-AT25 -> 0 | BH25: =G25-AU25 -> 0 | BI25: =H25-AV25 -> 0 | BJ25: =I25-AW25 -> 0 | BK25: =J25-AX25 -> 0 | BL25: =K25-AY25 -> 0 | ... BP25: =O25-BC25 -> -8.7599903 | BT25: Wagering & Media | BU25: =FY!C23 -> -514.3 | BV25: =FY!D23 -> -467 | BW25: =FY!E23 -> -507 | BX25: =FY!F23 -> -586.8 | BY25: =FY!G23 -> -591.4 | BZ25: =FY!H23 -> -611.0645 | CA25: =FY!I23 -> -629.39643 | CB25: =FY!J23 -> -648.27833 | CC25: =FY!K23 -> -667.72668 | CE25: =BX25 -> -586.8 | CF25: -591.4 | CG25: =CF25/CE25-1 -> 0.0078391275 | CH25: =BY25 -> -591.4 | CI25: =$CF25/CH25-1 -> 0 | CJ25: =CN25 -> -586.78344 | CK25: =$CF25/CJ25-1 -> 0.0078675666 | CN25: =DG25 -> -586.78344 | CP25: TAH_AU | CQ25: Operating expense excl depreciation - Wagering & media - Operating | CR25: consensus.vaactuals | CS25: =-_xll.VAData($AB25,CS$3,$AC25,$AD25) -> -514.3 | CT25: =-_xll.VAData($AB25,CT$3,$AC25,$AD25) -> -467 | CU25: =-_xll.VAData($AB25,CU$3,$AC25,$AD25) -> -507 | CV25: =-_xll.VAData($AB25,CV$3,$AC25,$AD25) -> -586.8 | CW25: =-_xll.VAData($AB25,CW$3,$AC25,$AD25) -> -591.4 | CX25: =-_xll.VAData($AB25,CX$3,$AC25,$AD25) -> -614.27169 | CY25: =-_xll.VAData($AB25,CY$3,$AC25,$AD25) -> -632.20707 | CZ25: =-_xll.VAData($AB25,CZ$3,$AC25,$AD25) -> -644.11474 | DA25: =-_xll.VAData($AB25,DA$3,$AC25,$AD25) -> -655.01183 | DC25: -514.3 | DD25: -467 | DE25: -507 | DF25: -586.8 | DG25: -586.78344 | DH25: -603.63728 | DI25: -618.89226 | DJ25: -632.12602 | DK25: -643.80172 | DM25: =BU25-DC25 -> 0 | DN25: =BV25-DD25 -> 0 | DO25: =BW25-DE25 -> 0 | DP25: =BX25-DF25 -> 0 | DQ25: =BY25-DG25 -> -4.6165578 | DR25: =BZ25-DH25 -> -7.4272246 | DS25: =CA25-DI25 -> -10.50417 | DT25: =CB25-DJ25 -> -16.152306 | DU25: =CC25-DK25 -> -23.924962
C26: Integrity Services | D26: =HY!M286 -> -55 | E26: =HY!N286 -> -58.1 | F26: =HY!O286 -> -58.5 | G26: =HY!P286 -> -51.6 | H26: =HY!Q286 -> -51.6 | I26: =HY!R286 -> -51.1 | J26: =HY!S286 -> -52.8 | K26: =HY!T286 -> -57.6 | ... O26: =HY!X286 -> -56.209975 | Q26: =J26 -> -52.8 | R26: -54.2 | S26: =R26/Q26-1 -> 0.026515152 | T26: =L26 -> -54.2 | U26: =$R26/T26-1 -> 0 | V26: =Z26 -> -56.193762 | W26: =$R26/V26-1 -> -0.035480129 | Z26: =AZ26 -> -56.193762 | AB26: TAH_AU | AC26: Operating expense excl depreciation - Gaming Services - Operating | AD26: consensus.vaactuals | AE26: =-_xll.VAData($AB26,AE$3,$AC26,$AD26) -> -55 | AF26: =-_xll.VAData($AB26,AF$3,$AC26,$AD26) -> -58.1 | AG26: =-_xll.VAData($AB26,AG$3,$AC26,$AD26) -> -58.5 | AH26: =-_xll.VAData($AB26,AH$3,$AC26,$AD26) -> -51.6 | AI26: =-_xll.VAData($AB26,AI$3,$AC26,$AD26) -> -51.6 | AJ26: =-_xll.VAData($AB26,AJ$3,$AC26,$AD26) -> -51.1 | AK26: =-_xll.VAData($AB26,AK$3,$AC26,$AD26) -> -52.8 | AL26: =-_xll.VAData($AB26,AL$3,$AC26,$AD26) -> -57.6 | ... AP26: =-_xll.VAData($AB26,AP$3,$AC26,$AD26) -> -56.51604 | AR26: -55 | AS26: -58.1 | AT26: -58.5 | AU26: -51.6 | AV26: -55.9 | AW26: -51.1 | AX26: -52.8 | AY26: -57.6 | AZ26: -56.193762 | BA26: -58.054477 | BB26: -57.687875 | BC26: -59.50671 | BE26: =D26-AR26 -> 0 | BF26: =E26-AS26 -> 0 | BG26: =F26-AT26 -> 0 | BH26: =G26-AU26 -> 0 | BI26: =H26-AV26 -> 4.3 | BJ26: =I26-AW26 -> 0 | BK26: =J26-AX26 -> 0 | BL26: =K26-AY26 -> 0 | ... BP26: =O26-BC26 -> 3.2967349 | BT26: Integrity Services | BU26: =FY!C24 -> -113.1 | BV26: =FY!D24 -> -110.1 | BW26: =FY!E24 -> -102.7 | BX26: =FY!F24 -> -110.4 | BY26: =FY!G24 -> -109.3 | BZ26: =FY!H24 -> -113.5454 | CA26: =FY!I24 -> -116.38403 | CB26: =FY!J24 -> -119.87556 | CC26: =FY!K24 -> -123.47182 | CE26: =BX26 -> -110.4 | CF26: -109.3 | CG26: =CF26/CE26-1 -> -0.0099637681 | CH26: =BY26 -> -109.3 | CI26: =$CF26/CH26-1 -> 0 | CJ26: =CN26 -> -111.38288 | CK26: =$CF26/CJ26-1 -> -0.018700152 | CN26: =DG26 -> -111.38288 | CP26: TAH_AU | CQ26: Operating expense excl depreciation - Gaming Services - Operating | CR26: consensus.vaactuals | CS26: =-_xll.VAData($AB26,CS$3,$AC26,$AD26) -> -113.1 | CT26: =-_xll.VAData($AB26,CT$3,$AC26,$AD26) -> -110.1 | CU26: =-_xll.VAData($AB26,CU$3,$AC26,$AD26) -> -102.7 | CV26: =-_xll.VAData($AB26,CV$3,$AC26,$AD26) -> -110.4 | CW26: =-_xll.VAData($AB26,CW$3,$AC26,$AD26) -> -109.3 | CX26: =-_xll.VAData($AB26,CX$3,$AC26,$AD26) -> -112.85154 | CY26: =-_xll.VAData($AB26,CY$3,$AC26,$AD26) -> -115.37988 | CZ26: =-_xll.VAData($AB26,CZ$3,$AC26,$AD26) -> -117.9385 | DA26: =-_xll.VAData($AB26,DA$3,$AC26,$AD26) -> -120.6119 | DC26: -113.1 | DD26: -110.1 | DE26: -102.7 | DF26: -110.4 | DG26: -111.38288 | DH26: -114.7552 | DI26: -117.58142 | DJ26: -120.3967 | DK26: -123.32601 | DM26: =BU26-DC26 -> 0 | DN26: =BV26-DD26 -> 0 | DO26: =BW26-DE26 -> 0 | DP26: =BX26-DF26 -> 0 | DQ26: =BY26-DG26 -> 2.0828768 | DR26: =BZ26-DH26 -> 1.209805 | DS26: =CA26-DI26 -> 1.1973845 | DT26: =CB26-DJ26 -> 0.52114137 | DU26: =CC26-DK26 -> -0.14581396
C27: Opex | D27: =HY!M288 -> -310.5 | E27: =HY!N288 -> -316.1 | F27: =HY!O288 -> -303.1 | G27: =HY!P288 -> -274.3 | H27: =HY!Q288 -> -315.8 | I27: =HY!R288 -> -298.2 | J27: =HY!S288 -> -354.2 | K27: =HY!T288 -> -343 | ... O27: =HY!X288 -> -372.91047 | Q27: =J27 -> -354.2 | R27: -350.2 | S27: =R27/Q27-1 -> -0.011293055 | T27: =L27 -> -350.2 | U27: =$R27/T27-1 -> 0 | V27: =Z27 -> -365.28093 | W27: =$R27/V27-1 -> -0.041285845 | Z27: =AZ27 -> -365.28093 | AB27: TAH_AU | AD27: consensus.vaactuals | AE27: =SUM(AE25:AE26) -> -312 | AF27: =SUM(AF25:AF26) -> -315.4 | AG27: =SUM(AG25:AG26) -> -302.4 | AH27: =SUM(AH25:AH26) -> -274.7 | AI27: =SUM(AI25:AI26) -> -311.5 | AJ27: =SUM(AJ25:AJ26) -> -298.2 | AK27: =SUM(AK25:AK26) -> -354.2 | AL27: =SUM(AL25:AL26) -> -343 | ... AP27: =SUM(AP25:AP26) -> -364.05046 | AR27: -312 | AS27: -315.4 | AT27: -302.4 | AU27: -274.7 | AV27: -315.8 | AW27: -298.2 | AX27: -354.2 | AY27: -343 | AZ27: -365.28093 | BA27: -347.15111 | BB27: -375.76612 | BC27: -355.74722 | BE27: =D27-AR27 -> 1.5 | BF27: =E27-AS27 -> -0.7 | BG27: =F27-AT27 -> -0.7 | BH27: =G27-AU27 -> 0.4 | BI27: =H27-AV27 -> 0 | BJ27: =I27-AW27 -> 0 | BK27: =J27-AX27 -> 0 | BL27: =K27-AY27 -> 0 | ... BP27: =O27-BC27 -> -17.163255 | BT27: Opex | BU27: =FY!C26 -> -626.6 | BV27: =FY!D26 -> -577.4 | BW27: =FY!E26 -> -614 | BX27: =FY!F26 -> -697.2 | BY27: =FY!G26 -> -700.7 | BZ27: =FY!H26 -> -736.3099 | CA27: =FY!I26 -> -786.98447 | CB27: =FY!J26 -> -802.804 | CC27: =FY!K26 -> -826.88812 | CE27: =BX27 -> -697.2 | CF27: -700.7 | CG27: =CF27/CE27-1 -> 0.0050200803 | CH27: =BY27 -> -700.7 | CI27: =$CF27/CH27-1 -> 0 | CJ27: =CN27 -> -698.16632 | CK27: =$CF27/CJ27-1 -> 0.0036290508 | CN27: =SUM(CN25:CN26) -> -698.16632 | CP27: TAH_AU | CR27: consensus.vaactuals | DM27: =BU27-DC27 -> -626.6 | DN27: =BV27-DD27 -> -577.4 | DO27: =BW27-DE27 -> -614 | DP27: =BX27-DF27 -> -697.2 | DQ27: =BY27-DG27 -> -700.7 | DR27: =BZ27-DH27 -> -736.3099 | DS27: =CA27-DI27 -> -786.98447 | DT27: =CB27-DJ27 -> -802.804 | DU27: =CC27-DK27 -> -826.88812
C29: Wagering & Media | D29: =HY!M292 -> 137.9 | E29: =HY!N292 -> 149.1 | F29: =HY!O292 -> 154.4 | G29: =HY!P292 -> 153.6 | H29: =HY!Q292 -> 134 | I29: =HY!R292 -> 117.2 | J29: =HY!S292 -> 156.7 | K29: =HY!T292 -> 172.4 | ... O29: =HY!X292 -> 180.29139 | Q29: =J29 -> 156.7 | R29: 181.4 | S29: =R29/Q29-1 -> 0.15762604 | T29: =L29 -> 181.4 | U29: =$R29/T29-1 -> 0 | V29: =Z29 -> 163.08897 | W29: =$R29/V29-1 -> 0.11227635 | Z29: =AZ29 -> 163.08897 | AB29: TAH_AU | AC29: EBITDA - Operating - Wagering & media | AD29: consensus.vaactuals | AE29: =_xll.VAData($AB29,AE$3,$AC29,$AD29) -> 137.9 | AF29: =_xll.VAData($AB29,AF$3,$AC29,$AD29) -> 149.1 | AG29: =_xll.VAData($AB29,AG$3,$AC29,$AD29) -> 154.4 | AH29: =_xll.VAData($AB29,AH$3,$AC29,$AD29) -> 153.6 | AI29: =_xll.VAData($AB29,AI$3,$AC29,$AD29) -> 134 | AJ29: =_xll.VAData($AB29,AJ$3,$AC29,$AD29) -> 117.2 | AK29: =_xll.VAData($AB29,AK$3,$AC29,$AD29) -> 156.7 | AL29: =_xll.VAData($AB29,AL$3,$AC29,$AD29) -> 172.4 | ... AP29: =_xll.VAData($AB29,AP$3,$AC29,$AD29) -> 183.23248 | AR29: 137.9 | AS29: 149.1 | AT29: 154.4 | AU29: 153.6 | AV29: 134 | AW29: 117.2 | AX29: 156.7 | AY29: 172.4 | AZ29: 163.08897 | BA29: 172.8015 | BB29: 183.52273 | BC29: 176.90265 | BE29: =D29-AR29 -> 0 | BF29: =E29-AS29 -> 0 | BG29: =F29-AT29 -> 0 | BH29: =G29-AU29 -> 0 | BI29: =H29-AV29 -> 0 | BJ29: =I29-AW29 -> 0 | BK29: =J29-AX29 -> 0 | BL29: =K29-AY29 -> 0 | ... BP29: =O29-BC29 -> 3.3887396 | BT29: Wagering & Media | BU29: =FY!C30 -> 287 | BV29: =FY!D30 -> 308 | BW29: =FY!E30 -> 251.2 | BX29: =FY!F30 -> 329.1 | BY29: =FY!G30 -> 361.8 | BZ29: =FY!H30 -> 390.48893 | CA29: =FY!I30 -> 379.26736 | CB29: =FY!J30 -> 369.21395 | CC29: =FY!K30 -> 372.3566 | CE29: =BX29 -> 329.1 | CF29: 361.8 | CG29: =CF29/CE29-1 -> 0.099361896 | CH29: =BY29 -> 361.8 | CI29: =$CF29/CH29-1 -> 0 | CJ29: =CN29 -> 350.46778 | CK29: =$CF29/CJ29-1 -> 0.032334546 | CN29: =DG29 -> 350.46778 | CP29: TAH_AU | CQ29: EBITDA - Operating - Wagering & media | CR29: consensus.vaactuals | CS29: =_xll.VAData($AB29,CS$3,$AC29,$AD29) -> 287 | CT29: =_xll.VAData($AB29,CT$3,$AC29,$AD29) -> 308 | CU29: =_xll.VAData($AB29,CU$3,$AC29,$AD29) -> 251.2 | CV29: =_xll.VAData($AB29,CV$3,$AC29,$AD29) -> 329.1 | CW29: =_xll.VAData($AB29,CW$3,$AC29,$AD29) -> 361.8 | CX29: =_xll.VAData($AB29,CX$3,$AC29,$AD29) -> 387.5186 | CY29: =_xll.VAData($AB29,CY$3,$AC29,$AD29) -> 398.00595 | CZ29: =_xll.VAData($AB29,CZ$3,$AC29,$AD29) -> 407.15707 | DA29: =_xll.VAData($AB29,DA$3,$AC29,$AD29) -> 417.41205 | DC29: 287 | DD29: 308 | DE29: 251.2 | DF29: 329.1 | DG29: 350.46778 | DH29: 366.36499 | DI29: 377.92365 | DJ29: 387.78201 | DK29: 399.17646 | DM29: =BU29-DC29 -> 0 | DN29: =BV29-DD29 -> 0 | DO29: =BW29-DE29 -> 0 | DP29: =BX29-DF29 -> 0 | DQ29: =BY29-DG29 -> 11.332217 | DR29: =BZ29-DH29 -> 24.123942 | DS29: =CA29-DI29 -> 1.343714 | DT29: =CB29-DJ29 -> -18.568063 | DU29: =CC29-DK29 -> -26.819861
C30: Integrity Services | D30: =HY!M293 -> 19.6 | E30: =HY!N293 -> 53.6 | F30: =HY!O293 -> 42.9 | G30: =HY!P293 -> 40.2 | H30: =HY!Q293 -> 28.3 | I30: =HY!R293 -> 30.7 | J30: =HY!S293 -> 33.5 | K30: =HY!T293 -> 28.9 | ... O30: =HY!X293 -> 35.015025 | Q30: =J30 -> 33.5 | R30: 36 | S30: =R30/Q30-1 -> 0.074626866 | T30: =L30 -> 36 | U30: =$R30/T30-1 -> 0 | V30: =Z30 -> 32.767105 | W30: =$R30/V30-1 -> 0.09866283 | Z30: =AZ30 -> 32.767105 | AB30: TAH_AU | AC30: EBITDA - Operating - Gaming services | AD30: consensus.vaactuals | AE30: =_xll.VAData($AB30,AE$3,$AC30,$AD30) -> 19.6 | AF30: =_xll.VAData($AB30,AF$3,$AC30,$AD30) -> 53.6 | AG30: =_xll.VAData($AB30,AG$3,$AC30,$AD30) -> 42.9 | AH30: =_xll.VAData($AB30,AH$3,$AC30,$AD30) -> 40.2 | AI30: =_xll.VAData($AB30,AI$3,$AC30,$AD30) -> 28.3 | AJ30: =_xll.VAData($AB30,AJ$3,$AC30,$AD30) -> 30.7 | AK30: =_xll.VAData($AB30,AK$3,$AC30,$AD30) -> 33.5 | AL30: =_xll.VAData($AB30,AL$3,$AC30,$AD30) -> 28.9 | ... AP30: =_xll.VAData($AB30,AP$3,$AC30,$AD30) -> 34.517045 | AR30: 19.6 | AS30: 53.6 | AT30: 42.9 | AU30: 40.2 | AV30: 35.8 | AW30: 30.7 | AX30: 33.5 | AY30: 28.9 | AZ30: 32.767105 | BA30: 31.006173 | BB30: 33.810396 | BC30: 32.064233 | BE30: =D30-AR30 -> 0 | BF30: =E30-AS30 -> 0 | BG30: =F30-AT30 -> 0 | BH30: =G30-AU30 -> 0 | BI30: =H30-AV30 -> -7.5 | BJ30: =I30-AW30 -> 0 | BK30: =J30-AX30 -> 0 | BL30: =K30-AY30 -> 0 | ... BP30: =O30-BC30 -> 2.9507918 | BT30: Integrity Services | BU30: =FY!C31 -> 73.2 | BV30: =FY!D31 -> 83.1 | BW30: =FY!E31 -> 59 | BX30: =FY!F31 -> 62.4 | BY30: =FY!G31 -> 69.9 | BZ30: =FY!H31 -> 70.731129 | CA30: =FY!I31 -> 72.499408 | CB30: =FY!J31 -> 74.67439 | CC30: =FY!K31 -> 76.914622 | CE30: =BX30 -> 62.4 | CF30: 69.9 | CG30: =CF30/CE30-1 -> 0.12019231 | CH30: =BY30 -> 69.9 | CI30: =$CF30/CH30-1 -> 0 | CJ30: =CN30 -> 68.433812 | CK30: =$CF30/CJ30-1 -> 0.021424906 | CN30: =DG30 -> 68.433812 | CP30: TAH_AU | CQ30: EBITDA - Operating - Gaming services | CR30: consensus.vaactuals | CS30: =_xll.VAData($AB30,CS$3,$AC30,$AD30) -> 73.2 | CT30: =_xll.VAData($AB30,CT$3,$AC30,$AD30) -> 83.1 | CU30: =_xll.VAData($AB30,CU$3,$AC30,$AD30) -> 59 | CV30: =_xll.VAData($AB30,CV$3,$AC30,$AD30) -> 62.4 | CW30: =_xll.VAData($AB30,CW$3,$AC30,$AD30) -> 69.9 | CX30: =_xll.VAData($AB30,CX$3,$AC30,$AD30) -> 70.691888 | CY30: =_xll.VAData($AB30,CY$3,$AC30,$AD30) -> 72.868839 | CZ30: =_xll.VAData($AB30,CZ$3,$AC30,$AD30) -> 75.058871 | DA30: =_xll.VAData($AB30,DA$3,$AC30,$AD30) -> 77.361237 | DC30: 73.2 | DD30: 83.1 | DE30: 59 | DF30: 62.4 | DG30: 68.433812 | DH30: 70.643597 | DI30: 72.92232 | DJ30: 75.115087 | DK30: 77.460728 | DM30: =BU30-DC30 -> 0 | DN30: =BV30-DD30 -> 0 | DO30: =BW30-DE30 -> 0 | DP30: =BX30-DF30 -> 0 | DQ30: =BY30-DG30 -> 1.466188 | DR30: =BZ30-DH30 -> 0.087532205 | DS30: =CA30-DI30 -> -0.42291273 | DT30: =CB30-DJ30 -> -0.44069685 | DU30: =CC30-DK30 -> -0.54610606
C31: EBITDA | D31: =HY!M295 -> 159 | E31: =HY!N295 -> 201.6 | F31: =HY!O295 -> 196.6 | G31: =HY!P295 -> 194.4 | H31: =HY!Q295 -> 169.8 | I31: =HY!R295 -> 147.9 | J31: =HY!S295 -> 190.2 | K31: =HY!T295 -> 201.3 | ... O31: =HY!X295 -> 220.50641 | Q31: =J31 -> 190.2 | R31: 217.4 | S31: =R31/Q31-1 -> 0.14300736 | T31: =L31 -> 217.4 | U31: =$R31/T31-1 -> 0 | V31: =Z31 -> 195.97401 | W31: =$R31/V31-1 -> 0.10933079 | Z31: =AZ31 -> 195.97401 | AB31: TAH_AU | AC31: EBITDA - Operating | AD31: consensus.vaactuals | AE31: =_xll.VAData($AB31,AE$3,$AC31,$AD31) -> 159 | AF31: =_xll.VAData($AB31,AF$3,$AC31,$AD31) -> 201.6 | AG31: =_xll.VAData($AB31,AG$3,$AC31,$AD31) -> 196.6 | AH31: =_xll.VAData($AB31,AH$3,$AC31,$AD31) -> 194.4 | AI31: =_xll.VAData($AB31,AI$3,$AC31,$AD31) -> 169.8 | AJ31: =_xll.VAData($AB31,AJ$3,$AC31,$AD31) -> 147.9 | AK31: =_xll.VAData($AB31,AK$3,$AC31,$AD31) -> 190.2 | AL31: =_xll.VAData($AB31,AL$3,$AC31,$AD31) -> 201.3 | ... AP31: =_xll.VAData($AB31,AP$3,$AC31,$AD31) -> 221.70116 | AR31: 159 | AS31: 201.6 | AT31: 196.6 | AU31: 194.4 | AV31: 169.8 | AW31: 147.9 | AX31: 190.2 | AY31: 201.3 | AZ31: 195.97401 | BA31: 205.36811 | BB31: 218.32381 | BC31: 211.06276 | BE31: =D31-AR31 -> 0 | BF31: =E31-AS31 -> 0 | BG31: =F31-AT31 -> 0 | BH31: =G31-AU31 -> 0 | BI31: =H31-AV31 -> 0 | BJ31: =I31-AW31 -> 0 | BK31: =J31-AX31 -> 0 | BL31: =K31-AY31 -> 0 | ... BP31: =O31-BC31 -> 9.4436556 | BT31: EBITDA | BU31: =FY!C33 -> 360.6 | BV31: =FY!D33 -> 391 | BW31: =FY!E33 -> 317.7 | BX31: =FY!F33 -> 391.5 | BY31: =FY!G33 -> 431.7 | BZ31: =FY!H33 -> 466.42006 | CA31: =FY!I33 -> 485.64577 | CB31: =FY!J33 -> 494.36371 | CC31: =FY!K33 -> 501.26086 | CE31: =BX31 -> 391.5 | CF31: 431.7 | CG31: =CF31/CE31-1 -> 0.10268199 | CH31: =BY31 -> 431.7 | CI31: =$CF31/CH31-1 -> 0 | CJ31: =CN31 -> 423.04047 | CK31: =$CF31/CJ31-1 -> 0.020469743 | CN31: =DG31 -> 423.04047 | CP31: TAH_AU | CQ31: EBITDA - Operating | CR31: consensus.vaactuals | CS31: =_xll.VAData($AB31,CS$3,$AC31,$AD31) -> 381.6 | CT31: =_xll.VAData($AB31,CT$3,$AC31,$AD31) -> 391 | CU31: =_xll.VAData($AB31,CU$3,$AC31,$AD31) -> 317.7 | CV31: =_xll.VAData($AB31,CV$3,$AC31,$AD31) -> 391.5 | CW31: =_xll.VAData($AB31,CW$3,$AC31,$AD31) -> 431.7 | CX31: =_xll.VAData($AB31,CX$3,$AC31,$AD31) -> 466.54104 | CY31: =_xll.VAData($AB31,CY$3,$AC31,$AD31) -> 489.5737 | CZ31: =_xll.VAData($AB31,CZ$3,$AC31,$AD31) -> 505.18115 | DA31: =_xll.VAData($AB31,DA$3,$AC31,$AD31) -> 518.4063 | DC31: 381.6 | DD31: 391 | DE31: 317.7 | DF31: 391.5 | DG31: 423.04047 | DH31: 440.67815 | DI31: 458.80963 | DJ31: 470.63364 | DK31: 483.28422 | DM31: =BU31-DC31 -> -21 | DN31: =BV31-DD31 -> 0 | DO31: =BW31-DE31 -> 0 | DP31: =BX31-DF31 -> 0 | DQ31: =BY31-DG31 -> 8.6595296 | DR31: =BZ31-DH31 -> 25.741919 | DS31: =CA31-DI31 -> 26.836143 | DT31: =CB31-DJ31 -> 23.730071 | DU31: =CC31-DK31 -> 17.976638
C33: Wagering & Media | Z33: -91.070612 | AB33: TAH_AU | AC33: Depreciation and amortization - Wagering & media | AD33: consensus.vaactuals | AE33: =-_xll.VAData($AB33,AE$3,$AC33,$AD33) -> -105.2 | AF33: =-_xll.VAData($AB33,AF$3,$AC33,$AD33) -> -109.8 | AG33: =-_xll.VAData($AB33,AG$3,$AC33,$AD33) -> -96.5 | AH33: =-_xll.VAData($AB33,AH$3,$AC33,$AD33) -> -95.3 | AI33: =-_xll.VAData($AB33,AI$3,$AC33,$AD33) -> -100.7 | AJ33: =-_xll.VAData($AB33,AJ$3,$AC33,$AD33) -> -80.2 | AK33: =-_xll.VAData($AB33,AK$3,$AC33,$AD33) -> -77.3 | AL33: =-_xll.VAData($AB33,AL$3,$AC33,$AD33) -> -83.6 | ... AP33: =-_xll.VAData($AB33,AP$3,$AC33,$AD33) -> -94.076916 | AR33: -105.2 | AS33: -109.8 | AT33: -96.5 | AU33: -95.3 | AV33: -100.7 | AW33: -80.2 | AX33: -77.3 | AY33: -83.6 | AZ33: -88.521205 | BA33: -87.849554 | BB33: -87.676956 | BC33: -87.730128 | BT33: Wagering & Media | CN33: =DG33 -> -172.92966 | CP33: TAH_AU | CQ33: Depreciation and amortization - Wagering & media | CR33: consensus.vaactuals | CS33: =-_xll.VAData($AB33,CS$3,$AC33,$AD33) -> -215 | CT33: =-_xll.VAData($AB33,CT$3,$AC33,$AD33) -> -191.8 | CU33: =-_xll.VAData($AB33,CU$3,$AC33,$AD33) -> -180.9 | CV33: =-_xll.VAData($AB33,CV$3,$AC33,$AD33) -> -160.9 | CW33: =-_xll.VAData($AB33,CW$3,$AC33,$AD33) -> -170.6 | CX33: =-_xll.VAData($AB33,CX$3,$AC33,$AD33) -> -187.22822 | CY33: =-_xll.VAData($AB33,CY$3,$AC33,$AD33) -> -190.69892 | CZ33: =-_xll.VAData($AB33,CZ$3,$AC33,$AD33) -> -191.78459 | DA33: =-_xll.VAData($AB33,DA$3,$AC33,$AD33) -> -192.68213 | DC33: -215 | DD33: -191.8 | DE33: -180.9 | DF33: -160.9 | DG33: -172.92966 | DH33: -173.29548 | DI33: -175.96894 | DJ33: -176.80913 | DK33: -177.6618
C34: Integrity Services | Z34: -17.66849 | AB34: TAH_AU | AC34: Depreciation and amortization - Gaming services | AD34: consensus.vaactuals | AE34: =-_xll.VAData($AB34,AE$3,$AC34,$AD34) -> -37.5 | AF34: =-_xll.VAData($AB34,AF$3,$AC34,$AD34) -> -33.9 | AG34: =-_xll.VAData($AB34,AG$3,$AC34,$AD34) -> -26.9 | AH34: =-_xll.VAData($AB34,AH$3,$AC34,$AD34) -> -21.8 | AI34: =-_xll.VAData($AB34,AI$3,$AC34,$AD34) -> -18.7 | AJ34: =-_xll.VAData($AB34,AJ$3,$AC34,$AD34) -> -20.3 | AK34: =-_xll.VAData($AB34,AK$3,$AC34,$AD34) -> -20.2 | AL34: =-_xll.VAData($AB34,AL$3,$AC34,$AD34) -> -21.7 | ... AP34: =-_xll.VAData($AB34,AP$3,$AC34,$AD34) -> -21.025934 | AR34: -37.5 | AS34: -33.9 | AT34: -26.9 | AU34: -21.8 | AV34: -19.1 | AW34: -20.3 | AX34: -20.2 | AY34: -21.7 | AZ34: -20.925868 | BA34: -21.550109 | BB34: -21.371317 | BC34: -22.044559 | BT34: Integrity Services | CN34: =DG34 -> -42.275217 | CP34: TAH_AU | CQ34: Depreciation and amortization - Gaming services | CR34: consensus.vaactuals | CS34: =-_xll.VAData($AB34,CS$3,$AC34,$AD34) -> -71.4 | CT34: =-_xll.VAData($AB34,CT$3,$AC34,$AD34) -> -48.7 | CU34: =-_xll.VAData($AB34,CU$3,$AC34,$AD34) -> -39 | CV34: =-_xll.VAData($AB34,CV$3,$AC34,$AD34) -> -41.9 | CW34: =-_xll.VAData($AB34,CW$3,$AC34,$AD34) -> -42.4 | CX34: =-_xll.VAData($AB34,CX$3,$AC34,$AD34) -> -42.509549 | CY34: =-_xll.VAData($AB34,CY$3,$AC34,$AD34) -> -42.814856 | CZ34: =-_xll.VAData($AB34,CZ$3,$AC34,$AD34) -> -43.323012 | DA34: =-_xll.VAData($AB34,DA$3,$AC34,$AD34) -> -44.046064 | DC34: -71.4 | DD34: -48.7 | DE34: -39 | DF34: -41.9 | DG34: -42.275217 | DH34: -43.366179 | DI34: -44.108172 | DJ34: -44.835332 | DK34: -45.7149
C35: D&A | D35: =HY!M301 -> -142.7 | E35: =HY!N301 -> -143.7 | F35: =HY!O301 -> -123.4 | G35: =HY!P301 -> -117.1 | H35: =HY!Q301 -> -119.8 | I35: =HY!R301 -> -100.5 | J35: =HY!S301 -> -97.5 | K35: =HY!T301 -> -105.3 | ... O35: =HY!X301 -> -114.2 | Q35: =J35 -> -97.5 | S35: =R35/Q35-1 -> -1 | T35: =L35 -> -107.2 | U35: =$R35/T35-1 -> -1 | V35: =Z35 -> -108.7391 | W35: =$R35/V35-1 -> -1 | Z35: -108.7391 | AB35: TAH_AU | AC35: Depreciation and amortization - Operating | AD35: consensus.vaactuals | AE35: =-_xll.VAData($AB35,AE$3,$AC35,$AD35) -> -142.7 | AF35: =-_xll.VAData($AB35,AF$3,$AC35,$AD35) -> -143.7 | AG35: =-_xll.VAData($AB35,AG$3,$AC35,$AD35) -> -123.4 | AH35: =-_xll.VAData($AB35,AH$3,$AC35,$AD35) -> -117.1 | AI35: =-_xll.VAData($AB35,AI$3,$AC35,$AD35) -> -119.8 | AJ35: =-_xll.VAData($AB35,AJ$3,$AC35,$AD35) -> -100.5 | AK35: =-_xll.VAData($AB35,AK$3,$AC35,$AD35) -> -97.5 | AL35: =-_xll.VAData($AB35,AL$3,$AC35,$AD35) -> -105.3 | ... AP35: =-_xll.VAData($AB35,AP$3,$AC35,$AD35) -> -116.26445 | AR35: -142.7 | AS35: -143.7 | AT35: -123.4 | AU35: -117.1 | AV35: -119.8 | AW35: -100.5 | AX35: -97.5 | AY35: -105.3 | AZ35: -109.65592 | BA35: -109.73637 | BB35: -108.89114 | BC35: -109.74347 | BE35: =D35-AR35 -> 0 | BF35: =E35-AS35 -> 0 | BG35: =F35-AT35 -> 0 | BH35: =G35-AU35 -> 0 | BI35: =H35-AV35 -> 0 | BJ35: =I35-AW35 -> 0 | BK35: =J35-AX35 -> 0 | BL35: =K35-AY35 -> 0 | ... BP35: =O35-BC35 -> -4.4565293 | BT35: D&A | BU35: =FY!C47 -> -286.4 | BV35: =FY!D47 -> -240.5 | BW35: =FY!E47 -> -220.3 | BX35: =FY!F47 -> -202.8 | BY35: =FY!G47 -> -213 | BZ35: =FY!H47 -> -228.4 | CA35: =FY!I47 -> -223.4 | CB35: =FY!J47 -> -225.19597 | CC35: =FY!K47 -> -215.35471 | CE35: =BX35 -> -202.8 | CG35: =CF35/CE35-1 -> -1 | CH35: =BY35 -> -213 | CI35: =$CF35/CH35-1 -> -1 | CJ35: =CN35 -> -215.95051 | CK35: =$CF35/CJ35-1 -> -1 | CN35: =DG35 -> -215.95051 | CP35: TAH_AU | CQ35: Depreciation and amortization - Operating | CR35: consensus.vaactuals | CS35: =-_xll.VAData($AB35,CS$3,$AC35,$AD35) -> -286.4 | CT35: =-_xll.VAData($AB35,CT$3,$AC35,$AD35) -> -240.5 | CU35: =-_xll.VAData($AB35,CU$3,$AC35,$AD35) -> -220.3 | CV35: =-_xll.VAData($AB35,CV$3,$AC35,$AD35) -> -202.8 | CW35: =-_xll.VAData($AB35,CW$3,$AC35,$AD35) -> -213 | CX35: =-_xll.VAData($AB35,CX$3,$AC35,$AD35) -> -231.52416 | CY35: =-_xll.VAData($AB35,CY$3,$AC35,$AD35) -> -238.32715 | CZ35: =-_xll.VAData($AB35,CZ$3,$AC35,$AD35) -> -240.44391 | DA35: =-_xll.VAData($AB35,DA$3,$AC35,$AD35) -> -241.64497 | DC35: -286.4 | DD35: -240.5 | DE35: -220.3 | DF35: -202.8 | DG35: -215.95051 | DH35: -216.83039 | DI35: -220.96367 | DJ35: -221.7731 | DK35: -222.23934 | DM35: =BU35-DC35 -> 0 | DN35: =BV35-DD35 -> 0 | DO35: =BW35-DE35 -> 0 | DP35: =BX35-DF35 -> 0 | DQ35: =BY35-DG35 -> 2.9505103 | DR35: =BZ35-DH35 -> -11.569607 | DS35: =CD35-DI35 -> 220.96367 | DT35: =CE35-DJ35 -> 18.973105 | DU35: =CF35-DK35 -> 222.23934
C37: Wagering & Media | Z37: 106.52633 | AB37: TAH_AU | AC37: Operating income/(loss) - Operating - Wagering & media | AD37: consensus.vaactuals | AE37: 57.9 | AF37: =_xll.VAData($AB37,AF$3,$AC37,$AD37) -> 39.3 | AG37: 57.9 | AH37: =_xll.VAData($AB37,AH$3,$AC37,$AD37) -> 58.3 | AI37: =_xll.VAData($AB37,AI$3,$AC37,$AD37) -> 33.3 | AJ37: =_xll.VAData($AB37,AJ$3,$AC37,$AD37) -> 37 | AK37: =_xll.VAData($AB37,AK$3,$AC37,$AD37) -> 79.4 | AL37: =_xll.VAData($AB37,AL$3,$AC37,$AD37) -> 88.8 | AM37: =_xll.VAData($AB37,AM$3,$AC37,$AD37) -> 95.3 | AN37: =_xll.VAData($AB37,AN$3,$AC37,$AD37) -> 95.9 | AO37: =_xll.VAData($AB37,AO$3,$AC37,$AD37) -> 110.39589 | AP37: =_xll.VAData($AB37,AP$3,$AC37,$AD37) -> 89.523202 | AR37: 57.9 | AS37: 39.3 | AT37: 57.9 | AU37: 58.3 | AV37: 33.3 | AW37: 37 | AX37: 79.4 | AY37: 88.8 | AZ37: 74.358824 | BA37: 84.694989 | BB37: 94.74099 | BC37: 89.574316 | BT37: Wagering & Media | CN37: =DG37 -> 177.32625 | CP37: TAH_AU | CQ37: Operating income/(loss) - Operating - Wagering & media | CR37: consensus.vaactuals | CS37: 57.9 | CT37: =_xll.VAData($AB37,CT$3,$AC37,$AD37) -> 116.2 | CU37: 57.9 | CV37: =_xll.VAData($AB37,CV$3,$AC37,$AD37) -> 168.2 | CW37: =_xll.VAData($AB37,CW$3,$AC37,$AD37) -> 191.2 | CX37: =_xll.VAData($AB37,CX$3,$AC37,$AD37) -> 199.91909 | CY37: =_xll.VAData($AB37,CY$3,$AC37,$AD37) -> 209.64935 | CZ37: =_xll.VAData($AB37,CZ$3,$AC37,$AD37) -> 220.11538 | DA37: =_xll.VAData($AB37,DA$3,$AC37,$AD37) -> 230.36184 | DC37: 57.9 | DD37: 116.2 | DE37: 57.9 | DF37: 168.2 | DG37: 177.32625 | DH37: 192.70135 | DI37: 204.96136 | DJ37: 214.85301 | DK37: 225.94543
C38: Integrity Services | Z38: 14.337753 | AB38: TAH_AU | AC38: Operating income/(loss) - Operating - Gaming services | AD38: consensus.vaactuals | AE38: =_xll.VAData($AB38,AE$3,$AC38,$AD38) -> -17.9 | AF38: =_xll.VAData($AB38,AF$3,$AC38,$AD38) -> 19.7 | AG38: =_xll.VAData($AB38,AG$3,$AC38,$AD38) -> 16 | AH38: =_xll.VAData($AB38,AH$3,$AC38,$AD38) -> 18.4 | AI38: =_xll.VAData($AB38,AI$3,$AC38,$AD38) -> 9.6 | AJ38: =_xll.VAData($AB38,AJ$3,$AC38,$AD38) -> 10.4 | AK38: =_xll.VAData($AB38,AK$3,$AC38,$AD38) -> 13.3 | AL38: =_xll.VAData($AB38,AL$3,$AC38,$AD38) -> 7.2 | ... AP38: =_xll.VAData($AB38,AP$3,$AC38,$AD38) -> 13.428863 | AR38: -17.9 | AS38: 19.7 | AT38: 16 | AU38: 18.4 | AV38: 16.7 | AW38: 10.4 | AX38: 13.3 | AY38: 7.2 | AZ38: 11.990265 | BA38: 9.425288 | BB38: 12.599276 | BC38: 10.002183 | BT38: Integrity Services | CN38: =DG38 -> 26.084207 | CP38: TAH_AU | CQ38: Operating income/(loss) - Operating - Gaming services | CR38: consensus.vaactuals | CS38: =_xll.VAData($AB38,CS$3,$AC38,$AD38) -> 1.8 | CT38: =_xll.VAData($AB38,CT$3,$AC38,$AD38) -> 34.4 | CU38: =_xll.VAData($AB38,CU$3,$AC38,$AD38) -> 20 | CV38: =_xll.VAData($AB38,CV$3,$AC38,$AD38) -> 20.5 | CW38: =_xll.VAData($AB38,CW$3,$AC38,$AD38) -> 27.5 | CX38: =_xll.VAData($AB38,CX$3,$AC38,$AD38) -> 28.177433 | CY38: =_xll.VAData($AB38,CY$3,$AC38,$AD38) -> 30.100162 | CZ38: =_xll.VAData($AB38,CZ$3,$AC38,$AD38) -> 31.783919 | DA38: =_xll.VAData($AB38,DA$3,$AC38,$AD38) -> 33.371 | DC38: 1.8 | DD38: 34.4 | DE38: 20 | DF38: 20.5 | DG38: 26.084207 | DH38: 26.916693 | DI38: 28.460314 | DJ38: 29.915872 | DK38: 31.38127
C39: EBIT | D39: =HY!M311 -> 16.3 | E39: =HY!N311 -> 57.9 | F39: =HY!O311 -> 73.2 | G39: =HY!P416 -> -78.9 | H39: =HY!Q416 -> -74.6 | I39: =HY!R416 -> -74.6 | J39: =HY!S416 -> -32.95 | K39: =HY!T416 -> -53.75 | L39: =HY!U416 -> -55.05 | M39: =HY!V416 -> -39.65 | N39: =HY!W416 -> -49 | O39: =HY!X416 -> -49 | Q39: =J39 -> -32.95 | S39: =R39/Q39-1 -> -1 | T39: =L39 -> -55.05 | U39: =$R39/T39-1 -> -1 | V39: =Z39 -> 120.86409 | W39: =$R39/V39-1 -> -1 | Z39: 120.86409 | AB39: TAH_AU | AC39: Operating income/(loss) - Operating | AD39: consensus.vaactuals | AE39: =_xll.VAData($AB39,AE$3,$AC39,$AD39) -> 16.3 | AF39: =_xll.VAData($AB39,AF$3,$AC39,$AD39) -> 57.9 | AG39: =_xll.VAData($AB39,AG$3,$AC39,$AD39) -> 73.2 | AH39: =_xll.VAData($AB39,AH$3,$AC39,$AD39) -> 77.297995 | AI39: =_xll.VAData($AB39,AI$3,$AC39,$AD39) -> 50 | AJ39: =_xll.VAData($AB39,AJ$3,$AC39,$AD39) -> 47.4 | AK39: =_xll.VAData($AB39,AK$3,$AC39,$AD39) -> 92.7 | AL39: =_xll.VAData($AB39,AL$3,$AC39,$AD39) -> 96 | ... AP39: =_xll.VAData($AB39,AP$3,$AC39,$AD39) -> 105.43671 | AR39: 16.3 | AS39: 57.9 | AT39: 73.2 | AU39: 77.297995 | AV39: 50 | AW39: 47.4 | AX39: 92.7 | AY39: 96 | AZ39: 86.31809 | BA39: 95.631743 | BB39: 109.43267 | BC39: 101.31928 | BE39: =D39-AR39 -> 0 | BF39: =E39-AS39 -> 0 | BG39: =F39-AT39 -> 0 | BH39: =G39-AU39 -> -156.198 | BI39: =H39-AV39 -> -124.6 | BJ39: =I39-AW39 -> -122 | BK39: =J39-AX39 -> -125.65 | BL39: =K39-AY39 -> -149.75 | ... BP39: =O39-BC39 -> -150.31928 | BT39: EBIT | BU39: =FY!C49 -> 74.2 | BV39: =FY!D49 -> 150.5 | BW39: =FY!E49 -> 97.4 | BX39: =FY!F49 -> 188.7 | BY39: =FY!G49 -> 218.7 | BZ39: =FY!H49 -> 238.02006 | CA39: =FY!I49 -> 262.24577 | CB39: =FY!J49 -> 269.16774 | CC39: =FY!K49 -> 285.90615 | CE39: =BX39 -> 188.7 | CG39: =CF39/CE39-1 -> -1 | CH39: =BY39 -> 218.7 | CI39: =$CF39/CH39-1 -> -1 | CJ39: =CN39 -> 207.08996 | CK39: =$CF39/CJ39-1 -> -1 | CN39: =DG39 -> 207.08996 | CP39: TAH_AU | CQ39: Operating income/(loss) - Operating | CR39: consensus.vaactuals | CS39: =_xll.VAData($AB39,CS$3,$AC39,$AD39) -> 95.2 | CT39: =_xll.VAData($AB39,CT$3,$AC39,$AD39) -> 150.5 | CU39: =_xll.VAData($AB39,CU$3,$AC39,$AD39) -> 97.4 | CV39: =_xll.VAData($AB39,CV$3,$AC39,$AD39) -> 188.7 | CW39: =_xll.VAData($AB39,CW$3,$AC39,$AD39) -> 218.7 | CX39: =_xll.VAData($AB39,CX$3,$AC39,$AD39) -> 235.01687 | CY39: =_xll.VAData($AB39,CY$3,$AC39,$AD39) -> 251.24654 | CZ39: =_xll.VAData($AB39,CZ$3,$AC39,$AD39) -> 264.73724 | DA39: =_xll.VAData($AB39,DA$3,$AC39,$AD39) -> 276.76132 | DC39: 95.2 | DD39: 150.5 | DE39: 97.4 | DF39: 188.7 | DG39: 207.08996 | DH39: 223.84775 | DI39: 237.84596 | DJ39: 248.86053 | DK39: 261.04487 | DM39: =BU39-DC39 -> -21 | DN39: =BV39-DD39 -> 0 | DO39: =BW39-DE39 -> 0 | DP39: =BX39-DF39 -> 0 | DQ39: =BY39-DG39 -> 11.61004 | DR39: =BZ39-DH39 -> 14.172312 | DS39: =CD39-DI39 -> -237.84596 | DT39: =CE39-DJ39 -> -60.160535 | DU39: =CF39-DK39 -> -261.04487
C41: Margins | BT41: Margins
C42: Wagering & Media | D42: =D21/D17 -> 0.3678964 | E42: =E21/E17 -> 0.36662156 | F42: =F21/F17 -> 0.34168311 | G42: =G21/G17 -> 0.35367571 | H42: =H21/H17 -> 0.35276733 | I42: =I21/I17 -> 0.34821258 | J42: =J21/J17 -> 0.36848456 | K42: =K21/K17 -> 0.38290398 | ... O42: =O21/O17 -> 0.395 | Q42: =Q21/Q17 -> 0.36848456 | R42: =R21/R17 -> 0.38094478 | S42: =($R42-Q42)*100 -> 1.2460225 | T42: =T21/T17 -> 0.38094478 | U42: =($R42-T42)*100 -> 0 | V42: =V21/V17 -> 0.38231949 | W42: =($R42-V42)*100 -> -0.13747075 | Z42: =Z21/Z17 -> 0.38231949 | BE42: =D42-AR42 -> 0.3678964 | BF42: =E42-AS42 -> 0.36662156 | BG42: =F42-AT42 -> 0.34168311 | BH42: =G42-AU42 -> 0.35367571 | BI42: =H42-AV42 -> 0.35276733 | BJ42: =I42-AW42 -> 0.34821258 | BK42: =J42-AX42 -> 0.36848456 | BL42: =K42-AY42 -> 0.38290398 | ... BP42: =O42-BC42 -> 0.395 | BT42: Wagering & Media | BU42: =BU21/BU17 -> 0.36724873 | BV42: =BV21/BV17 -> 0.347409 | BW42: =BW21/BW17 -> 0.35056408 | BX42: =BX21/BX17 -> 0.37555355 | BY42: =BY21/BY17 -> 0.38831629 | BZ42: =BZ21/BZ17 -> 0.395 | CA42: =CA21/CA17 -> 0.395 | CB42: =CB21/CB17 -> 0.395 | CC42: =CC21/CC17 -> 0.395 | CE42: =CE21/CE17 -> 0.37555355 | CF42: =CF21/CF17 -> 0.38831629 | CG42: =($CF42-CE42)*100 -> 1.276274 | CH42: =CH21/CH17 -> 0.38831629 | CI42: =($CF42-CH42)*100 -> 0 | CJ42: =CJ21/CJ17 -> 0.38127615 | CK42: =($CF42-CJ42)*100 -> 0.70401388 | CN42: =CN21/CN17 -> 0.38127615
C43: Integrity Services | D43: =D22/D18 -> 0.93718593 | E43: =E22/E18 -> 0.95225916 | F43: =F22/F18 -> 0.93198529 | G43: =G22/G18 -> 0.96835443 | H43: =H22/H18 -> 0.99501868 | I43: =I22/I18 -> 0.9843562 | J43: =J22/J18 -> 0.97956867 | K43: =K22/K18 -> 0.98631699 | ... O43: =O22/O18 -> 0.98998888 | Q43: =Q22/Q18 -> 0.97956867 | R43: =R22/R18 -> 0.98364231 | S43: =($R43-Q43)*100 -> 0.40736399 | T43: =T22/T18 -> 0.98364231 | U43: =($R43-T43)*100 -> 0 | V43: =V22/V18 -> 0.98504127 | W43: =($R43-V43)*100 -> -0.13989594 | Z43: =Z22/Z18 -> 0.98504127 | BE43: =D43-AR43 -> 0.93718593 | BF43: =E43-AS43 -> 0.95225916 | BG43: =F43-AT43 -> 0.93198529 | BH43: =G43-AU43 -> 0.96835443 | BI43: =H43-AV43 -> 0.99501868 | BJ43: =I43-AW43 -> 0.9843562 | BK43: =J43-AX43 -> 0.97956867 | BL43: =K43-AY43 -> 0.98631699 | ... BP43: =O43-BC43 -> 0.98998888 | BT43: Integrity Services | BU43: =BU22/BU18 -> 0.94616557 | BV43: =BV22/BV18 -> 0.94891945 | BW43: =BW22/BW18 -> 0.98959608 | BX43: =BX22/BX18 -> 0.98293515 | BY43: =BY22/BY18 -> 0.98678414 | BZ43: =BZ22/BZ18 -> 0.98998888 | CA43: =CA22/CA18 -> 0.98998888 | CB43: =CB22/CB18 -> 0.98998888 | CC43: =CC22/CC18 -> 0.98998888 | CE43: =CE22/CE18 -> 0.98293515 | CF43: =CF22/CF18 -> 0.98678414 | CG43: =($CF43-CE43)*100 -> 0.38489874 | CH43: =CH22/CH18 -> 0.98678414 | CI43: =($CF43-CH43)*100 -> 0 | CJ43: =CJ22/CJ18 -> 0.98767533 | CK43: =($CF43-CJ43)*100 -> -0.089118843 | CN43: =CN22/CN18 -> 0.98767533
C44: Variable Contribution | D44: =D23/D19 -> 0.40744598 | E44: =E23/E19 -> 0.42261224 | F44: =F23/F19 -> 0.39207532 | G44: =G23/G19 -> 0.40408656 | H44: =H23/H19 -> 0.40145503 | I44: =I23/I19 -> 0.39502347 | J44: =J23/J19 -> 0.40892361 | K44: =K23/K19 -> 0.42414089 | ... O44: =O23/O19 -> 0.44087942 | Q44: =Q23/Q19 -> 0.40892361 | R44: =R23/R19 -> 0.42203881 | S44: =($R44-Q44)*100 -> 1.3115205 | T44: =T23/T19 -> 0.42203881 | U44: =($R44-T44)*100 -> 0 | V44: =V23/V19 -> 0.42342561 | W44: =($R44-V44)*100 -> -0.13867955 | Z44: =Z23/Z19 -> 0.42342561 | BE44: =D44-AR44 -> 0.40744598 | BF44: =E44-AS44 -> 0.42261224 | BG44: =F44-AT44 -> 0.39207532 | BH44: =G44-AU44 -> 0.40408656 | BI44: =H44-AV44 -> 0.40145503 | BJ44: =I44-AW44 -> 0.39502347 | BK44: =J44-AX44 -> 0.40892361 | BL44: =K44-AY44 -> 0.42414089 | ... BP44: =O44-BC44 -> 0.44087942 | BT44: Variable Contribution | BU44: =BU23/BU19 -> 0.41526101 | BV44: =BV23/BV19 -> 0.39779823 | BW44: =BW23/BW19 -> 0.39834965 | BX44: =BX23/BX19 -> 0.41639256 | BY44: =BY23/BY19 -> 0.4295414 | BZ44: =BZ23/BZ19 -> 0.43783904 | CA44: =CA23/CA19 -> 0.4470298 | CB44: =CB23/CB19 -> 0.45071741 | CC44: =CC23/CC19 -> 0.45109751 | CE44: =CE23/CE19 -> 0.41639256 | CF44: =CF23/CF19 -> 0.4295414 | CG44: =($CF44-CE44)*100 -> 1.3148838 | CH44: =CH23/CH19 -> 0.4295414 | CI44: =($CF44-CH44)*100 -> 0 | CJ44: =CJ23/CJ19 -> 0.42320411 | CK44: =($CF44-CJ44)*100 -> 0.63372905 | CN44: =CN23/CN19 -> 0.42320411
C46: Wagering & Media | D46: =D29/D17 -> 0.12847028 | E46: =E29/E17 -> 0.13450609 | F46: =F29/F17 -> 0.1324526 | G46: =G29/G17 -> 0.14421181 | H46: =H29/H17 -> 0.12000716 | I46: =I29/I17 -> 0.11202447 | J46: =J29/J17 -> 0.12604569 | K46: =K29/K17 -> 0.14419538 | ... O46: =O29/O17 -> 0.14674694 | Q46: =Q29/Q17 -> 0.12604569 | R46: =R29/R17 -> 0.14474944 | S46: =($R46-Q46)*100 -> 1.8703753 | T46: =T29/T17 -> 0.14474944 | U46: =($R46-T46)*100 -> 0 | V46: =V29/V17 -> 0.13200834 | W46: =($R46-V46)*100 -> 1.2741103 | Z46: =Z29/Z17 -> 0.13200834 | BE46: =D46-AR46 -> 0.12847028 | BF46: =E46-AS46 -> 0.13450609 | BG46: =F46-AT46 -> 0.1324526 | BH46: =G46-AU46 -> 0.14421181 | BI46: =H46-AV46 -> 0.12000716 | BJ46: =I46-AW46 -> 0.11202447 | BK46: =J46-AX46 -> 0.12604569 | BL46: =K46-AY46 -> 0.14419538 | ... BP46: =O46-BC46 -> 0.14674694 | BT46: Wagering & Media | BU46: =BU29/BU17 -> 0.13153673 | BV46: =BV29/BV17 -> 0.13806706 | BW46: =BW29/BW17 -> 0.11614574 | BX46: =BX29/BX17 -> 0.13494341 | BY46: =BY29/BY17 -> 0.14739072 | BZ46: =BZ29/BZ17 -> 0.15400389 | CA46: =CA29/CA17 -> 0.14852383 | CB46: =CB29/CB17 -> 0.1433323 | CC46: =CC29/CC17 -> 0.14141258 | CE46: =CE29/CE17 -> 0.13494341 | CF46: =CF29/CF17 -> 0.14739072 | CG46: =($CF46-CE46)*100 -> 1.2447305 | CH46: =CH29/CH17 -> 0.14739072 | CI46: =($CF46-CH46)*100 -> 0 | CJ46: =CJ29/CJ17 -> 0.14198714 | CK46: =($CF46-CJ46)*100 -> 0.54035799 | CN46: =CN29/CN17 -> 0.14198714
C47: Integrity Services | D47: =D30/D18 -> 0.24623116 | E47: =E30/E18 -> 0.456948 | F47: =F30/F18 -> 0.39430147 | G47: =G30/G18 -> 0.42405063 | H47: =H30/H18 -> 0.35242839 | I47: =I30/I18 -> 0.36943442 | J47: =J30/J18 -> 0.38024972 | K47: =K30/K18 -> 0.3295325 | ... O47: =O30/O18 -> 0.37998888 | Q47: =Q30/Q18 -> 0.38024972 | R47: =R30/R18 -> 0.39258451 | S47: =($R47-Q47)*100 -> 1.2334798 | T47: =T30/T18 -> 0.39258451 | U47: =($R47-T47)*100 -> 0 | V47: =V30/V18 -> 0.36368988 | W47: =($R47-V47)*100 -> 2.8894632 | Z47: =Z30/Z18 -> 0.36368988 | BE47: =D47-AR47 -> 0.24623116 | BF47: =E47-AS47 -> 0.456948 | BG47: =F47-AT47 -> 0.39430147 | BH47: =G47-AU47 -> 0.42405063 | BI47: =H47-AV47 -> 0.35242839 | BJ47: =I47-AW47 -> 0.36943442 | BK47: =J47-AX47 -> 0.38024972 | BL47: =K47-AY47 -> 0.3295325 | ... BP47: =O47-BC47 -> 0.37998888 | BT47: Integrity Services | BU47: =BU30/BU18 -> 0.37176232 | BV47: =BV30/BV18 -> 0.40815324 | BW47: =BW30/BW18 -> 0.36107711 | BX47: =BX30/BX18 -> 0.35494881 | BY47: =BY30/BY18 -> 0.38491189 | BZ47: =BZ30/BZ18 -> 0.37998888 | CA47: =CA30/CA18 -> 0.37998888 | CB47: =CB30/CB18 -> 0.37998888 | CC47: =CC30/CC18 -> 0.37998888 | CE47: =CE30/CE18 -> 0.35494881 | CF47: =CF30/CF18 -> 0.38491189 | CG47: =($CF47-CE47)*100 -> 2.9963089 | CH47: =CH30/CH18 -> 0.38491189 | CI47: =($CF47-CH47)*100 -> 0 | CJ47: =CJ30/CJ18 -> 0.37570442 | CK47: =($CF47-CJ47)*100 -> 0.92074738 | CN47: =CN30/CN18 -> 0.37570442
C48: EBITDA | D48: =D31/D19 -> 0.1379849 | E48: =E31/E19 -> 0.16457143 | F48: =F31/F19 -> 0.15425657 | G48: =G31/G19 -> 0.16760066 | H48: =H31/H19 -> 0.14037698 | I48: =I31/I19 -> 0.13096609 | J48: =J31/J19 -> 0.14286787 | K48: =K31/K19 -> 0.15686122 | ... O48: =O31/O19 -> 0.16382537 | Q48: =Q31/Q19 -> 0.14286787 | R48: =R31/R19 -> 0.16164771 | S48: =($R48-Q48)*100 -> 1.8779833 | T48: =T31/T19 -> 0.16164771 | U48: =($R48-T48)*100 -> 0 | V48: =V31/V19 -> 0.14789329 | W48: =($R48-V48)*100 -> 1.3754421 | Z48: =Z31/Z19 -> 0.14789329 | BE48: =D48-AR48 -> 0.1379849 | BF48: =E48-AS48 -> 0.16457143 | BG48: =F48-AT48 -> 0.15425657 | BH48: =G48-AU48 -> 0.16760066 | BI48: =H48-AV48 -> 0.14037698 | BJ48: =I48-AW48 -> 0.13096609 | BK48: =J48-AX48 -> 0.14286787 | BL48: =K48-AY48 -> 0.15686122 | ... BP48: =O48-BC48 -> 0.16382537 | BT48: EBITDA | BU48: =BU31/BU19 -> 0.15168468 | BV48: =BV31/BV19 -> 0.16061453 | BW48: =BW31/BW19 -> 0.13583308 | BX48: =BX31/BX19 -> 0.1497361 | BY48: =BY31/BY19 -> 0.16375223 | BZ48: =BZ31/BZ19 -> 0.16979448 | CA48: =CA31/CA19 -> 0.17059011 | CB48: =CB31/CB19 -> 0.17177295 | CC48: =CC31/CC19 -> 0.17025012 | CE48: =CE31/CE19 -> 0.1497361 | CF48: =CF31/CF19 -> 0.16375223 | CG48: =($CF48-CE48)*100 -> 1.4016131 | CH48: =CH31/CH19 -> 0.16375223 | CI48: =($CF48-CH48)*100 -> 0 | CJ48: =CJ31/CJ19 -> 0.15970647 | CK48: =($CF48-CJ48)*100 -> 0.40457625 | CN48: =CN31/CN19 -> 0.15970647
C50: * 1H24 numbers include MPS business that was sold ($7.5m EBITDA impact in Integrity Services)
C54: Tabcorp 1H26 Result - Wagering KPI's | BT54: Tabcorp FY26 Result - Wagering KPI's
D55: =D$3 -> 1H22A | E55: =E$3 -> 2H22A | F55: =F$3 -> 1H23A | G55: =G$3 -> 2H23A | H55: =H$3 -> 1H24A | I55: =I$3 -> 2H24E | J55: =J$3 -> 1H25E | K55: =K$3 -> 2H25E | ... O55: =O$3 -> 2H27E | Q55: =Q$3 -> 1H25A | R55: =R$3 -> 1H26A | S55: =S$3 -> % change | T55: =T$3 -> E&Pe 1H26E | U55: =U$3 -> % diff | V55: =V$3 -> VA Cons. 1H26E | W55: =W$3 -> % diff | Z55: 1H25 | AE55: 1H22 | AF55: 2H22 | AG55: 1H23 | AH55: 2H23 | AI55: 1H24 | AJ55: 2H24 | AK55: 1H25 | AL55: 2H25 | AM55: 1H26 | AN55: 2H26 | AO55: 1H27 | AP55: 2H27 | AR55: 1H22 | AS55: 2H22 | AT55: 1H23 | AU55: 2H23 | AV55: 1H24 | AW55: 2H24 | AX55: 1H25 | AY55: 2H25 | AZ55: 1H26 | BA55: 2H26 | BB55: 1H27 | BC55: 2H27 | BE55: 1H22 | BF55: 2H22 | BG55: 1H23 | BH55: 2H23 | BI55: 1H24 | BJ55: 2H24 | BK55: 1H25 | BL55: 2H25 | BM55: 1H26 | BN55: 2H26 | BO55: 1H27 | BP55: 2H27 | BU55: =BU$3 -> FY22A | BV55: =BV$3 -> FY23A | BW55: =BW$3 -> FY24A | BX55: =BX$3 -> FY25E | BY55: =BY$3 -> FY26E | BZ55: =BZ$3 -> FY27E | CA55: =CA$3 -> FY28E | CB55: =CB$3 -> FY29E | CC55: =CC$3 -> FY30E | CE55: =CE$3 -> FY25A | CF55: =CF$3 -> FY26A | CG55: =CG$3 -> % change | CH55: =CH$3 -> E&Pe FY26E | CI55: =CI$3 -> % diff | CJ55: =CJ$3 -> VA Cons. FY26E | CK55: =CK$3 -> % diff | CN55: =DG55 -> FY26 | CS55: FY22 | CT55: FY23 | CU55: FY24 | CV55: FY25 | CW55: FY26 | CX55: FY27 | CY55: FY27 | CZ55: FY27 | DA55: FY27 | DC55: FY22 | DD55: FY23 | DE55: FY24 | DF55: FY25 | DG55: FY26 | DH55: FY27 | DI55: FY27 | DJ55: FY27 | DK55: FY27 | DM55: FY22 | DN55: FY23 | DO55: FY24 | DP55: FY25 | DQ55: FY26 | DR55: FY27 | DS55: FY28 | DT55: FY29 | DU55: FY30
C57: Turnover | BT57: Turnover
C58: Digital Turnover | D58: =HY!M78 -> 5259 | E58: =HY!N78 -> 4438 | F58: =HY!O78 -> 4920.5 | G58: =HY!P78 -> 4346.2 | H58: =HY!Q78 -> 4731.2 | I58: =HY!R78 -> 4077.9 | J58: =HY!S78 -> 4353.9 | K58: =HY!T78 -> 4028 | ... O58: =HY!X78 -> 4139.8261 | Q58: =J58 -> 4353.9 | R58: 4343.4 | S58: =R58/Q58-1 -> -0.002411631 | T58: =L58 -> 4343.4 | U58: =$R58/T58-1 -> 0 | AB58: TAH_AU | BT58: Digital Turnover | BU58: =FY!C212 -> 9697 | BV58: =FY!D212 -> 9266.7 | BW58: =FY!E212 -> 8809.1 | BX58: =FY!F212 -> 8381.9 | BY58: =FY!G212 -> 8446.3 | BZ58: =FY!H212 -> 8561.4073 | CA58: =FY!I212 -> 8729.8179 | CB58: =FY!J212 -> 8904.4143 | CC58: =FY!K212 -> 9171.5467 | CE58: =BX58 -> 8381.9 | CF58: 8446.3 | CG58: =CF58/CE58-1 -> 0.0076832222 | CH58: =BY58 -> 8446.3 | CI58: =$CF58/CH58-1 -> 0 | CP58: TAH_AU
C59: Cash Wagering Turnover | D59: =HY!M79 -> 1720.5 | E59: =HY!N79 -> 2476.2 | F59: =HY!O79 -> 2839 | G59: =HY!P79 -> 2445.1 | H59: =HY!Q79 -> 2732.4 | I59: =HY!R79 -> 2516.2 | J59: =HY!S79 -> 2791.8 | K59: =HY!T79 -> 2569.2 | ... O59: =HY!X79 -> 2584.82 | Q59: =J59 -> 2791.8 | R59: 2825.1 | S59: =R59/Q59-1 -> 0.011927789 | T59: =L59 -> 2825.1 | U59: =$R59/T59-1 -> 0 | AB59: TAH_AU | BT59: Cash Wagering Turnover | BU59: =FY!C213 -> 4196.7 | BV59: =FY!D213 -> 5284.1 | BW59: =FY!E213 -> 5248.6 | BX59: =FY!F213 -> 5361 | BY59: =FY!G213 -> 5415.1 | BZ59: =FY!H213 -> 5429.6957 | CA59: =FY!I213 -> 5348.2503 | CB59: =FY!J213 -> 5268.0265 | CC59: =FY!K213 -> 5320.7068 | CE59: =BX59 -> 5361 | CF59: 5415.1 | CG59: =CF59/CE59-1 -> 0.010091401 | CH59: =BY59 -> 5415.1 | CI59: =$CF59/CH59-1 -> 0 | CP59: TAH_AU
C61: Racing | D61: =HY!M69 -> 6032.2 | E61: =HY!N69 -> 5737.5 | F61: =HY!O69 -> 6500.8 | G61: =HY!P69 -> 5445.7 | H61: =HY!Q69 -> 6120.1 | I61: =HY!R69 -> 5241.1 | J61: =HY!S69 -> 5798.3 | K61: =HY!T69 -> 5104.7 | Q61: =J61 -> 5798.3 | R61: 5728.3 | S61: =R61/Q61-1 -> -0.012072504 | AB61: TAH_AU | BT61: Racing | BU61: =FY!C215 -> 11769.7 | BV61: =FY!D215 -> 11946.5 | BW61: =FY!E215 -> 11361.2 | BX61: =FY!F215 -> 10903 | CE61: =BX61 -> 10903 | CF61: 10785 | CG61: =CF61/CE61-1 -> -0.010822709 | CP61: TAH_AU
C62: Sport | D62: =HY!M70 -> 947.3 | E62: =HY!N70 -> 1176.7 | F62: =HY!O70 -> 1258.7 | G62: =HY!P70 -> 1345.6 | H62: =HY!Q70 -> 1343.5 | I62: =HY!R70 -> 1353 | J62: =HY!S70 -> 1347.4 | K62: =HY!T70 -> 1492.6 | Q62: =J62 -> 1347.4 | R62: 1440.2 | S62: =R62/Q62-1 -> 0.068873386 | AB62: TAH_AU | BT62: Sport | BU62: =FY!C216 -> 2124 | BV62: =FY!D216 -> 2604.3 | BW62: =FY!E216 -> 2696.5 | BX62: =FY!F216 -> 2840 | CE62: =BX62 -> 2840 | CF62: 3076 | CG62: =CF62/CE62-1 -> 0.083098592 | CP62: TAH_AU
C63: Digital Active Users (000's) | D63: =HY!M62 -> 780 | E63: =HY!N62 -> 783 | F63: =HY!O62 -> 797 | G63: =HY!P62 -> 805 | H63: =HY!Q62 -> 786 | I63: =HY!R62 -> 798 | J63: =HY!S62 -> 801 | K63: =HY!T62 -> 792 | Q63: =J63 -> 801 | R63: 766 | S63: =R63/Q63-1 -> -0.043695381 | AB63: TAH_AU | BT63: Digital Active Users (000's) | BU63: =FY!C217 -> 783 | BV63: =FY!D217 -> 805 | BW63: =FY!E217 -> 798 | BX63: =FY!F217 -> 792 | CE63: =BX63 -> 792 | CF63: 786 | CG63: =CF63/CE63-1 -> -0.0075757576 | CP63: TAH_AU
C65: Revenue | BT65: Revenue
C66: Digital Wagering | F66: =HY!O175 -> 493 | G66: =HY!P175 -> 449.7 | H66: =HY!Q175 -> 473.4 | I66: =HY!R175 -> 448.6 | J66: =HY!S175 -> 539.6 | K66: =HY!T175 -> 530.1 | L66: =HY!U175 -> 536.9 | M66: =HY!V175 -> 535.9 | ... O66: =HY!X175 -> 537.16765 | Q66: =J66 -> 539.6 | R66: 536.9 | S66: =R66/Q66-1 -> -0.0050037064 | T66: =L66 -> 536.9 | U66: =$R66/T66-1 -> 0 | V66: =Z66 -> 530.11767 | W66: =$R66/V66-1 -> 0.012794011 | Z66: =AZ66 -> 530.11767 | AB66: TAH_AU | AC66: Revenue - Digital Wagering | AD66: consensus.vaactuals | AE66: =_xll.VAData($AB66,AE$3,$AC66,$AD66) -> 579.9 | AF66: =_xll.VAData($AB66,AF$3,$AC66,$AD66) -> 493.6 | AG66: =_xll.VAData($AB66,AG$3,$AC66,$AD66) -> 493 | AH66: =_xll.VAData($AB66,AH$3,$AC66,$AD66) -> 449.7 | AI66: =_xll.VAData($AB66,AI$3,$AC66,$AD66) -> 473.4 | AJ66: =_xll.VAData($AB66,AJ$3,$AC66,$AD66) -> 448.6 | AK66: =_xll.VAData($AB66,AK$3,$AC66,$AD66) -> 539.6 | AL66: =_xll.VAData($AB66,AL$3,$AC66,$AD66) -> 530.1 | ... AP66: =_xll.VAData($AB66,AP$3,$AC66,$AD66) -> 534.23182 | AR66: 579.9 | AS66: 493.6 | AT66: 493 | AU66: 449.7 | AV66: 473.4 | AW66: 448.6 | AX66: 539.6 | AY66: 530.1 | AZ66: 530.11767 | BA66: 533.51528 | BB66: 582.65666 | BC66: 549.39258 | BE66: =D66-AR66 -> -579.9 | BF66: =E66-AS66 -> -493.6 | BG66: =F66-AT66 -> 0 | BH66: =G66-AU66 -> 0 | BI66: =H66-AV66 -> 0 | BJ66: =I66-AW66 -> 0 | BK66: =J66-AX66 -> 0 | BL66: =K66-AY66 -> 0 | ... BP66: =O66-BC66 -> -12.224928 | BT66: Digital Wagering | BV66: =FY!D220 -> 942.7 | BW66: =FY!E220 -> 922 | BX66: =FY!F220 -> 1069.7 | BY66: =FY!G220 -> 1072.8 | BZ66: =FY!H220 -> 1108.33 | CA66: =FY!I220 -> 1127.8167 | CB66: =FY!J220 -> 1150.165 | CC66: =FY!K220 -> 1184.358 | CE66: =BX66 -> 1069.7 | CF66: 1072.8 | CG66: =CF66/CE66-1 -> 0.0028980088 | CH66: =BY66 -> 1072.8 | CI66: =$CF66/CH66-1 -> 0 | CJ66: =CN66 -> 1067.2085 | CK66: =$CF66/CJ66-1 -> 0.0052394026 | CN66: =DG66 -> 1067.2085 | CP66: TAH_AU | CQ66: Revenue - Digital Wagering | CR66: consensus.vaactuals | CS66: =_xll.VAData($AB66,CS$3,$AC66,$AD66) -> 1073.5 | CT66: =_xll.VAData($AB66,CT$3,$AC66,$AD66) -> 942.7 | CU66: =_xll.VAData($AB66,CU$3,$AC66,$AD66) -> 922 | CV66: =_xll.VAData($AB66,CV$3,$AC66,$AD66) -> 1069.7 | CW66: =_xll.VAData($AB66,CW$3,$AC66,$AD66) -> 1072.8 | CX66: =_xll.VAData($AB66,CX$3,$AC66,$AD66) -> 1097.67 | CY66: =_xll.VAData($AB66,CY$3,$AC66,$AD66) -> 1126.564 | CZ66: =_xll.VAData($AB66,CZ$3,$AC66,$AD66) -> 1156.5075 | DA66: =_xll.VAData($AB66,DA$3,$AC66,$AD66) -> 1187.4839 | DC66: 1073.5 | DD66: 942.7 | DE66: 922 | DF66: 1069.7 | DG66: 1067.2085 | DH66: 1114.7953 | DI66: 1153.5207 | DJ66: 1193.2855 | DK66: 1233.1468 | DM66: =BU66-DC66 -> -1073.5 | DN66: =BV66-DD66 -> 0 | DO66: =BW66-DE66 -> 0 | DP66: =BX66-DF66 -> 0 | DQ66: =BY66-DG66 -> 5.5915348 | DR66: =BZ66-DH66 -> -6.4652881 | DS66: =CD66-DI66 -> -1153.5207 | DT66: =CE66-DJ66 -> -123.58552 | DU66: =CF66-DK66 -> -160.34684
C67: Retail Wagering | F67: =HY!O176 -> 437.4 | G67: =HY!P176 -> 381 | H67: =HY!Q176 -> 420.6 | I67: =HY!R176 -> 401.2 | J67: =HY!S176 -> 497.1 | K67: =HY!T176 -> 468.6 | L67: =HY!U176 -> 511.1 | M67: =HY!V176 -> 470.1 | ... O67: =HY!X176 -> 484.4194 | Q67: =J67 -> 497.1 | R67: 511.1 | S67: =R67/Q67-1 -> 0.028163347 | T67: =L67 -> 511.1 | U67: =$R67/T67-1 -> 0 | V67: =Z67 -> 488.26483 | W67: =$R67/V67-1 -> 0.04676799 | Z67: =AZ67 -> 488.26483 | AB67: TAH_AU | AC67: Revenue - Cash Wagering | AD67: consensus.vaactuals | AE67: =_xll.VAData($AB67,AE$3,$AC67,$AD67) -> 276.6 | AF67: =_xll.VAData($AB67,AF$3,$AC67,$AD67) -> 377.4 | AG67: =_xll.VAData($AB67,AG$3,$AC67,$AD67) -> 437.4 | AH67: =_xll.VAData($AB67,AH$3,$AC67,$AD67) -> 381 | AI67: =_xll.VAData($AB67,AI$3,$AC67,$AD67) -> 420.6 | AJ67: =_xll.VAData($AB67,AJ$3,$AC67,$AD67) -> 401.2 | AK67: =_xll.VAData($AB67,AK$3,$AC67,$AD67) -> 497.1 | AL67: =_xll.VAData($AB67,AL$3,$AC67,$AD67) -> 468.6 | ... AP67: =_xll.VAData($AB67,AP$3,$AC67,$AD67) -> 479.17947 | AR67: 276.6 | AS67: 377.4 | AT67: 437.4 | AU67: 381 | AV67: 420.6 | AW67: 401.2 | AX67: 497.1 | AY67: 468.6 | AZ67: 488.26483 | BA67: 470.76149 | BB67: 515.97407 | BC67: 479.63889 | BE67: =D67-AR67 -> -276.6 | BF67: =E67-AS67 -> -377.4 | BG67: =F67-AT67 -> 0 | BH67: =G67-AU67 -> 0 | BI67: =H67-AV67 -> 0 | BJ67: =I67-AW67 -> 0 | BK67: =J67-AX67 -> 0 | BL67: =K67-AY67 -> 0 | ... BP67: =O67-BC67 -> 4.7805055 | BT67: Retail Wagering | BV67: =FY!D221 -> 818.4 | BW67: =FY!E221 -> 821.8 | BX67: =FY!F221 -> 965.7 | BY67: =FY!G221 -> 981.2 | BZ67: =FY!H221 -> 1015.2483 | CA67: =FY!I221 -> 1001.4025 | CB67: =FY!J221 -> 988.67399 | CC67: =FY!K221 -> 998.56073 | CE67: =BX67 -> 965.7 | CF67: 981.2 | CG67: =CF67/CE67-1 -> 0.016050533 | CH67: =BY67 -> 981.2 | CI67: =$CF67/CH67-1 -> 0 | CJ67: =CN67 -> 983.17555 | CK67: =$CF67/CJ67-1 -> -0.0020093569 | CN67: =DG67 -> 983.17555 | CP67: TAH_AU | CQ67: Revenue - Cash Wagering | CR67: consensus.vaactuals | CS67: =_xll.VAData($AB67,CS$3,$AC67,$AD67) -> 654 | CT67: =_xll.VAData($AB67,CT$3,$AC67,$AD67) -> 818.4 | CU67: =_xll.VAData($AB67,CU$3,$AC67,$AD67) -> 821.8 | CV67: =_xll.VAData($AB67,CV$3,$AC67,$AD67) -> 965.7 | CW67: =_xll.VAData($AB67,CW$3,$AC67,$AD67) -> 981.2 | CX67: =_xll.VAData($AB67,CX$3,$AC67,$AD67) -> 1005.2979 | CY67: =_xll.VAData($AB67,CY$3,$AC67,$AD67) -> 1015.4807 | CZ67: =_xll.VAData($AB67,CZ$3,$AC67,$AD67) -> 1026.3613 | DA67: =_xll.VAData($AB67,DA$3,$AC67,$AD67) -> 1035.4701 | DC67: 654 | DD67: 818.4 | DE67: 821.8 | DF67: 965.7 | DG67: 983.17555 | DH67: 999.80239 | DI67: 1008.9927 | DJ67: 1020.6121 | DK67: 1029.9532 | DM67: =BU67-DC67 -> -654 | DN67: =BV67-DD67 -> 0 | DO67: =BW67-DE67 -> 0 | DP67: =BX67-DF67 -> 0 | DQ67: =BY67-DG67 -> -1.9755506 | DR67: =BZ67-DH67 -> 15.445877 | DS67: =CD67-DI67 -> -1008.9927 | DT67: =CE67-DJ67 -> -54.912107 | DU67: =CF67-DK67 -> -48.753247
C68: International Wagering | F68: =HY!O177 -> 120.9 | G68: =HY!P177 -> 128.4 | H68: =HY!Q177 -> 109.3 | I68: =HY!R177 -> 103 | J68: =HY!S177 -> 108 | K68: =HY!T177 -> 124.2 | L68: =HY!U177 -> 115.1 | M68: =HY!V177 -> 108.6 | ... O68: =HY!X177 -> 109 | Q68: =J68 -> 108 | R68: 115.1 | S68: =R68/Q68-1 -> 0.065740741 | T68: =L68 -> 115.1 | U68: =$R68/T68-1 -> 0 | V68: =Z68 -> 115.349 | W68: =$R68/V68-1 -> -0.0021586773 | Z68: =AZ68 -> 115.349 | AB68: TAH_AU | AC68: Revenue - International wagering | AD68: consensus.vaactuals | AE68: =_xll.VAData($AB68,AE$3,$AC68,$AD68) -> 167.85818 | AF68: =_xll.VAData($AB68,AF$3,$AC68,$AD68) -> 177.3005 | AG68: =_xll.VAData($AB68,AG$3,$AC68,$AD68) -> 120.9 | AH68: =_xll.VAData($AB68,AH$3,$AC68,$AD68) -> 128.4 | AI68: =_xll.VAData($AB68,AI$3,$AC68,$AD68) -> 109.2 | AJ68: =_xll.VAData($AB68,AJ$3,$AC68,$AD68) -> 103.1 | AK68: =_xll.VAData($AB68,AK$3,$AC68,$AD68) -> 108 | AL68: =_xll.VAData($AB68,AL$3,$AC68,$AD68) -> 124.2 | ... AP68: =_xll.VAData($AB68,AP$3,$AC68,$AD68) -> 112.03705 | AR68: 167.85818 | AS68: 177.3005 | AT68: 120.9 | AU68: 128.4 | AV68: 109.2 | AW68: 103.1 | AX68: 108 | AY68: 124.2 | AZ68: 115.349 | BA68: 125.89995 | BB68: 118.63987 | BC68: 129.01749 | BE68: =D68-AR68 -> -167.85818 | BF68: =E68-AS68 -> -177.3005 | BG68: =F68-AT68 -> 0 | BH68: =G68-AU68 -> 0 | BI68: =H68-AV68 -> 0.1 | BJ68: =I68-AW68 -> -0.1 | BK68: =J68-AX68 -> 0 | BL68: =K68-AY68 -> 0 | ... BP68: =O68-BC68 -> -20.01749 | BT68: International Wagering | BV68: =FY!D222 -> 249.3 | BW68: =FY!E222 -> 212.3 | BX68: =FY!F222 -> 232.2 | BY68: =FY!G222 -> 223.7 | BZ68: =FY!H222 -> 216 | CA68: =FY!I222 -> 222.48 | CB68: =FY!J222 -> 229.1544 | CC68: =FY!K222 -> 236.02903 | CE68: =BX68 -> 232.2 | CF68: 223.7 | CG68: =CF68/CE68-1 -> -0.036606374 | CH68: =BY68 -> 223.7 | CI68: =$CF68/CH68-1 -> 0 | CJ68: =CN68 -> 241.39638 | CK68: =$CF68/CJ68-1 -> -0.073308401 | CN68: =DG68 -> 241.39638 | CP68: TAH_AU | CQ68: Revenue - International wagering | CR68: consensus.vaactuals | CS68: =_xll.VAData($AB68,CS$3,$AC68,$AD68) -> 345.15868 | CT68: =_xll.VAData($AB68,CT$3,$AC68,$AD68) -> 249.3 | CU68: =_xll.VAData($AB68,CU$3,$AC68,$AD68) -> 212.3 | CV68: =_xll.VAData($AB68,CV$3,$AC68,$AD68) -> 232.2 | CW68: =_xll.VAData($AB68,CW$3,$AC68,$AD68) -> 223.7 | CX68: =_xll.VAData($AB68,CX$3,$AC68,$AD68) -> 227.57196 | CY68: =_xll.VAData($AB68,CY$3,$AC68,$AD68) -> 233.19328 | CZ68: =_xll.VAData($AB68,CZ$3,$AC68,$AD68) -> 238.26184 | DA68: =_xll.VAData($AB68,DA$3,$AC68,$AD68) -> 243.48694 | DC68: 345.15868 | DD68: 249.3 | DE68: 212.3 | DF68: 232.2 | DG68: 241.39638 | DH68: 249.19167 | DI68: 256.74501 | DJ68: 263.19943 | DK68: 269.84294 | DM68: =BU68-DC68 -> -345.15868 | DN68: =BV68-DD68 -> 0 | DO68: =BW68-DE68 -> 0 | DP68: =BX68-DF68 -> 0 | DQ68: =BY68-DG68 -> -17.696383 | DR68: =BZ68-DH68 -> -33.191668 | DS68: =CD68-DI68 -> -256.74501 | DT68: =CE68-DJ68 -> -30.999432 | DU68: =CF68-DK68 -> -46.142941
C69: Wagering | F69: =HY!O178 -> 1051.3 | G69: =HY!P178 -> 959.1 | H69: =HY!Q178 -> 1003.3 | I69: =HY!R178 -> 952.8 | J69: =HY!S178 -> 1144.7 | K69: =HY!T178 -> 1122.9 | L69: =HY!U178 -> 1163.1 | M69: =HY!V178 -> 1114.6 | ... O69: =HY!X178 -> 1130.5871 | Q69: =J69 -> 1144.7 | R69: 1163.1 | S69: =R69/Q69-1 -> 0.016074081 | T69: =L69 -> 1163.1 | U69: =$R69/T69-1 -> 0 | V69: =Z69 -> 1131.67 | W69: =$R69/V69-1 -> 0.027773129 | Z69: =AZ69 -> 1131.67 | AB69: TAH_AU | AC69: Total revenue - Wagering | AD69: consensus.vaactuals | AE69: =_xll.VAData($AB69,AE$3,$AC69,$AD69) -> 856.5 | AF69: =_xll.VAData($AB69,AF$3,$AC69,$AD69) -> 871 | AG69: =_xll.VAData($AB69,AG$3,$AC69,$AD69) -> 1051.3 | AH69: =_xll.VAData($AB69,AH$3,$AC69,$AD69) -> 959.1 | AI69: =_xll.VAData($AB69,AI$3,$AC69,$AD69) -> 1003.2 | AJ69: =_xll.VAData($AB69,AJ$3,$AC69,$AD69) -> 952.9 | AK69: =_xll.VAData($AB69,AK$3,$AC69,$AD69) -> 1144.7 | AL69: =_xll.VAData($AB69,AL$3,$AC69,$AD69) -> 1122.9 | ... AP69: =_xll.VAData($AB69,AP$3,$AC69,$AD69) -> 1129.0198 | AR69: 856.5 | AS69: 871 | AT69: 1051.3 | AU69: 959.1 | AV69: 1003.2 | AW69: 952.9 | AX69: 1144.7 | AY69: 1122.9 | AZ69: 1131.67 | BA69: 1129.0801 | BB69: 1217.4976 | BC69: 1158.4443 | BE69: =D69-AR69 -> -856.5 | BF69: =E69-AS69 -> -871 | BG69: =F69-AT69 -> 0 | BH69: =G69-AU69 -> 0 | BI69: =H69-AV69 -> 0.1 | BJ69: =I69-AW69 -> -0.1 | BK69: =J69-AX69 -> 0 | BL69: =K69-AY69 -> 0 | ... BP69: =O69-BC69 -> -27.857216 | BT69: Wagering | BV69: =FY!D223 -> 2010.4 | BW69: =FY!E223 -> 1956.1 | BX69: =FY!F223 -> 2267.6 | BY69: =FY!G223 -> 2277.7 | BZ69: =FY!H223 -> 2339.5783 | CA69: =FY!I223 -> 2351.6992 | CB69: =FY!J223 -> 2367.9934 | CC69: =FY!K223 -> 2418.9477 | CE69: =BX69 -> 2267.6 | CF69: 2277.7 | CG69: =CF69/CE69-1 -> 0.0044540483 | CH69: =BY69 -> 2277.7 | CI69: =$CF69/CH69-1 -> 0 | CJ69: =CN69 -> 2291.7804 | CK69: =$CF69/CJ69-1 -> -0.0061438691 | CN69: =DG69 -> 2291.7804 | CP69: TAH_AU | CQ69: Total revenue - Wagering | CR69: consensus.vaactuals | CS69: =_xll.VAData($AB69,CS$3,$AC69,$AD69) -> 1727.5 | CT69: =_xll.VAData($AB69,CT$3,$AC69,$AD69) -> 2010.4 | CU69: =_xll.VAData($AB69,CU$3,$AC69,$AD69) -> 1956.1 | CV69: =_xll.VAData($AB69,CV$3,$AC69,$AD69) -> 2267.6 | CW69: =_xll.VAData($AB69,CW$3,$AC69,$AD69) -> 2277.7 | CX69: =_xll.VAData($AB69,CX$3,$AC69,$AD69) -> 2334.1113 | CY69: =_xll.VAData($AB69,CY$3,$AC69,$AD69) -> 2389.8094 | CZ69: =_xll.VAData($AB69,CZ$3,$AC69,$AD69) -> 2436.4307 | DA69: =_xll.VAData($AB69,DA$3,$AC69,$AD69) -> 2482.506 | DC69: 1727.5 | DD69: 2010.4 | DE69: 1956.1 | DF69: 2267.6 | DG69: 2291.7804 | DH69: 2363.7894 | DI69: 2419.2584 | DJ69: 2477.0971 | DK69: 2532.943 | DM69: =BU69-DC69 -> -1727.5 | DN69: =BV69-DD69 -> 0 | DO69: =BW69-DE69 -> 0 | DP69: =BX69-DF69 -> 0 | DQ69: =BY69-DG69 -> -14.080399 | DR69: =BZ69-DH69 -> -24.211079 | DS69: =CD69-DI69 -> -2419.2584 | DT69: =CE69-DJ69 -> -209.49706 | DU69: =CF69-DK69 -> -255.24302
C70: Media | F70: =HY!O179 -> 114.4 | G70: =HY!P179 -> 106 | H70: =HY!Q179 -> 189.1 | I70: =HY!R179 -> 171.8 | J70: =HY!S179 -> 192.1 | K70: =HY!T179 -> 178.5 | L70: =HY!U179 -> 192.4 | M70: =HY!V179 -> 185.4 | ... O70: =HY!X179 -> 188 | Q70: =J70 -> 192.1 | S70: =R70/Q70-1 -> -1 | T70: =L70 -> 192.4 | U70: =$R70/T70-1 -> -1 | V70: =Z70 -> 164.68587 | W70: =$R70/V70-1 -> -1 | Z70: =AZ70 -> 164.68587 | AB70: TAH_AU | AC70: Total revenue - Media | AD70: consensus.vaactuals | AE70: =_xll.VAData($AB70,AE$3,$AC70,$AD70) -> 216.9 | AF70: =_xll.VAData($AB70,AF$3,$AC70,$AD70) -> 237.5 | AG70: =_xll.VAData($AB70,AG$3,$AC70,$AD70) -> 114.4 | AH70: =_xll.VAData($AB70,AH$3,$AC70,$AD70) -> 106 | AI70: =_xll.VAData($AB70,AI$3,$AC70,$AD70) -> 189.1 | AJ70: =_xll.VAData($AB70,AJ$3,$AC70,$AD70) -> 171.8 | AK70: =_xll.VAData($AB70,AK$3,$AC70,$AD70) -> 192.1 | AL70: =_xll.VAData($AB70,AL$3,$AC70,$AD70) -> 178.5 | ... AP70: =_xll.VAData($AB70,AP$3,$AC70,$AD70) -> 190.35993 | AR70: 216.9 | AS70: 237.5 | AT70: 114.4 | AU70: 106 | AV70: 113.4 | AW70: 93.3 | AX70: 192.1 | AY70: 178.5 | AZ70: 164.68587 | BA70: 152.80458 | BB70: 168.74057 | BC70: 156.8159 | BE70: =D70-AR70 -> -216.9 | BF70: =E70-AS70 -> -237.5 | BG70: =F70-AT70 -> 0 | BH70: =G70-AU70 -> 1.1368684e-13 | BI70: =H70-AV70 -> 75.7 | BJ70: =I70-AW70 -> 78.5 | BK70: =J70-AX70 -> 0 | BL70: =K70-AY70 -> 0 | ... BP70: =O70-BC70 -> 31.184102 | BT70: Media | BV70: =FY!D224 -> 220.4 | BW70: =FY!E224 -> 360.9 | BX70: =FY!F224 -> 370.6 | BY70: =FY!G224 -> 377.8 | BZ70: =FY!H224 -> 376 | CA70: =FY!I224 -> 385.48 | CB70: =FY!J224 -> 395.2084 | CC70: =FY!K224 -> 405.19193 | CE70: =BX70 -> 370.6 | CG70: =CF70/CE70-1 -> -1 | CH70: =BY70 -> 377.8 | CI70: =$CF70/CH70-1 -> -1 | CJ70: =CN70 -> 375.36027 | CK70: =$CF70/CJ70-1 -> -1 | CN70: =DG70 -> 375.36027 | CP70: TAH_AU | CQ70: Total revenue - Media | CR70: consensus.vaactuals | CS70: =_xll.VAData($AB70,CS$3,$AC70,$AD70) -> 454.4 | CT70: =_xll.VAData($AB70,CT$3,$AC70,$AD70) -> 220.4 | CU70: =_xll.VAData($AB70,CU$3,$AC70,$AD70) -> 360.9 | CV70: =_xll.VAData($AB70,CV$3,$AC70,$AD70) -> 370.6 | CW70: =_xll.VAData($AB70,CW$3,$AC70,$AD70) -> 377.8 | CX70: =_xll.VAData($AB70,CX$3,$AC70,$AD70) -> 386.6441 | CY70: =_xll.VAData($AB70,CY$3,$AC70,$AD70) -> 395.84716 | CZ70: =_xll.VAData($AB70,CZ$3,$AC70,$AD70) -> 404.99232 | DA70: =_xll.VAData($AB70,DA$3,$AC70,$AD70) -> 415.23386 | DC70: 454.4 | DD70: 220.4 | DE70: 360.9 | DF70: 370.6 | DG70: 375.36027 | DH70: 382.22692 | DI70: 389.4496 | DJ70: 396.56256 | DK70: 406.14465 | DM70: =BU70-DC70 -> -454.4 | DN70: =BV70-DD70 -> 0 | DO70: =BW70-DE70 -> 0 | DP70: =BX70-DF70 -> 0 | DQ70: =BY70-DG70 -> 2.4397282 | DR70: =BZ70-DH70 -> -6.2269155 | DS70: =CD70-DI70 -> -389.4496 | DT70: =CE70-DJ70 -> -25.962564 | DU70: =CF70-DK70 -> -406.14465
C71: Intersegment Elimination | F71: =HY!O180 -> 0 | G71: =HY!P180 -> 0 | H71: =HY!Q180 -> -75.7 | I71: =HY!R180 -> -78.5 | J71: =HY!S180 -> -93.6 | K71: =HY!T180 -> -105.8 | L71: =HY!U180 -> -102.3 | M71: =HY!V180 -> -98.5 | ... O71: =HY!X180 -> -90 | Q71: =J71 -> -93.6 | S71: =R71/Q71-1 -> -1 | T71: =L71 -> -102.3 | U71: =$R71/T71-1 -> -1 | V71: =Z71 -> -95.458137 | W71: =$R71/V71-1 -> -1 | Z71: =AZ71 -> -95.458137 | AB71: TAH_AU | AC71: Total revenue - Intra segment | AD71: consensus.vaactuals | AE71: =_xll.VAData($AB71,AE$3,$AC71,$AD71) -> - | AF71: =_xll.VAData($AB71,AF$3,$AC71,$AD71) -> - | AG71: =_xll.VAData($AB71,AG$3,$AC71,$AD71) -> -0.2 | AH71: =_xll.VAData($AB71,AH$3,$AC71,$AD71) -> 0.2 | AI71: =_xll.VAData($AB71,AI$3,$AC71,$AD71) -> -75.7 | AJ71: =_xll.VAData($AB71,AJ$3,$AC71,$AD71) -> -78.5 | AK71: =_xll.VAData($AB71,AK$3,$AC71,$AD71) -> -93.6 | AL71: =_xll.VAData($AB71,AL$3,$AC71,$AD71) -> -105.8 | ... AP71: =_xll.VAData($AB71,AP$3,$AC71,$AD71) -> -93.735 | AR71: - | AS71: - | AT71: - | AU71: - | AV71: -75.7 | AW71: -78.5 | AX71: -93.6 | AY71: -105.8 | AZ71: -95.458137 | BA71: -99.617383 | BB71: -97.052548 | BC71: -101.33657 | BE71: =D71-AR71 -> #VALUE! | BF71: =E71-AS71 -> #VALUE! | BG71: =F71-AT71 -> #VALUE! | BH71: =G71-AU71 -> #VALUE! | BI71: =H71-AV71 -> 0 | BJ71: =I71-AW71 -> 0 | BK71: =J71-AX71 -> 0 | BL71: =K71-AY71 -> 0 | ... BP71: =O71-BC71 -> 11.336572 | BT71: Intersegment Elimination | BV71: =FY!D225 -> 0 | BW71: =FY!E225 -> -154.2 | BX71: =FY!F225 -> -199.4 | BY71: =FY!G225 -> -200.8 | BZ71: =FY!H225 -> -180 | CA71: =FY!I225 -> -183.6 | CB71: =FY!J225 -> -187.272 | CC71: =FY!K225 -> -191.01744 | CE71: =BX71 -> -199.4 | CG71: =CF71/CE71-1 -> -1 | CH71: =BY71 -> -200.8 | CI71: =$CF71/CH71-1 -> -1 | CJ71: =CN71 -> -201.00107 | CK71: =$CF71/CJ71-1 -> -1 | CN71: =DG71 -> -201.00107 | CP71: TAH_AU | CQ71: Total revenue - Intra segment | CR71: consensus.vaactuals | CS71: =_xll.VAData($AB71,CS$3,$AC71,$AD71) -> - | CT71: =_xll.VAData($AB71,CT$3,$AC71,$AD71) -> - | CU71: =_xll.VAData($AB71,CU$3,$AC71,$AD71) -> -154.2 | CV71: =_xll.VAData($AB71,CV$3,$AC71,$AD71) -> -199.4 | CW71: =_xll.VAData($AB71,CW$3,$AC71,$AD71) -> -200.8 | CX71: =_xll.VAData($AB71,CX$3,$AC71,$AD71) -> -189.64912 | CY71: =_xll.VAData($AB71,CY$3,$AC71,$AD71) -> -192.96916 | CZ71: =_xll.VAData($AB71,CZ$3,$AC71,$AD71) -> -196.37112 | DA71: =_xll.VAData($AB71,DA$3,$AC71,$AD71) -> -199.85709 | DC71: - | DD71: - | DE71: -154.2 | DF71: -199.4 | DG71: -201.00107 | DH71: -200.76435 | DI71: -204.36303 | DJ71: -208.04926 | DK71: -211.82526 | DM71: =BU71-DC71 -> #VALUE! | DN71: =BV71-DD71 -> #VALUE! | DO71: =BW71-DE71 -> 0 | DP71: =BX71-DF71 -> 0 | DQ71: =BY71-DG71 -> 0.20107017 | DR71: =BZ71-DH71 -> 20.764352 | DS71: =CD71-DI71 -> 204.36303 | DT71: =CE71-DJ71 -> 8.6492586 | DU71: =CF71-DK71 -> 211.82526
C72: Media & Wagering | F72: =HY!O181 -> 114.4 | G72: =HY!P181 -> 106 | H72: =HY!Q181 -> 113.4 | I72: =HY!R181 -> 93.3 | J72: =HY!S181 -> 98.5 | K72: =HY!T181 -> 72.7 | L72: =HY!U181 -> 90.1 | M72: =HY!V181 -> 86.9 | ... O72: =HY!X181 -> 98 | Q72: =J72 -> 98.5 | S72: =R72/Q72-1 -> -1 | T72: =L72 -> 90.1 | U72: =$R72/T72-1 -> -1 | V72: =Z72 -> -95.458137 | W72: =$R72/V72-1 -> -1 | Z72: =AZ72 -> -95.458137 | AB72: TAH_AU | AC72: Total revenue - Intra segment | AD72: consensus.vaactuals | AE72: =_xll.VAData($AB72,AE$3,$AC72,$AD72) -> - | AF72: =_xll.VAData($AB72,AF$3,$AC72,$AD72) -> - | AG72: =_xll.VAData($AB72,AG$3,$AC72,$AD72) -> -0.2 | AH72: =_xll.VAData($AB72,AH$3,$AC72,$AD72) -> 0.2 | AI72: =_xll.VAData($AB72,AI$3,$AC72,$AD72) -> -75.7 | AJ72: =_xll.VAData($AB72,AJ$3,$AC72,$AD72) -> -78.5 | AK72: =_xll.VAData($AB72,AK$3,$AC72,$AD72) -> -93.6 | AL72: =_xll.VAData($AB72,AL$3,$AC72,$AD72) -> -105.8 | ... AP72: =_xll.VAData($AB72,AP$3,$AC72,$AD72) -> -93.735 | AR72: - | AS72: - | AT72: - | AU72: - | AV72: -75.7 | AW72: -78.5 | AX72: -93.6 | AY72: -105.8 | AZ72: -95.458137 | BA72: -99.617383 | BB72: -97.052548 | BC72: -101.33657 | BE72: =D72-AR72 -> #VALUE! | BF72: =E72-AS72 -> #VALUE! | BG72: =F72-AT72 -> #VALUE! | BH72: =G72-AU72 -> #VALUE! | BI72: =H72-AV72 -> 189.1 | BJ72: =I72-AW72 -> 171.8 | BK72: =J72-AX72 -> 192.1 | BL72: =K72-AY72 -> 178.5 | ... BP72: =O72-BC72 -> 199.33657 | BT72: Wagering & Media Revenue | BV72: =FY!D226 -> 2230.8 | BW72: =FY!E226 -> 2162.8 | BX72: =FY!F226 -> 2438.8 | BY72: =FY!G226 -> 2454.7 | BZ72: =FY!H226 -> 2535.5783 | CA72: =FY!I226 -> 2553.5792 | CB72: =FY!J226 -> 2575.9298 | CC72: =FY!K226 -> 2633.1222 | CE72: =BX72 -> 2438.8 | CG72: =CF72/CE72-1 -> -1 | CH72: =BY72 -> 2454.7 | CI72: =$CF72/CH72-1 -> -1 | CJ72: =CN72 -> -201.00107 | CK72: =$CF72/CJ72-1 -> -1 | CN72: =DG72 -> -201.00107 | CP72: TAH_AU | CQ72: Total revenue - Intra segment | CR72: consensus.vaactuals | CS72: =_xll.VAData($AB72,CS$3,$AC72,$AD72) -> - | CT72: =_xll.VAData($AB72,CT$3,$AC72,$AD72) -> - | CU72: =_xll.VAData($AB72,CU$3,$AC72,$AD72) -> -154.2 | CV72: =_xll.VAData($AB72,CV$3,$AC72,$AD72) -> -199.4 | CW72: =_xll.VAData($AB72,CW$3,$AC72,$AD72) -> -200.8 | CX72: =_xll.VAData($AB72,CX$3,$AC72,$AD72) -> -189.64912 | CY72: =_xll.VAData($AB72,CY$3,$AC72,$AD72) -> -192.96916 | CZ72: =_xll.VAData($AB72,CZ$3,$AC72,$AD72) -> -196.37112 | DA72: =_xll.VAData($AB72,DA$3,$AC72,$AD72) -> -199.85709 | DC72: - | DD72: - | DE72: -154.2 | DF72: -199.4 | DG72: -201.00107 | DH72: -200.76435 | DI72: -204.36303 | DJ72: -208.04926 | DK72: -211.82526 | DM72: =BU72-DC72 -> #VALUE! | DN72: =BV72-DD72 -> #VALUE! | DO72: =BW72-DE72 -> 2317 | DP72: =BX72-DF72 -> 2638.2 | DQ72: =BY72-DG72 -> 2655.7011 | DR72: =BZ72-DH72 -> 2736.3427 | DS72: =CD72-DI72 -> 204.36303 | DT72: =CE72-DJ72 -> 2646.8493 | DU72: =CF72-DK72 -> 211.82526
C74: Yields | BT74: Yields
C75: Digital Gross Yield | D75: =HY!M86 -> 0.17 | E75: =HY!N86 -> 0.16781501 | F75: =HY!O86 -> 0.164 | G75: =HY!P86 -> 0.164 | H75: =HY!Q86 -> 0.165 | I75: =HY!R86 -> 0.172 | J75: =HY!S86 -> 0.17 | K75: =HY!T86 -> 0.169 | ... O75: =HY!X86 -> 0.168 | Q75: =J75 -> 0.17 | R75: 0.163 | S75: =($R75-Q75)*100 -> -0.7 | T75: =L75 -> 0.163 | U75: =($R75-T75)*100 -> 0 | AB75: TAH_AU | BT75: Digital Gross Yield | BU75: =FY!C230 -> 0.169 | BV75: =FY!D230 -> 0.164 | BW75: =FY!E230 -> 0.168 | BX75: =FY!F230 -> 0.17 | BY75: =FY!G230 -> 0.166 | BZ75: =FY!H230 -> 0.168 | CA75: =FY!I230 -> 0.168 | CB75: =FY!J230 -> 0.168 | CC75: =FY!K230 -> 0.168 | CE75: =BX75 -> 0.17 | CF75: 0.166 | CG75: =($CF75-CE75)*100 -> -0.4 | CH75: =BY75 -> 0.166 | CI75: =($CF75-CH75)*100 -> 0 | CP75: TAH_AU
C76: Digital Net Yield | D76: =HY!M87 -> 0.134 | E76: =HY!N87 -> 0.13515097 | F76: =HY!O87 -> 0.122 | G76: =HY!P87 -> 0.124 | H76: =HY!Q87 -> 0.121 | I76: =HY!R87 -> 0.133 | J76: =HY!S87 -> 0.128 | K76: =HY!T87 -> 0.13 | ... O76: =HY!X87 -> 0.1285 | Q76: =J76 -> 0.128 | R76: 0.123 | S76: =($R76-Q76)*100 -> -0.5 | T76: =L76 -> 0.123 | U76: =($R76-T76)*100 -> 0 | AB76: TAH_AU | BT76: Digital Net Yield | BU76: =FY!C231 -> 0.134 | BV76: =FY!D231 -> 0.123 | BW76: =FY!E231 -> 0.127 | BX76: =FY!F231 -> 0.129 | BY76: =FY!G231 -> 0.126 | BZ76: =FY!H231 -> 0.1285 | CA76: =FY!I231 -> 0.128 | CB76: =FY!J231 -> 0.128 | CC76: =FY!K231 -> 0.128 | CE76: =BX76 -> 0.129 | CF76: 0.126 | CG76: =($CF76-CE76)*100 -> -0.3 | CH76: =BY76 -> 0.126 | CI76: =($CF76-CH76)*100 -> 0 | CP76: TAH_AU
C77: Retail Gross/Net Yield | D77: =HY!M107 -> 0.167 | E77: =HY!N107 -> 0.16585898 | F77: =HY!O107 -> 0.166 | G77: =HY!P107 -> 0.1677232 | H77: =HY!Q107 -> 0.168 | I77: =HY!R107 -> 0.17395279 | J77: =HY!S107 -> 0.172 | K77: =HY!T107 -> 0.1698194 | ... O77: =HY!X107 -> 0.17 | Q77: =J77 -> 0.172 | R77: 0.17 | S77: =($R77-Q77)*100 -> -0.2 | T77: =L77 -> 0.17 | U77: =($R77-T77)*100 -> 0 | AB77: TAH_AU | BT77: Retail Gross/Net Yield | BU77: =FY!C232 -> 0.167 | BV77: =FY!D232 -> 0.167 | BW77: =FY!E232 -> 0.171 | BX77: =FY!F232 -> 0.171 | BY77: =FY!G232 -> 0.17 | BZ77: =FY!H232 -> 0.17 | CA77: =FY!I232 -> 0.17 | CB77: =FY!J232 -> 0.17 | CC77: =FY!K232 -> 0.17 | CE77: =BX77 -> 0.171 | CF77: 0.17 | CG77: =($CF77-CE77)*100 -> -0.1 | CH77: =BY77 -> 0.17 | CI77: =($CF77-CH77)*100 -> 0 | CP77: TAH_AU

Sheet Rev Tables
E2: FY24A | F2: FY25A | G2: FY26E | H2: FY27E | I2: FY28E | J2: FY29E | K2: FY30E | L2: FY31E | M2: FY32E | N2: FY33E | O2: FY34E
C3: Revenue | D3: New | E3: =FY!E$63 -> 2338.9 | F3: =FY!F$63 -> 2614.6 | G3: =FY!G$63 -> 2636.3 | H3: =FY!H$63 -> 2746.9683 | I3: =FY!I$63 -> 2846.8577 | J3: =FY!J$63 -> 2878.0067 | K3: =FY!K$63 -> 2944.2614 | L3: =FY!L$63 -> 2992.3348 | ... O3: =FY!O$63 -> 3147.8114
D4: Old | E4: 2338.9 | F4: 2614.6 | G4: 2636.3 | H4: 2746.9683 | I4: 2846.8577 | J4: 2878.0067 | K4: 2944.2614 | L4: 2992.3348 | M4: 3042.2498 | N4: 3094.0578 | O4: 3147.8114 | Q4: << BetMakers
D5: % change | E5: =E3/E4-1 -> 0 | F5: =F3/F4-1 -> 0 | G5: =G3/G4-1 -> 0 | H5: =H3/H4-1 -> 0 | I5: =I3/I4-1 -> 0 | J5: =J3/J4-1 -> 0 | K5: =K3/K4-1 -> 0 | L5: =L3/L4-1 -> 0 | ... O5: =O3/O4-1 -> 0
C6: EBITDA | D6: New | E6: =FY!E$67 -> 317.7 | F6: =FY!F$67 -> 391.5 | G6: =FY!G$67 -> 431.7 | H6: =FY!H$67 -> 466.42006 | I6: =FY!I$67 -> 485.64577 | J6: =FY!J$67 -> 494.36371 | K6: =FY!K$67 -> 501.26086 | L6: =FY!L$67 -> 507.07545 | ... O6: =FY!O$67 -> 527.37455
D7: Old | E7: 317.7 | F7: 391.5 | G7: 431.7 | H7: 466.42006 | I7: 485.64577 | J7: 494.36371 | K7: 501.26086 | L7: 507.07545 | M7: 513.3558 | N7: 520.11697 | O7: 527.37455
D8: % change | E8: =E6/E7-1 -> 0 | F8: =F6/F7-1 -> 0 | G8: =G6/G7-1 -> 0 | H8: =H6/H7-1 -> 0 | I8: =I6/I7-1 -> 0 | J8: =J6/J7-1 -> 0 | K8: =K6/K7-1 -> 0 | L8: =L6/L7-1 -> 0 | ... O8: =O6/O7-1 -> 0
C9: NPAT | D9: New | E9: =FY!E81 -> 28 | F9: =FY!F81 -> 49.5 | G9: =FY!G81 -> 71.1 | H9: =FY!H81 -> 89.710264 | I9: =FY!I81 -> 110.08763 | J9: =FY!J81 -> 120.65763 | K9: =FY!K81 -> 137.49126 | L9: =FY!L81 -> 149.04168 | ... O9: =FY!O81 -> 203.06758
D10: Old | E10: 28 | F10: 49.5 | G10: 71.1 | H10: 89.710264 | I10: 110.08763 | J10: 120.65763 | K10: 137.49126 | L10: 149.04168 | M10: 158.36107 | N10: 167.95645 | O10: 203.06758
D11: % change | E11: =E9/E10-1 -> 0 | F11: =F9/F10-1 -> 0 | G11: =G9/G10-1 -> 0 | H11: =H9/H10-1 -> 0 | I11: =I9/I10-1 -> 0 | J11: =J9/J10-1 -> 0 | K11: =K9/K10-1 -> 0 | L11: =L9/L10-1 -> 0 | ... O11: =O9/O10-1 -> 0
C12: Valuation | D12: New | H12: =HY!D740 -> 0.89457633
D13: Old | H13: 0.89457633
D14: % change | H14: =H12/H13-1 -> 0

Sheet Revisions
C2: TLC
G3: FY22A | H3: FY22A | I3: FY23A | J3: FY23A | K3: FY24A | L3: FY24A | M3: FY25A | N3: FY25A | O3: FY26A | P3: FY26A | Q3: FY27A | R3: FY27A | S3: FY28A | T3: FY28A | U3: FY29A | V3: FY29A | W3: FY30A | X3: FY30A | Y3: FY31A | Z3: FY31A | AA3: FY32A | AB3: FY32A | AC3: FY33A | AD3: FY33A | AE3: FY34A | AF3: FY34A
D5: Units | F5: VAL | G5: 1H22A | H5: 2H22A | I5: 1H23A | J5: 2H23A | K5: 1H24E | L5: 2H24E | M5: 1H25E | N5: 2H25E | O5: 1H26E | P5: 2H26E | Q5: 1H27E | R5: 2H27E | S5: 1H28E | T5: 2H28E | U5: 1H29E | V5: 2H29E | W5: 1H30E | X5: 2H30E | Y5: 1H31E | Z5: 2H31E | AA5: 1H32E | AB5: 2H32E | AC5: 1H33E | AD5: 2H33E | AE5: 1H34E | AF5: 2H34E | AI5: Units | AK5: VAL | AL5: FY22A | AM5: FY23A | AN5: FY24A | AO5: FY25A | AP5: FY26A | AQ5: FY27A | AR5: FY28A | AS5: FY29A | AT5: FY30A | AU5: FY31A | AV5: FY32A | AW5: FY33A | AX5: FY34A
G6: 44561 | H6: =EOMONTH(G6,6) -> 44742 | I6: =EOMONTH(H6,6) -> 44926 | J6: =EOMONTH(I6,6) -> 45107 | K6: =EOMONTH(J6,6) -> 45291 | L6: =EOMONTH(K6,6) -> 45473 | M6: =EOMONTH(L6,6) -> 45657 | N6: =EOMONTH(M6,6) -> 45838 | O6: =EOMONTH(N6,6) -> 46022 | ... AF6: =EOMONTH(AE6,6) -> 49125 | AL6: 44742 | AM6: =EOMONTH(AL6,12) -> 45107 | AN6: =EOMONTH(AM6,12) -> 45473 | AO6: =EOMONTH(AN6,12) -> 45838 | AP6: =EOMONTH(AO6,12) -> 46203 | AQ6: =EOMONTH(AP6,12) -> 46568 | AR6: =EOMONTH(AQ6,12) -> 46934 | AS6: =EOMONTH(AR6,12) -> 47299 | AT6: =EOMONTH(AS6,12) -> 47664 | ... AX6: =EOMONTH(AW6,12) -> 49125
A8: X | C8: LIVE
C10: WAGERING KPI's
B11: =$C$10&C11 -> WAGERING KPI'sDigital Turnover | C11: Digital Turnover | D11: A$m | G11: =HY!M78 -> 5259 | H11: =HY!N78 -> 4438 | I11: =HY!O78 -> 4920.5 | J11: =HY!P78 -> 4346.2 | K11: =HY!Q78 -> 4731.2 | L11: =HY!R78 -> 4077.9 | M11: =HY!S78 -> 4353.9 | N11: =HY!T78 -> 4028 | ... AF11: =HY!AL78 -> 5042.0322 | AL11: =SUMIFS($G11:$AF11,$G$3:$AF$3,AL$5) -> 9697 | AM11: =SUMIFS($G11:$AF11,$G$3:$AF$3,AM$5) -> 9266.7 | AN11: =SUMIFS($G11:$AF11,$G$3:$AF$3,AN$5) -> 8809.1 | AO11: =SUMIFS($G11:$AF11,$G$3:$AF$3,AO$5) -> 8381.9 | AP11: =SUMIFS($G11:$AF11,$G$3:$AF$3,AP$5) -> 8446.3 | AQ11: =SUMIFS($G11:$AF11,$G$3:$AF$3,AQ$5) -> 8561.4073 | AR11: =SUMIFS($G11:$AF11,$G$3:$AF$3,AR$5) -> 8729.8179 | AS11: =SUMIFS($G11:$AF11,$G$3:$AF$3,AS$5) -> 8904.4143 | ... AX11: =SUMIFS($G11:$AF11,$G$3:$AF$3,AX$5) -> 10322.657
B12: =$C$10&C12 -> WAGERING KPI'sRetail Turnover | C12: Retail Turnover | D12: A$m | G12: =HY!M79 -> 1720.5 | H12: =HY!N79 -> 2476.2 | I12: =HY!O79 -> 2839 | J12: =HY!P79 -> 2445.1 | K12: =HY!Q79 -> 2732.4 | L12: =HY!R79 -> 2516.2 | M12: =HY!S79 -> 2791.8 | N12: =HY!T79 -> 2569.2 | ... AF12: =HY!AL79 -> 2433.1278 | AL12: =SUMIFS($G12:$AF12,$G$3:$AF$3,AL$5) -> 4196.7 | AM12: =SUMIFS($G12:$AF12,$G$3:$AF$3,AM$5) -> 5284.1 | AN12: =SUMIFS($G12:$AF12,$G$3:$AF$3,AN$5) -> 5248.6 | AO12: =SUMIFS($G12:$AF12,$G$3:$AF$3,AO$5) -> 5361 | AP12: =SUMIFS($G12:$AF12,$G$3:$AF$3,AP$5) -> 5415.1 | AQ12: =SUMIFS($G12:$AF12,$G$3:$AF$3,AQ$5) -> 5429.6957 | AR12: =SUMIFS($G12:$AF12,$G$3:$AF$3,AR$5) -> 5348.2503 | AS12: =SUMIFS($G12:$AF12,$G$3:$AF$3,AS$5) -> 5268.0265 | ... AX12: =SUMIFS($G12:$AF12,$G$3:$AF$3,AX$5) -> 5111.0497
B13: =$C$10&C13 -> WAGERING KPI'sDigital Revenue | C13: Digital Revenue | D13: A$m | G13: =HY!M102 -> 579.9 | H13: =HY!N102 -> 493.6 | I13: =HY!O102 -> 493 | J13: =HY!P102 -> 449.7 | K13: =HY!Q102 -> 473.4 | L13: =HY!R102 -> 448.6 | M13: =HY!S102 -> 539.6 | N13: =HY!T102 -> 530.1 | ... AF13: =HY!AL102 -> 650.58013 | AL13: =SUMIFS($G13:$AF13,$G$3:$AF$3,AL$5) -> 1073.5 | AM13: =SUMIFS($G13:$AF13,$G$3:$AF$3,AM$5) -> 942.7 | AN13: =SUMIFS($G13:$AF13,$G$3:$AF$3,AN$5) -> 922 | AO13: =SUMIFS($G13:$AF13,$G$3:$AF$3,AO$5) -> 1069.7 | AP13: =SUMIFS($G13:$AF13,$G$3:$AF$3,AP$5) -> 1072.8 | AQ13: =SUMIFS($G13:$AF13,$G$3:$AF$3,AQ$5) -> 1108.33 | AR13: =SUMIFS($G13:$AF13,$G$3:$AF$3,AR$5) -> 1127.8167 | AS13: =SUMIFS($G13:$AF13,$G$3:$AF$3,AS$5) -> 1150.165 | ... AX13: =SUMIFS($G13:$AF13,$G$3:$AF$3,AX$5) -> 1331.7
B14: =$C$10&C14 -> WAGERING KPI'sRetail Revenue | C14: Retail Revenue | D14: A$m | G14: =HY!M117 -> 276.6 | H14: =HY!N117 -> 377.4 | I14: =HY!O117 -> 437.4 | J14: =HY!P117 -> 381 | K14: =HY!Q117 -> 420.6 | L14: =HY!R117 -> 401.2 | M14: =HY!S117 -> 497.1 | N14: =HY!T117 -> 468.6 | ... AF14: =HY!AL117 -> 456.63593 | AL14: =SUMIFS($G14:$AF14,$G$3:$AF$3,AL$5) -> 654 | AM14: =SUMIFS($G14:$AF14,$G$3:$AF$3,AM$5) -> 818.4 | AN14: =SUMIFS($G14:$AF14,$G$3:$AF$3,AN$5) -> 821.8 | AO14: =SUMIFS($G14:$AF14,$G$3:$AF$3,AO$5) -> 965.7 | AP14: =SUMIFS($G14:$AF14,$G$3:$AF$3,AP$5) -> 981.2 | AQ14: =SUMIFS($G14:$AF14,$G$3:$AF$3,AQ$5) -> 1015.2483 | AR14: =SUMIFS($G14:$AF14,$G$3:$AF$3,AR$5) -> 1001.4025 | AS14: =SUMIFS($G14:$AF14,$G$3:$AF$3,AS$5) -> 988.67399 | ... AX14: =SUMIFS($G14:$AF14,$G$3:$AF$3,AX$5) -> 959.21346
B15: =$C$10&C15 -> WAGERING KPI'sDigital Gross Yield | C15: Digital Gross Yield | D15: % | G15: =HY!M86 -> 0.17 | H15: =HY!N86 -> 0.16781501 | I15: =HY!O86 -> 0.164 | J15: =HY!P86 -> 0.164 | K15: =HY!Q86 -> 0.165 | L15: =HY!R86 -> 0.172 | M15: =HY!S86 -> 0.17 | N15: =HY!T86 -> 0.169 | ... AF15: =HY!AL86 -> 0.168 | AL15: =AVERAGEIFS($G15:$AF15,$G$3:$AF$3,AL$5) -> 0.1689075 | AM15: =AVERAGEIFS($G15:$AF15,$G$3:$AF$3,AM$5) -> 0.164 | AN15: =AVERAGEIFS($G15:$AF15,$G$3:$AF$3,AN$5) -> 0.1685 | AO15: =AVERAGEIFS($G15:$AF15,$G$3:$AF$3,AO$5) -> 0.1695 | AP15: =AVERAGEIFS($G15:$AF15,$G$3:$AF$3,AP$5) -> 0.1655 | AQ15: =AVERAGEIFS($G15:$AF15,$G$3:$AF$3,AQ$5) -> 0.168 | AR15: =AVERAGEIFS($G15:$AF15,$G$3:$AF$3,AR$5) -> 0.168 | AS15: =AVERAGEIFS($G15:$AF15,$G$3:$AF$3,AS$5) -> 0.168 | ... AX15: =AVERAGEIFS($G15:$AF15,$G$3:$AF$3,AX$5) -> 0.168
